{
  "type": "Feature",
  "properties": {
    "gn:admin1_code":"15.0",
    "gn:asciiname":"Quimatunga",
    "gn:country_code":"AO",
    "gn:dem":809,
    "gn:feature_class":"P",
    "gn:feature_code":"PPL",
    "gn:name":"Quimatunga",
    "gn:population":0,
    "gn:timezone":"Africa/Luanda",
    "iso:country":"AO",
    "wof:name":"Quimatunga",
    "wof:placetype":"locality"
},
  "geometry": {"coordinates":[15.24005,-5.88158],"type":"Point"}
}