{
  "type": "Feature",
  "properties": {
    "gn:admin1_code":"15.0",
    "gn:asciiname":"Quissaco-Segundo",
    "gn:country_code":"AO",
    "gn:dem":740,
    "gn:feature_class":"P",
    "gn:feature_code":"PPL",
    "gn:name":"Quissaco-Segundo",
    "gn:population":0,
    "gn:timezone":"Africa/Luanda",
    "iso:country":"AO",
    "wof:name":"Quissaco-Segundo",
    "wof:placetype":"locality"
},
  "geometry": {"coordinates":[15.63491,-6.13258],"type":"Point"}
}