{
  "type": "Feature",
  "properties": {
    "gn:admin1_code":"12.0",
    "gn:asciiname":"Ngolome",
    "gn:country_code":"AO",
    "gn:dem":1164,
    "gn:feature_class":"P",
    "gn:feature_code":"PPL",
    "gn:name":"Ngolome",
    "gn:population":0,
    "gn:timezone":"Africa/Luanda",
    "iso:country":"AO",
    "wof:name":"Ngolome",
    "wof:placetype":"locality"
},
  "geometry": {"coordinates":[15.8069,-8.89726],"type":"Point"}
}