{
  "type": "Feature",
  "properties": {
    "gn:admin1_code":"18.0",
    "gn:asciiname":"Muambumba",
    "gn:country_code":"AO",
    "gn:dem":1370,
    "gn:feature_class":"P",
    "gn:feature_code":"PPL",
    "gn:name":"Muambumba",
    "gn:population":0,
    "gn:timezone":"Africa/Luanda",
    "iso:country":"AO",
    "wof:name":"Muambumba",
    "wof:placetype":"locality"
},
  "geometry": {"coordinates":[19.17242,-10.90731],"type":"Point"}
}