{
  "type": "Feature",
  "properties": {
    "gn:admin1_code":"18.0",
    "gn:asciiname":"Caio",
    "gn:country_code":"AO",
    "gn:dem":1217,
    "gn:feature_class":"P",
    "gn:feature_code":"PPL",
    "gn:name":"Caio",
    "gn:population":0,
    "gn:timezone":"Africa/Luanda",
    "iso:country":"AO",
    "name:bre_x_preferred":[
        "Caio"
    ],
    "name:ceb_x_preferred":[
        "Caio"
    ],
    "name:cym_x_preferred":[
        "Caeo"
    ],
    "name:deu_x_preferred":[
        "Caio"
    ],
    "name:ita_x_preferred":[
        "Caio"
    ],
    "name:jpn_x_preferred":[
        "\u30ab\u30a4\u30aa"
    ],
    "name:nld_x_preferred":[
        "Caio"
    ],
    "name:por_x_preferred":[
        "Caio"
    ],
    "name:swe_x_preferred":[
        "Caio"
    ],
    "wof:name":"Caio",
    "wof:placetype":"locality"
},
  "geometry": {"coordinates":[20.4225,-10.82861],"type":"Point"}
}