{
  "type": "Feature",
  "properties": {
    "gn:admin1_code":"14.0",
    "gn:asciiname":"Bairro Jica",
    "gn:country_code":"AO",
    "gn:dem":1099,
    "gn:feature_class":"P",
    "gn:feature_code":"PPL",
    "gn:name":"Bairro Jica",
    "gn:population":0,
    "gn:timezone":"Africa/Luanda",
    "iso:country":"AO",
    "wof:name":"Bairro Jica",
    "wof:placetype":"locality"
},
  "geometry": {"coordinates":[21.40356,-14.19601],"type":"Point"}
}