{
  "type": "Feature",
  "properties": {
    "gn:admin1_code":"16.0",
    "gn:asciiname":"Luvaca",
    "gn:country_code":"AO",
    "gn:dem":543,
    "gn:feature_class":"P",
    "gn:feature_code":"PPL",
    "gn:name":"Luvaca",
    "gn:population":0,
    "gn:timezone":"Africa/Luanda",
    "iso:country":"AO",
    "name:por_x_preferred":[
        "Luvaca"
    ],
    "wof:name":"Luvaca",
    "wof:placetype":"locality"
},
  "geometry": {"coordinates":[14.76667,-5.98333],"type":"Point"}
}