{
  "type": "Feature",
  "properties": {
    "gn:admin1_code":"18.0",
    "gn:asciiname":"Muamucosso",
    "gn:country_code":"AO",
    "gn:dem":1294,
    "gn:feature_class":"P",
    "gn:feature_code":"PPL",
    "gn:name":"Muamucosso",
    "gn:population":0,
    "gn:timezone":"Africa/Luanda",
    "iso:country":"AO",
    "wof:name":"Muamucosso",
    "wof:placetype":"locality"
},
  "geometry": {"coordinates":[18.5507,-10.46295],"type":"Point"}
}