{
  "type": "Feature",
  "properties": {
    "gn:admin1_code":"12.0",
    "gn:asciiname":"Satchicuta",
    "gn:country_code":"AO",
    "gn:dem":1346,
    "gn:feature_class":"P",
    "gn:feature_code":"PPL",
    "gn:name":"Satchicuta",
    "gn:population":0,
    "gn:timezone":"Africa/Luanda",
    "iso:country":"AO",
    "wof:name":"Satchicuta",
    "wof:placetype":"locality"
},
  "geometry": {"coordinates":[18.49319,-11.2844],"type":"Point"}
}