{
  "type": "Feature",
  "properties": {
    "gn:admin1_code":"6.0",
    "gn:asciiname":"Quicalabala",
    "gn:country_code":"AO",
    "gn:dem":1312,
    "gn:feature_class":"P",
    "gn:feature_code":"PPLL",
    "gn:name":"Quicalabala",
    "gn:population":0,
    "gn:timezone":"Africa/Luanda",
    "iso:country":"AO",
    "name:und_x_variant":[
        "Kualavala",
        "Quicalabala"
    ],
    "wof:name":"Quicalabala",
    "wof:placetype":"locality"
},
  "geometry": {"coordinates":[14.89343,-11.31555],"type":"Point"}
}