{
  "type": "Feature",
  "properties": {
    "gn:admin1_code":"12.0",
    "gn:asciiname":"Navio",
    "gn:country_code":"AO",
    "gn:dem":1112,
    "gn:feature_class":"P",
    "gn:feature_code":"PPL",
    "gn:name":"Navio",
    "gn:population":0,
    "gn:timezone":"Africa/Luanda",
    "iso:country":"AO",
    "name:und_x_variant":[
        "Nambua",
        "Navio"
    ],
    "wof:name":"Navio",
    "wof:placetype":"locality"
},
  "geometry": {"coordinates":[16.42199,-9.28365],"type":"Point"}
}