{
  "type": "Feature",
  "properties": {
    "gn:admin1_code":"8.0",
    "gn:asciiname":"Capila",
    "gn:cc2":"AO",
    "gn:country_code":"AO",
    "gn:dem":1504,
    "gn:feature_class":"P",
    "gn:feature_code":"PPL",
    "gn:name":"Capila",
    "gn:population":0,
    "gn:timezone":"Africa/Luanda",
    "iso:country":"AO",
    "name:ast_x_preferred":[
        "Capila"
    ],
    "name:ceb_x_preferred":[
        "Capila"
    ],
    "name:nor_x_preferred":[
        "Capila"
    ],
    "name:spa_x_preferred":[
        "Capila"
    ],
    "name:swe_x_preferred":[
        "Capila"
    ],
    "name:und_x_variant":[
        "Cabile",
        "Capila"
    ],
    "name:vie_x_preferred":[
        "Capila"
    ],
    "name:war_x_preferred":[
        "Capila"
    ],
    "wof:name":"Capila",
    "wof:placetype":"locality"
},
  "geometry": {"coordinates":[15.33917,-12.885],"type":"Point"}
}