{
  "type": "Feature",
  "properties": {
    "gn:admin1_code":"15.0",
    "gn:asciiname":"Mangarage",
    "gn:country_code":"AO",
    "gn:dem":1117,
    "gn:feature_class":"P",
    "gn:feature_code":"PPL",
    "gn:name":"Mangarage",
    "gn:population":0,
    "gn:timezone":"Africa/Luanda",
    "iso:country":"AO",
    "wof:name":"Mangarage",
    "wof:placetype":"locality"
},
  "geometry": {"coordinates":[16.01243,-8.02834],"type":"Point"}
}