{
  "type": "Feature",
  "properties": {
    "gn:admin1_code":"15.0",
    "gn:asciiname":"Quitungo",
    "gn:country_code":"AO",
    "gn:dem":849,
    "gn:feature_class":"P",
    "gn:feature_code":"PPL",
    "gn:name":"Quitungo",
    "gn:population":0,
    "gn:timezone":"Africa/Luanda",
    "iso:country":"AO",
    "wof:name":"Quitungo",
    "wof:placetype":"locality"
},
  "geometry": {"coordinates":[16.1797,-6.34453],"type":"Point"}
}