{
  "type": "Feature",
  "properties": {
    "gn:admin1_code":"17.0",
    "gn:asciiname":"Muana Cagi",
    "gn:country_code":"AO",
    "gn:dem":1032,
    "gn:feature_class":"P",
    "gn:feature_code":"PPL",
    "gn:name":"Muana Cagi",
    "gn:population":0,
    "gn:timezone":"Africa/Luanda",
    "iso:country":"AO",
    "wof:name":"Muana Cagi",
    "wof:placetype":"locality"
},
  "geometry": {"coordinates":[18.22618,-8.83598],"type":"Point"}
}