{
  "type": "Feature",
  "properties": {
    "gn:admin1_code":"12.0",
    "gn:asciiname":"Cassanza",
    "gn:country_code":"AO",
    "gn:dem":719,
    "gn:feature_class":"P",
    "gn:feature_code":"PPL",
    "gn:name":"Cassanza",
    "gn:population":0,
    "gn:timezone":"Africa/Luanda",
    "iso:country":"AO",
    "wof:name":"Cassanza",
    "wof:placetype":"locality"
},
  "geometry": {"coordinates":[17.25228,-8.74016],"type":"Point"}
}