{
  "type": "Feature",
  "properties": {
    "gn:admin1_code":"8.0",
    "gn:asciiname":"Oliverio",
    "gn:country_code":"AO",
    "gn:dem":1740,
    "gn:feature_class":"P",
    "gn:feature_code":"PPL",
    "gn:name":"Oliv\u00e9rio",
    "gn:population":0,
    "gn:timezone":"Africa/Luanda",
    "iso:country":"AO",
    "name:deu_x_preferred":[
        "Oliverio"
    ],
    "name:ita_x_preferred":[
        "Oliverio"
    ],
    "wof:name":"Oliverio",
    "wof:placetype":"locality"
},
  "geometry": {"coordinates":[15.46667,-12.68333],"type":"Point"}
}