{
  "type": "Feature",
  "properties": {
    "gn:admin1_code":"15.0",
    "gn:asciiname":"Quimbundo",
    "gn:country_code":"AO",
    "gn:dem":824,
    "gn:feature_class":"P",
    "gn:feature_code":"PPL",
    "gn:name":"Quimbundo",
    "gn:population":0,
    "gn:timezone":"Africa/Luanda",
    "iso:country":"AO",
    "name:und_x_variant":[
        "Quimundo",
        "Quimbundo"
    ],
    "wof:name":"Quimbundo",
    "wof:placetype":"locality"
},
  "geometry": {"coordinates":[14.93435,-8.13185],"type":"Point"}
}