{
  "type": "Feature",
  "properties": {
    "gn:admin1_code":"3.0",
    "gn:asciiname":"Bucomazi",
    "gn:cc2":"AO",
    "gn:country_code":"AO",
    "gn:dem":83,
    "gn:feature_class":"P",
    "gn:feature_code":"PPL",
    "gn:name":"Bucomazi",
    "gn:population":0,
    "gn:timezone":"Africa/Luanda",
    "iso:country":"AO",
    "name:und_x_variant":[
        "Buco",
        "Buco Maze",
        "Bucomasi",
        "Bucomazi"
    ],
    "wof:name":"Bucomazi",
    "wof:placetype":"locality"
},
  "geometry": {"coordinates":[12.23333,-5.45],"type":"Point"}
}