{
  "type": "Feature",
  "properties": {
    "gn:admin1_code":"19.0",
    "gn:asciiname":"Caju",
    "gn:country_code":"AO",
    "gn:dem":10,
    "gn:feature_class":"P",
    "gn:feature_code":"PPLL",
    "gn:name":"Caj\u00fa",
    "gn:population":0,
    "gn:timezone":"Africa/Luanda",
    "iso:country":"AO",
    "name:ceb_x_preferred":[
        "Caju"
    ],
    "name:ita_x_preferred":[
        "Caju"
    ],
    "name:por_x_preferred":[
        "Caju"
    ],
    "name:swe_x_preferred":[
        "Caju"
    ],
    "wof:name":"Caju",
    "wof:placetype":"locality"
},
  "geometry": {"coordinates":[13.98442,-9.52684],"type":"Point"}
}