{
  "type": "Feature",
  "properties": {
    "gn:admin1_code":"15.0",
    "gn:asciiname":"Pumbo Quimalungo",
    "gn:country_code":"AO",
    "gn:dem":853,
    "gn:feature_class":"P",
    "gn:feature_code":"PPL",
    "gn:name":"Pumbo Quimalungo",
    "gn:population":0,
    "gn:timezone":"Africa/Luanda",
    "iso:country":"AO",
    "name:und_x_variant":[
        "Banza Longa",
        "Pumbo Quimalungo"
    ],
    "wof:name":"Pumbo Quimalungo",
    "wof:placetype":"locality"
},
  "geometry": {"coordinates":[15.47313,-6.39105],"type":"Point"}
}