{
  "type": "Feature",
  "properties": {
    "gn:admin1_code":"1.0",
    "gn:asciiname":"Sapucusso",
    "gn:country_code":"AO",
    "gn:dem":1261,
    "gn:feature_class":"P",
    "gn:feature_code":"PPL",
    "gn:name":"Sapucusso",
    "gn:population":0,
    "gn:timezone":"Africa/Luanda",
    "iso:country":"AO",
    "wof:name":"Sapucusso",
    "wof:placetype":"locality"
},
  "geometry": {"coordinates":[14.80133,-12.30085],"type":"Point"}
}