{
  "type": "Feature",
  "properties": {
    "gn:admin1_code":"17.0",
    "gn:asciiname":"Salucunda",
    "gn:country_code":"AO",
    "gn:dem":991,
    "gn:feature_class":"P",
    "gn:feature_code":"PPL",
    "gn:name":"Salucunda",
    "gn:population":0,
    "gn:timezone":"Africa/Luanda",
    "iso:country":"AO",
    "wof:name":"Salucunda",
    "wof:placetype":"locality"
},
  "geometry": {"coordinates":[19.88458,-7.74976],"type":"Point"}
}