{
  "type": "Feature",
  "properties": {
    "gn:admin1_code":"12.0",
    "gn:asciiname":"Ndala Mataba",
    "gn:country_code":"AO",
    "gn:dem":1227,
    "gn:feature_class":"P",
    "gn:feature_code":"PPL",
    "gn:name":"Ndala Mataba",
    "gn:population":0,
    "gn:timezone":"Africa/Luanda",
    "iso:country":"AO",
    "name:und_x_variant":[
        "Caminanga",
        "Dala Mataba",
        "Ndala Mataba"
    ],
    "wof:name":"Ndala Mataba",
    "wof:placetype":"locality"
},
  "geometry": {"coordinates":[16.42915,-8.9006],"type":"Point"}
}