{
  "type": "Feature",
  "properties": {
    "gn:admin1_code":"19.0",
    "gn:asciiname":"Lunga Riamica",
    "gn:cc2":"AO",
    "gn:country_code":"AO",
    "gn:dem":122,
    "gn:feature_class":"P",
    "gn:feature_code":"PPL",
    "gn:name":"Lunga Ri\u00e1mica",
    "gn:population":0,
    "gn:timezone":"Africa/Luanda",
    "iso:country":"AO",
    "name:und_x_variant":[
        "Lungario Mica",
        "Lunga Ri\u00e1mica"
    ],
    "wof:name":"Lunga Riamica",
    "wof:placetype":"locality"
},
  "geometry": {"coordinates":[14.36667,-9.83333],"type":"Point"}
}