{
  "type": "Feature",
  "properties": {
    "gn:admin1_code":"15.0",
    "gn:asciiname":"Regedoria do Caindo",
    "gn:cc2":"AO",
    "gn:country_code":"AO",
    "gn:dem":1100,
    "gn:feature_class":"P",
    "gn:feature_code":"PPL",
    "gn:name":"Regedoria do Caindo",
    "gn:population":0,
    "gn:timezone":"Africa/Luanda",
    "iso:country":"AO",
    "name:und_x_variant":[
        "Quimabengo",
        "Quimaengo",
        "Regedoria do Caindo"
    ],
    "wof:name":"Regedoria do Caindo",
    "wof:placetype":"locality"
},
  "geometry": {"coordinates":[15.33333,-7.13333],"type":"Point"}
}