{
  "type": "Feature",
  "properties": {
    "gn:admin1_code":"15.0",
    "gn:asciiname":"Cassange",
    "gn:country_code":"AO",
    "gn:dem":1208,
    "gn:feature_class":"P",
    "gn:feature_code":"PPL",
    "gn:name":"Cassange",
    "gn:population":0,
    "gn:timezone":"Africa/Luanda",
    "iso:country":"AO",
    "wof:name":"Cassange",
    "wof:placetype":"locality"
},
  "geometry": {"coordinates":[15.61667,-7.83333],"type":"Point"}
}