{
  "type": "Feature",
  "properties": {
    "gn:admin1_code":"5.0",
    "gn:asciiname":"Quicacuna",
    "gn:country_code":"AO",
    "gn:dem":976,
    "gn:feature_class":"P",
    "gn:feature_code":"PPL",
    "gn:name":"Quicacuna",
    "gn:population":0,
    "gn:timezone":"Africa/Luanda",
    "iso:country":"AO",
    "wof:name":"Quicacuna",
    "wof:placetype":"locality"
},
  "geometry": {"coordinates":[15.21818,-8.63478],"type":"Point"}
}