{
  "type": "Feature",
  "properties": {
    "gn:admin1_code":"15.0",
    "gn:asciiname":"Quicomba",
    "gn:country_code":"AO",
    "gn:dem":817,
    "gn:feature_class":"P",
    "gn:feature_code":"PPL",
    "gn:name":"Quicomba",
    "gn:population":0,
    "gn:timezone":"Africa/Luanda",
    "iso:country":"AO",
    "wof:name":"Quicomba",
    "wof:placetype":"locality"
},
  "geometry": {"coordinates":[15.63333,-5.86667],"type":"Point"}
}