{
  "type": "Feature",
  "properties": {
    "gn:admin1_code":"2.0",
    "gn:asciiname":"Techicola",
    "gn:cc2":"AO",
    "gn:country_code":"AO",
    "gn:dem":1473,
    "gn:feature_class":"P",
    "gn:feature_code":"PPL",
    "gn:name":"Techicola",
    "gn:population":0,
    "gn:timezone":"Africa/Luanda",
    "iso:country":"AO",
    "name:und_x_variant":[
        "Cacota",
        "Cac\u00f3la",
        "Techicola"
    ],
    "wof:name":"Techicola",
    "wof:placetype":"locality"
},
  "geometry": {"coordinates":[17.01667,-13.36667],"type":"Point"}
}