{
  "type": "Feature",
  "properties": {
    "gn:admin1_code":"18.0",
    "gn:asciiname":"Catchinga",
    "gn:country_code":"AO",
    "gn:dem":1309,
    "gn:feature_class":"P",
    "gn:feature_code":"PPL",
    "gn:name":"Catchinga",
    "gn:population":0,
    "gn:timezone":"Africa/Luanda",
    "iso:country":"AO",
    "wof:name":"Catchinga",
    "wof:placetype":"locality"
},
  "geometry": {"coordinates":[19.79583,-11.21332],"type":"Point"}
}