{
  "type": "Feature",
  "properties": {
    "gn:admin1_code":"8.0",
    "gn:asciiname":"Mendes",
    "gn:country_code":"AO",
    "gn:dem":1627,
    "gn:feature_class":"P",
    "gn:feature_code":"PPL",
    "gn:name":"Mendes",
    "gn:population":0,
    "gn:timezone":"Africa/Luanda",
    "iso:country":"AO",
    "name:cat_x_preferred":[
        "Per-Banebdjedet"
    ],
    "name:deu_x_preferred":[
        "Mendes"
    ],
    "name:ell_x_preferred":[
        "\u039c\u03ad\u03bd\u03b4\u03b7\u03c2"
    ],
    "name:epo_x_preferred":[
        "Mendes"
    ],
    "name:eus_x_preferred":[
        "Mendes"
    ],
    "name:fra_x_preferred":[
        "Mend\u00e8s"
    ],
    "name:ita_x_preferred":[
        "Mendes"
    ],
    "name:nld_x_preferred":[
        "Mendes"
    ],
    "name:por_x_preferred":[
        "Mend\u00e9s"
    ],
    "name:slk_x_preferred":[
        "Mendes"
    ],
    "name:spa_x_preferred":[
        "Mendes"
    ],
    "name:ukr_x_preferred":[
        "\u041c\u0435\u043d\u0434\u0435\u0441"
    ],
    "name:urd_x_preferred":[
        "\u0645\u06cc\u0646\u062f\u06cc\u0633"
    ],
    "name:zho_x_preferred":[
        "\u95e8\u5fb7\u65af"
    ],
    "wof:name":"Mendes",
    "wof:placetype":"locality"
},
  "geometry": {"coordinates":[15.98333,-12.53333],"type":"Point"}
}