{
  "type": "Feature",
  "properties": {
    "gn:admin1_code":"8.0",
    "gn:asciiname":"Mendes",
    "gn:country_code":"AO",
    "gn:dem":1627,
    "gn:feature_class":"P",
    "gn:feature_code":"PPL",
    "gn:name":"Mendes",
    "gn:population":0,
    "gn:timezone":"Africa/Luanda",
    "iso:country":"AO",
    "wof:name":"Mendes",
    "wof:placetype":"locality"
},
  "geometry": {"coordinates":[15.98333,-12.53333],"type":"Point"}
}