{
  "type": "Feature",
  "properties": {
    "gn:admin1_code":"15.0",
    "gn:asciiname":"Catumbo",
    "gn:country_code":"AO",
    "gn:dem":1279,
    "gn:feature_class":"P",
    "gn:feature_code":"PPL",
    "gn:name":"Catumbo",
    "gn:population":0,
    "gn:timezone":"Africa/Luanda",
    "iso:country":"AO",
    "wof:name":"Catumbo",
    "wof:placetype":"locality"
},
  "geometry": {"coordinates":[15.23403,-7.93399],"type":"Point"}
}