{
  "type": "Feature",
  "properties": {
    "gn:admin1_code":"15.0",
    "gn:asciiname":"Cangola",
    "gn:cc2":"AO",
    "gn:country_code":"AO",
    "gn:dem":1158,
    "gn:feature_class":"P",
    "gn:feature_code":"PPL",
    "gn:name":"Cangola",
    "gn:population":0,
    "gn:timezone":"Africa/Luanda",
    "iso:country":"AO",
    "name:und_x_variant":[
        "Zanga",
        "Cangola"
    ],
    "wof:name":"Cangola",
    "wof:placetype":"locality"
},
  "geometry": {"coordinates":[15.88333,-7.95],"type":"Point"}
}