{
  "type": "Feature",
  "properties": {
    "gn:admin1_code":"6.0",
    "gn:asciiname":"Muembege",
    "gn:country_code":"AO",
    "gn:dem":1381,
    "gn:feature_class":"P",
    "gn:feature_code":"PPL",
    "gn:name":"Muembege",
    "gn:population":0,
    "gn:timezone":"Africa/Luanda",
    "iso:country":"AO",
    "name:und_x_variant":[
        "Muimbeje",
        "Muembeje",
        "Muambege",
        "Muembege"
    ],
    "wof:name":"Muembege",
    "wof:placetype":"locality"
},
  "geometry": {"coordinates":[14.90899,-10.53485],"type":"Point"}
}