{
  "type": "Feature",
  "properties": {
    "gn:admin1_code":"15.0",
    "gn:asciiname":"Bumbo",
    "gn:country_code":"AO",
    "gn:dem":620,
    "gn:feature_class":"P",
    "gn:feature_code":"PPL",
    "gn:name":"Bumbo",
    "gn:population":0,
    "gn:timezone":"Africa/Luanda",
    "iso:country":"AO",
    "wof:name":"Bumbo",
    "wof:placetype":"locality"
},
  "geometry": {"coordinates":[14.48272,-6.92075],"type":"Point"}
}