{
  "type": "Feature",
  "properties": {
    "gn:admin1_code":"5.0",
    "gn:asciiname":"Ndala Nzamba",
    "gn:country_code":"AO",
    "gn:dem":1266,
    "gn:feature_class":"P",
    "gn:feature_code":"PPL",
    "gn:name":"Ndala Nzamba",
    "gn:population":0,
    "gn:timezone":"Africa/Luanda",
    "iso:country":"AO",
    "wof:name":"Ndala Nzamba",
    "wof:placetype":"locality"
},
  "geometry": {"coordinates":[15.35804,-8.30719],"type":"Point"}
}