{
  "type": "Feature",
  "properties": {
    "gn:admin1_code":"6.0",
    "gn:asciiname":"Bunde",
    "gn:country_code":"AO",
    "gn:dem":32,
    "gn:feature_class":"P",
    "gn:feature_code":"PPL",
    "gn:name":"Bunde",
    "gn:population":0,
    "gn:timezone":"Africa/Luanda",
    "iso:country":"AO",
    "name:und_x_variant":[
        "Zamba",
        "Dunde"
    ],
    "wof:name":"Bunde",
    "wof:placetype":"locality"
},
  "geometry": {"coordinates":[14.18543,-10.28962],"type":"Point"}
}