{
  "type": "Feature",
  "properties": {
    "gn:admin1_code":"8.0",
    "gn:asciiname":"Livongue",
    "gn:cc2":"AO",
    "gn:country_code":"AO",
    "gn:dem":1865,
    "gn:feature_class":"P",
    "gn:feature_code":"PPL",
    "gn:name":"Livongue",
    "gn:population":0,
    "gn:timezone":"Africa/Luanda",
    "iso:country":"AO",
    "name:und_x_variant":[
        "Libongue",
        "Livongue"
    ],
    "wof:name":"Livongue",
    "wof:placetype":"locality"
},
  "geometry": {"coordinates":[15.64611,-12.71944],"type":"Point"}
}