{
  "type": "Feature",
  "properties": {
    "gn:admin1_code":"12.0",
    "gn:asciiname":"Canambua",
    "gn:cc2":"AO",
    "gn:country_code":"AO",
    "gn:dem":1137,
    "gn:feature_class":"P",
    "gn:feature_code":"PPL",
    "gn:name":"Can\u00e2mbua",
    "gn:population":0,
    "gn:timezone":"Africa/Luanda",
    "iso:country":"AO",
    "name:und_x_variant":[
        "Cumambua",
        "Can\u00e2mbua"
    ],
    "wof:name":"Canambua",
    "wof:placetype":"locality"
},
  "geometry": {"coordinates":[16.36028,-9.55222],"type":"Point"}
}