{
  "type": "Feature",
  "properties": {
    "gn:admin1_code":"6.0",
    "gn:asciiname":"Laranja",
    "gn:country_code":"AO",
    "gn:dem":818,
    "gn:feature_class":"P",
    "gn:feature_code":"PPL",
    "gn:name":"Laranja",
    "gn:population":0,
    "gn:timezone":"Africa/Luanda",
    "iso:country":"AO",
    "wof:name":"Laranja",
    "wof:placetype":"locality"
},
  "geometry": {"coordinates":[14.26545,-11.0868],"type":"Point"}
}