{
  "type": "Feature",
  "properties": {
    "gn:admin1_code":"12.0",
    "gn:asciiname":"Massaca",
    "gn:country_code":"AO",
    "gn:dem":1047,
    "gn:feature_class":"P",
    "gn:feature_code":"PPL",
    "gn:name":"Massaca",
    "gn:population":0,
    "gn:timezone":"Africa/Luanda",
    "iso:country":"AO",
    "wof:name":"Massaca",
    "wof:placetype":"locality"
},
  "geometry": {"coordinates":[16.07,-9.71417],"type":"Point"}
}