{
  "type": "Feature",
  "properties": {
    "gn:admin1_code":"12.0",
    "gn:asciiname":"Quitumbi",
    "gn:country_code":"AO",
    "gn:dem":705,
    "gn:feature_class":"P",
    "gn:feature_code":"PPL",
    "gn:name":"Quitumbi",
    "gn:population":0,
    "gn:timezone":"Africa/Luanda",
    "iso:country":"AO",
    "wof:name":"Quitumbi",
    "wof:placetype":"locality"
},
  "geometry": {"coordinates":[17.25785,-9.35058],"type":"Point"}
}