{
  "type": "Feature",
  "properties": {
    "gn:admin1_code":"6.0",
    "gn:asciiname":"Se Nova",
    "gn:country_code":"AO",
    "gn:dem":1272,
    "gn:feature_class":"P",
    "gn:feature_code":"PPL",
    "gn:name":"S\u00e9 Nova",
    "gn:population":0,
    "gn:timezone":"Africa/Luanda",
    "iso:country":"AO",
    "wof:name":"Se Nova",
    "wof:placetype":"locality"
},
  "geometry": {"coordinates":[15.06223,-11.26851],"type":"Point"}
}