{
  "type": "Feature",
  "properties": {
    "gn:admin1_code":"15.0",
    "gn:asciiname":"Tuihango",
    "gn:country_code":"AO",
    "gn:dem":1282,
    "gn:feature_class":"P",
    "gn:feature_code":"PPL",
    "gn:name":"Tuihango",
    "gn:population":0,
    "gn:timezone":"Africa/Luanda",
    "iso:country":"AO",
    "wof:name":"Tuihango",
    "wof:placetype":"locality"
},
  "geometry": {"coordinates":[15.49761,-7.88606],"type":"Point"}
}