{
  "type": "Feature",
  "properties": {
    "gn:admin1_code":"12.0",
    "gn:asciiname":"Cassangi",
    "gn:country_code":"AO",
    "gn:dem":1195,
    "gn:feature_class":"P",
    "gn:feature_code":"PPL",
    "gn:name":"Cassangi",
    "gn:population":0,
    "gn:timezone":"Africa/Luanda",
    "iso:country":"AO",
    "wof:name":"Cassangi",
    "wof:placetype":"locality"
},
  "geometry": {"coordinates":[17.24874,-9.74695],"type":"Point"}
}