{
  "type": "Feature",
  "properties": {
    "gn:admin1_code":"17.0",
    "gn:asciiname":"Samongue",
    "gn:cc2":"AO",
    "gn:country_code":"AO",
    "gn:dem":976,
    "gn:feature_class":"P",
    "gn:feature_code":"PPL",
    "gn:name":"Samongue",
    "gn:population":0,
    "gn:timezone":"Africa/Luanda",
    "iso:country":"AO",
    "name:und_x_variant":[
        "Xamongue",
        "Samongue"
    ],
    "wof:name":"Samongue",
    "wof:placetype":"locality"
},
  "geometry": {"coordinates":[19.96667,-7.85],"type":"Point"}
}