{
  "type": "Feature",
  "properties": {
    "gn:admin1_code":"1.0",
    "gn:asciiname":"Bolonguera",
    "gn:country_code":"AO",
    "gn:dem":575,
    "gn:feature_class":"P",
    "gn:feature_code":"PPL",
    "gn:name":"Bolonguera",
    "gn:population":0,
    "gn:timezone":"Africa/Luanda",
    "iso:country":"AO",
    "wof:name":"Bolonguera",
    "wof:placetype":"locality"
},
  "geometry": {"coordinates":[13.58333,-13.55],"type":"Point"}
}