{
  "type": "Feature",
  "properties": {
    "gn:admin1_code":"6.0",
    "gn:asciiname":"Ndangi Nhia",
    "gn:country_code":"AO",
    "gn:dem":893,
    "gn:feature_class":"P",
    "gn:feature_code":"PPL",
    "gn:name":"Ndangi Nhia",
    "gn:population":0,
    "gn:timezone":"Africa/Luanda",
    "iso:country":"AO",
    "wof:name":"Ndangi Nhia",
    "wof:placetype":"locality"
},
  "geometry": {"coordinates":[14.55516,-10.52252],"type":"Point"}
}