{
  "type": "Feature",
  "properties": {
    "gn:admin1_code":"14.0",
    "gn:asciiname":"Manhinga",
    "gn:country_code":"AO",
    "gn:dem":1019,
    "gn:feature_class":"P",
    "gn:feature_code":"PPL",
    "gn:name":"Manhinga",
    "gn:population":0,
    "gn:timezone":"Africa/Luanda",
    "iso:country":"AO",
    "wof:name":"Manhinga",
    "wof:placetype":"locality"
},
  "geometry": {"coordinates":[22.2909,-10.63083],"type":"Point"}
}