{
  "type": "Feature",
  "properties": {
    "gn:admin1_code":"12.0",
    "gn:asciiname":"Tomba",
    "gn:country_code":"AO",
    "gn:dem":910,
    "gn:feature_class":"P",
    "gn:feature_code":"PPL",
    "gn:name":"Tomba",
    "gn:population":0,
    "gn:timezone":"Africa/Luanda",
    "iso:country":"AO",
    "wof:name":"Tomba",
    "wof:placetype":"locality"
},
  "geometry": {"coordinates":[15.57545,-9.18218],"type":"Point"}
}