{
  "type": "Feature",
  "properties": {
    "gn:admin1_code":"7.0",
    "gn:asciiname":"Cubati",
    "gn:cc2":"AO",
    "gn:country_code":"AO",
    "gn:dem":1255,
    "gn:feature_class":"P",
    "gn:feature_code":"PPL",
    "gn:name":"Cubati",
    "gn:population":0,
    "gn:timezone":"Africa/Luanda",
    "iso:country":"AO",
    "name:und_x_variant":[
        "Cachueca",
        "Mangongo",
        "Magongo",
        "Cubati"
    ],
    "wof:name":"Cubati",
    "wof:placetype":"locality"
},
  "geometry": {"coordinates":[16.85,-15.33333],"type":"Point"}
}