{
  "type": "Feature",
  "properties": {
    "gn:admin1_code":"7.0",
    "gn:asciiname":"Cubati",
    "gn:cc2":"AO",
    "gn:country_code":"AO",
    "gn:dem":1255,
    "gn:feature_class":"P",
    "gn:feature_code":"PPL",
    "gn:name":"Cubati",
    "gn:population":0,
    "gn:timezone":"Africa/Luanda",
    "iso:country":"AO",
    "name:bpy_x_preferred":[
        "\u0995\u09c1\u09ac\u09be\u099f\u09bf"
    ],
    "name:eus_x_preferred":[
        "Cubati"
    ],
    "name:fra_x_preferred":[
        "Cubati"
    ],
    "name:hye_x_preferred":[
        "\u053f\u0578\u0582\u0562\u0561\u057f\u056b"
    ],
    "name:ita_x_preferred":[
        "Cubati"
    ],
    "name:kat_x_preferred":[
        "\u10d9\u10e3\u10d1\u10d0\u10e2\u10d8"
    ],
    "name:kaz_x_preferred":[
        "\u041a\u0443\u0431\u0430\u0442\u0438"
    ],
    "name:nld_x_preferred":[
        "Cubati"
    ],
    "name:nor_x_preferred":[
        "Cubati"
    ],
    "name:por_x_preferred":[
        "Cubati"
    ],
    "name:ron_x_preferred":[
        "Cubati"
    ],
    "name:rus_x_preferred":[
        "\u041a\u0443\u0431\u0430\u0442\u0438"
    ],
    "name:und_x_variant":[
        "Cachueca",
        "Mangongo",
        "Magongo",
        "Cubati"
    ],
    "name:vie_x_preferred":[
        "Cubati"
    ],
    "name:vol_x_preferred":[
        "Cubati"
    ],
    "name:war_x_preferred":[
        "Cubati"
    ],
    "name:zho_x_preferred":[
        "\u5e93\u5df4\u8482"
    ],
    "wof:name":"Cubati",
    "wof:placetype":"locality"
},
  "geometry": {"coordinates":[16.85,-15.33333],"type":"Point"}
}