{
  "type": "Feature",
  "properties": {
    "gn:admin1_code":"19.0",
    "gn:asciiname":"Quizanga",
    "gn:country_code":"AO",
    "gn:dem":383,
    "gn:feature_class":"P",
    "gn:feature_code":"PPL",
    "gn:name":"Quizanga",
    "gn:population":0,
    "gn:timezone":"Africa/Luanda",
    "iso:country":"AO",
    "wof:name":"Quizanga",
    "wof:placetype":"locality"
},
  "geometry": {"coordinates":[14.49401,-10.08305],"type":"Point"}
}