{
  "type": "Feature",
  "properties": {
    "gn:admin1_code":"17.0",
    "gn:asciiname":"Muanha Ngando",
    "gn:country_code":"AO",
    "gn:dem":951,
    "gn:feature_class":"P",
    "gn:feature_code":"PPL",
    "gn:name":"Muanha Ngando",
    "gn:population":0,
    "gn:timezone":"Africa/Luanda",
    "iso:country":"AO",
    "wof:name":"Muanha Ngando",
    "wof:placetype":"locality"
},
  "geometry": {"coordinates":[18.32247000000001,-9.33912],"type":"Point"}
}