{
  "type": "Feature",
  "properties": {
    "gn:admin1_code":"12.0",
    "gn:asciiname":"Caquiengue",
    "gn:country_code":"AO",
    "gn:dem":1072,
    "gn:feature_class":"P",
    "gn:feature_code":"PPL",
    "gn:name":"Caquiengue",
    "gn:population":0,
    "gn:timezone":"Africa/Luanda",
    "iso:country":"AO",
    "name:und_x_variant":[
        "Hembi",
        "Caquiengue"
    ],
    "wof:name":"Caquiengue",
    "wof:placetype":"locality"
},
  "geometry": {"coordinates":[16.20879,-9.46307],"type":"Point"}
}