{
  "type": "Feature",
  "properties": {
    "gn:admin1_code":"14.0",
    "gn:asciiname":"Tchizimo",
    "gn:country_code":"AO",
    "gn:dem":1301,
    "gn:feature_class":"P",
    "gn:feature_code":"PPL",
    "gn:name":"Tchizimo",
    "gn:population":0,
    "gn:timezone":"Africa/Luanda",
    "iso:country":"AO",
    "wof:name":"Tchizimo",
    "wof:placetype":"locality"
},
  "geometry": {"coordinates":[20.13333,-13.75],"type":"Point"}
}