{
  "type": "Feature",
  "properties": {
    "gn:admin1_code":"8.0",
    "gn:asciiname":"Cachicala",
    "gn:country_code":"AO",
    "gn:dem":1929,
    "gn:feature_class":"P",
    "gn:feature_code":"PPL",
    "gn:name":"Cachicala",
    "gn:population":0,
    "gn:timezone":"Africa/Luanda",
    "iso:country":"AO",
    "wof:name":"Cachicala",
    "wof:placetype":"locality"
},
  "geometry": {"coordinates":[14.98333,-12.98333],"type":"Point"}
}