{
  "type": "Feature",
  "properties": {
    "gn:admin1_code":"6.0",
    "gn:asciiname":"Capolo",
    "gn:country_code":"AO",
    "gn:dem":26,
    "gn:feature_class":"P",
    "gn:feature_code":"PPL",
    "gn:name":"Capolo",
    "gn:population":0,
    "gn:timezone":"Africa/Luanda",
    "iso:country":"AO",
    "name:und_x_variant":[
        "Kapolo",
        "Copolo",
        "Capolo"
    ],
    "wof:name":"Capolo",
    "wof:placetype":"locality"
},
  "geometry": {"coordinates":[13.98592,-10.39093],"type":"Point"}
}