{
  "type": "Feature",
  "properties": {
    "gn:admin1_code":"15.0",
    "gn:asciiname":"Mbanza Luanda",
    "gn:country_code":"AO",
    "gn:dem":1150,
    "gn:feature_class":"P",
    "gn:feature_code":"PPL",
    "gn:name":"Mbanza Luanda",
    "gn:population":0,
    "gn:timezone":"Africa/Luanda",
    "iso:country":"AO",
    "name:rus_x_preferred":[
        "\u041b\u0443\u0430\u043d\u0434\u0430"
    ],
    "name:und_x_variant":[
        "Banza Loanda",
        "Banza Luanda",
        "Luanda",
        "Mbanza Luanda"
    ],
    "wof:name":"Mbanza Luanda",
    "wof:placetype":"locality"
},
  "geometry": {"coordinates":[15.18549,-7.64544],"type":"Point"}
}