{
  "type": "Feature",
  "properties": {
    "gn:admin1_code":"19.0",
    "gn:asciiname":"Casseques",
    "gn:country_code":"AO",
    "gn:dem":202,
    "gn:feature_class":"P",
    "gn:feature_code":"PPLL",
    "gn:name":"Casseques",
    "gn:population":0,
    "gn:timezone":"Africa/Luanda",
    "iso:country":"AO",
    "wof:name":"Casseques",
    "wof:placetype":"locality"
},
  "geometry": {"coordinates":[13.74583,-9.84084],"type":"Point"}
}