{
  "type": "Feature",
  "properties": {
    "gn:admin1_code":"12.0",
    "gn:asciiname":"Cazanga Segundo",
    "gn:country_code":"AO",
    "gn:dem":954,
    "gn:feature_class":"P",
    "gn:feature_code":"PPL",
    "gn:name":"Cazanga Segundo",
    "gn:population":0,
    "gn:timezone":"Africa/Luanda",
    "iso:country":"AO",
    "wof:name":"Cazanga Segundo",
    "wof:placetype":"locality"
},
  "geometry": {"coordinates":[15.7843,-9.13113],"type":"Point"}
}