{
  "type": "Feature",
  "properties": {
    "gn:admin1_code":"0.0",
    "gn:asciiname":"Lutente",
    "gn:country_code":"AO",
    "gn:dem":965,
    "gn:feature_class":"P",
    "gn:feature_code":"PPL",
    "gn:name":"Lutente",
    "gn:population":0,
    "gn:timezone":"Africa/Luanda",
    "iso:country":"AO",
    "wof:name":"Lutente",
    "wof:placetype":"locality"
},
  "geometry": {"coordinates":[13.97972,-12.67861],"type":"Point"}
}