{
  "type": "Feature",
  "properties": {
    "gn:admin1_code":"12.0",
    "gn:asciiname":"Matandala",
    "gn:country_code":"AO",
    "gn:dem":1216,
    "gn:feature_class":"P",
    "gn:feature_code":"PPL",
    "gn:name":"Matandala",
    "gn:population":0,
    "gn:timezone":"Africa/Luanda",
    "iso:country":"AO",
    "wof:name":"Matandala",
    "wof:placetype":"locality"
},
  "geometry": {"coordinates":[17.04606,-9.12053],"type":"Point"}
}