{
  "type": "Feature",
  "properties": {
    "gn:admin1_code":"18.0",
    "gn:asciiname":"Cassaza",
    "gn:cc2":"AO",
    "gn:country_code":"AO",
    "gn:dem":1008,
    "gn:feature_class":"P",
    "gn:feature_code":"PPL",
    "gn:name":"Cassaza",
    "gn:population":0,
    "gn:timezone":"Africa/Luanda",
    "iso:country":"AO",
    "name:und_x_variant":[
        "Machambanda",
        "Cassaza"
    ],
    "wof:name":"Cassaza",
    "wof:placetype":"locality"
},
  "geometry": {"coordinates":[21.61667000000001,-9.73333],"type":"Point"}
}