{
  "type": "Feature",
  "properties": {
    "gn:admin1_code":"15.0",
    "gn:asciiname":"Quilongui",
    "gn:country_code":"AO",
    "gn:dem":841,
    "gn:feature_class":"P",
    "gn:feature_code":"PPL",
    "gn:name":"Quilongui",
    "gn:population":0,
    "gn:timezone":"Africa/Luanda",
    "iso:country":"AO",
    "wof:name":"Quilongui",
    "wof:placetype":"locality"
},
  "geometry": {"coordinates":[14.99484,-6.01299],"type":"Point"}
}