{
  "type": "Feature",
  "properties": {
    "gn:admin1_code":"3.0",
    "gn:asciiname":"Mazi",
    "gn:country_code":"AO",
    "gn:dem":72,
    "gn:feature_class":"P",
    "gn:feature_code":"PPL",
    "gn:name":"Mazi",
    "gn:population":0,
    "gn:timezone":"Africa/Luanda",
    "iso:country":"AO",
    "name:ceb_x_preferred":[
        "Mazi"
    ],
    "name:swe_x_preferred":[
        "Mazi"
    ],
    "wof:name":"Mazi",
    "wof:placetype":"locality"
},
  "geometry": {"coordinates":[12.26667,-5.45],"type":"Point"}
}