{
  "type": "Feature",
  "properties": {
    "gn:admin1_code":"6.0",
    "gn:asciiname":"Cateta",
    "gn:country_code":"AO",
    "gn:dem":1035,
    "gn:feature_class":"P",
    "gn:feature_code":"PPL",
    "gn:name":"Cateta",
    "gn:population":0,
    "gn:timezone":"Africa/Luanda",
    "iso:country":"AO",
    "name:und_x_variant":[
        "Cabeba",
        "Cateta"
    ],
    "wof:name":"Cateta",
    "wof:placetype":"locality"
},
  "geometry": {"coordinates":[14.97521,-10.07855],"type":"Point"}
}