{
  "type": "Feature",
  "properties": {
    "gn:admin1_code":"8.0",
    "gn:asciiname":"Luhunguhe",
    "gn:country_code":"AO",
    "gn:dem":1619,
    "gn:feature_class":"P",
    "gn:feature_code":"PPL",
    "gn:name":"Luhunguhe",
    "gn:population":0,
    "gn:timezone":"Africa/Luanda",
    "iso:country":"AO",
    "wof:name":"Luhunguhe",
    "wof:placetype":"locality"
},
  "geometry": {"coordinates":[14.98333,-12.63333],"type":"Point"}
}