{
  "type": "Feature",
  "properties": {
    "gn:admin1_code":"14.0",
    "gn:asciiname":"Moxico",
    "gn:cc2":"AO",
    "gn:country_code":"AO",
    "gn:dem":1173,
    "gn:feature_class":"P",
    "gn:feature_code":"PPL",
    "gn:name":"Moxico",
    "gn:population":0,
    "gn:timezone":"Africa/Luanda",
    "iso:country":"AO",
    "name:ceb_x_preferred":[
        "Moxico"
    ],
    "name:swe_x_preferred":[
        "Moxico"
    ],
    "name:und_x_variant":[
        "Maxico"
    ],
    "wof:name":"Moxico",
    "wof:placetype":"locality"
},
  "geometry": {"coordinates":[21.25,-13.26667],"type":"Point"}
}