{
  "type": "Feature",
  "properties": {
    "gn:admin1_code":"5.0",
    "gn:asciiname":"Mulolo Primeiro",
    "gn:country_code":"AO",
    "gn:dem":759,
    "gn:feature_class":"P",
    "gn:feature_code":"PPL",
    "gn:name":"Mulolo Primeiro",
    "gn:population":0,
    "gn:timezone":"Africa/Luanda",
    "iso:country":"AO",
    "wof:name":"Mulolo Primeiro",
    "wof:placetype":"locality"
},
  "geometry": {"coordinates":[14.82779,-9.09086],"type":"Point"}
}