{
  "type": "Feature",
  "properties": {
    "gn:admin1_code":"15.0",
    "gn:asciiname":"Quimengue",
    "gn:country_code":"AO",
    "gn:dem":1014,
    "gn:feature_class":"P",
    "gn:feature_code":"PPL",
    "gn:name":"Quimengue",
    "gn:population":0,
    "gn:timezone":"Africa/Luanda",
    "iso:country":"AO",
    "wof:name":"Quimengue",
    "wof:placetype":"locality"
},
  "geometry": {"coordinates":[15.88333,-7.35],"type":"Point"}
}