{
  "type": "Feature",
  "properties": {
    "gn:admin1_code":"15.0",
    "gn:asciiname":"Quiteca Malungo",
    "gn:country_code":"AO",
    "gn:dem":1138,
    "gn:feature_class":"P",
    "gn:feature_code":"PPL",
    "gn:name":"Quiteca Malungo",
    "gn:population":0,
    "gn:timezone":"Africa/Luanda",
    "iso:country":"AO",
    "wof:name":"Quiteca Malungo",
    "wof:placetype":"locality"
},
  "geometry": {"coordinates":[15.56467,-7.03858],"type":"Point"}
}