{
  "type": "Feature",
  "properties": {
    "gn:admin1_code":"6.0",
    "gn:asciiname":"Ndalangombe",
    "gn:country_code":"AO",
    "gn:dem":923,
    "gn:feature_class":"P",
    "gn:feature_code":"PPL",
    "gn:name":"Ndalangombe",
    "gn:population":0,
    "gn:timezone":"Africa/Luanda",
    "iso:country":"AO",
    "wof:name":"Ndalangombe",
    "wof:placetype":"locality"
},
  "geometry": {"coordinates":[14.36812,-10.46886],"type":"Point"}
}