{
  "type": "Feature",
  "properties": {
    "iso:country":"AO",
    "name:chi_x_preferred":[
        "\u7a46\u5eab\u7d22"
    ],
    "name:dut_x_preferred":[
        "Mucusso"
    ],
    "name:eng_x_preferred":[
        "Mucusso"
    ],
    "name:fre_x_preferred":[
        "Mucusso"
    ],
    "name:per_x_preferred":[
        "\u0645\u0648\u06a9\u0648\u0633\u0648\u060c \u0622\u0646\u06af\u0648\u0644\u0627"
    ],
    "name:por_x_preferred":[
        "Mucusso"
    ],
    "name:rus_x_preferred":[
        "\u041c\u0443\u043a\u0443\u0441\u0441\u043e"
    ],
    "ne:ADM0CAP":0.0,
    "ne:ADM0NAME":"Angola",
    "ne:ADM0_A3":"AGO",
    "ne:ADM1NAME":"Cuando Cubango",
    "ne:ADMIN1_COD":0,
    "ne:CAPALT":0,
    "ne:CHANGED":4,
    "ne:CHECKME":0,
    "ne:COMPARE":0,
    "ne:DIFFASCII":0,
    "ne:DIFFNOTE":"Changed scale rank.",
    "ne:ELEVATION":0.0,
    "ne:FEATURECLA":"Populated place",
    "ne:GEONAMEID":-1,
    "ne:GEONAMESNO":"No GeoNames match due to small population, not in GeoNames, or poor NEV placement.",
    "ne:GN_POP":0,
    "ne:GTOPO30":0.0,
    "ne:ISO_A2":"AO",
    "ne:LABELRANK":6,
    "ne:LATITUDE":-18.019534,
    "ne:LONGITUDE":21.429999,
    "ne:LS_MATCH":0,
    "ne:LS_NAME":"Mucusso",
    "ne:MAX_AREAKM":0.0,
    "ne:MAX_AREAMI":0.0,
    "ne:MAX_BBXMAX":0.0,
    "ne:MAX_BBXMIN":0.0,
    "ne:MAX_BBYMAX":0.0,
    "ne:MAX_BBYMIN":0.0,
    "ne:MAX_NATSCA":0.0,
    "ne:MAX_PERKM":0.0,
    "ne:MAX_PERMI":0.0,
    "ne:MAX_POP10":0,
    "ne:MAX_POP20":0,
    "ne:MAX_POP300":0,
    "ne:MAX_POP310":0,
    "ne:MAX_POP50":0,
    "ne:MEAN_BBXC":0.0,
    "ne:MEAN_BBYC":0.0,
    "ne:MEGACITY":0,
    "ne:MIN_AREAKM":0.0,
    "ne:MIN_AREAMI":0.0,
    "ne:MIN_BBXMAX":0.0,
    "ne:MIN_BBXMIN":0.0,
    "ne:MIN_BBYMAX":0.0,
    "ne:MIN_BBYMIN":0.0,
    "ne:MIN_PERKM":0.0,
    "ne:MIN_PERMI":0.0,
    "ne:NAME":"Mucusso",
    "ne:NAMEASCII":"Mucusso",
    "ne:NAMEDIFF":0,
    "ne:NATSCALE":20,
    "ne:POP1950":0,
    "ne:POP1955":0,
    "ne:POP1960":0,
    "ne:POP1965":0,
    "ne:POP1970":0,
    "ne:POP1975":0,
    "ne:POP1980":0,
    "ne:POP1985":0,
    "ne:POP1990":0,
    "ne:POP1995":0,
    "ne:POP2000":0,
    "ne:POP2005":0,
    "ne:POP2010":0,
    "ne:POP2015":0,
    "ne:POP2020":0,
    "ne:POP2025":0,
    "ne:POP2050":0,
    "ne:POP_MAX":100,
    "ne:POP_MIN":100,
    "ne:POP_OTHER":0,
    "ne:RANK_MAX":1,
    "ne:RANK_MIN":1,
    "ne:SCALERANK":7,
    "ne:SOV0NAME":"Angola",
    "ne:SOV_A3":"AGO",
    "ne:UN_FID":0,
    "ne:UN_LAT":0.0,
    "ne:UN_LONG":0.0,
    "ne:WORLDCITY":0,
    "ne:min_zoom":6.7,
    "wof:name":"Mucusso",
    "wof:placetype":"locality"
},
  "geometry": {"coordinates":[21.42999914417891,-18.01953448605832],"type":"Point"}
}