{
  "type": "Feature",
  "properties": {
    "gn:admin1_code":"8.0",
    "gn:asciiname":"Ngumbe",
    "gn:country_code":"AO",
    "gn:dem":1693,
    "gn:feature_class":"P",
    "gn:feature_code":"PPL",
    "gn:name":"Ngumbe",
    "gn:population":0,
    "gn:timezone":"Africa/Luanda",
    "iso:country":"AO",
    "wof:name":"Ngumbe",
    "wof:placetype":"locality"
},
  "geometry": {"coordinates":[15.54056,-12.9925],"type":"Point"}
}