{
  "type": "Feature",
  "properties": {
    "gn:admin1_code":"12.0",
    "gn:asciiname":"Zatula",
    "gn:country_code":"AO",
    "gn:dem":1179,
    "gn:feature_class":"P",
    "gn:feature_code":"PPL",
    "gn:name":"Zatula",
    "gn:population":0,
    "gn:timezone":"Africa/Luanda",
    "iso:country":"AO",
    "name:und_x_variant":[
        "Zatuta",
        "Zatula"
    ],
    "wof:name":"Zatula",
    "wof:placetype":"locality"
},
  "geometry": {"coordinates":[15.87192,-8.53145],"type":"Point"}
}