{
  "type": "Feature",
  "properties": {
    "gn:admin1_code":"8.0",
    "gn:asciiname":"Catala",
    "gn:country_code":"AO",
    "gn:dem":1433,
    "gn:feature_class":"P",
    "gn:feature_code":"PPL",
    "gn:name":"Catala",
    "gn:population":0,
    "gn:timezone":"Africa/Luanda",
    "iso:country":"AO",
    "wof:name":"Catala",
    "wof:placetype":"locality"
},
  "geometry": {"coordinates":[15.35,-12.15],"type":"Point"}
}