{
  "type": "Feature",
  "properties": {
    "gn:admin1_code":"7.0",
    "gn:asciiname":"Uia",
    "gn:cc2":"AO",
    "gn:country_code":"AO",
    "gn:dem":1125,
    "gn:feature_class":"P",
    "gn:feature_code":"PPL",
    "gn:name":"Uia",
    "gn:population":0,
    "gn:timezone":"Africa/Luanda",
    "iso:country":"AO",
    "name:rus_x_preferred":[
        "\u0423\u044f"
    ],
    "name:und_x_variant":[
        "Huia",
        "Uia"
    ],
    "wof:name":"Uia",
    "wof:placetype":"locality"
},
  "geometry": {"coordinates":[14.61667,-16.45],"type":"Point"}
}