{
  "type": "Feature",
  "properties": {
    "gn:admin1_code":"15.0",
    "gn:asciiname":"Sadia",
    "gn:country_code":"AO",
    "gn:dem":873,
    "gn:feature_class":"P",
    "gn:feature_code":"PPL",
    "gn:name":"S\u00e1dia",
    "gn:population":0,
    "gn:timezone":"Africa/Luanda",
    "iso:country":"AO",
    "name:ara_x_preferred":[
        "\u0633\u0627\u062f\u064a\u0627"
    ],
    "name:deu_x_preferred":[
        "Sadia"
    ],
    "name:fra_x_preferred":[
        "Sadia"
    ],
    "name:hye_x_preferred":[
        "Sadia"
    ],
    "name:por_x_preferred":[
        "Sadia S."
    ],
    "name:rus_x_preferred":[
        "Sadia"
    ],
    "wof:name":"Sadia",
    "wof:placetype":"locality"
},
  "geometry": {"coordinates":[14.96667,-5.96667],"type":"Point"}
}