{
  "type": "Feature",
  "properties": {
    "gn:admin1_code":"19.0",
    "gn:asciiname":"Cariongo",
    "gn:cc2":"AO",
    "gn:country_code":"AO",
    "gn:dem":20,
    "gn:feature_class":"P",
    "gn:feature_code":"PPL",
    "gn:name":"Cariongo",
    "gn:population":0,
    "gn:timezone":"Africa/Luanda",
    "iso:country":"AO",
    "name:und_x_variant":[
        "Cadiongo",
        "Cariongo"
    ],
    "wof:name":"Cariongo",
    "wof:placetype":"locality"
},
  "geometry": {"coordinates":[13.67972,-8.57389],"type":"Point"}
}