{
  "type": "Feature",
  "properties": {
    "gn:admin1_code":"2.0",
    "gn:asciiname":"Sandele",
    "gn:country_code":"AO",
    "gn:dem":1600,
    "gn:feature_class":"P",
    "gn:feature_code":"PPL",
    "gn:name":"Sandele",
    "gn:population":0,
    "gn:timezone":"Africa/Luanda",
    "iso:country":"AO",
    "wof:name":"Sandele",
    "wof:placetype":"locality"
},
  "geometry": {"coordinates":[16.93098,-11.44674],"type":"Point"}
}