{
  "type": "Feature",
  "properties": {
    "gn:admin1_code":"15.0",
    "gn:asciiname":"Taia",
    "gn:country_code":"AO",
    "gn:dem":872,
    "gn:feature_class":"P",
    "gn:feature_code":"PPL",
    "gn:name":"Taia",
    "gn:population":0,
    "gn:timezone":"Africa/Luanda",
    "iso:country":"AO",
    "wof:name":"Taia",
    "wof:placetype":"locality"
},
  "geometry": {"coordinates":[15.06203,-5.98596],"type":"Point"}
}