{
  "type": "Feature",
  "properties": {
    "gn:admin1_code":"14.0",
    "gn:asciiname":"Salilemo",
    "gn:country_code":"AO",
    "gn:dem":1090,
    "gn:feature_class":"P",
    "gn:feature_code":"PPL",
    "gn:name":"Salilemo",
    "gn:population":0,
    "gn:timezone":"Africa/Luanda",
    "iso:country":"AO",
    "wof:name":"Salilemo",
    "wof:placetype":"locality"
},
  "geometry": {"coordinates":[22.19299,-10.70292],"type":"Point"}
}