{
  "type": "Feature",
  "properties": {
    "gn:admin1_code":"12.0",
    "gn:asciiname":"Marimba Nguengo",
    "gn:country_code":"AO",
    "gn:dem":661,
    "gn:feature_class":"P",
    "gn:feature_code":"PPL",
    "gn:name":"Marimba Nguengo",
    "gn:population":0,
    "gn:timezone":"Africa/Luanda",
    "iso:country":"AO",
    "name:rus_x_preferred":[
        "\u041c\u0430\u0440\u0438\u043c\u0431\u0430\u043d\u0433\u0443\u0435\u043d\u0433\u0443"
    ],
    "name:und_x_variant":[
        "Marimba",
        "Marimba Nguengo"
    ],
    "wof:name":"Marimba Nguengo",
    "wof:placetype":"locality"
},
  "geometry": {"coordinates":[17.48349,-8.18202],"type":"Point"}
}