{
  "type": "Feature",
  "properties": {
    "gn:admin1_code":"12.0",
    "gn:asciiname":"Capembe",
    "gn:country_code":"AO",
    "gn:dem":1104,
    "gn:feature_class":"P",
    "gn:feature_code":"PPL",
    "gn:name":"Capembe",
    "gn:population":0,
    "gn:timezone":"Africa/Luanda",
    "iso:country":"AO",
    "wof:name":"Capembe",
    "wof:placetype":"locality"
},
  "geometry": {"coordinates":[17.58775,-10.28115],"type":"Point"}
}