{
  "type": "Feature",
  "properties": {
    "gn:admin1_code":"14.0",
    "gn:asciiname":"Chimuanga",
    "gn:cc2":"AO",
    "gn:country_code":"AO",
    "gn:dem":1070,
    "gn:feature_class":"P",
    "gn:feature_code":"PPL",
    "gn:name":"Chimuanga",
    "gn:population":0,
    "gn:timezone":"Africa/Luanda",
    "iso:country":"AO",
    "name:und_x_variant":[
        "Shilendela",
        "Chitendela",
        "Chimuanga"
    ],
    "wof:name":"Chimuanga",
    "wof:placetype":"locality"
},
  "geometry": {"coordinates":[22.55,-12.21667],"type":"Point"}
}