{
  "type": "Feature",
  "properties": {
    "gn:admin1_code":"12.0",
    "gn:asciiname":"Satemba",
    "gn:country_code":"AO",
    "gn:dem":1108,
    "gn:feature_class":"P",
    "gn:feature_code":"PPL",
    "gn:name":"Satemba",
    "gn:population":0,
    "gn:timezone":"Africa/Luanda",
    "iso:country":"AO",
    "wof:name":"Satemba",
    "wof:placetype":"locality"
},
  "geometry": {"coordinates":[17.7501,-10.54471],"type":"Point"}
}