{
  "type": "Feature",
  "properties": {
    "gn:admin1_code":"12.0",
    "gn:asciiname":"Cabisso",
    "gn:country_code":"AO",
    "gn:dem":736,
    "gn:feature_class":"P",
    "gn:feature_code":"PPL",
    "gn:name":"Cabisso",
    "gn:population":0,
    "gn:timezone":"Africa/Luanda",
    "iso:country":"AO",
    "wof:name":"Cabisso",
    "wof:placetype":"locality"
},
  "geometry": {"coordinates":[17.15537999999999,-9.06227],"type":"Point"}
}