{
  "type": "Feature",
  "properties": {
    "gn:admin1_code":"6.0",
    "gn:asciiname":"Quiundo",
    "gn:country_code":"AO",
    "gn:dem":1280,
    "gn:feature_class":"P",
    "gn:feature_code":"PPLL",
    "gn:name":"Quiundo",
    "gn:population":0,
    "gn:timezone":"Africa/Luanda",
    "iso:country":"AO",
    "wof:name":"Quiundo",
    "wof:placetype":"locality"
},
  "geometry": {"coordinates":[15.37251,-10.45338],"type":"Point"}
}