{
  "type": "Feature",
  "properties": {
    "gn:admin1_code":"17.0",
    "gn:asciiname":"Camaia",
    "gn:cc2":"AO",
    "gn:country_code":"AO",
    "gn:dem":826,
    "gn:feature_class":"P",
    "gn:feature_code":"PPL",
    "gn:name":"Camaia",
    "gn:population":0,
    "gn:timezone":"Africa/Luanda",
    "iso:country":"AO",
    "name:und_x_variant":[
        "Cameia",
        "Camaia"
    ],
    "wof:name":"Camaia",
    "wof:placetype":"locality"
},
  "geometry": {"coordinates":[21.06667,-8.05],"type":"Point"}
}