{
  "type": "Feature",
  "properties": {
    "gn:admin1_code":"17.0",
    "gn:asciiname":"Mundanga",
    "gn:country_code":"AO",
    "gn:dem":1073,
    "gn:feature_class":"P",
    "gn:feature_code":"PPL",
    "gn:name":"Mundanga",
    "gn:population":0,
    "gn:timezone":"Africa/Luanda",
    "iso:country":"AO",
    "wof:name":"Mundanga",
    "wof:placetype":"locality"
},
  "geometry": {"coordinates":[19.16667,-9.55],"type":"Point"}
}