{
  "type": "Feature",
  "properties": {
    "gn:admin1_code":"15.0",
    "gn:asciiname":"Quimbuco Segundo",
    "gn:country_code":"AO",
    "gn:dem":1006,
    "gn:feature_class":"P",
    "gn:feature_code":"PPL",
    "gn:name":"Quimbuco Segundo",
    "gn:population":0,
    "gn:timezone":"Africa/Luanda",
    "iso:country":"AO",
    "name:und_x_variant":[
        "Quimbuco"
    ],
    "wof:name":"Quimbuco Segundo",
    "wof:placetype":"locality"
},
  "geometry": {"coordinates":[15.87442,-7.00945],"type":"Point"}
}