{
  "type": "Feature",
  "properties": {
    "gn:admin1_code":"12.0",
    "gn:asciiname":"Mulundo",
    "gn:country_code":"AO",
    "gn:dem":1331,
    "gn:feature_class":"P",
    "gn:feature_code":"PPL",
    "gn:name":"Mulundo",
    "gn:population":0,
    "gn:timezone":"Africa/Luanda",
    "iso:country":"AO",
    "wof:name":"Mulundo",
    "wof:placetype":"locality"
},
  "geometry": {"coordinates":[18.00135,-10.84875],"type":"Point"}
}