{
  "type": "Feature",
  "properties": {
    "gn:admin1_code":"16.0",
    "gn:asciiname":"Conco",
    "gn:cc2":"AO",
    "gn:country_code":"AO",
    "gn:dem":582,
    "gn:feature_class":"P",
    "gn:feature_code":"PPL",
    "gn:name":"Conco",
    "gn:population":0,
    "gn:timezone":"Africa/Luanda",
    "iso:country":"AO",
    "name:azb_x_preferred":[
        "\u06a9\u0648\u0646\u06a9\u0648"
    ],
    "name:bul_x_preferred":[
        "\u041a\u043e\u043d\u043a\u043e"
    ],
    "name:cat_x_preferred":[
        "Conco"
    ],
    "name:ceb_x_preferred":[
        "Conco"
    ],
    "name:deu_x_preferred":[
        "Conco"
    ],
    "name:epo_x_preferred":[
        "Conco"
    ],
    "name:eus_x_preferred":[
        "Conco"
    ],
    "name:fas_x_preferred":[
        "\u06a9\u0648\u0646\u06a9\u0648"
    ],
    "name:fra_x_preferred":[
        "Conco"
    ],
    "name:hun_x_preferred":[
        "Conco"
    ],
    "name:hye_x_preferred":[
        "\u053f\u0578\u0576\u056f\u0578"
    ],
    "name:ita_x_preferred":[
        "Conco"
    ],
    "name:jpn_x_preferred":[
        "\u30b3\u30f3\u30b3"
    ],
    "name:kaz_x_preferred":[
        "\u041a\u043e\u043d\u043a\u043e"
    ],
    "name:lat_x_preferred":[
        "Concum"
    ],
    "name:lmo_x_preferred":[
        "Conco"
    ],
    "name:msa_x_preferred":[
        "Conco"
    ],
    "name:nap_x_preferred":[
        "Conco"
    ],
    "name:nld_x_preferred":[
        "Conco"
    ],
    "name:nor_x_preferred":[
        "Conco"
    ],
    "name:pms_x_preferred":[
        "Conco"
    ],
    "name:pol_x_preferred":[
        "Conco"
    ],
    "name:por_x_preferred":[
        "Conco"
    ],
    "name:ron_x_preferred":[
        "Conco"
    ],
    "name:rus_x_preferred":[
        "\u041a\u043e\u043d\u043a\u043e"
    ],
    "name:scn_x_preferred":[
        "Conco"
    ],
    "name:spa_x_preferred":[
        "Conco"
    ],
    "name:srp_x_preferred":[
        "\u041a\u043e\u043d\u043a\u043e"
    ],
    "name:tgl_x_preferred":[
        "Conco"
    ],
    "name:ukr_x_preferred":[
        "\u041a\u043e\u043d\u043a\u043e"
    ],
    "name:und_x_variant":[
        "Konko"
    ],
    "name:uzb_x_preferred":[
        "Conco"
    ],
    "name:vec_x_preferred":[
        "Conco"
    ],
    "name:vol_x_preferred":[
        "Conco"
    ],
    "name:war_x_preferred":[
        "Conco"
    ],
    "wof:name":"Conco",
    "wof:placetype":"locality"
},
  "geometry": {"coordinates":[14.31667,-6.56667],"type":"Point"}
}