{
  "type": "Feature",
  "properties": {
    "gn:admin1_code":"12.0",
    "gn:asciiname":"Zangula",
    "gn:country_code":"AO",
    "gn:dem":1075,
    "gn:feature_class":"P",
    "gn:feature_code":"PPL",
    "gn:name":"Zangula",
    "gn:population":0,
    "gn:timezone":"Africa/Luanda",
    "iso:country":"AO",
    "wof:name":"Zangula",
    "wof:placetype":"locality"
},
  "geometry": {"coordinates":[16.12187999999999,-7.92312],"type":"Point"}
}