{
  "type": "Feature",
  "properties": {
    "gn:admin1_code":"14.0",
    "gn:asciiname":"Pelumba",
    "gn:cc2":"AO",
    "gn:country_code":"AO",
    "gn:dem":1193,
    "gn:feature_class":"P",
    "gn:feature_code":"PPL",
    "gn:name":"Pelumba",
    "gn:population":0,
    "gn:timezone":"Africa/Luanda",
    "iso:country":"AO",
    "name:und_x_variant":[
        "Lumba",
        "Pelumba"
    ],
    "wof:name":"Pelumba",
    "wof:placetype":"locality"
},
  "geometry": {"coordinates":[20.45,-11.41667],"type":"Point"}
}