{
  "type": "Feature",
  "properties": {
    "gn:admin1_code":"19.0",
    "gn:asciiname":"Camona",
    "gn:country_code":"AO",
    "gn:dem":178,
    "gn:feature_class":"P",
    "gn:feature_code":"PPL",
    "gn:name":"Camona",
    "gn:population":0,
    "gn:timezone":"Africa/Luanda",
    "iso:country":"AO",
    "wof:name":"Camona",
    "wof:placetype":"locality"
},
  "geometry": {"coordinates":[13.75046,-9.85913],"type":"Point"}
}