{
  "type": "Feature",
  "properties": {
    "gn:admin1_code":"12.0",
    "gn:asciiname":"Quingungo",
    "gn:country_code":"AO",
    "gn:dem":955,
    "gn:feature_class":"P",
    "gn:feature_code":"PPL",
    "gn:name":"Quingungo",
    "gn:population":0,
    "gn:timezone":"Africa/Luanda",
    "iso:country":"AO",
    "wof:name":"Quingungo",
    "wof:placetype":"locality"
},
  "geometry": {"coordinates":[15.77481,-9.16487],"type":"Point"}
}