{
  "type": "Feature",
  "properties": {
    "gn:admin1_code":"17.0",
    "gn:asciiname":"Catolo",
    "gn:country_code":"AO",
    "gn:dem":707,
    "gn:feature_class":"P",
    "gn:feature_code":"PPL",
    "gn:name":"Catolo",
    "gn:population":0,
    "gn:timezone":"Africa/Luanda",
    "iso:country":"AO",
    "wof:name":"Catolo",
    "wof:placetype":"locality"
},
  "geometry": {"coordinates":[17.58333,-8.58333],"type":"Point"}
}