{
  "type": "Feature",
  "properties": {
    "gn:admin1_code":"17.0",
    "gn:asciiname":"Tchicalanga",
    "gn:country_code":"AO",
    "gn:dem":765,
    "gn:feature_class":"P",
    "gn:feature_code":"PPL",
    "gn:name":"Tchicalanga",
    "gn:population":0,
    "gn:timezone":"Africa/Luanda",
    "iso:country":"AO",
    "wof:name":"Tchicalanga",
    "wof:placetype":"locality"
},
  "geometry": {"coordinates":[17.9898,-8.64161],"type":"Point"}
}