{
  "type": "Feature",
  "properties": {
    "gn:admin1_code":"4.0",
    "gn:asciiname":"Chiriquima",
    "gn:cc2":"AO",
    "gn:country_code":"AO",
    "gn:dem":1144,
    "gn:feature_class":"P",
    "gn:feature_code":"PPL",
    "gn:name":"Chiriquima",
    "gn:population":0,
    "gn:timezone":"Africa/Luanda",
    "iso:country":"AO",
    "name:und_x_variant":[
        "Chiquelequele",
        "Chiriquima"
    ],
    "wof:name":"Chiriquima",
    "wof:placetype":"locality"
},
  "geometry": {"coordinates":[19.08333,-16.73333],"type":"Point"}
}