{
  "type": "Feature",
  "properties": {
    "gn:admin1_code":"17.0",
    "gn:asciiname":"Cajamba",
    "gn:country_code":"AO",
    "gn:dem":856,
    "gn:feature_class":"P",
    "gn:feature_code":"PPL",
    "gn:name":"Cajamba",
    "gn:population":0,
    "gn:timezone":"Africa/Luanda",
    "iso:country":"AO",
    "wof:name":"Cajamba",
    "wof:placetype":"locality"
},
  "geometry": {"coordinates":[20.82673,-8.42841],"type":"Point"}
}