{
  "type": "Feature",
  "properties": {
    "gn:admin1_code":"15.0",
    "gn:asciiname":"Quimbidi",
    "gn:country_code":"AO",
    "gn:dem":904,
    "gn:feature_class":"P",
    "gn:feature_code":"PPL",
    "gn:name":"Quimbidi",
    "gn:population":0,
    "gn:timezone":"Africa/Luanda",
    "iso:country":"AO",
    "wof:name":"Quimbidi",
    "wof:placetype":"locality"
},
  "geometry": {"coordinates":[15.86972,-6.60737],"type":"Point"}
}