{
  "type": "Feature",
  "properties": {
    "gn:admin1_code":"15.0",
    "gn:asciiname":"Quivulo",
    "gn:country_code":"AO",
    "gn:dem":1031,
    "gn:feature_class":"P",
    "gn:feature_code":"PPL",
    "gn:name":"Quivulo",
    "gn:population":0,
    "gn:timezone":"Africa/Luanda",
    "iso:country":"AO",
    "wof:name":"Quivulo",
    "wof:placetype":"locality"
},
  "geometry": {"coordinates":[15.27266,-6.88165],"type":"Point"}
}