{
  "type": "Feature",
  "properties": {
    "gn:admin1_code":"15.0",
    "gn:asciiname":"Quigonga Cavanga",
    "gn:cc2":"AO",
    "gn:country_code":"AO",
    "gn:dem":784,
    "gn:feature_class":"P",
    "gn:feature_code":"PPL",
    "gn:name":"Quigonga Cavanga",
    "gn:population":0,
    "gn:timezone":"Africa/Luanda",
    "iso:country":"AO",
    "name:und_x_variant":[
        "Quingonga",
        "Quigonga Cavanga"
    ],
    "wof:name":"Quigonga Cavanga",
    "wof:placetype":"locality"
},
  "geometry": {"coordinates":[14.86667,-8.15],"type":"Point"}
}