{
  "type": "Feature",
  "properties": {
    "gn:admin1_code":"19.0",
    "gn:asciiname":"Muquiama Samba",
    "gn:country_code":"AO",
    "gn:dem":607,
    "gn:feature_class":"P",
    "gn:feature_code":"PPL",
    "gn:name":"Muquiama Samba",
    "gn:population":0,
    "gn:timezone":"Africa/Luanda",
    "iso:country":"AO",
    "name:und_x_variant":[
        "Maquiama Samba",
        "Muquiama Samba"
    ],
    "wof:name":"Muquiama Samba",
    "wof:placetype":"locality"
},
  "geometry": {"coordinates":[14.37652,-8.56892],"type":"Point"}
}