{
  "type": "Feature",
  "properties": {
    "gn:admin1_code":"12.0",
    "gn:asciiname":"Cauaha",
    "gn:country_code":"AO",
    "gn:dem":1146,
    "gn:feature_class":"P",
    "gn:feature_code":"PPL",
    "gn:name":"Cau\u00e1ha",
    "gn:population":0,
    "gn:timezone":"Africa/Luanda",
    "iso:country":"AO",
    "name:und_x_variant":[
        "Cav\u00e1",
        "Cau\u00e1",
        "Cau\u00e1ha"
    ],
    "wof:name":"Cauaha",
    "wof:placetype":"locality"
},
  "geometry": {"coordinates":[15.92064,-8.93681],"type":"Point"}
}