{
  "type": "Feature",
  "properties": {
    "gn:admin1_code":"1.0",
    "gn:asciiname":"Quivaluca",
    "gn:country_code":"AO",
    "gn:dem":784,
    "gn:feature_class":"P",
    "gn:feature_code":"PPL",
    "gn:name":"Quivaluca",
    "gn:population":0,
    "gn:timezone":"Africa/Luanda",
    "iso:country":"AO",
    "wof:name":"Quivaluca",
    "wof:placetype":"locality"
},
  "geometry": {"coordinates":[14.21667,-12.71667],"type":"Point"}
}