{
  "type": "Feature",
  "properties": {
    "gn:admin1_code":"6.0",
    "gn:asciiname":"Zumba",
    "gn:country_code":"AO",
    "gn:dem":1264,
    "gn:feature_class":"P",
    "gn:feature_code":"PPL",
    "gn:name":"Zumba",
    "gn:population":0,
    "gn:timezone":"Africa/Luanda",
    "iso:country":"AO",
    "name:und_x_variant":[
        "Fundahanga",
        "Zumba"
    ],
    "wof:name":"Zumba",
    "wof:placetype":"locality"
},
  "geometry": {"coordinates":[15.11596,-10.70985],"type":"Point"}
}