{
  "type": "Feature",
  "properties": {
    "gn:admin1_code":"6.0",
    "gn:asciiname":"Zumba",
    "gn:country_code":"AO",
    "gn:dem":1264,
    "gn:feature_class":"P",
    "gn:feature_code":"PPL",
    "gn:name":"Zumba",
    "gn:population":0,
    "gn:timezone":"Africa/Luanda",
    "iso:country":"AO",
    "name:ara_x_preferred":[
        "\u0632\u0648\u0645\u0628\u0627"
    ],
    "name:bel_x_preferred":[
        "\u0417\u0443\u043c\u0431\u0430"
    ],
    "name:bul_x_preferred":[
        "\u0417\u0443\u043c\u0431\u0430"
    ],
    "name:cat_x_preferred":[
        "Zumba"
    ],
    "name:ces_x_preferred":[
        "Zumba"
    ],
    "name:deu_x_preferred":[
        "Zumba"
    ],
    "name:est_x_preferred":[
        "Zumba"
    ],
    "name:fas_x_preferred":[
        "\u0632\u0648\u0645\u0628\u0627"
    ],
    "name:fin_x_preferred":[
        "Zumba"
    ],
    "name:fra_x_preferred":[
        "Zumba"
    ],
    "name:glg_x_preferred":[
        "Zumba"
    ],
    "name:heb_x_preferred":[
        "\u05d6\u05d5\u05de\u05d1\u05d4"
    ],
    "name:hun_x_preferred":[
        "Zumba"
    ],
    "name:ita_x_preferred":[
        "Zumba"
    ],
    "name:jpn_x_preferred":[
        "\u30ba\u30f3\u30d0"
    ],
    "name:mal_x_preferred":[
        "\u0d38\u0d41\u0d02\u0d2c"
    ],
    "name:nld_x_preferred":[
        "Zumba"
    ],
    "name:nno_x_preferred":[
        "Zumba"
    ],
    "name:nor_x_preferred":[
        "Zumba"
    ],
    "name:pol_x_preferred":[
        "Zumba"
    ],
    "name:por_x_preferred":[
        "Zumba"
    ],
    "name:ron_x_preferred":[
        "Zumba"
    ],
    "name:rus_x_preferred":[
        "\u0417\u0443\u043c\u0431\u0430"
    ],
    "name:slk_x_preferred":[
        "Zumba"
    ],
    "name:slv_x_preferred":[
        "Zumba"
    ],
    "name:spa_x_preferred":[
        "Zumba"
    ],
    "name:swe_x_preferred":[
        "Zumba"
    ],
    "name:tur_x_preferred":[
        "Zumba"
    ],
    "name:und_x_variant":[
        "Fundahanga",
        "Zumba"
    ],
    "name:urd_x_preferred":[
        "\u0632\u0648\u0645\u0628\u0627"
    ],
    "wof:name":"Zumba",
    "wof:placetype":"locality"
},
  "geometry": {"coordinates":[15.11596,-10.70985],"type":"Point"}
}