{
  "type": "Feature",
  "properties": {
    "gn:admin1_code":"14.0",
    "gn:asciiname":"Camissevo",
    "gn:cc2":"AO",
    "gn:country_code":"AO",
    "gn:dem":1123,
    "gn:feature_class":"P",
    "gn:feature_code":"PPL",
    "gn:name":"Camissevo",
    "gn:population":0,
    "gn:timezone":"Africa/Luanda",
    "iso:country":"AO",
    "name:und_x_variant":[
        "Chacassiba",
        "Camissevo"
    ],
    "wof:name":"Camissevo",
    "wof:placetype":"locality"
},
  "geometry": {"coordinates":[21.25,-12.91667],"type":"Point"}
}