{
  "type": "Feature",
  "properties": {
    "gn:admin1_code":"19.0",
    "gn:asciiname":"Gavumo",
    "gn:country_code":"AO",
    "gn:dem":182,
    "gn:feature_class":"P",
    "gn:feature_code":"PPL",
    "gn:name":"Gavumo",
    "gn:population":0,
    "gn:timezone":"Africa/Luanda",
    "iso:country":"AO",
    "wof:name":"Gavumo",
    "wof:placetype":"locality"
},
  "geometry": {"coordinates":[13.71667,-9.81667],"type":"Point"}
}