{
  "type": "Feature",
  "properties": {
    "gn:admin1_code":"12.0",
    "gn:asciiname":"Cangingo Valodia",
    "gn:country_code":"AO",
    "gn:dem":1023,
    "gn:feature_class":"P",
    "gn:feature_code":"PPL",
    "gn:name":"Cangingo Val\u00f4dia",
    "gn:population":0,
    "gn:timezone":"Africa/Luanda",
    "iso:country":"AO",
    "wof:name":"Cangingo Valodia",
    "wof:placetype":"locality"
},
  "geometry": {"coordinates":[15.61386,-9.38979],"type":"Point"}
}