{
  "type": "Feature",
  "properties": {
    "gn:admin1_code":"12.0",
    "gn:asciiname":"Decimo Primeiro de Novembro",
    "gn:country_code":"AO",
    "gn:dem":699,
    "gn:feature_class":"P",
    "gn:feature_code":"PPL",
    "gn:name":"D\u00e9cimo Primeiro de Novembro",
    "gn:population":0,
    "gn:timezone":"Africa/Luanda",
    "iso:country":"AO",
    "wof:name":"Decimo Primeiro de Novembro",
    "wof:placetype":"locality"
},
  "geometry": {"coordinates":[16.56119,-7.67835],"type":"Point"}
}