{
  "type": "Feature",
  "properties": {
    "gn:admin1_code":"18.0",
    "gn:asciiname":"Cassai-Fana",
    "gn:country_code":"AO",
    "gn:dem":1078,
    "gn:feature_class":"P",
    "gn:feature_code":"PPL",
    "gn:name":"Cassai-Fana",
    "gn:population":0,
    "gn:timezone":"Africa/Luanda",
    "iso:country":"AO",
    "name:und_x_variant":[
        "Tonga",
        "Cassai Sul",
        "Cassai",
        "Cassai-Fana"
    ],
    "wof:name":"Cassai-Fana",
    "wof:placetype":"locality"
},
  "geometry": {"coordinates":[21.96974,-10.58891],"type":"Point"}
}