{
  "type": "Feature",
  "properties": {
    "gn:admin1_code":"9.0",
    "gn:asciiname":"Napoleao",
    "gn:country_code":"AO",
    "gn:dem":1418,
    "gn:feature_class":"P",
    "gn:feature_code":"PPLL",
    "gn:name":"Napole\u00e3o",
    "gn:population":0,
    "gn:timezone":"Africa/Luanda",
    "iso:country":"AO",
    "wof:name":"Napoleao",
    "wof:placetype":"locality"
},
  "geometry": {"coordinates":[15.81502,-14.84144],"type":"Point"}
}