{
  "type": "Feature",
  "properties": {
    "gn:admin1_code":"17.0",
    "gn:asciiname":"Prospeccao",
    "gn:country_code":"AO",
    "gn:dem":964,
    "gn:feature_class":"P",
    "gn:feature_code":"PPL",
    "gn:name":"Prospec\u00e7\u00e3o",
    "gn:population":0,
    "gn:timezone":"Africa/Luanda",
    "iso:country":"AO",
    "wof:name":"Prospeccao",
    "wof:placetype":"locality"
},
  "geometry": {"coordinates":[20.4729,-8.31076],"type":"Point"}
}