{
  "type": "Feature",
  "properties": {
    "gn:admin1_code":"18.0",
    "gn:asciiname":"Samanenga",
    "gn:cc2":"AO",
    "gn:country_code":"AO",
    "gn:dem":881,
    "gn:feature_class":"P",
    "gn:feature_code":"PPL",
    "gn:name":"Samanenga",
    "gn:population":0,
    "gn:timezone":"Africa/Luanda",
    "iso:country":"AO",
    "name:und_x_variant":[
        "Cauhama",
        "Samanenga"
    ],
    "wof:name":"Samanenga",
    "wof:placetype":"locality"
},
  "geometry": {"coordinates":[21.15,-9.13333],"type":"Point"}
}