{
  "type": "Feature",
  "properties": {
    "gn:admin1_code":"19.0",
    "gn:asciiname":"Cacanda",
    "gn:country_code":"AO",
    "gn:dem":630,
    "gn:feature_class":"P",
    "gn:feature_code":"PPL",
    "gn:name":"Cacanda",
    "gn:population":0,
    "gn:timezone":"Africa/Luanda",
    "iso:country":"AO",
    "wof:name":"Cacanda",
    "wof:placetype":"locality"
},
  "geometry": {"coordinates":[14.48338,-8.70069],"type":"Point"}
}