{
  "type": "Feature",
  "properties": {
    "gn:admin1_code":"6.0",
    "gn:asciiname":"Mulengue",
    "gn:country_code":"AO",
    "gn:dem":1160,
    "gn:feature_class":"P",
    "gn:feature_code":"PPL",
    "gn:name":"Mulengue",
    "gn:population":0,
    "gn:timezone":"Africa/Luanda",
    "iso:country":"AO",
    "wof:name":"Mulengue",
    "wof:placetype":"locality"
},
  "geometry": {"coordinates":[14.65846,-10.72541],"type":"Point"}
}