{
  "type": "Feature",
  "properties": {
    "gn:admin1_code":"8.0",
    "gn:asciiname":"Tchilela",
    "gn:country_code":"AO",
    "gn:dem":1627,
    "gn:feature_class":"P",
    "gn:feature_code":"PPL",
    "gn:name":"Tchilela",
    "gn:population":0,
    "gn:timezone":"Africa/Luanda",
    "iso:country":"AO",
    "wof:name":"Tchilela",
    "wof:placetype":"locality"
},
  "geometry": {"coordinates":[15.45694,-12.56972],"type":"Point"}
}