{
  "type": "Feature",
  "properties": {
    "gn:admin1_code":"17.0",
    "gn:asciiname":"Manuel Angola",
    "gn:country_code":"AO",
    "gn:dem":880,
    "gn:feature_class":"P",
    "gn:feature_code":"PPL",
    "gn:name":"Manuel Angola",
    "gn:population":0,
    "gn:timezone":"Africa/Luanda",
    "iso:country":"AO",
    "wof:name":"Manuel Angola",
    "wof:placetype":"locality"
},
  "geometry": {"coordinates":[18.01659,-9.15637],"type":"Point"}
}