{
  "type": "Feature",
  "properties": {
    "gn:admin1_code":"6.0",
    "gn:asciiname":"Capolo",
    "gn:country_code":"AO",
    "gn:dem":1417,
    "gn:feature_class":"P",
    "gn:feature_code":"PPL",
    "gn:name":"Cap\u00f4lo",
    "gn:population":0,
    "gn:timezone":"Africa/Luanda",
    "iso:country":"AO",
    "wof:name":"Capolo",
    "wof:placetype":"locality"
},
  "geometry": {"coordinates":[14.84772,-11.57621],"type":"Point"}
}