{
  "type": "Feature",
  "properties": {
    "gn:admin1_code":"2.0",
    "gn:asciiname":"Cunhomola",
    "gn:country_code":"AO",
    "gn:dem":1527,
    "gn:feature_class":"P",
    "gn:feature_code":"PPL",
    "gn:name":"Cunhomola",
    "gn:population":0,
    "gn:timezone":"Africa/Luanda",
    "iso:country":"AO",
    "wof:name":"Cunhomola",
    "wof:placetype":"locality"
},
  "geometry": {"coordinates":[17.12022,-11.45505],"type":"Point"}
}