{
  "type": "Feature",
  "properties": {
    "gn:admin1_code":"15.0",
    "gn:asciiname":"Munvundo",
    "gn:country_code":"AO",
    "gn:dem":598,
    "gn:feature_class":"P",
    "gn:feature_code":"PPL",
    "gn:name":"Munvundo",
    "gn:population":0,
    "gn:timezone":"Africa/Luanda",
    "iso:country":"AO",
    "wof:name":"Munvundo",
    "wof:placetype":"locality"
},
  "geometry": {"coordinates":[16.28226,-6.15472],"type":"Point"}
}