{
  "type": "Feature",
  "properties": {
    "gn:admin1_code":"16.0",
    "gn:asciiname":"Luata",
    "gn:country_code":"AO",
    "gn:dem":979,
    "gn:feature_class":"P",
    "gn:feature_code":"PPL",
    "gn:name":"Luata",
    "gn:population":0,
    "gn:timezone":"Africa/Luanda",
    "iso:country":"AO",
    "wof:name":"Luata",
    "wof:placetype":"locality"
},
  "geometry": {"coordinates":[14.88333,-6.23333],"type":"Point"}
}