{
  "type": "Feature",
  "properties": {
    "gn:admin1_code":"15.0",
    "gn:asciiname":"Babi",
    "gn:country_code":"AO",
    "gn:dem":916,
    "gn:feature_class":"P",
    "gn:feature_code":"PPL",
    "gn:name":"Babi",
    "gn:population":0,
    "gn:timezone":"Africa/Luanda",
    "iso:country":"AO",
    "name:cat_x_preferred":[
        "Babi"
    ],
    "name:ceb_x_preferred":[
        "Babi"
    ],
    "name:deu_x_preferred":[
        "Babi"
    ],
    "name:ind_x_preferred":[
        "Babi"
    ],
    "name:ita_x_preferred":[
        "Babi"
    ],
    "name:por_x_preferred":[
        "Babi"
    ],
    "name:spa_x_preferred":[
        "Babi"
    ],
    "name:swe_x_preferred":[
        "Babi"
    ],
    "name:und_x_variant":[
        "Caquengue Babi"
    ],
    "wof:name":"Babi",
    "wof:placetype":"locality"
},
  "geometry": {"coordinates":[15.08415,-7.54324],"type":"Point"}
}