{
  "type": "Feature",
  "properties": {
    "gn:admin1_code":"19.0",
    "gn:asciiname":"Catuto",
    "gn:country_code":"AO",
    "gn:dem":131,
    "gn:feature_class":"P",
    "gn:feature_code":"PPL",
    "gn:name":"Catuto",
    "gn:population":0,
    "gn:timezone":"Africa/Luanda",
    "iso:country":"AO",
    "wof:name":"Catuto",
    "wof:placetype":"locality"
},
  "geometry": {"coordinates":[14.28333,-9.95],"type":"Point"}
}