{
  "type": "Feature",
  "properties": {
    "gn:admin1_code":"19.0",
    "gn:asciiname":"Quissari",
    "gn:cc2":"AO",
    "gn:country_code":"AO",
    "gn:dem":17,
    "gn:feature_class":"P",
    "gn:feature_code":"PPL",
    "gn:name":"Quissari",
    "gn:population":0,
    "gn:timezone":"Africa/Luanda",
    "iso:country":"AO",
    "name:und_x_variant":[
        "Quiss\u00e1di",
        "Quissari"
    ],
    "wof:name":"Quissari",
    "wof:placetype":"locality"
},
  "geometry": {"coordinates":[13.61139,-8.60917],"type":"Point"}
}