{
  "type": "Feature",
  "properties": {
    "gn:admin1_code":"6.0",
    "gn:asciiname":"Malanca",
    "gn:country_code":"AO",
    "gn:dem":1394,
    "gn:feature_class":"P",
    "gn:feature_code":"PPL",
    "gn:name":"Malanca",
    "gn:population":0,
    "gn:timezone":"Africa/Luanda",
    "iso:country":"AO",
    "name:deu_x_preferred":[
        "Malanca"
    ],
    "name:ita_x_preferred":[
        "Malanca"
    ],
    "name:nld_x_preferred":[
        "Malanca"
    ],
    "wof:name":"Malanca",
    "wof:placetype":"locality"
},
  "geometry": {"coordinates":[15.25,-11.68333],"type":"Point"}
}