{
  "type": "Feature",
  "properties": {
    "gn:admin1_code":"2.0",
    "gn:asciiname":"Caserva",
    "gn:cc2":"AO",
    "gn:country_code":"AO",
    "gn:dem":1419,
    "gn:feature_class":"P",
    "gn:feature_code":"PPL",
    "gn:name":"Caserva",
    "gn:population":0,
    "gn:timezone":"Africa/Luanda",
    "iso:country":"AO",
    "name:und_x_variant":[
        "Caseroa",
        "Caserva"
    ],
    "wof:name":"Caserva",
    "wof:placetype":"locality"
},
  "geometry": {"coordinates":[17.43333,-13.13333],"type":"Point"}
}