{
  "type": "Feature",
  "properties": {
    "gn:admin1_code":"6.0",
    "gn:asciiname":"Donda",
    "gn:country_code":"AO",
    "gn:dem":76,
    "gn:feature_class":"P",
    "gn:feature_code":"PPL",
    "gn:name":"Donda",
    "gn:population":0,
    "gn:timezone":"Africa/Luanda",
    "iso:country":"AO",
    "name:ceb_x_preferred":[
        "Donda"
    ],
    "name:deu_x_preferred":[
        "Donda"
    ],
    "name:spa_x_preferred":[
        "Donda"
    ],
    "name:swe_x_preferred":[
        "Donda"
    ],
    "wof:name":"Donda",
    "wof:placetype":"locality"
},
  "geometry": {"coordinates":[14.0255,-10.76736],"type":"Point"}
}