{
  "type": "Feature",
  "properties": {
    "gn:admin1_code":"6.0",
    "gn:asciiname":"Lussusso",
    "gn:country_code":"AO",
    "gn:dem":1134,
    "gn:feature_class":"P",
    "gn:feature_code":"PPL",
    "gn:name":"Lussusso",
    "gn:population":0,
    "gn:timezone":"Africa/Luanda",
    "iso:country":"AO",
    "wof:name":"Lussusso",
    "wof:placetype":"locality"
},
  "geometry": {"coordinates":[14.8114,-10.22278],"type":"Point"}
}