{
  "type": "Feature",
  "properties": {
    "gn:admin1_code":"16.0",
    "gn:asciiname":"Tomboco",
    "gn:country_code":"AO",
    "gn:dem":534,
    "gn:feature_class":"P",
    "gn:feature_code":"PPL",
    "gn:name":"Tomboco",
    "gn:population":0,
    "gn:timezone":"Africa/Luanda",
    "iso:country":"AO",
    "name:cat_x_preferred":[
        "Tomboco"
    ],
    "name:deu_x_preferred":[
        "Tomboco"
    ],
    "name:fra_x_preferred":[
        "Tomboco"
    ],
    "name:ita_x_preferred":[
        "Tomboco"
    ],
    "name:msa_x_preferred":[
        "Tomboco"
    ],
    "name:por_x_preferred":[
        "Tomboco"
    ],
    "name:spa_x_preferred":[
        "Tomboco"
    ],
    "name:zho_x_preferred":[
        "\u901a\u535a\u79d1"
    ],
    "wof:name":"Tomboco",
    "wof:placetype":"locality"
},
  "geometry": {"coordinates":[14.61667,-6.13333],"type":"Point"}
}