{
  "type": "Feature",
  "properties": {
    "gn:admin1_code":"6.0",
    "gn:asciiname":"Cambuze",
    "gn:country_code":"AO",
    "gn:dem":1349,
    "gn:feature_class":"P",
    "gn:feature_code":"PPL",
    "gn:name":"Cambuze",
    "gn:population":0,
    "gn:timezone":"Africa/Luanda",
    "iso:country":"AO",
    "wof:name":"Cambuze",
    "wof:placetype":"locality"
},
  "geometry": {"coordinates":[16.06349,-10.46414],"type":"Point"}
}