{
  "type": "Feature",
  "properties": {
    "gn:admin1_code":"1.0",
    "gn:asciiname":"Catala",
    "gn:country_code":"AO",
    "gn:dem":680,
    "gn:feature_class":"P",
    "gn:feature_code":"PPL",
    "gn:name":"Catala",
    "gn:population":0,
    "gn:timezone":"Africa/Luanda",
    "iso:country":"AO",
    "wof:name":"Catala",
    "wof:placetype":"locality"
},
  "geometry": {"coordinates":[14.01667,-12.88333],"type":"Point"}
}