{
  "type": "Feature",
  "properties": {
    "gn:admin1_code":"5.0",
    "gn:asciiname":"Muenembala",
    "gn:cc2":"AO",
    "gn:country_code":"AO",
    "gn:dem":581,
    "gn:feature_class":"P",
    "gn:feature_code":"PPL",
    "gn:name":"Muenembala",
    "gn:population":0,
    "gn:timezone":"Africa/Luanda",
    "iso:country":"AO",
    "name:und_x_variant":[
        "Muenebala",
        "Muenembala"
    ],
    "wof:name":"Muenembala",
    "wof:placetype":"locality"
},
  "geometry": {"coordinates":[14.71667,-9.03333],"type":"Point"}
}