{
  "type": "Feature",
  "properties": {
    "gn:admin1_code":"2.0",
    "gn:asciiname":"Vinuco",
    "gn:cc2":"AO",
    "gn:country_code":"AO",
    "gn:dem":1303,
    "gn:feature_class":"P",
    "gn:feature_code":"PPL",
    "gn:name":"Vinuco",
    "gn:population":0,
    "gn:timezone":"Africa/Luanda",
    "iso:country":"AO",
    "name:und_x_variant":[
        "Vicungo",
        "Vinuco"
    ],
    "wof:name":"Vinuco",
    "wof:placetype":"locality"
},
  "geometry": {"coordinates":[17.66667,-12.01667],"type":"Point"}
}