{
  "type": "Feature",
  "properties": {
    "gn:admin1_code":"2.0",
    "gn:asciiname":"Sambungo",
    "gn:country_code":"AO",
    "gn:dem":1684,
    "gn:feature_class":"P",
    "gn:feature_code":"PPL",
    "gn:name":"Sambungo",
    "gn:population":0,
    "gn:timezone":"Africa/Luanda",
    "iso:country":"AO",
    "wof:name":"Sambungo",
    "wof:placetype":"locality"
},
  "geometry": {"coordinates":[17.03343,-11.25166],"type":"Point"}
}