{
  "type": "Feature",
  "properties": {
    "gn:admin1_code":"12.0",
    "gn:asciiname":"Pata",
    "gn:country_code":"AO",
    "gn:dem":1059,
    "gn:feature_class":"P",
    "gn:feature_code":"PPL",
    "gn:name":"Pata",
    "gn:population":0,
    "gn:timezone":"Africa/Luanda",
    "iso:country":"AO",
    "name:ceb_x_preferred":[
        "Pata"
    ],
    "name:ces_x_preferred":[
        "Pata"
    ],
    "name:epo_x_preferred":[
        "Pata"
    ],
    "name:fin_x_preferred":[
        "Pata"
    ],
    "name:fra_x_preferred":[
        "Pata"
    ],
    "name:hun_x_preferred":[
        "Pata"
    ],
    "name:ita_x_preferred":[
        "Pata"
    ],
    "name:kor_x_preferred":[
        "\ud30c\ud0c0"
    ],
    "name:por_x_preferred":[
        "Pata"
    ],
    "name:que_x_preferred":[
        "Pata"
    ],
    "name:sco_x_preferred":[
        "Pata"
    ],
    "name:spa_x_preferred":[
        "Pata"
    ],
    "name:swe_x_preferred":[
        "Pata"
    ],
    "name:war_x_preferred":[
        "Pata"
    ],
    "wof:name":"Pata",
    "wof:placetype":"locality"
},
  "geometry": {"coordinates":[16.70576,-10.28963],"type":"Point"}
}