{
  "type": "Feature",
  "properties": {
    "gn:admin1_code":"12.0",
    "gn:asciiname":"Pata",
    "gn:country_code":"AO",
    "gn:dem":1059,
    "gn:feature_class":"P",
    "gn:feature_code":"PPL",
    "gn:name":"Pata",
    "gn:population":0,
    "gn:timezone":"Africa/Luanda",
    "iso:country":"AO",
    "wof:name":"Pata",
    "wof:placetype":"locality"
},
  "geometry": {"coordinates":[16.70576,-10.28963],"type":"Point"}
}