{
  "type": "Feature",
  "properties": {
    "gn:admin1_code":"5.0",
    "gn:asciiname":"Chicuandala",
    "gn:country_code":"AO",
    "gn:dem":1209,
    "gn:feature_class":"P",
    "gn:feature_code":"PPL",
    "gn:name":"Chicuandala",
    "gn:population":0,
    "gn:timezone":"Africa/Luanda",
    "iso:country":"AO",
    "name:und_x_variant":[
        "Chico Andala",
        "Chicuandala"
    ],
    "wof:name":"Chicuandala",
    "wof:placetype":"locality"
},
  "geometry": {"coordinates":[15.64163,-8.86059],"type":"Point"}
}