{
  "type": "Feature",
  "properties": {
    "gn:admin1_code":"15.0",
    "gn:asciiname":"Ngunga",
    "gn:country_code":"AO",
    "gn:dem":983,
    "gn:feature_class":"P",
    "gn:feature_code":"PPL",
    "gn:name":"Ngunga",
    "gn:population":0,
    "gn:timezone":"Africa/Luanda",
    "iso:country":"AO",
    "wof:name":"Ngunga",
    "wof:placetype":"locality"
},
  "geometry": {"coordinates":[15.93407,-6.98489],"type":"Point"}
}