{
  "type": "Feature",
  "properties": {
    "gn:admin1_code":"19.0",
    "gn:asciiname":"Guela",
    "gn:country_code":"AO",
    "gn:dem":112,
    "gn:feature_class":"P",
    "gn:feature_code":"PPL",
    "gn:name":"Guela",
    "gn:population":0,
    "gn:timezone":"Africa/Luanda",
    "iso:country":"AO",
    "wof:name":"Guela",
    "wof:placetype":"locality"
},
  "geometry": {"coordinates":[14.01067,-9.90249],"type":"Point"}
}