{
  "type": "Feature",
  "properties": {
    "gn:admin1_code":"6.0",
    "gn:asciiname":"Ebo",
    "gn:country_code":"AO",
    "gn:dem":1369,
    "gn:feature_class":"P",
    "gn:feature_code":"PPL",
    "gn:name":"Ebo",
    "gn:population":0,
    "gn:timezone":"Africa/Luanda",
    "iso:country":"AO",
    "name:und_x_variant":[
        "Hebo",
        "Ebo"
    ],
    "wof:name":"Ebo",
    "wof:placetype":"locality"
},
  "geometry": {"coordinates":[14.69501,-11.04501],"type":"Point"}
}