{
  "type": "Feature",
  "properties": {
    "gn:admin1_code":"12.0",
    "gn:asciiname":"Ndala Maquita Segundo",
    "gn:country_code":"AO",
    "gn:dem":1156,
    "gn:feature_class":"P",
    "gn:feature_code":"PPL",
    "gn:name":"Ndala Maquita Segundo",
    "gn:population":0,
    "gn:timezone":"Africa/Luanda",
    "iso:country":"AO",
    "wof:name":"Ndala Maquita Segundo",
    "wof:placetype":"locality"
},
  "geometry": {"coordinates":[17.09461,-9.22244],"type":"Point"}
}