{
  "type": "Feature",
  "properties": {
    "gn:admin1_code":"2.0",
    "gn:asciiname":"Quisseque",
    "gn:country_code":"AO",
    "gn:dem":1731,
    "gn:feature_class":"P",
    "gn:feature_code":"PPL",
    "gn:name":"Quisseque",
    "gn:population":0,
    "gn:timezone":"Africa/Luanda",
    "iso:country":"AO",
    "name:deu_x_preferred":[
        "Quisseque"
    ],
    "name:por_x_preferred":[
        "Quisseque"
    ],
    "wof:name":"Quisseque",
    "wof:placetype":"locality"
},
  "geometry": {"coordinates":[17.05087,-11.85679],"type":"Point"}
}