{
  "type": "Feature",
  "properties": {
    "gn:admin1_code":"14.0",
    "gn:asciiname":"Mocovoto",
    "gn:cc2":"AO",
    "gn:country_code":"AO",
    "gn:dem":1210,
    "gn:feature_class":"P",
    "gn:feature_code":"PPL",
    "gn:name":"Mocovoto",
    "gn:population":0,
    "gn:timezone":"Africa/Luanda",
    "iso:country":"AO",
    "name:und_x_variant":[
        "Macoboto",
        "Mocovoto"
    ],
    "wof:name":"Mocovoto",
    "wof:placetype":"locality"
},
  "geometry": {"coordinates":[20.43333,-13.75],"type":"Point"}
}