{
  "type": "Feature",
  "properties": {
    "gn:admin1_code":"8.0",
    "gn:asciiname":"Vale do Vindica",
    "gn:country_code":"AO",
    "gn:dem":1611,
    "gn:feature_class":"P",
    "gn:feature_code":"PPL",
    "gn:name":"Vale do Vindica",
    "gn:population":0,
    "gn:timezone":"Africa/Luanda",
    "iso:country":"AO",
    "wof:name":"Vale do Vindica",
    "wof:placetype":"locality"
},
  "geometry": {"coordinates":[15.46917,-12.55028],"type":"Point"}
}