{
  "type": "Feature",
  "properties": {
    "gn:admin1_code":"12.0",
    "gn:asciiname":"Numbafo",
    "gn:country_code":"AO",
    "gn:dem":1139,
    "gn:feature_class":"P",
    "gn:feature_code":"PPL",
    "gn:name":"Numbafo",
    "gn:population":0,
    "gn:timezone":"Africa/Luanda",
    "iso:country":"AO",
    "wof:name":"Numbafo",
    "wof:placetype":"locality"
},
  "geometry": {"coordinates":[16.29911,-9.08658],"type":"Point"}
}