{
  "type": "Feature",
  "properties": {
    "gn:admin1_code":"4.0",
    "gn:asciiname":"Maongo",
    "gn:country_code":"AO",
    "gn:dem":1228,
    "gn:feature_class":"P",
    "gn:feature_code":"PPL",
    "gn:name":"Maongo",
    "gn:population":0,
    "gn:timezone":"Africa/Luanda",
    "iso:country":"AO",
    "wof:name":"Maongo",
    "wof:placetype":"locality"
},
  "geometry": {"coordinates":[19.75,-15.58333],"type":"Point"}
}