{
  "type": "Feature",
  "properties": {
    "iso:country":"AO",
    "name:ceb_x_preferred":[
        "Cubal"
    ],
    "name:eng_x_preferred":[
        "Rio Quicombo"
    ],
    "name:nob_x_preferred":[
        "Quicombo"
    ],
    "name:por_x_preferred":[
        "Rio Cubal-Quicombo"
    ],
    "name:rus_x_preferred":[
        "\u041a\u0438\u043a\u043e\u043c\u0431\u043e"
    ],
    "name:swe_x_preferred":[
        "Cubal"
    ],
    "name:und_x_variant":[
        "Kikombo"
    ],
    "name:zho_x_preferred":[
        "\u57fa\u5b54\u535a\u6cb3"
    ],
    "qs:gn_country":"AO",
    "qs:gn_fcode":"PPL",
    "qs:gn_pop":0,
    "qs:name":"Quicombo",
    "qs:name_adm0":"Angola",
    "qs:name_adm1":"Cuanza Sul",
    "qs:photos":16,
    "qs:photos_1k":3,
    "qs:photos_9k":1,
    "qs:photos_9r":1,
    "qs:photos_all":16,
    "qs:photos_sr":1,
    "qs:placetype":"Town",
    "qs:pop_sr":"0",
    "qs:woe_adm0":23424745,
    "wd:wordcount":43,
    "wof:name":"Quicombo",
    "wof:placetype":"locality"
},
  "geometry": {"coordinates":[13.81671,-11.31944],"type":"Point"}
}