{
  "type": "Feature",
  "properties": {
    "gn:admin1_code":"8.0",
    "gn:asciiname":"Chipatchiva",
    "gn:country_code":"AO",
    "gn:dem":1665,
    "gn:feature_class":"P",
    "gn:feature_code":"PPL",
    "gn:name":"Chipatchiva",
    "gn:population":0,
    "gn:timezone":"Africa/Luanda",
    "iso:country":"AO",
    "wof:name":"Chipatchiva",
    "wof:placetype":"locality"
},
  "geometry": {"coordinates":[15.6725,-12.82889],"type":"Point"}
}