{
  "type": "Feature",
  "properties": {
    "gn:admin1_code":"14.0",
    "gn:asciiname":"Sandando",
    "gn:country_code":"AO",
    "gn:dem":1175,
    "gn:feature_class":"P",
    "gn:feature_code":"PPL",
    "gn:name":"Sandando",
    "gn:population":0,
    "gn:timezone":"Africa/Luanda",
    "iso:country":"AO",
    "wof:name":"Sandando",
    "wof:placetype":"locality"
},
  "geometry": {"coordinates":[20.71667,-11.66667],"type":"Point"}
}