{
  "type": "Feature",
  "properties": {
    "gn:admin1_code":"12.0",
    "gn:asciiname":"Camacundua",
    "gn:country_code":"AO",
    "gn:dem":1033,
    "gn:feature_class":"P",
    "gn:feature_code":"PPL",
    "gn:name":"Camacundua",
    "gn:population":0,
    "gn:timezone":"Africa/Luanda",
    "iso:country":"AO",
    "wof:name":"Camacundua",
    "wof:placetype":"locality"
},
  "geometry": {"coordinates":[16.27639,-9.70667],"type":"Point"}
}