{
  "type": "Feature",
  "properties": {
    "gn:admin1_code":"18.0",
    "gn:asciiname":"Cambatchiango",
    "gn:country_code":"AO",
    "gn:dem":1021,
    "gn:feature_class":"P",
    "gn:feature_code":"PPL",
    "gn:name":"Cambatchiango",
    "gn:population":0,
    "gn:timezone":"Africa/Luanda",
    "iso:country":"AO",
    "wof:name":"Cambatchiango",
    "wof:placetype":"locality"
},
  "geometry": {"coordinates":[18.74653,-10.10227],"type":"Point"}
}