{
  "type": "Feature",
  "properties": {
    "gn:admin1_code":"18.0",
    "gn:asciiname":"Morache",
    "gn:cc2":"AO",
    "gn:country_code":"AO",
    "gn:dem":1105,
    "gn:feature_class":"P",
    "gn:feature_code":"PPL",
    "gn:name":"Morache",
    "gn:population":0,
    "gn:timezone":"Africa/Luanda",
    "iso:country":"AO",
    "name:und_x_variant":[
        "Marache",
        "Morache"
    ],
    "wof:name":"Morache",
    "wof:placetype":"locality"
},
  "geometry": {"coordinates":[20.93333,-10.23333],"type":"Point"}
}