{
  "type": "Feature",
  "properties": {
    "gn:admin1_code":"2.0",
    "gn:asciiname":"Nharea",
    "gn:country_code":"AO",
    "gn:dem":1645,
    "gn:feature_class":"P",
    "gn:feature_code":"PPL",
    "gn:name":"Nhar\u00eaa",
    "gn:population":0,
    "gn:timezone":"Africa/Luanda",
    "iso:country":"AO",
    "name:und_x_variant":[
        "N\u2019Harreia",
        "Nhareia",
        "Nhar\u00eaa"
    ],
    "wof:name":"Nharea",
    "wof:placetype":"locality"
},
  "geometry": {"coordinates":[16.96496,-11.47512],"type":"Point"}
}