{
  "type": "Feature",
  "properties": {
    "gn:admin1_code":"6.0",
    "gn:asciiname":"Quicala",
    "gn:country_code":"AO",
    "gn:dem":1258,
    "gn:feature_class":"P",
    "gn:feature_code":"PPL",
    "gn:name":"Quicala",
    "gn:population":0,
    "gn:timezone":"Africa/Luanda",
    "iso:country":"AO",
    "wof:name":"Quicala",
    "wof:placetype":"locality"
},
  "geometry": {"coordinates":[15.01667,-11.18333],"type":"Point"}
}