{
  "type": "Feature",
  "properties": {
    "gn:admin1_code":"15.0",
    "gn:asciiname":"Canvuavo",
    "gn:cc2":"AO",
    "gn:country_code":"AO",
    "gn:dem":948,
    "gn:feature_class":"P",
    "gn:feature_code":"PPL",
    "gn:name":"Canvuavo",
    "gn:population":0,
    "gn:timezone":"Africa/Luanda",
    "iso:country":"AO",
    "name:und_x_variant":[
        "Kanvaubo",
        "Canvuabo",
        "Cavuavo",
        "Canvuavo"
    ],
    "wof:name":"Canvuavo",
    "wof:placetype":"locality"
},
  "geometry": {"coordinates":[15.86667,-6.78333],"type":"Point"}
}