{
  "type": "Feature",
  "properties": {
    "gn:admin1_code":"12.0",
    "gn:asciiname":"Caissaca",
    "gn:country_code":"AO",
    "gn:dem":1200,
    "gn:feature_class":"P",
    "gn:feature_code":"PPL",
    "gn:name":"Caissaca",
    "gn:population":0,
    "gn:timezone":"Africa/Luanda",
    "iso:country":"AO",
    "wof:name":"Caissaca",
    "wof:placetype":"locality"
},
  "geometry": {"coordinates":[16.19441,-9.32041],"type":"Point"}
}