{
  "type": "Feature",
  "properties": {
    "gn:admin1_code":"18.0",
    "gn:asciiname":"Saluinda",
    "gn:country_code":"AO",
    "gn:dem":1244,
    "gn:feature_class":"P",
    "gn:feature_code":"PPL",
    "gn:name":"Saluinda",
    "gn:population":0,
    "gn:timezone":"Africa/Luanda",
    "iso:country":"AO",
    "wof:name":"Saluinda",
    "wof:placetype":"locality"
},
  "geometry": {"coordinates":[20.2975,-10.87944],"type":"Point"}
}