{
  "type": "Feature",
  "properties": {
    "gn:admin1_code":"14.0",
    "gn:asciiname":"Nhamuchiri",
    "gn:cc2":"AO",
    "gn:country_code":"AO",
    "gn:dem":1107,
    "gn:feature_class":"P",
    "gn:feature_code":"PPL",
    "gn:name":"Nhamuchiri",
    "gn:population":0,
    "gn:timezone":"Africa/Luanda",
    "iso:country":"AO",
    "name:und_x_variant":[
        "Nhamuxir",
        "Nhamuzir",
        "Nhamuchiri"
    ],
    "wof:name":"Nhamuchiri",
    "wof:placetype":"locality"
},
  "geometry": {"coordinates":[21.91667,-11.38333],"type":"Point"}
}