{
  "type": "Feature",
  "properties": {
    "gn:admin1_code":"12.0",
    "gn:asciiname":"Cambango",
    "gn:country_code":"AO",
    "gn:dem":1145,
    "gn:feature_class":"P",
    "gn:feature_code":"PPL",
    "gn:name":"Cambango",
    "gn:population":0,
    "gn:timezone":"Africa/Luanda",
    "iso:country":"AO",
    "wof:name":"Cambango",
    "wof:placetype":"locality"
},
  "geometry": {"coordinates":[17.64764,-10.63259],"type":"Point"}
}