{
  "type": "Feature",
  "properties": {
    "gn:admin1_code":"12.0",
    "gn:asciiname":"Bela Vista",
    "gn:country_code":"AO",
    "gn:dem":1071,
    "gn:feature_class":"P",
    "gn:feature_code":"PPL",
    "gn:name":"Bela Vista",
    "gn:population":0,
    "gn:timezone":"Africa/Luanda",
    "iso:country":"AO",
    "name:ukr_x_preferred":[
        "\u0411\u0435\u043b\u0430-\u0412\u0456\u0441\u0442\u0430"
    ],
    "wof:name":"Bela Vista",
    "wof:placetype":"locality"
},
  "geometry": {"coordinates":[15.75611,-9.42328],"type":"Point"}
}