{
  "type": "Feature",
  "properties": {
    "gn:admin1_code":"6.0",
    "gn:asciiname":"Malanje do Mucongo",
    "gn:country_code":"AO",
    "gn:dem":667,
    "gn:feature_class":"P",
    "gn:feature_code":"PPL",
    "gn:name":"Malanje do Mucongo",
    "gn:population":0,
    "gn:timezone":"Africa/Luanda",
    "iso:country":"AO",
    "wof:name":"Malanje do Mucongo",
    "wof:placetype":"locality"
},
  "geometry": {"coordinates":[14.77012,-10.04972],"type":"Point"}
}