{
  "type": "Feature",
  "properties": {
    "gn:admin1_code":"2.0",
    "gn:asciiname":"Sacaianda",
    "gn:country_code":"AO",
    "gn:dem":1514,
    "gn:feature_class":"P",
    "gn:feature_code":"PPL",
    "gn:name":"Sacaianda",
    "gn:population":0,
    "gn:timezone":"Africa/Luanda",
    "iso:country":"AO",
    "wof:name":"Sacaianda",
    "wof:placetype":"locality"
},
  "geometry": {"coordinates":[17.23333,-13.55],"type":"Point"}
}