{
  "type": "Feature",
  "properties": {
    "gn:admin1_code":"6.0",
    "gn:asciiname":"Cacuso",
    "gn:country_code":"AO",
    "gn:dem":947,
    "gn:feature_class":"P",
    "gn:feature_code":"PPL",
    "gn:name":"Cacuso",
    "gn:population":0,
    "gn:timezone":"Africa/Luanda",
    "iso:country":"AO",
    "wof:name":"Cacuso",
    "wof:placetype":"locality"
},
  "geometry": {"coordinates":[14.90587,-9.99218],"type":"Point"}
}