{
  "type": "Feature",
  "properties": {
    "gn:admin1_code":"2.0",
    "gn:asciiname":"Tchipumo",
    "gn:country_code":"AO",
    "gn:dem":1745,
    "gn:feature_class":"P",
    "gn:feature_code":"PPL",
    "gn:name":"Tchipumo",
    "gn:population":0,
    "gn:timezone":"Africa/Luanda",
    "iso:country":"AO",
    "wof:name":"Tchipumo",
    "wof:placetype":"locality"
},
  "geometry": {"coordinates":[16.99102,-11.75621],"type":"Point"}
}