{
  "type": "Feature",
  "properties": {
    "gn:admin1_code":"6.0",
    "gn:asciiname":"Mulungo",
    "gn:country_code":"AO",
    "gn:dem":1257,
    "gn:feature_class":"P",
    "gn:feature_code":"PPL",
    "gn:name":"Mulungo",
    "gn:population":0,
    "gn:timezone":"Africa/Luanda",
    "iso:country":"AO",
    "wof:name":"Mulungo",
    "wof:placetype":"locality"
},
  "geometry": {"coordinates":[15.02606,-10.47931],"type":"Point"}
}