{
  "type": "Feature",
  "properties": {
    "gn:admin1_code":"12.0",
    "gn:asciiname":"Ngonga Canhongo",
    "gn:country_code":"AO",
    "gn:dem":1127,
    "gn:feature_class":"P",
    "gn:feature_code":"PPL",
    "gn:name":"Ngonga Canhongo",
    "gn:population":0,
    "gn:timezone":"Africa/Luanda",
    "iso:country":"AO",
    "wof:name":"Ngonga Canhongo",
    "wof:placetype":"locality"
},
  "geometry": {"coordinates":[16.15124,-8.95538],"type":"Point"}
}