{
  "type": "Feature",
  "properties": {
    "gn:admin1_code":"3.0",
    "gn:asciiname":"Tumba",
    "gn:cc2":"AO",
    "gn:country_code":"AO",
    "gn:dem":121,
    "gn:feature_class":"P",
    "gn:feature_code":"PPL",
    "gn:name":"Tumba",
    "gn:population":0,
    "gn:timezone":"Africa/Luanda",
    "iso:country":"AO",
    "name:rus_x_preferred":[
        "\u0422\u0443\u043c\u0431\u0430"
    ],
    "name:und_x_variant":[
        "Itumba",
        "Tando",
        "Tumba"
    ],
    "wof:name":"Tumba",
    "wof:placetype":"locality"
},
  "geometry": {"coordinates":[12.33333,-5.71667],"type":"Point"}
}