{
  "type": "Feature",
  "properties": {
    "gn:admin1_code":"12.0",
    "gn:asciiname":"Major Canhangulo",
    "gn:country_code":"AO",
    "gn:dem":800,
    "gn:feature_class":"P",
    "gn:feature_code":"PPL",
    "gn:name":"Major Canhangulo",
    "gn:population":0,
    "gn:timezone":"Africa/Luanda",
    "iso:country":"AO",
    "name:und_x_variant":[
        "Munhunga Nzamba de Cima"
    ],
    "wof:name":"Major Canhangulo",
    "wof:placetype":"locality"
},
  "geometry": {"coordinates":[15.48299,-9.37103],"type":"Point"}
}