{
  "type": "Feature",
  "properties": {
    "gn:admin1_code":"15.0",
    "gn:asciiname":"Quicabato",
    "gn:country_code":"AO",
    "gn:dem":1183,
    "gn:feature_class":"P",
    "gn:feature_code":"PPL",
    "gn:name":"Quicabato",
    "gn:population":0,
    "gn:timezone":"Africa/Luanda",
    "iso:country":"AO",
    "wof:name":"Quicabato",
    "wof:placetype":"locality"
},
  "geometry": {"coordinates":[15.59541,-7.69005],"type":"Point"}
}