{
  "type": "Feature",
  "properties": {
    "gn:admin1_code":"12.0",
    "gn:asciiname":"Cambanve",
    "gn:country_code":"AO",
    "gn:dem":1079,
    "gn:feature_class":"P",
    "gn:feature_code":"PPL",
    "gn:name":"Cambanve",
    "gn:population":0,
    "gn:timezone":"Africa/Luanda",
    "iso:country":"AO",
    "wof:name":"Cambanve",
    "wof:placetype":"locality"
},
  "geometry": {"coordinates":[16.14278,-9.52611],"type":"Point"}
}