{
  "type": "Feature",
  "properties": {
    "gn:admin1_code":"6.0",
    "gn:asciiname":"Ringa",
    "gn:country_code":"AO",
    "gn:dem":1078,
    "gn:feature_class":"P",
    "gn:feature_code":"PPL",
    "gn:name":"Ringa",
    "gn:population":0,
    "gn:timezone":"Africa/Luanda",
    "iso:country":"AO",
    "wof:name":"Ringa",
    "wof:placetype":"locality"
},
  "geometry": {"coordinates":[14.83212,-9.98709],"type":"Point"}
}