{
  "type": "Feature",
  "properties": {
    "gn:admin1_code":"5.0",
    "gn:asciiname":"Quilometro Vinte",
    "gn:country_code":"AO",
    "gn:dem":89,
    "gn:feature_class":"P",
    "gn:feature_code":"PPL",
    "gn:name":"Quil\u00f4metro Vinte",
    "gn:population":0,
    "gn:timezone":"Africa/Luanda",
    "iso:country":"AO",
    "wof:name":"Quilometro Vinte",
    "wof:placetype":"locality"
},
  "geometry": {"coordinates":[14.30638,-9.42549],"type":"Point"}
}