{
  "type": "Feature",
  "properties": {
    "gn:admin1_code":"9.0",
    "gn:asciiname":"Sapalalo",
    "gn:country_code":"AO",
    "gn:dem":1302,
    "gn:feature_class":"P",
    "gn:feature_code":"PPLL",
    "gn:name":"Sapalalo",
    "gn:population":0,
    "gn:timezone":"Africa/Luanda",
    "iso:country":"AO",
    "wof:name":"Sapalalo",
    "wof:placetype":"locality"
},
  "geometry": {"coordinates":[14.5683,-14.87493],"type":"Point"}
}