{
  "type": "Feature",
  "properties": {
    "gn:admin1_code":"17.0",
    "gn:asciiname":"Cassele",
    "gn:country_code":"AO",
    "gn:dem":719,
    "gn:feature_class":"P",
    "gn:feature_code":"PPL",
    "gn:name":"Cassele",
    "gn:population":0,
    "gn:timezone":"Africa/Luanda",
    "iso:country":"AO",
    "name:und_x_variant":[
        "Casele",
        "Cassela",
        "Cassele"
    ],
    "wof:name":"Cassele",
    "wof:placetype":"locality"
},
  "geometry": {"coordinates":[17.60979,-8.82452],"type":"Point"}
}