{
  "type": "Feature",
  "properties": {
    "gn:admin1_code":"14.0",
    "gn:asciiname":"Uachia",
    "gn:cc2":"AO",
    "gn:country_code":"AO",
    "gn:dem":1133,
    "gn:feature_class":"P",
    "gn:feature_code":"PPL",
    "gn:name":"Uachia",
    "gn:population":0,
    "gn:timezone":"Africa/Luanda",
    "iso:country":"AO",
    "name:und_x_variant":[
        "Uatchia",
        "Uachia"
    ],
    "wof:name":"Uachia",
    "wof:placetype":"locality"
},
  "geometry": {"coordinates":[21.36667000000001,-13.91667],"type":"Point"}
}