{
  "type": "Feature",
  "properties": {
    "gn:admin1_code":"6.0",
    "gn:asciiname":"Colo-Colo",
    "gn:country_code":"AO",
    "gn:dem":1271,
    "gn:feature_class":"P",
    "gn:feature_code":"PPL",
    "gn:name":"Colo-Colo",
    "gn:population":0,
    "gn:timezone":"Africa/Luanda",
    "iso:country":"AO",
    "name:amh_x_preferred":[
        "\u12ae\u120e-\u12ae\u120e"
    ],
    "name:ang_x_preferred":[
        "Colo-Colo"
    ],
    "name:ara_x_preferred":[
        "\u0643\u0648\u0644\u0648-\u0643\u0648\u0644\u0648"
    ],
    "name:aze_x_preferred":[
        "Kolo-Kolo"
    ],
    "name:bel_x_preferred":[
        "\u0424\u041a \u041a\u043e\u043b\u0430-\u041a\u043e\u043b\u0430"
    ],
    "name:bos_x_preferred":[
        "Colo-Colo"
    ],
    "name:bul_x_preferred":[
        "\u041a\u043e\u043b\u043e \u041a\u043e\u043b\u043e"
    ],
    "name:ces_x_preferred":[
        "Colo-Colo"
    ],
    "name:cym_x_preferred":[
        "Colo-Colo"
    ],
    "name:dan_x_preferred":[
        "Colo-Colo"
    ],
    "name:deu_x_preferred":[
        "CSD Colo-Colo"
    ],
    "name:diq_x_preferred":[
        "Colo-Colo"
    ],
    "name:ell_x_preferred":[
        "\u039a\u03cc\u03bb\u03bf-\u039a\u03cc\u03bb\u03bf"
    ],
    "name:eus_x_preferred":[
        "Colo-Colo"
    ],
    "name:frp_x_preferred":[
        "Colo-Colo"
    ],
    "name:glg_x_preferred":[
        "Colo-Colo"
    ],
    "name:heb_x_preferred":[
        "\u05e7\u05d5\u05dc\u05d5-\u05e7\u05d5\u05dc\u05d5"
    ],
    "name:hun_x_preferred":[
        "Colo-Colo"
    ],
    "name:ile_x_preferred":[
        "Colo-Colo"
    ],
    "name:ind_x_preferred":[
        "Colo-Colo"
    ],
    "name:kor_x_preferred":[
        "\ucf5c\ub85c-\ucf5c\ub85c"
    ],
    "name:lat_x_preferred":[
        "Colo-Colo"
    ],
    "name:lav_x_preferred":[
        "Colo-Colo"
    ],
    "name:lit_x_preferred":[
        "Colo-Colo"
    ],
    "name:nld_x_preferred":[
        "Colo-Colo"
    ],
    "name:nor_x_preferred":[
        "Colo-Colo"
    ],
    "name:oci_x_preferred":[
        "Colo-Colo"
    ],
    "name:pol_x_preferred":[
        "CSD Colo-Colo"
    ],
    "name:rmy_x_preferred":[
        "Colo-Colo"
    ],
    "name:ron_x_preferred":[
        "Colo-Colo"
    ],
    "name:rus_x_preferred":[
        "\u041a\u043e\u043b\u043e-\u041a\u043e\u043b\u043e"
    ],
    "name:sco_x_preferred":[
        "Colo-Colo"
    ],
    "name:slv_x_preferred":[
        "Colo-Colo"
    ],
    "name:srd_x_preferred":[
        "Colo-Colo"
    ],
    "name:swe_x_preferred":[
        "Colo-Colo"
    ],
    "name:tat_x_preferred":[
        "\u041a\u043e\u043b\u043e-\u041a\u043e\u043b\u043e"
    ],
    "name:tur_x_preferred":[
        "CSD Colo-Colo"
    ],
    "name:ukr_x_preferred":[
        "\u041a\u043e\u043b\u043e-\u041a\u043e\u043b\u043e"
    ],
    "name:uzb_x_preferred":[
        "Colo-Colo"
    ],
    "name:vie_x_preferred":[
        "Colo-Colo"
    ],
    "name:yid_x_preferred":[
        "\u05e7\u05d0\u05dc\u05d0-\u05e7\u05d0\u05dc\u05d0"
    ],
    "name:zho_x_preferred":[
        "\u79d1\u6d1b\u79d1\u6d1b\u7ade\u6280\u4ff1\u4e50\u90e8"
    ],
    "wof:name":"Colo-Colo",
    "wof:placetype":"locality"
},
  "geometry": {"coordinates":[15.00945,-11.34213],"type":"Point"}
}