{
  "type": "Feature",
  "properties": {
    "gn:admin1_code":"6.0",
    "gn:asciiname":"Colo-Colo",
    "gn:country_code":"AO",
    "gn:dem":1271,
    "gn:feature_class":"P",
    "gn:feature_code":"PPL",
    "gn:name":"Colo-Colo",
    "gn:population":0,
    "gn:timezone":"Africa/Luanda",
    "iso:country":"AO",
    "wof:name":"Colo-Colo",
    "wof:placetype":"locality"
},
  "geometry": {"coordinates":[15.00945,-11.34213],"type":"Point"}
}