{
  "type": "Feature",
  "properties": {
    "gn:admin1_code":"5.0",
    "gn:asciiname":"Quiongola",
    "gn:cc2":"AO",
    "gn:country_code":"AO",
    "gn:dem":839,
    "gn:feature_class":"P",
    "gn:feature_code":"PPL",
    "gn:name":"Quiongola",
    "gn:population":0,
    "gn:timezone":"Africa/Luanda",
    "iso:country":"AO",
    "name:und_x_variant":[
        "Quingola",
        "Quiungola",
        "Quiongola"
    ],
    "wof:name":"Quiongola",
    "wof:placetype":"locality"
},
  "geometry": {"coordinates":[14.96667,-8.88333],"type":"Point"}
}