{
  "type": "Feature",
  "properties": {
    "gn:admin1_code":"1.0",
    "gn:asciiname":"Moma",
    "gn:country_code":"AO",
    "gn:dem":1224,
    "gn:feature_class":"P",
    "gn:feature_code":"PPL",
    "gn:name":"Moma",
    "gn:population":0,
    "gn:timezone":"Africa/Luanda",
    "iso:country":"AO",
    "name:bel_x_preferred":[
        "\u041c\u043e\u043c\u0430"
    ],
    "name:cat_x_preferred":[
        "Moma"
    ],
    "name:ceb_x_preferred":[
        "Moma"
    ],
    "name:deu_x_preferred":[
        "Moma"
    ],
    "name:fra_x_preferred":[
        "Moma"
    ],
    "name:heb_x_preferred":[
        "\u05de\u05d5\u05de\u05d4"
    ],
    "name:hun_x_preferred":[
        "MoMA"
    ],
    "name:ita_x_preferred":[
        "Moma"
    ],
    "name:nld_x_preferred":[
        "Moma"
    ],
    "name:pol_x_preferred":[
        "Moma"
    ],
    "name:rus_x_preferred":[
        "\u041c\u043e\u043c\u0430"
    ],
    "name:spa_x_preferred":[
        "Moma"
    ],
    "name:swe_x_preferred":[
        "Moma"
    ],
    "wof:name":"Moma",
    "wof:placetype":"locality"
},
  "geometry": {"coordinates":[14.21667,-12.51667],"type":"Point"}
}