{
  "type": "Feature",
  "properties": {
    "gn:admin1_code":"3.0",
    "gn:asciiname":"Sanda Massala",
    "gn:cc2":"AO",
    "gn:country_code":"AO",
    "gn:dem":538,
    "gn:feature_class":"P",
    "gn:feature_code":"PPL",
    "gn:name":"Sanda Massala",
    "gn:population":0,
    "gn:timezone":"Africa/Luanda",
    "iso:country":"AO",
    "name:und_x_variant":[
        "Sanga Massala",
        "Sanda Massala"
    ],
    "wof:name":"Sanda Massala",
    "wof:placetype":"locality"
},
  "geometry": {"coordinates":[13.01667,-4.68333],"type":"Point"}
}