{
  "type": "Feature",
  "properties": {
    "gn:admin1_code":"4.0",
    "gn:asciiname":"Dima",
    "gn:country_code":"AO",
    "gn:dem":1060,
    "gn:feature_class":"P",
    "gn:feature_code":"PPL",
    "gn:name":"Dima",
    "gn:population":0,
    "gn:timezone":"Africa/Luanda",
    "iso:country":"AO",
    "wof:name":"Dima",
    "wof:placetype":"locality"
},
  "geometry": {"coordinates":[21.36667000000001,-15.46667],"type":"Point"}
}