{
  "type": "Feature",
  "properties": {
    "gn:admin1_code":"14.0",
    "gn:asciiname":"Chepate",
    "gn:country_code":"AO",
    "gn:dem":1126,
    "gn:feature_class":"P",
    "gn:feature_code":"PPL",
    "gn:name":"Chepate",
    "gn:population":0,
    "gn:timezone":"Africa/Luanda",
    "iso:country":"AO",
    "wof:name":"Chepate",
    "wof:placetype":"locality"
},
  "geometry": {"coordinates":[22.88333,-12.91667],"type":"Point"}
}