{
  "type": "Feature",
  "properties": {
    "gn:admin1_code":"15.0",
    "gn:asciiname":"Ebuessa",
    "gn:country_code":"AO",
    "gn:dem":923,
    "gn:feature_class":"P",
    "gn:feature_code":"PPL",
    "gn:name":"Ebuessa",
    "gn:population":0,
    "gn:timezone":"Africa/Luanda",
    "iso:country":"AO",
    "wof:name":"Ebuessa",
    "wof:placetype":"locality"
},
  "geometry": {"coordinates":[15.13333,-7.51667],"type":"Point"}
}