{
  "type": "Feature",
  "properties": {
    "gn:admin1_code":"17.0",
    "gn:asciiname":"Congolo",
    "gn:country_code":"AO",
    "gn:dem":862,
    "gn:feature_class":"P",
    "gn:feature_code":"PPL",
    "gn:name":"Congolo",
    "gn:population":0,
    "gn:timezone":"Africa/Luanda",
    "iso:country":"AO",
    "wof:name":"Congolo",
    "wof:placetype":"locality"
},
  "geometry": {"coordinates":[20.83333,-8.45],"type":"Point"}
}