{
  "type": "Feature",
  "properties": {
    "gn:admin1_code":"16.0",
    "gn:asciiname":"Mbelengue",
    "gn:country_code":"AO",
    "gn:dem":379,
    "gn:feature_class":"P",
    "gn:feature_code":"PPL",
    "gn:name":"Mbelengue",
    "gn:population":0,
    "gn:timezone":"Africa/Luanda",
    "iso:country":"AO",
    "wof:name":"Mbelengue",
    "wof:placetype":"locality"
},
  "geometry": {"coordinates":[13.90007,-6.60049],"type":"Point"}
}