{
  "type": "Feature",
  "properties": {
    "gn:admin1_code":"12.0",
    "gn:asciiname":"Mucande",
    "gn:country_code":"AO",
    "gn:dem":1096,
    "gn:feature_class":"P",
    "gn:feature_code":"PPL",
    "gn:name":"Mucande",
    "gn:population":0,
    "gn:timezone":"Africa/Luanda",
    "iso:country":"AO",
    "wof:name":"Mucande",
    "wof:placetype":"locality"
},
  "geometry": {"coordinates":[17.36667000000001,-10.88333],"type":"Point"}
}