{
  "type": "Feature",
  "properties": {
    "gn:admin1_code":"16.0",
    "gn:asciiname":"Luvo",
    "gn:country_code":"AO",
    "gn:dem":323,
    "gn:feature_class":"P",
    "gn:feature_code":"PPL",
    "gn:name":"Luvo",
    "gn:population":0,
    "gn:timezone":"Africa/Luanda",
    "iso:country":"AO",
    "wof:name":"Luvo",
    "wof:placetype":"locality"
},
  "geometry": {"coordinates":[14.08419,-5.84925],"type":"Point"}
}