{
  "type": "Feature",
  "properties": {
    "gn:admin1_code":"8.0",
    "gn:asciiname":"Tende",
    "gn:cc2":"AO",
    "gn:country_code":"AO",
    "gn:dem":1334,
    "gn:feature_class":"P",
    "gn:feature_code":"PPL",
    "gn:name":"Tende",
    "gn:population":0,
    "gn:timezone":"Africa/Luanda",
    "iso:country":"AO",
    "name:und_x_variant":[
        "Utende",
        "Tende"
    ],
    "wof:name":"Tende",
    "wof:placetype":"locality"
},
  "geometry": {"coordinates":[15.71667,-11.53333],"type":"Point"}
}