{
  "type": "Feature",
  "properties": {
    "gn:admin1_code":"6.0",
    "gn:asciiname":"Sengo",
    "gn:country_code":"AO",
    "gn:dem":1287,
    "gn:feature_class":"P",
    "gn:feature_code":"PPL",
    "gn:name":"Sengo",
    "gn:population":0,
    "gn:timezone":"Africa/Luanda",
    "iso:country":"AO",
    "name:ceb_x_preferred":[
        "Sengo"
    ],
    "name:swe_x_preferred":[
        "Sengo"
    ],
    "wof:name":"Sengo",
    "wof:placetype":"locality"
},
  "geometry": {"coordinates":[15.2553,-10.65035],"type":"Point"}
}