{
  "type": "Feature",
  "properties": {
    "gn:admin1_code":"15.0",
    "gn:asciiname":"Quilabila",
    "gn:cc2":"AO",
    "gn:country_code":"AO",
    "gn:dem":1075,
    "gn:feature_class":"P",
    "gn:feature_code":"PPL",
    "gn:name":"Quilabila",
    "gn:population":0,
    "gn:timezone":"Africa/Luanda",
    "iso:country":"AO",
    "name:und_x_variant":[
        "Quimiala",
        "Quimaiala",
        "Quilabila"
    ],
    "wof:name":"Quilabila",
    "wof:placetype":"locality"
},
  "geometry": {"coordinates":[15.85,-7.55],"type":"Point"}
}