{
  "type": "Feature",
  "properties": {
    "gn:admin1_code":"1.0",
    "gn:asciiname":"Calupuca",
    "gn:country_code":"AO",
    "gn:dem":1409,
    "gn:feature_class":"P",
    "gn:feature_code":"PPL",
    "gn:name":"Calupuca",
    "gn:population":0,
    "gn:timezone":"Africa/Luanda",
    "iso:country":"AO",
    "wof:name":"Calupuca",
    "wof:placetype":"locality"
},
  "geometry": {"coordinates":[14.35,-12.41667],"type":"Point"}
}