{
  "type": "Feature",
  "properties": {
    "gn:admin1_code":"15.0",
    "gn:asciiname":"Ngombe",
    "gn:country_code":"AO",
    "gn:dem":730,
    "gn:feature_class":"P",
    "gn:feature_code":"PPL",
    "gn:name":"Ngombe",
    "gn:population":0,
    "gn:timezone":"Africa/Luanda",
    "iso:country":"AO",
    "wof:name":"Ngombe",
    "wof:placetype":"locality"
},
  "geometry": {"coordinates":[14.81724,-6.96332],"type":"Point"}
}