{
  "type": "Feature",
  "properties": {
    "gn:admin1_code":"12.0",
    "gn:asciiname":"Quimonha",
    "gn:country_code":"AO",
    "gn:dem":1158,
    "gn:feature_class":"P",
    "gn:feature_code":"PPL",
    "gn:name":"Quimonha",
    "gn:population":0,
    "gn:timezone":"Africa/Luanda",
    "iso:country":"AO",
    "wof:name":"Quimonha",
    "wof:placetype":"locality"
},
  "geometry": {"coordinates":[15.87889,-8.78372],"type":"Point"}
}