{
  "type": "Feature",
  "properties": {
    "gn:admin1_code":"2.0",
    "gn:asciiname":"Canguenenguene",
    "gn:country_code":"AO",
    "gn:dem":1721,
    "gn:feature_class":"P",
    "gn:feature_code":"PPL",
    "gn:name":"Canguenenguene",
    "gn:population":0,
    "gn:timezone":"Africa/Luanda",
    "iso:country":"AO",
    "wof:name":"Canguenenguene",
    "wof:placetype":"locality"
},
  "geometry": {"coordinates":[17.03302,-11.83949],"type":"Point"}
}