{
  "type": "Feature",
  "properties": {
    "gn:admin1_code":"15.0",
    "gn:asciiname":"Quinheta",
    "gn:country_code":"AO",
    "gn:dem":552,
    "gn:feature_class":"P",
    "gn:feature_code":"PPL",
    "gn:name":"Quinheta",
    "gn:population":0,
    "gn:timezone":"Africa/Luanda",
    "iso:country":"AO",
    "wof:name":"Quinheta",
    "wof:placetype":"locality"
},
  "geometry": {"coordinates":[16.0692,-5.94818],"type":"Point"}
}