{
  "type": "Feature",
  "properties": {
    "gn:admin1_code":"5.0",
    "gn:asciiname":"Sobocoto",
    "gn:country_code":"AO",
    "gn:dem":799,
    "gn:feature_class":"P",
    "gn:feature_code":"PPL",
    "gn:name":"Sobocoto",
    "gn:population":0,
    "gn:timezone":"Africa/Luanda",
    "iso:country":"AO",
    "wof:name":"Sobocoto",
    "wof:placetype":"locality"
},
  "geometry": {"coordinates":[14.92012,-9.28481],"type":"Point"}
}