{
  "type": "Feature",
  "properties": {
    "gn:admin1_code":"18.0",
    "gn:asciiname":"Muanguanza",
    "gn:country_code":"AO",
    "gn:dem":1026,
    "gn:feature_class":"P",
    "gn:feature_code":"PPL",
    "gn:name":"Muanguanza",
    "gn:population":0,
    "gn:timezone":"Africa/Luanda",
    "iso:country":"AO",
    "wof:name":"Muanguanza",
    "wof:placetype":"locality"
},
  "geometry": {"coordinates":[20.6878,-9.34132],"type":"Point"}
}