{
  "type": "Feature",
  "properties": {
    "gn:admin1_code":"15.0",
    "gn:asciiname":"Candamba",
    "gn:country_code":"AO",
    "gn:dem":764,
    "gn:feature_class":"P",
    "gn:feature_code":"PPL",
    "gn:name":"Candamba",
    "gn:population":0,
    "gn:timezone":"Africa/Luanda",
    "iso:country":"AO",
    "wof:name":"Candamba",
    "wof:placetype":"locality"
},
  "geometry": {"coordinates":[16.2743,-6.49096],"type":"Point"}
}