{
  "type": "Feature",
  "properties": {
    "gn:admin1_code":"15.0",
    "gn:asciiname":"Quinzambi",
    "gn:country_code":"AO",
    "gn:dem":1203,
    "gn:feature_class":"P",
    "gn:feature_code":"PPL",
    "gn:name":"Quinzambi",
    "gn:population":0,
    "gn:timezone":"Africa/Luanda",
    "iso:country":"AO",
    "wof:name":"Quinzambi",
    "wof:placetype":"locality"
},
  "geometry": {"coordinates":[15.05663,-7.20034],"type":"Point"}
}