{
  "type": "Feature",
  "properties": {
    "gn:admin1_code":"14.0",
    "gn:asciiname":"Muchir",
    "gn:country_code":"AO",
    "gn:dem":1198,
    "gn:feature_class":"P",
    "gn:feature_code":"PPL",
    "gn:name":"Muchir",
    "gn:population":0,
    "gn:timezone":"Africa/Luanda",
    "iso:country":"AO",
    "wof:name":"Muchir",
    "wof:placetype":"locality"
},
  "geometry": {"coordinates":[21.06667,-14.08333],"type":"Point"}
}