{
  "type": "Feature",
  "properties": {
    "gn:admin1_code":"6.0",
    "gn:asciiname":"Ngombe",
    "gn:country_code":"AO",
    "gn:dem":917,
    "gn:feature_class":"P",
    "gn:feature_code":"PPL",
    "gn:name":"Ngombe",
    "gn:population":0,
    "gn:timezone":"Africa/Luanda",
    "iso:country":"AO",
    "wof:name":"Ngombe",
    "wof:placetype":"locality"
},
  "geometry": {"coordinates":[14.36323,-10.94141],"type":"Point"}
}