{
  "type": "Feature",
  "properties": {
    "gn:admin1_code":"6.0",
    "gn:asciiname":"Haca",
    "gn:country_code":"AO",
    "gn:dem":1034,
    "gn:feature_class":"P",
    "gn:feature_code":"PPL",
    "gn:name":"Haca",
    "gn:population":0,
    "gn:timezone":"Africa/Luanda",
    "iso:country":"AO",
    "wof:name":"Haca",
    "wof:placetype":"locality"
},
  "geometry": {"coordinates":[14.41861,-11.12622],"type":"Point"}
}