{
  "type": "Feature",
  "properties": {
    "gn:admin1_code":"6.0",
    "gn:asciiname":"Quitunda",
    "gn:country_code":"AO",
    "gn:dem":1338,
    "gn:feature_class":"P",
    "gn:feature_code":"PPLL",
    "gn:name":"Quitunda",
    "gn:population":0,
    "gn:timezone":"Africa/Luanda",
    "iso:country":"AO",
    "wof:name":"Quitunda",
    "wof:placetype":"locality"
},
  "geometry": {"coordinates":[15.14526,-11.27716],"type":"Point"}
}