{
  "type": "Feature",
  "properties": {
    "gn:admin1_code":"5.0",
    "gn:asciiname":"Cavunda",
    "gn:country_code":"AO",
    "gn:dem":436,
    "gn:feature_class":"P",
    "gn:feature_code":"PPL",
    "gn:name":"Cavunda",
    "gn:population":0,
    "gn:timezone":"Africa/Luanda",
    "iso:country":"AO",
    "name:und_x_variant":[
        "Cavunga",
        "Cavunga Capaca\u00e7a",
        "Cavunda"
    ],
    "wof:name":"Cavunda",
    "wof:placetype":"locality"
},
  "geometry": {"coordinates":[14.65262,-8.92458],"type":"Point"}
}