{
  "type": "Feature",
  "properties": {
    "gn:admin1_code":"8.0",
    "gn:asciiname":"Cavinda",
    "gn:country_code":"AO",
    "gn:dem":1709,
    "gn:feature_class":"P",
    "gn:feature_code":"PPL",
    "gn:name":"Cavinda",
    "gn:population":0,
    "gn:timezone":"Africa/Luanda",
    "iso:country":"AO",
    "wof:name":"Cavinda",
    "wof:placetype":"locality"
},
  "geometry": {"coordinates":[15.83333,-13.11667],"type":"Point"}
}