{
  "type": "Feature",
  "properties": {
    "gn:admin1_code":"15.0",
    "gn:asciiname":"Quitande",
    "gn:cc2":"AO",
    "gn:country_code":"AO",
    "gn:dem":1166,
    "gn:feature_class":"P",
    "gn:feature_code":"PPL",
    "gn:name":"Quitande",
    "gn:population":0,
    "gn:timezone":"Africa/Luanda",
    "iso:country":"AO",
    "name:und_x_variant":[
        "Quitambo",
        "Quitande"
    ],
    "wof:name":"Quitande",
    "wof:placetype":"locality"
},
  "geometry": {"coordinates":[15.36667,-7.31667],"type":"Point"}
}