{
  "type": "Feature",
  "properties": {
    "gn:admin1_code":"15.0",
    "gn:asciiname":"Banza Bongo",
    "gn:country_code":"AO",
    "gn:dem":825,
    "gn:feature_class":"P",
    "gn:feature_code":"PPL",
    "gn:name":"Banza Bongo",
    "gn:population":0,
    "gn:timezone":"Africa/Luanda",
    "iso:country":"AO",
    "wof:name":"Banza Bongo",
    "wof:placetype":"locality"
},
  "geometry": {"coordinates":[15.18333,-6.03333],"type":"Point"}
}