{
  "type": "Feature",
  "properties": {
    "gn:admin1_code":"2.0",
    "gn:asciiname":"Iandelela",
    "gn:country_code":"AO",
    "gn:dem":1504,
    "gn:feature_class":"P",
    "gn:feature_code":"PPL",
    "gn:name":"Iandelela",
    "gn:population":0,
    "gn:timezone":"Africa/Luanda",
    "iso:country":"AO",
    "wof:name":"Iandelela",
    "wof:placetype":"locality"
},
  "geometry": {"coordinates":[16.56661,-11.53067],"type":"Point"}
}