{
  "type": "Feature",
  "properties": {
    "gn:admin1_code":"6.0",
    "gn:asciiname":"Che",
    "gn:country_code":"AO",
    "gn:dem":1226,
    "gn:feature_class":"P",
    "gn:feature_code":"PPL",
    "gn:name":"Che",
    "gn:population":0,
    "gn:timezone":"Africa/Luanda",
    "iso:country":"AO",
    "name:bre_x_preferred":[
        "Che"
    ],
    "name:cat_x_preferred":[
        "Che"
    ],
    "name:ces_x_preferred":[
        "Che"
    ],
    "name:fra_x_preferred":[
        "Che"
    ],
    "name:glg_x_preferred":[
        "Che"
    ],
    "name:heb_x_preferred":[
        "\u05e6'\u05d4"
    ],
    "name:nld_x_preferred":[
        "Che"
    ],
    "name:por_x_preferred":[
        "Che"
    ],
    "name:spa_x_preferred":[
        "Che"
    ],
    "name:swe_x_preferred":[
        "Che"
    ],
    "name:tur_x_preferred":[
        "Che"
    ],
    "wof:name":"Che",
    "wof:placetype":"locality"
},
  "geometry": {"coordinates":[15.33354,-10.58256],"type":"Point"}
}