{
  "type": "Feature",
  "properties": {
    "gn:admin1_code":"6.0",
    "gn:asciiname":"Che",
    "gn:country_code":"AO",
    "gn:dem":1226,
    "gn:feature_class":"P",
    "gn:feature_code":"PPL",
    "gn:name":"Che",
    "gn:population":0,
    "gn:timezone":"Africa/Luanda",
    "iso:country":"AO",
    "wof:name":"Che",
    "wof:placetype":"locality"
},
  "geometry": {"coordinates":[15.33354,-10.58256],"type":"Point"}
}