{
  "type": "Feature",
  "properties": {
    "gn:admin1_code":"15.0",
    "gn:asciiname":"Quimuanza Langa",
    "gn:country_code":"AO",
    "gn:dem":1031,
    "gn:feature_class":"P",
    "gn:feature_code":"PPL",
    "gn:name":"Quimuanza Langa",
    "gn:population":0,
    "gn:timezone":"Africa/Luanda",
    "iso:country":"AO",
    "name:und_x_variant":[
        "Langa",
        "Quimuanza Langa"
    ],
    "wof:name":"Quimuanza Langa",
    "wof:placetype":"locality"
},
  "geometry": {"coordinates":[15.86503,-7.23794],"type":"Point"}
}