{
  "type": "Feature",
  "properties": {
    "gn:admin1_code":"2.0",
    "gn:asciiname":"Cambandua",
    "gn:country_code":"AO",
    "gn:dem":1427,
    "gn:feature_class":"P",
    "gn:feature_code":"PPL",
    "gn:name":"Camb\u00e2ndua",
    "gn:population":0,
    "gn:timezone":"Africa/Luanda",
    "iso:country":"AO",
    "wof:name":"Cambandua",
    "wof:placetype":"locality"
},
  "geometry": {"coordinates":[17.33333,-12.51667],"type":"Point"}
}