{
  "type": "Feature",
  "properties": {
    "gn:admin1_code":"12.0",
    "gn:asciiname":"Quimoma",
    "gn:country_code":"AO",
    "gn:dem":1064,
    "gn:feature_class":"P",
    "gn:feature_code":"PPL",
    "gn:name":"Quimoma",
    "gn:population":0,
    "gn:timezone":"Africa/Luanda",
    "iso:country":"AO",
    "wof:name":"Quimoma",
    "wof:placetype":"locality"
},
  "geometry": {"coordinates":[15.92739,-9.39654],"type":"Point"}
}