{
  "type": "Feature",
  "properties": {
    "gn:admin1_code":"1.0",
    "gn:asciiname":"Chimelundo",
    "gn:country_code":"AO",
    "gn:dem":388,
    "gn:feature_class":"P",
    "gn:feature_code":"PPL",
    "gn:name":"Chim\u00e9lundo",
    "gn:population":0,
    "gn:timezone":"Africa/Luanda",
    "iso:country":"AO",
    "name:und_x_variant":[
        "Chim\u00e9lundo",
        "Chimelundo",
        "Tchimelundo"
    ],
    "wof:name":"Chimelundo",
    "wof:placetype":"locality"
},
  "geometry": {"coordinates":[13.64,-12.68389],"type":"Point"}
}