{
  "type": "Feature",
  "properties": {
    "gn:admin1_code":"14.0",
    "gn:asciiname":"Luanga",
    "gn:country_code":"AO",
    "gn:dem":1097,
    "gn:feature_class":"P",
    "gn:feature_code":"PPL",
    "gn:name":"Luanga",
    "gn:population":0,
    "gn:timezone":"Africa/Luanda",
    "iso:country":"AO",
    "wof:name":"Luanga",
    "wof:placetype":"locality"
},
  "geometry": {"coordinates":[22.24536,-10.71226],"type":"Point"}
}