{
  "type": "Feature",
  "properties": {
    "gn:admin1_code":"9.0",
    "gn:asciiname":"Dongua Camutontola",
    "gn:country_code":"AO",
    "gn:dem":1502,
    "gn:feature_class":"P",
    "gn:feature_code":"PPLL",
    "gn:name":"Dongua Camutontola",
    "gn:population":0,
    "gn:timezone":"Africa/Luanda",
    "iso:country":"AO",
    "wof:name":"Dongua Camutontola",
    "wof:placetype":"locality"
},
  "geometry": {"coordinates":[14.16748,-14.75552],"type":"Point"}
}