{
  "type": "Feature",
  "properties": {
    "gn:admin1_code":"14.0",
    "gn:asciiname":"Cha Pungana",
    "gn:country_code":"AO",
    "gn:dem":1521,
    "gn:feature_class":"P",
    "gn:feature_code":"PPL",
    "gn:name":"Ch\u00e1 Pungana",
    "gn:population":0,
    "gn:timezone":"Africa/Luanda",
    "iso:country":"AO",
    "wof:name":"Cha Pungana",
    "wof:placetype":"locality"
},
  "geometry": {"coordinates":[18.65,-13.73333],"type":"Point"}
}