{
  "type": "Feature",
  "properties": {
    "gn:admin1_code":"20.0",
    "gn:asciiname":"Bita",
    "gn:country_code":"AO",
    "gn:dem":102,
    "gn:feature_class":"P",
    "gn:feature_code":"PPL",
    "gn:name":"Bita",
    "gn:population":0,
    "gn:timezone":"Africa/Luanda",
    "iso:country":"AO",
    "wof:name":"Bita",
    "wof:placetype":"locality"
},
  "geometry": {"coordinates":[13.29065,-9.0553],"type":"Point"}
}