{
  "type": "Feature",
  "properties": {
    "gn:admin1_code":"14.0",
    "gn:asciiname":"Catueji",
    "gn:country_code":"AO",
    "gn:dem":1251,
    "gn:feature_class":"P",
    "gn:feature_code":"PPL",
    "gn:name":"Catu\u00e9ji",
    "gn:population":0,
    "gn:timezone":"Africa/Luanda",
    "iso:country":"AO",
    "wof:name":"Catueji",
    "wof:placetype":"locality"
},
  "geometry": {"coordinates":[20.18954,-11.45497],"type":"Point"}
}