{
  "type": "Feature",
  "properties": {
    "gn:admin1_code":"15.0",
    "gn:asciiname":"Quinguela",
    "gn:country_code":"AO",
    "gn:dem":916,
    "gn:feature_class":"P",
    "gn:feature_code":"PPL",
    "gn:name":"Quinguela",
    "gn:population":0,
    "gn:timezone":"Africa/Luanda",
    "iso:country":"AO",
    "wof:name":"Quinguela",
    "wof:placetype":"locality"
},
  "geometry": {"coordinates":[16.08592,-7.60353],"type":"Point"}
}