{
  "type": "Feature",
  "properties": {
    "gn:admin1_code":"15.0",
    "gn:asciiname":"Quizenga",
    "gn:country_code":"AO",
    "gn:dem":1034,
    "gn:feature_class":"P",
    "gn:feature_code":"PPL",
    "gn:name":"Quizenga",
    "gn:population":0,
    "gn:timezone":"Africa/Luanda",
    "iso:country":"AO",
    "wof:name":"Quizenga",
    "wof:placetype":"locality"
},
  "geometry": {"coordinates":[15.48333,-7.16667],"type":"Point"}
}