{
  "type": "Feature",
  "properties": {
    "gn:admin1_code":"2.0",
    "gn:asciiname":"Cavanga",
    "gn:country_code":"AO",
    "gn:dem":1642,
    "gn:feature_class":"P",
    "gn:feature_code":"PPL",
    "gn:name":"Cavanga",
    "gn:population":0,
    "gn:timezone":"Africa/Luanda",
    "iso:country":"AO",
    "wof:name":"Cavanga",
    "wof:placetype":"locality"
},
  "geometry": {"coordinates":[16.68338,-11.52466],"type":"Point"}
}