{
  "type": "Feature",
  "properties": {
    "gn:admin1_code":"12.0",
    "gn:asciiname":"Quilundula",
    "gn:country_code":"AO",
    "gn:dem":698,
    "gn:feature_class":"P",
    "gn:feature_code":"PPL",
    "gn:name":"Quilundula",
    "gn:population":0,
    "gn:timezone":"Africa/Luanda",
    "iso:country":"AO",
    "wof:name":"Quilundula",
    "wof:placetype":"locality"
},
  "geometry": {"coordinates":[17.29345,-8.96893],"type":"Point"}
}