{
  "type": "Feature",
  "properties": {
    "gn:admin1_code":"12.0",
    "gn:asciiname":"Cambeu",
    "gn:country_code":"AO",
    "gn:dem":1219,
    "gn:feature_class":"P",
    "gn:feature_code":"PPL",
    "gn:name":"Cambeu",
    "gn:population":0,
    "gn:timezone":"Africa/Luanda",
    "iso:country":"AO",
    "wof:name":"Cambeu",
    "wof:placetype":"locality"
},
  "geometry": {"coordinates":[17.93293,-10.81167],"type":"Point"}
}