{
  "type": "Feature",
  "properties": {
    "gn:admin1_code":"14.0",
    "gn:asciiname":"Massobi",
    "gn:cc2":"AO",
    "gn:country_code":"AO",
    "gn:dem":1076,
    "gn:feature_class":"P",
    "gn:feature_code":"PPL",
    "gn:name":"Massobi",
    "gn:population":0,
    "gn:timezone":"Africa/Luanda",
    "iso:country":"AO",
    "name:und_x_variant":[
        "Menua",
        "Menia",
        "Massobi"
    ],
    "wof:name":"Massobi",
    "wof:placetype":"locality"
},
  "geometry": {"coordinates":[22.61667000000001,-12.16667],"type":"Point"}
}