{
  "type": "Feature",
  "properties": {
    "gn:admin1_code":"16.0",
    "gn:asciiname":"Sanza",
    "gn:country_code":"AO",
    "gn:dem":672,
    "gn:feature_class":"P",
    "gn:feature_code":"PPL",
    "gn:name":"Sanza",
    "gn:population":0,
    "gn:timezone":"Africa/Luanda",
    "iso:country":"AO",
    "name:azb_x_preferred":[
        "\u0633\u0627\u0646\u062a\u0632\u0627"
    ],
    "name:bar_x_preferred":[
        "Sanza"
    ],
    "name:bul_x_preferred":[
        "\u0421\u0430\u043d\u0446\u0430"
    ],
    "name:ceb_x_preferred":[
        "Sanza"
    ],
    "name:deu_x_preferred":[
        "Sanza"
    ],
    "name:epo_x_preferred":[
        "Sanza"
    ],
    "name:eus_x_preferred":[
        "Sanza"
    ],
    "name:fas_x_preferred":[
        "\u0633\u0627\u0646\u062a\u0632\u0627"
    ],
    "name:fra_x_preferred":[
        "Sanza"
    ],
    "name:hun_x_preferred":[
        "Sanza"
    ],
    "name:hye_x_preferred":[
        "\u054d\u0561\u0576\u0581\u0561"
    ],
    "name:ina_x_preferred":[
        "Sanza"
    ],
    "name:ita_x_preferred":[
        "Sanza"
    ],
    "name:jpn_x_preferred":[
        "\u30b5\u30f3\u30c4\u30a1"
    ],
    "name:kaz_x_preferred":[
        "\u0421\u0430\u043d\u0446\u0430"
    ],
    "name:kor_x_preferred":[
        "\uc0b0\ucc28"
    ],
    "name:lat_x_preferred":[
        "Santia"
    ],
    "name:lmo_x_preferred":[
        "Sanza"
    ],
    "name:msa_x_preferred":[
        "Sanza"
    ],
    "name:nap_x_preferred":[
        "Sanza"
    ],
    "name:nld_x_preferred":[
        "Sanza"
    ],
    "name:pms_x_preferred":[
        "Sanza"
    ],
    "name:pol_x_preferred":[
        "Sanza"
    ],
    "name:por_x_preferred":[
        "Sanza"
    ],
    "name:ron_x_preferred":[
        "Sanza"
    ],
    "name:rus_x_preferred":[
        "\u0421\u0430\u043d\u0446\u0430"
    ],
    "name:scn_x_preferred":[
        "Sanza"
    ],
    "name:spa_x_preferred":[
        "Sanza"
    ],
    "name:srp_x_preferred":[
        "\u0421\u0430\u043d\u0446\u0430"
    ],
    "name:tgl_x_preferred":[
        "Sanza"
    ],
    "name:ukr_x_preferred":[
        "\u0421\u0430\u043d\u0446\u0430"
    ],
    "name:uzb_x_preferred":[
        "Sanza"
    ],
    "name:vec_x_preferred":[
        "Sanza"
    ],
    "name:vie_x_preferred":[
        "Sanza"
    ],
    "name:vol_x_preferred":[
        "Sanza"
    ],
    "name:war_x_preferred":[
        "Sanza"
    ],
    "wof:name":"Sanza",
    "wof:placetype":"locality"
},
  "geometry": {"coordinates":[14.86667,-6.33333],"type":"Point"}
}