{
  "type": "Feature",
  "properties": {
    "gn:admin1_code":"12.0",
    "gn:asciiname":"Mundondo",
    "gn:country_code":"AO",
    "gn:dem":708,
    "gn:feature_class":"P",
    "gn:feature_code":"PPL",
    "gn:name":"Mundondo",
    "gn:population":0,
    "gn:timezone":"Africa/Luanda",
    "iso:country":"AO",
    "wof:name":"Mundondo",
    "wof:placetype":"locality"
},
  "geometry": {"coordinates":[17.41907999999999,-7.88832],"type":"Point"}
}