{
  "type": "Feature",
  "properties": {
    "gn:admin1_code":"2.0",
    "gn:asciiname":"Cavango",
    "gn:cc2":"AO",
    "gn:country_code":"AO",
    "gn:dem":1390,
    "gn:feature_class":"P",
    "gn:feature_code":"PPL",
    "gn:name":"Cavango",
    "gn:population":0,
    "gn:timezone":"Africa/Luanda",
    "iso:country":"AO",
    "name:und_x_variant":[
        "Ganangua",
        "Cavango"
    ],
    "wof:name":"Cavango",
    "wof:placetype":"locality"
},
  "geometry": {"coordinates":[17.43333,-12.75],"type":"Point"}
}