{
  "type": "Feature",
  "properties": {
    "gn:admin1_code":"6.0",
    "gn:asciiname":"Quissole",
    "gn:country_code":"AO",
    "gn:dem":1202,
    "gn:feature_class":"P",
    "gn:feature_code":"PPL",
    "gn:name":"Quissole",
    "gn:population":0,
    "gn:timezone":"Africa/Luanda",
    "iso:country":"AO",
    "wof:name":"Quissole",
    "wof:placetype":"locality"
},
  "geometry": {"coordinates":[14.87388,-10.75319],"type":"Point"}
}