{
  "type": "Feature",
  "properties": {
    "gn:admin1_code":"2.0",
    "gn:asciiname":"Maria Teresa",
    "gn:country_code":"AO",
    "gn:dem":1635,
    "gn:feature_class":"P",
    "gn:feature_code":"PPL",
    "gn:name":"Maria Teresa",
    "gn:population":0,
    "gn:timezone":"Africa/Luanda",
    "iso:country":"AO",
    "wof:name":"Maria Teresa",
    "wof:placetype":"locality"
},
  "geometry": {"coordinates":[17.1035,-11.48043],"type":"Point"}
}