{
  "type": "Feature",
  "properties": {
    "gn:admin1_code":"12.0",
    "gn:asciiname":"Canguri",
    "gn:country_code":"AO",
    "gn:dem":1144,
    "gn:feature_class":"P",
    "gn:feature_code":"PPL",
    "gn:name":"Canguri",
    "gn:population":0,
    "gn:timezone":"Africa/Luanda",
    "iso:country":"AO",
    "wof:name":"Canguri",
    "wof:placetype":"locality"
},
  "geometry": {"coordinates":[16.66667,-9.53333],"type":"Point"}
}