{
  "type": "Feature",
  "properties": {
    "gn:admin1_code":"17.0",
    "gn:asciiname":"Camutue",
    "gn:country_code":"AO",
    "gn:dem":691,
    "gn:feature_class":"P",
    "gn:feature_code":"PPL",
    "gn:name":"Cam\u00fatue",
    "gn:population":0,
    "gn:timezone":"Africa/Luanda",
    "iso:country":"AO",
    "wof:name":"Camutue",
    "wof:placetype":"locality"
},
  "geometry": {"coordinates":[17.85336000000001,-8.54811],"type":"Point"}
}