{
  "type": "Feature",
  "properties": {
    "gn:admin1_code":"6.0",
    "gn:asciiname":"Cane",
    "gn:country_code":"AO",
    "gn:dem":1157,
    "gn:feature_class":"P",
    "gn:feature_code":"PPL",
    "gn:name":"Cane",
    "gn:population":0,
    "gn:timezone":"Africa/Luanda",
    "iso:country":"AO",
    "wof:name":"Cane",
    "wof:placetype":"locality"
},
  "geometry": {"coordinates":[14.51491,-11.5074],"type":"Point"}
}