{
  "type": "Feature",
  "properties": {
    "gn:admin1_code":"6.0",
    "gn:asciiname":"Ngolalombo",
    "gn:country_code":"AO",
    "gn:dem":103,
    "gn:feature_class":"P",
    "gn:feature_code":"PPL",
    "gn:name":"Ngolalombo",
    "gn:population":0,
    "gn:timezone":"Africa/Luanda",
    "iso:country":"AO",
    "wof:name":"Ngolalombo",
    "wof:placetype":"locality"
},
  "geometry": {"coordinates":[13.60045,-10.3116],"type":"Point"}
}