{
  "type": "Feature",
  "properties": {
    "gn:admin1_code":"1.0",
    "gn:asciiname":"Catanga",
    "gn:country_code":"AO",
    "gn:dem":1193,
    "gn:feature_class":"P",
    "gn:feature_code":"PPLL",
    "gn:name":"Catanga",
    "gn:population":0,
    "gn:timezone":"Africa/Luanda",
    "iso:country":"AO",
    "wof:name":"Catanga",
    "wof:placetype":"locality"
},
  "geometry": {"coordinates":[14.68912,-12.33542],"type":"Point"}
}