{
  "type": "Feature",
  "properties": {
    "gn:admin1_code":"6.0",
    "gn:asciiname":"Nguendela",
    "gn:country_code":"AO",
    "gn:dem":925,
    "gn:feature_class":"P",
    "gn:feature_code":"PPL",
    "gn:name":"Nguendela",
    "gn:population":0,
    "gn:timezone":"Africa/Luanda",
    "iso:country":"AO",
    "wof:name":"Nguendela",
    "wof:placetype":"locality"
},
  "geometry": {"coordinates":[14.3789,-11.06085],"type":"Point"}
}