{
  "type": "Feature",
  "properties": {
    "gn:admin1_code":"6.0",
    "gn:asciiname":"Lobito",
    "gn:country_code":"AO",
    "gn:dem":1341,
    "gn:feature_class":"P",
    "gn:feature_code":"PPL",
    "gn:name":"Lobito",
    "gn:population":0,
    "gn:timezone":"Africa/Luanda",
    "iso:country":"AO",
    "wof:name":"Lobito",
    "wof:placetype":"locality"
},
  "geometry": {"coordinates":[15.56579,-11.42774],"type":"Point"}
}