{
  "type": "Feature",
  "properties": {
    "gn:admin1_code":"18.0",
    "gn:asciiname":"Chamaba",
    "gn:country_code":"AO",
    "gn:dem":1009,
    "gn:feature_class":"P",
    "gn:feature_code":"PPL",
    "gn:name":"Chamaba",
    "gn:population":0,
    "gn:timezone":"Africa/Luanda",
    "iso:country":"AO",
    "wof:name":"Chamaba",
    "wof:placetype":"locality"
},
  "geometry": {"coordinates":[21.55,-9.51667],"type":"Point"}
}