{
  "type": "Feature",
  "properties": {
    "gn:admin1_code":"1.0",
    "gn:asciiname":"Hanha do Norte",
    "gn:country_code":"AO",
    "gn:dem":83,
    "gn:feature_class":"P",
    "gn:feature_code":"PPL",
    "gn:name":"Hanha do Norte",
    "gn:population":0,
    "gn:timezone":"Africa/Luanda",
    "iso:country":"AO",
    "name:und_x_variant":[
        "Anha",
        "Hanha",
        "Hanha do Norte"
    ],
    "wof:name":"Hanha do Norte",
    "wof:placetype":"locality"
},
  "geometry": {"coordinates":[13.71161,-12.25064],"type":"Point"}
}