{
  "type": "Feature",
  "properties": {
    "gn:admin1_code":"8.0",
    "gn:asciiname":"Duarte",
    "gn:country_code":"AO",
    "gn:dem":1650,
    "gn:feature_class":"P",
    "gn:feature_code":"PPL",
    "gn:name":"Duarte",
    "gn:population":0,
    "gn:timezone":"Africa/Luanda",
    "iso:country":"AO",
    "name:bre_x_preferred":[
        "Duarte"
    ],
    "name:bul_x_preferred":[
        "\u0414\u0443\u0430\u0440\u0442\u0438"
    ],
    "name:ceb_x_preferred":[
        "Duarte"
    ],
    "name:ces_x_preferred":[
        "Duarte"
    ],
    "name:deu_x_preferred":[
        "Duarte"
    ],
    "name:fin_x_preferred":[
        "Duarte"
    ],
    "name:fra_x_preferred":[
        "Duarte"
    ],
    "name:heb_x_preferred":[
        "\u05d3\u05d5\u05d0\u05e8\u05d8\u05d4"
    ],
    "name:hun_x_preferred":[
        "Duarte"
    ],
    "name:ita_x_preferred":[
        "Duarte"
    ],
    "name:jpn_x_preferred":[
        "\u30c9\u30a5\u30a2\u30eb\u30c6"
    ],
    "name:kor_x_preferred":[
        "\ub450\uc544\ub974\ud2b8"
    ],
    "name:nld_x_preferred":[
        "Duarte"
    ],
    "name:pol_x_preferred":[
        "Duarte"
    ],
    "name:por_x_preferred":[
        "Duarte"
    ],
    "name:rus_x_preferred":[
        "\u0414\u0443\u0430\u0440\u0442\u0435"
    ],
    "name:spa_x_preferred":[
        "Duarte"
    ],
    "name:swe_x_preferred":[
        "Duarte"
    ],
    "name:ukr_x_preferred":[
        "\u0414\u0443\u0430\u0440\u0442\u0435"
    ],
    "wof:name":"Duarte",
    "wof:placetype":"locality"
},
  "geometry": {"coordinates":[15.88333,-11.96667],"type":"Point"}
}