{
  "type": "Feature",
  "properties": {
    "gn:admin1_code":"16.0",
    "gn:asciiname":"Vumputo",
    "gn:cc2":"AO",
    "gn:country_code":"AO",
    "gn:dem":190,
    "gn:feature_class":"P",
    "gn:feature_code":"PPL",
    "gn:name":"Vumputo",
    "gn:population":0,
    "gn:timezone":"Africa/Luanda",
    "iso:country":"AO",
    "name:und_x_variant":[
        "Vungo",
        "Vumputo"
    ],
    "wof:name":"Vumputo",
    "wof:placetype":"locality"
},
  "geometry": {"coordinates":[13.33333,-6.03333],"type":"Point"}
}