{
  "type": "Feature",
  "properties": {
    "gn:admin1_code":"19.0",
    "gn:asciiname":"Quibuba",
    "gn:country_code":"AO",
    "gn:dem":834,
    "gn:feature_class":"P",
    "gn:feature_code":"PPL",
    "gn:name":"Quibuba",
    "gn:population":0,
    "gn:timezone":"Africa/Luanda",
    "iso:country":"AO",
    "name:und_x_variant":[
        "Cang\u00falele"
    ],
    "wof:name":"Quibuba",
    "wof:placetype":"locality"
},
  "geometry": {"coordinates":[14.83496,-8.69986],"type":"Point"}
}