{
  "type": "Feature",
  "properties": {
    "gn:admin1_code":"8.0",
    "gn:asciiname":"Joaquim Pinto",
    "gn:country_code":"AO",
    "gn:dem":1634,
    "gn:feature_class":"P",
    "gn:feature_code":"PPL",
    "gn:name":"Joaquim Pinto",
    "gn:population":0,
    "gn:timezone":"Africa/Luanda",
    "iso:country":"AO",
    "name:cat_x_preferred":[
        "Joaquim Pinto"
    ],
    "name:deu_x_preferred":[
        "Joaquim Pinto"
    ],
    "name:fra_x_preferred":[
        "Joaquim Pinto"
    ],
    "name:kor_x_preferred":[
        "\uc870\uc544\ud0b9 \ud540\ud22c"
    ],
    "name:por_x_preferred":[
        "Joaquim Pinto"
    ],
    "wof:name":"Joaquim Pinto",
    "wof:placetype":"locality"
},
  "geometry": {"coordinates":[15.43333,-13.13333],"type":"Point"}
}