{
  "type": "Feature",
  "properties": {
    "gn:admin1_code":"15.0",
    "gn:asciiname":"Mbanza Maconda",
    "gn:country_code":"AO",
    "gn:dem":979,
    "gn:feature_class":"P",
    "gn:feature_code":"PPL",
    "gn:name":"Mbanza Maconda",
    "gn:population":0,
    "gn:timezone":"Africa/Luanda",
    "iso:country":"AO",
    "wof:name":"Mbanza Maconda",
    "wof:placetype":"locality"
},
  "geometry": {"coordinates":[15.98947,-7.24582],"type":"Point"}
}