{
  "type": "Feature",
  "properties": {
    "gn:admin1_code":"15.0",
    "gn:asciiname":"Cambamba",
    "gn:country_code":"AO",
    "gn:dem":805,
    "gn:feature_class":"P",
    "gn:feature_code":"PPL",
    "gn:name":"Cambamba",
    "gn:population":0,
    "gn:timezone":"Africa/Luanda",
    "iso:country":"AO",
    "name:por_x_preferred":[
        "Cambamba"
    ],
    "wof:name":"Cambamba",
    "wof:placetype":"locality"
},
  "geometry": {"coordinates":[16.52873,-6.56912],"type":"Point"}
}