{
  "type": "Feature",
  "properties": {
    "gn:admin1_code":"15.0",
    "gn:asciiname":"Quimombo",
    "gn:country_code":"AO",
    "gn:dem":612,
    "gn:feature_class":"P",
    "gn:feature_code":"PPL",
    "gn:name":"Quimombo",
    "gn:population":0,
    "gn:timezone":"Africa/Luanda",
    "iso:country":"AO",
    "name:por_x_preferred":[
        "Quimombo"
    ],
    "name:und_x_variant":[
        "Quimiamba",
        "Quimbengue"
    ],
    "wof:name":"Quimombo",
    "wof:placetype":"locality"
},
  "geometry": {"coordinates":[16.03318,-6.01261],"type":"Point"}
}