{
  "type": "Feature",
  "properties": {
    "gn:admin1_code":"4.0",
    "gn:asciiname":"Vioto",
    "gn:country_code":"AO",
    "gn:dem":1318,
    "gn:feature_class":"P",
    "gn:feature_code":"PPL",
    "gn:name":"Vioto",
    "gn:population":0,
    "gn:timezone":"Africa/Luanda",
    "iso:country":"AO",
    "wof:name":"Vioto",
    "wof:placetype":"locality"
},
  "geometry": {"coordinates":[17.68942000000001,-14.74642],"type":"Point"}
}