{
  "type": "Feature",
  "properties": {
    "gn:admin1_code":"6.0",
    "gn:asciiname":"Quimbambane",
    "gn:country_code":"AO",
    "gn:dem":1291,
    "gn:feature_class":"P",
    "gn:feature_code":"PPL",
    "gn:name":"Quimbambane",
    "gn:population":0,
    "gn:timezone":"Africa/Luanda",
    "iso:country":"AO",
    "wof:name":"Quimbambane",
    "wof:placetype":"locality"
},
  "geometry": {"coordinates":[15.35923,-10.42348],"type":"Point"}
}