{
  "type": "Feature",
  "properties": {
    "gn:admin1_code":"19.0",
    "gn:asciiname":"Ngombe Ia Quimenga",
    "gn:country_code":"AO",
    "gn:dem":959,
    "gn:feature_class":"P",
    "gn:feature_code":"PPL",
    "gn:name":"Ngombe I\u00e1 Quimenga",
    "gn:population":0,
    "gn:timezone":"Africa/Luanda",
    "iso:country":"AO",
    "wof:name":"Ngombe Ia Quimenga",
    "wof:placetype":"locality"
},
  "geometry": {"coordinates":[14.72034,-8.67526],"type":"Point"}
}