{
  "type": "Feature",
  "properties": {
    "gn:admin1_code":"15.0",
    "gn:asciiname":"Quinzala Capuri",
    "gn:country_code":"AO",
    "gn:dem":1210,
    "gn:feature_class":"P",
    "gn:feature_code":"PPL",
    "gn:name":"Quinzala Capuri",
    "gn:population":0,
    "gn:timezone":"Africa/Luanda",
    "iso:country":"AO",
    "wof:name":"Quinzala Capuri",
    "wof:placetype":"locality"
},
  "geometry": {"coordinates":[15.13938,-7.28218],"type":"Point"}
}