{
  "type": "Feature",
  "properties": {
    "gn:admin1_code":"12.0",
    "gn:asciiname":"Sandala",
    "gn:country_code":"AO",
    "gn:dem":1373,
    "gn:feature_class":"P",
    "gn:feature_code":"PPL",
    "gn:name":"Sandala",
    "gn:population":0,
    "gn:timezone":"Africa/Luanda",
    "iso:country":"AO",
    "name:ceb_x_preferred":[
        "Sandala"
    ],
    "name:swe_x_preferred":[
        "Sandala"
    ],
    "wof:name":"Sandala",
    "wof:placetype":"locality"
},
  "geometry": {"coordinates":[18.30756,-11.02613],"type":"Point"}
}