{
  "type": "Feature",
  "properties": {
    "gn:admin1_code":"1.0",
    "gn:asciiname":"Cuconda",
    "gn:country_code":"AO",
    "gn:dem":1153,
    "gn:feature_class":"P",
    "gn:feature_code":"PPL",
    "gn:name":"Cuconda",
    "gn:population":0,
    "gn:timezone":"Africa/Luanda",
    "iso:country":"AO",
    "wof:name":"Cuconda",
    "wof:placetype":"locality"
},
  "geometry": {"coordinates":[14.03333,-12.58333],"type":"Point"}
}