{
  "type": "Feature",
  "properties": {
    "gn:admin1_code":"1.0",
    "gn:asciiname":"Calenguer",
    "gn:country_code":"AO",
    "gn:dem":892,
    "gn:feature_class":"P",
    "gn:feature_code":"PPL",
    "gn:name":"Calenguer",
    "gn:population":0,
    "gn:timezone":"Africa/Luanda",
    "iso:country":"AO",
    "wof:name":"Calenguer",
    "wof:placetype":"locality"
},
  "geometry": {"coordinates":[14.23333,-13.05],"type":"Point"}
}