{
  "type": "Feature",
  "properties": {
    "gn:admin1_code":"6.0",
    "gn:asciiname":"Cacuaco",
    "gn:cc2":"AO",
    "gn:country_code":"AO",
    "gn:dem":235,
    "gn:feature_class":"P",
    "gn:feature_code":"PPL",
    "gn:name":"Cacuaco",
    "gn:population":0,
    "gn:timezone":"Africa/Luanda",
    "iso:country":"AO",
    "name:cat_x_preferred":[
        "Cacuaco"
    ],
    "name:ceb_x_preferred":[
        "Cacuaco Municipality"
    ],
    "name:deu_x_preferred":[
        "Cacuaco"
    ],
    "name:fra_x_preferred":[
        "Cacuaco"
    ],
    "name:ita_x_preferred":[
        "Cacuaco"
    ],
    "name:msa_x_preferred":[
        "Cacuaco"
    ],
    "name:por_x_preferred":[
        "Cacuaco"
    ],
    "name:spa_x_preferred":[
        "Cacuaco"
    ],
    "name:swe_x_preferred":[
        "Cacuaco"
    ],
    "name:und_x_variant":[
        "Cua"
    ],
    "name:zho_x_preferred":[
        "\u5361\u5938\u79d1"
    ],
    "wof:name":"Cacuaco",
    "wof:placetype":"locality"
},
  "geometry": {"coordinates":[14.23333,-10.81667],"type":"Point"}
}