{
  "type": "Feature",
  "properties": {
    "gn:admin1_code":"6.0",
    "gn:asciiname":"Bondo Pequeno",
    "gn:country_code":"AO",
    "gn:dem":1181,
    "gn:feature_class":"P",
    "gn:feature_code":"PPL",
    "gn:name":"Bondo Pequeno",
    "gn:population":0,
    "gn:timezone":"Africa/Luanda",
    "iso:country":"AO",
    "wof:name":"Bondo Pequeno",
    "wof:placetype":"locality"
},
  "geometry": {"coordinates":[14.79482,-10.78453],"type":"Point"}
}