{
  "type": "Feature",
  "properties": {
    "gn:admin1_code":"17.0",
    "gn:asciiname":"Valodia",
    "gn:country_code":"AO",
    "gn:dem":1001,
    "gn:feature_class":"P",
    "gn:feature_code":"PPL",
    "gn:name":"Val\u00f3dia",
    "gn:population":0,
    "gn:timezone":"Africa/Luanda",
    "iso:country":"AO",
    "wof:name":"Valodia",
    "wof:placetype":"locality"
},
  "geometry": {"coordinates":[17.80522999999999,-9.50843],"type":"Point"}
}