{
  "type": "Feature",
  "properties": {
    "gn:admin1_code":"8.0",
    "gn:asciiname":"Ecunna",
    "gn:cc2":"AO",
    "gn:country_code":"AO",
    "gn:dem":1742,
    "gn:feature_class":"P",
    "gn:feature_code":"PPL",
    "gn:name":"Ecunna",
    "gn:population":0,
    "gn:timezone":"Africa/Luanda",
    "iso:country":"AO",
    "name:und_x_variant":[
        "Vila Flor",
        "Ekunha",
        "Ecunna"
    ],
    "wof:name":"Ecunna",
    "wof:placetype":"locality"
},
  "geometry": {"coordinates":[15.50556,-12.67889],"type":"Point"}
}