{
  "type": "Feature",
  "properties": {
    "gn:admin1_code":"5.0",
    "gn:asciiname":"Quirianga",
    "gn:country_code":"AO",
    "gn:dem":1066,
    "gn:feature_class":"P",
    "gn:feature_code":"PPL",
    "gn:name":"Quirianga",
    "gn:population":0,
    "gn:timezone":"Africa/Luanda",
    "iso:country":"AO",
    "wof:name":"Quirianga",
    "wof:placetype":"locality"
},
  "geometry": {"coordinates":[15.5811,-9.00288],"type":"Point"}
}