{
  "type": "Feature",
  "properties": {
    "gn:admin1_code":"4.0",
    "gn:asciiname":"Sacachai",
    "gn:cc2":"AO",
    "gn:country_code":"AO",
    "gn:dem":1087,
    "gn:feature_class":"P",
    "gn:feature_code":"PPL",
    "gn:name":"Sacachai",
    "gn:population":0,
    "gn:timezone":"Africa/Luanda",
    "iso:country":"AO",
    "name:und_x_variant":[
        "Sacatxai",
        "Sacachai"
    ],
    "wof:name":"Sacachai",
    "wof:placetype":"locality"
},
  "geometry": {"coordinates":[20.66667,-17.03333],"type":"Point"}
}