{
  "type": "Feature",
  "properties": {
    "gn:admin1_code":"12.0",
    "gn:asciiname":"Catoxi",
    "gn:country_code":"AO",
    "gn:dem":1073,
    "gn:feature_class":"P",
    "gn:feature_code":"PPL",
    "gn:name":"Catoxi",
    "gn:population":0,
    "gn:timezone":"Africa/Luanda",
    "iso:country":"AO",
    "wof:name":"Catoxi",
    "wof:placetype":"locality"
},
  "geometry": {"coordinates":[16.37743,-8.21583],"type":"Point"}
}