{
  "type": "Feature",
  "properties": {
    "gn:admin1_code":"1.0",
    "gn:asciiname":"Bumba",
    "gn:country_code":"AO",
    "gn:dem":1040,
    "gn:feature_class":"P",
    "gn:feature_code":"PPL",
    "gn:name":"Bumba",
    "gn:population":0,
    "gn:timezone":"Africa/Luanda",
    "iso:country":"AO",
    "wof:name":"Bumba",
    "wof:placetype":"locality"
},
  "geometry": {"coordinates":[14.26667,-12.06667],"type":"Point"}
}