{
  "type": "Feature",
  "properties": {
    "gn:admin1_code":"6.0",
    "gn:asciiname":"Camanda",
    "gn:country_code":"AO",
    "gn:dem":1046,
    "gn:feature_class":"P",
    "gn:feature_code":"PPL",
    "gn:name":"Camanda",
    "gn:population":0,
    "gn:timezone":"Africa/Luanda",
    "iso:country":"AO",
    "wof:name":"Camanda",
    "wof:placetype":"locality"
},
  "geometry": {"coordinates":[14.46534,-10.65129],"type":"Point"}
}