{
  "type": "Feature",
  "properties": {
    "gn:admin1_code":"15.0",
    "gn:asciiname":"Quisongo",
    "gn:country_code":"AO",
    "gn:dem":870,
    "gn:feature_class":"P",
    "gn:feature_code":"PPL",
    "gn:name":"Quisongo",
    "gn:population":0,
    "gn:timezone":"Africa/Luanda",
    "iso:country":"AO",
    "wof:name":"Quisongo",
    "wof:placetype":"locality"
},
  "geometry": {"coordinates":[15.1951,-6.29872],"type":"Point"}
}