{
  "type": "Feature",
  "properties": {
    "gn:admin1_code":"14.0",
    "gn:asciiname":"Calai",
    "gn:country_code":"AO",
    "gn:dem":1104,
    "gn:feature_class":"P",
    "gn:feature_code":"PPL",
    "gn:name":"Calai",
    "gn:population":0,
    "gn:timezone":"Africa/Luanda",
    "iso:country":"AO",
    "name:cat_x_preferred":[
        "Calai"
    ],
    "name:deu_x_preferred":[
        "Calai"
    ],
    "name:ita_x_preferred":[
        "Kalai"
    ],
    "name:por_x_preferred":[
        "Calai"
    ],
    "name:spa_x_preferred":[
        "Calai"
    ],
    "name:zho_x_preferred":[
        "\u5361\u62c9\u4f0a"
    ],
    "wof:name":"Calai",
    "wof:placetype":"locality"
},
  "geometry": {"coordinates":[21.92826,-11.33184],"type":"Point"}
}