{
  "type": "Feature",
  "properties": {
    "gn:admin1_code":"19.0",
    "gn:asciiname":"Porto Quipiri",
    "gn:cc2":"AO",
    "gn:country_code":"AO",
    "gn:dem":30,
    "gn:feature_class":"P",
    "gn:feature_code":"PPL",
    "gn:name":"Porto Quipiri",
    "gn:population":0,
    "gn:timezone":"Africa/Luanda",
    "iso:country":"AO",
    "name:und_x_variant":[
        "Quipini",
        "Porto Quipire",
        "Porto Quipiye",
        "Porto Quipiri"
    ],
    "wof:name":"Porto Quipiri",
    "wof:placetype":"locality"
},
  "geometry": {"coordinates":[13.55611,-8.61306],"type":"Point"}
}