{
  "type": "Feature",
  "properties": {
    "gn:admin1_code":"15.0",
    "gn:asciiname":"Quimbuila",
    "gn:country_code":"AO",
    "gn:dem":905,
    "gn:feature_class":"P",
    "gn:feature_code":"PPL",
    "gn:name":"Quimbuila",
    "gn:population":0,
    "gn:timezone":"Africa/Luanda",
    "iso:country":"AO",
    "wof:name":"Quimbuila",
    "wof:placetype":"locality"
},
  "geometry": {"coordinates":[15.11083,-6.08275],"type":"Point"}
}