{
  "type": "Feature",
  "properties": {
    "gn:admin1_code":"5.0",
    "gn:asciiname":"Camigi",
    "gn:country_code":"AO",
    "gn:dem":1114,
    "gn:feature_class":"P",
    "gn:feature_code":"PPL",
    "gn:name":"Cam\u00edgi",
    "gn:population":0,
    "gn:timezone":"Africa/Luanda",
    "iso:country":"AO",
    "wof:name":"Camigi",
    "wof:placetype":"locality"
},
  "geometry": {"coordinates":[15.59947,-8.97222],"type":"Point"}
}