{
  "type": "Feature",
  "properties": {
    "gn:admin1_code":"9.0",
    "gn:asciiname":"Chitata",
    "gn:country_code":"AO",
    "gn:dem":1627,
    "gn:feature_class":"P",
    "gn:feature_code":"PPL",
    "gn:name":"Chitata",
    "gn:population":0,
    "gn:timezone":"Africa/Luanda",
    "iso:country":"AO",
    "wof:name":"Chitata",
    "wof:placetype":"locality"
},
  "geometry": {"coordinates":[15.71667,-13.75],"type":"Point"}
}