{
  "type": "Feature",
  "properties": {
    "gn:admin1_code":"16.0",
    "gn:asciiname":"Lunguegi",
    "gn:country_code":"AO",
    "gn:dem":417,
    "gn:feature_class":"P",
    "gn:feature_code":"PPL",
    "gn:name":"Lungu\u00e9gi",
    "gn:population":0,
    "gn:timezone":"Africa/Luanda",
    "iso:country":"AO",
    "name:und_x_variant":[
        "Lungueji",
        "Lunguege",
        "Lungu\u00e9gi"
    ],
    "wof:name":"Lunguegi",
    "wof:placetype":"locality"
},
  "geometry": {"coordinates":[14.21834,-6.1839],"type":"Point"}
}