{
  "type": "Feature",
  "properties": {
    "gn:admin1_code":"1.0",
    "gn:asciiname":"Sao Jose",
    "gn:cc2":"AO",
    "gn:country_code":"AO",
    "gn:dem":32,
    "gn:feature_class":"P",
    "gn:feature_code":"PPL",
    "gn:name":"S\u00e3o Jos\u00e9",
    "gn:population":0,
    "gn:timezone":"Africa/Luanda",
    "iso:country":"AO",
    "name:und_x_variant":[
        "Binga",
        "Pescaria Sa\u00f4 Jos\u00e9",
        "S\u00e3o Jos\u00e9"
    ],
    "wof:name":"Sao Jose",
    "wof:placetype":"locality"
},
  "geometry": {"coordinates":[12.65,-13.33333],"type":"Point"}
}