{
  "type": "Feature",
  "properties": {
    "gn:admin1_code":"18.0",
    "gn:asciiname":"Sacaiquele",
    "gn:country_code":"AO",
    "gn:dem":1144,
    "gn:feature_class":"P",
    "gn:feature_code":"PPL",
    "gn:name":"Sacaiquele",
    "gn:population":0,
    "gn:timezone":"Africa/Luanda",
    "iso:country":"AO",
    "wof:name":"Sacaiquele",
    "wof:placetype":"locality"
},
  "geometry": {"coordinates":[20.44833,-10.94611],"type":"Point"}
}