{
  "type": "Feature",
  "properties": {
    "gn:admin1_code":"17.0",
    "gn:asciiname":"Munguanha Segundo",
    "gn:country_code":"AO",
    "gn:dem":775,
    "gn:feature_class":"P",
    "gn:feature_code":"PPL",
    "gn:name":"Munguanha Segundo",
    "gn:population":0,
    "gn:timezone":"Africa/Luanda",
    "iso:country":"AO",
    "wof:name":"Munguanha Segundo",
    "wof:placetype":"locality"
},
  "geometry": {"coordinates":[21.24877,-7.47577],"type":"Point"}
}