{
  "type": "Feature",
  "properties": {
    "gn:admin1_code":"12.0",
    "gn:asciiname":"Cabita",
    "gn:country_code":"AO",
    "gn:dem":1132,
    "gn:feature_class":"P",
    "gn:feature_code":"PPL",
    "gn:name":"Cabita",
    "gn:population":0,
    "gn:timezone":"Africa/Luanda",
    "iso:country":"AO",
    "wof:name":"Cabita",
    "wof:placetype":"locality"
},
  "geometry": {"coordinates":[17.1421,-10.31767],"type":"Point"}
}