{
  "type": "Feature",
  "properties": {
    "gn:admin1_code":"8.0",
    "gn:asciiname":"Chambuluca",
    "gn:country_code":"AO",
    "gn:dem":1755,
    "gn:feature_class":"P",
    "gn:feature_code":"PPL",
    "gn:name":"Chambuluca",
    "gn:population":0,
    "gn:timezone":"Africa/Luanda",
    "iso:country":"AO",
    "wof:name":"Chambuluca",
    "wof:placetype":"locality"
},
  "geometry": {"coordinates":[15.535,-12.70806],"type":"Point"}
}