{
  "type": "Feature",
  "properties": {
    "gn:admin1_code":"15.0",
    "gn:asciiname":"Biri",
    "gn:country_code":"AO",
    "gn:dem":1249,
    "gn:feature_class":"P",
    "gn:feature_code":"PPL",
    "gn:name":"Biri",
    "gn:population":0,
    "gn:timezone":"Africa/Luanda",
    "iso:country":"AO",
    "name:ceb_x_preferred":[
        "Biri"
    ],
    "name:ces_x_preferred":[
        "Biri"
    ],
    "name:deu_x_preferred":[
        "Biri"
    ],
    "name:fra_x_preferred":[
        "Biri"
    ],
    "name:hun_x_preferred":[
        "Biri"
    ],
    "name:ita_x_preferred":[
        "Biri"
    ],
    "name:swe_x_preferred":[
        "Biri"
    ],
    "name:tgl_x_preferred":[
        "Biri"
    ],
    "name:und_x_variant":[
        "Bir",
        "Bire"
    ],
    "wof:name":"Biri",
    "wof:placetype":"locality"
},
  "geometry": {"coordinates":[15.54045,-8.03203],"type":"Point"}
}