{
  "type": "Feature",
  "properties": {
    "gn:admin1_code":"17.0",
    "gn:asciiname":"Mungo",
    "gn:cc2":"AO",
    "gn:country_code":"AO",
    "gn:dem":827,
    "gn:feature_class":"P",
    "gn:feature_code":"PPL",
    "gn:name":"Mungo",
    "gn:population":0,
    "gn:timezone":"Africa/Luanda",
    "iso:country":"AO",
    "name:ceb_x_preferred":[
        "Mungo"
    ],
    "name:ces_x_preferred":[
        "Mungo"
    ],
    "name:deu_x_preferred":[
        "Mungo"
    ],
    "name:fra_x_preferred":[
        "Mungo"
    ],
    "name:pol_x_preferred":[
        "Mungo"
    ],
    "name:rus_x_preferred":[
        "\u041c\u0443\u043d\u0433\u0443"
    ],
    "name:rus_x_variant":[
        "\u041c\u0443\u043d\u0433\u043e"
    ],
    "name:swe_x_preferred":[
        "Mungo"
    ],
    "name:und_x_variant":[
        "Karumbu",
        "Carumbo"
    ],
    "wof:name":"Mungo",
    "wof:placetype":"locality"
},
  "geometry": {"coordinates":[19.93333,-7.73333],"type":"Point"}
}