{
  "type": "Feature",
  "properties": {
    "gn:admin1_code":"2.0",
    "gn:asciiname":"Enhuangule",
    "gn:country_code":"AO",
    "gn:dem":1716,
    "gn:feature_class":"P",
    "gn:feature_code":"PPL",
    "gn:name":"Enhuangule",
    "gn:population":0,
    "gn:timezone":"Africa/Luanda",
    "iso:country":"AO",
    "wof:name":"Enhuangule",
    "wof:placetype":"locality"
},
  "geometry": {"coordinates":[16.76278,-11.73489],"type":"Point"}
}