{
  "type": "Feature",
  "properties": {
    "gn:admin1_code":"6.0",
    "gn:asciiname":"Ulumbo",
    "gn:country_code":"AO",
    "gn:dem":961,
    "gn:feature_class":"P",
    "gn:feature_code":"PPL",
    "gn:name":"Ulumbo",
    "gn:population":0,
    "gn:timezone":"Africa/Luanda",
    "iso:country":"AO",
    "wof:name":"Ulumbo",
    "wof:placetype":"locality"
},
  "geometry": {"coordinates":[15.38333,-9.98333],"type":"Point"}
}