{
  "type": "Feature",
  "properties": {
    "gn:admin1_code":"8.0",
    "gn:asciiname":"Cavir",
    "gn:cc2":"AO",
    "gn:country_code":"AO",
    "gn:dem":1520,
    "gn:feature_class":"P",
    "gn:feature_code":"PPL",
    "gn:name":"Cavir",
    "gn:population":0,
    "gn:timezone":"Africa/Luanda",
    "iso:country":"AO",
    "name:und_x_variant":[
        "Cabir",
        "Cavir"
    ],
    "wof:name":"Cavir",
    "wof:placetype":"locality"
},
  "geometry": {"coordinates":[16.28333,-11.71667],"type":"Point"}
}