{
  "type": "Feature",
  "properties": {
    "gn:admin1_code":"15.0",
    "gn:asciiname":"Vamba",
    "gn:country_code":"AO",
    "gn:dem":771,
    "gn:feature_class":"P",
    "gn:feature_code":"PPL",
    "gn:name":"Vamba",
    "gn:population":0,
    "gn:timezone":"Africa/Luanda",
    "iso:country":"AO",
    "name:epo_x_preferred":[
        "Luigi Bertelli"
    ],
    "name:fra_x_preferred":[
        "Luigi Bertelli"
    ],
    "name:ita_x_preferred":[
        "Luigi Bertelli"
    ],
    "name:pol_x_preferred":[
        "Luigi Bertelli"
    ],
    "wof:name":"Vamba",
    "wof:placetype":"locality"
},
  "geometry": {"coordinates":[14.95886,-7.97565],"type":"Point"}
}