{
  "type": "Feature",
  "properties": {
    "gn:admin1_code":"15.0",
    "gn:asciiname":"Quicanga",
    "gn:country_code":"AO",
    "gn:dem":1024,
    "gn:feature_class":"P",
    "gn:feature_code":"PPL",
    "gn:name":"Quicanga",
    "gn:population":0,
    "gn:timezone":"Africa/Luanda",
    "iso:country":"AO",
    "name:und_x_variant":[
        "Zunga"
    ],
    "wof:name":"Quicanga",
    "wof:placetype":"locality"
},
  "geometry": {"coordinates":[15.02277,-6.64005],"type":"Point"}
}