{
  "type": "Feature",
  "properties": {
    "gn:admin1_code":"15.0",
    "gn:asciiname":"Ncondo-Lembe",
    "gn:country_code":"AO",
    "gn:dem":917,
    "gn:feature_class":"P",
    "gn:feature_code":"PPL",
    "gn:name":"Ncondo-Lembe",
    "gn:population":0,
    "gn:timezone":"Africa/Luanda",
    "iso:country":"AO",
    "wof:name":"Ncondo-Lembe",
    "wof:placetype":"locality"
},
  "geometry": {"coordinates":[15.09779,-6.1126],"type":"Point"}
}