{
  "type": "Feature",
  "properties": {
    "gn:admin1_code":"12.0",
    "gn:asciiname":"Xiquita",
    "gn:country_code":"AO",
    "gn:dem":1006,
    "gn:feature_class":"P",
    "gn:feature_code":"PPL",
    "gn:name":"Xiquita",
    "gn:population":0,
    "gn:timezone":"Africa/Luanda",
    "iso:country":"AO",
    "wof:name":"Xiquita",
    "wof:placetype":"locality"
},
  "geometry": {"coordinates":[16.39337,-8.57581],"type":"Point"}
}