{
  "type": "Feature",
  "properties": {
    "gn:admin1_code":"8.0",
    "gn:asciiname":"Lominga",
    "gn:country_code":"AO",
    "gn:dem":1618,
    "gn:feature_class":"P",
    "gn:feature_code":"PPL",
    "gn:name":"Lominga",
    "gn:population":0,
    "gn:timezone":"Africa/Luanda",
    "iso:country":"AO",
    "wof:name":"Lominga",
    "wof:placetype":"locality"
},
  "geometry": {"coordinates":[15.86667,-12.65],"type":"Point"}
}