{
  "type": "Feature",
  "properties": {
    "gn:admin1_code":"1.0",
    "gn:asciiname":"Calindo",
    "gn:cc2":"AO",
    "gn:country_code":"AO",
    "gn:dem":1242,
    "gn:feature_class":"P",
    "gn:feature_code":"PPL",
    "gn:name":"Calindo",
    "gn:population":0,
    "gn:timezone":"Africa/Luanda",
    "iso:country":"AO",
    "name:und_x_variant":[
        "Ant\u00f3nio N. Silva",
        "Calindo"
    ],
    "wof:name":"Calindo",
    "wof:placetype":"locality"
},
  "geometry": {"coordinates":[14.66667,-12.81667],"type":"Point"}
}