{
  "type": "Feature",
  "properties": {
    "gn:admin1_code":"18.0",
    "gn:asciiname":"Ngando",
    "gn:country_code":"AO",
    "gn:dem":1074,
    "gn:feature_class":"P",
    "gn:feature_code":"PPL",
    "gn:name":"Ngando",
    "gn:population":0,
    "gn:timezone":"Africa/Luanda",
    "iso:country":"AO",
    "name:ceb_x_preferred":[
        "Ngando"
    ],
    "name:deu_x_preferred":[
        "Ngando"
    ],
    "name:swe_x_preferred":[
        "Ngando"
    ],
    "name:und_x_variant":[
        "Salumbo"
    ],
    "wof:name":"Ngando",
    "wof:placetype":"locality"
},
  "geometry": {"coordinates":[20.22877,-9.60222],"type":"Point"}
}