{
  "type": "Feature",
  "properties": {
    "gn:admin1_code":"16.0",
    "gn:asciiname":"Zamba",
    "gn:country_code":"AO",
    "gn:dem":648,
    "gn:feature_class":"P",
    "gn:feature_code":"PPL",
    "gn:name":"Zamba",
    "gn:population":0,
    "gn:timezone":"Africa/Luanda",
    "iso:country":"AO",
    "name:ceb_x_preferred":[
        "Zamba"
    ],
    "name:swe_x_preferred":[
        "Zamba"
    ],
    "wof:name":"Zamba",
    "wof:placetype":"locality"
},
  "geometry": {"coordinates":[14.33333,-6.48333],"type":"Point"}
}