{
  "type": "Feature",
  "properties": {
    "gn:admin1_code":"5.0",
    "gn:asciiname":"Santa Maria",
    "gn:country_code":"AO",
    "gn:dem":669,
    "gn:feature_class":"P",
    "gn:feature_code":"PPL",
    "gn:name":"Santa Maria",
    "gn:population":0,
    "gn:timezone":"Africa/Luanda",
    "iso:country":"AO",
    "wof:name":"Santa Maria",
    "wof:placetype":"locality"
},
  "geometry": {"coordinates":[14.69642,-9.07109],"type":"Point"}
}