{
  "type": "Feature",
  "properties": {
    "gn:admin1_code":"6.0",
    "gn:asciiname":"Chiongo",
    "gn:country_code":"AO",
    "gn:dem":1099,
    "gn:feature_class":"P",
    "gn:feature_code":"PPL",
    "gn:name":"Chiongo",
    "gn:population":0,
    "gn:timezone":"Africa/Luanda",
    "iso:country":"AO",
    "wof:name":"Chiongo",
    "wof:placetype":"locality"
},
  "geometry": {"coordinates":[14.33333,-11.48333],"type":"Point"}
}