{
  "type": "Feature",
  "properties": {
    "gn:admin1_code":"5.0",
    "gn:asciiname":"Cerca",
    "gn:country_code":"AO",
    "gn:dem":532,
    "gn:feature_class":"P",
    "gn:feature_code":"PPL",
    "gn:name":"Cerca",
    "gn:population":0,
    "gn:timezone":"Africa/Luanda",
    "iso:country":"AO",
    "wof:name":"Cerca",
    "wof:placetype":"locality"
},
  "geometry": {"coordinates":[14.56667,-9.06667],"type":"Point"}
}