{
  "type": "Feature",
  "properties": {
    "gn:admin1_code":"15.0",
    "gn:asciiname":"Saquela",
    "gn:country_code":"AO",
    "gn:dem":1174,
    "gn:feature_class":"P",
    "gn:feature_code":"PPL",
    "gn:name":"Saquela",
    "gn:population":0,
    "gn:timezone":"Africa/Luanda",
    "iso:country":"AO",
    "wof:name":"Saquela",
    "wof:placetype":"locality"
},
  "geometry": {"coordinates":[15.65,-8.01667],"type":"Point"}
}