{
  "type": "Feature",
  "properties": {
    "gn:admin1_code":"15.0",
    "gn:asciiname":"Benfica",
    "gn:country_code":"AO",
    "gn:dem":1084,
    "gn:feature_class":"P",
    "gn:feature_code":"PPL",
    "gn:name":"Benfica",
    "gn:population":0,
    "gn:timezone":"Africa/Luanda",
    "iso:country":"AO",
    "wof:name":"Benfica",
    "wof:placetype":"locality"
},
  "geometry": {"coordinates":[15.93809,-7.72954],"type":"Point"}
}