{
  "type": "Feature",
  "properties": {
    "gn:admin1_code":"6.0",
    "gn:asciiname":"Sambele",
    "gn:country_code":"AO",
    "gn:dem":828,
    "gn:feature_class":"P",
    "gn:feature_code":"PPLL",
    "gn:name":"Sambele",
    "gn:population":0,
    "gn:timezone":"Africa/Luanda",
    "iso:country":"AO",
    "wof:name":"Sambele",
    "wof:placetype":"locality"
},
  "geometry": {"coordinates":[14.41336,-11.05293],"type":"Point"}
}