{
  "type": "Feature",
  "properties": {
    "gn:admin1_code":"5.0",
    "gn:asciiname":"Luamba Munuma",
    "gn:country_code":"AO",
    "gn:dem":1228,
    "gn:feature_class":"P",
    "gn:feature_code":"PPL",
    "gn:name":"Luamba Munuma",
    "gn:population":0,
    "gn:timezone":"Africa/Luanda",
    "iso:country":"AO",
    "name:und_x_variant":[
        "Quambalanuma",
        "Munuma Luamba",
        "Luamba Munuma"
    ],
    "wof:name":"Luamba Munuma",
    "wof:placetype":"locality"
},
  "geometry": {"coordinates":[15.71014,-8.2622],"type":"Point"}
}