{
  "type": "Feature",
  "properties": {
    "gn:admin1_code":"15.0",
    "gn:asciiname":"Quimbala Zolele",
    "gn:country_code":"AO",
    "gn:dem":923,
    "gn:feature_class":"P",
    "gn:feature_code":"PPL",
    "gn:name":"Quimbala Zol\u00e9le",
    "gn:population":0,
    "gn:timezone":"Africa/Luanda",
    "iso:country":"AO",
    "wof:name":"Quimbala Zolele",
    "wof:placetype":"locality"
},
  "geometry": {"coordinates":[15.58957,-6.60914],"type":"Point"}
}