{
  "type": "Feature",
  "properties": {
    "gn:admin1_code":"16.0",
    "gn:asciiname":"Quifuma",
    "gn:country_code":"AO",
    "gn:dem":34,
    "gn:feature_class":"P",
    "gn:feature_code":"PPL",
    "gn:name":"Quifuma",
    "gn:population":0,
    "gn:timezone":"Africa/Luanda",
    "iso:country":"AO",
    "name:und_x_variant":[
        "Kifuma",
        "Quifuma"
    ],
    "wof:name":"Quifuma",
    "wof:placetype":"locality"
},
  "geometry": {"coordinates":[12.4323,-6.36908],"type":"Point"}
}