{
  "type": "Feature",
  "properties": {
    "gn:admin1_code":"6.0",
    "gn:asciiname":"Banza",
    "gn:country_code":"AO",
    "gn:dem":1359,
    "gn:feature_class":"P",
    "gn:feature_code":"PPL",
    "gn:name":"Banza",
    "gn:population":0,
    "gn:timezone":"Africa/Luanda",
    "iso:country":"AO",
    "name:ceb_x_preferred":[
        "Banza"
    ],
    "name:swe_x_preferred":[
        "Banza"
    ],
    "wof:name":"Banza",
    "wof:placetype":"locality"
},
  "geometry": {"coordinates":[15.51868,-10.82728],"type":"Point"}
}