{
  "type": "Feature",
  "properties": {
    "gn:admin1_code":"15.0",
    "gn:asciiname":"Manuela Paca",
    "gn:country_code":"AO",
    "gn:dem":911,
    "gn:feature_class":"P",
    "gn:feature_code":"PPL",
    "gn:name":"Manuela Paca",
    "gn:population":0,
    "gn:timezone":"Africa/Luanda",
    "iso:country":"AO",
    "wof:name":"Manuela Paca",
    "wof:placetype":"locality"
},
  "geometry": {"coordinates":[15.98719,-7.3272],"type":"Point"}
}