{
  "type": "Feature",
  "properties": {
    "gn:admin1_code":"15.0",
    "gn:asciiname":"Quintadi",
    "gn:country_code":"AO",
    "gn:dem":882,
    "gn:feature_class":"P",
    "gn:feature_code":"PPL",
    "gn:name":"Quintadi",
    "gn:population":0,
    "gn:timezone":"Africa/Luanda",
    "iso:country":"AO",
    "wof:name":"Quintadi",
    "wof:placetype":"locality"
},
  "geometry": {"coordinates":[15.20536,-6.08972],"type":"Point"}
}