{
  "type": "Feature",
  "properties": {
    "gn:admin1_code":"12.0",
    "gn:asciiname":"Caxinge",
    "gn:country_code":"AO",
    "gn:dem":930,
    "gn:feature_class":"P",
    "gn:feature_code":"PPL",
    "gn:name":"Caxinge",
    "gn:population":0,
    "gn:timezone":"Africa/Luanda",
    "iso:country":"AO",
    "wof:name":"Caxinge",
    "wof:placetype":"locality"
},
  "geometry": {"coordinates":[15.71667,-9.18333],"type":"Point"}
}