{
  "type": "Feature",
  "properties": {
    "gn:admin1_code":"12.0",
    "gn:asciiname":"Camizue",
    "gn:country_code":"AO",
    "gn:dem":1091,
    "gn:feature_class":"P",
    "gn:feature_code":"PPL",
    "gn:name":"Camizue",
    "gn:population":0,
    "gn:timezone":"Africa/Luanda",
    "iso:country":"AO",
    "wof:name":"Camizue",
    "wof:placetype":"locality"
},
  "geometry": {"coordinates":[16.24833,-9.63194],"type":"Point"}
}