{
  "type": "Feature",
  "properties": {
    "gn:admin1_code":"8.0",
    "gn:asciiname":"Evaristo",
    "gn:country_code":"AO",
    "gn:dem":1594,
    "gn:feature_class":"P",
    "gn:feature_code":"PPL",
    "gn:name":"Evaristo",
    "gn:population":0,
    "gn:timezone":"Africa/Luanda",
    "iso:country":"AO",
    "wof:name":"Evaristo",
    "wof:placetype":"locality"
},
  "geometry": {"coordinates":[15.31667,-12.31667],"type":"Point"}
}