{
  "type": "Feature",
  "properties": {
    "gn:admin1_code":"8.0",
    "gn:asciiname":"Lienque",
    "gn:country_code":"AO",
    "gn:dem":1843,
    "gn:feature_class":"P",
    "gn:feature_code":"PPL",
    "gn:name":"Lienque",
    "gn:population":0,
    "gn:timezone":"Africa/Luanda",
    "iso:country":"AO",
    "wof:name":"Lienque",
    "wof:placetype":"locality"
},
  "geometry": {"coordinates":[15.18333,-12.38333],"type":"Point"}
}