{
  "type": "Feature",
  "properties": {
    "gn:admin1_code":"18.0",
    "gn:asciiname":"Chauma",
    "gn:country_code":"AO",
    "gn:dem":899,
    "gn:feature_class":"P",
    "gn:feature_code":"PPL",
    "gn:name":"Chauma",
    "gn:population":0,
    "gn:timezone":"Africa/Luanda",
    "iso:country":"AO",
    "wof:name":"Chauma",
    "wof:placetype":"locality"
},
  "geometry": {"coordinates":[20.98333,-8.81667],"type":"Point"}
}