{
  "type": "Feature",
  "properties": {
    "gn:admin1_code":"17.0",
    "gn:asciiname":"Cabuaquesse",
    "gn:country_code":"AO",
    "gn:dem":771,
    "gn:feature_class":"P",
    "gn:feature_code":"PPL",
    "gn:name":"Cabuaquesse",
    "gn:population":0,
    "gn:timezone":"Africa/Luanda",
    "iso:country":"AO",
    "wof:name":"Cabuaquesse",
    "wof:placetype":"locality"
},
  "geometry": {"coordinates":[21.28912,-7.45291],"type":"Point"}
}