{
  "type": "Feature",
  "properties": {
    "gn:admin1_code":"14.0",
    "gn:asciiname":"Lifuti",
    "gn:cc2":"AO",
    "gn:country_code":"AO",
    "gn:dem":1201,
    "gn:feature_class":"P",
    "gn:feature_code":"PPL",
    "gn:name":"Lifuti",
    "gn:population":0,
    "gn:timezone":"Africa/Luanda",
    "iso:country":"AO",
    "name:und_x_variant":[
        "Limbute",
        "Lifuti"
    ],
    "wof:name":"Lifuti",
    "wof:placetype":"locality"
},
  "geometry": {"coordinates":[20.41667,-14.48333],"type":"Point"}
}