{
  "type": "Feature",
  "properties": {
    "gn:admin1_code":"2.0",
    "gn:asciiname":"Savialo",
    "gn:country_code":"AO",
    "gn:dem":1742,
    "gn:feature_class":"P",
    "gn:feature_code":"PPL",
    "gn:name":"Savialo",
    "gn:population":0,
    "gn:timezone":"Africa/Luanda",
    "iso:country":"AO",
    "wof:name":"Savialo",
    "wof:placetype":"locality"
},
  "geometry": {"coordinates":[16.44696,-12.40334],"type":"Point"}
}