{
  "type": "Feature",
  "properties": {
    "gn:admin1_code":"1.0",
    "gn:asciiname":"Condombe",
    "gn:country_code":"AO",
    "gn:dem":987,
    "gn:feature_class":"P",
    "gn:feature_code":"PPL",
    "gn:name":"Condombe",
    "gn:population":0,
    "gn:timezone":"Africa/Luanda",
    "iso:country":"AO",
    "wof:name":"Condombe",
    "wof:placetype":"locality"
},
  "geometry": {"coordinates":[14.28333,-12.85],"type":"Point"}
}