{
  "type": "Feature",
  "properties": {
    "gn:admin1_code":"6.0",
    "gn:asciiname":"Banza de Mussende",
    "gn:country_code":"AO",
    "gn:dem":593,
    "gn:feature_class":"P",
    "gn:feature_code":"PPL",
    "gn:name":"Banza de Mussende",
    "gn:population":0,
    "gn:timezone":"Africa/Luanda",
    "iso:country":"AO",
    "wof:name":"Banza de Mussende",
    "wof:placetype":"locality"
},
  "geometry": {"coordinates":[14.75915,-9.99614],"type":"Point"}
}