{
  "type": "Feature",
  "properties": {
    "gn:admin1_code":"6.0",
    "gn:asciiname":"Mucalanda",
    "gn:country_code":"AO",
    "gn:dem":938,
    "gn:feature_class":"P",
    "gn:feature_code":"PPL",
    "gn:name":"Mucalanda",
    "gn:population":0,
    "gn:timezone":"Africa/Luanda",
    "iso:country":"AO",
    "name:und_x_variant":[
        "Mucalande"
    ],
    "wof:name":"Mucalanda",
    "wof:placetype":"locality"
},
  "geometry": {"coordinates":[14.98243,-9.89753],"type":"Point"}
}