{
  "type": "Feature",
  "properties": {
    "gn:admin1_code":"18.0",
    "gn:asciiname":"Tchipapala",
    "gn:country_code":"AO",
    "gn:dem":1113,
    "gn:feature_class":"P",
    "gn:feature_code":"PPL",
    "gn:name":"Tchipapala",
    "gn:population":0,
    "gn:timezone":"Africa/Luanda",
    "iso:country":"AO",
    "wof:name":"Tchipapala",
    "wof:placetype":"locality"
},
  "geometry": {"coordinates":[20.46016,-9.98653],"type":"Point"}
}