{
  "type": "Feature",
  "properties": {
    "gn:admin1_code":"7.0",
    "gn:asciiname":"Chimbua",
    "gn:cc2":"AO",
    "gn:country_code":"AO",
    "gn:dem":1125,
    "gn:feature_class":"P",
    "gn:feature_code":"PPL",
    "gn:name":"Chimbua",
    "gn:population":0,
    "gn:timezone":"Africa/Luanda",
    "iso:country":"AO",
    "name:und_x_variant":[
        "Vau da Chimbua",
        "Vau de Chimbua",
        "Chimbua"
    ],
    "wof:name":"Chimbua",
    "wof:placetype":"locality"
},
  "geometry": {"coordinates":[15.11667,-16.55],"type":"Point"}
}