{
  "type": "Feature",
  "properties": {
    "gn:admin1_code":"15.0",
    "gn:asciiname":"Lunda",
    "gn:cc2":"AO",
    "gn:country_code":"AO",
    "gn:dem":1224,
    "gn:feature_class":"P",
    "gn:feature_code":"PPL",
    "gn:name":"Lunda",
    "gn:population":0,
    "gn:timezone":"Africa/Luanda",
    "iso:country":"AO",
    "name:bel_x_preferred":[
        "\u041b\u0443\u043d\u0434\u0430"
    ],
    "name:cat_x_preferred":[
        "Lunda"
    ],
    "name:ceb_x_preferred":[
        "Lunda"
    ],
    "name:deu_x_preferred":[
        "Lunda"
    ],
    "name:fra_x_preferred":[
        "Lunda"
    ],
    "name:lin_x_preferred":[
        "Lunda"
    ],
    "name:pol_x_preferred":[
        "Lunda"
    ],
    "name:por_x_preferred":[
        "Lunda"
    ],
    "name:rus_x_preferred":[
        "\u041b\u0443\u043d\u0434\u0430"
    ],
    "name:swe_x_preferred":[
        "Lunda"
    ],
    "name:und_x_variant":[
        "Banza Lunda",
        "Lunda"
    ],
    "wof:name":"Lunda",
    "wof:placetype":"locality"
},
  "geometry": {"coordinates":[15.08333,-7.25],"type":"Point"}
}