{
  "type": "Feature",
  "properties": {
    "gn:admin1_code":"6.0",
    "gn:asciiname":"Jamba",
    "gn:country_code":"AO",
    "gn:dem":1158,
    "gn:feature_class":"P",
    "gn:feature_code":"PPL",
    "gn:name":"Jamba",
    "gn:population":0,
    "gn:timezone":"Africa/Luanda",
    "iso:country":"AO",
    "name:ceb_x_preferred":[
        "Jamba"
    ],
    "name:deu_x_preferred":[
        "Jamba"
    ],
    "name:fin_x_preferred":[
        "Jamba"
    ],
    "name:fra_x_preferred":[
        "Jamba"
    ],
    "name:ita_x_preferred":[
        "Jamba"
    ],
    "name:nds_x_preferred":[
        "Jamba"
    ],
    "name:nld_x_preferred":[
        "Jamba"
    ],
    "name:por_x_preferred":[
        "Jamba"
    ],
    "name:swe_x_preferred":[
        "Jamba"
    ],
    "wof:name":"Jamba",
    "wof:placetype":"locality"
},
  "geometry": {"coordinates":[14.51212,-11.47192],"type":"Point"}
}