{
  "type": "Feature",
  "properties": {
    "gn:admin1_code":"13.0",
    "gn:asciiname":"Cuto",
    "gn:country_code":"AO",
    "gn:dem":498,
    "gn:feature_class":"P",
    "gn:feature_code":"PPL",
    "gn:name":"Cuto",
    "gn:population":0,
    "gn:timezone":"Africa/Luanda",
    "iso:country":"AO",
    "wof:name":"Cuto",
    "wof:placetype":"locality"
},
  "geometry": {"coordinates":[12.84441,-14.90643],"type":"Point"}
}