{
  "type": "Feature",
  "properties": {
    "gn:admin1_code":"15.0",
    "gn:asciiname":"Marian Nguabi",
    "gn:country_code":"AO",
    "gn:dem":1120,
    "gn:feature_class":"P",
    "gn:feature_code":"PPL",
    "gn:name":"Marian Nguabi",
    "gn:population":0,
    "gn:timezone":"Africa/Luanda",
    "iso:country":"AO",
    "wof:name":"Marian Nguabi",
    "wof:placetype":"locality"
},
  "geometry": {"coordinates":[15.33116,-7.12735],"type":"Point"}
}