{
  "type": "Feature",
  "properties": {
    "gn:admin1_code":"0.0",
    "gn:asciiname":"Hieque",
    "gn:country_code":"AO",
    "gn:dem":8,
    "gn:feature_class":"P",
    "gn:feature_code":"PPL",
    "gn:name":"Hieque",
    "gn:population":0,
    "gn:timezone":"Africa/Luanda",
    "iso:country":"AO",
    "wof:name":"Hieque",
    "wof:placetype":"locality"
},
  "geometry": {"coordinates":[12.98583,-12.91528],"type":"Point"}
}