{
  "type": "Feature",
  "properties": {
    "gn:admin1_code":"12.0",
    "gn:asciiname":"Bumba",
    "gn:country_code":"AO",
    "gn:dem":1106,
    "gn:feature_class":"P",
    "gn:feature_code":"PPL",
    "gn:name":"Bumba",
    "gn:population":0,
    "gn:timezone":"Africa/Luanda",
    "iso:country":"AO",
    "name:ceb_x_preferred":[
        "Bumba"
    ],
    "name:deu_x_preferred":[
        "Bumba"
    ],
    "name:fin_x_preferred":[
        "Bumba"
    ],
    "name:fra_x_preferred":[
        "Bumba"
    ],
    "name:heb_x_preferred":[
        "\u05d1\u05d5\u05de\u05d1\u05d4"
    ],
    "name:hun_x_preferred":[
        "Bumba"
    ],
    "name:ind_x_preferred":[
        "Bumba"
    ],
    "name:nld_x_preferred":[
        "Bumba"
    ],
    "name:ron_x_preferred":[
        "Bumba"
    ],
    "name:swe_x_preferred":[
        "Bumba"
    ],
    "name:ukr_x_preferred":[
        "\u0411\u0443\u043c\u0431\u0430"
    ],
    "wof:name":"Bumba",
    "wof:placetype":"locality"
},
  "geometry": {"coordinates":[16.26444,-9.57222],"type":"Point"}
}