{
  "type": "Feature",
  "properties": {
    "gn:admin1_code":"15.0",
    "gn:asciiname":"Baca",
    "gn:country_code":"AO",
    "gn:dem":1244,
    "gn:feature_class":"P",
    "gn:feature_code":"PPL",
    "gn:name":"Baca",
    "gn:population":0,
    "gn:timezone":"Africa/Luanda",
    "iso:country":"AO",
    "wof:name":"Baca",
    "wof:placetype":"locality"
},
  "geometry": {"coordinates":[15.73462,-8.02206],"type":"Point"}
}