{
  "type": "Feature",
  "properties": {
    "gn:admin1_code":"12.0",
    "gn:asciiname":"Camalanga",
    "gn:country_code":"AO",
    "gn:dem":1067,
    "gn:feature_class":"P",
    "gn:feature_code":"PPL",
    "gn:name":"Camalanga",
    "gn:population":0,
    "gn:timezone":"Africa/Luanda",
    "iso:country":"AO",
    "wof:name":"Camalanga",
    "wof:placetype":"locality"
},
  "geometry": {"coordinates":[15.65,-9.41667],"type":"Point"}
}