{
  "type": "Feature",
  "properties": {
    "gn:admin1_code":"12.0",
    "gn:asciiname":"Cungambango",
    "gn:country_code":"AO",
    "gn:dem":1142,
    "gn:feature_class":"P",
    "gn:feature_code":"PPL",
    "gn:name":"Cungambango",
    "gn:population":0,
    "gn:timezone":"Africa/Luanda",
    "iso:country":"AO",
    "wof:name":"Cungambango",
    "wof:placetype":"locality"
},
  "geometry": {"coordinates":[17.08132,-9.57635],"type":"Point"}
}