{
  "type": "Feature",
  "properties": {
    "gn:admin1_code":"6.0",
    "gn:asciiname":"Cahiumba",
    "gn:country_code":"AO",
    "gn:dem":1126,
    "gn:feature_class":"P",
    "gn:feature_code":"PPL",
    "gn:name":"Cahiumba",
    "gn:population":0,
    "gn:timezone":"Africa/Luanda",
    "iso:country":"AO",
    "wof:name":"Cahiumba",
    "wof:placetype":"locality"
},
  "geometry": {"coordinates":[14.41807,-10.94767],"type":"Point"}
}