{
  "type": "Feature",
  "properties": {
    "gn:admin1_code":"9.0",
    "gn:asciiname":"Dongue",
    "gn:cc2":"AO",
    "gn:country_code":"AO",
    "gn:dem":1289,
    "gn:feature_class":"P",
    "gn:feature_code":"PPL",
    "gn:name":"Dongue",
    "gn:population":0,
    "gn:timezone":"Africa/Luanda",
    "iso:country":"AO",
    "name:und_x_variant":[
        "Ondongui",
        "Donque",
        "Dongue",
        "Ndongue"
    ],
    "wof:name":"Dongue",
    "wof:placetype":"locality"
},
  "geometry": {"coordinates":[14.05,-15.43333],"type":"Point"}
}