{
  "type": "Feature",
  "properties": {
    "gn:admin1_code":"19.0",
    "gn:asciiname":"Cassumba Caxaquiama",
    "gn:country_code":"AO",
    "gn:dem":680,
    "gn:feature_class":"P",
    "gn:feature_code":"PPL",
    "gn:name":"Cassumba Caxaquiama",
    "gn:population":0,
    "gn:timezone":"Africa/Luanda",
    "iso:country":"AO",
    "name:und_x_variant":[
        "Cassumba Cacheacama",
        "Cassumba Caxaquiana",
        "Cassumba Caxaquiama"
    ],
    "wof:name":"Cassumba Caxaquiama",
    "wof:placetype":"locality"
},
  "geometry": {"coordinates":[14.7851,-8.49953],"type":"Point"}
}