{
  "type": "Feature",
  "properties": {
    "gn:admin1_code":"2.0",
    "gn:asciiname":"Sassonde",
    "gn:country_code":"AO",
    "gn:dem":1650,
    "gn:feature_class":"P",
    "gn:feature_code":"PPL",
    "gn:name":"Sassonde",
    "gn:population":0,
    "gn:timezone":"Africa/Luanda",
    "iso:country":"AO",
    "wof:name":"Sassonde",
    "wof:placetype":"locality"
},
  "geometry": {"coordinates":[16.93658,-11.49587],"type":"Point"}
}