{
  "type": "Feature",
  "properties": {
    "gn:admin1_code":"17.0",
    "gn:asciiname":"Cassassa",
    "gn:country_code":"AO",
    "gn:dem":1012,
    "gn:feature_class":"P",
    "gn:feature_code":"PPL",
    "gn:name":"Cassassa",
    "gn:population":0,
    "gn:timezone":"Africa/Luanda",
    "iso:country":"AO",
    "wof:name":"Cassassa",
    "wof:placetype":"locality"
},
  "geometry": {"coordinates":[19.42823,-7.68122],"type":"Point"}
}