{
  "type": "Feature",
  "properties": {
    "gn:admin1_code":"12.0",
    "gn:asciiname":"Dambi-Cassambi",
    "gn:country_code":"AO",
    "gn:dem":1112,
    "gn:feature_class":"P",
    "gn:feature_code":"PPL",
    "gn:name":"Dambi-Cassambi",
    "gn:population":0,
    "gn:timezone":"Africa/Luanda",
    "iso:country":"AO",
    "wof:name":"Dambi-Cassambi",
    "wof:placetype":"locality"
},
  "geometry": {"coordinates":[16.88417999999999,-10.12055],"type":"Point"}
}