{
  "type": "Feature",
  "properties": {
    "gn:admin1_code":"8.0",
    "gn:asciiname":"Tchissala",
    "gn:cc2":"AO",
    "gn:country_code":"AO",
    "gn:dem":1698,
    "gn:feature_class":"P",
    "gn:feature_code":"PPL",
    "gn:name":"Tchissala",
    "gn:population":0,
    "gn:timezone":"Africa/Luanda",
    "iso:country":"AO",
    "name:und_x_variant":[
        "Chissala",
        "Txissala",
        "Tchissala"
    ],
    "wof:name":"Tchissala",
    "wof:placetype":"locality"
},
  "geometry": {"coordinates":[15.63306,-12.75083],"type":"Point"}
}