{
  "type": "Feature",
  "properties": {
    "gn:admin1_code":"15.0",
    "gn:asciiname":"Quicanga",
    "gn:country_code":"AO",
    "gn:dem":909,
    "gn:feature_class":"P",
    "gn:feature_code":"PPL",
    "gn:name":"Quicanga",
    "gn:population":0,
    "gn:timezone":"Africa/Luanda",
    "iso:country":"AO",
    "name:und_x_variant":[
        "Quicongo",
        "Quicanga"
    ],
    "wof:name":"Quicanga",
    "wof:placetype":"locality"
},
  "geometry": {"coordinates":[15.76574,-6.58767],"type":"Point"}
}