{
  "type": "Feature",
  "properties": {
    "gn:admin1_code":"12.0",
    "gn:asciiname":"Sacambiembia",
    "gn:country_code":"AO",
    "gn:dem":1266,
    "gn:feature_class":"P",
    "gn:feature_code":"PPL",
    "gn:name":"Sacambiembia",
    "gn:population":0,
    "gn:timezone":"Africa/Luanda",
    "iso:country":"AO",
    "wof:name":"Sacambiembia",
    "wof:placetype":"locality"
},
  "geometry": {"coordinates":[18.53466,-11.3678],"type":"Point"}
}