{
  "type": "Feature",
  "properties": {
    "gn:admin1_code":"8.0",
    "gn:asciiname":"Tome",
    "gn:country_code":"AO",
    "gn:dem":1587,
    "gn:feature_class":"P",
    "gn:feature_code":"PPL",
    "gn:name":"Tom\u00e9",
    "gn:population":0,
    "gn:timezone":"Africa/Luanda",
    "iso:country":"AO",
    "name:ceb_x_preferred":[
        "Tome"
    ],
    "name:deu_x_preferred":[
        "Tome"
    ],
    "name:fra_x_preferred":[
        "Tome"
    ],
    "name:nld_x_preferred":[
        "Tome"
    ],
    "name:swe_x_preferred":[
        "Tome"
    ],
    "wof:name":"Tome",
    "wof:placetype":"locality"
},
  "geometry": {"coordinates":[15.96667,-11.98333],"type":"Point"}
}