{
  "type": "Feature",
  "properties": {
    "gn:admin1_code":"16.0",
    "gn:asciiname":"Cuancua",
    "gn:country_code":"AO",
    "gn:dem":367,
    "gn:feature_class":"P",
    "gn:feature_code":"PPL",
    "gn:name":"Cuancua",
    "gn:population":0,
    "gn:timezone":"Africa/Luanda",
    "iso:country":"AO",
    "wof:name":"Cuancua",
    "wof:placetype":"locality"
},
  "geometry": {"coordinates":[13.50878,-6.40556],"type":"Point"}
}