{
  "type": "Feature",
  "properties": {
    "gn:admin1_code":"12.0",
    "gn:asciiname":"Calembe",
    "gn:country_code":"AO",
    "gn:dem":1198,
    "gn:feature_class":"P",
    "gn:feature_code":"PPL",
    "gn:name":"Calembe",
    "gn:population":0,
    "gn:timezone":"Africa/Luanda",
    "iso:country":"AO",
    "wof:name":"Calembe",
    "wof:placetype":"locality"
},
  "geometry": {"coordinates":[15.78739,-8.76054],"type":"Point"}
}