{
  "type": "Feature",
  "properties": {
    "gn:admin1_code":"12.0",
    "gn:asciiname":"Cassungo",
    "gn:country_code":"AO",
    "gn:dem":770,
    "gn:feature_class":"P",
    "gn:feature_code":"PPL",
    "gn:name":"Cassungo",
    "gn:population":0,
    "gn:timezone":"Africa/Luanda",
    "iso:country":"AO",
    "wof:name":"Cassungo",
    "wof:placetype":"locality"
},
  "geometry": {"coordinates":[16.42208,-8.31073],"type":"Point"}
}