{
  "type": "Feature",
  "properties": {
    "gn:admin1_code":"12.0",
    "gn:asciiname":"Luvuri",
    "gn:country_code":"AO",
    "gn:dem":1121,
    "gn:feature_class":"P",
    "gn:feature_code":"PPL",
    "gn:name":"Luvuri",
    "gn:population":0,
    "gn:timezone":"Africa/Luanda",
    "iso:country":"AO",
    "wof:name":"Luvuri",
    "wof:placetype":"locality"
},
  "geometry": {"coordinates":[17.56141,-9.92019],"type":"Point"}
}