{
  "type": "Feature",
  "properties": {
    "gn:admin1_code":"4.0",
    "gn:asciiname":"Muleque",
    "gn:country_code":"AO",
    "gn:dem":1415,
    "gn:feature_class":"P",
    "gn:feature_code":"PPL",
    "gn:name":"Muleque",
    "gn:population":0,
    "gn:timezone":"Africa/Luanda",
    "iso:country":"AO",
    "wof:name":"Muleque",
    "wof:placetype":"locality"
},
  "geometry": {"coordinates":[16.53799,-14.55522],"type":"Point"}
}