{
  "type": "Feature",
  "properties": {
    "gn:admin1_code":"9.0",
    "gn:asciiname":"Catucutuco",
    "gn:country_code":"AO",
    "gn:dem":1260,
    "gn:feature_class":"P",
    "gn:feature_code":"PPLL",
    "gn:name":"Catucutuco",
    "gn:population":0,
    "gn:timezone":"Africa/Luanda",
    "iso:country":"AO",
    "wof:name":"Catucutuco",
    "wof:placetype":"locality"
},
  "geometry": {"coordinates":[14.8634,-14.63098],"type":"Point"}
}