{
  "type": "Feature",
  "properties": {
    "gn:admin1_code":"12.0",
    "gn:asciiname":"Singula",
    "gn:country_code":"AO",
    "gn:dem":1092,
    "gn:feature_class":"P",
    "gn:feature_code":"PPL",
    "gn:name":"Singula",
    "gn:population":0,
    "gn:timezone":"Africa/Luanda",
    "iso:country":"AO",
    "wof:name":"Singula",
    "wof:placetype":"locality"
},
  "geometry": {"coordinates":[17.48582,-10.50876],"type":"Point"}
}