{
  "type": "Feature",
  "properties": {
    "gn:admin1_code":"20.0",
    "gn:asciiname":"Camama",
    "gn:country_code":"AO",
    "gn:dem":84,
    "gn:feature_class":"P",
    "gn:feature_code":"PPL",
    "gn:name":"Camama",
    "gn:population":0,
    "gn:timezone":"Africa/Luanda",
    "iso:country":"AO",
    "wof:name":"Camama",
    "wof:placetype":"locality"
},
  "geometry": {"coordinates":[13.26294,-8.93562],"type":"Point"}
}