{
  "type": "Feature",
  "properties": {
    "gn:admin1_code":"6.0",
    "gn:asciiname":"Laurindo",
    "gn:country_code":"AO",
    "gn:dem":1728,
    "gn:feature_class":"P",
    "gn:feature_code":"PPL",
    "gn:name":"Laurindo",
    "gn:population":0,
    "gn:timezone":"Africa/Luanda",
    "iso:country":"AO",
    "wof:name":"Laurindo",
    "wof:placetype":"locality"
},
  "geometry": {"coordinates":[15.01667,-12.08333],"type":"Point"}
}