{
  "type": "Feature",
  "properties": {
    "gn:admin1_code":"12.0",
    "gn:asciiname":"Saivenga",
    "gn:country_code":"AO",
    "gn:dem":1366,
    "gn:feature_class":"P",
    "gn:feature_code":"PPL",
    "gn:name":"Saivenga",
    "gn:population":0,
    "gn:timezone":"Africa/Luanda",
    "iso:country":"AO",
    "wof:name":"Saivenga",
    "wof:placetype":"locality"
},
  "geometry": {"coordinates":[18.4738,-11.12739],"type":"Point"}
}