{
  "type": "Feature",
  "properties": {
    "gn:admin1_code":"12.0",
    "gn:asciiname":"Maundo",
    "gn:country_code":"AO",
    "gn:dem":1191,
    "gn:feature_class":"P",
    "gn:feature_code":"PPL",
    "gn:name":"Maundo",
    "gn:population":0,
    "gn:timezone":"Africa/Luanda",
    "iso:country":"AO",
    "wof:name":"Maundo",
    "wof:placetype":"locality"
},
  "geometry": {"coordinates":[16.51557,-8.99214],"type":"Point"}
}