{
  "type": "Feature",
  "properties": {
    "gn:admin1_code":"15.0",
    "gn:asciiname":"Vemba",
    "gn:country_code":"AO",
    "gn:dem":878,
    "gn:feature_class":"P",
    "gn:feature_code":"PPL",
    "gn:name":"Vemba",
    "gn:population":0,
    "gn:timezone":"Africa/Luanda",
    "iso:country":"AO",
    "wof:name":"Vemba",
    "wof:placetype":"locality"
},
  "geometry": {"coordinates":[15.05582,-6.05336],"type":"Point"}
}