{
  "type": "Feature",
  "properties": {
    "gn:admin1_code":"17.0",
    "gn:asciiname":"Tcheleca",
    "gn:country_code":"AO",
    "gn:dem":857,
    "gn:feature_class":"P",
    "gn:feature_code":"PPL",
    "gn:name":"Tcheleca",
    "gn:population":0,
    "gn:timezone":"Africa/Luanda",
    "iso:country":"AO",
    "wof:name":"Tcheleca",
    "wof:placetype":"locality"
},
  "geometry": {"coordinates":[21.56228,-8.16851],"type":"Point"}
}