{
  "type": "Feature",
  "properties": {
    "gn:admin1_code":"0.0",
    "gn:asciiname":"Vinte",
    "gn:country_code":"AO",
    "gn:dem":22,
    "gn:feature_class":"P",
    "gn:feature_code":"PPL",
    "gn:name":"Vinte",
    "gn:population":0,
    "gn:timezone":"Africa/Luanda",
    "iso:country":"AO",
    "wof:name":"Vinte",
    "wof:placetype":"locality"
},
  "geometry": {"coordinates":[13.49333,-12.51194],"type":"Point"}
}