{
  "type": "Feature",
  "properties": {
    "gn:admin1_code":"5.0",
    "gn:asciiname":"Quivange",
    "gn:country_code":"AO",
    "gn:dem":1223,
    "gn:feature_class":"P",
    "gn:feature_code":"PPL",
    "gn:name":"Quivange",
    "gn:population":0,
    "gn:timezone":"Africa/Luanda",
    "iso:country":"AO",
    "wof:name":"Quivange",
    "wof:placetype":"locality"
},
  "geometry": {"coordinates":[15.71054,-8.36098],"type":"Point"}
}