{
  "type": "Feature",
  "properties": {
    "gn:admin1_code":"6.0",
    "gn:asciiname":"Quinjanga",
    "gn:country_code":"AO",
    "gn:dem":1328,
    "gn:feature_class":"P",
    "gn:feature_code":"PPL",
    "gn:name":"Quinjanga",
    "gn:population":0,
    "gn:timezone":"Africa/Luanda",
    "iso:country":"AO",
    "wof:name":"Quinjanga",
    "wof:placetype":"locality"
},
  "geometry": {"coordinates":[15.00556,-10.78625],"type":"Point"}
}