{
  "type": "Feature",
  "properties": {
    "gn:admin1_code":"1.0",
    "gn:asciiname":"Caquinta",
    "gn:country_code":"AO",
    "gn:dem":41,
    "gn:feature_class":"P",
    "gn:feature_code":"PPL",
    "gn:name":"Caquinta",
    "gn:population":0,
    "gn:timezone":"Africa/Luanda",
    "iso:country":"AO",
    "wof:name":"Caquinta",
    "wof:placetype":"locality"
},
  "geometry": {"coordinates":[13.70426,-12.25872],"type":"Point"}
}