{
  "type": "Feature",
  "properties": {
    "gn:admin1_code":"17.0",
    "gn:asciiname":"Tchipatchi",
    "gn:country_code":"AO",
    "gn:dem":823,
    "gn:feature_class":"P",
    "gn:feature_code":"PPL",
    "gn:name":"Tchip\u00e1tchi",
    "gn:population":0,
    "gn:timezone":"Africa/Luanda",
    "iso:country":"AO",
    "wof:name":"Tchipatchi",
    "wof:placetype":"locality"
},
  "geometry": {"coordinates":[18.06817,-9.07504],"type":"Point"}
}