{
  "type": "Feature",
  "properties": {
    "gn:admin1_code":"8.0",
    "gn:asciiname":"Cauango",
    "gn:cc2":"AO",
    "gn:country_code":"AO",
    "gn:dem":1421,
    "gn:feature_class":"P",
    "gn:feature_code":"PPL",
    "gn:name":"Cauango",
    "gn:population":0,
    "gn:timezone":"Africa/Luanda",
    "iso:country":"AO",
    "name:und_x_variant":[
        "Cauanga",
        "Cauango"
    ],
    "wof:name":"Cauango",
    "wof:placetype":"locality"
},
  "geometry": {"coordinates":[15.61667,-11.85],"type":"Point"}
}