{
  "type": "Feature",
  "properties": {
    "gn:admin1_code":"6.0",
    "gn:asciiname":"Catita",
    "gn:country_code":"AO",
    "gn:dem":1260,
    "gn:feature_class":"P",
    "gn:feature_code":"PPL",
    "gn:name":"Catita",
    "gn:population":0,
    "gn:timezone":"Africa/Luanda",
    "iso:country":"AO",
    "wof:name":"Catita",
    "wof:placetype":"locality"
},
  "geometry": {"coordinates":[14.98309,-11.03796],"type":"Point"}
}