{
  "type": "Feature",
  "properties": {
    "gn:admin1_code":"6.0",
    "gn:asciiname":"Singelo",
    "gn:country_code":"AO",
    "gn:dem":1573,
    "gn:feature_class":"P",
    "gn:feature_code":"PPL",
    "gn:name":"Singelo",
    "gn:population":0,
    "gn:timezone":"Africa/Luanda",
    "iso:country":"AO",
    "wof:name":"Singelo",
    "wof:placetype":"locality"
},
  "geometry": {"coordinates":[14.83333,-11.73333],"type":"Point"}
}