{
  "type": "Feature",
  "properties": {
    "gn:admin1_code":"17.0",
    "gn:asciiname":"Tchicumbo",
    "gn:country_code":"AO",
    "gn:dem":1273,
    "gn:feature_class":"P",
    "gn:feature_code":"PPL",
    "gn:name":"Tchicumbo",
    "gn:population":0,
    "gn:timezone":"Africa/Luanda",
    "iso:country":"AO",
    "wof:name":"Tchicumbo",
    "wof:placetype":"locality"
},
  "geometry": {"coordinates":[18.15804,-10.37687],"type":"Point"}
}