{
  "type": "Feature",
  "properties": {
    "gn:admin1_code":"8.0",
    "gn:asciiname":"Calongunda",
    "gn:country_code":"AO",
    "gn:dem":1446,
    "gn:feature_class":"P",
    "gn:feature_code":"PPL",
    "gn:name":"Calongunda",
    "gn:population":0,
    "gn:timezone":"Africa/Luanda",
    "iso:country":"AO",
    "wof:name":"Calongunda",
    "wof:placetype":"locality"
},
  "geometry": {"coordinates":[15.31667,-12.05],"type":"Point"}
}