{
  "type": "Feature",
  "properties": {
    "gn:admin1_code":"4.0",
    "gn:asciiname":"Livro",
    "gn:country_code":"AO",
    "gn:dem":1458,
    "gn:feature_class":"P",
    "gn:feature_code":"PPL",
    "gn:name":"Livro",
    "gn:population":0,
    "gn:timezone":"Africa/Luanda",
    "iso:country":"AO",
    "name:jpn_x_preferred":[
        "\u30ea\u30fc\u30f4\u30ed"
    ],
    "name:pol_x_preferred":[
        "Livro"
    ],
    "name:por_x_preferred":[
        "Livro"
    ],
    "wof:name":"Livro",
    "wof:placetype":"locality"
},
  "geometry": {"coordinates":[18.21667,-14.73333],"type":"Point"}
}