{
  "type": "Feature",
  "properties": {
    "gn:admin1_code":"14.0",
    "gn:asciiname":"Tutengo",
    "gn:cc2":"AO",
    "gn:country_code":"AO",
    "gn:dem":1067,
    "gn:feature_class":"P",
    "gn:feature_code":"PPL",
    "gn:name":"Tutengo",
    "gn:population":0,
    "gn:timezone":"Africa/Luanda",
    "iso:country":"AO",
    "name:und_x_variant":[
        "Chitengo",
        "Tutengo"
    ],
    "wof:name":"Tutengo",
    "wof:placetype":"locality"
},
  "geometry": {"coordinates":[21.73333,-15.41667],"type":"Point"}
}