{
  "type": "Feature",
  "properties": {
    "gn:admin1_code":"6.0",
    "gn:asciiname":"Quitala",
    "gn:country_code":"AO",
    "gn:dem":1224,
    "gn:feature_class":"P",
    "gn:feature_code":"PPL",
    "gn:name":"Quitala",
    "gn:population":0,
    "gn:timezone":"Africa/Luanda",
    "iso:country":"AO",
    "wof:name":"Quitala",
    "wof:placetype":"locality"
},
  "geometry": {"coordinates":[15.07751,-10.81737],"type":"Point"}
}