{
  "type": "Feature",
  "properties": {
    "gn:admin1_code":"15.0",
    "gn:asciiname":"Quidiala",
    "gn:country_code":"AO",
    "gn:dem":1054,
    "gn:feature_class":"P",
    "gn:feature_code":"PPL",
    "gn:name":"Quidiala",
    "gn:population":0,
    "gn:timezone":"Africa/Luanda",
    "iso:country":"AO",
    "wof:name":"Quidiala",
    "wof:placetype":"locality"
},
  "geometry": {"coordinates":[15.85907,-7.52168],"type":"Point"}
}