{
  "type": "Feature",
  "properties": {
    "iso:country":"AO",
    "name:azb_x_preferred":[
        "\u06a9\u062a\u0648\u0645\u0628\u0644\u0627"
    ],
    "name:cat_x_preferred":[
        "Catumbela"
    ],
    "name:ceb_x_preferred":[
        "Catumbela"
    ],
    "name:ces_x_preferred":[
        "Alto Catumbela"
    ],
    "name:ces_x_variant":[
        "Catumbela"
    ],
    "name:deu_x_preferred":[
        "Catumbela"
    ],
    "name:ell_x_preferred":[
        "\u039a\u03b1\u03c4\u03bf\u03c5\u03bc\u03c0\u03ad\u03bb\u03b1"
    ],
    "name:eng_x_preferred":[
        "Catumbela"
    ],
    "name:fas_x_preferred":[
        "\u06a9\u062a\u0648\u0645\u0628\u0644\u0627\u060c \u0622\u0646\u06af\u0648\u0644\u0627"
    ],
    "name:fas_x_variant":[
        "\u06a9\u062a\u0648\u0645\u0628\u0644\u0627"
    ],
    "name:fra_x_preferred":[
        "Catumbela"
    ],
    "name:frr_x_preferred":[
        "Catumbela"
    ],
    "name:ita_x_preferred":[
        "Catumbela"
    ],
    "name:jpn_x_preferred":[
        "\u30ab\u30c4\u30f3\u30d9\u30e9"
    ],
    "name:msa_x_preferred":[
        "Catumbela"
    ],
    "name:nld_x_preferred":[
        "Catumbela"
    ],
    "name:nob_x_preferred":[
        "Catumbela"
    ],
    "name:pol_x_preferred":[
        "Catumbela"
    ],
    "name:por_x_preferred":[
        "Catumbela"
    ],
    "name:rus_x_preferred":[
        "\u041a\u0430\u0442\u0443\u043c\u0431\u0435\u043b\u0430"
    ],
    "name:spa_x_preferred":[
        "Catumbela"
    ],
    "name:swa_x_preferred":[
        "Catumbela"
    ],
    "name:swe_x_preferred":[
        "Catumbela"
    ],
    "name:ukr_x_preferred":[
        "\u041a\u0430\u0442\u0443\u043c\u0431\u0435\u043b\u0430"
    ],
    "name:und_x_variant":[
        "Katumbela"
    ],
    "name:zho_x_preferred":[
        "\u5361\u901a\u5e03\u62c9"
    ],
    "name:zul_x_preferred":[
        "Catumbela"
    ],
    "qs:gn_country":"AO",
    "qs:gn_fcode":"PPL",
    "qs:gn_pop":16977,
    "qs:name":"Catumbela",
    "qs:name_adm0":"Angola",
    "qs:name_adm1":"Benguela",
    "qs:photos":33,
    "qs:photos_1k":7,
    "qs:photos_9k":1,
    "qs:photos_9r":2,
    "qs:photos_all":33,
    "qs:photos_sr":2,
    "qs:placetype":"Town",
    "qs:pop_sr":"6",
    "qs:woe_adm0":23424745,
    "wd:wordcount":188,
    "wof:name":"Catumbela",
    "wof:placetype":"locality",
    "wof:population":16977
},
  "geometry": {"coordinates":[13.54722,-12.43139],"type":"Point"}
}