{
  "type": "Feature",
  "properties": {
    "gn:admin1_code":"15.0",
    "gn:asciiname":"Quinzambe",
    "gn:cc2":"AO",
    "gn:country_code":"AO",
    "gn:dem":688,
    "gn:feature_class":"P",
    "gn:feature_code":"PPL",
    "gn:name":"Quinzambe",
    "gn:population":0,
    "gn:timezone":"Africa/Luanda",
    "iso:country":"AO",
    "name:und_x_variant":[
        "Quinzambi",
        "Quinzambe"
    ],
    "wof:name":"Quinzambe",
    "wof:placetype":"locality"
},
  "geometry": {"coordinates":[14.63333,-7.73333],"type":"Point"}
}