{
  "type": "Feature",
  "properties": {
    "gn:admin1_code":"12.0",
    "gn:asciiname":"Quibunda",
    "gn:country_code":"AO",
    "gn:dem":657,
    "gn:feature_class":"P",
    "gn:feature_code":"PPL",
    "gn:name":"Quibunda",
    "gn:population":0,
    "gn:timezone":"Africa/Luanda",
    "iso:country":"AO",
    "wof:name":"Quibunda",
    "wof:placetype":"locality"
},
  "geometry": {"coordinates":[17.39188,-8.65351],"type":"Point"}
}