{
  "type": "Feature",
  "properties": {
    "gn:admin1_code":"14.0",
    "gn:asciiname":"Chiuende",
    "gn:cc2":"AO",
    "gn:country_code":"AO",
    "gn:dem":1182,
    "gn:feature_class":"P",
    "gn:feature_code":"PPL",
    "gn:name":"Chiuende",
    "gn:population":0,
    "gn:timezone":"Africa/Luanda",
    "iso:country":"AO",
    "name:und_x_variant":[
        "Kakundi",
        "Cacunde",
        "Chiuende"
    ],
    "wof:name":"Chiuende",
    "wof:placetype":"locality"
},
  "geometry": {"coordinates":[23.48333,-11.21667],"type":"Point"}
}