{
  "type": "Feature",
  "properties": {
    "gn:admin1_code":"12.0",
    "gn:asciiname":"Zenguel",
    "gn:cc2":"AO",
    "gn:country_code":"AO",
    "gn:dem":1132,
    "gn:feature_class":"P",
    "gn:feature_code":"PPL",
    "gn:name":"Zenguel",
    "gn:population":0,
    "gn:timezone":"Africa/Luanda",
    "iso:country":"AO",
    "name:und_x_variant":[
        "Zenguele",
        "Zenguel"
    ],
    "wof:name":"Zenguel",
    "wof:placetype":"locality"
},
  "geometry": {"coordinates":[16.11667000000001,-9.35],"type":"Point"}
}