{
  "type": "Feature",
  "properties": {
    "gn:admin1_code":"1.0",
    "gn:asciiname":"Capaco",
    "gn:cc2":"AO",
    "gn:country_code":"AO",
    "gn:dem":1015,
    "gn:feature_class":"P",
    "gn:feature_code":"PPL",
    "gn:name":"Capaco",
    "gn:population":0,
    "gn:timezone":"Africa/Luanda",
    "iso:country":"AO",
    "name:und_x_variant":[
        "Capaca",
        "Fazenda Capaco",
        "Fazenda Capaco Limitada",
        "Capaco"
    ],
    "wof:name":"Capaco",
    "wof:placetype":"locality"
},
  "geometry": {"coordinates":[14.45,-12.95],"type":"Point"}
}