{
  "type": "Feature",
  "properties": {
    "gn:admin1_code":"5.0",
    "gn:asciiname":"Helegl de Baixo",
    "gn:country_code":"AO",
    "gn:dem":766,
    "gn:feature_class":"P",
    "gn:feature_code":"PPL",
    "gn:name":"Helegl de Baixo",
    "gn:population":0,
    "gn:timezone":"Africa/Luanda",
    "iso:country":"AO",
    "wof:name":"Helegl de Baixo",
    "wof:placetype":"locality"
},
  "geometry": {"coordinates":[15.38985,-9.34173],"type":"Point"}
}