{
  "type": "Feature",
  "properties": {
    "gn:admin1_code":"5.0",
    "gn:asciiname":"Tango",
    "gn:country_code":"AO",
    "gn:dem":1237,
    "gn:feature_class":"P",
    "gn:feature_code":"PPL",
    "gn:name":"Tango",
    "gn:population":0,
    "gn:timezone":"Africa/Luanda",
    "iso:country":"AO",
    "wof:name":"Tango",
    "wof:placetype":"locality"
},
  "geometry": {"coordinates":[15.6349,-8.09419],"type":"Point"}
}