{
  "type": "Feature",
  "properties": {
    "gn:admin1_code":"5.0",
    "gn:asciiname":"Quilemba",
    "gn:country_code":"AO",
    "gn:dem":393,
    "gn:feature_class":"P",
    "gn:feature_code":"PPL",
    "gn:name":"Quilemba",
    "gn:population":0,
    "gn:timezone":"Africa/Luanda",
    "iso:country":"AO",
    "name:ceb_x_preferred":[
        "Quilemba"
    ],
    "name:swe_x_preferred":[
        "Quilemba"
    ],
    "name:und_x_variant":[
        "S\u00e3o Pedro da Quilemba",
        "Quilimba",
        "Quilemba",
        "Ngola Calunga"
    ],
    "wof:name":"Quilemba",
    "wof:placetype":"locality"
},
  "geometry": {"coordinates":[14.79116,-9.68346],"type":"Point"}
}