{
  "type": "Feature",
  "properties": {
    "gn:admin1_code":"17.0",
    "gn:asciiname":"Saquemba",
    "gn:country_code":"AO",
    "gn:dem":1134,
    "gn:feature_class":"P",
    "gn:feature_code":"PPL",
    "gn:name":"Saquemba",
    "gn:population":0,
    "gn:timezone":"Africa/Luanda",
    "iso:country":"AO",
    "wof:name":"Saquemba",
    "wof:placetype":"locality"
},
  "geometry": {"coordinates":[19.14107000000001,-8.2531],"type":"Point"}
}