{
  "type": "Feature",
  "properties": {
    "gn:admin1_code":"9.0",
    "gn:asciiname":"Fazenda F. Vilar",
    "gn:country_code":"AO",
    "gn:dem":1513,
    "gn:feature_class":"P",
    "gn:feature_code":"PPL",
    "gn:name":"Fazenda F. Vilar",
    "gn:population":0,
    "gn:timezone":"Africa/Luanda",
    "iso:country":"AO",
    "wof:name":"Fazenda F. Vilar",
    "wof:placetype":"locality"
},
  "geometry": {"coordinates":[13.88333,-14.96667],"type":"Point"}
}