{
  "type": "Feature",
  "properties": {
    "gn:admin1_code":"5.0",
    "gn:asciiname":"Mulemba",
    "gn:country_code":"AO",
    "gn:dem":502,
    "gn:feature_class":"P",
    "gn:feature_code":"PPL",
    "gn:name":"Mulemba",
    "gn:population":0,
    "gn:timezone":"Africa/Luanda",
    "iso:country":"AO",
    "wof:name":"Mulemba",
    "wof:placetype":"locality"
},
  "geometry": {"coordinates":[14.69102,-9.01064],"type":"Point"}
}