{
  "type": "Feature",
  "properties": {
    "gn:admin1_code":"14.0",
    "gn:asciiname":"Machada",
    "gn:country_code":"AO",
    "gn:dem":1097,
    "gn:feature_class":"P",
    "gn:feature_code":"PPL",
    "gn:name":"Machada",
    "gn:population":0,
    "gn:timezone":"Africa/Luanda",
    "iso:country":"AO",
    "wof:name":"Machada",
    "wof:placetype":"locality"
},
  "geometry": {"coordinates":[21.4992,-14.17713],"type":"Point"}
}