{
  "type": "Feature",
  "properties": {
    "gn:admin1_code":"9.0",
    "gn:asciiname":"Cucala",
    "gn:cc2":"AO",
    "gn:country_code":"AO",
    "gn:dem":1450,
    "gn:feature_class":"P",
    "gn:feature_code":"PPL",
    "gn:name":"Cucala",
    "gn:population":0,
    "gn:timezone":"Africa/Luanda",
    "iso:country":"AO",
    "name:und_x_variant":[
        "Cac\u00f4co",
        "Cucala"
    ],
    "wof:name":"Cucala",
    "wof:placetype":"locality"
},
  "geometry": {"coordinates":[15.18333,-14.11667],"type":"Point"}
}