{
  "type": "Feature",
  "properties": {
    "gn:admin1_code":"15.0",
    "gn:asciiname":"Banza Quinzau",
    "gn:country_code":"AO",
    "gn:dem":1015,
    "gn:feature_class":"P",
    "gn:feature_code":"PPL",
    "gn:name":"Banza Quinzau",
    "gn:population":0,
    "gn:timezone":"Africa/Luanda",
    "iso:country":"AO",
    "name:und_x_variant":[
        "Quizoa",
        "Banza Quizau",
        "Banza Quinzau"
    ],
    "wof:name":"Banza Quinzau",
    "wof:placetype":"locality"
},
  "geometry": {"coordinates":[15.13296,-6.62682],"type":"Point"}
}