{
  "type": "Feature",
  "properties": {
    "gn:admin1_code":"8.0",
    "gn:asciiname":"Calucamba",
    "gn:cc2":"AO",
    "gn:country_code":"AO",
    "gn:dem":1322,
    "gn:feature_class":"P",
    "gn:feature_code":"PPL",
    "gn:name":"Calucamba",
    "gn:population":0,
    "gn:timezone":"Africa/Luanda",
    "iso:country":"AO",
    "name:und_x_variant":[
        "Calussamba",
        "Calucamba"
    ],
    "wof:name":"Calucamba",
    "wof:placetype":"locality"
},
  "geometry": {"coordinates":[15.48333,-11.56667],"type":"Point"}
}