{
  "type": "Feature",
  "properties": {
    "gn:admin1_code":"15.0",
    "gn:asciiname":"Tele",
    "gn:country_code":"AO",
    "gn:dem":479,
    "gn:feature_class":"P",
    "gn:feature_code":"PPL",
    "gn:name":"Tele",
    "gn:population":0,
    "gn:timezone":"Africa/Luanda",
    "iso:country":"AO",
    "name:ceb_x_preferred":[
        "Tele"
    ],
    "name:deu_x_preferred":[
        "Tele"
    ],
    "name:fas_x_preferred":[
        "\u062a\u0644\u0647"
    ],
    "name:fra_x_preferred":[
        "Tele"
    ],
    "name:mhr_x_preferred":[
        "\u0422\u0435\u043b\u0435"
    ],
    "name:nor_x_preferred":[
        "Tele"
    ],
    "name:rus_x_preferred":[
        "\u0422\u0435\u043b\u0435"
    ],
    "name:swe_x_preferred":[
        "Tele"
    ],
    "name:tur_x_preferred":[
        "Tele"
    ],
    "wof:name":"Tele",
    "wof:placetype":"locality"
},
  "geometry": {"coordinates":[14.61667,-6.88333],"type":"Point"}
}