{
  "type": "Feature",
  "properties": {
    "gn:admin1_code":"14.0",
    "gn:asciiname":"Camundongo",
    "gn:cc2":"AO",
    "gn:country_code":"AO",
    "gn:dem":1112,
    "gn:feature_class":"P",
    "gn:feature_code":"PPL",
    "gn:name":"Camundongo",
    "gn:population":0,
    "gn:timezone":"Africa/Luanda",
    "iso:country":"AO",
    "name:und_x_variant":[
        "Cachungo",
        "Cabango",
        "Camundongo"
    ],
    "wof:name":"Camundongo",
    "wof:placetype":"locality"
},
  "geometry": {"coordinates":[23.18333,-11.55],"type":"Point"}
}