{
  "type": "Feature",
  "properties": {
    "gn:admin1_code":"3.0",
    "gn:asciiname":"Chinga",
    "gn:cc2":"AO",
    "gn:country_code":"AO",
    "gn:dem":10,
    "gn:feature_class":"P",
    "gn:feature_code":"PPL",
    "gn:name":"Chinga",
    "gn:population":0,
    "gn:timezone":"Africa/Luanda",
    "iso:country":"AO",
    "name:ceb_x_preferred":[
        "Chinga"
    ],
    "name:deu_x_preferred":[
        "Chinga"
    ],
    "name:swe_x_preferred":[
        "Chinga"
    ],
    "name:und_x_variant":[
        "Khinga"
    ],
    "wof:name":"Chinga",
    "wof:placetype":"locality"
},
  "geometry": {"coordinates":[12.23333,-5.53333],"type":"Point"}
}