{
  "type": "Feature",
  "properties": {
    "gn:admin1_code":"5.0",
    "gn:asciiname":"Quizucula",
    "gn:cc2":"AO",
    "gn:country_code":"AO",
    "gn:dem":995,
    "gn:feature_class":"P",
    "gn:feature_code":"PPL",
    "gn:name":"Quizucula",
    "gn:population":0,
    "gn:timezone":"Africa/Luanda",
    "iso:country":"AO",
    "name:und_x_variant":[
        "Quissucula",
        "Quizucula"
    ],
    "wof:name":"Quizucula",
    "wof:placetype":"locality"
},
  "geometry": {"coordinates":[15.53333,-9.06667],"type":"Point"}
}