{
  "type": "Feature",
  "properties": {
    "gn:admin1_code":"2.0",
    "gn:asciiname":"Cassumbe",
    "gn:country_code":"AO",
    "gn:dem":1474,
    "gn:feature_class":"P",
    "gn:feature_code":"PPL",
    "gn:name":"Cassumbe",
    "gn:population":0,
    "gn:timezone":"Africa/Luanda",
    "iso:country":"AO",
    "name:und_x_variant":[
        "Cassumbi",
        "Cassumbe"
    ],
    "wof:name":"Cassumbe",
    "wof:placetype":"locality"
},
  "geometry": {"coordinates":[16.59963,-11.14231],"type":"Point"}
}