{
  "type": "Feature",
  "properties": {
    "gn:admin1_code":"19.0",
    "gn:asciiname":"Iembe",
    "gn:country_code":"AO",
    "gn:dem":51,
    "gn:feature_class":"P",
    "gn:feature_code":"PPL",
    "gn:name":"Iembe",
    "gn:population":0,
    "gn:timezone":"Africa/Luanda",
    "iso:country":"AO",
    "name:und_x_variant":[
        "Lembe",
        "Embe",
        "Iembe"
    ],
    "wof:name":"Iembe",
    "wof:placetype":"locality"
},
  "geometry": {"coordinates":[13.34304,-8.2576],"type":"Point"}
}