{
  "type": "Feature",
  "properties": {
    "gn:admin1_code":"16.0",
    "gn:asciiname":"Mauele",
    "gn:cc2":"AO",
    "gn:country_code":"AO",
    "gn:dem":542,
    "gn:feature_class":"P",
    "gn:feature_code":"PPL",
    "gn:name":"Mauele",
    "gn:population":0,
    "gn:timezone":"Africa/Luanda",
    "iso:country":"AO",
    "name:und_x_variant":[
        "Ma\u00fbete",
        "Mauele"
    ],
    "wof:name":"Mauele",
    "wof:placetype":"locality"
},
  "geometry": {"coordinates":[14.65,-6.08333],"type":"Point"}
}