{
  "type": "Feature",
  "properties": {
    "gn:admin1_code":"17.0",
    "gn:asciiname":"Luachimo",
    "gn:country_code":"AO",
    "gn:dem":699,
    "gn:feature_class":"P",
    "gn:feature_code":"PPL",
    "gn:name":"Luachimo",
    "gn:population":0,
    "gn:timezone":"Africa/Luanda",
    "iso:country":"AO",
    "name:msa_x_preferred":[
        "Luachimo"
    ],
    "name:por_x_preferred":[
        "Luachimo"
    ],
    "name:und_x_variant":[
        "Camatundo"
    ],
    "wof:name":"Luachimo",
    "wof:placetype":"locality"
},
  "geometry": {"coordinates":[20.80656,-7.3843],"type":"Point"}
}