{
  "type": "Feature",
  "properties": {
    "gn:admin1_code":"16.0",
    "gn:asciiname":"Ngonzela",
    "gn:country_code":"AO",
    "gn:dem":535,
    "gn:feature_class":"P",
    "gn:feature_code":"PPL",
    "gn:name":"Ngonzela",
    "gn:population":0,
    "gn:timezone":"Africa/Luanda",
    "iso:country":"AO",
    "name:und_x_variant":[
        "Gouzela",
        "Goazela",
        "Gousela",
        "Ngonzela"
    ],
    "wof:name":"Ngonzela",
    "wof:placetype":"locality"
},
  "geometry": {"coordinates":[14.5268,-6.02587],"type":"Point"}
}