{
  "type": "Feature",
  "properties": {
    "gn:admin1_code":"8.0",
    "gn:asciiname":"Alcides Silva",
    "gn:country_code":"AO",
    "gn:dem":1465,
    "gn:feature_class":"P",
    "gn:feature_code":"PPL",
    "gn:name":"Alcides Silva",
    "gn:population":0,
    "gn:timezone":"Africa/Luanda",
    "iso:country":"AO",
    "wof:name":"Alcides Silva",
    "wof:placetype":"locality"
},
  "geometry": {"coordinates":[15.76667,-12.16667],"type":"Point"}
}