{
  "type": "Feature",
  "properties": {
    "gn:admin1_code":"16.0",
    "gn:asciiname":"Lau",
    "gn:country_code":"AO",
    "gn:dem":576,
    "gn:feature_class":"P",
    "gn:feature_code":"PPL",
    "gn:name":"Lau",
    "gn:population":0,
    "gn:timezone":"Africa/Luanda",
    "iso:country":"AO",
    "wof:name":"Lau",
    "wof:placetype":"locality"
},
  "geometry": {"coordinates":[14.28333,-6.58333],"type":"Point"}
}