{
  "type": "Feature",
  "properties": {
    "gn:admin1_code":"8.0",
    "gn:asciiname":"Cambongue",
    "gn:country_code":"AO",
    "gn:dem":1437,
    "gn:feature_class":"P",
    "gn:feature_code":"PPL",
    "gn:name":"Cambongue",
    "gn:population":0,
    "gn:timezone":"Africa/Luanda",
    "iso:country":"AO",
    "wof:name":"Cambongue",
    "wof:placetype":"locality"
},
  "geometry": {"coordinates":[15.36508,-12.0147],"type":"Point"}
}