{
  "type": "Feature",
  "properties": {
    "gn:admin1_code":"19.0",
    "gn:asciiname":"Quissonga",
    "gn:country_code":"AO",
    "gn:dem":210,
    "gn:feature_class":"P",
    "gn:feature_code":"PPL",
    "gn:name":"Quissonga",
    "gn:population":0,
    "gn:timezone":"Africa/Luanda",
    "iso:country":"AO",
    "wof:name":"Quissonga",
    "wof:placetype":"locality"
},
  "geometry": {"coordinates":[13.76667,-9.63333],"type":"Point"}
}