{
  "type": "Feature",
  "properties": {
    "gn:admin1_code":"6.0",
    "gn:asciiname":"Tembo",
    "gn:country_code":"AO",
    "gn:dem":1396,
    "gn:feature_class":"P",
    "gn:feature_code":"PPLL",
    "gn:name":"Tembo",
    "gn:population":0,
    "gn:timezone":"Africa/Luanda",
    "iso:country":"AO",
    "name:fra_x_preferred":[
        "Tembo"
    ],
    "wof:name":"Tembo",
    "wof:placetype":"locality"
},
  "geometry": {"coordinates":[15.44277,-11.41805],"type":"Point"}
}