{
  "type": "Feature",
  "properties": {
    "gn:admin1_code":"12.0",
    "gn:asciiname":"Muconzo",
    "gn:country_code":"AO",
    "gn:dem":1115,
    "gn:feature_class":"P",
    "gn:feature_code":"PPL",
    "gn:name":"Muconzo",
    "gn:population":0,
    "gn:timezone":"Africa/Luanda",
    "iso:country":"AO",
    "wof:name":"Muconzo",
    "wof:placetype":"locality"
},
  "geometry": {"coordinates":[16.1667,-9.38785],"type":"Point"}
}