{
  "type": "Feature",
  "properties": {
    "gn:admin1_code":"15.0",
    "gn:asciiname":"Quimbimbi",
    "gn:country_code":"AO",
    "gn:dem":564,
    "gn:feature_class":"P",
    "gn:feature_code":"PPL",
    "gn:name":"Quimbimbi",
    "gn:population":0,
    "gn:timezone":"Africa/Luanda",
    "iso:country":"AO",
    "wof:name":"Quimbimbi",
    "wof:placetype":"locality"
},
  "geometry": {"coordinates":[14.85,-6.55],"type":"Point"}
}