{
  "type": "Feature",
  "properties": {
    "gn:admin1_code":"12.0",
    "gn:asciiname":"Miquiriquiri",
    "gn:country_code":"AO",
    "gn:dem":1217,
    "gn:feature_class":"P",
    "gn:feature_code":"PPL",
    "gn:name":"Miquiriquiri",
    "gn:population":0,
    "gn:timezone":"Africa/Luanda",
    "iso:country":"AO",
    "wof:name":"Miquiriquiri",
    "wof:placetype":"locality"
},
  "geometry": {"coordinates":[16.42535,-8.888],"type":"Point"}
}