{
  "type": "Feature",
  "properties": {
    "gn:admin1_code":"12.0",
    "gn:asciiname":"Cambunze",
    "gn:country_code":"AO",
    "gn:dem":1053,
    "gn:feature_class":"P",
    "gn:feature_code":"PPL",
    "gn:name":"Cambunze",
    "gn:population":0,
    "gn:timezone":"Africa/Luanda",
    "iso:country":"AO",
    "wof:name":"Cambunze",
    "wof:placetype":"locality"
},
  "geometry": {"coordinates":[15.63536,-9.39079],"type":"Point"}
}