{
  "type": "Feature",
  "properties": {
    "gn:admin1_code":"6.0",
    "gn:asciiname":"Tocoelo",
    "gn:country_code":"AO",
    "gn:dem":121,
    "gn:feature_class":"P",
    "gn:feature_code":"PPL",
    "gn:name":"Tocoelo",
    "gn:population":0,
    "gn:timezone":"Africa/Luanda",
    "iso:country":"AO",
    "wof:name":"Tocoelo",
    "wof:placetype":"locality"
},
  "geometry": {"coordinates":[14.02576,-10.64237],"type":"Point"}
}