{
  "type": "Feature",
  "properties": {
    "gn:admin1_code":"8.0",
    "gn:asciiname":"Caimba",
    "gn:cc2":"AO",
    "gn:country_code":"AO",
    "gn:dem":1553,
    "gn:feature_class":"P",
    "gn:feature_code":"PPL",
    "gn:name":"Caimba",
    "gn:population":0,
    "gn:timezone":"Africa/Luanda",
    "iso:country":"AO",
    "name:und_x_variant":[
        "Cahimba",
        "Caimba"
    ],
    "wof:name":"Caimba",
    "wof:placetype":"locality"
},
  "geometry": {"coordinates":[15.93333,-12.05],"type":"Point"}
}