{
  "type": "Feature",
  "properties": {
    "gn:admin1_code":"12.0",
    "gn:asciiname":"Sangi",
    "gn:country_code":"AO",
    "gn:dem":1170,
    "gn:feature_class":"P",
    "gn:feature_code":"PPL",
    "gn:name":"Sangi",
    "gn:population":0,
    "gn:timezone":"Africa/Luanda",
    "iso:country":"AO",
    "name:ceb_x_preferred":[
        "Sangi"
    ],
    "name:swe_x_preferred":[
        "Sangi"
    ],
    "wof:name":"Sangi",
    "wof:placetype":"locality"
},
  "geometry": {"coordinates":[16.51441,-8.96898],"type":"Point"}
}