{
  "type": "Feature",
  "properties": {
    "gn:admin1_code":"15.0",
    "gn:asciiname":"Sole",
    "gn:country_code":"AO",
    "gn:dem":788,
    "gn:feature_class":"P",
    "gn:feature_code":"PPL",
    "gn:name":"Sole",
    "gn:population":0,
    "gn:timezone":"Africa/Luanda",
    "iso:country":"AO",
    "wof:name":"Sole",
    "wof:placetype":"locality"
},
  "geometry": {"coordinates":[15.33333,-5.88333],"type":"Point"}
}