{
  "type": "Feature",
  "properties": {
    "gn:admin1_code":"6.0",
    "gn:asciiname":"Capachi",
    "gn:country_code":"AO",
    "gn:dem":388,
    "gn:feature_class":"P",
    "gn:feature_code":"PPL",
    "gn:name":"Capachi",
    "gn:population":0,
    "gn:timezone":"Africa/Luanda",
    "iso:country":"AO",
    "wof:name":"Capachi",
    "wof:placetype":"locality"
},
  "geometry": {"coordinates":[14.27015,-10.55405],"type":"Point"}
}