{
  "type": "Feature",
  "properties": {
    "gn:admin1_code":"8.0",
    "gn:asciiname":"Tchindundule",
    "gn:country_code":"AO",
    "gn:dem":1673,
    "gn:feature_class":"P",
    "gn:feature_code":"PPL",
    "gn:name":"Tchindundule",
    "gn:population":0,
    "gn:timezone":"Africa/Luanda",
    "iso:country":"AO",
    "wof:name":"Tchindundule",
    "wof:placetype":"locality"
},
  "geometry": {"coordinates":[15.71361,-12.96556],"type":"Point"}
}