{
  "type": "Feature",
  "properties": {
    "gn:admin1_code":"17.0",
    "gn:asciiname":"Luangue",
    "gn:country_code":"AO",
    "gn:dem":960,
    "gn:feature_class":"P",
    "gn:feature_code":"PPL",
    "gn:name":"Luangue",
    "gn:population":0,
    "gn:timezone":"Africa/Luanda",
    "iso:country":"AO",
    "name:por_x_preferred":[
        "Luangue"
    ],
    "wof:name":"Luangue",
    "wof:placetype":"locality"
},
  "geometry": {"coordinates":[19.63333,-7.31667],"type":"Point"}
}