{
  "type": "Feature",
  "properties": {
    "gn:admin1_code":"12.0",
    "gn:asciiname":"Quibinda",
    "gn:country_code":"AO",
    "gn:dem":725,
    "gn:feature_class":"P",
    "gn:feature_code":"PPL",
    "gn:name":"Quibinda",
    "gn:population":0,
    "gn:timezone":"Africa/Luanda",
    "iso:country":"AO",
    "wof:name":"Quibinda",
    "wof:placetype":"locality"
},
  "geometry": {"coordinates":[17.04977,-8.9229],"type":"Point"}
}