{
  "type": "Feature",
  "properties": {
    "gn:admin1_code":"12.0",
    "gn:asciiname":"Marimba",
    "gn:country_code":"AO",
    "gn:dem":752,
    "gn:feature_class":"P",
    "gn:feature_code":"PPL",
    "gn:name":"Marimba",
    "gn:population":0,
    "gn:timezone":"Africa/Luanda",
    "iso:country":"AO",
    "name:cat_x_preferred":[
        "Marimba"
    ],
    "name:deu_x_preferred":[
        "Marimba"
    ],
    "name:ita_x_preferred":[
        "Marimba"
    ],
    "name:msa_x_preferred":[
        "Marimba"
    ],
    "name:por_x_preferred":[
        "Marimba"
    ],
    "name:rus_x_preferred":[
        "\u041c\u0430\u0440\u0438\u043c\u0431\u0430"
    ],
    "name:spa_x_preferred":[
        "Marimba"
    ],
    "name:und_x_variant":[
        "Marimbe"
    ],
    "name:zho_x_preferred":[
        "\u99ac\u6797\u5df4"
    ],
    "wof:name":"Marimba",
    "wof:placetype":"locality"
},
  "geometry": {"coordinates":[17.02277,-8.35998],"type":"Point"}
}