{
  "type": "Feature",
  "properties": {
    "gn:admin1_code":"6.0",
    "gn:asciiname":"Inconcom",
    "gn:country_code":"AO",
    "gn:dem":1055,
    "gn:feature_class":"P",
    "gn:feature_code":"PPL",
    "gn:name":"Inconcom",
    "gn:population":0,
    "gn:timezone":"Africa/Luanda",
    "iso:country":"AO",
    "name:und_x_variant":[
        "Gongo",
        "Ingongom",
        "Inconcom"
    ],
    "wof:name":"Inconcom",
    "wof:placetype":"locality"
},
  "geometry": {"coordinates":[14.28486,-11.41082],"type":"Point"}
}