{
  "type": "Feature",
  "properties": {
    "gn:admin1_code":"17.0",
    "gn:asciiname":"Cazengue",
    "gn:country_code":"AO",
    "gn:dem":898,
    "gn:feature_class":"P",
    "gn:feature_code":"PPL",
    "gn:name":"Cazengue",
    "gn:population":0,
    "gn:timezone":"Africa/Luanda",
    "iso:country":"AO",
    "wof:name":"Cazengue",
    "wof:placetype":"locality"
},
  "geometry": {"coordinates":[21.21331,-8.47106],"type":"Point"}
}