{
  "type": "Feature",
  "properties": {
    "gn:admin1_code":"7.0",
    "gn:asciiname":"Peco",
    "gn:cc2":"AO",
    "gn:country_code":"AO",
    "gn:dem":1246,
    "gn:feature_class":"P",
    "gn:feature_code":"PPL",
    "gn:name":"Peco",
    "gn:population":0,
    "gn:timezone":"Africa/Luanda",
    "iso:country":"AO",
    "name:und_x_variant":[
        "Incha",
        "Li\u00e9peca",
        "Liapeca",
        "Peco"
    ],
    "wof:name":"Peco",
    "wof:placetype":"locality"
},
  "geometry": {"coordinates":[16.76667,-15.18333],"type":"Point"}
}