{
  "type": "Feature",
  "properties": {
    "gn:admin1_code":"12.0",
    "gn:asciiname":"Mavalala",
    "gn:country_code":"AO",
    "gn:dem":870,
    "gn:feature_class":"P",
    "gn:feature_code":"PPL",
    "gn:name":"Mavalala",
    "gn:population":0,
    "gn:timezone":"Africa/Luanda",
    "iso:country":"AO",
    "wof:name":"Mavalala",
    "wof:placetype":"locality"
},
  "geometry": {"coordinates":[17.13332999999999,-9.25],"type":"Point"}
}