{
  "type": "Feature",
  "properties": {
    "gn:admin1_code":"14.0",
    "gn:asciiname":"Tchivumbo",
    "gn:country_code":"AO",
    "gn:dem":1162,
    "gn:feature_class":"P",
    "gn:feature_code":"PPL",
    "gn:name":"Tchivumbo",
    "gn:population":0,
    "gn:timezone":"Africa/Luanda",
    "iso:country":"AO",
    "wof:name":"Tchivumbo",
    "wof:placetype":"locality"
},
  "geometry": {"coordinates":[20.56744,-11.39498],"type":"Point"}
}