{
  "type": "Feature",
  "properties": {
    "gn:admin1_code":"15.0",
    "gn:asciiname":"Quiniangui",
    "gn:country_code":"AO",
    "gn:dem":884,
    "gn:feature_class":"P",
    "gn:feature_code":"PPL",
    "gn:name":"Quiniangui",
    "gn:population":0,
    "gn:timezone":"Africa/Luanda",
    "iso:country":"AO",
    "wof:name":"Quiniangui",
    "wof:placetype":"locality"
},
  "geometry": {"coordinates":[15.02488,-6.0408],"type":"Point"}
}