{
  "type": "Feature",
  "properties": {
    "gn:admin1_code":"5.0",
    "gn:asciiname":"Roca Vizeu",
    "gn:cc2":"AO",
    "gn:country_code":"AO",
    "gn:dem":519,
    "gn:feature_class":"P",
    "gn:feature_code":"PPL",
    "gn:name":"Ro\u00e7a Vizeu",
    "gn:population":0,
    "gn:timezone":"Africa/Luanda",
    "iso:country":"AO",
    "name:und_x_variant":[
        "Viegas Cardoso",
        "Ro\u00e7a Vizeu"
    ],
    "wof:name":"Roca Vizeu",
    "wof:placetype":"locality"
},
  "geometry": {"coordinates":[14.75,-9.15],"type":"Point"}
}