{
  "type": "Feature",
  "properties": {
    "gn:admin1_code":"4.0",
    "gn:asciiname":"Mulivama",
    "gn:country_code":"AO",
    "gn:dem":1417,
    "gn:feature_class":"P",
    "gn:feature_code":"PPL",
    "gn:name":"Mulivama",
    "gn:population":0,
    "gn:timezone":"Africa/Luanda",
    "iso:country":"AO",
    "wof:name":"Mulivama",
    "wof:placetype":"locality"
},
  "geometry": {"coordinates":[17.25,-15.08333],"type":"Point"}
}