{
  "type": "Feature",
  "properties": {
    "gn:admin1_code":"19.0",
    "gn:asciiname":"Cazua",
    "gn:country_code":"AO",
    "gn:dem":299,
    "gn:feature_class":"P",
    "gn:feature_code":"PPL",
    "gn:name":"Cazua",
    "gn:population":0,
    "gn:timezone":"Africa/Luanda",
    "iso:country":"AO",
    "wof:name":"Cazua",
    "wof:placetype":"locality"
},
  "geometry": {"coordinates":[14.46969,-8.83879],"type":"Point"}
}