{
  "type": "Feature",
  "properties": {
    "gn:admin1_code":"12.0",
    "gn:asciiname":"Hunga",
    "gn:country_code":"AO",
    "gn:dem":981,
    "gn:feature_class":"P",
    "gn:feature_code":"PPL",
    "gn:name":"Hunga",
    "gn:population":0,
    "gn:timezone":"Africa/Luanda",
    "iso:country":"AO",
    "name:ceb_x_preferred":[
        "Hunga"
    ],
    "name:fra_x_preferred":[
        "Hunga"
    ],
    "name:ita_x_preferred":[
        "Hunga"
    ],
    "name:new_x_preferred":[
        "\u0939\u0941\u0919\u094d\u0917\u093e"
    ],
    "name:por_x_preferred":[
        "Hunga"
    ],
    "name:spa_x_preferred":[
        "Hunga"
    ],
    "name:swe_x_preferred":[
        "Hunga"
    ],
    "name:war_x_preferred":[
        "Hunga"
    ],
    "wof:name":"Hunga",
    "wof:placetype":"locality"
},
  "geometry": {"coordinates":[15.62353,-9.74831],"type":"Point"}
}