{
  "type": "Feature",
  "properties": {
    "gn:admin1_code":"6.0",
    "gn:asciiname":"Zacaria",
    "gn:country_code":"AO",
    "gn:dem":1395,
    "gn:feature_class":"P",
    "gn:feature_code":"PPL",
    "gn:name":"Zacaria",
    "gn:population":0,
    "gn:timezone":"Africa/Luanda",
    "iso:country":"AO",
    "name:und_x_variant":[
        "Quitote"
    ],
    "wof:name":"Zacaria",
    "wof:placetype":"locality"
},
  "geometry": {"coordinates":[15.00577,-10.6354],"type":"Point"}
}