{
  "type": "Feature",
  "properties": {
    "gn:admin1_code":"15.0",
    "gn:asciiname":"Gumbe",
    "gn:cc2":"AO",
    "gn:country_code":"AO",
    "gn:dem":782,
    "gn:feature_class":"P",
    "gn:feature_code":"PPL",
    "gn:name":"Gumbe",
    "gn:population":0,
    "gn:timezone":"Africa/Luanda",
    "iso:country":"AO",
    "name:fra_x_preferred":[
        "Gumbe"
    ],
    "name:por_x_preferred":[
        "Gumb\u00e9"
    ],
    "name:und_x_variant":[
        "Gombe"
    ],
    "wof:name":"Gumbe",
    "wof:placetype":"locality"
},
  "geometry": {"coordinates":[14.98333,-5.95],"type":"Point"}
}