{
  "type": "Feature",
  "properties": {
    "gn:admin1_code":"12.0",
    "gn:asciiname":"Ndala Catucula",
    "gn:country_code":"AO",
    "gn:dem":1278,
    "gn:feature_class":"P",
    "gn:feature_code":"PPL",
    "gn:name":"Ndala Catucula",
    "gn:population":0,
    "gn:timezone":"Africa/Luanda",
    "iso:country":"AO",
    "name:und_x_variant":[
        "Dala"
    ],
    "wof:name":"Ndala Catucula",
    "wof:placetype":"locality"
},
  "geometry": {"coordinates":[15.8816,-8.27178],"type":"Point"}
}