{
  "type": "Feature",
  "properties": {
    "gn:admin1_code":"12.0",
    "gn:asciiname":"Mbanja Mudili",
    "gn:country_code":"AO",
    "gn:dem":764,
    "gn:feature_class":"P",
    "gn:feature_code":"PPL",
    "gn:name":"Mbanja Mudili",
    "gn:population":0,
    "gn:timezone":"Africa/Luanda",
    "iso:country":"AO",
    "wof:name":"Mbanja Mudili",
    "wof:placetype":"locality"
},
  "geometry": {"coordinates":[16.7169,-8.0252],"type":"Point"}
}