{
  "type": "Feature",
  "properties": {
    "gn:admin1_code":"16.0",
    "gn:asciiname":"Mbongui",
    "gn:country_code":"AO",
    "gn:dem":564,
    "gn:feature_class":"P",
    "gn:feature_code":"PPL",
    "gn:name":"Mbongui",
    "gn:population":0,
    "gn:timezone":"Africa/Luanda",
    "iso:country":"AO",
    "name:und_x_variant":[
        "Bongue"
    ],
    "wof:name":"Mbongui",
    "wof:placetype":"locality"
},
  "geometry": {"coordinates":[14.673,-6.04946],"type":"Point"}
}