{
  "type": "Feature",
  "properties": {
    "gn:admin1_code":"12.0",
    "gn:asciiname":"Buaca Nzango",
    "gn:country_code":"AO",
    "gn:dem":1198,
    "gn:feature_class":"P",
    "gn:feature_code":"PPL",
    "gn:name":"Buaca Nzango",
    "gn:population":0,
    "gn:timezone":"Africa/Luanda",
    "iso:country":"AO",
    "wof:name":"Buaca Nzango",
    "wof:placetype":"locality"
},
  "geometry": {"coordinates":[16.02908,-8.59525],"type":"Point"}
}