{
  "type": "Feature",
  "properties": {
    "gn:admin1_code":"12.0",
    "gn:asciiname":"Mutoto",
    "gn:country_code":"AO",
    "gn:dem":1168,
    "gn:feature_class":"P",
    "gn:feature_code":"PPL",
    "gn:name":"Mutoto",
    "gn:population":0,
    "gn:timezone":"Africa/Luanda",
    "iso:country":"AO",
    "wof:name":"Mutoto",
    "wof:placetype":"locality"
},
  "geometry": {"coordinates":[17.87469,-10.56308],"type":"Point"}
}