{
  "type": "Feature",
  "properties": {
    "gn:admin1_code":"19.0",
    "gn:asciiname":"Quifuta",
    "gn:country_code":"AO",
    "gn:dem":623,
    "gn:feature_class":"P",
    "gn:feature_code":"PPL",
    "gn:name":"Quifuta",
    "gn:population":0,
    "gn:timezone":"Africa/Luanda",
    "iso:country":"AO",
    "name:und_x_variant":[
        "Quifula"
    ],
    "wof:name":"Quifuta",
    "wof:placetype":"locality"
},
  "geometry": {"coordinates":[14.25889,-8.26657],"type":"Point"}
}