{
  "type": "Feature",
  "properties": {
    "gn:admin1_code":"3.0",
    "gn:asciiname":"Chimputo",
    "gn:cc2":"AO",
    "gn:country_code":"AO",
    "gn:dem":99,
    "gn:feature_class":"P",
    "gn:feature_code":"PPL",
    "gn:name":"Chimputo",
    "gn:population":0,
    "gn:timezone":"Africa/Luanda",
    "iso:country":"AO",
    "name:und_x_variant":[
        "Khimputo",
        "Chimputo"
    ],
    "wof:name":"Chimputo",
    "wof:placetype":"locality"
},
  "geometry": {"coordinates":[12.26667,-4.98333],"type":"Point"}
}