{
  "type": "Feature",
  "properties": {
    "gn:admin1_code":"8.0",
    "gn:asciiname":"Abilio",
    "gn:country_code":"AO",
    "gn:dem":1718,
    "gn:feature_class":"P",
    "gn:feature_code":"PPL",
    "gn:name":"Abilio",
    "gn:population":0,
    "gn:timezone":"Africa/Luanda",
    "iso:country":"AO",
    "wof:name":"Abilio",
    "wof:placetype":"locality"
},
  "geometry": {"coordinates":[15.95,-12.93333],"type":"Point"}
}