{
  "type": "Feature",
  "properties": {
    "gn:admin1_code":"9.0",
    "gn:asciiname":"Samba-Cavinga",
    "gn:cc2":"AO",
    "gn:country_code":"AO",
    "gn:dem":1527,
    "gn:feature_class":"P",
    "gn:feature_code":"PPL",
    "gn:name":"Samba-Cavinga",
    "gn:population":0,
    "gn:timezone":"Africa/Luanda",
    "iso:country":"AO",
    "name:und_x_variant":[
        "Cavinga",
        "Samba-Cavinga"
    ],
    "wof:name":"Samba-Cavinga",
    "wof:placetype":"locality"
},
  "geometry": {"coordinates":[16.26667,-14.28333],"type":"Point"}
}