{
  "type": "Feature",
  "properties": {
    "gn:admin1_code":"14.0",
    "gn:asciiname":"Cafungo",
    "gn:country_code":"AO",
    "gn:dem":1116,
    "gn:feature_class":"P",
    "gn:feature_code":"PPL",
    "gn:name":"Cafungo",
    "gn:population":0,
    "gn:timezone":"Africa/Luanda",
    "iso:country":"AO",
    "wof:name":"Cafungo",
    "wof:placetype":"locality"
},
  "geometry": {"coordinates":[22.09677000000001,-10.90737],"type":"Point"}
}