{
  "type": "Feature",
  "properties": {
    "gn:admin1_code":"17.0",
    "gn:asciiname":"Canguanda",
    "gn:country_code":"AO",
    "gn:dem":1067,
    "gn:feature_class":"P",
    "gn:feature_code":"PPL",
    "gn:name":"Canguanda",
    "gn:population":0,
    "gn:timezone":"Africa/Luanda",
    "iso:country":"AO",
    "wof:name":"Canguanda",
    "wof:placetype":"locality"
},
  "geometry": {"coordinates":[18.25181,-8.87492],"type":"Point"}
}