{
  "type": "Feature",
  "properties": {
    "gn:admin1_code":"8.0",
    "gn:asciiname":"Candeleia",
    "gn:cc2":"AO",
    "gn:country_code":"AO",
    "gn:dem":1596,
    "gn:feature_class":"P",
    "gn:feature_code":"PPL",
    "gn:name":"Candeleia",
    "gn:population":0,
    "gn:timezone":"Africa/Luanda",
    "iso:country":"AO",
    "name:und_x_variant":[
        "Candereia",
        "Candeleia"
    ],
    "wof:name":"Candeleia",
    "wof:placetype":"locality"
},
  "geometry": {"coordinates":[15.11667,-12.08333],"type":"Point"}
}