{
  "type": "Feature",
  "properties": {
    "gn:admin1_code":"5.0",
    "gn:asciiname":"Pamba de Baixo",
    "gn:country_code":"AO",
    "gn:dem":710,
    "gn:feature_class":"P",
    "gn:feature_code":"PPL",
    "gn:name":"Pamba de Baixo",
    "gn:population":0,
    "gn:timezone":"Africa/Luanda",
    "iso:country":"AO",
    "name:und_x_variant":[
        "Ambaca",
        "Pamba",
        "Pamba de Baixo"
    ],
    "wof:name":"Pamba de Baixo",
    "wof:placetype":"locality"
},
  "geometry": {"coordinates":[15.17525,-9.26816],"type":"Point"}
}