{
  "type": "Feature",
  "properties": {
    "gn:admin1_code":"5.0",
    "gn:asciiname":"Cambondo",
    "gn:country_code":"AO",
    "gn:dem":28,
    "gn:feature_class":"P",
    "gn:feature_code":"PPL",
    "gn:name":"Cambondo",
    "gn:population":0,
    "gn:timezone":"Africa/Luanda",
    "iso:country":"AO",
    "wof:name":"Cambondo",
    "wof:placetype":"locality"
},
  "geometry": {"coordinates":[14.30848,-9.69642],"type":"Point"}
}