{
  "type": "Feature",
  "properties": {
    "gn:admin1_code":"12.0",
    "gn:asciiname":"Lau",
    "gn:country_code":"AO",
    "gn:dem":1123,
    "gn:feature_class":"P",
    "gn:feature_code":"PPL",
    "gn:name":"Lau",
    "gn:population":0,
    "gn:timezone":"Africa/Luanda",
    "iso:country":"AO",
    "name:ceb_x_preferred":[
        "Lau"
    ],
    "name:ces_x_preferred":[
        "Lau"
    ],
    "name:deu_x_preferred":[
        "Lau"
    ],
    "name:fra_x_preferred":[
        "Lau"
    ],
    "name:heb_x_preferred":[
        "\u05dc\u05d0\u05d5"
    ],
    "name:nld_x_preferred":[
        "Lau"
    ],
    "name:swe_x_preferred":[
        "Lau"
    ],
    "name:ukr_x_preferred":[
        "LAU"
    ],
    "wof:name":"Lau",
    "wof:placetype":"locality"
},
  "geometry": {"coordinates":[16.33251,-9.41942],"type":"Point"}
}