{
  "type": "Feature",
  "properties": {
    "gn:admin1_code":"15.0",
    "gn:asciiname":"Dumbi",
    "gn:country_code":"AO",
    "gn:dem":504,
    "gn:feature_class":"P",
    "gn:feature_code":"PPL",
    "gn:name":"Dumbi",
    "gn:population":0,
    "gn:timezone":"Africa/Luanda",
    "iso:country":"AO",
    "wof:name":"Dumbi",
    "wof:placetype":"locality"
},
  "geometry": {"coordinates":[14.0245,-7.2002],"type":"Point"}
}