{
  "type": "Feature",
  "properties": {
    "gn:admin1_code":"16.0",
    "gn:asciiname":"Zongo",
    "gn:country_code":"AO",
    "gn:dem":484,
    "gn:feature_class":"P",
    "gn:feature_code":"PPL",
    "gn:name":"Zongo",
    "gn:population":0,
    "gn:timezone":"Africa/Luanda",
    "iso:country":"AO",
    "name:ara_x_preferred":[
        "\u0632\u0648\u0646\u063a\u0648"
    ],
    "name:ben_x_preferred":[
        "\u099c\u09cb\u0982\u0997\u09cb"
    ],
    "name:ceb_x_preferred":[
        "Zongo"
    ],
    "name:deu_x_preferred":[
        "Zongo"
    ],
    "name:ell_x_preferred":[
        "\u0396\u03cc\u03bd\u03b3\u03ba\u03bf"
    ],
    "name:fas_x_preferred":[
        "\u0632\u0648\u0646\u06af\u0648"
    ],
    "name:fra_x_preferred":[
        "Zongo"
    ],
    "name:heb_x_preferred":[
        "\u05d6\u05d5\u05e0\u05d2\u05d5"
    ],
    "name:hin_x_preferred":[
        "\u091c\u093c\u094b\u0902\u0917\u094b"
    ],
    "name:hun_x_preferred":[
        "Zongo"
    ],
    "name:ind_x_preferred":[
        "Zongo"
    ],
    "name:ita_x_preferred":[
        "Zongo"
    ],
    "name:kor_x_preferred":[
        "\uc885\uace0"
    ],
    "name:rus_x_preferred":[
        "\u0417\u043e\u043d\u0433\u043e"
    ],
    "name:spa_x_preferred":[
        "Zongo"
    ],
    "name:swe_x_preferred":[
        "Zongo"
    ],
    "name:tur_x_preferred":[
        "Zongo"
    ],
    "name:ukr_x_preferred":[
        "\u0417\u043e\u043d\u0433\u043e"
    ],
    "name:urd_x_preferred":[
        "\u0632\u0648\u0646\u06af\u0648"
    ],
    "name:vie_x_preferred":[
        "Zongo"
    ],
    "wof:name":"Zongo",
    "wof:placetype":"locality"
},
  "geometry": {"coordinates":[14.14837,-6.80996],"type":"Point"}
}