{
  "type": "Feature",
  "properties": {
    "gn:admin1_code":"16.0",
    "gn:asciiname":"Zongo",
    "gn:country_code":"AO",
    "gn:dem":484,
    "gn:feature_class":"P",
    "gn:feature_code":"PPL",
    "gn:name":"Zongo",
    "gn:population":0,
    "gn:timezone":"Africa/Luanda",
    "iso:country":"AO",
    "name:ceb_x_preferred":[
        "Zongo"
    ],
    "name:deu_x_preferred":[
        "Zongo"
    ],
    "name:fra_x_preferred":[
        "Zongo"
    ],
    "name:ita_x_preferred":[
        "Zongo"
    ],
    "name:rus_x_preferred":[
        "\u0417\u043e\u043d\u0433\u043e"
    ],
    "name:spa_x_preferred":[
        "Zongo"
    ],
    "name:swe_x_preferred":[
        "Zongo"
    ],
    "wof:name":"Zongo",
    "wof:placetype":"locality"
},
  "geometry": {"coordinates":[14.14837,-6.80996],"type":"Point"}
}