{
  "type": "Feature",
  "properties": {
    "gn:admin1_code":"17.0",
    "gn:asciiname":"Sufidi",
    "gn:country_code":"AO",
    "gn:dem":701,
    "gn:feature_class":"P",
    "gn:feature_code":"PPL",
    "gn:name":"Sufidi",
    "gn:population":0,
    "gn:timezone":"Africa/Luanda",
    "iso:country":"AO",
    "wof:name":"Sufidi",
    "wof:placetype":"locality"
},
  "geometry": {"coordinates":[20.85,-7.53333],"type":"Point"}
}