{
  "type": "Feature",
  "properties": {
    "gn:admin1_code":"1.0",
    "gn:asciiname":"Uombo",
    "gn:country_code":"AO",
    "gn:dem":1128,
    "gn:feature_class":"P",
    "gn:feature_code":"PPL",
    "gn:name":"Uombo",
    "gn:population":0,
    "gn:timezone":"Africa/Luanda",
    "iso:country":"AO",
    "wof:name":"Uombo",
    "wof:placetype":"locality"
},
  "geometry": {"coordinates":[14.23333,-12.28333],"type":"Point"}
}