{
  "type": "Feature",
  "properties": {
    "gn:admin1_code":"12.0",
    "gn:asciiname":"Canari",
    "gn:country_code":"AO",
    "gn:dem":1099,
    "gn:feature_class":"P",
    "gn:feature_code":"PPL",
    "gn:name":"Can\u00e1ri",
    "gn:population":0,
    "gn:timezone":"Africa/Luanda",
    "iso:country":"AO",
    "name:cat_x_preferred":[
        "Canari"
    ],
    "name:ceb_x_preferred":[
        "Canari"
    ],
    "name:cos_x_preferred":[
        "C\u00e0nari"
    ],
    "name:deu_x_preferred":[
        "Canari"
    ],
    "name:eus_x_preferred":[
        "Canari"
    ],
    "name:fra_x_preferred":[
        "Canari"
    ],
    "name:hun_x_preferred":[
        "Canari"
    ],
    "name:ita_x_preferred":[
        "Canari"
    ],
    "name:kaz_x_preferred":[
        "\u041a\u0430\u043d\u0430\u0440\u0438"
    ],
    "name:lat_x_preferred":[
        "Canari"
    ],
    "name:mlg_x_preferred":[
        "Canari"
    ],
    "name:msa_x_preferred":[
        "Canari"
    ],
    "name:nld_x_preferred":[
        "Canari"
    ],
    "name:oci_x_preferred":[
        "Canari"
    ],
    "name:pol_x_preferred":[
        "Canari"
    ],
    "name:por_x_preferred":[
        "Canari"
    ],
    "name:rus_x_preferred":[
        "\u041a\u0430\u043d\u0430\u0440\u0438"
    ],
    "name:slk_x_preferred":[
        "Canari"
    ],
    "name:slv_x_preferred":[
        "Canari"
    ],
    "name:spa_x_preferred":[
        "Canari"
    ],
    "name:srp_x_preferred":[
        "\u041a\u0430\u043d\u0430\u0440\u0438"
    ],
    "name:swe_x_preferred":[
        "Canari"
    ],
    "name:ukr_x_preferred":[
        "\u041a\u0430\u043d\u0430\u0440\u0456"
    ],
    "name:vie_x_preferred":[
        "Canari"
    ],
    "name:vol_x_preferred":[
        "Canari"
    ],
    "name:war_x_preferred":[
        "Canari"
    ],
    "wof:name":"Canari",
    "wof:placetype":"locality"
},
  "geometry": {"coordinates":[17.42178,-10.49354],"type":"Point"}
}