{
  "type": "Feature",
  "properties": {
    "gn:admin1_code":"12.0",
    "gn:asciiname":"Canari",
    "gn:country_code":"AO",
    "gn:dem":1099,
    "gn:feature_class":"P",
    "gn:feature_code":"PPL",
    "gn:name":"Can\u00e1ri",
    "gn:population":0,
    "gn:timezone":"Africa/Luanda",
    "iso:country":"AO",
    "wof:name":"Canari",
    "wof:placetype":"locality"
},
  "geometry": {"coordinates":[17.42178,-10.49354],"type":"Point"}
}