{
  "type": "Feature",
  "properties": {
    "gn:admin1_code":"8.0",
    "gn:asciiname":"Catchiungo",
    "gn:country_code":"AO",
    "gn:dem":1806,
    "gn:feature_class":"P",
    "gn:feature_code":"PPL",
    "gn:name":"Catchiungo",
    "gn:population":0,
    "gn:timezone":"Africa/Luanda",
    "iso:country":"AO",
    "name:azb_x_preferred":[
        "\u06a9\u062a\u0634\u06cc\u0648\u0646\u0642\u0648"
    ],
    "name:cat_x_preferred":[
        "Catchiungo"
    ],
    "name:deu_x_preferred":[
        "Cachiungo"
    ],
    "name:fas_x_preferred":[
        "\u06a9\u062a\u0634\u06cc\u0648\u0646\u06af\u0648"
    ],
    "name:ita_x_preferred":[
        "Katchiungo"
    ],
    "name:por_x_preferred":[
        "Cachiungo"
    ],
    "name:spa_x_preferred":[
        "Catchiungo"
    ],
    "name:und_x_variant":[
        "Bela Vista",
        "Vila-Nova"
    ],
    "name:zho_x_preferred":[
        "\u5361\u7279\u5e0c\u6c38\u6208"
    ],
    "wof:name":"Catchiungo",
    "wof:placetype":"locality"
},
  "geometry": {"coordinates":[16.23333,-12.56667],"type":"Point"}
}