{
  "type": "Feature",
  "properties": {
    "gn:admin1_code":"8.0",
    "gn:asciiname":"Catchiungo",
    "gn:country_code":"AO",
    "gn:dem":1806,
    "gn:feature_class":"P",
    "gn:feature_code":"PPL",
    "gn:name":"Catchiungo",
    "gn:population":0,
    "gn:timezone":"Africa/Luanda",
    "iso:country":"AO",
    "name:und_x_variant":[
        "Bela Vista",
        "Vila-Nova",
        "Katchiungo",
        "Catchiungo"
    ],
    "wof:name":"Catchiungo",
    "wof:placetype":"locality"
},
  "geometry": {"coordinates":[16.23333,-12.56667],"type":"Point"}
}