{
  "type": "Feature",
  "properties": {
    "gn:admin1_code":"17.0",
    "gn:asciiname":"Puto",
    "gn:country_code":"AO",
    "gn:dem":893,
    "gn:feature_class":"P",
    "gn:feature_code":"PPL",
    "gn:name":"Puto",
    "gn:population":0,
    "gn:timezone":"Africa/Luanda",
    "iso:country":"AO",
    "name:ceb_x_preferred":[
        "Puto"
    ],
    "name:lao_x_preferred":[
        "\u0e9b\u0eb9\u0ec2\u0e95"
    ],
    "name:msa_x_preferred":[
        "Putu piring"
    ],
    "name:nor_x_preferred":[
        "Puto"
    ],
    "name:spa_x_preferred":[
        "Puto"
    ],
    "name:tgl_x_preferred":[
        "Puto"
    ],
    "name:tha_x_preferred":[
        "\u0e1b\u0e39\u0e42\u0e15"
    ],
    "wof:name":"Puto",
    "wof:placetype":"locality"
},
  "geometry": {"coordinates":[21.69519,-7.46938],"type":"Point"}
}