{
  "type": "Feature",
  "properties": {
    "gn:admin1_code":"6.0",
    "gn:asciiname":"Betrame",
    "gn:country_code":"AO",
    "gn:dem":1362,
    "gn:feature_class":"P",
    "gn:feature_code":"PPL",
    "gn:name":"Betrame",
    "gn:population":0,
    "gn:timezone":"Africa/Luanda",
    "iso:country":"AO",
    "wof:name":"Betrame",
    "wof:placetype":"locality"
},
  "geometry": {"coordinates":[15.99258,-10.48712],"type":"Point"}
}