{
  "type": "Feature",
  "properties": {
    "gn:admin1_code":"15.0",
    "gn:asciiname":"Tavares",
    "gn:country_code":"AO",
    "gn:dem":488,
    "gn:feature_class":"P",
    "gn:feature_code":"PPL",
    "gn:name":"Tavares",
    "gn:population":0,
    "gn:timezone":"Africa/Luanda",
    "iso:country":"AO",
    "name:bpy_x_preferred":[
        "\u099f\u09be\u09ad\u09be\u09b0\u09c7\u09b8"
    ],
    "name:ceb_x_preferred":[
        "Tavares"
    ],
    "name:ces_x_preferred":[
        "Tavares"
    ],
    "name:deu_x_preferred":[
        "Tavares"
    ],
    "name:fin_x_preferred":[
        "Tavares"
    ],
    "name:fra_x_preferred":[
        "Tavares"
    ],
    "name:ita_x_preferred":[
        "Tavares"
    ],
    "name:jpn_x_preferred":[
        "\u30bf\u30f4\u30a1\u30ec\u30b9"
    ],
    "name:nld_x_preferred":[
        "Tavares"
    ],
    "name:nor_x_preferred":[
        "Tavares"
    ],
    "name:pol_x_preferred":[
        "Tavares"
    ],
    "name:por_x_preferred":[
        "Tavares"
    ],
    "name:rus_x_preferred":[
        "\u0422\u0430\u0432\u0430\u0440\u0435\u0441"
    ],
    "name:swe_x_preferred":[
        "Tavares"
    ],
    "name:ukr_x_preferred":[
        "\u0422\u0430\u0432\u0430\u0440\u0435\u0441"
    ],
    "name:vie_x_preferred":[
        "Tavares"
    ],
    "name:vol_x_preferred":[
        "Tavares"
    ],
    "wof:name":"Tavares",
    "wof:placetype":"locality"
},
  "geometry": {"coordinates":[14.56667,-6.66667],"type":"Point"}
}