{
  "type": "Feature",
  "properties": {
    "gn:admin1_code":"1.0",
    "gn:asciiname":"Chicamba",
    "gn:country_code":"AO",
    "gn:dem":1191,
    "gn:feature_class":"P",
    "gn:feature_code":"PPL",
    "gn:name":"Chicamba",
    "gn:population":0,
    "gn:timezone":"Africa/Luanda",
    "iso:country":"AO",
    "wof:name":"Chicamba",
    "wof:placetype":"locality"
},
  "geometry": {"coordinates":[14.43333,-12.26667],"type":"Point"}
}