{
  "type": "Feature",
  "properties": {
    "gn:admin1_code":"6.0",
    "gn:asciiname":"Vigesimo Quinto de Abril",
    "gn:country_code":"AO",
    "gn:dem":1132,
    "gn:feature_class":"P",
    "gn:feature_code":"PPL",
    "gn:name":"Vig\u00e9simo Quinto de Abril",
    "gn:population":0,
    "gn:timezone":"Africa/Luanda",
    "iso:country":"AO",
    "wof:name":"Vigesimo Quinto de Abril",
    "wof:placetype":"locality"
},
  "geometry": {"coordinates":[14.59354,-10.74233],"type":"Point"}
}