{
  "type": "Feature",
  "properties": {
    "gn:admin1_code":"15.0",
    "gn:asciiname":"Penda",
    "gn:country_code":"AO",
    "gn:dem":1257,
    "gn:feature_class":"P",
    "gn:feature_code":"PPL",
    "gn:name":"Penda",
    "gn:population":0,
    "gn:timezone":"Africa/Luanda",
    "iso:country":"AO",
    "wof:name":"Penda",
    "wof:placetype":"locality"
},
  "geometry": {"coordinates":[15.45144,-7.47439],"type":"Point"}
}