{
  "type": "Feature",
  "properties": {
    "gn:admin1_code":"15.0",
    "gn:asciiname":"Quimubabu",
    "gn:country_code":"AO",
    "gn:dem":777,
    "gn:feature_class":"P",
    "gn:feature_code":"PPL",
    "gn:name":"Quimubabu",
    "gn:population":0,
    "gn:timezone":"Africa/Luanda",
    "iso:country":"AO",
    "wof:name":"Quimubabu",
    "wof:placetype":"locality"
},
  "geometry": {"coordinates":[16.22797000000001,-6.37458],"type":"Point"}
}