{
  "type": "Feature",
  "properties": {
    "gn:admin1_code":"12.0",
    "gn:asciiname":"Cambo",
    "gn:country_code":"AO",
    "gn:dem":705,
    "gn:feature_class":"P",
    "gn:feature_code":"PPL",
    "gn:name":"Cambo",
    "gn:population":0,
    "gn:timezone":"Africa/Luanda",
    "iso:country":"AO",
    "name:cym_x_preferred":[
        "Cambo"
    ],
    "name:pol_x_preferred":[
        "Cambo"
    ],
    "name:und_x_variant":[
        "Monte Verde",
        "Cambo Camana",
        "Cahombo",
        "Belo Horizonte"
    ],
    "wof:name":"Cambo",
    "wof:placetype":"locality"
},
  "geometry": {"coordinates":[16.78557,-8.81189],"type":"Point"}
}