{
  "type": "Feature",
  "properties": {
    "gn:admin1_code":"5.0",
    "gn:asciiname":"Butungo",
    "gn:country_code":"AO",
    "gn:dem":575,
    "gn:feature_class":"P",
    "gn:feature_code":"PPL",
    "gn:name":"Butungo",
    "gn:population":0,
    "gn:timezone":"Africa/Luanda",
    "iso:country":"AO",
    "wof:name":"Butungo",
    "wof:placetype":"locality"
},
  "geometry": {"coordinates":[14.53333,-9.11667],"type":"Point"}
}