{
  "type": "Feature",
  "properties": {
    "gn:admin1_code":"17.0",
    "gn:asciiname":"Bungulo",
    "gn:country_code":"AO",
    "gn:dem":845,
    "gn:feature_class":"P",
    "gn:feature_code":"PPL",
    "gn:name":"Bungulo",
    "gn:population":0,
    "gn:timezone":"Africa/Luanda",
    "iso:country":"AO",
    "wof:name":"Bungulo",
    "wof:placetype":"locality"
},
  "geometry": {"coordinates":[21.50361,-8.02161],"type":"Point"}
}