{
  "type": "Feature",
  "properties": {
    "gn:admin1_code":"12.0",
    "gn:asciiname":"Quinjica",
    "gn:country_code":"AO",
    "gn:dem":1138,
    "gn:feature_class":"P",
    "gn:feature_code":"PPL",
    "gn:name":"Quinjica",
    "gn:population":0,
    "gn:timezone":"Africa/Luanda",
    "iso:country":"AO",
    "name:und_x_variant":[
        "Quingica",
        "Quinjica"
    ],
    "wof:name":"Quinjica",
    "wof:placetype":"locality"
},
  "geometry": {"coordinates":[15.88743,-8.92081],"type":"Point"}
}