{
  "type": "Feature",
  "properties": {
    "gn:admin1_code":"15.0",
    "gn:asciiname":"Zulo",
    "gn:country_code":"AO",
    "gn:dem":1114,
    "gn:feature_class":"P",
    "gn:feature_code":"PPL",
    "gn:name":"Zulo",
    "gn:population":0,
    "gn:timezone":"Africa/Luanda",
    "iso:country":"AO",
    "wof:name":"Zulo",
    "wof:placetype":"locality"
},
  "geometry": {"coordinates":[15.55,-7.56667],"type":"Point"}
}