{
  "type": "Feature",
  "properties": {
    "gn:admin1_code":"15.0",
    "gn:asciiname":"Zunga",
    "gn:country_code":"AO",
    "gn:dem":739,
    "gn:feature_class":"P",
    "gn:feature_code":"PPL",
    "gn:name":"Zunga",
    "gn:population":0,
    "gn:timezone":"Africa/Luanda",
    "iso:country":"AO",
    "wof:name":"Zunga",
    "wof:placetype":"locality"
},
  "geometry": {"coordinates":[14.83333,-6.96667],"type":"Point"}
}