{
  "type": "Feature",
  "properties": {
    "gn:admin1_code":"4.0",
    "gn:asciiname":"Cuelei",
    "gn:country_code":"AO",
    "gn:dem":1413,
    "gn:feature_class":"P",
    "gn:feature_code":"PPL",
    "gn:name":"Cuelei",
    "gn:population":0,
    "gn:timezone":"Africa/Luanda",
    "iso:country":"AO",
    "wof:name":"Cuelei",
    "wof:placetype":"locality"
},
  "geometry": {"coordinates":[17.37569,-14.67977],"type":"Point"}
}