{
  "type": "Feature",
  "properties": {
    "gn:admin1_code":"0.0",
    "gn:asciiname":"Chimama",
    "gn:country_code":"AO",
    "gn:dem":334,
    "gn:feature_class":"P",
    "gn:feature_code":"PPL",
    "gn:name":"Chimama",
    "gn:population":0,
    "gn:timezone":"Africa/Luanda",
    "iso:country":"AO",
    "wof:name":"Chimama",
    "wof:placetype":"locality"
},
  "geometry": {"coordinates":[13.84361,-12.41694],"type":"Point"}
}