{
  "type": "Feature",
  "properties": {
    "gn:admin1_code":"6.0",
    "gn:asciiname":"Tari",
    "gn:country_code":"AO",
    "gn:dem":1223,
    "gn:feature_class":"P",
    "gn:feature_code":"PPL",
    "gn:name":"Tari",
    "gn:population":0,
    "gn:timezone":"Africa/Luanda",
    "iso:country":"AO",
    "name:ceb_x_preferred":[
        "Tari"
    ],
    "name:deu_x_preferred":[
        "Tari"
    ],
    "name:fra_x_preferred":[
        "Tari"
    ],
    "name:ita_x_preferred":[
        "Tari"
    ],
    "name:nds_x_preferred":[
        "Tari"
    ],
    "name:rus_x_preferred":[
        "\u0422\u0430\u0440\u0438"
    ],
    "name:swe_x_preferred":[
        "Tari"
    ],
    "wof:name":"Tari",
    "wof:placetype":"locality"
},
  "geometry": {"coordinates":[15.06046,-10.51881],"type":"Point"}
}