{
  "type": "Feature",
  "properties": {
    "gn:admin1_code":"7.0",
    "gn:asciiname":"Mongua",
    "gn:country_code":"AO",
    "gn:dem":1131,
    "gn:feature_class":"P",
    "gn:feature_code":"PPL",
    "gn:name":"M\u00f4ngua",
    "gn:population":0,
    "gn:timezone":"Africa/Luanda",
    "iso:country":"AO",
    "name:ceb_x_preferred":[
        "Mongua"
    ],
    "name:fra_x_preferred":[
        "Mongua"
    ],
    "name:ita_x_preferred":[
        "Mongua"
    ],
    "name:kat_x_preferred":[
        "\u10db\u10dd\u10dc\u10d2\u10e3\u10d0"
    ],
    "name:msa_x_preferred":[
        "Mongua"
    ],
    "name:nld_x_preferred":[
        "Mongua"
    ],
    "name:por_x_preferred":[
        "Mongua"
    ],
    "name:rus_x_preferred":[
        "\u041c\u043e\u043d\u0433\u0443\u0430"
    ],
    "name:spa_x_preferred":[
        "Mongua"
    ],
    "name:swe_x_preferred":[
        "Mongua"
    ],
    "name:tgl_x_preferred":[
        "Mongua"
    ],
    "name:vie_x_preferred":[
        "Mongua"
    ],
    "name:war_x_preferred":[
        "Mongua"
    ],
    "wof:name":"Mongua",
    "wof:placetype":"locality"
},
  "geometry": {"coordinates":[15.36667,-16.71667],"type":"Point"}
}