{
  "type": "Feature",
  "properties": {
    "gn:admin1_code":"2.0",
    "gn:asciiname":"Ucuachalo",
    "gn:country_code":"AO",
    "gn:dem":1527,
    "gn:feature_class":"P",
    "gn:feature_code":"PPL",
    "gn:name":"Ucuachalo",
    "gn:population":0,
    "gn:timezone":"Africa/Luanda",
    "iso:country":"AO",
    "wof:name":"Ucuachalo",
    "wof:placetype":"locality"
},
  "geometry": {"coordinates":[16.89981,-11.43394],"type":"Point"}
}