{
  "type": "Feature",
  "properties": {
    "gn:admin1_code":"18.0",
    "gn:asciiname":"Muassunhengue",
    "gn:country_code":"AO",
    "gn:dem":1314,
    "gn:feature_class":"P",
    "gn:feature_code":"PPL",
    "gn:name":"Muassunhengue",
    "gn:population":0,
    "gn:timezone":"Africa/Luanda",
    "iso:country":"AO",
    "wof:name":"Muassunhengue",
    "wof:placetype":"locality"
},
  "geometry": {"coordinates":[19.47177000000001,-10.16214],"type":"Point"}
}