{
  "type": "Feature",
  "properties": {
    "gn:admin1_code":"5.0",
    "gn:asciiname":"Nhengo",
    "gn:country_code":"AO",
    "gn:dem":531,
    "gn:feature_class":"P",
    "gn:feature_code":"PPL",
    "gn:name":"Nhengo",
    "gn:population":0,
    "gn:timezone":"Africa/Luanda",
    "iso:country":"AO",
    "wof:name":"Nhengo",
    "wof:placetype":"locality"
},
  "geometry": {"coordinates":[14.60267,-9.0561],"type":"Point"}
}