{
  "type": "Feature",
  "properties": {
    "gn:admin1_code":"1.0",
    "gn:asciiname":"Cucuamalaen",
    "gn:country_code":"AO",
    "gn:dem":1222,
    "gn:feature_class":"P",
    "gn:feature_code":"PPL",
    "gn:name":"Cucuamalaen",
    "gn:population":0,
    "gn:timezone":"Africa/Luanda",
    "iso:country":"AO",
    "wof:name":"Cucuamalaen",
    "wof:placetype":"locality"
},
  "geometry": {"coordinates":[14.16667,-12.58333],"type":"Point"}
}