{
  "type": "Feature",
  "properties": {
    "gn:admin1_code":"17.0",
    "gn:asciiname":"Muacaienque",
    "gn:country_code":"AO",
    "gn:dem":1130,
    "gn:feature_class":"P",
    "gn:feature_code":"PPL",
    "gn:name":"Muacaienque",
    "gn:population":0,
    "gn:timezone":"Africa/Luanda",
    "iso:country":"AO",
    "wof:name":"Muacaienque",
    "wof:placetype":"locality"
},
  "geometry": {"coordinates":[18.88494,-8.97002],"type":"Point"}
}