{
  "type": "Feature",
  "properties": {
    "gn:admin1_code":"6.0",
    "gn:asciiname":"Cambanze",
    "gn:country_code":"AO",
    "gn:dem":882,
    "gn:feature_class":"P",
    "gn:feature_code":"PPL",
    "gn:name":"Cambanz\u00e9",
    "gn:population":0,
    "gn:timezone":"Africa/Luanda",
    "iso:country":"AO",
    "wof:name":"Cambanze",
    "wof:placetype":"locality"
},
  "geometry": {"coordinates":[14.36683,-10.56847],"type":"Point"}
}