{
  "type": "Feature",
  "properties": {
    "gn:admin1_code":"9.0",
    "gn:asciiname":"Matala",
    "gn:country_code":"AO",
    "gn:dem":1238,
    "gn:feature_class":"P",
    "gn:feature_code":"PPL",
    "gn:name":"Matala",
    "gn:population":0,
    "gn:timezone":"Africa/Luanda",
    "iso:country":"AO",
    "name:rus_x_preferred":[
        "\u041c\u0430\u0442\u0430\u043b\u0430"
    ],
    "name:und_x_variant":[
        "Aldeia da Matala",
        "Matala"
    ],
    "wof:name":"Matala",
    "wof:placetype":"locality"
},
  "geometry": {"coordinates":[15.03479,-14.73272],"type":"Point"}
}