{
  "type": "Feature",
  "properties": {
    "gn:admin1_code":"6.0",
    "gn:asciiname":"Minga",
    "gn:country_code":"AO",
    "gn:dem":944,
    "gn:feature_class":"P",
    "gn:feature_code":"PPL",
    "gn:name":"Minga",
    "gn:population":0,
    "gn:timezone":"Africa/Luanda",
    "iso:country":"AO",
    "name:cat_x_preferred":[
        "Minga"
    ],
    "name:ceb_x_preferred":[
        "Minga"
    ],
    "name:deu_x_preferred":[
        "Minga"
    ],
    "name:fra_x_preferred":[
        "Minga"
    ],
    "name:pol_x_preferred":[
        "Minga"
    ],
    "name:spa_x_preferred":[
        "Minga"
    ],
    "name:swe_x_preferred":[
        "Minga"
    ],
    "wof:name":"Minga",
    "wof:placetype":"locality"
},
  "geometry": {"coordinates":[14.28603,-11.10588],"type":"Point"}
}