{
  "type": "Feature",
  "properties": {
    "gn:admin1_code":"15.0",
    "gn:asciiname":"Quicuni",
    "gn:country_code":"AO",
    "gn:dem":1025,
    "gn:feature_class":"P",
    "gn:feature_code":"PPL",
    "gn:name":"Quicuni",
    "gn:population":0,
    "gn:timezone":"Africa/Luanda",
    "iso:country":"AO",
    "name:und_x_variant":[
        "Quifache",
        "Quicuni"
    ],
    "wof:name":"Quicuni",
    "wof:placetype":"locality"
},
  "geometry": {"coordinates":[15.94476,-7.28947],"type":"Point"}
}