{
  "type": "Feature",
  "properties": {
    "gn:admin1_code":"5.0",
    "gn:asciiname":"Zaca",
    "gn:country_code":"AO",
    "gn:dem":1191,
    "gn:feature_class":"P",
    "gn:feature_code":"PPL",
    "gn:name":"Zaca",
    "gn:population":0,
    "gn:timezone":"Africa/Luanda",
    "iso:country":"AO",
    "wof:name":"Zaca",
    "wof:placetype":"locality"
},
  "geometry": {"coordinates":[15.304,-8.27424],"type":"Point"}
}