{
  "type": "Feature",
  "properties": {
    "gn:admin1_code":"5.0",
    "gn:asciiname":"Tunda",
    "gn:country_code":"AO",
    "gn:dem":1272,
    "gn:feature_class":"P",
    "gn:feature_code":"PPL",
    "gn:name":"Tunda",
    "gn:population":0,
    "gn:timezone":"Africa/Luanda",
    "iso:country":"AO",
    "name:ind_x_preferred":[
        "Tunda"
    ],
    "name:spa_x_preferred":[
        "Tunda"
    ],
    "wof:name":"Tunda",
    "wof:placetype":"locality"
},
  "geometry": {"coordinates":[15.62803,-8.69496],"type":"Point"}
}