{
  "type": "Feature",
  "properties": {
    "gn:admin1_code":"1.0",
    "gn:asciiname":"Hahongo",
    "gn:country_code":"AO",
    "gn:dem":270,
    "gn:feature_class":"P",
    "gn:feature_code":"PPL",
    "gn:name":"Hahongo",
    "gn:population":0,
    "gn:timezone":"Africa/Luanda",
    "iso:country":"AO",
    "wof:name":"Hahongo",
    "wof:placetype":"locality"
},
  "geometry": {"coordinates":[13.98386,-11.98837],"type":"Point"}
}