{
  "type": "Feature",
  "properties": {
    "gn:admin1_code":"0.0",
    "gn:asciiname":"Halo",
    "gn:country_code":"AO",
    "gn:dem":774,
    "gn:feature_class":"P",
    "gn:feature_code":"PPL",
    "gn:name":"Halo",
    "gn:population":0,
    "gn:timezone":"Africa/Luanda",
    "iso:country":"AO",
    "wof:name":"Halo",
    "wof:placetype":"locality"
},
  "geometry": {"coordinates":[13.99,-12.97278],"type":"Point"}
}