{
  "type": "Feature",
  "properties": {
    "gn:admin1_code":"0.0",
    "gn:asciiname":"Halo",
    "gn:country_code":"AO",
    "gn:dem":774,
    "gn:feature_class":"P",
    "gn:feature_code":"PPL",
    "gn:name":"Halo",
    "gn:population":0,
    "gn:timezone":"Africa/Luanda",
    "iso:country":"AO",
    "name:ara_x_preferred":[
        "\u0647\u0627\u0644\u0629"
    ],
    "name:aze_x_preferred":[
        "Halo"
    ],
    "name:cat_x_preferred":[
        "Halo"
    ],
    "name:ceb_x_preferred":[
        "Halo"
    ],
    "name:dan_x_preferred":[
        "Halo"
    ],
    "name:deu_x_preferred":[
        "Halo"
    ],
    "name:ell_x_preferred":[
        "Halo"
    ],
    "name:eus_x_preferred":[
        "Halo"
    ],
    "name:fin_x_preferred":[
        "Halo"
    ],
    "name:fra_x_preferred":[
        "Halo"
    ],
    "name:heb_x_preferred":[
        "Halo"
    ],
    "name:hrv_x_preferred":[
        "Halo"
    ],
    "name:hun_x_preferred":[
        "Halo"
    ],
    "name:ind_x_preferred":[
        "Halo"
    ],
    "name:ita_x_preferred":[
        "Halo"
    ],
    "name:kor_x_preferred":[
        "\ud5e4\uc77c\ub85c"
    ],
    "name:nld_x_preferred":[
        "Halo"
    ],
    "name:nno_x_preferred":[
        "Halo"
    ],
    "name:nor_x_preferred":[
        "Halo"
    ],
    "name:pol_x_preferred":[
        "Halo"
    ],
    "name:por_x_preferred":[
        "Halo"
    ],
    "name:ron_x_preferred":[
        "Halo"
    ],
    "name:rus_x_preferred":[
        "Halo"
    ],
    "name:slk_x_preferred":[
        "Halo"
    ],
    "name:slv_x_preferred":[
        "Halo"
    ],
    "name:spa_x_preferred":[
        "Halo"
    ],
    "name:swe_x_preferred":[
        "Halo"
    ],
    "name:tur_x_preferred":[
        "Halo"
    ],
    "name:zho_x_preferred":[
        "Halo"
    ],
    "wof:name":"Halo",
    "wof:placetype":"locality"
},
  "geometry": {"coordinates":[13.99,-12.97278],"type":"Point"}
}