{
  "type": "Feature",
  "properties": {
    "gn:admin1_code":"2.0",
    "gn:asciiname":"Ndemba",
    "gn:country_code":"AO",
    "gn:dem":1683,
    "gn:feature_class":"P",
    "gn:feature_code":"PPL",
    "gn:name":"Ndemba",
    "gn:population":0,
    "gn:timezone":"Africa/Luanda",
    "iso:country":"AO",
    "wof:name":"Ndemba",
    "wof:placetype":"locality"
},
  "geometry": {"coordinates":[16.38226,-11.20234],"type":"Point"}
}