{
  "type": "Feature",
  "properties": {
    "gn:admin1_code":"15.0",
    "gn:asciiname":"Banza Tende",
    "gn:country_code":"AO",
    "gn:dem":1019,
    "gn:feature_class":"P",
    "gn:feature_code":"PPL",
    "gn:name":"Banza Tende",
    "gn:population":0,
    "gn:timezone":"Africa/Luanda",
    "iso:country":"AO",
    "wof:name":"Banza Tende",
    "wof:placetype":"locality"
},
  "geometry": {"coordinates":[15.05008,-6.55912],"type":"Point"}
}