{
  "type": "Feature",
  "properties": {
    "gn:admin1_code":"12.0",
    "gn:asciiname":"Golombole",
    "gn:country_code":"AO",
    "gn:dem":1063,
    "gn:feature_class":"P",
    "gn:feature_code":"PPL",
    "gn:name":"Golombole",
    "gn:population":0,
    "gn:timezone":"Africa/Luanda",
    "iso:country":"AO",
    "wof:name":"Golombole",
    "wof:placetype":"locality"
},
  "geometry": {"coordinates":[16.06028,-9.58694],"type":"Point"}
}