{
  "type": "Feature",
  "properties": {
    "gn:admin1_code":"8.0",
    "gn:asciiname":"Livongue",
    "gn:country_code":"AO",
    "gn:dem":1596,
    "gn:feature_class":"P",
    "gn:feature_code":"PPL",
    "gn:name":"Livongue",
    "gn:population":0,
    "gn:timezone":"Africa/Luanda",
    "iso:country":"AO",
    "wof:name":"Livongue",
    "wof:placetype":"locality"
},
  "geometry": {"coordinates":[15.53333,-12.46667],"type":"Point"}
}