{
  "type": "Feature",
  "properties": {
    "gn:admin1_code":"17.0",
    "gn:asciiname":"Cambanzumbe",
    "gn:cc2":"AO",
    "gn:country_code":"AO",
    "gn:dem":941,
    "gn:feature_class":"P",
    "gn:feature_code":"PPL",
    "gn:name":"Cambanzumbe",
    "gn:population":0,
    "gn:timezone":"Africa/Luanda",
    "iso:country":"AO",
    "name:und_x_variant":[
        "Quissango",
        "Cambanzumbe"
    ],
    "wof:name":"Cambanzumbe",
    "wof:placetype":"locality"
},
  "geometry": {"coordinates":[20.23333,-8.21667],"type":"Point"}
}