{
  "type": "Feature",
  "properties": {
    "gn:admin1_code":"12.0",
    "gn:asciiname":"Carianga",
    "gn:country_code":"AO",
    "gn:dem":1040,
    "gn:feature_class":"P",
    "gn:feature_code":"PPL",
    "gn:name":"Carianga",
    "gn:population":0,
    "gn:timezone":"Africa/Luanda",
    "iso:country":"AO",
    "wof:name":"Carianga",
    "wof:placetype":"locality"
},
  "geometry": {"coordinates":[15.98415,-9.16802],"type":"Point"}
}