{
  "type": "Feature",
  "properties": {
    "gn:admin1_code":"8.0",
    "gn:asciiname":"Catape",
    "gn:cc2":"AO",
    "gn:country_code":"AO",
    "gn:dem":1737,
    "gn:feature_class":"P",
    "gn:feature_code":"PPL",
    "gn:name":"Catape",
    "gn:population":0,
    "gn:timezone":"Africa/Luanda",
    "iso:country":"AO",
    "name:und_x_variant":[
        "Catapi",
        "Catape"
    ],
    "wof:name":"Catape",
    "wof:placetype":"locality"
},
  "geometry": {"coordinates":[15.75,-11.95],"type":"Point"}
}