{
  "type": "Feature",
  "properties": {
    "gn:admin1_code":"12.0",
    "gn:asciiname":"Casal",
    "gn:country_code":"AO",
    "gn:dem":1168,
    "gn:feature_class":"P",
    "gn:feature_code":"PPL",
    "gn:name":"Casal",
    "gn:population":0,
    "gn:timezone":"Africa/Luanda",
    "iso:country":"AO",
    "name:nld_x_preferred":[
        "Casal"
    ],
    "name:swe_x_preferred":[
        "Casal"
    ],
    "wof:name":"Casal",
    "wof:placetype":"locality"
},
  "geometry": {"coordinates":[16.45695,-9.42623],"type":"Point"}
}