{
  "type": "Feature",
  "properties": {
    "gn:admin1_code":"15.0",
    "gn:asciiname":"Lutanda",
    "gn:country_code":"AO",
    "gn:dem":1213,
    "gn:feature_class":"P",
    "gn:feature_code":"PPL",
    "gn:name":"Lutanda",
    "gn:population":0,
    "gn:timezone":"Africa/Luanda",
    "iso:country":"AO",
    "name:und_x_variant":[
        "Quicangana",
        "Lutanda"
    ],
    "wof:name":"Lutanda",
    "wof:placetype":"locality"
},
  "geometry": {"coordinates":[15.117,-7.18467],"type":"Point"}
}