{
  "type": "Feature",
  "properties": {
    "gn:admin1_code":"12.0",
    "gn:asciiname":"Mangando do Povo",
    "gn:country_code":"AO",
    "gn:dem":686,
    "gn:feature_class":"P",
    "gn:feature_code":"PPL",
    "gn:name":"Mangando do Povo",
    "gn:population":0,
    "gn:timezone":"Africa/Luanda",
    "iso:country":"AO",
    "wof:name":"Mangando do Povo",
    "wof:placetype":"locality"
},
  "geometry": {"coordinates":[17.00195,-8.00365],"type":"Point"}
}