{
  "type": "Feature",
  "properties": {
    "gn:admin1_code":"5.0",
    "gn:asciiname":"Camuanze",
    "gn:country_code":"AO",
    "gn:dem":306,
    "gn:feature_class":"P",
    "gn:feature_code":"PPL",
    "gn:name":"Camuanze",
    "gn:population":0,
    "gn:timezone":"Africa/Luanda",
    "iso:country":"AO",
    "wof:name":"Camuanze",
    "wof:placetype":"locality"
},
  "geometry": {"coordinates":[14.4948,-9.07249],"type":"Point"}
}