{
  "type": "Feature",
  "properties": {
    "gn:admin1_code":"6.0",
    "gn:asciiname":"Lusso",
    "gn:country_code":"AO",
    "gn:dem":1264,
    "gn:feature_class":"P",
    "gn:feature_code":"PPL",
    "gn:name":"Lusso",
    "gn:population":0,
    "gn:timezone":"Africa/Luanda",
    "iso:country":"AO",
    "wof:name":"Lusso",
    "wof:placetype":"locality"
},
  "geometry": {"coordinates":[15.56869,-10.59878],"type":"Point"}
}