{
  "type": "Feature",
  "properties": {
    "gn:admin1_code":"15.0",
    "gn:asciiname":"Coqueilo",
    "gn:country_code":"AO",
    "gn:dem":940,
    "gn:feature_class":"P",
    "gn:feature_code":"PPL",
    "gn:name":"Coqueilo",
    "gn:population":0,
    "gn:timezone":"Africa/Luanda",
    "iso:country":"AO",
    "wof:name":"Coqueilo",
    "wof:placetype":"locality"
},
  "geometry": {"coordinates":[15.06667,-6.28333],"type":"Point"}
}