{
  "type": "Feature",
  "properties": {
    "gn:admin1_code":"6.0",
    "gn:asciiname":"Mande Cungo",
    "gn:country_code":"AO",
    "gn:dem":1306,
    "gn:feature_class":"P",
    "gn:feature_code":"PPL",
    "gn:name":"Mande Cungo",
    "gn:population":0,
    "gn:timezone":"Africa/Luanda",
    "iso:country":"AO",
    "name:und_x_variant":[
        "Mande"
    ],
    "wof:name":"Mande Cungo",
    "wof:placetype":"locality"
},
  "geometry": {"coordinates":[15.10365,-11.44935],"type":"Point"}
}