{
  "type": "Feature",
  "properties": {
    "gn:admin1_code":"14.0",
    "gn:asciiname":"Samuriata",
    "gn:country_code":"AO",
    "gn:dem":1109,
    "gn:feature_class":"P",
    "gn:feature_code":"PPL",
    "gn:name":"Samuriata",
    "gn:population":0,
    "gn:timezone":"Africa/Luanda",
    "iso:country":"AO",
    "wof:name":"Samuriata",
    "wof:placetype":"locality"
},
  "geometry": {"coordinates":[21.65,-14.58333],"type":"Point"}
}