{
  "type": "Feature",
  "properties": {
    "gn:admin1_code":"18.0",
    "gn:asciiname":"Caisuassua",
    "gn:country_code":"AO",
    "gn:dem":1063,
    "gn:feature_class":"P",
    "gn:feature_code":"PPL",
    "gn:name":"Caisu\u00e1ssua",
    "gn:population":0,
    "gn:timezone":"Africa/Luanda",
    "iso:country":"AO",
    "wof:name":"Caisuassua",
    "wof:placetype":"locality"
},
  "geometry": {"coordinates":[20.31396,-9.60979],"type":"Point"}
}