{
  "type": "Feature",
  "properties": {
    "gn:admin1_code":"6.0",
    "gn:asciiname":"Imbando",
    "gn:country_code":"AO",
    "gn:dem":968,
    "gn:feature_class":"P",
    "gn:feature_code":"PPL",
    "gn:name":"Imbando",
    "gn:population":0,
    "gn:timezone":"Africa/Luanda",
    "iso:country":"AO",
    "wof:name":"Imbando",
    "wof:placetype":"locality"
},
  "geometry": {"coordinates":[14.36669,-10.77403],"type":"Point"}
}