{
  "type": "Feature",
  "properties": {
    "gn:admin1_code":"8.0",
    "gn:asciiname":"Manuel",
    "gn:country_code":"AO",
    "gn:dem":1352,
    "gn:feature_class":"P",
    "gn:feature_code":"PPL",
    "gn:name":"Manuel",
    "gn:population":0,
    "gn:timezone":"Africa/Luanda",
    "iso:country":"AO",
    "wof:name":"Manuel",
    "wof:placetype":"locality"
},
  "geometry": {"coordinates":[15.55,-11.73333],"type":"Point"}
}