{
  "type": "Feature",
  "properties": {
    "gn:admin1_code":"4.0",
    "gn:asciiname":"Napangololo",
    "gn:country_code":"AO",
    "gn:dem":1210,
    "gn:feature_class":"P",
    "gn:feature_code":"PPL",
    "gn:name":"Napangololo",
    "gn:population":0,
    "gn:timezone":"Africa/Luanda",
    "iso:country":"AO",
    "wof:name":"Napangololo",
    "wof:placetype":"locality"
},
  "geometry": {"coordinates":[17.71667,-16.06667],"type":"Point"}
}