{
  "type": "Feature",
  "properties": {
    "gn:admin1_code":"12.0",
    "gn:asciiname":"Deolinda",
    "gn:country_code":"AO",
    "gn:dem":959,
    "gn:feature_class":"P",
    "gn:feature_code":"PPL",
    "gn:name":"Deolinda",
    "gn:population":0,
    "gn:timezone":"Africa/Luanda",
    "iso:country":"AO",
    "wof:name":"Deolinda",
    "wof:placetype":"locality"
},
  "geometry": {"coordinates":[16.51464,-8.68566],"type":"Point"}
}