{
  "type": "Feature",
  "properties": {
    "gn:admin1_code":"12.0",
    "gn:asciiname":"Deolinda",
    "gn:country_code":"AO",
    "gn:dem":959,
    "gn:feature_class":"P",
    "gn:feature_code":"PPL",
    "gn:name":"Deolinda",
    "gn:population":0,
    "gn:timezone":"Africa/Luanda",
    "iso:country":"AO",
    "name:cat_x_preferred":[
        "Deolinda"
    ],
    "name:deu_x_preferred":[
        "Deolinda"
    ],
    "name:ext_x_preferred":[
        "Deolinda"
    ],
    "name:fra_x_preferred":[
        "Deolinda"
    ],
    "name:glg_x_preferred":[
        "Deolinda"
    ],
    "name:ita_x_preferred":[
        "Deolinda"
    ],
    "name:kor_x_preferred":[
        "\ub370\uc62c\ub9b0\ub2e4"
    ],
    "name:por_x_preferred":[
        "Deolinda"
    ],
    "name:spa_x_preferred":[
        "Deolinda"
    ],
    "name:swe_x_preferred":[
        "Deolinda"
    ],
    "wof:name":"Deolinda",
    "wof:placetype":"locality"
},
  "geometry": {"coordinates":[16.51464,-8.68566],"type":"Point"}
}