{
  "type": "Feature",
  "properties": {
    "gn:admin1_code":"16.0",
    "gn:asciiname":"Xamindele",
    "gn:cc2":"AO",
    "gn:country_code":"AO",
    "gn:dem":365,
    "gn:feature_class":"P",
    "gn:feature_code":"PPL",
    "gn:name":"Xamindele",
    "gn:population":0,
    "gn:timezone":"Africa/Luanda",
    "iso:country":"AO",
    "name:und_x_variant":[
        "Kaque",
        "Caque",
        "Xamindele"
    ],
    "wof:name":"Xamindele",
    "wof:placetype":"locality"
},
  "geometry": {"coordinates":[13.81667,-6.66667],"type":"Point"}
}