{
  "type": "Feature",
  "properties": {
    "gn:admin1_code":"12.0",
    "gn:asciiname":"Vila Matilde",
    "gn:country_code":"AO",
    "gn:dem":1169,
    "gn:feature_class":"P",
    "gn:feature_code":"PPL",
    "gn:name":"Vila Matilde",
    "gn:population":0,
    "gn:timezone":"Africa/Luanda",
    "iso:country":"AO",
    "wof:name":"Vila Matilde",
    "wof:placetype":"locality"
},
  "geometry": {"coordinates":[16.37389,-9.54194],"type":"Point"}
}