{
  "type": "Feature",
  "properties": {
    "gn:admin1_code":"15.0",
    "gn:asciiname":"Quimuquengi",
    "gn:country_code":"AO",
    "gn:dem":1072,
    "gn:feature_class":"P",
    "gn:feature_code":"PPL",
    "gn:name":"Quimuquengi",
    "gn:population":0,
    "gn:timezone":"Africa/Luanda",
    "iso:country":"AO",
    "wof:name":"Quimuquengi",
    "wof:placetype":"locality"
},
  "geometry": {"coordinates":[15.83571,-7.52679],"type":"Point"}
}