{
  "type": "Feature",
  "properties": {
    "gn:admin1_code":"6.0",
    "gn:asciiname":"Santa Filomena",
    "gn:cc2":"AO",
    "gn:country_code":"AO",
    "gn:dem":51,
    "gn:feature_class":"P",
    "gn:feature_code":"PPL",
    "gn:name":"Santa Filomena",
    "gn:population":0,
    "gn:timezone":"Africa/Luanda",
    "iso:country":"AO",
    "name:und_x_variant":[
        "Fazenda Santa Filomena",
        "Quissanga Grande",
        "Fazenda Filomena",
        "Kisingo Grande",
        "Santa Filomena"
    ],
    "wof:name":"Santa Filomena",
    "wof:placetype":"locality"
},
  "geometry": {"coordinates":[13.78333,-11.65],"type":"Point"}
}