{
  "type": "Feature",
  "properties": {
    "gn:admin1_code":"9.0",
    "gn:asciiname":"Saiombo",
    "gn:country_code":"AO",
    "gn:dem":2052,
    "gn:feature_class":"P",
    "gn:feature_code":"PPL",
    "gn:name":"Saiombo",
    "gn:population":0,
    "gn:timezone":"Africa/Luanda",
    "iso:country":"AO",
    "name:und_x_variant":[
        "Tchaiombo"
    ],
    "wof:name":"Saiombo",
    "wof:placetype":"locality"
},
  "geometry": {"coordinates":[13.40358,-14.9591],"type":"Point"}
}