{
  "type": "Feature",
  "properties": {
    "gn:admin1_code":"8.0",
    "gn:asciiname":"Quipeio",
    "gn:country_code":"AO",
    "gn:dem":1571,
    "gn:feature_class":"P",
    "gn:feature_code":"PPL",
    "gn:name":"Quipeio",
    "gn:population":0,
    "gn:timezone":"Africa/Luanda",
    "iso:country":"AO",
    "wof:name":"Quipeio",
    "wof:placetype":"locality"
},
  "geometry": {"coordinates":[15.51667,-12.43333],"type":"Point"}
}