{
  "type": "Feature",
  "properties": {
    "gn:admin1_code":"14.0",
    "gn:asciiname":"Cambaba",
    "gn:cc2":"AO",
    "gn:country_code":"AO",
    "gn:dem":1299,
    "gn:feature_class":"P",
    "gn:feature_code":"PPL",
    "gn:name":"Cambaba",
    "gn:population":0,
    "gn:timezone":"Africa/Luanda",
    "iso:country":"AO",
    "name:und_x_variant":[
        "Capombo",
        "Cambaba"
    ],
    "wof:name":"Cambaba",
    "wof:placetype":"locality"
},
  "geometry": {"coordinates":[20.61667000000001,-13.23333],"type":"Point"}
}