{
  "type": "Feature",
  "properties": {
    "gn:admin1_code":"8.0",
    "gn:asciiname":"Capali",
    "gn:country_code":"AO",
    "gn:dem":1335,
    "gn:feature_class":"P",
    "gn:feature_code":"PPL",
    "gn:name":"Capali",
    "gn:population":0,
    "gn:timezone":"Africa/Luanda",
    "iso:country":"AO",
    "wof:name":"Capali",
    "wof:placetype":"locality"
},
  "geometry": {"coordinates":[15.53333,-11.68333],"type":"Point"}
}