{
  "type": "Feature",
  "properties": {
    "gn:admin1_code":"8.0",
    "gn:asciiname":"Sucumula",
    "gn:country_code":"AO",
    "gn:dem":1712,
    "gn:feature_class":"P",
    "gn:feature_code":"PPL",
    "gn:name":"Sucumula",
    "gn:population":0,
    "gn:timezone":"Africa/Luanda",
    "iso:country":"AO",
    "wof:name":"Sucumula",
    "wof:placetype":"locality"
},
  "geometry": {"coordinates":[15.46278,-13.05306],"type":"Point"}
}