{
  "type": "Feature",
  "properties": {
    "gn:admin1_code":"6.0",
    "gn:asciiname":"Ndemba",
    "gn:country_code":"AO",
    "gn:dem":1409,
    "gn:feature_class":"P",
    "gn:feature_code":"PPL",
    "gn:name":"Ndemba",
    "gn:population":0,
    "gn:timezone":"Africa/Luanda",
    "iso:country":"AO",
    "wof:name":"Ndemba",
    "wof:placetype":"locality"
},
  "geometry": {"coordinates":[14.91237,-10.5278],"type":"Point"}
}