{
  "type": "Feature",
  "properties": {
    "gn:admin1_code":"6.0",
    "gn:asciiname":"Cassueca",
    "gn:country_code":"AO",
    "gn:dem":1225,
    "gn:feature_class":"P",
    "gn:feature_code":"PPL",
    "gn:name":"Cassueca",
    "gn:population":0,
    "gn:timezone":"Africa/Luanda",
    "iso:country":"AO",
    "wof:name":"Cassueca",
    "wof:placetype":"locality"
},
  "geometry": {"coordinates":[15.09309,-10.03457],"type":"Point"}
}