{
  "type": "Feature",
  "properties": {
    "gn:admin1_code":"15.0",
    "gn:asciiname":"Quibonda",
    "gn:country_code":"AO",
    "gn:dem":762,
    "gn:feature_class":"P",
    "gn:feature_code":"PPL",
    "gn:name":"Quibonda",
    "gn:population":0,
    "gn:timezone":"Africa/Luanda",
    "iso:country":"AO",
    "wof:name":"Quibonda",
    "wof:placetype":"locality"
},
  "geometry": {"coordinates":[14.88333,-6.78333],"type":"Point"}
}