{
  "type": "Feature",
  "properties": {
    "gn:admin1_code":"17.0",
    "gn:asciiname":"Imbi",
    "gn:country_code":"AO",
    "gn:dem":736,
    "gn:feature_class":"P",
    "gn:feature_code":"PPL",
    "gn:name":"Imbi",
    "gn:population":0,
    "gn:timezone":"Africa/Luanda",
    "iso:country":"AO",
    "name:und_x_variant":[
        "Imbe"
    ],
    "wof:name":"Imbi",
    "wof:placetype":"locality"
},
  "geometry": {"coordinates":[17.65202,-8.93779],"type":"Point"}
}