{
  "type": "Feature",
  "properties": {
    "gn:admin1_code":"15.0",
    "gn:asciiname":"Cassule",
    "gn:country_code":"AO",
    "gn:dem":1201,
    "gn:feature_class":"P",
    "gn:feature_code":"PPL",
    "gn:name":"Cassule",
    "gn:population":0,
    "gn:timezone":"Africa/Luanda",
    "iso:country":"AO",
    "wof:name":"Cassule",
    "wof:placetype":"locality"
},
  "geometry": {"coordinates":[15.29794,-7.43724],"type":"Point"}
}