{
  "type": "Feature",
  "properties": {
    "gn:admin1_code":"6.0",
    "gn:admin2_code":"3347070.0",
    "gn:asciiname":"Calulo",
    "gn:country_code":"AO",
    "gn:dem":1082,
    "gn:feature_class":"P",
    "gn:feature_code":"PPLL",
    "gn:name":"Calulo",
    "gn:population":0,
    "gn:timezone":"Africa/Luanda",
    "iso:country":"AO",
    "name:ara_x_preferred":[
        "\u0643\u0627\u0644\u0648\u0644\u0648"
    ],
    "name:ben_x_preferred":[
        "\u0995\u09be\u09b2\u09c1\u09b2\u09cb"
    ],
    "name:deu_x_preferred":[
        "Calulo"
    ],
    "name:ell_x_preferred":[
        "\u039a\u03b1\u03bb\u03bf\u03cd\u03bb\u03bf"
    ],
    "name:fas_x_preferred":[
        "\u06a9\u0627\u0644\u0648\u0644\u0648"
    ],
    "name:heb_x_preferred":[
        "\u05e7\u05dc\u05d5\u05dc\u05d5"
    ],
    "name:hin_x_preferred":[
        "\u0915\u093e\u0932\u0942\u0932\u094b"
    ],
    "name:hun_x_preferred":[
        "Calulo"
    ],
    "name:ind_x_preferred":[
        "Calulo"
    ],
    "name:ita_x_preferred":[
        "Calulo"
    ],
    "name:jpn_x_preferred":[
        "\u30ab\u30eb\u30ed"
    ],
    "name:kor_x_preferred":[
        "\uce7c\ub8f0\ub85c"
    ],
    "name:nld_x_preferred":[
        "Calulo"
    ],
    "name:rus_x_preferred":[
        "\u041a\u0430\u043b\u0443\u043b\u043e"
    ],
    "name:spa_x_preferred":[
        "Calulo"
    ],
    "name:swe_x_preferred":[
        "Calulo"
    ],
    "name:tur_x_preferred":[
        "Calulo"
    ],
    "name:ukr_x_preferred":[
        "\u041a\u0430\u043b\u0443\u043b\u043e"
    ],
    "name:und_x_variant":[
        "Cabulo"
    ],
    "name:urd_x_preferred":[
        "\u06a9\u0627\u0644\u0648\u0644\u0648"
    ],
    "name:vie_x_preferred":[
        "Calulo"
    ],
    "name:zho_cn_x_preferred":[
        "\u5361\u5362\u6d1b"
    ],
    "name:zho_tw_x_preferred":[
        "\u5361\u76e7\u6d1b"
    ],
    "wof:name":"Calulo",
    "wof:placetype":"locality"
},
  "geometry": {"coordinates":[16.36564,-10.29968],"type":"Point"}
}