{
  "type": "Feature",
  "properties": {
    "gn:admin1_code":"6.0",
    "gn:admin2_code":"3347070.0",
    "gn:asciiname":"Calulo",
    "gn:country_code":"AO",
    "gn:dem":1082,
    "gn:feature_class":"P",
    "gn:feature_code":"PPLL",
    "gn:name":"Calulo",
    "gn:population":0,
    "gn:timezone":"Africa/Luanda",
    "iso:country":"AO",
    "name:deu_x_preferred":[
        "Calulo"
    ],
    "name:ita_x_preferred":[
        "Calulo"
    ],
    "name:rus_x_preferred":[
        "\u041a\u0430\u043b\u0443\u043b\u043e"
    ],
    "name:und_x_variant":[
        "Cabulo",
        "Calulo"
    ],
    "wof:name":"Calulo",
    "wof:placetype":"locality"
},
  "geometry": {"coordinates":[16.36564,-10.29968],"type":"Point"}
}