{
  "type": "Feature",
  "properties": {
    "gn:admin1_code":"5.0",
    "gn:asciiname":"Quicunhe",
    "gn:country_code":"AO",
    "gn:dem":1217,
    "gn:feature_class":"P",
    "gn:feature_code":"PPL",
    "gn:name":"Quicunhe",
    "gn:population":0,
    "gn:timezone":"Africa/Luanda",
    "iso:country":"AO",
    "wof:name":"Quicunhe",
    "wof:placetype":"locality"
},
  "geometry": {"coordinates":[15.43333,-8.61667],"type":"Point"}
}