{
  "type": "Feature",
  "properties": {
    "gn:admin1_code":"2.0",
    "gn:asciiname":"Lopi",
    "gn:country_code":"AO",
    "gn:dem":1758,
    "gn:feature_class":"P",
    "gn:feature_code":"PPL",
    "gn:name":"Lopi",
    "gn:population":0,
    "gn:timezone":"Africa/Luanda",
    "iso:country":"AO",
    "wof:name":"Lopi",
    "wof:placetype":"locality"
},
  "geometry": {"coordinates":[16.99061,-11.61388],"type":"Point"}
}