{
  "type": "Feature",
  "properties": {
    "gn:admin1_code":"12.0",
    "gn:asciiname":"Quiluigi",
    "gn:country_code":"AO",
    "gn:dem":1100,
    "gn:feature_class":"P",
    "gn:feature_code":"PPL",
    "gn:name":"Quiluigi",
    "gn:population":0,
    "gn:timezone":"Africa/Luanda",
    "iso:country":"AO",
    "wof:name":"Quiluigi",
    "wof:placetype":"locality"
},
  "geometry": {"coordinates":[16.36952999999999,-9.23276],"type":"Point"}
}