{
  "type": "Feature",
  "properties": {
    "gn:admin1_code":"6.0",
    "gn:asciiname":"Amboiva",
    "gn:country_code":"AO",
    "gn:dem":1262,
    "gn:feature_class":"P",
    "gn:feature_code":"PPL",
    "gn:name":"Ambo\u00edva",
    "gn:population":0,
    "gn:timezone":"Africa/Luanda",
    "iso:country":"AO",
    "name:und_x_variant":[
        "Ambovia",
        "Ambo\u00edva"
    ],
    "wof:name":"Amboiva",
    "wof:placetype":"locality"
},
  "geometry": {"coordinates":[14.72726,-11.54071],"type":"Point"}
}