{
  "type": "Feature",
  "properties": {
    "gn:admin1_code":"13.0",
    "gn:asciiname":"Chipia",
    "gn:country_code":"AO",
    "gn:dem":468,
    "gn:feature_class":"P",
    "gn:feature_code":"PPL",
    "gn:name":"Ch\u00edpia",
    "gn:population":0,
    "gn:timezone":"Africa/Luanda",
    "iso:country":"AO",
    "wof:name":"Chipia",
    "wof:placetype":"locality"
},
  "geometry": {"coordinates":[12.78964,-14.88375],"type":"Point"}
}