{
  "type": "Feature",
  "properties": {
    "gn:admin1_code":"2.0",
    "gn:asciiname":"Dele",
    "gn:country_code":"AO",
    "gn:dem":1351,
    "gn:feature_class":"P",
    "gn:feature_code":"PPL",
    "gn:name":"Dele",
    "gn:population":0,
    "gn:timezone":"Africa/Luanda",
    "iso:country":"AO",
    "wof:name":"Dele",
    "wof:placetype":"locality"
},
  "geometry": {"coordinates":[17.38332999999999,-12.45],"type":"Point"}
}