{
  "type": "Feature",
  "properties": {
    "gn:admin1_code":"12.0",
    "gn:asciiname":"Mbondo",
    "gn:country_code":"AO",
    "gn:dem":1081,
    "gn:feature_class":"P",
    "gn:feature_code":"PPL",
    "gn:name":"Mbondo",
    "gn:population":0,
    "gn:timezone":"Africa/Luanda",
    "iso:country":"AO",
    "wof:name":"Mbondo",
    "wof:placetype":"locality"
},
  "geometry": {"coordinates":[16.15046,-7.99806],"type":"Point"}
}