{
  "type": "Feature",
  "properties": {
    "gn:admin1_code":"15.0",
    "gn:asciiname":"Quicola",
    "gn:country_code":"AO",
    "gn:dem":927,
    "gn:feature_class":"P",
    "gn:feature_code":"PPL",
    "gn:name":"Quicola",
    "gn:population":0,
    "gn:timezone":"Africa/Luanda",
    "iso:country":"AO",
    "wof:name":"Quicola",
    "wof:placetype":"locality"
},
  "geometry": {"coordinates":[15.03333,-6.05],"type":"Point"}
}