{
  "type": "Feature",
  "properties": {
    "gn:admin1_code":"15.0",
    "gn:asciiname":"Milango",
    "gn:country_code":"AO",
    "gn:dem":1172,
    "gn:feature_class":"P",
    "gn:feature_code":"PPL",
    "gn:name":"Milango",
    "gn:population":0,
    "gn:timezone":"Africa/Luanda",
    "iso:country":"AO",
    "wof:name":"Milango",
    "wof:placetype":"locality"
},
  "geometry": {"coordinates":[15.18656,-7.05566],"type":"Point"}
}