{
  "type": "Feature",
  "properties": {
    "gn:admin1_code":"17.0",
    "gn:asciiname":"Caungula",
    "gn:country_code":"AO",
    "gn:dem":1074,
    "gn:feature_class":"P",
    "gn:feature_code":"PPL",
    "gn:name":"Caungula",
    "gn:population":0,
    "gn:timezone":"Africa/Luanda",
    "iso:country":"AO",
    "name:und_x_variant":[
        "Camaxilo",
        "Cuangula",
        "Calungula",
        "Kuangula",
        "Cahungula",
        "Caungula"
    ],
    "wof:name":"Caungula",
    "wof:placetype":"locality"
},
  "geometry": {"coordinates":[18.63557,-8.4223],"type":"Point"}
}