{
  "type": "Feature",
  "properties": {
    "gn:admin1_code":"17.0",
    "gn:asciiname":"Caungula",
    "gn:country_code":"AO",
    "gn:dem":1074,
    "gn:feature_class":"P",
    "gn:feature_code":"PPL",
    "gn:name":"Caungula",
    "gn:population":0,
    "gn:timezone":"Africa/Luanda",
    "iso:country":"AO",
    "name:azb_x_preferred":[
        "\u06a9\u0648\u0646\u0642\u0648\u0644\u0627"
    ],
    "name:cat_x_preferred":[
        "Caungula"
    ],
    "name:deu_x_preferred":[
        "Caungula"
    ],
    "name:fas_x_preferred":[
        "\u06a9\u0648\u0646\u06af\u0648\u0644\u0627"
    ],
    "name:ita_x_preferred":[
        "Caungula"
    ],
    "name:por_x_preferred":[
        "Caungula"
    ],
    "name:spa_x_preferred":[
        "Caungula"
    ],
    "name:und_x_variant":[
        "Camaxilo",
        "Cuangula",
        "Calungula",
        "Kuangula",
        "Cahungula"
    ],
    "name:zho_x_preferred":[
        "\u5361\u6eab\u53e4\u62c9"
    ],
    "wof:name":"Caungula",
    "wof:placetype":"locality"
},
  "geometry": {"coordinates":[18.63557,-8.4223],"type":"Point"}
}