{
  "type": "Feature",
  "properties": {
    "gn:admin1_code":"15.0",
    "gn:asciiname":"Quimuzembo",
    "gn:country_code":"AO",
    "gn:dem":1250,
    "gn:feature_class":"P",
    "gn:feature_code":"PPL",
    "gn:name":"Quimuzembo",
    "gn:population":0,
    "gn:timezone":"Africa/Luanda",
    "iso:country":"AO",
    "name:und_x_variant":[
        "Quiosso",
        "Quimuzendo",
        "Quimuzembo"
    ],
    "wof:name":"Quimuzembo",
    "wof:placetype":"locality"
},
  "geometry": {"coordinates":[15.13714,-7.38345],"type":"Point"}
}