{
  "type": "Feature",
  "properties": {
    "gn:admin1_code":"12.0",
    "gn:asciiname":"Quimbengui",
    "gn:country_code":"AO",
    "gn:dem":591,
    "gn:feature_class":"P",
    "gn:feature_code":"PPL",
    "gn:name":"Quimb\u00eangui",
    "gn:population":0,
    "gn:timezone":"Africa/Luanda",
    "iso:country":"AO",
    "wof:name":"Quimbengui",
    "wof:placetype":"locality"
},
  "geometry": {"coordinates":[16.73088,-7.69694],"type":"Point"}
}