{
  "type": "Feature",
  "properties": {
    "gn:admin1_code":"19.0",
    "gn:asciiname":"Fazenda Marimba",
    "gn:country_code":"AO",
    "gn:dem":589,
    "gn:feature_class":"P",
    "gn:feature_code":"PPL",
    "gn:name":"Fazenda Marimba",
    "gn:population":0,
    "gn:timezone":"Africa/Luanda",
    "iso:country":"AO",
    "wof:name":"Fazenda Marimba",
    "wof:placetype":"locality"
},
  "geometry": {"coordinates":[14.45,-8.65],"type":"Point"}
}