{
  "type": "Feature",
  "properties": {
    "gn:admin1_code":"12.0",
    "gn:asciiname":"Amaral",
    "gn:country_code":"AO",
    "gn:dem":1059,
    "gn:feature_class":"P",
    "gn:feature_code":"PPL",
    "gn:name":"Amaral",
    "gn:population":0,
    "gn:timezone":"Africa/Luanda",
    "iso:country":"AO",
    "wof:name":"Amaral",
    "wof:placetype":"locality"
},
  "geometry": {"coordinates":[15.93903,-9.26785],"type":"Point"}
}