{
  "type": "Feature",
  "properties": {
    "gn:admin1_code":"12.0",
    "gn:asciiname":"Mulumbila",
    "gn:country_code":"AO",
    "gn:dem":1113,
    "gn:feature_class":"P",
    "gn:feature_code":"PPL",
    "gn:name":"Mulumbila",
    "gn:population":0,
    "gn:timezone":"Africa/Luanda",
    "iso:country":"AO",
    "wof:name":"Mulumbila",
    "wof:placetype":"locality"
},
  "geometry": {"coordinates":[16.80017999999999,-10.18125],"type":"Point"}
}