{
  "type": "Feature",
  "properties": {
    "gn:admin1_code":"1.0",
    "gn:asciiname":"Taramanjamba",
    "gn:country_code":"AO",
    "gn:dem":594,
    "gn:feature_class":"P",
    "gn:feature_code":"PPL",
    "gn:name":"Taramanjamba",
    "gn:population":0,
    "gn:timezone":"Africa/Luanda",
    "iso:country":"AO",
    "wof:name":"Taramanjamba",
    "wof:placetype":"locality"
},
  "geometry": {"coordinates":[13.26667,-13.18333],"type":"Point"}
}