{
  "type": "Feature",
  "properties": {
    "gn:admin1_code":"17.0",
    "gn:asciiname":"Cafunfo",
    "gn:country_code":"AO",
    "gn:dem":853,
    "gn:feature_class":"P",
    "gn:feature_code":"PPL",
    "gn:name":"Cafunfo",
    "gn:population":0,
    "gn:timezone":"Africa/Luanda",
    "iso:country":"AO",
    "name:cat_x_preferred":[
        "Cafunfo"
    ],
    "name:fas_x_preferred":[
        "\u06a9\u0627\u0641\u0648\u0646\u0641\u0648"
    ],
    "wof:name":"Cafunfo",
    "wof:placetype":"locality"
},
  "geometry": {"coordinates":[17.99572000000001,-8.7672],"type":"Point"}
}