{
  "type": "Feature",
  "properties": {
    "gn:admin1_code":"8.0",
    "gn:asciiname":"Cumbao",
    "gn:cc2":"AO",
    "gn:country_code":"AO",
    "gn:dem":1735,
    "gn:feature_class":"P",
    "gn:feature_code":"PPL",
    "gn:name":"Cumb\u00e3o",
    "gn:population":0,
    "gn:timezone":"Africa/Luanda",
    "iso:country":"AO",
    "name:und_x_variant":[
        "Comp\u00e3o",
        "Cumb\u00e3o"
    ],
    "wof:name":"Cumbao",
    "wof:placetype":"locality"
},
  "geometry": {"coordinates":[15.81667,-12.98333],"type":"Point"}
}