{
  "type": "Feature",
  "properties": {
    "gn:admin1_code":"15.0",
    "gn:asciiname":"Quitomassala",
    "gn:country_code":"AO",
    "gn:dem":890,
    "gn:feature_class":"P",
    "gn:feature_code":"PPL",
    "gn:name":"Quitomassala",
    "gn:population":0,
    "gn:timezone":"Africa/Luanda",
    "iso:country":"AO",
    "wof:name":"Quitomassala",
    "wof:placetype":"locality"
},
  "geometry": {"coordinates":[15.64232,-6.54448],"type":"Point"}
}