{
  "type": "Feature",
  "properties": {
    "gn:admin1_code":"2.0",
    "gn:asciiname":"Salohoca",
    "gn:country_code":"AO",
    "gn:dem":1782,
    "gn:feature_class":"P",
    "gn:feature_code":"PPL",
    "gn:name":"Salohoca",
    "gn:population":0,
    "gn:timezone":"Africa/Luanda",
    "iso:country":"AO",
    "wof:name":"Salohoca",
    "wof:placetype":"locality"
},
  "geometry": {"coordinates":[16.41837,-12.46355],"type":"Point"}
}