{
  "type": "Feature",
  "properties": {
    "gn:admin1_code":"12.0",
    "gn:asciiname":"Gingi Quinguangua",
    "gn:country_code":"AO",
    "gn:dem":1213,
    "gn:feature_class":"P",
    "gn:feature_code":"PPL",
    "gn:name":"Gingi Quinguangua",
    "gn:population":0,
    "gn:timezone":"Africa/Luanda",
    "iso:country":"AO",
    "wof:name":"Gingi Quinguangua",
    "wof:placetype":"locality"
},
  "geometry": {"coordinates":[17.07235,-9.27522],"type":"Point"}
}