{
  "type": "Feature",
  "properties": {
    "gn:admin1_code":"5.0",
    "gn:asciiname":"Bango Tumba",
    "gn:country_code":"AO",
    "gn:dem":910,
    "gn:feature_class":"P",
    "gn:feature_code":"PPL",
    "gn:name":"Bango Tumba",
    "gn:population":0,
    "gn:timezone":"Africa/Luanda",
    "iso:country":"AO",
    "wof:name":"Bango Tumba",
    "wof:placetype":"locality"
},
  "geometry": {"coordinates":[14.75158,-8.92938],"type":"Point"}
}