{
  "type": "Feature",
  "properties": {
    "gn:admin1_code":"6.0",
    "gn:asciiname":"Cassangi de Cada",
    "gn:country_code":"AO",
    "gn:dem":1265,
    "gn:feature_class":"P",
    "gn:feature_code":"PPL",
    "gn:name":"Cassangi de Cad\u00e1",
    "gn:population":0,
    "gn:timezone":"Africa/Luanda",
    "iso:country":"AO",
    "wof:name":"Cassangi de Cada",
    "wof:placetype":"locality"
},
  "geometry": {"coordinates":[14.81582,-10.84895],"type":"Point"}
}