{
  "type": "Feature",
  "properties": {
    "gn:admin1_code":"17.0",
    "gn:asciiname":"Tchitopo",
    "gn:country_code":"AO",
    "gn:dem":791,
    "gn:feature_class":"P",
    "gn:feature_code":"PPL",
    "gn:name":"Tchitopo",
    "gn:population":0,
    "gn:timezone":"Africa/Luanda",
    "iso:country":"AO",
    "name:und_x_variant":[
        "Xitopo",
        "Chitopo",
        "Tchitopo"
    ],
    "wof:name":"Tchitopo",
    "wof:placetype":"locality"
},
  "geometry": {"coordinates":[20.18282,-7.34636],"type":"Point"}
}