{
  "type": "Feature",
  "properties": {
    "gn:admin1_code":"15.0",
    "gn:asciiname":"Imambambe",
    "gn:country_code":"AO",
    "gn:dem":768,
    "gn:feature_class":"P",
    "gn:feature_code":"PPL",
    "gn:name":"Imambambe",
    "gn:population":0,
    "gn:timezone":"Africa/Luanda",
    "iso:country":"AO",
    "wof:name":"Imambambe",
    "wof:placetype":"locality"
},
  "geometry": {"coordinates":[14.71667,-7.91667],"type":"Point"}
}