{
  "type": "Feature",
  "properties": {
    "gn:admin1_code":"18.0",
    "gn:asciiname":"Safutchi",
    "gn:country_code":"AO",
    "gn:dem":1202,
    "gn:feature_class":"P",
    "gn:feature_code":"PPL",
    "gn:name":"Safutchi",
    "gn:population":0,
    "gn:timezone":"Africa/Luanda",
    "iso:country":"AO",
    "name:und_x_variant":[
        "Safuchi",
        "Safuche",
        "Safutchi"
    ],
    "wof:name":"Safutchi",
    "wof:placetype":"locality"
},
  "geometry": {"coordinates":[19.03825,-10.24891],"type":"Point"}
}