{
  "type": "Feature",
  "properties": {
    "iso:country":"AO",
    "name:azb_x_preferred":[
        "\u0645\u0648\u06a9\u0646\u062f\u0627"
    ],
    "name:cat_x_preferred":[
        "Muconda"
    ],
    "name:deu_x_preferred":[
        "Muconda"
    ],
    "name:eng_x_preferred":[
        "Muconda"
    ],
    "name:fas_x_preferred":[
        "\u0645\u0648\u06a9\u0646\u062f\u0627\u060c \u0622\u0646\u06af\u0648\u0644\u0627"
    ],
    "name:fas_x_variant":[
        "\u0645\u0648\u06a9\u0646\u062f\u0627"
    ],
    "name:fra_x_preferred":[
        "Muconda"
    ],
    "name:ita_x_preferred":[
        "Muconda"
    ],
    "name:msa_x_preferred":[
        "Mukonda"
    ],
    "name:nld_x_preferred":[
        "Muconda"
    ],
    "name:por_x_preferred":[
        "Muconda"
    ],
    "name:spa_x_preferred":[
        "Muconda"
    ],
    "name:zho_x_preferred":[
        "\u7a46\u5b54\u9054"
    ],
    "ne:ADM0CAP":0.0,
    "ne:ADM0NAME":"Angola",
    "ne:ADM0_A3":"AGO",
    "ne:ADM1NAME":"Lunda Sul",
    "ne:ADMIN1_COD":0,
    "ne:CAPALT":0,
    "ne:CHANGED":0,
    "ne:CHECKME":0,
    "ne:COMPARE":0,
    "ne:DIFFASCII":0,
    "ne:ELEVATION":0.0,
    "ne:FEATURECLA":"Populated place",
    "ne:GEONAMEID":-1,
    "ne:GEONAMESNO":"No GeoNames match due to small population, not in GeoNames, or poor NEV placement.",
    "ne:GN_POP":0,
    "ne:GTOPO30":0.0,
    "ne:ISO_A2":"AO",
    "ne:LABELRANK":6,
    "ne:LATITUDE":-10.599626,
    "ne:LONGITUDE":21.31998,
    "ne:LS_MATCH":1,
    "ne:LS_NAME":"Muconda",
    "ne:MAX_AREAKM":3.0,
    "ne:MAX_AREAMI":1.0,
    "ne:MAX_BBXMAX":21.325,
    "ne:MAX_BBXMIN":21.308333,
    "ne:MAX_BBYMAX":-10.583333,
    "ne:MAX_BBYMIN":-10.6,
    "ne:MAX_NATSCA":20.0,
    "ne:MAX_PERKM":7.0,
    "ne:MAX_PERMI":5.0,
    "ne:MAX_POP10":2324,
    "ne:MAX_POP20":2324,
    "ne:MAX_POP300":0,
    "ne:MAX_POP310":0,
    "ne:MAX_POP50":0,
    "ne:MEAN_BBXC":21.316667,
    "ne:MEAN_BBYC":-10.591667,
    "ne:MEGACITY":0,
    "ne:MIN_AREAKM":3.0,
    "ne:MIN_AREAMI":1.0,
    "ne:MIN_BBXMAX":21.325,
    "ne:MIN_BBXMIN":21.308333,
    "ne:MIN_BBYMAX":-10.583333,
    "ne:MIN_BBYMIN":-10.6,
    "ne:MIN_PERKM":7.0,
    "ne:MIN_PERMI":5.0,
    "ne:NAME":"Muconda",
    "ne:NAMEASCII":"Muconda",
    "ne:NAMEDIFF":0,
    "ne:NATSCALE":20,
    "ne:POP1950":0,
    "ne:POP1955":0,
    "ne:POP1960":0,
    "ne:POP1965":0,
    "ne:POP1970":0,
    "ne:POP1975":0,
    "ne:POP1980":0,
    "ne:POP1985":0,
    "ne:POP1990":0,
    "ne:POP1995":0,
    "ne:POP2000":0,
    "ne:POP2005":0,
    "ne:POP2010":0,
    "ne:POP2015":0,
    "ne:POP2020":0,
    "ne:POP2025":0,
    "ne:POP2050":0,
    "ne:POP_MAX":2324,
    "ne:POP_MIN":2324,
    "ne:POP_OTHER":0,
    "ne:RANK_MAX":4,
    "ne:RANK_MIN":4,
    "ne:SCALERANK":7,
    "ne:SOV0NAME":"Angola",
    "ne:SOV_A3":"AGO",
    "ne:UN_FID":0,
    "ne:UN_LAT":0.0,
    "ne:UN_LONG":0.0,
    "ne:WORLDCITY":0,
    "ne:min_zoom":6.7,
    "wof:name":"Muconda",
    "wof:placetype":"locality"
},
  "geometry": {"coordinates":[21.31998001982959,-10.59962563186195],"type":"Point"}
}