{
  "type": "Feature",
  "properties": {
    "gn:admin1_code":"13.0",
    "gn:asciiname":"Tombua",
    "gn:country_code":"AO",
    "gn:dem":11,
    "gn:feature_class":"P",
    "gn:feature_code":"PPL",
    "gn:name":"T\u00f4mbua",
    "gn:population":0,
    "gn:timezone":"Africa/Luanda",
    "iso:country":"AO",
    "name:rus_x_preferred":[
        "\u0422\u043e\u043c\u0431\u0443\u0430"
    ],
    "name:und_x_variant":[
        "Porto Alexandre",
        "Port Alexander",
        "T\u00f4mbua"
    ],
    "wof:name":"Tombua",
    "wof:placetype":"locality"
},
  "geometry": {"coordinates":[11.84485,-15.80394],"type":"Point"}
}