{
  "type": "Feature",
  "properties": {
    "gn:admin1_code":"13.0",
    "gn:asciiname":"Tombua",
    "gn:country_code":"AO",
    "gn:dem":11,
    "gn:feature_class":"P",
    "gn:feature_code":"PPL",
    "gn:name":"T\u00f4mbua",
    "gn:population":0,
    "gn:timezone":"Africa/Luanda",
    "iso:country":"AO",
    "name:azb_x_preferred":[
        "\u062a\u0645\u0628\u0648\u0627"
    ],
    "name:cat_x_preferred":[
        "T\u00f4mbwa"
    ],
    "name:ceb_x_preferred":[
        "T\u00f4mbua"
    ],
    "name:deu_x_preferred":[
        "T\u00f4mbua"
    ],
    "name:fas_x_preferred":[
        "\u062a\u0645\u0628\u0648\u0627"
    ],
    "name:fra_x_preferred":[
        "Tomboa"
    ],
    "name:ita_x_preferred":[
        "Tomboa"
    ],
    "name:msa_x_preferred":[
        "T\u00f4mbua"
    ],
    "name:nld_x_preferred":[
        "T\u00f4mbwa"
    ],
    "name:nor_x_preferred":[
        "Tomboa"
    ],
    "name:pol_x_preferred":[
        "T\u00f4mbua"
    ],
    "name:por_x_preferred":[
        "T\u00f4mbua"
    ],
    "name:ron_x_preferred":[
        "Tombua"
    ],
    "name:rus_x_preferred":[
        "\u0422\u043e\u043c\u0431\u0443\u0430"
    ],
    "name:spa_x_preferred":[
        "Tombua"
    ],
    "name:swe_x_preferred":[
        "T\u00f4mbua"
    ],
    "name:tgl_x_preferred":[
        "T\u00f4mbwa"
    ],
    "name:und_x_variant":[
        "Porto Alexandre",
        "Port Alexander"
    ],
    "name:zho_x_preferred":[
        "\u901a\u5e03\u963f"
    ],
    "wof:name":"Tombua",
    "wof:placetype":"locality"
},
  "geometry": {"coordinates":[11.84485,-15.80394],"type":"Point"}
}