{
  "type": "Feature",
  "properties": {
    "gn:admin1_code":"12.0",
    "gn:asciiname":"Missoxe",
    "gn:country_code":"AO",
    "gn:dem":946,
    "gn:feature_class":"P",
    "gn:feature_code":"PPL",
    "gn:name":"Missoxe",
    "gn:population":0,
    "gn:timezone":"Africa/Luanda",
    "iso:country":"AO",
    "wof:name":"Missoxe",
    "wof:placetype":"locality"
},
  "geometry": {"coordinates":[15.63333,-9.23333],"type":"Point"}
}