{
  "type": "Feature",
  "properties": {
    "gn:admin1_code":"6.0",
    "gn:asciiname":"Caxilo de Mussende",
    "gn:country_code":"AO",
    "gn:dem":932,
    "gn:feature_class":"P",
    "gn:feature_code":"PPL",
    "gn:name":"Caxilo de Mussende",
    "gn:population":0,
    "gn:timezone":"Africa/Luanda",
    "iso:country":"AO",
    "wof:name":"Caxilo de Mussende",
    "wof:placetype":"locality"
},
  "geometry": {"coordinates":[14.79758,-9.93212],"type":"Point"}
}