{
  "type": "Feature",
  "properties": {
    "gn:admin1_code":"20.0",
    "gn:asciiname":"Luanda-Sul",
    "gn:country_code":"AO",
    "gn:dem":53,
    "gn:feature_class":"P",
    "gn:feature_code":"PPL",
    "gn:name":"Luanda-Sul",
    "gn:population":0,
    "gn:timezone":"Africa/Luanda",
    "iso:country":"AO",
    "wof:name":"Luanda-Sul",
    "wof:placetype":"locality"
},
  "geometry": {"coordinates":[13.18093,-8.90127],"type":"Point"}
}