{
  "type": "Feature",
  "properties": {
    "gn:admin1_code":"6.0",
    "gn:asciiname":"Ipumba",
    "gn:country_code":"AO",
    "gn:dem":195,
    "gn:feature_class":"P",
    "gn:feature_code":"PPL",
    "gn:name":"Ipumba",
    "gn:population":0,
    "gn:timezone":"Africa/Luanda",
    "iso:country":"AO",
    "wof:name":"Ipumba",
    "wof:placetype":"locality"
},
  "geometry": {"coordinates":[14.20167,-10.75453],"type":"Point"}
}