{
  "type": "Feature",
  "properties": {
    "gn:admin1_code":"2.0",
    "gn:asciiname":"Donde",
    "gn:country_code":"AO",
    "gn:dem":1766,
    "gn:feature_class":"P",
    "gn:feature_code":"PPL",
    "gn:name":"Donde",
    "gn:population":0,
    "gn:timezone":"Africa/Luanda",
    "iso:country":"AO",
    "wof:name":"Donde",
    "wof:placetype":"locality"
},
  "geometry": {"coordinates":[16.41667,-12.53333],"type":"Point"}
}