{
  "type": "Feature",
  "properties": {
    "gn:admin1_code":"4.0",
    "gn:asciiname":"Machocue",
    "gn:cc2":"AO",
    "gn:country_code":"AO",
    "gn:dem":991,
    "gn:feature_class":"P",
    "gn:feature_code":"PPL",
    "gn:name":"Machocue",
    "gn:population":0,
    "gn:timezone":"Africa/Luanda",
    "iso:country":"AO",
    "name:und_x_variant":[
        "Mungombe",
        "Machocue"
    ],
    "wof:name":"Machocue",
    "wof:placetype":"locality"
},
  "geometry": {"coordinates":[23.01667,-17.51667],"type":"Point"}
}