{
  "type": "Feature",
  "properties": {
    "gn:admin1_code":"17.0",
    "gn:asciiname":"Muaneno",
    "gn:country_code":"AO",
    "gn:dem":974,
    "gn:feature_class":"P",
    "gn:feature_code":"PPL",
    "gn:name":"Muaneno",
    "gn:population":0,
    "gn:timezone":"Africa/Luanda",
    "iso:country":"AO",
    "wof:name":"Muaneno",
    "wof:placetype":"locality"
},
  "geometry": {"coordinates":[20.64011,-8.55938],"type":"Point"}
}