{
  "type": "Feature",
  "properties": {
    "gn:admin1_code":"14.0",
    "gn:asciiname":"Catimbo",
    "gn:cc2":"AO",
    "gn:country_code":"AO",
    "gn:dem":1106,
    "gn:feature_class":"P",
    "gn:feature_code":"PPL",
    "gn:name":"Catimbo",
    "gn:population":0,
    "gn:timezone":"Africa/Luanda",
    "iso:country":"AO",
    "name:und_x_variant":[
        "Chimbambo",
        "Catimbo"
    ],
    "wof:name":"Catimbo",
    "wof:placetype":"locality"
},
  "geometry": {"coordinates":[23.13333,-11.71667],"type":"Point"}
}