{
  "type": "Feature",
  "properties": {
    "gn:admin1_code":"1.0",
    "gn:asciiname":"Chimbaia",
    "gn:country_code":"AO",
    "gn:dem":1620,
    "gn:feature_class":"P",
    "gn:feature_code":"PPL",
    "gn:name":"Chimbaia",
    "gn:population":0,
    "gn:timezone":"Africa/Luanda",
    "iso:country":"AO",
    "wof:name":"Chimbaia",
    "wof:placetype":"locality"
},
  "geometry": {"coordinates":[14.98626,-12.3652],"type":"Point"}
}