{
  "type": "Feature",
  "properties": {
    "gn:admin1_code":"12.0",
    "gn:asciiname":"Cacolo",
    "gn:country_code":"AO",
    "gn:dem":1151,
    "gn:feature_class":"P",
    "gn:feature_code":"PPL",
    "gn:name":"Cacolo",
    "gn:population":0,
    "gn:timezone":"Africa/Luanda",
    "iso:country":"AO",
    "name:azb_x_preferred":[
        "\u06a9\u0627\u06a9\u0648\u0644\u0648"
    ],
    "name:cat_x_preferred":[
        "Cacolo"
    ],
    "name:deu_x_preferred":[
        "Cacolo"
    ],
    "name:fas_x_preferred":[
        "\u06a9\u0627\u06a9\u0648\u0644\u0648"
    ],
    "name:ita_x_preferred":[
        "Cacolo"
    ],
    "name:msa_x_preferred":[
        "Kakolo"
    ],
    "name:pol_x_preferred":[
        "Cacolo"
    ],
    "name:por_x_preferred":[
        "Cacolo"
    ],
    "name:spa_x_preferred":[
        "Cacolo"
    ],
    "name:zho_x_preferred":[
        "\u5361\u79d1\u6d1b"
    ],
    "wof:name":"Cacolo",
    "wof:placetype":"locality"
},
  "geometry": {"coordinates":[16.02992,-9.48941],"type":"Point"}
}