{
  "type": "Feature",
  "properties": {
    "gn:admin1_code":"12.0",
    "gn:asciiname":"Cacolo",
    "gn:country_code":"AO",
    "gn:dem":1151,
    "gn:feature_class":"P",
    "gn:feature_code":"PPL",
    "gn:name":"Cacolo",
    "gn:population":0,
    "gn:timezone":"Africa/Luanda",
    "iso:country":"AO",
    "name:ara_x_preferred":[
        "\u0643\u0627\u0643\u0648\u0644\u0648"
    ],
    "name:azb_x_preferred":[
        "\u06a9\u0627\u06a9\u0648\u0644\u0648"
    ],
    "name:ben_x_preferred":[
        "\u0995\u09be\u0995\u09cb\u09b2\u09cb"
    ],
    "name:cat_x_preferred":[
        "Cacolo"
    ],
    "name:deu_x_preferred":[
        "Cacolo"
    ],
    "name:ell_x_preferred":[
        "\u039a\u03b1\u03ba\u03cc\u03bb\u03bf"
    ],
    "name:fas_x_preferred":[
        "\u06a9\u0627\u06a9\u0648\u0644\u0648"
    ],
    "name:heb_x_preferred":[
        "\u05e7\u05e7\u05d5\u05dc\u05d5\u05dc"
    ],
    "name:hin_x_preferred":[
        "\u0915\u0915\u094b\u0932\u094b"
    ],
    "name:hun_x_preferred":[
        "Cacolo"
    ],
    "name:ind_x_preferred":[
        "Cacolo"
    ],
    "name:ita_x_preferred":[
        "Cacolo"
    ],
    "name:kor_x_preferred":[
        "\uce74\ucf5c\ub85c"
    ],
    "name:msa_x_preferred":[
        "Kakolo"
    ],
    "name:pol_x_preferred":[
        "Cacolo"
    ],
    "name:por_x_preferred":[
        "Cacolo"
    ],
    "name:rus_x_preferred":[
        "\u041a\u0430\u043a\u043e\u043b\u043e"
    ],
    "name:spa_x_preferred":[
        "Cacolo"
    ],
    "name:tur_x_preferred":[
        "Cacolo"
    ],
    "name:ukr_x_preferred":[
        "\u041a\u0430\u043a\u043e\u043b\u043e"
    ],
    "name:urd_x_preferred":[
        "\u06a9\u0627\u06a9\u0648\u0644\u0648"
    ],
    "name:vie_x_preferred":[
        "Cacolo"
    ],
    "name:zho_x_preferred":[
        "\u5361\u79d1\u6d1b"
    ],
    "wof:name":"Cacolo",
    "wof:placetype":"locality"
},
  "geometry": {"coordinates":[16.02992,-9.48941],"type":"Point"}
}