{
  "type": "Feature",
  "properties": {
    "gn:admin1_code":"19.0",
    "gn:asciiname":"Maria Teresa",
    "gn:country_code":"AO",
    "gn:dem":166,
    "gn:feature_class":"P",
    "gn:feature_code":"PPL",
    "gn:name":"Maria Teresa",
    "gn:population":0,
    "gn:timezone":"Africa/Luanda",
    "iso:country":"AO",
    "name:und_x_variant":[
        "Maria Tereza",
        "Maria Teresa"
    ],
    "wof:name":"Maria Teresa",
    "wof:placetype":"locality"
},
  "geometry": {"coordinates":[14.10467,-9.25335],"type":"Point"}
}