{
  "type": "Feature",
  "properties": {
    "gn:admin1_code":"19.0",
    "gn:asciiname":"Mumbondo",
    "gn:country_code":"AO",
    "gn:dem":44,
    "gn:feature_class":"P",
    "gn:feature_code":"PPL",
    "gn:name":"Mumbondo",
    "gn:population":0,
    "gn:timezone":"Africa/Luanda",
    "iso:country":"AO",
    "name:msa_x_preferred":[
        "Mumbondo"
    ],
    "wof:name":"Mumbondo",
    "wof:placetype":"locality"
},
  "geometry": {"coordinates":[14.12968,-10.18192],"type":"Point"}
}