{
  "type": "Feature",
  "properties": {
    "gn:admin1_code":"17.0",
    "gn:asciiname":"Fernando",
    "gn:country_code":"AO",
    "gn:dem":853,
    "gn:feature_class":"P",
    "gn:feature_code":"PPL",
    "gn:name":"Fernando",
    "gn:population":0,
    "gn:timezone":"Africa/Luanda",
    "iso:country":"AO",
    "wof:name":"Fernando",
    "wof:placetype":"locality"
},
  "geometry": {"coordinates":[19.91914,-7.74054],"type":"Point"}
}