{
  "type": "Feature",
  "properties": {
    "gn:admin1_code":"16.0",
    "gn:asciiname":"Quincunga",
    "gn:country_code":"AO",
    "gn:dem":639,
    "gn:feature_class":"P",
    "gn:feature_code":"PPL",
    "gn:name":"Quincunga",
    "gn:population":0,
    "gn:timezone":"Africa/Luanda",
    "iso:country":"AO",
    "wof:name":"Quincunga",
    "wof:placetype":"locality"
},
  "geometry": {"coordinates":[14.36667,-6.58333],"type":"Point"}
}