{
  "type": "Feature",
  "properties": {
    "gn:admin1_code":"13.0",
    "gn:asciiname":"Caraculo",
    "gn:country_code":"AO",
    "gn:dem":445,
    "gn:feature_class":"P",
    "gn:feature_code":"PPL",
    "gn:name":"Caraculo",
    "gn:population":0,
    "gn:timezone":"Africa/Luanda",
    "iso:country":"AO",
    "name:und_x_variant":[
        "Dois Irm\u00e3os",
        "Caraculo"
    ],
    "wof:name":"Caraculo",
    "wof:placetype":"locality"
},
  "geometry": {"coordinates":[12.66724,-14.99274],"type":"Point"}
}