{
  "type": "Feature",
  "properties": {
    "gn:admin1_code":"12.0",
    "gn:asciiname":"Nguvo",
    "gn:country_code":"AO",
    "gn:dem":1175,
    "gn:feature_class":"P",
    "gn:feature_code":"PPL",
    "gn:name":"Nguvo",
    "gn:population":0,
    "gn:timezone":"Africa/Luanda",
    "iso:country":"AO",
    "wof:name":"Nguvo",
    "wof:placetype":"locality"
},
  "geometry": {"coordinates":[16.02941,-8.85449],"type":"Point"}
}