{
  "type": "Feature",
  "properties": {
    "gn:admin1_code":"16.0",
    "gn:asciiname":"Ngunguma",
    "gn:country_code":"AO",
    "gn:dem":34,
    "gn:feature_class":"P",
    "gn:feature_code":"PPL",
    "gn:name":"Ngunguma",
    "gn:population":0,
    "gn:timezone":"Africa/Luanda",
    "iso:country":"AO",
    "wof:name":"Ngunguma",
    "wof:placetype":"locality"
},
  "geometry": {"coordinates":[12.74978,-6.86132],"type":"Point"}
}