{
  "type": "Feature",
  "properties": {
    "gn:admin1_code":"6.0",
    "gn:asciiname":"Tchicano",
    "gn:country_code":"AO",
    "gn:dem":1235,
    "gn:feature_class":"P",
    "gn:feature_code":"PPLL",
    "gn:name":"Tchicano",
    "gn:population":0,
    "gn:timezone":"Africa/Luanda",
    "iso:country":"AO",
    "name:und_x_variant":[
        "Sequina",
        "Chicano",
        "Tchicano"
    ],
    "wof:name":"Tchicano",
    "wof:placetype":"locality"
},
  "geometry": {"coordinates":[15.93696,-10.41382],"type":"Point"}
}