{
  "type": "Feature",
  "properties": {
    "gn:admin1_code":"15.0",
    "gn:asciiname":"Mbanza Zombo",
    "gn:country_code":"AO",
    "gn:dem":967,
    "gn:feature_class":"P",
    "gn:feature_code":"PPL",
    "gn:name":"Mbanza Zombo",
    "gn:population":0,
    "gn:timezone":"Africa/Luanda",
    "iso:country":"AO",
    "name:und_x_variant":[
        "Banza Zombo"
    ],
    "wof:name":"Mbanza Zombo",
    "wof:placetype":"locality"
},
  "geometry": {"coordinates":[15.05862,-6.18499],"type":"Point"}
}