{
  "type": "Feature",
  "properties": {
    "gn:admin1_code":"6.0",
    "gn:asciiname":"Conde Centro",
    "gn:country_code":"AO",
    "gn:dem":1213,
    "gn:feature_class":"P",
    "gn:feature_code":"PPL",
    "gn:name":"Conde Centro",
    "gn:population":0,
    "gn:timezone":"Africa/Luanda",
    "iso:country":"AO",
    "wof:name":"Conde Centro",
    "wof:placetype":"locality"
},
  "geometry": {"coordinates":[14.68915,-10.87206],"type":"Point"}
}