{
  "type": "Feature",
  "properties": {
    "gn:admin1_code":"5.0",
    "gn:admin2_code":"2242801.0",
    "gn:asciiname":"Mussende",
    "gn:country_code":"AO",
    "gn:dem":343,
    "gn:feature_class":"P",
    "gn:feature_code":"PPL",
    "gn:name":"Mussende",
    "gn:population":0,
    "gn:timezone":"Africa/Luanda",
    "iso:country":"AO",
    "name:azb_x_preferred":[
        "\u0645\u0648\u0633\u0646\u062f\u0647"
    ],
    "name:cat_x_preferred":[
        "Mussende"
    ],
    "name:deu_x_preferred":[
        "Mussende"
    ],
    "name:fas_x_preferred":[
        "\u0645\u0648\u0633\u0646\u062f\u0647"
    ],
    "name:ita_x_preferred":[
        "Mussende"
    ],
    "name:msa_x_preferred":[
        "Mussende"
    ],
    "name:por_x_preferred":[
        "Mussende"
    ],
    "name:spa_x_preferred":[
        "Mussende"
    ],
    "name:zho_x_preferred":[
        "\u7a46\u68ee\u4ee3"
    ],
    "wof:name":"Mussende",
    "wof:placetype":"locality"
},
  "geometry": {"coordinates":[14.81785,-9.4688],"type":"Point"}
}