{
  "type": "Feature",
  "properties": {
    "gn:admin1_code":"5.0",
    "gn:admin2_code":"2242801.0",
    "gn:asciiname":"Mussende",
    "gn:country_code":"AO",
    "gn:dem":343,
    "gn:feature_class":"P",
    "gn:feature_code":"PPL",
    "gn:name":"Mussende",
    "gn:population":0,
    "gn:timezone":"Africa/Luanda",
    "iso:country":"AO",
    "wof:name":"Mussende",
    "wof:placetype":"locality"
},
  "geometry": {"coordinates":[14.81785,-9.4688],"type":"Point"}
}