{
  "type": "Feature",
  "properties": {
    "gn:admin1_code":"6.0",
    "gn:asciiname":"Nzolo",
    "gn:country_code":"AO",
    "gn:dem":825,
    "gn:feature_class":"P",
    "gn:feature_code":"PPL",
    "gn:name":"Nzolo",
    "gn:population":0,
    "gn:timezone":"Africa/Luanda",
    "iso:country":"AO",
    "wof:name":"Nzolo",
    "wof:placetype":"locality"
},
  "geometry": {"coordinates":[14.40198,-10.70442],"type":"Point"}
}