{
  "type": "Feature",
  "properties": {
    "gn:admin1_code":"5.0",
    "gn:asciiname":"Muvimba",
    "gn:country_code":"AO",
    "gn:dem":1152,
    "gn:feature_class":"P",
    "gn:feature_code":"PPL",
    "gn:name":"Muvimba",
    "gn:population":0,
    "gn:timezone":"Africa/Luanda",
    "iso:country":"AO",
    "name:und_x_variant":[
        "Movimba",
        "Muvimba"
    ],
    "wof:name":"Muvimba",
    "wof:placetype":"locality"
},
  "geometry": {"coordinates":[15.38133,-8.24007],"type":"Point"}
}