{
  "type": "Feature",
  "properties": {
    "gn:admin1_code":"6.0",
    "gn:asciiname":"Dumbo",
    "gn:country_code":"AO",
    "gn:dem":1003,
    "gn:feature_class":"P",
    "gn:feature_code":"PPL",
    "gn:name":"Dumbo",
    "gn:population":0,
    "gn:timezone":"Africa/Luanda",
    "iso:country":"AO",
    "name:und_x_variant":[
        "Dumbo de Capiro",
        "Dumbo"
    ],
    "wof:name":"Dumbo",
    "wof:placetype":"locality"
},
  "geometry": {"coordinates":[14.25947,-11.45179],"type":"Point"}
}