{
  "type": "Feature",
  "properties": {
    "gn:admin1_code":"17.0",
    "gn:asciiname":"Culaxingo",
    "gn:country_code":"AO",
    "gn:dem":764,
    "gn:feature_class":"P",
    "gn:feature_code":"PPL",
    "gn:name":"Culaxingo",
    "gn:population":0,
    "gn:timezone":"Africa/Luanda",
    "iso:country":"AO",
    "wof:name":"Culaxingo",
    "wof:placetype":"locality"
},
  "geometry": {"coordinates":[17.85,-8.65],"type":"Point"}
}