{
  "type": "Feature",
  "properties": {
    "gn:admin1_code":"4.0",
    "gn:asciiname":"Comandante Jica",
    "gn:country_code":"AO",
    "gn:dem":1363,
    "gn:feature_class":"P",
    "gn:feature_code":"PPL",
    "gn:name":"Comandante Jica",
    "gn:population":0,
    "gn:timezone":"Africa/Luanda",
    "iso:country":"AO",
    "wof:name":"Comandante Jica",
    "wof:placetype":"locality"
},
  "geometry": {"coordinates":[17.67894,-14.6811],"type":"Point"}
}