{
  "type": "Feature",
  "properties": {
    "gn:admin1_code":"12.0",
    "gn:asciiname":"Banze",
    "gn:country_code":"AO",
    "gn:dem":1060,
    "gn:feature_class":"P",
    "gn:feature_code":"PPL",
    "gn:name":"Banze",
    "gn:population":0,
    "gn:timezone":"Africa/Luanda",
    "iso:country":"AO",
    "wof:name":"Banze",
    "wof:placetype":"locality"
},
  "geometry": {"coordinates":[16.36972,-9.67444],"type":"Point"}
}