{
  "type": "Feature",
  "properties": {
    "gn:admin1_code":"12.0",
    "gn:asciiname":"Dombo",
    "gn:country_code":"AO",
    "gn:dem":1078,
    "gn:feature_class":"P",
    "gn:feature_code":"PPL",
    "gn:name":"Dombo",
    "gn:population":0,
    "gn:timezone":"Africa/Luanda",
    "iso:country":"AO",
    "wof:name":"Dombo",
    "wof:placetype":"locality"
},
  "geometry": {"coordinates":[16.85756,-10.7088],"type":"Point"}
}