{
  "type": "Feature",
  "properties": {
    "gn:admin1_code":"15.0",
    "gn:asciiname":"D. Antonio",
    "gn:country_code":"AO",
    "gn:dem":795,
    "gn:feature_class":"P",
    "gn:feature_code":"PPL",
    "gn:name":"D. Ant\u00f3nio",
    "gn:population":0,
    "gn:timezone":"Africa/Luanda",
    "iso:country":"AO",
    "name:por_x_preferred":[
        "D. Ant\u00f3nio"
    ],
    "wof:name":"D. Antonio",
    "wof:placetype":"locality"
},
  "geometry": {"coordinates":[16.22792999999999,-6.30363],"type":"Point"}
}