{
  "type": "Feature",
  "properties": {
    "gn:admin1_code":"5.0",
    "gn:asciiname":"Cacuanza",
    "gn:country_code":"AO",
    "gn:dem":21,
    "gn:feature_class":"P",
    "gn:feature_code":"PPL",
    "gn:name":"Cacuanza",
    "gn:population":0,
    "gn:timezone":"Africa/Luanda",
    "iso:country":"AO",
    "wof:name":"Cacuanza",
    "wof:placetype":"locality"
},
  "geometry": {"coordinates":[14.36667,-9.68333],"type":"Point"}
}