{
  "type": "Feature",
  "properties": {
    "gn:admin1_code":"16.0",
    "gn:asciiname":"Cuanda",
    "gn:country_code":"AO",
    "gn:dem":5,
    "gn:feature_class":"P",
    "gn:feature_code":"PPL",
    "gn:name":"Cuanda",
    "gn:population":0,
    "gn:timezone":"Africa/Luanda",
    "iso:country":"AO",
    "wof:name":"Cuanda",
    "wof:placetype":"locality"
},
  "geometry": {"coordinates":[12.33392,-6.12563],"type":"Point"}
}