{
  "type": "Feature",
  "properties": {
    "gn:admin1_code":"12.0",
    "gn:asciiname":"Sacambinza",
    "gn:country_code":"AO",
    "gn:dem":1154,
    "gn:feature_class":"P",
    "gn:feature_code":"PPL",
    "gn:name":"Sacambinza",
    "gn:population":0,
    "gn:timezone":"Africa/Luanda",
    "iso:country":"AO",
    "wof:name":"Sacambinza",
    "wof:placetype":"locality"
},
  "geometry": {"coordinates":[17.77648,-10.98507],"type":"Point"}
}