{
  "type": "Feature",
  "properties": {
    "gn:admin1_code":"17.0",
    "gn:asciiname":"Itanda",
    "gn:country_code":"AO",
    "gn:dem":872,
    "gn:feature_class":"P",
    "gn:feature_code":"PPL",
    "gn:name":"Itanda",
    "gn:population":0,
    "gn:timezone":"Africa/Luanda",
    "iso:country":"AO",
    "name:und_x_variant":[
        "Capetungo",
        "Itanda",
        "Calumuna",
        "Camabumba"
    ],
    "wof:name":"Itanda",
    "wof:placetype":"locality"
},
  "geometry": {"coordinates":[21.64333,-7.34318],"type":"Point"}
}