{
  "type": "Feature",
  "properties": {
    "gn:admin1_code":"18.0",
    "gn:asciiname":"Capembe",
    "gn:cc2":"AO",
    "gn:country_code":"AO",
    "gn:dem":948,
    "gn:feature_class":"P",
    "gn:feature_code":"PPL",
    "gn:name":"Capembe",
    "gn:population":0,
    "gn:timezone":"Africa/Luanda",
    "iso:country":"AO",
    "name:und_x_variant":[
        "Chamabenda",
        "Capembe"
    ],
    "wof:name":"Capembe",
    "wof:placetype":"locality"
},
  "geometry": {"coordinates":[21.13333,-8.71667],"type":"Point"}
}