{
  "type": "Feature",
  "properties": {
    "gn:admin1_code":"15.0",
    "gn:asciiname":"Quindele",
    "gn:country_code":"AO",
    "gn:dem":969,
    "gn:feature_class":"P",
    "gn:feature_code":"PPL",
    "gn:name":"Quindele",
    "gn:population":0,
    "gn:timezone":"Africa/Luanda",
    "iso:country":"AO",
    "wof:name":"Quindele",
    "wof:placetype":"locality"
},
  "geometry": {"coordinates":[15.38665,-6.92118],"type":"Point"}
}