{
  "type": "Feature",
  "properties": {
    "gn:admin1_code":"18.0",
    "gn:asciiname":"Muamuieie",
    "gn:country_code":"AO",
    "gn:dem":1265,
    "gn:feature_class":"P",
    "gn:feature_code":"PPL",
    "gn:name":"Muamuieie",
    "gn:population":0,
    "gn:timezone":"Africa/Luanda",
    "iso:country":"AO",
    "name:und_x_variant":[
        "Mu\u00e1 Muiei",
        "Mamiei",
        "Muamuieie"
    ],
    "wof:name":"Muamuieie",
    "wof:placetype":"locality"
},
  "geometry": {"coordinates":[19.15439,-10.25204],"type":"Point"}
}