{
  "type": "Feature",
  "properties": {
    "gn:admin1_code":"6.0",
    "gn:asciiname":"Sapia",
    "gn:country_code":"AO",
    "gn:dem":1379,
    "gn:feature_class":"P",
    "gn:feature_code":"PPL",
    "gn:name":"Sapia",
    "gn:population":0,
    "gn:timezone":"Africa/Luanda",
    "iso:country":"AO",
    "wof:name":"Sapia",
    "wof:placetype":"locality"
},
  "geometry": {"coordinates":[15.29843,-11.38683],"type":"Point"}
}