{
  "type": "Feature",
  "properties": {
    "gn:admin1_code":"18.0",
    "gn:asciiname":"Muandonji",
    "gn:country_code":"AO",
    "gn:dem":1062,
    "gn:feature_class":"P",
    "gn:feature_code":"PPL",
    "gn:name":"Muandonji",
    "gn:population":0,
    "gn:timezone":"Africa/Luanda",
    "iso:country":"AO",
    "name:und_x_variant":[
        "Mondongi",
        "Mondonji",
        "Muandonge",
        "Muandonji"
    ],
    "wof:name":"Muandonji",
    "wof:placetype":"locality"
},
  "geometry": {"coordinates":[20.58476,-9.57409],"type":"Point"}
}