{
  "type": "Feature",
  "properties": {
    "gn:admin1_code":"6.0",
    "gn:asciiname":"Cassembo Correia",
    "gn:country_code":"AO",
    "gn:dem":1381,
    "gn:feature_class":"P",
    "gn:feature_code":"PPL",
    "gn:name":"Cassembo Correia",
    "gn:population":0,
    "gn:timezone":"Africa/Luanda",
    "iso:country":"AO",
    "wof:name":"Cassembo Correia",
    "wof:placetype":"locality"
},
  "geometry": {"coordinates":[16.03675,-10.48482],"type":"Point"}
}