{
  "type": "Feature",
  "properties": {
    "gn:admin1_code":"8.0",
    "gn:asciiname":"Gongo",
    "gn:country_code":"AO",
    "gn:dem":1659,
    "gn:feature_class":"P",
    "gn:feature_code":"PPL",
    "gn:name":"Gongo",
    "gn:population":0,
    "gn:timezone":"Africa/Luanda",
    "iso:country":"AO",
    "wof:name":"Gongo",
    "wof:placetype":"locality"
},
  "geometry": {"coordinates":[15.41667,-12.23333],"type":"Point"}
}