{
  "type": "Feature",
  "properties": {
    "gn:admin1_code":"17.0",
    "gn:asciiname":"Sambuege Segundo",
    "gn:country_code":"AO",
    "gn:dem":831,
    "gn:feature_class":"P",
    "gn:feature_code":"PPL",
    "gn:name":"Sambuege Segundo",
    "gn:population":0,
    "gn:timezone":"Africa/Luanda",
    "iso:country":"AO",
    "wof:name":"Sambuege Segundo",
    "wof:placetype":"locality"
},
  "geometry": {"coordinates":[20.73667,-8.26287],"type":"Point"}
}