{
  "type": "Feature",
  "properties": {
    "gn:admin1_code":"12.0",
    "gn:asciiname":"Cacuso de Baixo",
    "gn:country_code":"AO",
    "gn:dem":1001,
    "gn:feature_class":"P",
    "gn:feature_code":"PPL",
    "gn:name":"Cacuso de Baixo",
    "gn:population":0,
    "gn:timezone":"Africa/Luanda",
    "iso:country":"AO",
    "wof:name":"Cacuso de Baixo",
    "wof:placetype":"locality"
},
  "geometry": {"coordinates":[15.74887,-9.32118],"type":"Point"}
}