{
  "type": "Feature",
  "properties": {
    "gn:admin1_code":"5.0",
    "gn:asciiname":"Leale",
    "gn:country_code":"AO",
    "gn:dem":940,
    "gn:feature_class":"P",
    "gn:feature_code":"PPL",
    "gn:name":"Leale",
    "gn:population":0,
    "gn:timezone":"Africa/Luanda",
    "iso:country":"AO",
    "name:ukr_x_preferred":[
        "\u041b\u0435\u0439\u043b"
    ],
    "wof:name":"Leale",
    "wof:placetype":"locality"
},
  "geometry": {"coordinates":[15.58333,-9.16667],"type":"Point"}
}