{
  "type": "Feature",
  "properties": {
    "gn:admin1_code":"19.0",
    "gn:asciiname":"Paranhos",
    "gn:country_code":"AO",
    "gn:dem":16,
    "gn:feature_class":"P",
    "gn:feature_code":"PPL",
    "gn:name":"Paranhos",
    "gn:population":0,
    "gn:timezone":"Africa/Luanda",
    "iso:country":"AO",
    "name:ceb_x_preferred":[
        "Paranhos"
    ],
    "name:deu_x_preferred":[
        "Paranhos"
    ],
    "name:fra_x_preferred":[
        "Paranhos"
    ],
    "name:nds_x_preferred":[
        "Paranhos"
    ],
    "name:nld_x_preferred":[
        "Paranhos"
    ],
    "name:por_x_preferred":[
        "Paranhos"
    ],
    "name:rus_x_preferred":[
        "\u041f\u0430\u0440\u0430\u043d\u044c\u044e\u0448"
    ],
    "name:swe_x_preferred":[
        "Paranhos"
    ],
    "name:ukr_x_preferred":[
        "\u041f\u0430\u0440\u0430\u043d\u044e\u0448"
    ],
    "wof:name":"Paranhos",
    "wof:placetype":"locality"
},
  "geometry": {"coordinates":[13.67111,-8.5575],"type":"Point"}
}