{
  "type": "Feature",
  "properties": {
    "gn:admin1_code":"19.0",
    "gn:asciiname":"Paranhos",
    "gn:country_code":"AO",
    "gn:dem":16,
    "gn:feature_class":"P",
    "gn:feature_code":"PPL",
    "gn:name":"Paranhos",
    "gn:population":0,
    "gn:timezone":"Africa/Luanda",
    "iso:country":"AO",
    "wof:name":"Paranhos",
    "wof:placetype":"locality"
},
  "geometry": {"coordinates":[13.67111,-8.5575],"type":"Point"}
}