{
  "type": "Feature",
  "properties": {
    "gn:admin1_code":"3.0",
    "gn:asciiname":"Tchissanga",
    "gn:cc2":"AO",
    "gn:country_code":"AO",
    "gn:dem":64,
    "gn:feature_class":"P",
    "gn:feature_code":"PPL",
    "gn:name":"Tchissanga",
    "gn:population":0,
    "gn:timezone":"Africa/Luanda",
    "iso:country":"AO",
    "name:und_x_variant":[
        "Bongo Venzo",
        "Bongo Nenzo",
        "Bengo Venzo",
        "Tchissanga"
    ],
    "wof:name":"Tchissanga",
    "wof:placetype":"locality"
},
  "geometry": {"coordinates":[12.18333,-4.95],"type":"Point"}
}