{
  "type": "Feature",
  "properties": {
    "gn:admin1_code":"12.0",
    "gn:asciiname":"Nzari",
    "gn:country_code":"AO",
    "gn:dem":1088,
    "gn:feature_class":"P",
    "gn:feature_code":"PPL",
    "gn:name":"Nz\u00e1ri",
    "gn:population":0,
    "gn:timezone":"Africa/Luanda",
    "iso:country":"AO",
    "name:und_x_variant":[
        "Zar",
        "Quizanga",
        "Nz\u00e1ri"
    ],
    "wof:name":"Nzari",
    "wof:placetype":"locality"
},
  "geometry": {"coordinates":[15.9682,-9.25374],"type":"Point"}
}