{
  "type": "Feature",
  "properties": {
    "gn:admin1_code":"12.0",
    "gn:asciiname":"Capassa Issanga",
    "gn:country_code":"AO",
    "gn:dem":705,
    "gn:feature_class":"P",
    "gn:feature_code":"PPL",
    "gn:name":"Capassa Issanga",
    "gn:population":0,
    "gn:timezone":"Africa/Luanda",
    "iso:country":"AO",
    "wof:name":"Capassa Issanga",
    "wof:placetype":"locality"
},
  "geometry": {"coordinates":[16.74922999999999,-8.7165],"type":"Point"}
}