{
  "type": "Feature",
  "properties": {
    "gn:admin1_code":"9.0",
    "gn:asciiname":"Cavissi",
    "gn:country_code":"AO",
    "gn:dem":1466,
    "gn:feature_class":"P",
    "gn:feature_code":"PPL",
    "gn:name":"Cavissi",
    "gn:population":0,
    "gn:timezone":"Africa/Luanda",
    "iso:country":"AO",
    "wof:name":"Cavissi",
    "wof:placetype":"locality"
},
  "geometry": {"coordinates":[14.223,-14.57093],"type":"Point"}
}