{
  "type": "Feature",
  "properties": {
    "gn:admin1_code":"12.0",
    "gn:asciiname":"Tenda",
    "gn:country_code":"AO",
    "gn:dem":1194,
    "gn:feature_class":"P",
    "gn:feature_code":"PPL",
    "gn:name":"Tenda",
    "gn:population":0,
    "gn:timezone":"Africa/Luanda",
    "iso:country":"AO",
    "name:ceb_x_preferred":[
        "Tenda"
    ],
    "name:deu_x_preferred":[
        "Tenda"
    ],
    "name:fra_x_preferred":[
        "Tenda"
    ],
    "name:ita_x_preferred":[
        "Tenda"
    ],
    "name:swe_x_preferred":[
        "Tenda"
    ],
    "name:zho_x_preferred":[
        "Tenda"
    ],
    "wof:name":"Tenda",
    "wof:placetype":"locality"
},
  "geometry": {"coordinates":[15.81254,-8.70065],"type":"Point"}
}