{
  "type": "Feature",
  "properties": {
    "gn:admin1_code":"12.0",
    "gn:asciiname":"Angola Nova",
    "gn:country_code":"AO",
    "gn:dem":757,
    "gn:feature_class":"P",
    "gn:feature_code":"PPL",
    "gn:name":"Angola Nova",
    "gn:population":0,
    "gn:timezone":"Africa/Luanda",
    "iso:country":"AO",
    "wof:name":"Angola Nova",
    "wof:placetype":"locality"
},
  "geometry": {"coordinates":[16.46492000000001,-7.61708],"type":"Point"}
}