{
  "type": "Feature",
  "properties": {
    "gn:admin1_code":"12.0",
    "gn:asciiname":"Calolo Velho",
    "gn:country_code":"AO",
    "gn:dem":1141,
    "gn:feature_class":"P",
    "gn:feature_code":"PPL",
    "gn:name":"Calolo Velho",
    "gn:population":0,
    "gn:timezone":"Africa/Luanda",
    "iso:country":"AO",
    "wof:name":"Calolo Velho",
    "wof:placetype":"locality"
},
  "geometry": {"coordinates":[16.26371,-9.24683],"type":"Point"}
}