{
  "type": "Feature",
  "properties": {
    "gn:admin1_code":"13.0",
    "gn:asciiname":"Subida Grande",
    "gn:cc2":"AO",
    "gn:country_code":"AO",
    "gn:dem":136,
    "gn:feature_class":"P",
    "gn:feature_code":"PPL",
    "gn:name":"Subida Grande",
    "gn:population":0,
    "gn:timezone":"Africa/Luanda",
    "iso:country":"AO",
    "name:und_x_variant":[
        "Subida",
        "Subida Grande"
    ],
    "wof:name":"Subida Grande",
    "wof:placetype":"locality"
},
  "geometry": {"coordinates":[12.15,-15.35],"type":"Point"}
}