{
  "type": "Feature",
  "properties": {
    "gn:admin1_code":"15.0",
    "gn:asciiname":"Quilamba",
    "gn:country_code":"AO",
    "gn:dem":1141,
    "gn:feature_class":"P",
    "gn:feature_code":"PPL",
    "gn:name":"Quilamba",
    "gn:population":0,
    "gn:timezone":"Africa/Luanda",
    "iso:country":"AO",
    "wof:name":"Quilamba",
    "wof:placetype":"locality"
},
  "geometry": {"coordinates":[15.64782,-7.69206],"type":"Point"}
}