{
  "type": "Feature",
  "properties": {
    "gn:admin1_code":"8.0",
    "gn:asciiname":"Goio",
    "gn:cc2":"AO",
    "gn:country_code":"AO",
    "gn:dem":1659,
    "gn:feature_class":"P",
    "gn:feature_code":"PPL",
    "gn:name":"Goio",
    "gn:population":0,
    "gn:timezone":"Africa/Luanda",
    "iso:country":"AO",
    "name:und_x_variant":[
        "Goro",
        "Goio"
    ],
    "wof:name":"Goio",
    "wof:placetype":"locality"
},
  "geometry": {"coordinates":[15.61667,-12.05],"type":"Point"}
}