{
  "type": "Feature",
  "properties": {
    "gn:admin1_code":"16.0",
    "gn:asciiname":"Camba",
    "gn:country_code":"AO",
    "gn:dem":482,
    "gn:feature_class":"P",
    "gn:feature_code":"PPL",
    "gn:name":"Camba",
    "gn:population":0,
    "gn:timezone":"Africa/Luanda",
    "iso:country":"AO",
    "wof:name":"Camba",
    "wof:placetype":"locality"
},
  "geometry": {"coordinates":[14.14878,-6.81468],"type":"Point"}
}