{
  "type": "Feature",
  "properties": {
    "gn:admin1_code":"6.0",
    "gn:asciiname":"Dembe",
    "gn:country_code":"AO",
    "gn:dem":1308,
    "gn:feature_class":"P",
    "gn:feature_code":"PPL",
    "gn:name":"Dembe",
    "gn:population":0,
    "gn:timezone":"Africa/Luanda",
    "iso:country":"AO",
    "name:ceb_x_preferred":[
        "Dembe"
    ],
    "name:swe_x_preferred":[
        "Dembe"
    ],
    "wof:name":"Dembe",
    "wof:placetype":"locality"
},
  "geometry": {"coordinates":[15.46893,-10.7333],"type":"Point"}
}