{
  "type": "Feature",
  "properties": {
    "gn:admin1_code":"16.0",
    "gn:asciiname":"Luena",
    "gn:country_code":"AO",
    "gn:dem":547,
    "gn:feature_class":"P",
    "gn:feature_code":"PPL",
    "gn:name":"Luena",
    "gn:population":0,
    "gn:timezone":"Africa/Luanda",
    "iso:country":"AO",
    "wof:name":"Luena",
    "wof:placetype":"locality"
},
  "geometry": {"coordinates":[14.13333,-6.71667],"type":"Point"}
}