{
  "type": "Feature",
  "properties": {
    "gn:admin1_code":"16.0",
    "gn:asciiname":"Cunga",
    "gn:country_code":"AO",
    "gn:dem":822,
    "gn:feature_class":"P",
    "gn:feature_code":"PPL",
    "gn:name":"Cunga",
    "gn:population":0,
    "gn:timezone":"Africa/Luanda",
    "iso:country":"AO",
    "wof:name":"Cunga",
    "wof:placetype":"locality"
},
  "geometry": {"coordinates":[14.78333,-6.23333],"type":"Point"}
}