{
  "type": "Feature",
  "properties": {
    "gn:admin1_code":"12.0",
    "gn:asciiname":"Castembala",
    "gn:country_code":"AO",
    "gn:dem":1061,
    "gn:feature_class":"P",
    "gn:feature_code":"PPL",
    "gn:name":"Castembala",
    "gn:population":0,
    "gn:timezone":"Africa/Luanda",
    "iso:country":"AO",
    "wof:name":"Castembala",
    "wof:placetype":"locality"
},
  "geometry": {"coordinates":[16.49389,-9.60278],"type":"Point"}
}