{
  "type": "Feature",
  "properties": {
    "gn:admin1_code":"19.0",
    "gn:asciiname":"Bom Jesus",
    "gn:country_code":"AO",
    "gn:dem":565,
    "gn:feature_class":"P",
    "gn:feature_code":"PPL",
    "gn:name":"Bom Jesus",
    "gn:population":0,
    "gn:timezone":"Africa/Luanda",
    "iso:country":"AO",
    "wof:name":"Bom Jesus",
    "wof:placetype":"locality"
},
  "geometry": {"coordinates":[14.21667,-8.01667],"type":"Point"}
}