{
  "type": "Feature",
  "properties": {
    "gn:admin1_code":"8.0",
    "gn:asciiname":"Sananga",
    "gn:country_code":"AO",
    "gn:dem":1729,
    "gn:feature_class":"P",
    "gn:feature_code":"PPL",
    "gn:name":"Sananga",
    "gn:population":0,
    "gn:timezone":"Africa/Luanda",
    "iso:country":"AO",
    "wof:name":"Sananga",
    "wof:placetype":"locality"
},
  "geometry": {"coordinates":[14.96667,-12.63333],"type":"Point"}
}