{
  "type": "Feature",
  "properties": {
    "gn:admin1_code":"16.0",
    "gn:asciiname":"Lufunde",
    "gn:country_code":"AO",
    "gn:dem":451,
    "gn:feature_class":"P",
    "gn:feature_code":"PPL",
    "gn:name":"Lufunde",
    "gn:population":0,
    "gn:timezone":"Africa/Luanda",
    "iso:country":"AO",
    "wof:name":"Lufunde",
    "wof:placetype":"locality"
},
  "geometry": {"coordinates":[13.72305,-6.13141],"type":"Point"}
}