{
  "type": "Feature",
  "properties": {
    "gn:admin1_code":"17.0",
    "gn:asciiname":"Chidece",
    "gn:country_code":"AO",
    "gn:dem":744,
    "gn:feature_class":"P",
    "gn:feature_code":"PPL",
    "gn:name":"Chidece",
    "gn:population":0,
    "gn:timezone":"Africa/Luanda",
    "iso:country":"AO",
    "wof:name":"Chidece",
    "wof:placetype":"locality"
},
  "geometry": {"coordinates":[21.15,-7.46667],"type":"Point"}
}