{
  "type": "Feature",
  "properties": {
    "gn:admin1_code":"12.0",
    "gn:admin2_code":"3347614.0",
    "gn:asciiname":"Capunda",
    "gn:country_code":"AO",
    "gn:dem":1148,
    "gn:feature_class":"P",
    "gn:feature_code":"PPL",
    "gn:name":"Capunda",
    "gn:population":0,
    "gn:timezone":"Africa/Luanda",
    "iso:country":"AO",
    "name:por_x_preferred":[
        "Capunda"
    ],
    "name:und_x_variant":[
        "Quimbango"
    ],
    "wof:name":"Capunda",
    "wof:placetype":"locality"
},
  "geometry": {"coordinates":[17.36834,-10.67751],"type":"Point"}
}