{
  "type": "Feature",
  "properties": {
    "gn:admin1_code":"9.0",
    "gn:asciiname":"Tchicole",
    "gn:country_code":"AO",
    "gn:dem":1295,
    "gn:feature_class":"P",
    "gn:feature_code":"PPL",
    "gn:name":"Tchicole",
    "gn:population":0,
    "gn:timezone":"Africa/Luanda",
    "iso:country":"AO",
    "wof:name":"Tchicole",
    "wof:placetype":"locality"
},
  "geometry": {"coordinates":[15.60605,-14.82536],"type":"Point"}
}