{
  "type": "Feature",
  "properties": {
    "gn:admin1_code":"14.0",
    "gn:asciiname":"Tchinguli",
    "gn:country_code":"AO",
    "gn:dem":1085,
    "gn:feature_class":"P",
    "gn:feature_code":"PPL",
    "gn:name":"Tchinguli",
    "gn:population":0,
    "gn:timezone":"Africa/Luanda",
    "iso:country":"AO",
    "wof:name":"Tchinguli",
    "wof:placetype":"locality"
},
  "geometry": {"coordinates":[22.1714,-10.81638],"type":"Point"}
}