{
  "type": "Feature",
  "properties": {
    "gn:admin1_code":"12.0",
    "gn:asciiname":"Zongo Ambela",
    "gn:country_code":"AO",
    "gn:dem":1134,
    "gn:feature_class":"P",
    "gn:feature_code":"PPL",
    "gn:name":"Zongo Ambela",
    "gn:population":0,
    "gn:timezone":"Africa/Luanda",
    "iso:country":"AO",
    "name:und_x_variant":[
        "Nzango Ambete",
        "Zango Ambele",
        "Zongo Ambela"
    ],
    "wof:name":"Zongo Ambela",
    "wof:placetype":"locality"
},
  "geometry": {"coordinates":[17.38639,-10.20023],"type":"Point"}
}