{
  "type": "Feature",
  "properties": {
    "gn:admin1_code":"4.0",
    "gn:asciiname":"Chimbiringua",
    "gn:cc2":"AO",
    "gn:country_code":"AO",
    "gn:dem":1078,
    "gn:feature_class":"P",
    "gn:feature_code":"PPL",
    "gn:name":"Chimbiringua",
    "gn:population":0,
    "gn:timezone":"Africa/Luanda",
    "iso:country":"AO",
    "name:und_x_variant":[
        "Marunga",
        "Chimbiringua"
    ],
    "wof:name":"Chimbiringua",
    "wof:placetype":"locality"
},
  "geometry": {"coordinates":[20.03333,-17.48333],"type":"Point"}
}