{
  "type": "Feature",
  "properties": {
    "gn:admin1_code":"13.0",
    "gn:asciiname":"Giraul",
    "gn:cc2":"AO",
    "gn:country_code":"AO",
    "gn:dem":15,
    "gn:feature_class":"P",
    "gn:feature_code":"PPL",
    "gn:name":"Gira\u00fal",
    "gn:population":0,
    "gn:timezone":"Africa/Luanda",
    "iso:country":"AO",
    "name:und_x_variant":[
        "Gira\u00fal de Baixo",
        "Giraul de Cima",
        "Gira\u00fal"
    ],
    "wof:name":"Giraul",
    "wof:placetype":"locality"
},
  "geometry": {"coordinates":[12.16139,-15.06528],"type":"Point"}
}