{
  "type": "Feature",
  "properties": {
    "gn:admin1_code":"16.0",
    "gn:asciiname":"Pelo",
    "gn:cc2":"AO",
    "gn:country_code":"AO",
    "gn:dem":322,
    "gn:feature_class":"P",
    "gn:feature_code":"PPL",
    "gn:name":"Pelo",
    "gn:population":0,
    "gn:timezone":"Africa/Luanda",
    "iso:country":"AO",
    "name:und_x_variant":[
        "Pete",
        "Pelo"
    ],
    "wof:name":"Pelo",
    "wof:placetype":"locality"
},
  "geometry": {"coordinates":[14.01667,-6.45],"type":"Point"}
}