{
  "type": "Feature",
  "properties": {
    "gn:admin1_code":"15.0",
    "gn:asciiname":"Comessa",
    "gn:country_code":"AO",
    "gn:dem":1255,
    "gn:feature_class":"P",
    "gn:feature_code":"PPL",
    "gn:name":"Comessa",
    "gn:population":0,
    "gn:timezone":"Africa/Luanda",
    "iso:country":"AO",
    "name:und_x_variant":[
        "Comessa I",
        "Comessa Primeiro"
    ],
    "wof:name":"Comessa",
    "wof:placetype":"locality"
},
  "geometry": {"coordinates":[15.88724,-8.17987],"type":"Point"}
}