{
  "type": "Feature",
  "properties": {
    "gn:admin1_code":"12.0",
    "gn:asciiname":"Mulo",
    "gn:country_code":"AO",
    "gn:dem":697,
    "gn:feature_class":"P",
    "gn:feature_code":"PPL",
    "gn:name":"Mulo",
    "gn:population":0,
    "gn:timezone":"Africa/Luanda",
    "iso:country":"AO",
    "name:ceb_x_preferred":[
        "Mulo"
    ],
    "name:deu_x_preferred":[
        "Mulo"
    ],
    "name:epo_x_preferred":[
        "Mulo"
    ],
    "name:ita_x_preferred":[
        "Mulo"
    ],
    "name:swe_x_preferred":[
        "Mulo"
    ],
    "wof:name":"Mulo",
    "wof:placetype":"locality"
},
  "geometry": {"coordinates":[17.17982,-8.9135],"type":"Point"}
}