{
  "type": "Feature",
  "properties": {
    "gn:admin1_code":"0.0",
    "gn:asciiname":"Viencenge",
    "gn:country_code":"AO",
    "gn:dem":330,
    "gn:feature_class":"P",
    "gn:feature_code":"PPL",
    "gn:name":"Viencenge",
    "gn:population":0,
    "gn:timezone":"Africa/Luanda",
    "iso:country":"AO",
    "wof:name":"Viencenge",
    "wof:placetype":"locality"
},
  "geometry": {"coordinates":[13.56972,-12.71083],"type":"Point"}
}