{
  "type": "Feature",
  "properties": {
    "gn:admin1_code":"2.0",
    "gn:asciiname":"Pessi",
    "gn:country_code":"AO",
    "gn:dem":1450,
    "gn:feature_class":"P",
    "gn:feature_code":"PPL",
    "gn:name":"Pessi",
    "gn:population":0,
    "gn:timezone":"Africa/Luanda",
    "iso:country":"AO",
    "wof:name":"Pessi",
    "wof:placetype":"locality"
},
  "geometry": {"coordinates":[17.43789,-11.97791],"type":"Point"}
}