{
  "type": "Feature",
  "properties": {
    "gn:admin1_code":"12.0",
    "gn:asciiname":"Taca",
    "gn:country_code":"AO",
    "gn:dem":676,
    "gn:feature_class":"P",
    "gn:feature_code":"PPL",
    "gn:name":"Taca",
    "gn:population":0,
    "gn:timezone":"Africa/Luanda",
    "iso:country":"AO",
    "name:und_x_variant":[
        "Sabataca"
    ],
    "wof:name":"Taca",
    "wof:placetype":"locality"
},
  "geometry": {"coordinates":[17.40067,-8.63063],"type":"Point"}
}