{
  "type": "Feature",
  "properties": {
    "gn:admin1_code":"1.0",
    "gn:asciiname":"Chingongo",
    "gn:country_code":"AO",
    "gn:dem":1209,
    "gn:feature_class":"P",
    "gn:feature_code":"PPL",
    "gn:name":"Chingongo",
    "gn:population":0,
    "gn:timezone":"Africa/Luanda",
    "iso:country":"AO",
    "name:und_x_variant":[
        "Tchingongo",
        "Chingongo"
    ],
    "wof:name":"Chingongo",
    "wof:placetype":"locality"
},
  "geometry": {"coordinates":[14.5161,-12.31938],"type":"Point"}
}