{
  "type": "Feature",
  "properties": {
    "gn:admin1_code":"15.0",
    "gn:asciiname":"Candombe",
    "gn:country_code":"AO",
    "gn:dem":837,
    "gn:feature_class":"P",
    "gn:feature_code":"PPL",
    "gn:name":"Candombe",
    "gn:population":0,
    "gn:timezone":"Africa/Luanda",
    "iso:country":"AO",
    "wof:name":"Candombe",
    "wof:placetype":"locality"
},
  "geometry": {"coordinates":[15.06861,-7.59796],"type":"Point"}
}