{
  "type": "Feature",
  "properties": {
    "gn:admin1_code":"15.0",
    "gn:asciiname":"Candombe",
    "gn:country_code":"AO",
    "gn:dem":837,
    "gn:feature_class":"P",
    "gn:feature_code":"PPL",
    "gn:name":"Candombe",
    "gn:population":0,
    "gn:timezone":"Africa/Luanda",
    "iso:country":"AO",
    "name:bre_x_preferred":[
        "Candombe"
    ],
    "name:cat_x_preferred":[
        "Candombe"
    ],
    "name:deu_x_preferred":[
        "Candombe"
    ],
    "name:fas_x_preferred":[
        "\u06a9\u0627\u0646\u062f\u0648\u0645\u0628\u0647"
    ],
    "name:fin_x_preferred":[
        "Candombe"
    ],
    "name:fra_x_preferred":[
        "Candombe"
    ],
    "name:jpn_x_preferred":[
        "\u30ab\u30f3\u30c9\u30f3\u30d9"
    ],
    "name:nld_x_preferred":[
        "Candombe"
    ],
    "name:pol_x_preferred":[
        "Candombe"
    ],
    "name:por_x_preferred":[
        "Candombe"
    ],
    "name:spa_x_preferred":[
        "Candombe"
    ],
    "name:swe_x_preferred":[
        "Candombe"
    ],
    "name:tur_x_preferred":[
        "Candombe"
    ],
    "wof:name":"Candombe",
    "wof:placetype":"locality"
},
  "geometry": {"coordinates":[15.06861,-7.59796],"type":"Point"}
}