{
  "type": "Feature",
  "properties": {
    "gn:admin1_code":"12.0",
    "gn:asciiname":"Quiluangi Cambala",
    "gn:country_code":"AO",
    "gn:dem":1011,
    "gn:feature_class":"P",
    "gn:feature_code":"PPL",
    "gn:name":"Quiluangi Cambala",
    "gn:population":0,
    "gn:timezone":"Africa/Luanda",
    "iso:country":"AO",
    "wof:name":"Quiluangi Cambala",
    "wof:placetype":"locality"
},
  "geometry": {"coordinates":[17.07597,-9.06201],"type":"Point"}
}