{
  "type": "Feature",
  "properties": {
    "gn:admin1_code":"6.0",
    "gn:asciiname":"Ngango",
    "gn:country_code":"AO",
    "gn:dem":1525,
    "gn:feature_class":"P",
    "gn:feature_code":"PPL",
    "gn:name":"Ngango",
    "gn:population":0,
    "gn:timezone":"Africa/Luanda",
    "iso:country":"AO",
    "wof:name":"Ngango",
    "wof:placetype":"locality"
},
  "geometry": {"coordinates":[15.8944,-10.60412],"type":"Point"}
}