{
  "type": "Feature",
  "properties": {
    "gn:admin1_code":"1.0",
    "gn:asciiname":"Chindumbo",
    "gn:country_code":"AO",
    "gn:dem":1391,
    "gn:feature_class":"P",
    "gn:feature_code":"PPL",
    "gn:name":"Chindumbo",
    "gn:population":0,
    "gn:timezone":"Africa/Luanda",
    "iso:country":"AO",
    "wof:name":"Chindumbo",
    "wof:placetype":"locality"
},
  "geometry": {"coordinates":[14.94646,-12.46776],"type":"Point"}
}