{
  "type": "Feature",
  "properties": {
    "gn:admin1_code":"12.0",
    "gn:asciiname":"Zeco",
    "gn:country_code":"AO",
    "gn:dem":1138,
    "gn:feature_class":"P",
    "gn:feature_code":"PPL",
    "gn:name":"Zeco",
    "gn:population":0,
    "gn:timezone":"Africa/Luanda",
    "iso:country":"AO",
    "wof:name":"Zeco",
    "wof:placetype":"locality"
},
  "geometry": {"coordinates":[17.16667,-10.35],"type":"Point"}
}