{
  "type": "Feature",
  "properties": {
    "gn:admin1_code":"17.0",
    "gn:asciiname":"Cataila Segundo",
    "gn:country_code":"AO",
    "gn:dem":706,
    "gn:feature_class":"P",
    "gn:feature_code":"PPL",
    "gn:name":"Cataila Segundo",
    "gn:population":0,
    "gn:timezone":"Africa/Luanda",
    "iso:country":"AO",
    "wof:name":"Cataila Segundo",
    "wof:placetype":"locality"
},
  "geometry": {"coordinates":[21.41851,-7.67592],"type":"Point"}
}