{
  "type": "Feature",
  "properties": {
    "gn:admin1_code":"12.0",
    "gn:asciiname":"Samuel",
    "gn:country_code":"AO",
    "gn:dem":1141,
    "gn:feature_class":"P",
    "gn:feature_code":"PPL",
    "gn:name":"Samuel",
    "gn:population":0,
    "gn:timezone":"Africa/Luanda",
    "iso:country":"AO",
    "wof:name":"Samuel",
    "wof:placetype":"locality"
},
  "geometry": {"coordinates":[16.35994,-9.36192],"type":"Point"}
}