{
  "type": "Feature",
  "properties": {
    "gn:admin1_code":"2.0",
    "gn:asciiname":"Belmonte",
    "gn:country_code":"AO",
    "gn:dem":1505,
    "gn:feature_class":"P",
    "gn:feature_code":"PPL",
    "gn:name":"Belmonte",
    "gn:population":0,
    "gn:timezone":"Africa/Luanda",
    "iso:country":"AO",
    "name:bpy_x_preferred":[
        "\u09ac\u09c7\u09b2\u09ae\u09cb\u09a8\u09cd\u099f\u09c7"
    ],
    "name:bre_x_preferred":[
        "Belmonte"
    ],
    "name:cat_x_preferred":[
        "Belmonte"
    ],
    "name:ceb_x_preferred":[
        "Belmonte"
    ],
    "name:deu_x_preferred":[
        "Belmonte"
    ],
    "name:epo_x_preferred":[
        "Belmonte"
    ],
    "name:eus_x_preferred":[
        "Belmonte"
    ],
    "name:fin_x_preferred":[
        "Belmonte"
    ],
    "name:fra_x_preferred":[
        "Belmonte"
    ],
    "name:glg_x_preferred":[
        "Belmonte"
    ],
    "name:hun_x_preferred":[
        "Belmonte"
    ],
    "name:ita_x_preferred":[
        "Belmonte"
    ],
    "name:msa_x_preferred":[
        "Belmonte"
    ],
    "name:nld_x_preferred":[
        "Belmonte"
    ],
    "name:nor_x_preferred":[
        "Belmonte"
    ],
    "name:oci_x_preferred":[
        "Belmonte"
    ],
    "name:pol_x_preferred":[
        "Belmonte"
    ],
    "name:por_x_preferred":[
        "Belmonte"
    ],
    "name:rus_x_preferred":[
        "\u0411\u0435\u043b\u043c\u043e\u043d\u0442\u0438"
    ],
    "name:sco_x_preferred":[
        "Belmonte"
    ],
    "name:spa_x_preferred":[
        "Belmonte"
    ],
    "name:swe_x_preferred":[
        "Belmonte"
    ],
    "name:ukr_x_preferred":[
        "\u0411\u0435\u043b\u043c\u043e\u043d\u0442\u0435"
    ],
    "name:uzb_x_preferred":[
        "Belmonte"
    ],
    "name:vie_x_preferred":[
        "Belmonte"
    ],
    "name:vol_x_preferred":[
        "Belmonte"
    ],
    "name:war_x_preferred":[
        "Belmonte"
    ],
    "wof:name":"Belmonte",
    "wof:placetype":"locality"
},
  "geometry": {"coordinates":[16.4062,-11.49191],"type":"Point"}
}