{
  "type": "Feature",
  "properties": {
    "gn:admin1_code":"2.0",
    "gn:asciiname":"Belmonte",
    "gn:country_code":"AO",
    "gn:dem":1505,
    "gn:feature_class":"P",
    "gn:feature_code":"PPL",
    "gn:name":"Belmonte",
    "gn:population":0,
    "gn:timezone":"Africa/Luanda",
    "iso:country":"AO",
    "wof:name":"Belmonte",
    "wof:placetype":"locality"
},
  "geometry": {"coordinates":[16.4062,-11.49191],"type":"Point"}
}