{
  "type": "Feature",
  "properties": {
    "gn:admin1_code":"12.0",
    "gn:asciiname":"Quizua",
    "gn:country_code":"AO",
    "gn:dem":959,
    "gn:feature_class":"P",
    "gn:feature_code":"PPL",
    "gn:name":"Quizua",
    "gn:population":0,
    "gn:timezone":"Africa/Luanda",
    "iso:country":"AO",
    "wof:name":"Quizua",
    "wof:placetype":"locality"
},
  "geometry": {"coordinates":[18.36069,-9.97117],"type":"Point"}
}