{
  "type": "Feature",
  "properties": {
    "gn:admin1_code":"12.0",
    "gn:asciiname":"Mbundi",
    "gn:country_code":"AO",
    "gn:dem":1102,
    "gn:feature_class":"P",
    "gn:feature_code":"PPL",
    "gn:name":"Mbundi",
    "gn:population":0,
    "gn:timezone":"Africa/Luanda",
    "iso:country":"AO",
    "name:und_x_variant":[
        "Mulamba"
    ],
    "wof:name":"Mbundi",
    "wof:placetype":"locality"
},
  "geometry": {"coordinates":[16.8173,-10.05468],"type":"Point"}
}