{
  "type": "Feature",
  "properties": {
    "gn:admin1_code":"14.0",
    "gn:asciiname":"Canjonja",
    "gn:country_code":"AO",
    "gn:dem":1080,
    "gn:feature_class":"P",
    "gn:feature_code":"PPL",
    "gn:name":"Canjonja",
    "gn:population":0,
    "gn:timezone":"Africa/Luanda",
    "iso:country":"AO",
    "wof:name":"Canjonja",
    "wof:placetype":"locality"
},
  "geometry": {"coordinates":[21.31667,-15.31667],"type":"Point"}
}