{
  "type": "Feature",
  "properties": {
    "gn:admin1_code":"8.0",
    "gn:asciiname":"Caloenge",
    "gn:country_code":"AO",
    "gn:dem":1581,
    "gn:feature_class":"P",
    "gn:feature_code":"PPL",
    "gn:name":"Caloenge",
    "gn:population":0,
    "gn:timezone":"Africa/Luanda",
    "iso:country":"AO",
    "wof:name":"Caloenge",
    "wof:placetype":"locality"
},
  "geometry": {"coordinates":[16.25,-11.95],"type":"Point"}
}