{
  "type": "Feature",
  "properties": {
    "gn:admin1_code":"12.0",
    "gn:asciiname":"Macala",
    "gn:country_code":"AO",
    "gn:dem":1234,
    "gn:feature_class":"P",
    "gn:feature_code":"PPL",
    "gn:name":"Macala",
    "gn:population":0,
    "gn:timezone":"Africa/Luanda",
    "iso:country":"AO",
    "name:und_x_variant":[
        "Munana",
        "Menana",
        "Macala"
    ],
    "wof:name":"Macala",
    "wof:placetype":"locality"
},
  "geometry": {"coordinates":[16.41228,-8.85622],"type":"Point"}
}