{
  "type": "Feature",
  "properties": {
    "gn:admin1_code":"6.0",
    "gn:asciiname":"Quilala",
    "gn:country_code":"AO",
    "gn:dem":1339,
    "gn:feature_class":"P",
    "gn:feature_code":"PPL",
    "gn:name":"Quilala",
    "gn:population":0,
    "gn:timezone":"Africa/Luanda",
    "iso:country":"AO",
    "wof:name":"Quilala",
    "wof:placetype":"locality"
},
  "geometry": {"coordinates":[15.02395,-10.75509],"type":"Point"}
}