{
  "type": "Feature",
  "properties": {
    "gn:admin1_code":"5.0",
    "gn:asciiname":"Calumbo",
    "gn:country_code":"AO",
    "gn:dem":866,
    "gn:feature_class":"P",
    "gn:feature_code":"PPL",
    "gn:name":"Calumbo",
    "gn:population":0,
    "gn:timezone":"Africa/Luanda",
    "iso:country":"AO",
    "name:cat_x_preferred":[
        "Calumbo"
    ],
    "name:por_x_preferred":[
        "Calumbo"
    ],
    "wof:name":"Calumbo",
    "wof:placetype":"locality"
},
  "geometry": {"coordinates":[15.26589,-8.3171],"type":"Point"}
}