{
  "type": "Feature",
  "properties": {
    "gn:admin1_code":"15.0",
    "gn:asciiname":"Quissassa",
    "gn:country_code":"AO",
    "gn:dem":1071,
    "gn:feature_class":"P",
    "gn:feature_code":"PPL",
    "gn:name":"Quissassa",
    "gn:population":0,
    "gn:timezone":"Africa/Luanda",
    "iso:country":"AO",
    "name:und_x_variant":[
        "Quissossa"
    ],
    "wof:name":"Quissassa",
    "wof:placetype":"locality"
},
  "geometry": {"coordinates":[15.84395,-7.53265],"type":"Point"}
}