{
  "type": "Feature",
  "properties": {
    "gn:admin1_code":"16.0",
    "gn:asciiname":"Ncalambata",
    "gn:country_code":"AO",
    "gn:dem":576,
    "gn:feature_class":"P",
    "gn:feature_code":"PPL",
    "gn:name":"Ncalambata",
    "gn:population":0,
    "gn:timezone":"Africa/Luanda",
    "iso:country":"AO",
    "name:und_x_variant":[
        "Sanga",
        "Calambala",
        "Calambata",
        "Ncalambata"
    ],
    "wof:name":"Ncalambata",
    "wof:placetype":"locality"
},
  "geometry": {"coordinates":[14.34795,-6.19145],"type":"Point"}
}