{
  "type": "Feature",
  "properties": {
    "gn:admin1_code":"5.0",
    "gn:asciiname":"Quiboto",
    "gn:country_code":"AO",
    "gn:dem":810,
    "gn:feature_class":"P",
    "gn:feature_code":"PPL",
    "gn:name":"Quiboto",
    "gn:population":0,
    "gn:timezone":"Africa/Luanda",
    "iso:country":"AO",
    "name:und_x_variant":[
        "Quibuto",
        "Quiboto"
    ],
    "wof:name":"Quiboto",
    "wof:placetype":"locality"
},
  "geometry": {"coordinates":[15.26747,-8.47628],"type":"Point"}
}