{
  "type": "Feature",
  "properties": {
    "gn:admin1_code":"1.0",
    "gn:asciiname":"Tive",
    "gn:cc2":"AO",
    "gn:country_code":"AO",
    "gn:dem":695,
    "gn:feature_class":"P",
    "gn:feature_code":"PPL",
    "gn:name":"Tiv\u00e9",
    "gn:population":0,
    "gn:timezone":"Africa/Luanda",
    "iso:country":"AO",
    "name:und_x_variant":[
        "Tiu\u00e9",
        "Tiv\u00e9"
    ],
    "wof:name":"Tive",
    "wof:placetype":"locality"
},
  "geometry": {"coordinates":[13.35,-13.36667],"type":"Point"}
}