{
  "type": "Feature",
  "properties": {
    "gn:admin1_code":"5.0",
    "gn:asciiname":"Lialala",
    "gn:country_code":"AO",
    "gn:dem":1215,
    "gn:feature_class":"P",
    "gn:feature_code":"PPL",
    "gn:name":"Lialala",
    "gn:population":0,
    "gn:timezone":"Africa/Luanda",
    "iso:country":"AO",
    "wof:name":"Lialala",
    "wof:placetype":"locality"
},
  "geometry": {"coordinates":[15.56667,-8.06667],"type":"Point"}
}