{
  "type": "Feature",
  "properties": {
    "gn:admin1_code":"3.0",
    "gn:asciiname":"Tanda Matiaba",
    "gn:cc2":"AO",
    "gn:country_code":"AO",
    "gn:dem":217,
    "gn:feature_class":"P",
    "gn:feature_code":"PPL",
    "gn:name":"Tanda Matiaba",
    "gn:population":0,
    "gn:timezone":"Africa/Luanda",
    "iso:country":"AO",
    "name:und_x_variant":[
        "Tando Matiaba",
        "Tota Hola",
        "Tota Ola",
        "Tanda Matiaba"
    ],
    "wof:name":"Tanda Matiaba",
    "wof:placetype":"locality"
},
  "geometry": {"coordinates":[12.71667,-4.76667],"type":"Point"}
}