{
  "type": "Feature",
  "properties": {
    "gn:admin1_code":"16.0",
    "gn:asciiname":"Banza",
    "gn:country_code":"AO",
    "gn:dem":534,
    "gn:feature_class":"P",
    "gn:feature_code":"PPL",
    "gn:name":"Banza",
    "gn:population":0,
    "gn:timezone":"Africa/Luanda",
    "iso:country":"AO",
    "wof:name":"Banza",
    "wof:placetype":"locality"
},
  "geometry": {"coordinates":[14.06667,-6.66667],"type":"Point"}
}