{
  "type": "Feature",
  "properties": {
    "gn:admin1_code":"6.0",
    "gn:asciiname":"Gonga",
    "gn:country_code":"AO",
    "gn:dem":1323,
    "gn:feature_class":"P",
    "gn:feature_code":"PPL",
    "gn:name":"Gonga",
    "gn:population":0,
    "gn:timezone":"Africa/Luanda",
    "iso:country":"AO",
    "wof:name":"Gonga",
    "wof:placetype":"locality"
},
  "geometry": {"coordinates":[15.11667,-11.66667],"type":"Point"}
}