{
  "type": "Feature",
  "properties": {
    "gn:admin1_code":"14.0",
    "gn:asciiname":"Tobola",
    "gn:country_code":"AO",
    "gn:dem":1083,
    "gn:feature_class":"P",
    "gn:feature_code":"PPL",
    "gn:name":"Tobola",
    "gn:population":0,
    "gn:timezone":"Africa/Luanda",
    "iso:country":"AO",
    "wof:name":"Tobola",
    "wof:placetype":"locality"
},
  "geometry": {"coordinates":[21.56667,-15.43333],"type":"Point"}
}