{
  "type": "Feature",
  "properties": {
    "gn:admin1_code":"15.0",
    "gn:asciiname":"Cuilo Futa",
    "gn:country_code":"AO",
    "gn:dem":791,
    "gn:feature_class":"P",
    "gn:feature_code":"PPL",
    "gn:name":"Cuilo Futa",
    "gn:population":0,
    "gn:timezone":"Africa/Luanda",
    "iso:country":"AO",
    "name:und_x_variant":[
        "Cuila Futa",
        "Cuilo Futa"
    ],
    "wof:name":"Cuilo Futa",
    "wof:placetype":"locality"
},
  "geometry": {"coordinates":[15.72873,-6.42505],"type":"Point"}
}