{
  "type": "Feature",
  "properties": {
    "gn:admin1_code":"12.0",
    "gn:asciiname":"Tumba",
    "gn:country_code":"AO",
    "gn:dem":1163,
    "gn:feature_class":"P",
    "gn:feature_code":"PPL",
    "gn:name":"Tumba",
    "gn:population":0,
    "gn:timezone":"Africa/Luanda",
    "iso:country":"AO",
    "wof:name":"Tumba",
    "wof:placetype":"locality"
},
  "geometry": {"coordinates":[17.03424,-9.81358],"type":"Point"}
}