{
  "type": "Feature",
  "properties": {
    "gn:admin1_code":"15.0",
    "gn:asciiname":"Cuale",
    "gn:country_code":"AO",
    "gn:dem":706,
    "gn:feature_class":"P",
    "gn:feature_code":"PPL",
    "gn:name":"Cuale",
    "gn:population":0,
    "gn:timezone":"Africa/Luanda",
    "iso:country":"AO",
    "name:por_x_preferred":[
        "Cuale"
    ],
    "wof:name":"Cuale",
    "wof:placetype":"locality"
},
  "geometry": {"coordinates":[15.03701,-7.89655],"type":"Point"}
}