{
  "type": "Feature",
  "properties": {
    "gn:admin1_code":"15.0",
    "gn:asciiname":"Mbanza Bata Quimocondo",
    "gn:country_code":"AO",
    "gn:dem":845,
    "gn:feature_class":"P",
    "gn:feature_code":"PPL",
    "gn:name":"Mbanza Bata Quimocondo",
    "gn:population":0,
    "gn:timezone":"Africa/Luanda",
    "iso:country":"AO",
    "name:und_x_variant":[
        "Banza Quimocondo"
    ],
    "wof:name":"Mbanza Bata Quimocondo",
    "wof:placetype":"locality"
},
  "geometry": {"coordinates":[15.23618,-6.07094],"type":"Point"}
}