{
  "type": "Feature",
  "properties": {
    "gn:admin1_code":"5.0",
    "gn:asciiname":"Cacala",
    "gn:country_code":"AO",
    "gn:dem":1219,
    "gn:feature_class":"P",
    "gn:feature_code":"PPL",
    "gn:name":"Cacala",
    "gn:population":0,
    "gn:timezone":"Africa/Luanda",
    "iso:country":"AO",
    "wof:name":"Cacala",
    "wof:placetype":"locality"
},
  "geometry": {"coordinates":[15.66891,-8.7153],"type":"Point"}
}