{
  "type": "Feature",
  "properties": {
    "gn:admin1_code":"15.0",
    "gn:asciiname":"Quimbulo",
    "gn:country_code":"AO",
    "gn:dem":506,
    "gn:feature_class":"P",
    "gn:feature_code":"PPL",
    "gn:name":"Quimbulo",
    "gn:population":0,
    "gn:timezone":"Africa/Luanda",
    "iso:country":"AO",
    "wof:name":"Quimbulo",
    "wof:placetype":"locality"
},
  "geometry": {"coordinates":[17.05653,-7.38427],"type":"Point"}
}