{
  "type": "Feature",
  "properties": {
    "gn:admin1_code":"12.0",
    "gn:asciiname":"Cuango",
    "gn:country_code":"AO",
    "gn:dem":1085,
    "gn:feature_class":"P",
    "gn:feature_code":"PPL",
    "gn:name":"Cuango",
    "gn:population":0,
    "gn:timezone":"Africa/Luanda",
    "iso:country":"AO",
    "wof:name":"Cuango",
    "wof:placetype":"locality"
},
  "geometry": {"coordinates":[16.214,-9.46024],"type":"Point"}
}