{
  "type": "Feature",
  "properties": {
    "gn:admin1_code":"17.0",
    "gn:asciiname":"Muanzanza",
    "gn:country_code":"AO",
    "gn:dem":1198,
    "gn:feature_class":"P",
    "gn:feature_code":"PPL",
    "gn:name":"Muanzanza",
    "gn:population":0,
    "gn:timezone":"Africa/Luanda",
    "iso:country":"AO",
    "wof:name":"Muanzanza",
    "wof:placetype":"locality"
},
  "geometry": {"coordinates":[18.73126,-8.24476],"type":"Point"}
}