{
  "type": "Feature",
  "properties": {
    "gn:admin1_code":"9.0",
    "gn:admin2_code":"3347760.0",
    "gn:asciiname":"Quilemba",
    "gn:country_code":"AO",
    "gn:dem":1935,
    "gn:feature_class":"P",
    "gn:feature_code":"PPL",
    "gn:name":"Quilemba",
    "gn:population":0,
    "gn:timezone":"Africa/Luanda",
    "iso:country":"AO",
    "name:ceb_x_preferred":[
        "Quilemba"
    ],
    "name:swe_x_preferred":[
        "Quilemba"
    ],
    "wof:name":"Quilemba",
    "wof:placetype":"locality"
},
  "geometry": {"coordinates":[13.48053,-14.77766],"type":"Point"}
}