{
  "type": "Feature",
  "properties": {
    "gn:admin1_code":"4.0",
    "gn:asciiname":"Baixo Longa",
    "gn:cc2":"AO",
    "gn:country_code":"AO",
    "gn:dem":1214,
    "gn:feature_class":"P",
    "gn:feature_code":"PPL",
    "gn:name":"Baixo Longa",
    "gn:population":0,
    "gn:timezone":"Africa/Luanda",
    "iso:country":"AO",
    "name:por_x_preferred":[
        "Baixo Longa"
    ],
    "name:und_x_variant":[
        "Longa",
        "Baishu Longa",
        "Baizo Longa",
        "Baixo Longa"
    ],
    "wof:name":"Baixo Longa",
    "wof:placetype":"locality"
},
  "geometry": {"coordinates":[18.66667,-15.68333],"type":"Point"}
}