{
  "type": "Feature",
  "properties": {
    "gn:admin1_code":"15.0",
    "gn:asciiname":"Vuanga",
    "gn:country_code":"AO",
    "gn:dem":914,
    "gn:feature_class":"P",
    "gn:feature_code":"PPL",
    "gn:name":"Vuanga",
    "gn:population":0,
    "gn:timezone":"Africa/Luanda",
    "iso:country":"AO",
    "wof:name":"Vuanga",
    "wof:placetype":"locality"
},
  "geometry": {"coordinates":[15.09306,-6.08383],"type":"Point"}
}