{
  "type": "Feature",
  "properties": {
    "gn:admin1_code":"5.0",
    "gn:asciiname":"Cahima",
    "gn:country_code":"AO",
    "gn:dem":1299,
    "gn:feature_class":"P",
    "gn:feature_code":"PPL",
    "gn:name":"Cahima",
    "gn:population":0,
    "gn:timezone":"Africa/Luanda",
    "iso:country":"AO",
    "name:und_x_variant":[
        "Caima"
    ],
    "wof:name":"Cahima",
    "wof:placetype":"locality"
},
  "geometry": {"coordinates":[15.49701,-8.49716],"type":"Point"}
}