{
  "type": "Feature",
  "properties": {
    "gn:admin1_code":"15.0",
    "gn:asciiname":"Miguel",
    "gn:country_code":"AO",
    "gn:dem":789,
    "gn:feature_class":"P",
    "gn:feature_code":"PPL",
    "gn:name":"Miguel",
    "gn:population":0,
    "gn:timezone":"Africa/Luanda",
    "iso:country":"AO",
    "wof:name":"Miguel",
    "wof:placetype":"locality"
},
  "geometry": {"coordinates":[16.18112,-7.33248],"type":"Point"}
}