{
  "type": "Feature",
  "properties": {
    "gn:admin1_code":"1.0",
    "gn:asciiname":"Ndala",
    "gn:country_code":"AO",
    "gn:dem":61,
    "gn:feature_class":"P",
    "gn:feature_code":"PPL",
    "gn:name":"Ndala",
    "gn:population":0,
    "gn:timezone":"Africa/Luanda",
    "iso:country":"AO",
    "wof:name":"Ndala",
    "wof:placetype":"locality"
},
  "geometry": {"coordinates":[13.28167,-12.63639],"type":"Point"}
}