{
  "type": "Feature",
  "properties": {
    "gn:admin1_code":"15.0",
    "gn:asciiname":"Talambanza",
    "gn:country_code":"AO",
    "gn:dem":741,
    "gn:feature_class":"P",
    "gn:feature_code":"PPL",
    "gn:name":"Talambanza",
    "gn:population":0,
    "gn:timezone":"Africa/Luanda",
    "iso:country":"AO",
    "name:und_x_variant":[
        "Talabanza",
        "Talambanza"
    ],
    "wof:name":"Talambanza",
    "wof:placetype":"locality"
},
  "geometry": {"coordinates":[15.04291,-7.92187],"type":"Point"}
}