{
  "type": "Feature",
  "properties": {
    "gn:admin1_code":"8.0",
    "gn:asciiname":"Chicucuma",
    "gn:cc2":"AO",
    "gn:country_code":"AO",
    "gn:dem":1787,
    "gn:feature_class":"P",
    "gn:feature_code":"PPL",
    "gn:name":"Chicucuma",
    "gn:population":0,
    "gn:timezone":"Africa/Luanda",
    "iso:country":"AO",
    "name:und_x_variant":[
        "Txima",
        "Tchima",
        "Chicucuma"
    ],
    "wof:name":"Chicucuma",
    "wof:placetype":"locality"
},
  "geometry": {"coordinates":[15.66667,-12.66667],"type":"Point"}
}