{
  "type": "Feature",
  "properties": {
    "gn:admin1_code":"12.0",
    "gn:asciiname":"Cambo Camana",
    "gn:country_code":"AO",
    "gn:dem":894,
    "gn:feature_class":"P",
    "gn:feature_code":"PPL",
    "gn:name":"Cambo Camana",
    "gn:population":0,
    "gn:timezone":"Africa/Luanda",
    "iso:country":"AO",
    "name:und_x_variant":[
        "Kambo Kamana",
        "Cambo Canana",
        "Cambo Camana"
    ],
    "wof:name":"Cambo Camana",
    "wof:placetype":"locality"
},
  "geometry": {"coordinates":[16.63599,-8.84917],"type":"Point"}
}