{
  "type": "Feature",
  "properties": {
    "gn:admin1_code":"4.0",
    "gn:asciiname":"Calola",
    "gn:cc2":"AO",
    "gn:country_code":"AO",
    "gn:dem":1127,
    "gn:feature_class":"P",
    "gn:feature_code":"PPL",
    "gn:name":"Calola",
    "gn:population":0,
    "gn:timezone":"Africa/Luanda",
    "iso:country":"AO",
    "name:und_x_variant":[
        "Culola",
        "Calola"
    ],
    "wof:name":"Calola",
    "wof:placetype":"locality"
},
  "geometry": {"coordinates":[18.23333,-17.13332999999999],"type":"Point"}
}