{
  "type": "Feature",
  "properties": {
    "gn:admin1_code":"16.0",
    "gn:asciiname":"Quimpungo",
    "gn:country_code":"AO",
    "gn:dem":111,
    "gn:feature_class":"P",
    "gn:feature_code":"PPL",
    "gn:name":"Quimpungo",
    "gn:population":0,
    "gn:timezone":"Africa/Luanda",
    "iso:country":"AO",
    "wof:name":"Quimpungo",
    "wof:placetype":"locality"
},
  "geometry": {"coordinates":[13.25,-5.96667],"type":"Point"}
}