{
  "type": "Feature",
  "properties": {
    "gn:admin1_code":"2.0",
    "gn:asciiname":"Caxitele",
    "gn:country_code":"AO",
    "gn:dem":1598,
    "gn:feature_class":"P",
    "gn:feature_code":"PPL",
    "gn:name":"Caxitele",
    "gn:population":0,
    "gn:timezone":"Africa/Luanda",
    "iso:country":"AO",
    "wof:name":"Caxitele",
    "wof:placetype":"locality"
},
  "geometry": {"coordinates":[16.65502,-11.48679],"type":"Point"}
}