{
  "type": "Feature",
  "properties": {
    "gn:admin1_code":"1.0",
    "gn:asciiname":"Cuhula",
    "gn:country_code":"AO",
    "gn:dem":134,
    "gn:feature_class":"P",
    "gn:feature_code":"PPL",
    "gn:name":"Cuhula",
    "gn:population":0,
    "gn:timezone":"Africa/Luanda",
    "iso:country":"AO",
    "wof:name":"Cuhula",
    "wof:placetype":"locality"
},
  "geometry": {"coordinates":[13.72557,-12.05358],"type":"Point"}
}