{
  "type": "Feature",
  "properties": {
    "gn:admin1_code":"12.0",
    "gn:asciiname":"Dambi",
    "gn:country_code":"AO",
    "gn:dem":1102,
    "gn:feature_class":"P",
    "gn:feature_code":"PPL",
    "gn:name":"Dambi",
    "gn:population":0,
    "gn:timezone":"Africa/Luanda",
    "iso:country":"AO",
    "wof:name":"Dambi",
    "wof:placetype":"locality"
},
  "geometry": {"coordinates":[16.11713,-9.46794],"type":"Point"}
}