{
  "type": "Feature",
  "properties": {
    "gn:admin1_code":"15.0",
    "gn:asciiname":"Uembo",
    "gn:country_code":"AO",
    "gn:dem":862,
    "gn:feature_class":"P",
    "gn:feature_code":"PPL",
    "gn:name":"Uembo",
    "gn:population":0,
    "gn:timezone":"Africa/Luanda",
    "iso:country":"AO",
    "wof:name":"Uembo",
    "wof:placetype":"locality"
},
  "geometry": {"coordinates":[15.11667,-6.06667],"type":"Point"}
}