{
  "type": "Feature",
  "properties": {
    "gn:admin1_code":"12.0",
    "gn:asciiname":"Queta",
    "gn:country_code":"AO",
    "gn:dem":1116,
    "gn:feature_class":"P",
    "gn:feature_code":"PPL",
    "gn:name":"Queta",
    "gn:population":0,
    "gn:timezone":"Africa/Luanda",
    "iso:country":"AO",
    "wof:name":"Queta",
    "wof:placetype":"locality"
},
  "geometry": {"coordinates":[16.12094,-8.13057],"type":"Point"}
}