{
  "type": "Feature",
  "properties": {
    "gn:admin1_code":"16.0",
    "gn:asciiname":"Sacambunge",
    "gn:country_code":"AO",
    "gn:dem":1137,
    "gn:feature_class":"P",
    "gn:feature_code":"PPL",
    "gn:name":"Sacambunge",
    "gn:population":0,
    "gn:timezone":"Africa/Luanda",
    "iso:country":"AO",
    "wof:name":"Sacambunge",
    "wof:placetype":"locality"
},
  "geometry": {"coordinates":[20.4498,-10.2615],"type":"Point"}
}