{
  "type": "Feature",
  "properties": {
    "gn:admin1_code":"16.0",
    "gn:asciiname":"Cumba",
    "gn:cc2":"AO",
    "gn:country_code":"AO",
    "gn:dem":521,
    "gn:feature_class":"P",
    "gn:feature_code":"PPL",
    "gn:name":"Cumba",
    "gn:population":0,
    "gn:timezone":"Africa/Luanda",
    "iso:country":"AO",
    "name:und_x_variant":[
        "Comba",
        "Cumba"
    ],
    "wof:name":"Cumba",
    "wof:placetype":"locality"
},
  "geometry": {"coordinates":[14.73333,-5.98333],"type":"Point"}
}