{
  "type": "Feature",
  "properties": {
    "gn:admin1_code":"4.0",
    "gn:asciiname":"Tueja",
    "gn:cc2":"AO",
    "gn:country_code":"AO",
    "gn:dem":1012,
    "gn:feature_class":"P",
    "gn:feature_code":"PPL",
    "gn:name":"Tueja",
    "gn:population":0,
    "gn:timezone":"Africa/Luanda",
    "iso:country":"AO",
    "name:und_x_variant":[
        "Tueya",
        "Tueja"
    ],
    "wof:name":"Tueja",
    "wof:placetype":"locality"
},
  "geometry": {"coordinates":[22.36667000000001,-17.41667],"type":"Point"}
}