{
  "type": "Feature",
  "properties": {
    "gn:admin1_code":"16.0",
    "gn:asciiname":"Sange",
    "gn:cc2":"AO",
    "gn:country_code":"AO",
    "gn:dem":394,
    "gn:feature_class":"P",
    "gn:feature_code":"PPL",
    "gn:name":"Sange",
    "gn:population":0,
    "gn:timezone":"Africa/Luanda",
    "iso:country":"AO",
    "name:ceb_x_preferred":[
        "Sange"
    ],
    "name:deu_x_preferred":[
        "Sange"
    ],
    "name:fra_x_preferred":[
        "Sange"
    ],
    "name:swe_x_preferred":[
        "Sange"
    ],
    "name:und_x_variant":[
        "Kionzo",
        "Coinzo",
        "Sange"
    ],
    "wof:name":"Sange",
    "wof:placetype":"locality"
},
  "geometry": {"coordinates":[13.66667,-6.16667],"type":"Point"}
}