{
  "type": "Feature",
  "properties": {
    "gn:admin1_code":"9.0",
    "gn:asciiname":"Catala",
    "gn:cc2":"AO",
    "gn:country_code":"AO",
    "gn:dem":1502,
    "gn:feature_class":"P",
    "gn:feature_code":"PPL",
    "gn:name":"Catala",
    "gn:population":0,
    "gn:timezone":"Africa/Luanda",
    "iso:country":"AO",
    "name:und_x_variant":[
        "Catula",
        "Catala"
    ],
    "wof:name":"Catala",
    "wof:placetype":"locality"
},
  "geometry": {"coordinates":[16.35,-14.31667],"type":"Point"}
}