{
  "type": "Feature",
  "properties": {
    "gn:admin1_code":"18.0",
    "gn:asciiname":"Mualucanda",
    "gn:country_code":"AO",
    "gn:dem":1352,
    "gn:feature_class":"P",
    "gn:feature_code":"PPL",
    "gn:name":"Mualucanda",
    "gn:population":0,
    "gn:timezone":"Africa/Luanda",
    "iso:country":"AO",
    "wof:name":"Mualucanda",
    "wof:placetype":"locality"
},
  "geometry": {"coordinates":[19.36276,-10.27103],"type":"Point"}
}