{
  "type": "Feature",
  "properties": {
    "gn:admin1_code":"15.0",
    "gn:asciiname":"Quifulo",
    "gn:country_code":"AO",
    "gn:dem":971,
    "gn:feature_class":"P",
    "gn:feature_code":"PPL",
    "gn:name":"Quifulo",
    "gn:population":0,
    "gn:timezone":"Africa/Luanda",
    "iso:country":"AO",
    "wof:name":"Quifulo",
    "wof:placetype":"locality"
},
  "geometry": {"coordinates":[16.07109,-7.5972],"type":"Point"}
}