{
  "type": "Feature",
  "properties": {
    "gn:admin1_code":"15.0",
    "gn:asciiname":"Quimansanga",
    "gn:country_code":"AO",
    "gn:dem":1072,
    "gn:feature_class":"P",
    "gn:feature_code":"PPLL",
    "gn:name":"Quimansanga",
    "gn:population":0,
    "gn:timezone":"Africa/Luanda",
    "iso:country":"AO",
    "wof:name":"Quimansanga",
    "wof:placetype":"locality"
},
  "geometry": {"coordinates":[15.8276,-7.69441],"type":"Point"}
}