{
  "type": "Feature",
  "properties": {
    "gn:admin1_code":"8.0",
    "gn:asciiname":"Mangonga I",
    "gn:country_code":"AO",
    "gn:dem":1844,
    "gn:feature_class":"P",
    "gn:feature_code":"PPL",
    "gn:name":"Mangonga I",
    "gn:population":0,
    "gn:timezone":"Africa/Luanda",
    "iso:country":"AO",
    "wof:name":"Mangonga I",
    "wof:placetype":"locality"
},
  "geometry": {"coordinates":[15.40611,-12.83639],"type":"Point"}
}