{
  "type": "Feature",
  "properties": {
    "gn:admin1_code":"8.0",
    "gn:asciiname":"Candingo II",
    "gn:country_code":"AO",
    "gn:dem":1641,
    "gn:feature_class":"P",
    "gn:feature_code":"PPL",
    "gn:name":"Candingo II",
    "gn:population":0,
    "gn:timezone":"Africa/Luanda",
    "iso:country":"AO",
    "wof:name":"Candingo II",
    "wof:placetype":"locality"
},
  "geometry": {"coordinates":[15.47917,-12.54139],"type":"Point"}
}