{
  "type": "Feature",
  "properties": {
    "gn:admin1_code":"5.0",
    "gn:asciiname":"Tonhe Angola",
    "gn:country_code":"AO",
    "gn:dem":1319,
    "gn:feature_class":"P",
    "gn:feature_code":"PPL",
    "gn:name":"Tonhe Angola",
    "gn:population":0,
    "gn:timezone":"Africa/Luanda",
    "iso:country":"AO",
    "wof:name":"Tonhe Angola",
    "wof:placetype":"locality"
},
  "geometry": {"coordinates":[15.27243,-8.11868],"type":"Point"}
}