{
  "type": "Feature",
  "properties": {
    "gn:admin1_code":"12.0",
    "gn:asciiname":"Nzamba de Baixo",
    "gn:country_code":"AO",
    "gn:dem":994,
    "gn:feature_class":"P",
    "gn:feature_code":"PPL",
    "gn:name":"Nzamba de Baixo",
    "gn:population":0,
    "gn:timezone":"Africa/Luanda",
    "iso:country":"AO",
    "wof:name":"Nzamba de Baixo",
    "wof:placetype":"locality"
},
  "geometry": {"coordinates":[15.67861,-9.30315],"type":"Point"}
}