{
  "type": "Feature",
  "properties": {
    "gn:admin1_code":"8.0",
    "gn:asciiname":"Nova Aurora",
    "gn:cc2":"AO",
    "gn:country_code":"AO",
    "gn:dem":1698,
    "gn:feature_class":"P",
    "gn:feature_code":"PPL",
    "gn:name":"Nova Aurora",
    "gn:population":0,
    "gn:timezone":"Africa/Luanda",
    "iso:country":"AO",
    "name:bpy_x_preferred":[
        "\u09a8\u09cb\u09ad\u09be \u0994\u09b0\u09cb\u09b0\u09be"
    ],
    "name:ceb_x_preferred":[
        "Nova Aurora"
    ],
    "name:deu_x_preferred":[
        "Nova Aurora"
    ],
    "name:ita_x_preferred":[
        "Nova Aurora"
    ],
    "name:nld_x_preferred":[
        "Nova Aurora"
    ],
    "name:nor_x_preferred":[
        "Nova Aurora"
    ],
    "name:por_x_preferred":[
        "Nova Aurora"
    ],
    "name:swe_x_preferred":[
        "Nova Aurora"
    ],
    "name:und_x_variant":[
        "Fazenda Nova Aurora",
        "Aurora",
        "Fazenda Aurora",
        "Auroca",
        "Fazenda N. Aurora",
        "Nova Aurora"
    ],
    "name:vie_x_preferred":[
        "Nova Aurora"
    ],
    "name:vol_x_preferred":[
        "Nova Aurora"
    ],
    "wof:name":"Nova Aurora",
    "wof:placetype":"locality"
},
  "geometry": {"coordinates":[15.96667,-11.96667],"type":"Point"}
}