{
  "type": "Feature",
  "properties": {
    "gn:admin1_code":"8.0",
    "gn:asciiname":"Nova Aurora",
    "gn:cc2":"AO",
    "gn:country_code":"AO",
    "gn:dem":1698,
    "gn:feature_class":"P",
    "gn:feature_code":"PPL",
    "gn:name":"Nova Aurora",
    "gn:population":0,
    "gn:timezone":"Africa/Luanda",
    "iso:country":"AO",
    "name:und_x_variant":[
        "Fazenda Nova Aurora",
        "Aurora",
        "Fazenda Aurora",
        "Auroca",
        "Fazenda N. Aurora",
        "Nova Aurora"
    ],
    "wof:name":"Nova Aurora",
    "wof:placetype":"locality"
},
  "geometry": {"coordinates":[15.96667,-11.96667],"type":"Point"}
}