{
  "type": "Feature",
  "properties": {
    "gn:admin1_code":"8.0",
    "gn:asciiname":"Cassoma",
    "gn:country_code":"AO",
    "gn:dem":1828,
    "gn:feature_class":"P",
    "gn:feature_code":"PPL",
    "gn:name":"Cassoma",
    "gn:population":0,
    "gn:timezone":"Africa/Luanda",
    "iso:country":"AO",
    "wof:name":"Cassoma",
    "wof:placetype":"locality"
},
  "geometry": {"coordinates":[15.52667,-12.86833],"type":"Point"}
}