{
  "type": "Feature",
  "properties": {
    "gn:admin1_code":"6.0",
    "gn:asciiname":"Cutemba",
    "gn:cc2":"AO",
    "gn:country_code":"AO",
    "gn:dem":821,
    "gn:feature_class":"P",
    "gn:feature_code":"PPL",
    "gn:name":"Cutemba",
    "gn:population":0,
    "gn:timezone":"Africa/Luanda",
    "iso:country":"AO",
    "name:und_x_variant":[
        "Culembe",
        "Cutemba"
    ],
    "wof:name":"Cutemba",
    "wof:placetype":"locality"
},
  "geometry": {"coordinates":[14.18333,-11.35],"type":"Point"}
}