{
  "type": "Feature",
  "properties": {
    "gn:admin1_code":"15.0",
    "gn:asciiname":"Benga",
    "gn:country_code":"AO",
    "gn:dem":760,
    "gn:feature_class":"P",
    "gn:feature_code":"PPL",
    "gn:name":"Benga",
    "gn:population":0,
    "gn:timezone":"Africa/Luanda",
    "iso:country":"AO",
    "name:ceb_x_preferred":[
        "Benga"
    ],
    "name:deu_x_preferred":[
        "Benga"
    ],
    "name:fin_x_preferred":[
        "Benga"
    ],
    "name:fra_x_preferred":[
        "Benga"
    ],
    "name:por_x_preferred":[
        "Benga"
    ],
    "name:ron_x_preferred":[
        "Benga"
    ],
    "name:swe_x_preferred":[
        "Benga"
    ],
    "wof:name":"Benga",
    "wof:placetype":"locality"
},
  "geometry": {"coordinates":[15.68096,-6.11184],"type":"Point"}
}