{
  "type": "Feature",
  "properties": {
    "gn:admin1_code":"17.0",
    "gn:asciiname":"Cabinda",
    "gn:cc2":"AO",
    "gn:country_code":"AO",
    "gn:dem":751,
    "gn:feature_class":"P",
    "gn:feature_code":"PPL",
    "gn:name":"Cabinda",
    "gn:population":0,
    "gn:timezone":"Africa/Luanda",
    "iso:country":"AO",
    "name:afr_x_preferred":[
        "Cabinda"
    ],
    "name:ast_x_preferred":[
        "Cabinda"
    ],
    "name:ceb_x_preferred":[
        "Cabinda"
    ],
    "name:cym_x_preferred":[
        "Cabinda"
    ],
    "name:deu_x_preferred":[
        "Cabinda"
    ],
    "name:frr_x_preferred":[
        "Cabinda"
    ],
    "name:ita_x_preferred":[
        "Cabinda"
    ],
    "name:lfn_x_preferred":[
        "Cabinda"
    ],
    "name:ltz_x_preferred":[
        "Cabinda"
    ],
    "name:nld_x_preferred":[
        "Cabinda"
    ],
    "name:nor_x_preferred":[
        "Cabinda"
    ],
    "name:por_x_preferred":[
        "Cabinda"
    ],
    "name:rus_x_preferred":[
        "\u041a\u0430\u0431\u0438\u043d\u0434\u0430"
    ],
    "name:spa_x_preferred":[
        "Cabinda"
    ],
    "name:swe_x_preferred":[
        "Cabinda"
    ],
    "name:tgl_x_preferred":[
        "Cabinda"
    ],
    "name:tur_x_preferred":[
        "Cabinda"
    ],
    "name:und_x_variant":[
        "Cabinde",
        "Cabinda"
    ],
    "wof:name":"Cabinda",
    "wof:placetype":"locality"
},
  "geometry": {"coordinates":[18.11667000000001,-8.16667],"type":"Point"}
}