{
  "type": "Feature",
  "properties": {
    "gn:admin1_code":"8.0",
    "gn:asciiname":"Tchicalambue",
    "gn:country_code":"AO",
    "gn:dem":1675,
    "gn:feature_class":"P",
    "gn:feature_code":"PPL",
    "gn:name":"Tchicalambue",
    "gn:population":0,
    "gn:timezone":"Africa/Luanda",
    "iso:country":"AO",
    "wof:name":"Tchicalambue",
    "wof:placetype":"locality"
},
  "geometry": {"coordinates":[15.54306,-12.73833],"type":"Point"}
}