{
  "type": "Feature",
  "properties": {
    "gn:admin1_code":"0.0",
    "gn:asciiname":"Ombe",
    "gn:country_code":"AO",
    "gn:dem":479,
    "gn:feature_class":"P",
    "gn:feature_code":"PPL",
    "gn:name":"Ombe",
    "gn:population":0,
    "gn:timezone":"Africa/Luanda",
    "iso:country":"AO",
    "wof:name":"Ombe",
    "wof:placetype":"locality"
},
  "geometry": {"coordinates":[13.67806,-12.92194],"type":"Point"}
}