{
  "type": "Feature",
  "properties": {
    "gn:admin1_code":"15.0",
    "gn:asciiname":"Alfandega",
    "gn:country_code":"AO",
    "gn:dem":1084,
    "gn:feature_class":"P",
    "gn:feature_code":"PPL",
    "gn:name":"Alf\u00e2ndega",
    "gn:population":0,
    "gn:timezone":"Africa/Luanda",
    "iso:country":"AO",
    "wof:name":"Alfandega",
    "wof:placetype":"locality"
},
  "geometry": {"coordinates":[15.83843,-7.53706],"type":"Point"}
}