{
  "type": "Feature",
  "properties": {
    "gn:admin1_code":"6.0",
    "gn:asciiname":"Capuene",
    "gn:country_code":"AO",
    "gn:dem":1244,
    "gn:feature_class":"P",
    "gn:feature_code":"PPL",
    "gn:name":"Capuene",
    "gn:population":0,
    "gn:timezone":"Africa/Luanda",
    "iso:country":"AO",
    "wof:name":"Capuene",
    "wof:placetype":"locality"
},
  "geometry": {"coordinates":[14.70613,-10.83387],"type":"Point"}
}