{
  "type": "Feature",
  "properties": {
    "gn:admin1_code":"5.0",
    "gn:asciiname":"Fazenda Camoma",
    "gn:country_code":"AO",
    "gn:dem":685,
    "gn:feature_class":"P",
    "gn:feature_code":"PPL",
    "gn:name":"Fazenda Camoma",
    "gn:population":0,
    "gn:timezone":"Africa/Luanda",
    "iso:country":"AO",
    "wof:name":"Fazenda Camoma",
    "wof:placetype":"locality"
},
  "geometry": {"coordinates":[15.06667,-9.33333],"type":"Point"}
}