{
  "type": "Feature",
  "properties": {
    "gn:admin1_code":"17.0",
    "gn:asciiname":"Canji",
    "gn:country_code":"AO",
    "gn:dem":703,
    "gn:feature_class":"P",
    "gn:feature_code":"PPL",
    "gn:name":"Canji",
    "gn:population":0,
    "gn:timezone":"Africa/Luanda",
    "iso:country":"AO",
    "wof:name":"Canji",
    "wof:placetype":"locality"
},
  "geometry": {"coordinates":[17.57869,-8.40927],"type":"Point"}
}