{
  "type": "Feature",
  "properties": {
    "gn:admin1_code":"12.0",
    "gn:asciiname":"Lutula",
    "gn:country_code":"AO",
    "gn:dem":1046,
    "gn:feature_class":"P",
    "gn:feature_code":"PPL",
    "gn:name":"Lutula",
    "gn:population":0,
    "gn:timezone":"Africa/Luanda",
    "iso:country":"AO",
    "wof:name":"Lutula",
    "wof:placetype":"locality"
},
  "geometry": {"coordinates":[15.95,-9.36667],"type":"Point"}
}