{
  "type": "Feature",
  "properties": {
    "gn:admin1_code":"12.0",
    "gn:asciiname":"Catombe",
    "gn:country_code":"AO",
    "gn:dem":1062,
    "gn:feature_class":"P",
    "gn:feature_code":"PPL",
    "gn:name":"Catombe",
    "gn:population":0,
    "gn:timezone":"Africa/Luanda",
    "iso:country":"AO",
    "wof:name":"Catombe",
    "wof:placetype":"locality"
},
  "geometry": {"coordinates":[16.14861,-9.55444],"type":"Point"}
}