{
  "type": "Feature",
  "properties": {
    "gn:admin1_code":"17.0",
    "gn:asciiname":"Tchamulolo",
    "gn:country_code":"AO",
    "gn:dem":756,
    "gn:feature_class":"P",
    "gn:feature_code":"PPL",
    "gn:name":"Tchamulolo",
    "gn:population":0,
    "gn:timezone":"Africa/Luanda",
    "iso:country":"AO",
    "wof:name":"Tchamulolo",
    "wof:placetype":"locality"
},
  "geometry": {"coordinates":[18.00561,-8.68394],"type":"Point"}
}