{
  "type": "Feature",
  "properties": {
    "gn:admin1_code":"6.0",
    "gn:asciiname":"Limba",
    "gn:country_code":"AO",
    "gn:dem":1300,
    "gn:feature_class":"P",
    "gn:feature_code":"PPL",
    "gn:name":"Limba",
    "gn:population":0,
    "gn:timezone":"Africa/Luanda",
    "iso:country":"AO",
    "name:ceb_x_preferred":[
        "Limba"
    ],
    "name:deu_x_preferred":[
        "Limba"
    ],
    "name:fra_x_preferred":[
        "Limba"
    ],
    "name:ita_x_preferred":[
        "Limba"
    ],
    "name:new_x_preferred":[
        "\u0932\u093f\u092e\u094d\u092c\u093e"
    ],
    "name:nld_x_preferred":[
        "Limba"
    ],
    "name:rus_x_preferred":[
        "\u041b\u0438\u043c\u0431\u0430"
    ],
    "name:swe_x_preferred":[
        "Limba"
    ],
    "wof:name":"Limba",
    "wof:placetype":"locality"
},
  "geometry": {"coordinates":[14.78552,-11.1861],"type":"Point"}
}