{
  "type": "Feature",
  "properties": {
    "gn:admin1_code":"14.0",
    "gn:asciiname":"Mucoca Primeiro",
    "gn:country_code":"AO",
    "gn:dem":1069,
    "gn:feature_class":"P",
    "gn:feature_code":"PPL",
    "gn:name":"Mucoca Primeiro",
    "gn:population":0,
    "gn:timezone":"Africa/Luanda",
    "iso:country":"AO",
    "wof:name":"Mucoca Primeiro",
    "wof:placetype":"locality"
},
  "geometry": {"coordinates":[22.08795,-10.65296],"type":"Point"}
}