{
  "type": "Feature",
  "properties": {
    "gn:admin1_code":"12.0",
    "gn:asciiname":"Valodia",
    "gn:country_code":"AO",
    "gn:dem":749,
    "gn:feature_class":"P",
    "gn:feature_code":"PPL",
    "gn:name":"Val\u00f3dia",
    "gn:population":0,
    "gn:timezone":"Africa/Luanda",
    "iso:country":"AO",
    "wof:name":"Valodia",
    "wof:placetype":"locality"
},
  "geometry": {"coordinates":[17.19803,-9.37577],"type":"Point"}
}