{
  "type": "Feature",
  "properties": {
    "gn:admin1_code":"14.0",
    "gn:asciiname":"Camuanha",
    "gn:cc2":"AO",
    "gn:country_code":"AO",
    "gn:dem":1119,
    "gn:feature_class":"P",
    "gn:feature_code":"PPL",
    "gn:name":"Camuanha",
    "gn:population":0,
    "gn:timezone":"Africa/Luanda",
    "iso:country":"AO",
    "name:und_x_variant":[
        "Camuanho",
        "Camuanha"
    ],
    "wof:name":"Camuanha",
    "wof:placetype":"locality"
},
  "geometry": {"coordinates":[20.73333,-14.65],"type":"Point"}
}