{
  "type": "Feature",
  "properties": {
    "gn:admin1_code":"9.0",
    "gn:asciiname":"Nondumbo",
    "gn:country_code":"AO",
    "gn:dem":1257,
    "gn:feature_class":"P",
    "gn:feature_code":"PPL",
    "gn:name":"Nondumbo",
    "gn:population":0,
    "gn:timezone":"Africa/Luanda",
    "iso:country":"AO",
    "wof:name":"Nondumbo",
    "wof:placetype":"locality"
},
  "geometry": {"coordinates":[15.04548,-14.56586],"type":"Point"}
}