{
  "type": "Feature",
  "properties": {
    "gn:admin1_code":"12.0",
    "gn:asciiname":"Quibuco",
    "gn:country_code":"AO",
    "gn:dem":1237,
    "gn:feature_class":"P",
    "gn:feature_code":"PPL",
    "gn:name":"Quibuco",
    "gn:population":0,
    "gn:timezone":"Africa/Luanda",
    "iso:country":"AO",
    "wof:name":"Quibuco",
    "wof:placetype":"locality"
},
  "geometry": {"coordinates":[17.00002000000001,-9.50861],"type":"Point"}
}