{
  "type": "Feature",
  "properties": {
    "gn:admin1_code":"12.0",
    "gn:asciiname":"Mulolo",
    "gn:country_code":"AO",
    "gn:dem":1384,
    "gn:feature_class":"P",
    "gn:feature_code":"PPL",
    "gn:name":"Mulolo",
    "gn:population":0,
    "gn:timezone":"Africa/Luanda",
    "iso:country":"AO",
    "wof:name":"Mulolo",
    "wof:placetype":"locality"
},
  "geometry": {"coordinates":[18.41174,-11.17336],"type":"Point"}
}