{
  "type": "Feature",
  "properties": {
    "gn:admin1_code":"6.0",
    "gn:asciiname":"Candulo",
    "gn:country_code":"AO",
    "gn:dem":1076,
    "gn:feature_class":"P",
    "gn:feature_code":"PPLL",
    "gn:name":"Candulo",
    "gn:population":0,
    "gn:timezone":"Africa/Luanda",
    "iso:country":"AO",
    "wof:name":"Candulo",
    "wof:placetype":"locality"
},
  "geometry": {"coordinates":[14.88897,-10.04136],"type":"Point"}
}