{
  "type": "Feature",
  "properties": {
    "gn:admin1_code":"6.0",
    "gn:asciiname":"Manuel Marques de Silva",
    "gn:cc2":"AO",
    "gn:country_code":"AO",
    "gn:dem":1469,
    "gn:feature_class":"P",
    "gn:feature_code":"PPL",
    "gn:name":"Manuel Marques de Silva",
    "gn:population":0,
    "gn:timezone":"Africa/Luanda",
    "iso:country":"AO",
    "name:und_x_variant":[
        "M. Silva",
        "Manuel Marques de Silva"
    ],
    "wof:name":"Manuel Marques de Silva",
    "wof:placetype":"locality"
},
  "geometry": {"coordinates":[15.43333,-11.13333],"type":"Point"}
}