{
  "type": "Feature",
  "properties": {
    "gn:admin1_code":"12.0",
    "gn:asciiname":"Sinendele",
    "gn:country_code":"AO",
    "gn:dem":1094,
    "gn:feature_class":"P",
    "gn:feature_code":"PPL",
    "gn:name":"Sinendele",
    "gn:population":0,
    "gn:timezone":"Africa/Luanda",
    "iso:country":"AO",
    "wof:name":"Sinendele",
    "wof:placetype":"locality"
},
  "geometry": {"coordinates":[17.75464,-10.59743],"type":"Point"}
}