{
  "type": "Feature",
  "properties": {
    "gn:admin1_code":"19.0",
    "gn:asciiname":"Quiage",
    "gn:country_code":"AO",
    "gn:dem":830,
    "gn:feature_class":"P",
    "gn:feature_code":"PPL",
    "gn:name":"Quiage",
    "gn:population":0,
    "gn:timezone":"Africa/Luanda",
    "iso:country":"AO",
    "name:cat_x_preferred":[
        "Quiage"
    ],
    "name:msa_x_preferred":[
        "Kiaje"
    ],
    "name:por_x_preferred":[
        "Quiage"
    ],
    "name:und_x_variant":[
        "Quiege"
    ],
    "wof:name":"Quiage",
    "wof:placetype":"locality"
},
  "geometry": {"coordinates":[14.94982,-8.50671],"type":"Point"}
}