{
  "type": "Feature",
  "properties": {
    "gn:admin1_code":"14.0",
    "gn:asciiname":"Savihemba",
    "gn:country_code":"AO",
    "gn:dem":1098,
    "gn:feature_class":"P",
    "gn:feature_code":"PPL",
    "gn:name":"Savihemba",
    "gn:population":0,
    "gn:timezone":"Africa/Luanda",
    "iso:country":"AO",
    "wof:name":"Savihemba",
    "wof:placetype":"locality"
},
  "geometry": {"coordinates":[22.21403,-10.69918],"type":"Point"}
}