{
  "type": "Feature",
  "properties": {
    "gn:admin1_code":"6.0",
    "gn:asciiname":"Ualo",
    "gn:country_code":"AO",
    "gn:dem":1153,
    "gn:feature_class":"P",
    "gn:feature_code":"PPL",
    "gn:name":"Ualo",
    "gn:population":0,
    "gn:timezone":"Africa/Luanda",
    "iso:country":"AO",
    "wof:name":"Ualo",
    "wof:placetype":"locality"
},
  "geometry": {"coordinates":[14.47801,-11.46629],"type":"Point"}
}