{
  "type": "Feature",
  "properties": {
    "gn:admin1_code":"2.0",
    "gn:asciiname":"Talala",
    "gn:country_code":"AO",
    "gn:dem":1689,
    "gn:feature_class":"P",
    "gn:feature_code":"PPL",
    "gn:name":"Talala",
    "gn:population":0,
    "gn:timezone":"Africa/Luanda",
    "iso:country":"AO",
    "name:ceb_x_preferred":[
        "Talala"
    ],
    "name:swe_x_preferred":[
        "Talala"
    ],
    "name:und_x_variant":[
        "Tarala"
    ],
    "wof:name":"Talala",
    "wof:placetype":"locality"
},
  "geometry": {"coordinates":[17.07249,-11.58451],"type":"Point"}
}