{
  "type": "Feature",
  "properties": {
    "gn:admin1_code":"2.0",
    "gn:asciiname":"Calitongo",
    "gn:country_code":"AO",
    "gn:dem":1426,
    "gn:feature_class":"P",
    "gn:feature_code":"PPL",
    "gn:name":"Calitongo",
    "gn:population":0,
    "gn:timezone":"Africa/Luanda",
    "iso:country":"AO",
    "wof:name":"Calitongo",
    "wof:placetype":"locality"
},
  "geometry": {"coordinates":[16.73106,-11.26513],"type":"Point"}
}