{
  "type": "Feature",
  "properties": {
    "gn:admin1_code":"6.0",
    "gn:asciiname":"Lobito",
    "gn:country_code":"AO",
    "gn:dem":1151,
    "gn:feature_class":"P",
    "gn:feature_code":"PPL",
    "gn:name":"Lobito",
    "gn:population":0,
    "gn:timezone":"Africa/Luanda",
    "iso:country":"AO",
    "wof:name":"Lobito",
    "wof:placetype":"locality"
},
  "geometry": {"coordinates":[14.53333,-11.51667],"type":"Point"}
}