{
  "type": "Feature",
  "properties": {
    "gn:admin1_code":"18.0",
    "gn:asciiname":"Muaxiteca",
    "gn:country_code":"AO",
    "gn:dem":1181,
    "gn:feature_class":"P",
    "gn:feature_code":"PPL",
    "gn:name":"Muaxiteca",
    "gn:population":0,
    "gn:timezone":"Africa/Luanda",
    "iso:country":"AO",
    "wof:name":"Muaxiteca",
    "wof:placetype":"locality"
},
  "geometry": {"coordinates":[18.98333,-10.65],"type":"Point"}
}