{
  "type": "Feature",
  "properties": {
    "gn:admin1_code":"15.0",
    "gn:asciiname":"Mbanza-Quilombo",
    "gn:country_code":"AO",
    "gn:dem":841,
    "gn:feature_class":"P",
    "gn:feature_code":"PPL",
    "gn:name":"Mbanza-Quilombo",
    "gn:population":0,
    "gn:timezone":"Africa/Luanda",
    "iso:country":"AO",
    "wof:name":"Mbanza-Quilombo",
    "wof:placetype":"locality"
},
  "geometry": {"coordinates":[15.20755,-5.92053],"type":"Point"}
}