{
  "type": "Feature",
  "properties": {
    "gn:admin1_code":"2.0",
    "gn:asciiname":"Onduimbar",
    "gn:country_code":"AO",
    "gn:dem":1645,
    "gn:feature_class":"P",
    "gn:feature_code":"PPL",
    "gn:name":"Onduimbar",
    "gn:population":0,
    "gn:timezone":"Africa/Luanda",
    "iso:country":"AO",
    "wof:name":"Onduimbar",
    "wof:placetype":"locality"
},
  "geometry": {"coordinates":[15.96667,-11.15],"type":"Point"}
}