{
  "type": "Feature",
  "properties": {
    "gn:admin1_code":"12.0",
    "gn:asciiname":"Buluca",
    "gn:country_code":"AO",
    "gn:dem":1123,
    "gn:feature_class":"P",
    "gn:feature_code":"PPL",
    "gn:name":"Buluca",
    "gn:population":0,
    "gn:timezone":"Africa/Luanda",
    "iso:country":"AO",
    "wof:name":"Buluca",
    "wof:placetype":"locality"
},
  "geometry": {"coordinates":[17.01339,-9.67974],"type":"Point"}
}