{
  "type": "Feature",
  "properties": {
    "gn:admin1_code":"19.0",
    "gn:asciiname":"Chaca",
    "gn:country_code":"AO",
    "gn:dem":111,
    "gn:feature_class":"P",
    "gn:feature_code":"PPL",
    "gn:name":"Chaca",
    "gn:population":0,
    "gn:timezone":"Africa/Luanda",
    "iso:country":"AO",
    "name:ceb_x_preferred":[
        "Chaca"
    ],
    "name:kor_x_preferred":[
        "\ucc28\uce74\uc18d"
    ],
    "name:swe_x_preferred":[
        "Chaca"
    ],
    "wof:name":"Chaca",
    "wof:placetype":"locality"
},
  "geometry": {"coordinates":[14.18333,-9.85],"type":"Point"}
}