{
  "type": "Feature",
  "properties": {
    "gn:admin1_code":"6.0",
    "gn:asciiname":"Salomao",
    "gn:country_code":"AO",
    "gn:dem":1717,
    "gn:feature_class":"P",
    "gn:feature_code":"PPL",
    "gn:name":"Salom\u00e3o",
    "gn:population":0,
    "gn:timezone":"Africa/Luanda",
    "iso:country":"AO",
    "wof:name":"Salomao",
    "wof:placetype":"locality"
},
  "geometry": {"coordinates":[14.9792,-11.95451],"type":"Point"}
}