{
  "type": "Feature",
  "properties": {
    "gn:admin1_code":"17.0",
    "gn:asciiname":"Cuilo Velho",
    "gn:country_code":"AO",
    "gn:dem":1051,
    "gn:feature_class":"P",
    "gn:feature_code":"PPL",
    "gn:name":"Cuilo Velho",
    "gn:population":0,
    "gn:timezone":"Africa/Luanda",
    "iso:country":"AO",
    "name:und_x_variant":[
        "Caungula",
        "Calungula",
        "Cahungula"
    ],
    "wof:name":"Cuilo Velho",
    "wof:placetype":"locality"
},
  "geometry": {"coordinates":[19.43221,-7.7956],"type":"Point"}
}