{
  "type": "Feature",
  "properties": {
    "gn:admin1_code":"6.0",
    "gn:asciiname":"Ndala Cachibo",
    "gn:country_code":"AO",
    "gn:dem":914,
    "gn:feature_class":"P",
    "gn:feature_code":"PPL",
    "gn:name":"Ndala Cachibo",
    "gn:population":0,
    "gn:timezone":"Africa/Luanda",
    "iso:country":"AO",
    "name:und_x_variant":[
        "Nadala Kachilo",
        "Dala Cachiba",
        "Dala Cachibo",
        "Ndala Cachibo"
    ],
    "wof:name":"Ndala Cachibo",
    "wof:placetype":"locality"
},
  "geometry": {"coordinates":[14.64595,-10.4652],"type":"Point"}
}