{
  "type": "Feature",
  "properties": {
    "gn:admin1_code":"12.0",
    "gn:asciiname":"Cangindongo",
    "gn:country_code":"AO",
    "gn:dem":1080,
    "gn:feature_class":"P",
    "gn:feature_code":"PPL",
    "gn:name":"Cangindongo",
    "gn:population":0,
    "gn:timezone":"Africa/Luanda",
    "iso:country":"AO",
    "wof:name":"Cangindongo",
    "wof:placetype":"locality"
},
  "geometry": {"coordinates":[15.85,-9.45],"type":"Point"}
}