{
  "type": "Feature",
  "properties": {
    "gn:admin1_code":"6.0",
    "gn:asciiname":"Ipela do Ngalo",
    "gn:country_code":"AO",
    "gn:dem":1041,
    "gn:feature_class":"P",
    "gn:feature_code":"PPL",
    "gn:name":"Ipela do Ngalo",
    "gn:population":0,
    "gn:timezone":"Africa/Luanda",
    "iso:country":"AO",
    "name:und_x_variant":[
        "Impela",
        "Impela da Camarata",
        "Lpela do Galo",
        "Ipela do Galo",
        "Ipela do Ngalo"
    ],
    "wof:name":"Ipela do Ngalo",
    "wof:placetype":"locality"
},
  "geometry": {"coordinates":[14.3197,-11.34362],"type":"Point"}
}