{
  "type": "Feature",
  "properties": {
    "gn:admin1_code":"12.0",
    "gn:asciiname":"Quicando",
    "gn:country_code":"AO",
    "gn:dem":1231,
    "gn:feature_class":"P",
    "gn:feature_code":"PPL",
    "gn:name":"Quicando",
    "gn:population":0,
    "gn:timezone":"Africa/Luanda",
    "iso:country":"AO",
    "wof:name":"Quicando",
    "wof:placetype":"locality"
},
  "geometry": {"coordinates":[15.86733,-8.31472],"type":"Point"}
}