{
  "type": "Feature",
  "properties": {
    "gn:admin1_code":"15.0",
    "gn:asciiname":"Quissanga",
    "gn:country_code":"AO",
    "gn:dem":808,
    "gn:feature_class":"P",
    "gn:feature_code":"PPL",
    "gn:name":"Quissanga",
    "gn:population":0,
    "gn:timezone":"Africa/Luanda",
    "iso:country":"AO",
    "name:ceb_x_preferred":[
        "Quissanga"
    ],
    "name:swe_x_preferred":[
        "Quissanga"
    ],
    "wof:name":"Quissanga",
    "wof:placetype":"locality"
},
  "geometry": {"coordinates":[15.04033,-7.34783],"type":"Point"}
}