{
  "type": "Feature",
  "properties": {
    "gn:admin1_code":"9.0",
    "gn:asciiname":"Tchova",
    "gn:country_code":"AO",
    "gn:dem":1305,
    "gn:feature_class":"P",
    "gn:feature_code":"PPLL",
    "gn:name":"Tchova",
    "gn:population":0,
    "gn:timezone":"Africa/Luanda",
    "iso:country":"AO",
    "wof:name":"Tchova",
    "wof:placetype":"locality"
},
  "geometry": {"coordinates":[14.6387,-14.53816],"type":"Point"}
}