{
  "type": "Feature",
  "properties": {
    "gn:admin1_code":"6.0",
    "gn:asciiname":"Hala Choa",
    "gn:country_code":"AO",
    "gn:dem":1465,
    "gn:feature_class":"P",
    "gn:feature_code":"PPL",
    "gn:name":"Hala Ch\u00f4a",
    "gn:population":0,
    "gn:timezone":"Africa/Luanda",
    "iso:country":"AO",
    "wof:name":"Hala Choa",
    "wof:placetype":"locality"
},
  "geometry": {"coordinates":[14.60619,-11.01378],"type":"Point"}
}