{
  "type": "Feature",
  "properties": {
    "gn:admin1_code":"1.0",
    "gn:asciiname":"Lumingo",
    "gn:cc2":"AO",
    "gn:country_code":"AO",
    "gn:dem":1149,
    "gn:feature_class":"P",
    "gn:feature_code":"PPL",
    "gn:name":"Lumingo",
    "gn:population":0,
    "gn:timezone":"Africa/Luanda",
    "iso:country":"AO",
    "name:und_x_variant":[
        "Domingo",
        "Lumingo"
    ],
    "wof:name":"Lumingo",
    "wof:placetype":"locality"
},
  "geometry": {"coordinates":[14.55,-12.26667],"type":"Point"}
}