{
  "type": "Feature",
  "properties": {
    "gn:admin1_code":"6.0",
    "gn:asciiname":"Tanganhica",
    "gn:country_code":"AO",
    "gn:dem":1542,
    "gn:feature_class":"P",
    "gn:feature_code":"PPL",
    "gn:name":"Tanganhica",
    "gn:population":0,
    "gn:timezone":"Africa/Luanda",
    "iso:country":"AO",
    "wof:name":"Tanganhica",
    "wof:placetype":"locality"
},
  "geometry": {"coordinates":[15.23333,-11.93333],"type":"Point"}
}