{
  "type": "Feature",
  "properties": {
    "gn:admin1_code":"2.0",
    "gn:asciiname":"Ndondelo",
    "gn:country_code":"AO",
    "gn:dem":1729,
    "gn:feature_class":"P",
    "gn:feature_code":"PPL",
    "gn:name":"Ndondelo",
    "gn:population":0,
    "gn:timezone":"Africa/Luanda",
    "iso:country":"AO",
    "wof:name":"Ndondelo",
    "wof:placetype":"locality"
},
  "geometry": {"coordinates":[17.00789,-11.97941],"type":"Point"}
}