{
  "type": "Feature",
  "properties": {
    "gn:admin1_code":"1.0",
    "gn:asciiname":"L. Farinha",
    "gn:country_code":"AO",
    "gn:dem":1205,
    "gn:feature_class":"P",
    "gn:feature_code":"PPL",
    "gn:name":"L. Farinha",
    "gn:population":0,
    "gn:timezone":"Africa/Luanda",
    "iso:country":"AO",
    "wof:name":"L. Farinha",
    "wof:placetype":"locality"
},
  "geometry": {"coordinates":[14.41667,-12.21667],"type":"Point"}
}