{
  "type": "Feature",
  "properties": {
    "gn:admin1_code":"15.0",
    "gn:asciiname":"Quivemba",
    "gn:country_code":"AO",
    "gn:dem":970,
    "gn:feature_class":"P",
    "gn:feature_code":"PPL",
    "gn:name":"Quivemba",
    "gn:population":0,
    "gn:timezone":"Africa/Luanda",
    "iso:country":"AO",
    "wof:name":"Quivemba",
    "wof:placetype":"locality"
},
  "geometry": {"coordinates":[15.05838,-6.14546],"type":"Point"}
}