{
  "type": "Feature",
  "properties": {
    "gn:admin1_code":"8.0",
    "gn:asciiname":"Tchicoma",
    "gn:country_code":"AO",
    "gn:dem":1698,
    "gn:feature_class":"P",
    "gn:feature_code":"PPL",
    "gn:name":"Tchicoma",
    "gn:population":0,
    "gn:timezone":"Africa/Luanda",
    "iso:country":"AO",
    "wof:name":"Tchicoma",
    "wof:placetype":"locality"
},
  "geometry": {"coordinates":[15.52556,-12.51806],"type":"Point"}
}