{
  "type": "Feature",
  "properties": {
    "gn:admin1_code":"17.0",
    "gn:asciiname":"Quichingi",
    "gn:country_code":"AO",
    "gn:dem":732,
    "gn:feature_class":"P",
    "gn:feature_code":"PPL",
    "gn:name":"Quichingi",
    "gn:population":0,
    "gn:timezone":"Africa/Luanda",
    "iso:country":"AO",
    "name:und_x_variant":[
        "Quixinge",
        "Quichinge",
        "Quichingi"
    ],
    "wof:name":"Quichingi",
    "wof:placetype":"locality"
},
  "geometry": {"coordinates":[17.63332999999999,-8.74164],"type":"Point"}
}