{
  "type": "Feature",
  "properties": {
    "gn:admin1_code":"17.0",
    "gn:asciiname":"Muhungo",
    "gn:country_code":"AO",
    "gn:dem":938,
    "gn:feature_class":"P",
    "gn:feature_code":"PPL",
    "gn:name":"Muhungo",
    "gn:population":0,
    "gn:timezone":"Africa/Luanda",
    "iso:country":"AO",
    "wof:name":"Muhungo",
    "wof:placetype":"locality"
},
  "geometry": {"coordinates":[18.40685,-9.3979],"type":"Point"}
}