{
  "type": "Feature",
  "properties": {
    "gn:admin1_code":"5.0",
    "gn:asciiname":"Quiato",
    "gn:country_code":"AO",
    "gn:dem":1087,
    "gn:feature_class":"P",
    "gn:feature_code":"PPL",
    "gn:name":"Quiato",
    "gn:population":0,
    "gn:timezone":"Africa/Luanda",
    "iso:country":"AO",
    "wof:name":"Quiato",
    "wof:placetype":"locality"
},
  "geometry": {"coordinates":[15.45688,-9.05512],"type":"Point"}
}