{
  "type": "Feature",
  "properties": {
    "gn:admin1_code":"15.0",
    "gn:asciiname":"Marinda",
    "gn:country_code":"AO",
    "gn:dem":1054,
    "gn:feature_class":"P",
    "gn:feature_code":"PPL",
    "gn:name":"Marinda",
    "gn:population":0,
    "gn:timezone":"Africa/Luanda",
    "iso:country":"AO",
    "name:und_x_variant":[
        "Macinda",
        "Quiteca Bunga Marinda",
        "Marinda",
        "Quiteca Bunga"
    ],
    "wof:name":"Marinda",
    "wof:placetype":"locality"
},
  "geometry": {"coordinates":[15.98952,-7.68757],"type":"Point"}
}