{
  "type": "Feature",
  "properties": {
    "gn:admin1_code":"5.0",
    "gn:asciiname":"Cassanzo",
    "gn:country_code":"AO",
    "gn:dem":48,
    "gn:feature_class":"P",
    "gn:feature_code":"PPL",
    "gn:name":"Cassanzo",
    "gn:population":0,
    "gn:timezone":"Africa/Luanda",
    "iso:country":"AO",
    "wof:name":"Cassanzo",
    "wof:placetype":"locality"
},
  "geometry": {"coordinates":[14.40251,-9.5011],"type":"Point"}
}