{
  "type": "Feature",
  "properties": {
    "gn:admin1_code":"14.0",
    "gn:asciiname":"Sangombe",
    "gn:cc2":"AO",
    "gn:country_code":"AO",
    "gn:dem":1324,
    "gn:feature_class":"P",
    "gn:feature_code":"PPL",
    "gn:name":"Sangombe",
    "gn:population":0,
    "gn:timezone":"Africa/Luanda",
    "iso:country":"AO",
    "name:und_x_variant":[
        "Satombi",
        "Sangombe"
    ],
    "wof:name":"Sangombe",
    "wof:placetype":"locality"
},
  "geometry": {"coordinates":[19.51667,-12.45],"type":"Point"}
}