{
  "type": "Feature",
  "properties": {
    "gn:admin1_code":"15.0",
    "gn:asciiname":"Muncula",
    "gn:country_code":"AO",
    "gn:dem":855,
    "gn:feature_class":"P",
    "gn:feature_code":"PPL",
    "gn:name":"Muncula",
    "gn:population":0,
    "gn:timezone":"Africa/Luanda",
    "iso:country":"AO",
    "wof:name":"Muncula",
    "wof:placetype":"locality"
},
  "geometry": {"coordinates":[15.30998,-6.47891],"type":"Point"}
}