{
  "type": "Feature",
  "properties": {
    "gn:admin1_code":"19.0",
    "gn:asciiname":"Pedro Bravo",
    "gn:country_code":"AO",
    "gn:dem":301,
    "gn:feature_class":"P",
    "gn:feature_code":"PPL",
    "gn:name":"Pedro Bravo",
    "gn:population":0,
    "gn:timezone":"Africa/Luanda",
    "iso:country":"AO",
    "wof:name":"Pedro Bravo",
    "wof:placetype":"locality"
},
  "geometry": {"coordinates":[14.25,-8.68333],"type":"Point"}
}