{
  "type": "Feature",
  "properties": {
    "gn:admin1_code":"5.0",
    "gn:asciiname":"Tande",
    "gn:country_code":"AO",
    "gn:dem":702,
    "gn:feature_class":"P",
    "gn:feature_code":"PPL",
    "gn:name":"Tande",
    "gn:population":0,
    "gn:timezone":"Africa/Luanda",
    "iso:country":"AO",
    "name:fas_x_preferred":[
        "\u062a\u0627\u0646\u062f\u0647"
    ],
    "name:ita_x_preferred":[
        "Alexandre Samuel"
    ],
    "name:nor_x_preferred":[
        "Alexandre Samuel"
    ],
    "name:por_x_preferred":[
        "Tande"
    ],
    "name:spa_x_preferred":[
        "Tande"
    ],
    "wof:name":"Tande",
    "wof:placetype":"locality"
},
  "geometry": {"coordinates":[14.78333,-9.01667],"type":"Point"}
}