{
  "type": "Feature",
  "properties": {
    "gn:admin1_code":"17.0",
    "gn:asciiname":"Calengo",
    "gn:country_code":"AO",
    "gn:dem":819,
    "gn:feature_class":"P",
    "gn:feature_code":"PPL",
    "gn:name":"Calengo",
    "gn:population":0,
    "gn:timezone":"Africa/Luanda",
    "iso:country":"AO",
    "wof:name":"Calengo",
    "wof:placetype":"locality"
},
  "geometry": {"coordinates":[18.31667,-8.06667],"type":"Point"}
}