{
  "type": "Feature",
  "properties": {
    "gn:admin1_code":"6.0",
    "gn:asciiname":"Calunga",
    "gn:country_code":"AO",
    "gn:dem":1135,
    "gn:feature_class":"P",
    "gn:feature_code":"PPL",
    "gn:name":"Calunga",
    "gn:population":0,
    "gn:timezone":"Africa/Luanda",
    "iso:country":"AO",
    "wof:name":"Calunga",
    "wof:placetype":"locality"
},
  "geometry": {"coordinates":[15.75,-9.96667],"type":"Point"}
}