{
  "type": "Feature",
  "properties": {
    "gn:admin1_code":"6.0",
    "gn:asciiname":"Catanda",
    "gn:cc2":"AO",
    "gn:country_code":"AO",
    "gn:dem":871,
    "gn:feature_class":"P",
    "gn:feature_code":"PPL",
    "gn:name":"Catanda",
    "gn:population":0,
    "gn:timezone":"Africa/Luanda",
    "iso:country":"AO",
    "name:und_x_variant":[
        "Calanda",
        "Kalanda",
        "Catanda"
    ],
    "wof:name":"Catanda",
    "wof:placetype":"locality"
},
  "geometry": {"coordinates":[14.45,-11.71667],"type":"Point"}
}