{
  "type": "Feature",
  "properties": {
    "gn:admin1_code":"8.0",
    "gn:asciiname":"Chinga",
    "gn:country_code":"AO",
    "gn:dem":1701,
    "gn:feature_class":"P",
    "gn:feature_code":"PPL",
    "gn:name":"Chinga",
    "gn:population":0,
    "gn:timezone":"Africa/Luanda",
    "iso:country":"AO",
    "wof:name":"Chinga",
    "wof:placetype":"locality"
},
  "geometry": {"coordinates":[15.11667,-12.18333],"type":"Point"}
}