{
  "type": "Feature",
  "properties": {
    "gn:admin1_code":"19.0",
    "gn:asciiname":"Roca Santarem",
    "gn:country_code":"AO",
    "gn:dem":755,
    "gn:feature_class":"P",
    "gn:feature_code":"PPL",
    "gn:name":"Ro\u00e7a Santar\u00e9m",
    "gn:population":0,
    "gn:timezone":"Africa/Luanda",
    "iso:country":"AO",
    "name:und_x_variant":[
        "Fazenda Goveiro",
        "Ro\u00e7a Santar\u00e9m"
    ],
    "wof:name":"Roca Santarem",
    "wof:placetype":"locality"
},
  "geometry": {"coordinates":[14.43333,-8.51667],"type":"Point"}
}