{
  "type": "Feature",
  "properties": {
    "gn:admin1_code":"15.0",
    "gn:asciiname":"Lunga",
    "gn:country_code":"AO",
    "gn:dem":744,
    "gn:feature_class":"P",
    "gn:feature_code":"PPL",
    "gn:name":"Lunga",
    "gn:population":0,
    "gn:timezone":"Africa/Luanda",
    "iso:country":"AO",
    "name:ceb_x_preferred":[
        "Lunga"
    ],
    "name:deu_x_preferred":[
        "Lunga"
    ],
    "name:epo_x_preferred":[
        "Lunga"
    ],
    "name:fra_x_preferred":[
        "Lunga"
    ],
    "name:hun_x_preferred":[
        "Lunga"
    ],
    "name:ita_x_preferred":[
        "Lunga"
    ],
    "name:por_x_preferred":[
        "Lunga"
    ],
    "name:ron_x_preferred":[
        "Lunga"
    ],
    "name:rus_x_preferred":[
        "\u041b\u0443\u043d\u0433\u0430"
    ],
    "name:srp_x_preferred":[
        "\u041b\u0443\u043d\u0433\u0430"
    ],
    "name:swe_x_preferred":[
        "Lunga"
    ],
    "name:ukr_x_preferred":[
        "\u041b\u0443\u043d\u0433\u0430"
    ],
    "wof:name":"Lunga",
    "wof:placetype":"locality"
},
  "geometry": {"coordinates":[15.62928,-6.23821],"type":"Point"}
}