{
  "type": "Feature",
  "properties": {
    "gn:admin1_code":"15.0",
    "gn:asciiname":"Lunga",
    "gn:country_code":"AO",
    "gn:dem":744,
    "gn:feature_class":"P",
    "gn:feature_code":"PPL",
    "gn:name":"Lunga",
    "gn:population":0,
    "gn:timezone":"Africa/Luanda",
    "iso:country":"AO",
    "wof:name":"Lunga",
    "wof:placetype":"locality"
},
  "geometry": {"coordinates":[15.62928,-6.23821],"type":"Point"}
}