{
  "type": "Feature",
  "properties": {
    "gn:admin1_code":"12.0",
    "gn:asciiname":"Chacaleia",
    "gn:country_code":"AO",
    "gn:dem":1054,
    "gn:feature_class":"P",
    "gn:feature_code":"PPL",
    "gn:name":"Chacaleia",
    "gn:population":0,
    "gn:timezone":"Africa/Luanda",
    "iso:country":"AO",
    "wof:name":"Chacaleia",
    "wof:placetype":"locality"
},
  "geometry": {"coordinates":[16.56667,-9.96667],"type":"Point"}
}