{
  "type": "Feature",
  "properties": {
    "gn:admin1_code":"4.0",
    "gn:asciiname":"Muchine",
    "gn:country_code":"AO",
    "gn:dem":1096,
    "gn:feature_class":"P",
    "gn:feature_code":"PPL",
    "gn:name":"Muchine",
    "gn:population":0,
    "gn:timezone":"Africa/Luanda",
    "iso:country":"AO",
    "wof:name":"Muchine",
    "wof:placetype":"locality"
},
  "geometry": {"coordinates":[20.96667,-17.41667],"type":"Point"}
}