{
  "type": "Feature",
  "properties": {
    "gn:admin1_code":"19.0",
    "gn:asciiname":"Cambambi",
    "gn:country_code":"AO",
    "gn:dem":15,
    "gn:feature_class":"P",
    "gn:feature_code":"PPL",
    "gn:name":"Cambambi",
    "gn:population":0,
    "gn:timezone":"Africa/Luanda",
    "iso:country":"AO",
    "wof:name":"Cambambi",
    "wof:placetype":"locality"
},
  "geometry": {"coordinates":[13.63722,-8.58056],"type":"Point"}
}