{
  "type": "Feature",
  "properties": {
    "gn:admin1_code":"1.0",
    "gn:asciiname":"Biopio",
    "gn:country_code":"AO",
    "gn:dem":169,
    "gn:feature_class":"P",
    "gn:feature_code":"PPL",
    "gn:name":"Bi\u00f3pio",
    "gn:population":0,
    "gn:timezone":"Africa/Luanda",
    "iso:country":"AO",
    "name:und_x_variant":[
        "Biapio",
        "Aldeia do Bi\u00f3pio",
        "Bi\u00f3pio"
    ],
    "wof:name":"Biopio",
    "wof:placetype":"locality"
},
  "geometry": {"coordinates":[13.74112,-12.46592],"type":"Point"}
}