{
  "type": "Feature",
  "properties": {
    "gn:admin1_code":"16.0",
    "gn:asciiname":"Upite-Queno",
    "gn:country_code":"AO",
    "gn:dem":1176,
    "gn:feature_class":"P",
    "gn:feature_code":"PPL",
    "gn:name":"Upite-Queno",
    "gn:population":0,
    "gn:timezone":"Africa/Luanda",
    "iso:country":"AO",
    "wof:name":"Upite-Queno",
    "wof:placetype":"locality"
},
  "geometry": {"coordinates":[20.20391,-10.33664],"type":"Point"}
}