{
  "type": "Feature",
  "properties": {
    "gn:admin1_code":"14.0",
    "gn:asciiname":"Inhamo",
    "gn:country_code":"AO",
    "gn:dem":1450,
    "gn:feature_class":"P",
    "gn:feature_code":"PPL",
    "gn:name":"Inhamo",
    "gn:population":0,
    "gn:timezone":"Africa/Luanda",
    "iso:country":"AO",
    "wof:name":"Inhamo",
    "wof:placetype":"locality"
},
  "geometry": {"coordinates":[18.76667,-12.93333],"type":"Point"}
}