{
  "type": "Feature",
  "properties": {
    "gn:admin1_code":"18.0",
    "gn:asciiname":"Tchivundo Terceiro",
    "gn:country_code":"AO",
    "gn:dem":1030,
    "gn:feature_class":"P",
    "gn:feature_code":"PPL",
    "gn:name":"Tchivundo Terceiro",
    "gn:population":0,
    "gn:timezone":"Africa/Luanda",
    "iso:country":"AO",
    "name:und_x_variant":[
        "Miss\u00e3o Paulo Cambuta"
    ],
    "wof:name":"Tchivundo Terceiro",
    "wof:placetype":"locality"
},
  "geometry": {"coordinates":[21.94837,-9.81325],"type":"Point"}
}