{
  "type": "Feature",
  "properties": {
    "gn:admin1_code":"15.0",
    "gn:asciiname":"Senga",
    "gn:country_code":"AO",
    "gn:dem":958,
    "gn:feature_class":"P",
    "gn:feature_code":"PPL",
    "gn:name":"Senga",
    "gn:population":0,
    "gn:timezone":"Africa/Luanda",
    "iso:country":"AO",
    "name:ceb_x_preferred":[
        "Senga"
    ],
    "name:ita_x_preferred":[
        "Senga"
    ],
    "name:swa_x_preferred":[
        "Senga"
    ],
    "name:swe_x_preferred":[
        "Senga"
    ],
    "wof:name":"Senga",
    "wof:placetype":"locality"
},
  "geometry": {"coordinates":[15.23456,-6.55522],"type":"Point"}
}