{
  "type": "Feature",
  "properties": {
    "gn:admin1_code":"15.0",
    "gn:asciiname":"Quindona",
    "gn:country_code":"AO",
    "gn:dem":832,
    "gn:feature_class":"P",
    "gn:feature_code":"PPL",
    "gn:name":"Quindona",
    "gn:population":0,
    "gn:timezone":"Africa/Luanda",
    "iso:country":"AO",
    "wof:name":"Quindona",
    "wof:placetype":"locality"
},
  "geometry": {"coordinates":[15.2125,-5.90777],"type":"Point"}
}