{
  "type": "Feature",
  "properties": {
    "gn:admin1_code":"15.0",
    "gn:asciiname":"Quicambunda",
    "gn:country_code":"AO",
    "gn:dem":1296,
    "gn:feature_class":"P",
    "gn:feature_code":"PPL",
    "gn:name":"Quicambunda",
    "gn:population":0,
    "gn:timezone":"Africa/Luanda",
    "iso:country":"AO",
    "name:und_x_variant":[
        "Quicabanda",
        "Quicambunda"
    ],
    "wof:name":"Quicambunda",
    "wof:placetype":"locality"
},
  "geometry": {"coordinates":[15.11057,-7.3408],"type":"Point"}
}