{
  "type": "Feature",
  "properties": {
    "gn:admin1_code":"8.0",
    "gn:asciiname":"Pambala",
    "gn:country_code":"AO",
    "gn:dem":1787,
    "gn:feature_class":"P",
    "gn:feature_code":"PPL",
    "gn:name":"Pambala",
    "gn:population":0,
    "gn:timezone":"Africa/Luanda",
    "iso:country":"AO",
    "wof:name":"Pambala",
    "wof:placetype":"locality"
},
  "geometry": {"coordinates":[15.45528,-12.98806],"type":"Point"}
}