{
  "type": "Feature",
  "properties": {
    "gn:admin1_code":"6.0",
    "gn:asciiname":"Jamba",
    "gn:cc2":"AO",
    "gn:country_code":"AO",
    "gn:dem":874,
    "gn:feature_class":"P",
    "gn:feature_code":"PPL",
    "gn:name":"Jamba",
    "gn:population":0,
    "gn:timezone":"Africa/Luanda",
    "iso:country":"AO",
    "name:und_x_variant":[
        "Jamba Segundo",
        "Jamba"
    ],
    "wof:name":"Jamba",
    "wof:placetype":"locality"
},
  "geometry": {"coordinates":[14.25,-11.16667],"type":"Point"}
}