{
  "type": "Feature",
  "properties": {
    "gn:admin1_code":"6.0",
    "gn:asciiname":"Fazenda Santa Isabel",
    "gn:cc2":"AO",
    "gn:country_code":"AO",
    "gn:dem":584,
    "gn:feature_class":"P",
    "gn:feature_code":"PPL",
    "gn:name":"Fazenda Santa Isabel",
    "gn:population":0,
    "gn:timezone":"Africa/Luanda",
    "iso:country":"AO",
    "name:und_x_variant":[
        "Ro\u00e7a Santa Isabel",
        "Fazenda Santa Isabel"
    ],
    "wof:name":"Fazenda Santa Isabel",
    "wof:placetype":"locality"
},
  "geometry": {"coordinates":[14.76667,-9.98333],"type":"Point"}
}