{
  "type": "Feature",
  "properties": {
    "gn:admin1_code":"19.0",
    "gn:asciiname":"Cachilo",
    "gn:country_code":"AO",
    "gn:dem":678,
    "gn:feature_class":"P",
    "gn:feature_code":"PPL",
    "gn:name":"Cachilo",
    "gn:population":0,
    "gn:timezone":"Africa/Luanda",
    "iso:country":"AO",
    "wof:name":"Cachilo",
    "wof:placetype":"locality"
},
  "geometry": {"coordinates":[14.46094,-10.29511],"type":"Point"}
}