{
  "type": "Feature",
  "properties": {
    "gn:admin1_code":"6.0",
    "gn:asciiname":"Humbi",
    "gn:country_code":"AO",
    "gn:dem":1224,
    "gn:feature_class":"P",
    "gn:feature_code":"PPL",
    "gn:name":"Humbi",
    "gn:population":0,
    "gn:timezone":"Africa/Luanda",
    "iso:country":"AO",
    "wof:name":"Humbi",
    "wof:placetype":"locality"
},
  "geometry": {"coordinates":[15.04468,-10.92374],"type":"Point"}
}