{
  "type": "Feature",
  "properties": {
    "gn:admin1_code":"6.0",
    "gn:asciiname":"Catandondo",
    "gn:country_code":"AO",
    "gn:dem":13,
    "gn:feature_class":"P",
    "gn:feature_code":"PPL",
    "gn:name":"Catandondo",
    "gn:population":0,
    "gn:timezone":"Africa/Luanda",
    "iso:country":"AO",
    "wof:name":"Catandondo",
    "wof:placetype":"locality"
},
  "geometry": {"coordinates":[13.96817,-10.41835],"type":"Point"}
}