{
  "type": "Feature",
  "properties": {
    "gn:admin1_code":"2.0",
    "gn:asciiname":"Chatuala",
    "gn:country_code":"AO",
    "gn:dem":1260,
    "gn:feature_class":"P",
    "gn:feature_code":"PPL",
    "gn:name":"Chatuala",
    "gn:population":0,
    "gn:timezone":"Africa/Luanda",
    "iso:country":"AO",
    "wof:name":"Chatuala",
    "wof:placetype":"locality"
},
  "geometry": {"coordinates":[16.63332999999999,-11.01667],"type":"Point"}
}