{
  "type": "Feature",
  "properties": {
    "gn:admin1_code":"16.0",
    "gn:admin2_code":"2236966.0",
    "gn:asciiname":"Sumba",
    "gn:country_code":"AO",
    "gn:dem":54,
    "gn:feature_class":"P",
    "gn:feature_code":"PPL",
    "gn:name":"Sumba",
    "gn:population":0,
    "gn:timezone":"Africa/Luanda",
    "iso:country":"AO",
    "wof:name":"Sumba",
    "wof:placetype":"locality"
},
  "geometry": {"coordinates":[12.63247,-6.14986],"type":"Point"}
}