{
  "type": "Feature",
  "properties": {
    "gn:admin1_code":"19.0",
    "gn:asciiname":"Muxaluando",
    "gn:country_code":"AO",
    "gn:dem":566,
    "gn:feature_class":"P",
    "gn:feature_code":"PPL",
    "gn:name":"Muxaluando",
    "gn:population":0,
    "gn:timezone":"Africa/Luanda",
    "iso:country":"AO",
    "name:und_x_variant":[
        "General Freire",
        "Muchalnau",
        "Muxaluau",
        "Muchaluando",
        "Muxuluando",
        "Muchaluau",
        "Muxaluando"
    ],
    "wof:name":"Muxaluando",
    "wof:placetype":"locality"
},
  "geometry": {"coordinates":[14.28838,-8.12307],"type":"Point"}
}