{
  "type": "Feature",
  "properties": {
    "gn:admin1_code":"5.0",
    "gn:asciiname":"Capungo",
    "gn:country_code":"AO",
    "gn:dem":29,
    "gn:feature_class":"P",
    "gn:feature_code":"PPL",
    "gn:name":"Capungo",
    "gn:population":0,
    "gn:timezone":"Africa/Luanda",
    "iso:country":"AO",
    "wof:name":"Capungo",
    "wof:placetype":"locality"
},
  "geometry": {"coordinates":[14.31271,-9.53774],"type":"Point"}
}