{
  "type": "Feature",
  "properties": {
    "gn:admin1_code":"20.0",
    "gn:asciiname":"Bita",
    "gn:country_code":"AO",
    "gn:dem":6,
    "gn:feature_class":"P",
    "gn:feature_code":"PPL",
    "gn:name":"Bita",
    "gn:population":0,
    "gn:timezone":"Africa/Luanda",
    "iso:country":"AO",
    "name:ceb_x_preferred":[
        "Bita"
    ],
    "name:swe_x_preferred":[
        "Bita"
    ],
    "wof:name":"Bita",
    "wof:placetype":"locality"
},
  "geometry": {"coordinates":[13.29211,-9.12244],"type":"Point"}
}