{
  "type": "Feature",
  "properties": {
    "gn:admin1_code":"6.0",
    "gn:asciiname":"Capanga",
    "gn:country_code":"AO",
    "gn:dem":1165,
    "gn:feature_class":"P",
    "gn:feature_code":"PPL",
    "gn:name":"Capanga",
    "gn:population":0,
    "gn:timezone":"Africa/Luanda",
    "iso:country":"AO",
    "wof:name":"Capanga",
    "wof:placetype":"locality"
},
  "geometry": {"coordinates":[14.45683,-10.66846],"type":"Point"}
}