{
  "type": "Feature",
  "properties": {
    "gn:admin1_code":"12.0",
    "gn:asciiname":"Madele ia Senda",
    "gn:country_code":"AO",
    "gn:dem":687,
    "gn:feature_class":"P",
    "gn:feature_code":"PPL",
    "gn:name":"Madele i\u00e1 Senda",
    "gn:population":0,
    "gn:timezone":"Africa/Luanda",
    "iso:country":"AO",
    "wof:name":"Madele ia Senda",
    "wof:placetype":"locality"
},
  "geometry": {"coordinates":[16.52931,-8.23246],"type":"Point"}
}