{
  "type": "Feature",
  "properties": {
    "gn:admin1_code":"15.0",
    "gn:asciiname":"Maquela",
    "gn:country_code":"AO",
    "gn:dem":864,
    "gn:feature_class":"P",
    "gn:feature_code":"PPL",
    "gn:name":"Maquela",
    "gn:population":0,
    "gn:timezone":"Africa/Luanda",
    "iso:country":"AO",
    "wof:name":"Maquela",
    "wof:placetype":"locality"
},
  "geometry": {"coordinates":[15.08333,-6.05],"type":"Point"}
}