{
  "type": "Feature",
  "properties": {
    "gn:admin1_code":"15.0",
    "gn:asciiname":"Quipanzo",
    "gn:country_code":"AO",
    "gn:dem":1107,
    "gn:feature_class":"P",
    "gn:feature_code":"PPL",
    "gn:name":"Quipanzo",
    "gn:population":0,
    "gn:timezone":"Africa/Luanda",
    "iso:country":"AO",
    "wof:name":"Quipanzo",
    "wof:placetype":"locality"
},
  "geometry": {"coordinates":[15.16667,-6.71667],"type":"Point"}
}