{
  "type": "Feature",
  "properties": {
    "gn:admin1_code":"16.0",
    "gn:asciiname":"Ntongui",
    "gn:country_code":"AO",
    "gn:dem":299,
    "gn:feature_class":"P",
    "gn:feature_code":"PPL",
    "gn:name":"Ntongui",
    "gn:population":0,
    "gn:timezone":"Africa/Luanda",
    "iso:country":"AO",
    "wof:name":"Ntongui",
    "wof:placetype":"locality"
},
  "geometry": {"coordinates":[13.46494,-5.89514],"type":"Point"}
}