{
  "type": "Feature",
  "properties": {
    "gn:admin1_code":"1.0",
    "gn:asciiname":"Cavimbe",
    "gn:cc2":"AO",
    "gn:country_code":"AO",
    "gn:dem":1126,
    "gn:feature_class":"P",
    "gn:feature_code":"PPL",
    "gn:name":"Cavimbe",
    "gn:population":0,
    "gn:timezone":"Africa/Luanda",
    "iso:country":"AO",
    "name:und_x_variant":[
        "Cavimbi",
        "Cavimbe"
    ],
    "wof:name":"Cavimbe",
    "wof:placetype":"locality"
},
  "geometry": {"coordinates":[14.25,-12.26667],"type":"Point"}
}