{
  "type": "Feature",
  "properties": {
    "gn:admin1_code":"14.0",
    "gn:asciiname":"Maunga",
    "gn:cc2":"AO",
    "gn:country_code":"AO",
    "gn:dem":1062,
    "gn:feature_class":"P",
    "gn:feature_code":"PPL",
    "gn:name":"Maunga",
    "gn:population":0,
    "gn:timezone":"Africa/Luanda",
    "iso:country":"AO",
    "name:und_x_variant":[
        "Cauanda",
        "Maunga"
    ],
    "wof:name":"Maunga",
    "wof:placetype":"locality"
},
  "geometry": {"coordinates":[21.96667,-14.03333],"type":"Point"}
}