{
  "type": "Feature",
  "properties": {
    "gn:admin1_code":"1.0",
    "gn:asciiname":"Tchando",
    "gn:country_code":"AO",
    "gn:dem":1262,
    "gn:feature_class":"P",
    "gn:feature_code":"PPL",
    "gn:name":"Tchando",
    "gn:population":0,
    "gn:timezone":"Africa/Luanda",
    "iso:country":"AO",
    "wof:name":"Tchando",
    "wof:placetype":"locality"
},
  "geometry": {"coordinates":[14.48333,-12.76667],"type":"Point"}
}