{
  "type": "Feature",
  "properties": {
    "gn:admin1_code":"12.0",
    "gn:asciiname":"Cambamba",
    "gn:country_code":"AO",
    "gn:dem":1186,
    "gn:feature_class":"P",
    "gn:feature_code":"PPL",
    "gn:name":"Cambamba",
    "gn:population":0,
    "gn:timezone":"Africa/Luanda",
    "iso:country":"AO",
    "name:por_x_preferred":[
        "Cambamba"
    ],
    "wof:name":"Cambamba",
    "wof:placetype":"locality"
},
  "geometry": {"coordinates":[17.01986,-9.2686],"type":"Point"}
}