{
  "type": "Feature",
  "properties": {
    "gn:admin1_code":"12.0",
    "gn:asciiname":"Caboa",
    "gn:country_code":"AO",
    "gn:dem":1108,
    "gn:feature_class":"P",
    "gn:feature_code":"PPL",
    "gn:name":"Caboa",
    "gn:population":0,
    "gn:timezone":"Africa/Luanda",
    "iso:country":"AO",
    "wof:name":"Caboa",
    "wof:placetype":"locality"
},
  "geometry": {"coordinates":[15.63466,-9.62306],"type":"Point"}
}