{
  "type": "Feature",
  "properties": {
    "gn:admin1_code":"6.0",
    "gn:asciiname":"Gunjo",
    "gn:country_code":"AO",
    "gn:dem":1304,
    "gn:feature_class":"P",
    "gn:feature_code":"PPL",
    "gn:name":"Gunjo",
    "gn:population":0,
    "gn:timezone":"Africa/Luanda",
    "iso:country":"AO",
    "wof:name":"Gunjo",
    "wof:placetype":"locality"
},
  "geometry": {"coordinates":[14.73452,-11.48191],"type":"Point"}
}