{
  "type": "Feature",
  "properties": {
    "gn:admin1_code":"19.0",
    "gn:asciiname":"Quinzenza",
    "gn:country_code":"AO",
    "gn:dem":793,
    "gn:feature_class":"P",
    "gn:feature_code":"PPL",
    "gn:name":"Quinzenza",
    "gn:population":0,
    "gn:timezone":"Africa/Luanda",
    "iso:country":"AO",
    "name:und_x_variant":[
        "Quizenga",
        "Quinzenza"
    ],
    "wof:name":"Quinzenza",
    "wof:placetype":"locality"
},
  "geometry": {"coordinates":[14.78038,-8.73358],"type":"Point"}
}