{
  "type": "Feature",
  "properties": {
    "gn:admin1_code":"12.0",
    "gn:asciiname":"Missete",
    "gn:country_code":"AO",
    "gn:dem":757,
    "gn:feature_class":"P",
    "gn:feature_code":"PPL",
    "gn:name":"Missete",
    "gn:population":0,
    "gn:timezone":"Africa/Luanda",
    "iso:country":"AO",
    "wof:name":"Missete",
    "wof:placetype":"locality"
},
  "geometry": {"coordinates":[16.75847000000001,-8.08911],"type":"Point"}
}