{
  "type": "Feature",
  "properties": {
    "gn:admin1_code":"8.0",
    "gn:asciiname":"Tchindinganhe Segundo",
    "gn:country_code":"AO",
    "gn:dem":1484,
    "gn:feature_class":"P",
    "gn:feature_code":"PPL",
    "gn:name":"Tchindinganhe Segundo",
    "gn:population":0,
    "gn:timezone":"Africa/Luanda",
    "iso:country":"AO",
    "wof:name":"Tchindinganhe Segundo",
    "wof:placetype":"locality"
},
  "geometry": {"coordinates":[15.2509,-12.08809],"type":"Point"}
}