{
  "type": "Feature",
  "properties": {
    "gn:admin1_code":"8.0",
    "gn:asciiname":"Liassaca",
    "gn:cc2":"AO",
    "gn:country_code":"AO",
    "gn:dem":1581,
    "gn:feature_class":"P",
    "gn:feature_code":"PPL",
    "gn:name":"Liassaca",
    "gn:population":0,
    "gn:timezone":"Africa/Luanda",
    "iso:country":"AO",
    "name:und_x_variant":[
        "Cussaca",
        "Liassaca"
    ],
    "wof:name":"Liassaca",
    "wof:placetype":"locality"
},
  "geometry": {"coordinates":[15.58333,-11.76667],"type":"Point"}
}