{
  "type": "Feature",
  "properties": {
    "gn:admin1_code":"6.0",
    "gn:asciiname":"Monte Alto",
    "gn:country_code":"AO",
    "gn:dem":1822,
    "gn:feature_class":"P",
    "gn:feature_code":"PPL",
    "gn:name":"Monte Alto",
    "gn:population":0,
    "gn:timezone":"Africa/Luanda",
    "iso:country":"AO",
    "name:ceb_x_preferred":[
        "Monte Alto"
    ],
    "name:ita_x_preferred":[
        "Monte Alto"
    ],
    "name:mlg_x_preferred":[
        "Monte Alto"
    ],
    "name:nld_x_preferred":[
        "Monte Alto"
    ],
    "name:pol_x_preferred":[
        "Monte Alto"
    ],
    "name:por_x_preferred":[
        "Monte Alto"
    ],
    "name:srp_x_preferred":[
        "\u041c\u043e\u043d\u0442\u0435 \u0410\u043b\u0442\u043e"
    ],
    "name:swe_x_preferred":[
        "Monte Alto"
    ],
    "wof:name":"Monte Alto",
    "wof:placetype":"locality"
},
  "geometry": {"coordinates":[14.73219,-11.35707],"type":"Point"}
}