{
  "type": "Feature",
  "properties": {
    "gn:admin1_code":"8.0",
    "gn:asciiname":"Candingo I",
    "gn:cc2":"AO",
    "gn:country_code":"AO",
    "gn:dem":1884,
    "gn:feature_class":"P",
    "gn:feature_code":"PPL",
    "gn:name":"Candingo I",
    "gn:population":0,
    "gn:timezone":"Africa/Luanda",
    "iso:country":"AO",
    "name:und_x_variant":[
        "Candingo",
        "Candingo I"
    ],
    "wof:name":"Candingo I",
    "wof:placetype":"locality"
},
  "geometry": {"coordinates":[15.47194,-12.74083],"type":"Point"}
}