{
  "type": "Feature",
  "properties": {
    "gn:admin1_code":"15.0",
    "gn:asciiname":"Quizou",
    "gn:country_code":"AO",
    "gn:dem":406,
    "gn:feature_class":"P",
    "gn:feature_code":"PPL",
    "gn:name":"Quizou",
    "gn:population":0,
    "gn:timezone":"Africa/Luanda",
    "iso:country":"AO",
    "name:und_x_variant":[
        "Quinza\u00fa"
    ],
    "wof:name":"Quizou",
    "wof:placetype":"locality"
},
  "geometry": {"coordinates":[14.21667,-7.38333],"type":"Point"}
}