{
  "type": "Feature",
  "properties": {
    "gn:admin1_code":"1.0",
    "gn:asciiname":"Caombo",
    "gn:cc2":"AO",
    "gn:country_code":"AO",
    "gn:dem":1682,
    "gn:feature_class":"P",
    "gn:feature_code":"PPL",
    "gn:name":"Caombo",
    "gn:population":0,
    "gn:timezone":"Africa/Luanda",
    "iso:country":"AO",
    "name:cat_x_preferred":[
        "Cahombo"
    ],
    "name:deu_x_preferred":[
        "Cahombo"
    ],
    "name:ita_x_preferred":[
        "Cahombo"
    ],
    "name:msa_x_preferred":[
        "Caombo"
    ],
    "name:por_x_preferred":[
        "Caombo"
    ],
    "name:spa_x_preferred":[
        "Cahombo"
    ],
    "name:zho_x_preferred":[
        "\u5361\u7fc1\u535a"
    ],
    "wof:name":"Caombo",
    "wof:placetype":"locality"
},
  "geometry": {"coordinates":[14.88333,-12.63333],"type":"Point"}
}