{
  "type": "Feature",
  "properties": {
    "gn:admin1_code":"5.0",
    "gn:asciiname":"Quinzarinzari",
    "gn:country_code":"AO",
    "gn:dem":1207,
    "gn:feature_class":"P",
    "gn:feature_code":"PPL",
    "gn:name":"Quinzarinzari",
    "gn:population":0,
    "gn:timezone":"Africa/Luanda",
    "iso:country":"AO",
    "wof:name":"Quinzarinzari",
    "wof:placetype":"locality"
},
  "geometry": {"coordinates":[15.23582,-8.02535],"type":"Point"}
}