{
  "type": "Feature",
  "properties": {
    "gn:admin1_code":"14.0",
    "gn:asciiname":"Litue",
    "gn:cc2":"AO",
    "gn:country_code":"AO",
    "gn:dem":1135,
    "gn:feature_class":"P",
    "gn:feature_code":"PPL",
    "gn:name":"Litue",
    "gn:population":0,
    "gn:timezone":"Africa/Luanda",
    "iso:country":"AO",
    "name:und_x_variant":[
        "Ritu\u00e9",
        "Litue"
    ],
    "wof:name":"Litue",
    "wof:placetype":"locality"
},
  "geometry": {"coordinates":[21.36667000000001,-14.98333],"type":"Point"}
}