{
  "type": "Feature",
  "properties": {
    "gn:admin1_code":"6.0",
    "gn:asciiname":"Ulundo",
    "gn:country_code":"AO",
    "gn:dem":1490,
    "gn:feature_class":"P",
    "gn:feature_code":"PPL",
    "gn:name":"Ulundo",
    "gn:population":0,
    "gn:timezone":"Africa/Luanda",
    "iso:country":"AO",
    "wof:name":"Ulundo",
    "wof:placetype":"locality"
},
  "geometry": {"coordinates":[15.66667,-11.43333],"type":"Point"}
}