{
  "type": "Feature",
  "properties": {
    "gn:admin1_code":"19.0",
    "gn:asciiname":"Quipemba",
    "gn:country_code":"AO",
    "gn:dem":695,
    "gn:feature_class":"P",
    "gn:feature_code":"PPL",
    "gn:name":"Quipemba",
    "gn:population":0,
    "gn:timezone":"Africa/Luanda",
    "iso:country":"AO",
    "wof:name":"Quipemba",
    "wof:placetype":"locality"
},
  "geometry": {"coordinates":[14.23333,-7.88333],"type":"Point"}
}