{
  "type": "Feature",
  "properties": {
    "gn:admin1_code":"8.0",
    "gn:asciiname":"Tondoche",
    "gn:cc2":"AO",
    "gn:country_code":"AO",
    "gn:dem":1506,
    "gn:feature_class":"P",
    "gn:feature_code":"PPL",
    "gn:name":"Tondoche",
    "gn:population":0,
    "gn:timezone":"Africa/Luanda",
    "iso:country":"AO",
    "name:und_x_variant":[
        "Tandoche",
        "Tondoche"
    ],
    "wof:name":"Tondoche",
    "wof:placetype":"locality"
},
  "geometry": {"coordinates":[15.93333,-12.41667],"type":"Point"}
}