{
  "type": "Feature",
  "properties": {
    "gn:admin1_code":"6.0",
    "gn:asciiname":"Cahana",
    "gn:country_code":"AO",
    "gn:dem":64,
    "gn:feature_class":"P",
    "gn:feature_code":"PPL",
    "gn:name":"Cahana",
    "gn:population":0,
    "gn:timezone":"Africa/Luanda",
    "iso:country":"AO",
    "wof:name":"Cahana",
    "wof:placetype":"locality"
},
  "geometry": {"coordinates":[13.69989,-10.4283],"type":"Point"}
}