{
  "type": "Feature",
  "properties": {
    "gn:admin1_code":"6.0",
    "gn:asciiname":"Fazenda Faque",
    "gn:country_code":"AO",
    "gn:dem":818,
    "gn:feature_class":"P",
    "gn:feature_code":"PPL",
    "gn:name":"Fazenda Faque",
    "gn:population":0,
    "gn:timezone":"Africa/Luanda",
    "iso:country":"AO",
    "name:und_x_variant":[
        "Faque",
        "Fazenda Faque"
    ],
    "wof:name":"Fazenda Faque",
    "wof:placetype":"locality"
},
  "geometry": {"coordinates":[14.90805,-9.90167],"type":"Point"}
}