{
  "type": "Feature",
  "properties": {
    "gn:admin1_code":"14.0",
    "gn:asciiname":"Sautar",
    "gn:country_code":"AO",
    "gn:dem":1221,
    "gn:feature_class":"P",
    "gn:feature_code":"PPL",
    "gn:name":"Sautar",
    "gn:population":0,
    "gn:timezone":"Africa/Luanda",
    "iso:country":"AO",
    "wof:name":"Sautar",
    "wof:placetype":"locality"
},
  "geometry": {"coordinates":[19.81667,-12.23333],"type":"Point"}
}