{
  "type": "Feature",
  "properties": {
    "gn:admin1_code":"16.0",
    "gn:asciiname":"Tamba",
    "gn:country_code":"AO",
    "gn:dem":534,
    "gn:feature_class":"P",
    "gn:feature_code":"PPL",
    "gn:name":"Tamba",
    "gn:population":0,
    "gn:timezone":"Africa/Luanda",
    "iso:country":"AO",
    "name:ceb_x_preferred":[
        "Tamba"
    ],
    "name:cym_x_preferred":[
        "Tamba"
    ],
    "name:deu_x_preferred":[
        "Tamba"
    ],
    "name:fra_x_preferred":[
        "Tamba"
    ],
    "name:ind_x_preferred":[
        "Tamba"
    ],
    "name:nld_x_preferred":[
        "Tamba"
    ],
    "name:swe_x_preferred":[
        "Tamba"
    ],
    "wof:name":"Tamba",
    "wof:placetype":"locality"
},
  "geometry": {"coordinates":[14.78333,-6.06667],"type":"Point"}
}