{
  "type": "Feature",
  "properties": {
    "gn:admin1_code":"9.0",
    "gn:asciiname":"Cuandja A",
    "gn:country_code":"AO",
    "gn:dem":1445,
    "gn:feature_class":"P",
    "gn:feature_code":"PPL",
    "gn:name":"Cuandja A",
    "gn:population":0,
    "gn:timezone":"Africa/Luanda",
    "iso:country":"AO",
    "wof:name":"Cuandja A",
    "wof:placetype":"locality"
},
  "geometry": {"coordinates":[16.02187,-14.683],"type":"Point"}
}