{
  "type": "Feature",
  "properties": {
    "gn:admin1_code":"14.0",
    "gn:asciiname":"Caputungo",
    "gn:country_code":"AO",
    "gn:dem":1171,
    "gn:feature_class":"P",
    "gn:feature_code":"PPL",
    "gn:name":"Caputungo",
    "gn:population":0,
    "gn:timezone":"Africa/Luanda",
    "iso:country":"AO",
    "wof:name":"Caputungo",
    "wof:placetype":"locality"
},
  "geometry": {"coordinates":[21.05,-13.13333],"type":"Point"}
}