{
  "type": "Feature",
  "properties": {
    "gn:admin1_code":"1.0",
    "gn:asciiname":"Anhanga",
    "gn:country_code":"AO",
    "gn:dem":1107,
    "gn:feature_class":"P",
    "gn:feature_code":"PPL",
    "gn:name":"Anhanga",
    "gn:population":0,
    "gn:timezone":"Africa/Luanda",
    "iso:country":"AO",
    "wof:name":"Anhanga",
    "wof:placetype":"locality"
},
  "geometry": {"coordinates":[14.51667,-12.06667],"type":"Point"}
}