{
  "type": "Feature",
  "properties": {
    "gn:admin1_code":"14.0",
    "gn:asciiname":"Macouate",
    "gn:cc2":"AO",
    "gn:country_code":"AO",
    "gn:dem":1345,
    "gn:feature_class":"P",
    "gn:feature_code":"PPL",
    "gn:name":"Macouate",
    "gn:population":0,
    "gn:timezone":"Africa/Luanda",
    "iso:country":"AO",
    "name:und_x_variant":[
        "Mucouate",
        "Macouate"
    ],
    "wof:name":"Macouate",
    "wof:placetype":"locality"
},
  "geometry": {"coordinates":[19.33333,-12.51667],"type":"Point"}
}