{
  "type": "Feature",
  "properties": {
    "gn:admin1_code":"8.0",
    "gn:asciiname":"Cambinda",
    "gn:cc2":"AO",
    "gn:country_code":"AO",
    "gn:dem":1544,
    "gn:feature_class":"P",
    "gn:feature_code":"PPL",
    "gn:name":"Cambinda",
    "gn:population":0,
    "gn:timezone":"Africa/Luanda",
    "iso:country":"AO",
    "name:und_x_variant":[
        "Cambinda Cunene",
        "Cambinda"
    ],
    "wof:name":"Cambinda",
    "wof:placetype":"locality"
},
  "geometry": {"coordinates":[15.81667,-13.51667],"type":"Point"}
}