{
  "type": "Feature",
  "properties": {
    "gn:admin1_code":"15.0",
    "gn:asciiname":"Cunga dia Samba",
    "gn:country_code":"AO",
    "gn:dem":808,
    "gn:feature_class":"P",
    "gn:feature_code":"PPL",
    "gn:name":"C\u00fcnga di\u00e1 Samba",
    "gn:population":0,
    "gn:timezone":"Africa/Luanda",
    "iso:country":"AO",
    "name:und_x_variant":[
        "C\u00fcnga di\u00e1 Samba",
        "Cunga"
    ],
    "wof:name":"Cunga dia Samba",
    "wof:placetype":"locality"
},
  "geometry": {"coordinates":[14.95233,-8.09635],"type":"Point"}
}