{
  "type": "Feature",
  "properties": {
    "gn:admin1_code":"8.0",
    "gn:asciiname":"Ecaala",
    "gn:cc2":"AO",
    "gn:country_code":"AO",
    "gn:dem":1355,
    "gn:feature_class":"P",
    "gn:feature_code":"PPL",
    "gn:name":"Ecaala",
    "gn:population":0,
    "gn:timezone":"Africa/Luanda",
    "iso:country":"AO",
    "name:und_x_variant":[
        "Vecala",
        "Ecaala"
    ],
    "wof:name":"Ecaala",
    "wof:placetype":"locality"
},
  "geometry": {"coordinates":[14.93333,-12.78333],"type":"Point"}
}