{
  "type": "Feature",
  "properties": {
    "gn:admin1_code":"8.0",
    "gn:asciiname":"Candjamba",
    "gn:country_code":"AO",
    "gn:dem":2026,
    "gn:feature_class":"P",
    "gn:feature_code":"PPL",
    "gn:name":"Candjamba",
    "gn:population":0,
    "gn:timezone":"Africa/Luanda",
    "iso:country":"AO",
    "wof:name":"Candjamba",
    "wof:placetype":"locality"
},
  "geometry": {"coordinates":[15.39944,-12.60833],"type":"Point"}
}