{
  "type": "Feature",
  "properties": {
    "gn:admin1_code":"19.0",
    "gn:asciiname":"Fazenda Cunga",
    "gn:cc2":"AO",
    "gn:country_code":"AO",
    "gn:dem":8,
    "gn:feature_class":"P",
    "gn:feature_code":"PPL",
    "gn:name":"Fazenda Cunga",
    "gn:population":0,
    "gn:timezone":"Africa/Luanda",
    "iso:country":"AO",
    "name:und_x_variant":[
        "Cango",
        "Kunga",
        "Conga",
        "Cunga",
        "Fazenda Cunga"
    ],
    "wof:name":"Fazenda Cunga",
    "wof:placetype":"locality"
},
  "geometry": {"coordinates":[13.73333,-9.25],"type":"Point"}
}