{
  "type": "Feature",
  "properties": {
    "gn:admin1_code":"18.0",
    "gn:asciiname":"Cassunda",
    "gn:country_code":"AO",
    "gn:dem":1151,
    "gn:feature_class":"P",
    "gn:feature_code":"PPL",
    "gn:name":"Cassunda",
    "gn:population":0,
    "gn:timezone":"Africa/Luanda",
    "iso:country":"AO",
    "wof:name":"Cassunda",
    "wof:placetype":"locality"
},
  "geometry": {"coordinates":[21.05,-10.95],"type":"Point"}
}