{
  "type": "Feature",
  "properties": {
    "gn:admin1_code":"2.0",
    "gn:asciiname":"Cuiva",
    "gn:cc2":"AO",
    "gn:country_code":"AO",
    "gn:dem":1277,
    "gn:feature_class":"P",
    "gn:feature_code":"PPL",
    "gn:name":"Cuiva",
    "gn:population":0,
    "gn:timezone":"Africa/Luanda",
    "iso:country":"AO",
    "name:und_x_variant":[
        "Cuiba",
        "Cuiva"
    ],
    "wof:name":"Cuiva",
    "wof:placetype":"locality"
},
  "geometry": {"coordinates":[17.95,-12.13333],"type":"Point"}
}