{
  "type": "Feature",
  "properties": {
    "gn:admin1_code":"6.0",
    "gn:asciiname":"Chipende",
    "gn:country_code":"AO",
    "gn:dem":1331,
    "gn:feature_class":"P",
    "gn:feature_code":"PPL",
    "gn:name":"Chipende",
    "gn:population":0,
    "gn:timezone":"Africa/Luanda",
    "iso:country":"AO",
    "wof:name":"Chipende",
    "wof:placetype":"locality"
},
  "geometry": {"coordinates":[15.35,-11.75],"type":"Point"}
}