{
  "type": "Feature",
  "properties": {
    "gn:admin1_code":"3.0",
    "gn:asciiname":"Luali",
    "gn:cc2":"AO",
    "gn:country_code":"AO",
    "gn:dem":207,
    "gn:feature_class":"P",
    "gn:feature_code":"PPL",
    "gn:name":"Luali",
    "gn:population":0,
    "gn:timezone":"Africa/Luanda",
    "iso:country":"AO",
    "name:und_x_variant":[
        "Malende",
        "Luali"
    ],
    "wof:name":"Luali",
    "wof:placetype":"locality"
},
  "geometry": {"coordinates":[12.71667,-4.58333],"type":"Point"}
}