{
  "type": "Feature",
  "properties": {
    "gn:admin1_code":"6.0",
    "gn:asciiname":"Alberto",
    "gn:country_code":"AO",
    "gn:dem":1350,
    "gn:feature_class":"P",
    "gn:feature_code":"PPL",
    "gn:name":"Alberto",
    "gn:population":0,
    "gn:timezone":"Africa/Luanda",
    "iso:country":"AO",
    "wof:name":"Alberto",
    "wof:placetype":"locality"
},
  "geometry": {"coordinates":[15.36667,-11.83333],"type":"Point"}
}