{
  "type": "Feature",
  "properties": {
    "gn:admin1_code":"12.0",
    "gn:asciiname":"Sangulo",
    "gn:country_code":"AO",
    "gn:dem":1103,
    "gn:feature_class":"P",
    "gn:feature_code":"PPL",
    "gn:name":"Sangulo",
    "gn:population":0,
    "gn:timezone":"Africa/Luanda",
    "iso:country":"AO",
    "wof:name":"Sangulo",
    "wof:placetype":"locality"
},
  "geometry": {"coordinates":[17.6201,-10.81192],"type":"Point"}
}