{
  "type": "Feature",
  "properties": {
    "gn:admin1_code":"5.0",
    "gn:asciiname":"Quimaco",
    "gn:country_code":"AO",
    "gn:dem":1306,
    "gn:feature_class":"P",
    "gn:feature_code":"PPL",
    "gn:name":"Quimaco",
    "gn:population":0,
    "gn:timezone":"Africa/Luanda",
    "iso:country":"AO",
    "wof:name":"Quimaco",
    "wof:placetype":"locality"
},
  "geometry": {"coordinates":[15.47985,-8.16262],"type":"Point"}
}