{
  "type": "Feature",
  "properties": {
    "gn:admin1_code":"2.0",
    "gn:asciiname":"Caria",
    "gn:country_code":"AO",
    "gn:dem":1704,
    "gn:feature_class":"P",
    "gn:feature_code":"PPL",
    "gn:name":"Caria",
    "gn:population":0,
    "gn:timezone":"Africa/Luanda",
    "iso:country":"AO",
    "wof:name":"Caria",
    "wof:placetype":"locality"
},
  "geometry": {"coordinates":[16.83333,-12.71667],"type":"Point"}
}