{
  "type": "Feature",
  "properties": {
    "gn:admin1_code":"9.0",
    "gn:asciiname":"Maputo",
    "gn:cc2":"AO",
    "gn:country_code":"AO",
    "gn:dem":1117,
    "gn:feature_class":"P",
    "gn:feature_code":"PPL",
    "gn:name":"Maputo",
    "gn:population":0,
    "gn:timezone":"Africa/Luanda",
    "iso:country":"AO",
    "name:und_x_variant":[
        "B\u00e1fua",
        "Maputo"
    ],
    "wof:name":"Maputo",
    "wof:placetype":"locality"
},
  "geometry": {"coordinates":[13.53333,-16.21667],"type":"Point"}
}