{
  "type": "Feature",
  "properties": {
    "gn:admin1_code":"2.0",
    "gn:asciiname":"Savita",
    "gn:country_code":"AO",
    "gn:dem":1659,
    "gn:feature_class":"P",
    "gn:feature_code":"PPL",
    "gn:name":"Savita",
    "gn:population":0,
    "gn:timezone":"Africa/Luanda",
    "iso:country":"AO",
    "name:ceb_x_preferred":[
        "Savita"
    ],
    "name:swe_x_preferred":[
        "Savita"
    ],
    "wof:name":"Savita",
    "wof:placetype":"locality"
},
  "geometry": {"coordinates":[17.10228,-11.51825],"type":"Point"}
}