{
  "type": "Feature",
  "properties": {
    "gn:admin1_code":"8.0",
    "gn:asciiname":"Salongue",
    "gn:cc2":"AO",
    "gn:country_code":"AO",
    "gn:dem":1650,
    "gn:feature_class":"P",
    "gn:feature_code":"PPL",
    "gn:name":"Salongu\u00e9",
    "gn:population":0,
    "gn:timezone":"Africa/Luanda",
    "iso:country":"AO",
    "name:und_x_variant":[
        "Salongo\u00e9",
        "Sangui",
        "Salongu\u00e9"
    ],
    "wof:name":"Salongue",
    "wof:placetype":"locality"
},
  "geometry": {"coordinates":[15.88333,-11.96667],"type":"Point"}
}