{
  "type": "Feature",
  "properties": {
    "gn:admin1_code":"18.0",
    "gn:asciiname":"Dege",
    "gn:country_code":"AO",
    "gn:dem":1142,
    "gn:feature_class":"P",
    "gn:feature_code":"PPL",
    "gn:name":"Dege",
    "gn:population":0,
    "gn:timezone":"Africa/Luanda",
    "iso:country":"AO",
    "name:deu_x_preferred":[
        "Dege"
    ],
    "wof:name":"Dege",
    "wof:placetype":"locality"
},
  "geometry": {"coordinates":[20.96667,-11.36667],"type":"Point"}
}