{
  "type": "Feature",
  "properties": {
    "gn:admin1_code":"5.0",
    "gn:asciiname":"Zenza do Itombe",
    "gn:country_code":"AO",
    "gn:dem":78,
    "gn:feature_class":"P",
    "gn:feature_code":"PPL",
    "gn:name":"Zenza do Itombe",
    "gn:population":0,
    "gn:timezone":"Africa/Luanda",
    "iso:country":"AO",
    "name:und_x_variant":[
        "Cassoalala",
        "Zenza do Itompe",
        "Cassualala",
        "Zenza",
        "Senza",
        "Zenza do Itombe"
    ],
    "wof:name":"Zenza do Itombe",
    "wof:placetype":"locality"
},
  "geometry": {"coordinates":[14.21138,-9.28726],"type":"Point"}
}