{
  "type": "Feature",
  "properties": {
    "gn:admin1_code":"12.0",
    "gn:asciiname":"Gazela",
    "gn:cc2":"AO",
    "gn:country_code":"AO",
    "gn:dem":1200,
    "gn:feature_class":"P",
    "gn:feature_code":"PPL",
    "gn:name":"Gazela",
    "gn:population":0,
    "gn:timezone":"Africa/Luanda",
    "iso:country":"AO",
    "name:und_x_variant":[
        "Cazela",
        "Gazela"
    ],
    "wof:name":"Gazela",
    "wof:placetype":"locality"
},
  "geometry": {"coordinates":[16.65,-9.23333],"type":"Point"}
}