{
  "type": "Feature",
  "properties": {
    "gn:admin1_code":"6.0",
    "gn:asciiname":"Mussengue",
    "gn:country_code":"AO",
    "gn:dem":414,
    "gn:feature_class":"P",
    "gn:feature_code":"PPL",
    "gn:name":"Mussengue",
    "gn:population":0,
    "gn:timezone":"Africa/Luanda",
    "iso:country":"AO",
    "wof:name":"Mussengue",
    "wof:placetype":"locality"
},
  "geometry": {"coordinates":[14.2708,-10.78602],"type":"Point"}
}