{
  "type": "Feature",
  "properties": {
    "gn:admin1_code":"5.0",
    "gn:asciiname":"Mucusso",
    "gn:country_code":"AO",
    "gn:dem":732,
    "gn:feature_class":"P",
    "gn:feature_code":"PPL",
    "gn:name":"Mucusso",
    "gn:population":0,
    "gn:timezone":"Africa/Luanda",
    "iso:country":"AO",
    "wof:name":"Mucusso",
    "wof:placetype":"locality"
},
  "geometry": {"coordinates":[15.18333,-8.31667],"type":"Point"}
}