{
  "type": "Feature",
  "properties": {
    "gn:admin1_code":"5.0",
    "gn:asciiname":"Mucusso",
    "gn:country_code":"AO",
    "gn:dem":732,
    "gn:feature_class":"P",
    "gn:feature_code":"PPL",
    "gn:name":"Mucusso",
    "gn:population":0,
    "gn:timezone":"Africa/Luanda",
    "iso:country":"AO",
    "name:fas_x_preferred":[
        "\u0645\u0648\u06a9\u0648\u0633\u0648"
    ],
    "name:por_x_preferred":[
        "Mucusso"
    ],
    "name:rus_x_preferred":[
        "\u041c\u0443\u043a\u0443\u0441\u0441\u043e"
    ],
    "name:zho_x_preferred":[
        "\u7a46\u5eab\u7d22"
    ],
    "wof:name":"Mucusso",
    "wof:placetype":"locality"
},
  "geometry": {"coordinates":[15.18333,-8.31667],"type":"Point"}
}