{
  "type": "Feature",
  "properties": {
    "gn:admin1_code":"5.0",
    "gn:asciiname":"Mucusso",
    "gn:country_code":"AO",
    "gn:dem":732,
    "gn:feature_class":"P",
    "gn:feature_code":"PPL",
    "gn:name":"Mucusso",
    "gn:population":0,
    "gn:timezone":"Africa/Luanda",
    "iso:country":"AO",
    "name:ara_x_preferred":[
        "\u0645\u0648\u0643\u0648\u0633\u0648"
    ],
    "name:ben_x_preferred":[
        "\u09ae\u09c1\u0995\u09c1\u09b8\u09b8\u09cb"
    ],
    "name:deu_x_preferred":[
        "Mucusso"
    ],
    "name:ell_x_preferred":[
        "\u039c\u03bf\u03c5\u03ba\u03bf\u03cd\u03c3\u03bf"
    ],
    "name:fas_x_preferred":[
        "\u0645\u0648\u06a9\u0648\u0633\u0648"
    ],
    "name:heb_x_preferred":[
        "\u05de\u05d5\u05e7\u05d5\u05e1\u05d5"
    ],
    "name:hin_x_preferred":[
        "\u092e\u0941\u0915\u0941\u0938\u094b"
    ],
    "name:hun_x_preferred":[
        "Mucusso"
    ],
    "name:ind_x_preferred":[
        "Mucusso"
    ],
    "name:ita_x_preferred":[
        "Mucusso"
    ],
    "name:jpn_x_preferred":[
        "\u30e0\u30af\u30c3\u30bd"
    ],
    "name:kor_x_preferred":[
        "\ubb34\ucfe0\uc18c"
    ],
    "name:por_x_preferred":[
        "Mucusso"
    ],
    "name:rus_x_preferred":[
        "\u041c\u0443\u043a\u0443\u0441\u0441\u043e"
    ],
    "name:spa_x_preferred":[
        "Mucusso"
    ],
    "name:swe_x_preferred":[
        "Mucusso"
    ],
    "name:tur_x_preferred":[
        "Mucusso"
    ],
    "name:ukr_x_preferred":[
        "\u041c\u0443\u043a\u0443\u0441\u0441\u043e"
    ],
    "name:urd_x_preferred":[
        "\u0645\u0648\u06a9\u0648\u0633\u0648"
    ],
    "name:vie_x_preferred":[
        "Mucusso"
    ],
    "name:zho_x_preferred":[
        "\u7a46\u5eab\u7d22"
    ],
    "wof:name":"Mucusso",
    "wof:placetype":"locality"
},
  "geometry": {"coordinates":[15.18333,-8.31667],"type":"Point"}
}