{
  "type": "Feature",
  "properties": {
    "gn:admin1_code":"6.0",
    "gn:asciiname":"Ndele",
    "gn:country_code":"AO",
    "gn:dem":727,
    "gn:feature_class":"P",
    "gn:feature_code":"PPL",
    "gn:name":"Ndele",
    "gn:population":0,
    "gn:timezone":"Africa/Luanda",
    "iso:country":"AO",
    "name:ceb_x_preferred":[
        "Ndele"
    ],
    "name:deu_x_preferred":[
        "Ndele"
    ],
    "name:swe_x_preferred":[
        "Ndele"
    ],
    "name:und_x_variant":[
        "Dele"
    ],
    "wof:name":"Ndele",
    "wof:placetype":"locality"
},
  "geometry": {"coordinates":[14.23916,-11.15956],"type":"Point"}
}