{
  "type": "Feature",
  "properties": {
    "gn:admin1_code":"8.0",
    "gn:asciiname":"Sombolo",
    "gn:country_code":"AO",
    "gn:dem":1423,
    "gn:feature_class":"P",
    "gn:feature_code":"PPL",
    "gn:name":"Sombolo",
    "gn:population":0,
    "gn:timezone":"Africa/Luanda",
    "iso:country":"AO",
    "wof:name":"Sombolo",
    "wof:placetype":"locality"
},
  "geometry": {"coordinates":[15.43788,-12.09438],"type":"Point"}
}