{
  "type": "Feature",
  "properties": {
    "gn:admin1_code":"4.0",
    "gn:asciiname":"Tchihongo",
    "gn:country_code":"AO",
    "gn:dem":1386,
    "gn:feature_class":"P",
    "gn:feature_code":"PPL",
    "gn:name":"Tchihongo",
    "gn:population":0,
    "gn:timezone":"Africa/Luanda",
    "iso:country":"AO",
    "wof:name":"Tchihongo",
    "wof:placetype":"locality"
},
  "geometry": {"coordinates":[17.71981,-14.56146],"type":"Point"}
}