{
  "type": "Feature",
  "properties": {
    "gn:admin1_code":"12.0",
    "gn:asciiname":"Quiandongo",
    "gn:country_code":"AO",
    "gn:dem":948,
    "gn:feature_class":"P",
    "gn:feature_code":"PPL",
    "gn:name":"Quiandongo",
    "gn:population":0,
    "gn:timezone":"Africa/Luanda",
    "iso:country":"AO",
    "wof:name":"Quiandongo",
    "wof:placetype":"locality"
},
  "geometry": {"coordinates":[15.75,-9.21667],"type":"Point"}
}