{
  "type": "Feature",
  "properties": {
    "gn:admin1_code":"12.0",
    "gn:asciiname":"Cabonde",
    "gn:country_code":"AO",
    "gn:dem":1148,
    "gn:feature_class":"P",
    "gn:feature_code":"PPL",
    "gn:name":"Cabonde",
    "gn:population":0,
    "gn:timezone":"Africa/Luanda",
    "iso:country":"AO",
    "wof:name":"Cabonde",
    "wof:placetype":"locality"
},
  "geometry": {"coordinates":[17.47881,-10.81966],"type":"Point"}
}