{
  "type": "Feature",
  "properties": {
    "gn:admin1_code":"8.0",
    "gn:asciiname":"Catongalo",
    "gn:country_code":"AO",
    "gn:dem":1598,
    "gn:feature_class":"P",
    "gn:feature_code":"PPL",
    "gn:name":"Catongalo",
    "gn:population":0,
    "gn:timezone":"Africa/Luanda",
    "iso:country":"AO",
    "wof:name":"Catongalo",
    "wof:placetype":"locality"
},
  "geometry": {"coordinates":[15.88333,-11.58333],"type":"Point"}
}