{
  "type": "Feature",
  "properties": {
    "gn:admin1_code":"15.0",
    "gn:asciiname":"Canda",
    "gn:country_code":"AO",
    "gn:dem":925,
    "gn:feature_class":"P",
    "gn:feature_code":"PPL",
    "gn:name":"Canda",
    "gn:population":0,
    "gn:timezone":"Africa/Luanda",
    "iso:country":"AO",
    "name:azb_x_preferred":[
        "\u06a9\u0627\u0646\u062f\u0627"
    ],
    "name:bel_x_preferred":[
        "\u041a\u0430\u043d\u0434\u0430"
    ],
    "name:bul_x_preferred":[
        "\u041a\u0430\u043d\u0434\u0430"
    ],
    "name:ceb_x_preferred":[
        "Canda"
    ],
    "name:deu_x_preferred":[
        "Canda"
    ],
    "name:epo_x_preferred":[
        "Canda"
    ],
    "name:eus_x_preferred":[
        "Canda"
    ],
    "name:fas_x_preferred":[
        "\u06a9\u0627\u0646\u062f\u0627"
    ],
    "name:fra_x_preferred":[
        "Canda"
    ],
    "name:hun_x_preferred":[
        "Canda"
    ],
    "name:hye_x_preferred":[
        "\u053f\u0561\u0576\u0564\u0561"
    ],
    "name:ind_x_preferred":[
        "Canda"
    ],
    "name:ita_x_preferred":[
        "Canda"
    ],
    "name:jpn_x_preferred":[
        "\u30ab\u30f3\u30c0"
    ],
    "name:kaz_x_preferred":[
        "\u041a\u0430\u043d\u0434\u0430"
    ],
    "name:lat_x_preferred":[
        "Canda"
    ],
    "name:lmo_x_preferred":[
        "Canda"
    ],
    "name:msa_x_preferred":[
        "Canda"
    ],
    "name:nap_x_preferred":[
        "Canda"
    ],
    "name:nld_x_preferred":[
        "Canda"
    ],
    "name:pms_x_preferred":[
        "Canda"
    ],
    "name:pol_x_preferred":[
        "Canda"
    ],
    "name:por_x_preferred":[
        "Canda"
    ],
    "name:ron_x_preferred":[
        "Canda"
    ],
    "name:rus_x_preferred":[
        "\u041a\u0430\u043d\u0434\u0430"
    ],
    "name:scn_x_preferred":[
        "Canda"
    ],
    "name:spa_x_preferred":[
        "Canda"
    ],
    "name:srp_x_preferred":[
        "\u041a\u0430\u043d\u0434\u0430"
    ],
    "name:ukr_x_preferred":[
        "\u041a\u0430\u043d\u0434\u0430"
    ],
    "name:und_x_variant":[
        "Quicombo",
        "Canda"
    ],
    "name:uzb_x_preferred":[
        "Canda"
    ],
    "name:vec_x_preferred":[
        "Canda"
    ],
    "name:vie_x_preferred":[
        "Canda"
    ],
    "name:vol_x_preferred":[
        "Canda"
    ],
    "name:war_x_preferred":[
        "Canda"
    ],
    "wof:name":"Canda",
    "wof:placetype":"locality"
},
  "geometry": {"coordinates":[15.58854,-6.44109],"type":"Point"}
}