{
  "type": "Feature",
  "properties": {
    "gn:admin1_code":"15.0",
    "gn:asciiname":"Canda",
    "gn:country_code":"AO",
    "gn:dem":925,
    "gn:feature_class":"P",
    "gn:feature_code":"PPL",
    "gn:name":"Canda",
    "gn:population":0,
    "gn:timezone":"Africa/Luanda",
    "iso:country":"AO",
    "name:und_x_variant":[
        "Quicombo",
        "Canda"
    ],
    "wof:name":"Canda",
    "wof:placetype":"locality"
},
  "geometry": {"coordinates":[15.58854,-6.44109],"type":"Point"}
}