{
  "type": "Feature",
  "properties": {
    "gn:admin1_code":"15.0",
    "gn:asciiname":"Canambo",
    "gn:country_code":"AO",
    "gn:dem":557,
    "gn:feature_class":"P",
    "gn:feature_code":"PPL",
    "gn:name":"Canambo",
    "gn:population":0,
    "gn:timezone":"Africa/Luanda",
    "iso:country":"AO",
    "name:und_x_variant":[
        "S\u00e3o Conzo",
        "Cananxo",
        "S\u00e3o Konzo",
        "Canambo"
    ],
    "wof:name":"Canambo",
    "wof:placetype":"locality"
},
  "geometry": {"coordinates":[16.5333,-6.16274],"type":"Point"}
}