{
  "type": "Feature",
  "properties": {
    "gn:admin1_code":"7.0",
    "gn:asciiname":"Dombondola",
    "gn:cc2":"AO",
    "gn:country_code":"AO",
    "gn:dem":1122,
    "gn:feature_class":"P",
    "gn:feature_code":"PPL",
    "gn:name":"Dombondola",
    "gn:population":0,
    "gn:timezone":"Africa/Luanda",
    "iso:country":"AO",
    "name:und_x_variant":[
        "Forte Henrique Couceiro",
        "Dombondola"
    ],
    "wof:name":"Dombondola",
    "wof:placetype":"locality"
},
  "geometry": {"coordinates":[14.83333,-17.33333],"type":"Point"}
}