{
  "type": "Feature",
  "properties": {
    "gn:admin1_code":"15.0",
    "gn:asciiname":"Quisseque Bendo",
    "gn:country_code":"AO",
    "gn:dem":1249,
    "gn:feature_class":"P",
    "gn:feature_code":"PPL",
    "gn:name":"Quisseque Bendo",
    "gn:population":0,
    "gn:timezone":"Africa/Luanda",
    "iso:country":"AO",
    "wof:name":"Quisseque Bendo",
    "wof:placetype":"locality"
},
  "geometry": {"coordinates":[15.54305,-7.71255],"type":"Point"}
}