{
  "type": "Feature",
  "properties": {
    "gn:admin1_code":"15.0",
    "gn:asciiname":"Dinha",
    "gn:country_code":"AO",
    "gn:dem":1175,
    "gn:feature_class":"P",
    "gn:feature_code":"PPL",
    "gn:name":"Dinha",
    "gn:population":0,
    "gn:timezone":"Africa/Luanda",
    "iso:country":"AO",
    "name:und_x_variant":[
        "Linha",
        "Dinha"
    ],
    "wof:name":"Dinha",
    "wof:placetype":"locality"
},
  "geometry": {"coordinates":[15.98448,-8.09637],"type":"Point"}
}