{
  "type": "Feature",
  "properties": {
    "gn:admin1_code":"17.0",
    "gn:asciiname":"Culo",
    "gn:country_code":"AO",
    "gn:dem":757,
    "gn:feature_class":"P",
    "gn:feature_code":"PPL",
    "gn:name":"Culo",
    "gn:population":0,
    "gn:timezone":"Africa/Luanda",
    "iso:country":"AO",
    "wof:name":"Culo",
    "wof:placetype":"locality"
},
  "geometry": {"coordinates":[17.72631,-9.20229],"type":"Point"}
}