{
  "type": "Feature",
  "properties": {
    "gn:admin1_code":"2.0",
    "gn:asciiname":"Satchingongo",
    "gn:country_code":"AO",
    "gn:dem":1645,
    "gn:feature_class":"P",
    "gn:feature_code":"PPL",
    "gn:name":"Satchingongo",
    "gn:population":0,
    "gn:timezone":"Africa/Luanda",
    "iso:country":"AO",
    "wof:name":"Satchingongo",
    "wof:placetype":"locality"
},
  "geometry": {"coordinates":[17.16283,-11.89299],"type":"Point"}
}