{
  "type": "Feature",
  "properties": {
    "gn:admin1_code":"6.0",
    "gn:asciiname":"Congulo",
    "gn:country_code":"AO",
    "gn:dem":291,
    "gn:feature_class":"P",
    "gn:feature_code":"PPL",
    "gn:name":"Congulo",
    "gn:population":0,
    "gn:timezone":"Africa/Luanda",
    "iso:country":"AO",
    "wof:name":"Congulo",
    "wof:placetype":"locality"
},
  "geometry": {"coordinates":[14.24844,-10.88973],"type":"Point"}
}