{
  "type": "Feature",
  "properties": {
    "gn:admin1_code":"14.0",
    "gn:asciiname":"Lirica",
    "gn:country_code":"AO",
    "gn:dem":1051,
    "gn:feature_class":"P",
    "gn:feature_code":"PPL",
    "gn:name":"Lirica",
    "gn:population":0,
    "gn:timezone":"Africa/Luanda",
    "iso:country":"AO",
    "wof:name":"Lirica",
    "wof:placetype":"locality"
},
  "geometry": {"coordinates":[21.98333,-14.45],"type":"Point"}
}