{
  "type": "Feature",
  "properties": {
    "gn:admin1_code":"17.0",
    "gn:asciiname":"Nzembue",
    "gn:country_code":"AO",
    "gn:dem":999,
    "gn:feature_class":"P",
    "gn:feature_code":"PPL",
    "gn:name":"Nzembue",
    "gn:population":0,
    "gn:timezone":"Africa/Luanda",
    "iso:country":"AO",
    "wof:name":"Nzembue",
    "wof:placetype":"locality"
},
  "geometry": {"coordinates":[17.75427,-9.53562],"type":"Point"}
}