{
  "type": "Feature",
  "properties": {
    "gn:admin1_code":"6.0",
    "gn:asciiname":"Calembe",
    "gn:country_code":"AO",
    "gn:dem":1068,
    "gn:feature_class":"P",
    "gn:feature_code":"PPL",
    "gn:name":"Calembe",
    "gn:population":0,
    "gn:timezone":"Africa/Luanda",
    "iso:country":"AO",
    "wof:name":"Calembe",
    "wof:placetype":"locality"
},
  "geometry": {"coordinates":[14.37509,-11.16783],"type":"Point"}
}