{
  "type": "Feature",
  "properties": {
    "gn:admin1_code":"12.0",
    "gn:asciiname":"Ngola Quiluange",
    "gn:country_code":"AO",
    "gn:dem":1281,
    "gn:feature_class":"P",
    "gn:feature_code":"PPL",
    "gn:name":"Ngola Quiluange",
    "gn:population":0,
    "gn:timezone":"Africa/Luanda",
    "iso:country":"AO",
    "wof:name":"Ngola Quiluange",
    "wof:placetype":"locality"
},
  "geometry": {"coordinates":[16.02518,-8.3992],"type":"Point"}
}