{
  "type": "Feature",
  "properties": {
    "gn:admin1_code":"3.0",
    "gn:asciiname":"Chimbete",
    "gn:cc2":"AO",
    "gn:country_code":"AO",
    "gn:dem":229,
    "gn:feature_class":"P",
    "gn:feature_code":"PPL",
    "gn:name":"Chimbete",
    "gn:population":0,
    "gn:timezone":"Africa/Luanda",
    "iso:country":"AO",
    "name:und_x_variant":[
        "Chimbette",
        "Chimbezi",
        "Chimbelte",
        "Chimbete"
    ],
    "wof:name":"Chimbete",
    "wof:placetype":"locality"
},
  "geometry": {"coordinates":[12.56667,-4.63333],"type":"Point"}
}