{
  "type": "Feature",
  "properties": {
    "gn:admin1_code":"6.0",
    "gn:asciiname":"Banza",
    "gn:cc2":"AO",
    "gn:country_code":"AO",
    "gn:dem":1159,
    "gn:feature_class":"P",
    "gn:feature_code":"PPL",
    "gn:name":"Banza",
    "gn:population":0,
    "gn:timezone":"Africa/Luanda",
    "iso:country":"AO",
    "name:ceb_x_preferred":[
        "Banza"
    ],
    "name:swe_x_preferred":[
        "Banza"
    ],
    "name:und_x_variant":[
        "Bango",
        "Banga",
        "Banza"
    ],
    "wof:name":"Banza",
    "wof:placetype":"locality"
},
  "geometry": {"coordinates":[14.95,-10.28333],"type":"Point"}
}