{
  "type": "Feature",
  "properties": {
    "gn:admin1_code":"17.0",
    "gn:asciiname":"Safamba",
    "gn:country_code":"AO",
    "gn:dem":843,
    "gn:feature_class":"P",
    "gn:feature_code":"PPL",
    "gn:name":"Safamba",
    "gn:population":0,
    "gn:timezone":"Africa/Luanda",
    "iso:country":"AO",
    "wof:name":"Safamba",
    "wof:placetype":"locality"
},
  "geometry": {"coordinates":[21.26286,-7.68927],"type":"Point"}
}