{
  "type": "Feature",
  "properties": {
    "gn:admin1_code":"20.0",
    "gn:asciiname":"Soares",
    "gn:country_code":"AO",
    "gn:dem":2,
    "gn:feature_class":"P",
    "gn:feature_code":"PPL",
    "gn:name":"Soares",
    "gn:population":0,
    "gn:timezone":"Africa/Luanda",
    "iso:country":"AO",
    "name:por_x_preferred":[
        "Soares"
    ],
    "wof:name":"Soares",
    "wof:placetype":"locality"
},
  "geometry": {"coordinates":[13.29114,-9.16505],"type":"Point"}
}