{
  "type": "Feature",
  "properties": {
    "gn:admin1_code":"9.0",
    "gn:asciiname":"Candungo",
    "gn:cc2":"AO",
    "gn:country_code":"AO",
    "gn:dem":1484,
    "gn:feature_class":"P",
    "gn:feature_code":"PPL",
    "gn:name":"Candungo",
    "gn:population":0,
    "gn:timezone":"Africa/Luanda",
    "iso:country":"AO",
    "name:und_x_variant":[
        "Muongo",
        "Candungo"
    ],
    "wof:name":"Candungo",
    "wof:placetype":"locality"
},
  "geometry": {"coordinates":[15.73333,-13.93333],"type":"Point"}
}