{
  "type": "Feature",
  "properties": {
    "gn:admin1_code":"17.0",
    "gn:asciiname":"Satcheginga",
    "gn:country_code":"AO",
    "gn:dem":1055,
    "gn:feature_class":"P",
    "gn:feature_code":"PPL",
    "gn:name":"Satcheginga",
    "gn:population":0,
    "gn:timezone":"Africa/Luanda",
    "iso:country":"AO",
    "wof:name":"Satcheginga",
    "wof:placetype":"locality"
},
  "geometry": {"coordinates":[19.52376,-8.23953],"type":"Point"}
}