{
  "type": "Feature",
  "properties": {
    "gn:admin1_code":"17.0",
    "gn:asciiname":"Luembe",
    "gn:cc2":"AO",
    "gn:country_code":"AO",
    "gn:dem":680,
    "gn:feature_class":"P",
    "gn:feature_code":"PPL",
    "gn:name":"Luembe",
    "gn:population":0,
    "gn:timezone":"Africa/Luanda",
    "iso:country":"AO",
    "name:und_x_variant":[
        "Luembi",
        "Luembe"
    ],
    "wof:name":"Luembe",
    "wof:placetype":"locality"
},
  "geometry": {"coordinates":[21.18333,-7.31667],"type":"Point"}
}