{
  "type": "Feature",
  "properties": {
    "gn:admin1_code":"5.0",
    "gn:asciiname":"Canaulo Primeiro",
    "gn:country_code":"AO",
    "gn:dem":752,
    "gn:feature_class":"P",
    "gn:feature_code":"PPL",
    "gn:name":"Cana\u00falo Primeiro",
    "gn:population":0,
    "gn:timezone":"Africa/Luanda",
    "iso:country":"AO",
    "wof:name":"Canaulo Primeiro",
    "wof:placetype":"locality"
},
  "geometry": {"coordinates":[14.85147,-9.13206],"type":"Point"}
}