{
  "type": "Feature",
  "properties": {
    "gn:admin1_code":"15.0",
    "gn:asciiname":"Mbanza Quimbungo",
    "gn:country_code":"AO",
    "gn:dem":888,
    "gn:feature_class":"P",
    "gn:feature_code":"PPL",
    "gn:name":"Mbanza Quimbungo",
    "gn:population":0,
    "gn:timezone":"Africa/Luanda",
    "iso:country":"AO",
    "wof:name":"Mbanza Quimbungo",
    "wof:placetype":"locality"
},
  "geometry": {"coordinates":[15.0036,-6.01886],"type":"Point"}
}