{
  "type": "Feature",
  "properties": {
    "gn:admin1_code":"14.0",
    "gn:asciiname":"Samussamba",
    "gn:cc2":"AO",
    "gn:country_code":"AO",
    "gn:dem":1307,
    "gn:feature_class":"P",
    "gn:feature_code":"PPL",
    "gn:name":"Samussamba",
    "gn:population":0,
    "gn:timezone":"Africa/Luanda",
    "iso:country":"AO",
    "name:und_x_variant":[
        "Samba",
        "Samussamba"
    ],
    "wof:name":"Samussamba",
    "wof:placetype":"locality"
},
  "geometry": {"coordinates":[19.06667,-12.25],"type":"Point"}
}