{
  "type": "Feature",
  "properties": {
    "gn:admin1_code":"15.0",
    "gn:asciiname":"Cena Maianga",
    "gn:country_code":"AO",
    "gn:dem":1022,
    "gn:feature_class":"P",
    "gn:feature_code":"PPL",
    "gn:name":"Cena Maianga",
    "gn:population":0,
    "gn:timezone":"Africa/Luanda",
    "iso:country":"AO",
    "wof:name":"Cena Maianga",
    "wof:placetype":"locality"
},
  "geometry": {"coordinates":[15.84991,-7.29918],"type":"Point"}
}