{
  "type": "Feature",
  "properties": {
    "gn:admin1_code":"12.0",
    "gn:asciiname":"Macongo",
    "gn:country_code":"AO",
    "gn:dem":688,
    "gn:feature_class":"P",
    "gn:feature_code":"PPL",
    "gn:name":"Macongo",
    "gn:population":0,
    "gn:timezone":"Africa/Luanda",
    "iso:country":"AO",
    "wof:name":"Macongo",
    "wof:placetype":"locality"
},
  "geometry": {"coordinates":[16.8351,-7.86581],"type":"Point"}
}