{
  "type": "Feature",
  "properties": {
    "gn:admin1_code":"12.0",
    "gn:asciiname":"Mutonga",
    "gn:country_code":"AO",
    "gn:dem":1336,
    "gn:feature_class":"P",
    "gn:feature_code":"PPL",
    "gn:name":"Mutonga",
    "gn:population":0,
    "gn:timezone":"Africa/Luanda",
    "iso:country":"AO",
    "wof:name":"Mutonga",
    "wof:placetype":"locality"
},
  "geometry": {"coordinates":[17.94687,-10.19803],"type":"Point"}
}