{
  "type": "Feature",
  "properties": {
    "gn:admin1_code":"7.0",
    "gn:asciiname":"Techitocota",
    "gn:cc2":"AO",
    "gn:country_code":"AO",
    "gn:dem":1127,
    "gn:feature_class":"P",
    "gn:feature_code":"PPL",
    "gn:name":"Techitocota",
    "gn:population":0,
    "gn:timezone":"Africa/Luanda",
    "iso:country":"AO",
    "name:und_x_variant":[
        "Tchitocota",
        "Techitocota"
    ],
    "wof:name":"Techitocota",
    "wof:placetype":"locality"
},
  "geometry": {"coordinates":[15.05,-16.51667],"type":"Point"}
}