{
  "type": "Feature",
  "properties": {
    "gn:admin1_code":"2.0",
    "gn:asciiname":"Longondji",
    "gn:country_code":"AO",
    "gn:dem":1708,
    "gn:feature_class":"P",
    "gn:feature_code":"PPL",
    "gn:name":"Longondji",
    "gn:population":0,
    "gn:timezone":"Africa/Luanda",
    "iso:country":"AO",
    "wof:name":"Longondji",
    "wof:placetype":"locality"
},
  "geometry": {"coordinates":[16.96746,-11.60568],"type":"Point"}
}