{
  "type": "Feature",
  "properties": {
    "gn:admin1_code":"15.0",
    "gn:asciiname":"Quipembe",
    "gn:country_code":"AO",
    "gn:dem":1229,
    "gn:feature_class":"P",
    "gn:feature_code":"PPL",
    "gn:name":"Quipembe",
    "gn:population":0,
    "gn:timezone":"Africa/Luanda",
    "iso:country":"AO",
    "name:und_x_variant":[
        "Quipambe",
        "Quipembe"
    ],
    "wof:name":"Quipembe",
    "wof:placetype":"locality"
},
  "geometry": {"coordinates":[15.26167,-7.63985],"type":"Point"}
}