{
  "type": "Feature",
  "properties": {
    "gn:admin1_code":"19.0",
    "gn:asciiname":"Lobano",
    "gn:country_code":"AO",
    "gn:dem":228,
    "gn:feature_class":"P",
    "gn:feature_code":"PPL",
    "gn:name":"Lobano",
    "gn:population":0,
    "gn:timezone":"Africa/Luanda",
    "iso:country":"AO",
    "wof:name":"Lobano",
    "wof:placetype":"locality"
},
  "geometry": {"coordinates":[14.05,-8.71667],"type":"Point"}
}