{
  "type": "Feature",
  "properties": {
    "gn:admin1_code":"2.0",
    "gn:asciiname":"Nedegiva",
    "gn:cc2":"AO",
    "gn:country_code":"AO",
    "gn:dem":1434,
    "gn:feature_class":"P",
    "gn:feature_code":"PPL",
    "gn:name":"Nedegiva",
    "gn:population":0,
    "gn:timezone":"Africa/Luanda",
    "iso:country":"AO",
    "name:und_x_variant":[
        "Nedegiva do Cusseque",
        "Nedegiva"
    ],
    "wof:name":"Nedegiva",
    "wof:placetype":"locality"
},
  "geometry": {"coordinates":[17.13332999999999,-14.08333],"type":"Point"}
}