{
  "type": "Feature",
  "properties": {
    "gn:admin1_code":"17.0",
    "gn:asciiname":"Tchamaxingo",
    "gn:country_code":"AO",
    "gn:dem":1078,
    "gn:feature_class":"P",
    "gn:feature_code":"PPL",
    "gn:name":"Tchamaxingo",
    "gn:population":0,
    "gn:timezone":"Africa/Luanda",
    "iso:country":"AO",
    "wof:name":"Tchamaxingo",
    "wof:placetype":"locality"
},
  "geometry": {"coordinates":[18.71026,-9.55804],"type":"Point"}
}