{
  "type": "Feature",
  "properties": {
    "gn:admin1_code":"19.0",
    "gn:asciiname":"Gama",
    "gn:country_code":"AO",
    "gn:dem":8,
    "gn:feature_class":"P",
    "gn:feature_code":"PPL",
    "gn:name":"Gama",
    "gn:population":0,
    "gn:timezone":"Africa/Luanda",
    "iso:country":"AO",
    "wof:name":"Gama",
    "wof:placetype":"locality"
},
  "geometry": {"coordinates":[13.47639,-8.5675],"type":"Point"}
}