{
  "type": "Feature",
  "properties": {
    "gn:admin1_code":"12.0",
    "gn:asciiname":"Nzagi",
    "gn:country_code":"AO",
    "gn:dem":942,
    "gn:feature_class":"P",
    "gn:feature_code":"PPL",
    "gn:name":"Nzagi",
    "gn:population":0,
    "gn:timezone":"Africa/Luanda",
    "iso:country":"AO",
    "wof:name":"Nzagi",
    "wof:placetype":"locality"
},
  "geometry": {"coordinates":[18.4509,-9.87684],"type":"Point"}
}