{
  "type": "Feature",
  "properties": {
    "gn:admin1_code":"2.0",
    "gn:asciiname":"Techiamba",
    "gn:cc2":"AO",
    "gn:country_code":"AO",
    "gn:dem":1623,
    "gn:feature_class":"P",
    "gn:feature_code":"PPL",
    "gn:name":"Techiamba",
    "gn:population":0,
    "gn:timezone":"Africa/Luanda",
    "iso:country":"AO",
    "name:und_x_variant":[
        "Cuamba",
        "Techiamba"
    ],
    "wof:name":"Techiamba",
    "wof:placetype":"locality"
},
  "geometry": {"coordinates":[16.68333,-13.28333],"type":"Point"}
}