{
  "type": "Feature",
  "properties": {
    "gn:admin1_code":"16.0",
    "gn:asciiname":"Longua",
    "gn:country_code":"AO",
    "gn:dem":305,
    "gn:feature_class":"P",
    "gn:feature_code":"PPL",
    "gn:name":"Longua",
    "gn:population":0,
    "gn:timezone":"Africa/Luanda",
    "iso:country":"AO",
    "wof:name":"Longua",
    "wof:placetype":"locality"
},
  "geometry": {"coordinates":[13.49589,-5.92058],"type":"Point"}
}