{
  "type": "Feature",
  "properties": {
    "gn:admin1_code":"15.0",
    "gn:asciiname":"Quitamba",
    "gn:country_code":"AO",
    "gn:dem":1184,
    "gn:feature_class":"P",
    "gn:feature_code":"PPL",
    "gn:name":"Quitamba",
    "gn:population":0,
    "gn:timezone":"Africa/Luanda",
    "iso:country":"AO",
    "wof:name":"Quitamba",
    "wof:placetype":"locality"
},
  "geometry": {"coordinates":[15.16995,-7.28215],"type":"Point"}
}