{
  "type": "Feature",
  "properties": {
    "gn:admin1_code":"17.0",
    "gn:asciiname":"Muhungo a Hita",
    "gn:country_code":"AO",
    "gn:dem":679,
    "gn:feature_class":"P",
    "gn:feature_code":"PPL",
    "gn:name":"Muhungo \u00e0 Hita",
    "gn:population":0,
    "gn:timezone":"Africa/Luanda",
    "iso:country":"AO",
    "name:und_x_variant":[
        "Muhungo",
        "Muhungo-i\u00e1-Ita",
        "Mungaida",
        "Muhungo \u00e0 Hita"
    ],
    "wof:name":"Muhungo a Hita",
    "wof:placetype":"locality"
},
  "geometry": {"coordinates":[17.55867000000001,-9.19984],"type":"Point"}
}