{
  "type": "Feature",
  "properties": {
    "gn:admin1_code":"6.0",
    "gn:asciiname":"Lagoa Quilembuegi",
    "gn:country_code":"AO",
    "gn:dem":44,
    "gn:feature_class":"P",
    "gn:feature_code":"PPLL",
    "gn:name":"Lagoa Quilembuegi",
    "gn:population":0,
    "gn:timezone":"Africa/Luanda",
    "iso:country":"AO",
    "wof:name":"Lagoa Quilembuegi",
    "wof:placetype":"locality"
},
  "geometry": {"coordinates":[14.19975,-10.29897],"type":"Point"}
}