{
  "type": "Feature",
  "properties": {
    "gn:admin1_code":"15.0",
    "gn:asciiname":"Camatambo",
    "gn:country_code":"AO",
    "gn:dem":879,
    "gn:feature_class":"P",
    "gn:feature_code":"PPL",
    "gn:name":"Camatambo",
    "gn:population":0,
    "gn:timezone":"Africa/Luanda",
    "iso:country":"AO",
    "name:und_x_variant":[
        "Kamatambo",
        "Camatambo"
    ],
    "wof:name":"Camatambo",
    "wof:placetype":"locality"
},
  "geometry": {"coordinates":[15.31514,-6.5054],"type":"Point"}
}