{
  "type": "Feature",
  "properties": {
    "gn:admin1_code":"8.0",
    "gn:asciiname":"Chongorola",
    "gn:cc2":"AO",
    "gn:country_code":"AO",
    "gn:dem":1721,
    "gn:feature_class":"P",
    "gn:feature_code":"PPL",
    "gn:name":"Chongorola",
    "gn:population":0,
    "gn:timezone":"Africa/Luanda",
    "iso:country":"AO",
    "name:und_x_variant":[
        "Chingorolo",
        "Chongorola"
    ],
    "wof:name":"Chongorola",
    "wof:placetype":"locality"
},
  "geometry": {"coordinates":[16.13332999999999,-13.03333],"type":"Point"}
}