{
  "type": "Feature",
  "properties": {
    "gn:admin1_code":"17.0",
    "gn:asciiname":"Muafunga",
    "gn:country_code":"AO",
    "gn:dem":1058,
    "gn:feature_class":"P",
    "gn:feature_code":"PPL",
    "gn:name":"Muafunga",
    "gn:population":0,
    "gn:timezone":"Africa/Luanda",
    "iso:country":"AO",
    "wof:name":"Muafunga",
    "wof:placetype":"locality"
},
  "geometry": {"coordinates":[19.95855,-9.14174],"type":"Point"}
}