{
  "type": "Feature",
  "properties": {
    "gn:admin1_code":"18.0",
    "gn:asciiname":"Mahamba",
    "gn:country_code":"AO",
    "gn:dem":1368,
    "gn:feature_class":"P",
    "gn:feature_code":"PPL",
    "gn:name":"Mahamba",
    "gn:population":0,
    "gn:timezone":"Africa/Luanda",
    "iso:country":"AO",
    "wof:name":"Mahamba",
    "wof:placetype":"locality"
},
  "geometry": {"coordinates":[19.6402,-11.12201],"type":"Point"}
}