{
  "type": "Feature",
  "properties": {
    "gn:admin1_code":"15.0",
    "gn:asciiname":"Banza Lucunga",
    "gn:country_code":"AO",
    "gn:dem":1312,
    "gn:feature_class":"P",
    "gn:feature_code":"PPL",
    "gn:name":"Banza Lucunga",
    "gn:population":0,
    "gn:timezone":"Africa/Luanda",
    "iso:country":"AO",
    "name:und_x_variant":[
        "Lucunga",
        "Banza Lucunga"
    ],
    "wof:name":"Banza Lucunga",
    "wof:placetype":"locality"
},
  "geometry": {"coordinates":[15.27539,-7.56844],"type":"Point"}
}