{
  "type": "Feature",
  "properties": {
    "gn:admin1_code":"9.0",
    "gn:asciiname":"Tchiandungo",
    "gn:country_code":"AO",
    "gn:dem":1452,
    "gn:feature_class":"P",
    "gn:feature_code":"PPL",
    "gn:name":"Tchiandungo",
    "gn:population":0,
    "gn:timezone":"Africa/Luanda",
    "iso:country":"AO",
    "wof:name":"Tchiandungo",
    "wof:placetype":"locality"
},
  "geometry": {"coordinates":[15.73549,-14.55278],"type":"Point"}
}