{
  "type": "Feature",
  "properties": {
    "gn:admin1_code":"15.0",
    "gn:asciiname":"Quicage",
    "gn:country_code":"AO",
    "gn:dem":1242,
    "gn:feature_class":"P",
    "gn:feature_code":"PPL",
    "gn:name":"Quicage",
    "gn:population":0,
    "gn:timezone":"Africa/Luanda",
    "iso:country":"AO",
    "wof:name":"Quicage",
    "wof:placetype":"locality"
},
  "geometry": {"coordinates":[15.12842,-7.37811],"type":"Point"}
}