{
  "type": "Feature",
  "properties": {
    "gn:admin1_code":"5.0",
    "gn:asciiname":"Quipete",
    "gn:country_code":"AO",
    "gn:dem":974,
    "gn:feature_class":"P",
    "gn:feature_code":"PPL",
    "gn:name":"Quipete",
    "gn:population":0,
    "gn:timezone":"Africa/Luanda",
    "iso:country":"AO",
    "name:und_x_variant":[
        "Quip\u00eato",
        "Banza Quipete",
        "Quipete"
    ],
    "wof:name":"Quipete",
    "wof:placetype":"locality"
},
  "geometry": {"coordinates":[15.27781,-8.7277],"type":"Point"}
}