{
  "type": "Feature",
  "properties": {
    "gn:admin1_code":"8.0",
    "gn:asciiname":"Jacinto",
    "gn:country_code":"AO",
    "gn:dem":1530,
    "gn:feature_class":"P",
    "gn:feature_code":"PPL",
    "gn:name":"Jacinto",
    "gn:population":0,
    "gn:timezone":"Africa/Luanda",
    "iso:country":"AO",
    "wof:name":"Jacinto",
    "wof:placetype":"locality"
},
  "geometry": {"coordinates":[15.71667,-12.05],"type":"Point"}
}