{
  "type": "Feature",
  "properties": {
    "gn:admin1_code":"8.0",
    "gn:asciiname":"Quissango",
    "gn:cc2":"AO",
    "gn:country_code":"AO",
    "gn:dem":1482,
    "gn:feature_class":"P",
    "gn:feature_code":"PPL",
    "gn:name":"Quissango",
    "gn:population":0,
    "gn:timezone":"Africa/Luanda",
    "iso:country":"AO",
    "name:und_x_variant":[
        "Essango",
        "Quissango"
    ],
    "wof:name":"Quissango",
    "wof:placetype":"locality"
},
  "geometry": {"coordinates":[15.78333,-12.43333],"type":"Point"}
}