{
  "type": "Feature",
  "properties": {
    "gn:admin1_code":"14.0",
    "gn:asciiname":"Sacuando",
    "gn:country_code":"AO",
    "gn:dem":1096,
    "gn:feature_class":"P",
    "gn:feature_code":"PPL",
    "gn:name":"Sacuando",
    "gn:population":0,
    "gn:timezone":"Africa/Luanda",
    "iso:country":"AO",
    "wof:name":"Sacuando",
    "wof:placetype":"locality"
},
  "geometry": {"coordinates":[21.78333,-13.95],"type":"Point"}
}