{
  "type": "Feature",
  "properties": {
    "gn:admin1_code":"15.0",
    "gn:asciiname":"Nsosso",
    "gn:country_code":"AO",
    "gn:dem":819,
    "gn:feature_class":"P",
    "gn:feature_code":"PPL",
    "gn:name":"Nsosso",
    "gn:population":0,
    "gn:timezone":"Africa/Luanda",
    "iso:country":"AO",
    "wof:name":"Nsosso",
    "wof:placetype":"locality"
},
  "geometry": {"coordinates":[15.22262,-5.8929],"type":"Point"}
}