{
  "type": "Feature",
  "properties": {
    "gn:admin1_code":"12.0",
    "gn:asciiname":"Cangonga",
    "gn:country_code":"AO",
    "gn:dem":1104,
    "gn:feature_class":"P",
    "gn:feature_code":"PPL",
    "gn:name":"Cangonga",
    "gn:population":0,
    "gn:timezone":"Africa/Luanda",
    "iso:country":"AO",
    "wof:name":"Cangonga",
    "wof:placetype":"locality"
},
  "geometry": {"coordinates":[16.08286,-9.24367],"type":"Point"}
}