{
  "type": "Feature",
  "properties": {
    "gn:admin1_code":"18.0",
    "gn:asciiname":"Cambajomba",
    "gn:country_code":"AO",
    "gn:dem":1370,
    "gn:feature_class":"P",
    "gn:feature_code":"PPL",
    "gn:name":"Cambajomba",
    "gn:population":0,
    "gn:timezone":"Africa/Luanda",
    "iso:country":"AO",
    "wof:name":"Cambajomba",
    "wof:placetype":"locality"
},
  "geometry": {"coordinates":[19.36576,-10.46111],"type":"Point"}
}