{
  "type": "Feature",
  "properties": {
    "gn:admin1_code":"19.0",
    "gn:asciiname":"Quipetelo",
    "gn:country_code":"AO",
    "gn:dem":30,
    "gn:feature_class":"P",
    "gn:feature_code":"PPL",
    "gn:name":"Quipetelo",
    "gn:population":0,
    "gn:timezone":"Africa/Luanda",
    "iso:country":"AO",
    "wof:name":"Quipetelo",
    "wof:placetype":"locality"
},
  "geometry": {"coordinates":[13.545,-8.57528],"type":"Point"}
}