{
  "type": "Feature",
  "properties": {
    "gn:admin1_code":"15.0",
    "gn:asciiname":"Zongo ua Ngola",
    "gn:country_code":"AO",
    "gn:dem":1138,
    "gn:feature_class":"P",
    "gn:feature_code":"PPL",
    "gn:name":"Zongo u\u00e1 Ngola",
    "gn:population":0,
    "gn:timezone":"Africa/Luanda",
    "iso:country":"AO",
    "name:und_x_variant":[
        "Zongo",
        "Zongo Angola",
        "Zongo u\u00e1 Ngola"
    ],
    "wof:name":"Zongo ua Ngola",
    "wof:placetype":"locality"
},
  "geometry": {"coordinates":[15.18374,-6.78658],"type":"Point"}
}