{
  "type": "Feature",
  "properties": {
    "gn:admin1_code":"12.0",
    "gn:asciiname":"Gondo",
    "gn:cc2":"AO",
    "gn:country_code":"AO",
    "gn:dem":1067,
    "gn:feature_class":"P",
    "gn:feature_code":"PPL",
    "gn:name":"Gondo",
    "gn:population":0,
    "gn:timezone":"Africa/Luanda",
    "iso:country":"AO",
    "name:und_x_variant":[
        "Cangola",
        "Cangolo",
        "Gondo"
    ],
    "wof:name":"Gondo",
    "wof:placetype":"locality"
},
  "geometry": {"coordinates":[16.18778,-9.64278],"type":"Point"}
}