{
  "type": "Feature",
  "properties": {
    "gn:admin1_code":"15.0",
    "gn:asciiname":"Mbanza Bungo",
    "gn:country_code":"AO",
    "gn:dem":1261,
    "gn:feature_class":"P",
    "gn:feature_code":"PPL",
    "gn:name":"Mbanza Bungo",
    "gn:population":0,
    "gn:timezone":"Africa/Luanda",
    "iso:country":"AO",
    "wof:name":"Mbanza Bungo",
    "wof:placetype":"locality"
},
  "geometry": {"coordinates":[15.20965,-7.45229],"type":"Point"}
}