{
  "type": "Feature",
  "properties": {
    "gn:admin1_code":"17.0",
    "gn:asciiname":"Chambumba",
    "gn:country_code":"AO",
    "gn:dem":983,
    "gn:feature_class":"P",
    "gn:feature_code":"PPL",
    "gn:name":"Chambumba",
    "gn:population":0,
    "gn:timezone":"Africa/Luanda",
    "iso:country":"AO",
    "wof:name":"Chambumba",
    "wof:placetype":"locality"
},
  "geometry": {"coordinates":[20.03333,-7.73333],"type":"Point"}
}