{
  "type": "Feature",
  "properties": {
    "gn:admin1_code":"15.0",
    "gn:asciiname":"Quibege Primeiro",
    "gn:country_code":"AO",
    "gn:dem":1039,
    "gn:feature_class":"P",
    "gn:feature_code":"PPL",
    "gn:name":"Quibege Primeiro",
    "gn:population":0,
    "gn:timezone":"Africa/Luanda",
    "iso:country":"AO",
    "wof:name":"Quibege Primeiro",
    "wof:placetype":"locality"
},
  "geometry": {"coordinates":[15.78893,-7.33871],"type":"Point"}
}