{
  "type": "Feature",
  "properties": {
    "gn:admin1_code":"15.0",
    "gn:asciiname":"Quiuzoua Nova",
    "gn:country_code":"AO",
    "gn:dem":1230,
    "gn:feature_class":"P",
    "gn:feature_code":"PPL",
    "gn:name":"Quiuzoua Nova",
    "gn:population":0,
    "gn:timezone":"Africa/Luanda",
    "iso:country":"AO",
    "wof:name":"Quiuzoua Nova",
    "wof:placetype":"locality"
},
  "geometry": {"coordinates":[15.12323,-7.27602],"type":"Point"}
}