{
  "type": "Feature",
  "properties": {
    "gn:admin1_code":"15.0",
    "gn:asciiname":"Quimbanuno",
    "gn:country_code":"AO",
    "gn:dem":740,
    "gn:feature_class":"P",
    "gn:feature_code":"PPL",
    "gn:name":"Quimbanuno",
    "gn:population":0,
    "gn:timezone":"Africa/Luanda",
    "iso:country":"AO",
    "wof:name":"Quimbanuno",
    "wof:placetype":"locality"
},
  "geometry": {"coordinates":[16.40722,-6.35673],"type":"Point"}
}