{
  "type": "Feature",
  "properties": {
    "gn:admin1_code":"13.0",
    "gn:asciiname":"Pipas",
    "gn:country_code":"AO",
    "gn:dem":9,
    "gn:feature_class":"P",
    "gn:feature_code":"PPL",
    "gn:name":"Pipas",
    "gn:population":0,
    "gn:timezone":"Africa/Luanda",
    "iso:country":"AO",
    "wof:name":"Pipas",
    "wof:placetype":"locality"
},
  "geometry": {"coordinates":[12.19351,-14.95014],"type":"Point"}
}