{
  "type": "Feature",
  "properties": {
    "gn:admin1_code":"14.0",
    "gn:asciiname":"Cassamba",
    "gn:cc2":"AO",
    "gn:country_code":"AO",
    "gn:dem":1293,
    "gn:feature_class":"P",
    "gn:feature_code":"PPL",
    "gn:name":"Cassamba",
    "gn:population":0,
    "gn:timezone":"Africa/Luanda",
    "iso:country":"AO",
    "name:und_x_variant":[
        "Kasamba",
        "Cassamba"
    ],
    "wof:name":"Cassamba",
    "wof:placetype":"locality"
},
  "geometry": {"coordinates":[20.35,-13.08333],"type":"Point"}
}