{
  "type": "Feature",
  "properties": {
    "gn:admin1_code":"15.0",
    "gn:asciiname":"Ngole",
    "gn:country_code":"AO",
    "gn:dem":563,
    "gn:feature_class":"P",
    "gn:feature_code":"PPL",
    "gn:name":"Ngole",
    "gn:population":0,
    "gn:timezone":"Africa/Luanda",
    "iso:country":"AO",
    "wof:name":"Ngole",
    "wof:placetype":"locality"
},
  "geometry": {"coordinates":[14.58297,-7.12007],"type":"Point"}
}