{
  "type": "Feature",
  "properties": {
    "gn:admin1_code":"12.0",
    "gn:asciiname":"Muemba",
    "gn:country_code":"AO",
    "gn:dem":1156,
    "gn:feature_class":"P",
    "gn:feature_code":"PPL",
    "gn:name":"Muemba",
    "gn:population":0,
    "gn:timezone":"Africa/Luanda",
    "iso:country":"AO",
    "wof:name":"Muemba",
    "wof:placetype":"locality"
},
  "geometry": {"coordinates":[16.24278,-9.52861],"type":"Point"}
}