{
  "type": "Feature",
  "properties": {
    "gn:admin1_code":"12.0",
    "gn:asciiname":"Ngola Quiluangi",
    "gn:country_code":"AO",
    "gn:dem":1116,
    "gn:feature_class":"P",
    "gn:feature_code":"PPL",
    "gn:name":"Ngola Quiluangi",
    "gn:population":0,
    "gn:timezone":"Africa/Luanda",
    "iso:country":"AO",
    "wof:name":"Ngola Quiluangi",
    "wof:placetype":"locality"
},
  "geometry": {"coordinates":[15.96256,-9.04522],"type":"Point"}
}