{
  "type": "Feature",
  "properties": {
    "gn:admin1_code":"1.0",
    "gn:asciiname":"Santudo",
    "gn:country_code":"AO",
    "gn:dem":1279,
    "gn:feature_class":"P",
    "gn:feature_code":"PPL",
    "gn:name":"Santudo",
    "gn:population":0,
    "gn:timezone":"Africa/Luanda",
    "iso:country":"AO",
    "wof:name":"Santudo",
    "wof:placetype":"locality"
},
  "geometry": {"coordinates":[14.35,-12.33333],"type":"Point"}
}