{
  "type": "Feature",
  "properties": {
    "gn:admin1_code":"6.0",
    "gn:asciiname":"Hulundo",
    "gn:country_code":"AO",
    "gn:dem":1258,
    "gn:feature_class":"P",
    "gn:feature_code":"PPL",
    "gn:name":"Hulundo",
    "gn:population":0,
    "gn:timezone":"Africa/Luanda",
    "iso:country":"AO",
    "wof:name":"Hulundo",
    "wof:placetype":"locality"
},
  "geometry": {"coordinates":[15.39784,-10.57915],"type":"Point"}
}