{
  "type": "Feature",
  "properties": {
    "gn:admin1_code":"15.0",
    "gn:asciiname":"Lounda Quidia",
    "gn:country_code":"AO",
    "gn:dem":850,
    "gn:feature_class":"P",
    "gn:feature_code":"PPL",
    "gn:name":"Lounda Quidia",
    "gn:population":0,
    "gn:timezone":"Africa/Luanda",
    "iso:country":"AO",
    "name:und_x_variant":[
        "Banza Lande",
        "Londa Quiria",
        "Lounda Quidia"
    ],
    "wof:name":"Lounda Quidia",
    "wof:placetype":"locality"
},
  "geometry": {"coordinates":[15.35383,-6.07781],"type":"Point"}
}