{
  "type": "Feature",
  "properties": {
    "gn:admin1_code":"12.0",
    "gn:asciiname":"Pimpao",
    "gn:country_code":"AO",
    "gn:dem":965,
    "gn:feature_class":"P",
    "gn:feature_code":"PPL",
    "gn:name":"Pimp\u00e3o",
    "gn:population":0,
    "gn:timezone":"Africa/Luanda",
    "iso:country":"AO",
    "wof:name":"Pimpao",
    "wof:placetype":"locality"
},
  "geometry": {"coordinates":[18.38685,-9.85641],"type":"Point"}
}