{
  "type": "Feature",
  "properties": {
    "gn:admin1_code":"15.0",
    "gn:asciiname":"Gozolo",
    "gn:country_code":"AO",
    "gn:dem":845,
    "gn:feature_class":"P",
    "gn:feature_code":"PPL",
    "gn:name":"Gozolo",
    "gn:population":0,
    "gn:timezone":"Africa/Luanda",
    "iso:country":"AO",
    "wof:name":"Gozolo",
    "wof:placetype":"locality"
},
  "geometry": {"coordinates":[15.18914,-7.98315],"type":"Point"}
}