{
  "type": "Feature",
  "properties": {
    "gn:admin1_code":"17.0",
    "gn:asciiname":"Cambafota",
    "gn:country_code":"AO",
    "gn:dem":946,
    "gn:feature_class":"P",
    "gn:feature_code":"PPL",
    "gn:name":"Cambafota",
    "gn:population":0,
    "gn:timezone":"Africa/Luanda",
    "iso:country":"AO",
    "name:und_x_variant":[
        "Camba Fota"
    ],
    "wof:name":"Cambafota",
    "wof:placetype":"locality"
},
  "geometry": {"coordinates":[19.87664,-7.39156],"type":"Point"}
}