{
  "type": "Feature",
  "properties": {
    "gn:admin1_code":"18.0",
    "gn:asciiname":"Xicuma",
    "gn:country_code":"AO",
    "gn:dem":1090,
    "gn:feature_class":"P",
    "gn:feature_code":"PPL",
    "gn:name":"Xicuma",
    "gn:population":0,
    "gn:timezone":"Africa/Luanda",
    "iso:country":"AO",
    "wof:name":"Xicuma",
    "wof:placetype":"locality"
},
  "geometry": {"coordinates":[21.16667,-10.85],"type":"Point"}
}