{
  "type": "Feature",
  "properties": {
    "gn:admin1_code":"17.0",
    "gn:asciiname":"Cachita",
    "gn:country_code":"AO",
    "gn:dem":781,
    "gn:feature_class":"P",
    "gn:feature_code":"PPL",
    "gn:name":"Cachita",
    "gn:population":0,
    "gn:timezone":"Africa/Luanda",
    "iso:country":"AO",
    "wof:name":"Cachita",
    "wof:placetype":"locality"
},
  "geometry": {"coordinates":[21.56667,-8.26667],"type":"Point"}
}