{
  "type": "Feature",
  "properties": {
    "gn:admin1_code":"4.0",
    "gn:asciiname":"Dondi",
    "gn:country_code":"AO",
    "gn:dem":1147,
    "gn:feature_class":"P",
    "gn:feature_code":"PPL",
    "gn:name":"Dondi",
    "gn:population":0,
    "gn:timezone":"Africa/Luanda",
    "iso:country":"AO",
    "wof:name":"Dondi",
    "wof:placetype":"locality"
},
  "geometry": {"coordinates":[17.75,-16.41667],"type":"Point"}
}