{
  "type": "Feature",
  "properties": {
    "gn:admin1_code":"19.0",
    "gn:asciiname":"Maquembo",
    "gn:country_code":"AO",
    "gn:dem":632,
    "gn:feature_class":"P",
    "gn:feature_code":"PPL",
    "gn:name":"Maquembo",
    "gn:population":0,
    "gn:timezone":"Africa/Luanda",
    "iso:country":"AO",
    "wof:name":"Maquembo",
    "wof:placetype":"locality"
},
  "geometry": {"coordinates":[14.30373,-8.34069],"type":"Point"}
}