{
  "type": "Feature",
  "properties": {
    "gn:admin1_code":"4.0",
    "gn:asciiname":"Cuchi",
    "gn:country_code":"AO",
    "gn:dem":1353,
    "gn:feature_class":"P",
    "gn:feature_code":"PPL",
    "gn:name":"Cuchi",
    "gn:population":0,
    "gn:timezone":"Africa/Luanda",
    "iso:country":"AO",
    "name:rus_x_preferred":[
        "\u041a\u0443\u0448\u0438"
    ],
    "name:und_x_variant":[
        "Kuchi",
        "Cuche",
        "Cuchi"
    ],
    "wof:name":"Cuchi",
    "wof:placetype":"locality"
},
  "geometry": {"coordinates":[16.89929,-14.64978],"type":"Point"}
}