{
  "type": "Feature",
  "properties": {
    "gn:admin1_code":"4.0",
    "gn:asciiname":"Cuchi",
    "gn:country_code":"AO",
    "gn:dem":1353,
    "gn:feature_class":"P",
    "gn:feature_code":"PPL",
    "gn:name":"Cuchi",
    "gn:population":0,
    "gn:timezone":"Africa/Luanda",
    "iso:country":"AO",
    "name:azb_x_preferred":[
        "\u06a9\u0648\u0634\u06cc"
    ],
    "name:cat_x_preferred":[
        "Cuchi"
    ],
    "name:ceb_x_preferred":[
        "Munic\u00edpio Cuchi"
    ],
    "name:deu_x_preferred":[
        "Cuchi"
    ],
    "name:fas_x_preferred":[
        "\u06a9\u0648\u0634\u06cc"
    ],
    "name:ita_x_preferred":[
        "Kuchi"
    ],
    "name:por_x_preferred":[
        "Cuchi"
    ],
    "name:ron_x_preferred":[
        "Cuchi"
    ],
    "name:rus_x_preferred":[
        "\u041a\u0443\u0448\u0438"
    ],
    "name:spa_x_preferred":[
        "Cuchi"
    ],
    "name:swe_x_preferred":[
        "Munic\u00edpio Cuchi"
    ],
    "name:und_x_variant":[
        "Kuchi",
        "Cuche",
        "Cuchi"
    ],
    "name:zho_x_preferred":[
        "\u5eab\u5e0c"
    ],
    "wof:name":"Cuchi",
    "wof:placetype":"locality"
},
  "geometry": {"coordinates":[16.89929,-14.64978],"type":"Point"}
}