{
  "type": "Feature",
  "properties": {
    "gn:admin1_code":"6.0",
    "gn:asciiname":"Caheno",
    "gn:country_code":"AO",
    "gn:dem":1069,
    "gn:feature_class":"P",
    "gn:feature_code":"PPL",
    "gn:name":"Caheno",
    "gn:population":0,
    "gn:timezone":"Africa/Luanda",
    "iso:country":"AO",
    "wof:name":"Caheno",
    "wof:placetype":"locality"
},
  "geometry": {"coordinates":[14.30142,-11.07611],"type":"Point"}
}