{
  "type": "Feature",
  "properties": {
    "gn:admin1_code":"13.0",
    "gn:asciiname":"Carvalho Oliveira",
    "gn:country_code":"AO",
    "gn:dem":467,
    "gn:feature_class":"P",
    "gn:feature_code":"PPL",
    "gn:name":"Carvalho Oliveira",
    "gn:population":0,
    "gn:timezone":"Africa/Luanda",
    "iso:country":"AO",
    "wof:name":"Carvalho Oliveira",
    "wof:placetype":"locality"
},
  "geometry": {"coordinates":[12.78333,-14.88333],"type":"Point"}
}