{
  "type": "Feature",
  "properties": {
    "gn:admin1_code":"6.0",
    "gn:asciiname":"Quixia",
    "gn:country_code":"AO",
    "gn:dem":1477,
    "gn:feature_class":"P",
    "gn:feature_code":"PPL",
    "gn:name":"Quixia",
    "gn:population":0,
    "gn:timezone":"Africa/Luanda",
    "iso:country":"AO",
    "wof:name":"Quixia",
    "wof:placetype":"locality"
},
  "geometry": {"coordinates":[15.19,-11.46776],"type":"Point"}
}