{
  "type": "Feature",
  "properties": {
    "gn:admin1_code":"12.0",
    "gn:asciiname":"Chiguica",
    "gn:country_code":"AO",
    "gn:dem":1181,
    "gn:feature_class":"P",
    "gn:feature_code":"PPL",
    "gn:name":"Chiguica",
    "gn:population":0,
    "gn:timezone":"Africa/Luanda",
    "iso:country":"AO",
    "wof:name":"Chiguica",
    "wof:placetype":"locality"
},
  "geometry": {"coordinates":[16.25467,-9.33959],"type":"Point"}
}