{
  "type": "Feature",
  "properties": {
    "gn:admin1_code":"5.0",
    "gn:asciiname":"Quilucunhi",
    "gn:country_code":"AO",
    "gn:dem":847,
    "gn:feature_class":"P",
    "gn:feature_code":"PPL",
    "gn:name":"Quilucunhi",
    "gn:population":0,
    "gn:timezone":"Africa/Luanda",
    "iso:country":"AO",
    "wof:name":"Quilucunhi",
    "wof:placetype":"locality"
},
  "geometry": {"coordinates":[15.21754,-8.02827],"type":"Point"}
}