{
  "type": "Feature",
  "properties": {
    "gn:admin1_code":"12.0",
    "gn:asciiname":"Dumba Ngonge",
    "gn:country_code":"AO",
    "gn:dem":806,
    "gn:feature_class":"P",
    "gn:feature_code":"PPL",
    "gn:name":"Dumba Ngonge",
    "gn:population":0,
    "gn:timezone":"Africa/Luanda",
    "iso:country":"AO",
    "wof:name":"Dumba Ngonge",
    "wof:placetype":"locality"
},
  "geometry": {"coordinates":[17.47747,-9.79977],"type":"Point"}
}