{
  "type": "Feature",
  "properties": {
    "gn:admin1_code":"4.0",
    "gn:asciiname":"Liliengue",
    "gn:cc2":"AO",
    "gn:country_code":"AO",
    "gn:dem":1421,
    "gn:feature_class":"P",
    "gn:feature_code":"PPL",
    "gn:name":"Liliengue",
    "gn:population":0,
    "gn:timezone":"Africa/Luanda",
    "iso:country":"AO",
    "name:und_x_variant":[
        "Luhumba",
        "Liliengue"
    ],
    "wof:name":"Liliengue",
    "wof:placetype":"locality"
},
  "geometry": {"coordinates":[16.88332999999999,-14.43333],"type":"Point"}
}