{
  "type": "Feature",
  "properties": {
    "gn:admin1_code":"14.0",
    "gn:asciiname":"Samutete",
    "gn:cc2":"AO",
    "gn:country_code":"AO",
    "gn:dem":1152,
    "gn:feature_class":"P",
    "gn:feature_code":"PPL",
    "gn:name":"Samutete",
    "gn:population":0,
    "gn:timezone":"Africa/Luanda",
    "iso:country":"AO",
    "name:und_x_variant":[
        "Tuta",
        "Samutete"
    ],
    "wof:name":"Samutete",
    "wof:placetype":"locality"
},
  "geometry": {"coordinates":[20.83333,-14.68333],"type":"Point"}
}