{
  "type": "Feature",
  "properties": {
    "gn:admin1_code":"16.0",
    "gn:asciiname":"Coco",
    "gn:country_code":"AO",
    "gn:dem":295,
    "gn:feature_class":"P",
    "gn:feature_code":"PPL",
    "gn:name":"Coco",
    "gn:population":0,
    "gn:timezone":"Africa/Luanda",
    "iso:country":"AO",
    "name:cat_x_preferred":[
        "Coco"
    ],
    "name:ceb_x_preferred":[
        "Coco"
    ],
    "name:ces_x_preferred":[
        "Coco"
    ],
    "name:deu_x_preferred":[
        "Coco"
    ],
    "name:fin_x_preferred":[
        "Coco"
    ],
    "name:fra_x_preferred":[
        "Coco"
    ],
    "name:glg_x_preferred":[
        "Coco"
    ],
    "name:heb_x_preferred":[
        "\u05e7\u05d5\u05e7\u05d5"
    ],
    "name:ita_x_preferred":[
        "Coco"
    ],
    "name:nld_x_preferred":[
        "Coco"
    ],
    "name:pol_x_preferred":[
        "Coco"
    ],
    "name:por_x_preferred":[
        "Coco"
    ],
    "name:spa_x_preferred":[
        "Coco"
    ],
    "name:swe_x_preferred":[
        "Coco"
    ],
    "name:zho_x_preferred":[
        "CoCo"
    ],
    "wof:name":"Coco",
    "wof:placetype":"locality"
},
  "geometry": {"coordinates":[14.06667,-5.96667],"type":"Point"}
}