{
  "type": "Feature",
  "properties": {
    "gn:admin1_code":"18.0",
    "gn:asciiname":"Saurimo",
    "gn:country_code":"AO",
    "gn:dem":1098,
    "gn:feature_class":"P",
    "gn:feature_code":"PPL",
    "gn:name":"Saurimo",
    "gn:population":0,
    "gn:timezone":"Africa/Luanda",
    "iso:country":"AO",
    "name:afr_x_preferred":[
        "Saurimo"
    ],
    "name:ara_x_preferred":[
        "\u0633\u0627\u0648\u0631\u064a\u0645\u0648"
    ],
    "name:azb_x_preferred":[
        "\u0633\u0648\u0631\u06cc\u0645\u0648"
    ],
    "name:cat_x_preferred":[
        "Saurimo"
    ],
    "name:ceb_x_preferred":[
        "Saurimo"
    ],
    "name:deu_x_preferred":[
        "Saurimo"
    ],
    "name:fas_x_preferred":[
        "\u0633\u0648\u0631\u06cc\u0645\u0648"
    ],
    "name:fra_x_preferred":[
        "Saurimo"
    ],
    "name:frr_x_preferred":[
        "Saurimo"
    ],
    "name:heb_x_preferred":[
        "\u05e1\u05d0\u05d5\u05e8\u05d9\u05de\u05d5"
    ],
    "name:hrv_x_preferred":[
        "Saurimo"
    ],
    "name:ita_x_preferred":[
        "Saurimo"
    ],
    "name:kon_x_preferred":[
        "Saurimo"
    ],
    "name:lit_x_preferred":[
        "Saurimas"
    ],
    "name:ltz_x_preferred":[
        "Saurimo"
    ],
    "name:msa_x_preferred":[
        "Saurimo"
    ],
    "name:nld_x_preferred":[
        "Saurimo"
    ],
    "name:nor_x_preferred":[
        "Saurimo"
    ],
    "name:pol_x_preferred":[
        "Saurimo"
    ],
    "name:por_x_preferred":[
        "Saurimo"
    ],
    "name:ron_x_preferred":[
        "Saurimo"
    ],
    "name:rus_x_preferred":[
        "\u0421\u0430\u0443\u0440\u0438\u043c\u043e"
    ],
    "name:spa_x_preferred":[
        "Saurimo"
    ],
    "name:tgl_x_preferred":[
        "Saurimo"
    ],
    "name:ukr_x_preferred":[
        "\u0421\u0430\u0443\u0440\u0438\u043c\u043e"
    ],
    "name:urd_x_preferred":[
        "\u0633\u0627\u0648\u0631\u06cc\u0645\u0648"
    ],
    "name:war_x_preferred":[
        "Saurimo"
    ],
    "name:zho_x_preferred":[
        "\u7d39\u91cc\u6728"
    ],
    "wof:name":"Saurimo",
    "wof:placetype":"locality"
},
  "geometry": {"coordinates":[20.42631,-9.69396],"type":"Point"}
}