{
  "type": "Feature",
  "properties": {
    "gn:admin1_code":"18.0",
    "gn:asciiname":"Saurimo",
    "gn:country_code":"AO",
    "gn:dem":1098,
    "gn:feature_class":"P",
    "gn:feature_code":"PPL",
    "gn:name":"Saurimo",
    "gn:population":0,
    "gn:timezone":"Africa/Luanda",
    "iso:country":"AO",
    "wof:name":"Saurimo",
    "wof:placetype":"locality"
},
  "geometry": {"coordinates":[20.42631,-9.69396],"type":"Point"}
}