{
  "type": "Feature",
  "properties": {
    "gn:admin1_code":"8.0",
    "gn:asciiname":"Fazenda Lage e Irmao",
    "gn:cc2":"AO",
    "gn:country_code":"AO",
    "gn:dem":1473,
    "gn:feature_class":"P",
    "gn:feature_code":"PPL",
    "gn:name":"Fazenda Lage e Irm\u00e3o",
    "gn:population":0,
    "gn:timezone":"Africa/Luanda",
    "iso:country":"AO",
    "name:und_x_variant":[
        "A. Lage",
        "Fazenda Lage e Irm\u00e3o"
    ],
    "wof:name":"Fazenda Lage e Irmao",
    "wof:placetype":"locality"
},
  "geometry": {"coordinates":[15.23333,-12.98333],"type":"Point"}
}