{
  "type": "Feature",
  "properties": {
    "gn:admin1_code":"1.0",
    "gn:asciiname":"Chituto",
    "gn:cc2":"AO",
    "gn:country_code":"AO",
    "gn:dem":985,
    "gn:feature_class":"P",
    "gn:feature_code":"PPL",
    "gn:name":"Chituto",
    "gn:population":0,
    "gn:timezone":"Africa/Luanda",
    "iso:country":"AO",
    "name:und_x_variant":[
        "Quicuco",
        "Chituto"
    ],
    "wof:name":"Chituto",
    "wof:placetype":"locality"
},
  "geometry": {"coordinates":[14.03333,-12.55],"type":"Point"}
}