{
  "type": "Feature",
  "properties": {
    "gn:admin1_code":"12.0",
    "gn:asciiname":"Ngola Iota",
    "gn:country_code":"AO",
    "gn:dem":721,
    "gn:feature_class":"P",
    "gn:feature_code":"PPL",
    "gn:name":"Ngola Iota",
    "gn:population":0,
    "gn:timezone":"Africa/Luanda",
    "iso:country":"AO",
    "wof:name":"Ngola Iota",
    "wof:placetype":"locality"
},
  "geometry": {"coordinates":[16.55485,-8.48715],"type":"Point"}
}