{
  "type": "Feature",
  "properties": {
    "gn:admin1_code":"1.0",
    "gn:asciiname":"Cabinchia",
    "gn:cc2":"AO",
    "gn:country_code":"AO",
    "gn:dem":1848,
    "gn:feature_class":"P",
    "gn:feature_code":"PPL",
    "gn:name":"Cabinchia",
    "gn:population":0,
    "gn:timezone":"Africa/Luanda",
    "iso:country":"AO",
    "name:und_x_variant":[
        "Capuma",
        "Cabinchia"
    ],
    "wof:name":"Cabinchia",
    "wof:placetype":"locality"
},
  "geometry": {"coordinates":[14.85,-12.58333],"type":"Point"}
}