{
  "type": "Feature",
  "properties": {
    "gn:admin1_code":"4.0",
    "gn:asciiname":"Candingo",
    "gn:country_code":"AO",
    "gn:dem":1483,
    "gn:feature_class":"P",
    "gn:feature_code":"PPL",
    "gn:name":"Candingo",
    "gn:population":0,
    "gn:timezone":"Africa/Luanda",
    "iso:country":"AO",
    "wof:name":"Candingo",
    "wof:placetype":"locality"
},
  "geometry": {"coordinates":[17.18333,-14.33333],"type":"Point"}
}