{
  "type": "Feature",
  "properties": {
    "gn:admin1_code":"18.0",
    "gn:asciiname":"Satchipopo",
    "gn:country_code":"AO",
    "gn:dem":1035,
    "gn:feature_class":"P",
    "gn:feature_code":"PPL",
    "gn:name":"Satchipopo",
    "gn:population":0,
    "gn:timezone":"Africa/Luanda",
    "iso:country":"AO",
    "wof:name":"Satchipopo",
    "wof:placetype":"locality"
},
  "geometry": {"coordinates":[21.51133,-8.77539],"type":"Point"}
}