{
  "type": "Feature",
  "properties": {
    "gn:admin1_code":"12.0",
    "gn:asciiname":"Mussendeleque",
    "gn:country_code":"AO",
    "gn:dem":1134,
    "gn:feature_class":"P",
    "gn:feature_code":"PPL",
    "gn:name":"Mussendeleque",
    "gn:population":0,
    "gn:timezone":"Africa/Luanda",
    "iso:country":"AO",
    "wof:name":"Mussendeleque",
    "wof:placetype":"locality"
},
  "geometry": {"coordinates":[16.30486,-9.29208],"type":"Point"}
}