{
  "type": "Feature",
  "properties": {
    "gn:admin1_code":"9.0",
    "gn:asciiname":"Muvonde",
    "gn:country_code":"AO",
    "gn:dem":1284,
    "gn:feature_class":"P",
    "gn:feature_code":"PPL",
    "gn:name":"Muvonde",
    "gn:population":0,
    "gn:timezone":"Africa/Luanda",
    "iso:country":"AO",
    "wof:name":"Muvonde",
    "wof:placetype":"locality"
},
  "geometry": {"coordinates":[14.78304,-14.88066],"type":"Point"}
}