{
  "type": "Feature",
  "properties": {
    "gn:admin1_code":"9.0",
    "gn:asciiname":"Leca",
    "gn:country_code":"AO",
    "gn:dem":1480,
    "gn:feature_class":"P",
    "gn:feature_code":"PPL",
    "gn:name":"Le\u00e7a",
    "gn:population":0,
    "gn:timezone":"Africa/Luanda",
    "iso:country":"AO",
    "wof:name":"Leca",
    "wof:placetype":"locality"
},
  "geometry": {"coordinates":[15.63398,-14.60324],"type":"Point"}
}