{
  "type": "Feature",
  "properties": {
    "gn:admin1_code":"19.0",
    "gn:asciiname":"Quindala",
    "gn:country_code":"AO",
    "gn:dem":904,
    "gn:feature_class":"P",
    "gn:feature_code":"PPL",
    "gn:name":"Quindala",
    "gn:population":0,
    "gn:timezone":"Africa/Luanda",
    "iso:country":"AO",
    "wof:name":"Quindala",
    "wof:placetype":"locality"
},
  "geometry": {"coordinates":[14.72585,-8.62736],"type":"Point"}
}