{
  "type": "Feature",
  "properties": {
    "gn:admin1_code":"17.0",
    "gn:asciiname":"Quitapa",
    "gn:country_code":"AO",
    "gn:dem":1396,
    "gn:feature_class":"P",
    "gn:feature_code":"PPL",
    "gn:name":"Quitapa",
    "gn:population":0,
    "gn:timezone":"Africa/Luanda",
    "iso:country":"AO",
    "name:por_x_preferred":[
        "Quitapa"
    ],
    "wof:name":"Quitapa",
    "wof:placetype":"locality"
},
  "geometry": {"coordinates":[18.20167,-10.29609],"type":"Point"}
}