{
  "type": "Feature",
  "properties": {
    "gn:admin1_code":"15.0",
    "gn:asciiname":"Fazenda Mbongui",
    "gn:country_code":"AO",
    "gn:dem":818,
    "gn:feature_class":"P",
    "gn:feature_code":"PPL",
    "gn:name":"Fazenda Mbongui",
    "gn:population":0,
    "gn:timezone":"Africa/Luanda",
    "iso:country":"AO",
    "wof:name":"Fazenda Mbongui",
    "wof:placetype":"locality"
},
  "geometry": {"coordinates":[14.991,-7.41443],"type":"Point"}
}