{
  "type": "Feature",
  "properties": {
    "gn:admin1_code":"6.0",
    "gn:asciiname":"Cambondo",
    "gn:country_code":"AO",
    "gn:dem":1320,
    "gn:feature_class":"P",
    "gn:feature_code":"PPL",
    "gn:name":"Cambondo",
    "gn:population":0,
    "gn:timezone":"Africa/Luanda",
    "iso:country":"AO",
    "wof:name":"Cambondo",
    "wof:placetype":"locality"
},
  "geometry": {"coordinates":[15.21438,-10.40179],"type":"Point"}
}