{
  "type": "Feature",
  "properties": {
    "gn:admin1_code":"17.0",
    "gn:asciiname":"Muamuhongo",
    "gn:country_code":"AO",
    "gn:dem":1212,
    "gn:feature_class":"P",
    "gn:feature_code":"PPL",
    "gn:name":"Muamuhongo",
    "gn:population":0,
    "gn:timezone":"Africa/Luanda",
    "iso:country":"AO",
    "wof:name":"Muamuhongo",
    "wof:placetype":"locality"
},
  "geometry": {"coordinates":[19.3279,-9.37191],"type":"Point"}
}