{
  "type": "Feature",
  "properties": {
    "gn:admin1_code":"8.0",
    "gn:asciiname":"Sanambi",
    "gn:country_code":"AO",
    "gn:dem":1691,
    "gn:feature_class":"P",
    "gn:feature_code":"PPL",
    "gn:name":"Sanambi",
    "gn:population":0,
    "gn:timezone":"Africa/Luanda",
    "iso:country":"AO",
    "wof:name":"Sanambi",
    "wof:placetype":"locality"
},
  "geometry": {"coordinates":[15.70972,-12.67667],"type":"Point"}
}