{
  "type": "Feature",
  "properties": {
    "gn:admin1_code":"15.0",
    "gn:asciiname":"Quissoni",
    "gn:country_code":"AO",
    "gn:dem":870,
    "gn:feature_class":"P",
    "gn:feature_code":"PPL",
    "gn:name":"Quissoni",
    "gn:population":0,
    "gn:timezone":"Africa/Luanda",
    "iso:country":"AO",
    "name:und_x_variant":[
        "Quissone"
    ],
    "wof:name":"Quissoni",
    "wof:placetype":"locality"
},
  "geometry": {"coordinates":[15.48113,-6.28668],"type":"Point"}
}