{
  "type": "Feature",
  "properties": {
    "gn:admin1_code":"12.0",
    "gn:asciiname":"Calungangana",
    "gn:cc2":"AO",
    "gn:country_code":"AO",
    "gn:dem":1068,
    "gn:feature_class":"P",
    "gn:feature_code":"PPL",
    "gn:name":"Calungangana",
    "gn:population":0,
    "gn:timezone":"Africa/Luanda",
    "iso:country":"AO",
    "name:und_x_variant":[
        "Candangundo",
        "Candangunda",
        "Calungangana"
    ],
    "wof:name":"Calungangana",
    "wof:placetype":"locality"
},
  "geometry": {"coordinates":[16.65,-10.61667],"type":"Point"}
}