{
  "type": "Feature",
  "properties": {
    "gn:admin1_code":"17.0",
    "gn:asciiname":"Sombuege Segundo",
    "gn:country_code":"AO",
    "gn:dem":912,
    "gn:feature_class":"P",
    "gn:feature_code":"PPL",
    "gn:name":"Sombuege Segundo",
    "gn:population":0,
    "gn:timezone":"Africa/Luanda",
    "iso:country":"AO",
    "wof:name":"Sombuege Segundo",
    "wof:placetype":"locality"
},
  "geometry": {"coordinates":[20.66694,-8.00746],"type":"Point"}
}