{
  "type": "Feature",
  "properties": {
    "gn:admin1_code":"14.0",
    "gn:asciiname":"Samajilo",
    "gn:country_code":"AO",
    "gn:dem":1084,
    "gn:feature_class":"P",
    "gn:feature_code":"PPL",
    "gn:name":"Samajilo",
    "gn:population":0,
    "gn:timezone":"Africa/Luanda",
    "iso:country":"AO",
    "wof:name":"Samajilo",
    "wof:placetype":"locality"
},
  "geometry": {"coordinates":[22.10839,-10.81457],"type":"Point"}
}