{
  "type": "Feature",
  "properties": {
    "gn:admin1_code":"17.0",
    "gn:asciiname":"Muangingo",
    "gn:country_code":"AO",
    "gn:dem":871,
    "gn:feature_class":"P",
    "gn:feature_code":"PPL",
    "gn:name":"Muangingo",
    "gn:population":0,
    "gn:timezone":"Africa/Luanda",
    "iso:country":"AO",
    "wof:name":"Muangingo",
    "wof:placetype":"locality"
},
  "geometry": {"coordinates":[18.03016,-8.83959],"type":"Point"}
}