{
  "type": "Feature",
  "properties": {
    "gn:admin1_code":"19.0",
    "gn:asciiname":"Quioza",
    "gn:country_code":"AO",
    "gn:dem":713,
    "gn:feature_class":"P",
    "gn:feature_code":"PPL",
    "gn:name":"Quioza",
    "gn:population":0,
    "gn:timezone":"Africa/Luanda",
    "iso:country":"AO",
    "wof:name":"Quioza",
    "wof:placetype":"locality"
},
  "geometry": {"coordinates":[14.68333,-8.43333],"type":"Point"}
}