{
  "type": "Feature",
  "properties": {
    "gn:admin1_code":"12.0",
    "gn:asciiname":"Quiriassa",
    "gn:country_code":"AO",
    "gn:dem":1042,
    "gn:feature_class":"P",
    "gn:feature_code":"PPL",
    "gn:name":"Quiriassa",
    "gn:population":0,
    "gn:timezone":"Africa/Luanda",
    "iso:country":"AO",
    "wof:name":"Quiriassa",
    "wof:placetype":"locality"
},
  "geometry": {"coordinates":[16.13222,-9.54417],"type":"Point"}
}