{
  "type": "Feature",
  "properties": {
    "gn:admin1_code":"6.0",
    "gn:asciiname":"Balaca",
    "gn:country_code":"AO",
    "gn:dem":1498,
    "gn:feature_class":"P",
    "gn:feature_code":"PPL",
    "gn:name":"Bala\u00e7a",
    "gn:population":0,
    "gn:timezone":"Africa/Luanda",
    "iso:country":"AO",
    "wof:name":"Balaca",
    "wof:placetype":"locality"
},
  "geometry": {"coordinates":[14.82964,-11.30809],"type":"Point"}
}