{
  "type": "Feature",
  "properties": {
    "gn:admin1_code":"6.0",
    "gn:asciiname":"Banza Xariaia",
    "gn:country_code":"AO",
    "gn:dem":1038,
    "gn:feature_class":"P",
    "gn:feature_code":"PPL",
    "gn:name":"Banza Xariaia",
    "gn:population":0,
    "gn:timezone":"Africa/Luanda",
    "iso:country":"AO",
    "wof:name":"Banza Xariaia",
    "wof:placetype":"locality"
},
  "geometry": {"coordinates":[14.4966,-10.70688],"type":"Point"}
}