{
  "type": "Feature",
  "properties": {
    "gn:admin1_code":"12.0",
    "gn:asciiname":"Cambambe",
    "gn:country_code":"AO",
    "gn:dem":753,
    "gn:feature_class":"P",
    "gn:feature_code":"PPL",
    "gn:name":"Cambambe",
    "gn:population":0,
    "gn:timezone":"Africa/Luanda",
    "iso:country":"AO",
    "name:azb_x_preferred":[
        "\u06a9\u0645\u0628\u0645\u0628\u0647"
    ],
    "name:cat_x_preferred":[
        "Cambambe"
    ],
    "name:deu_x_preferred":[
        "Cambambe"
    ],
    "name:fas_x_preferred":[
        "\u06a9\u0645\u0628\u0645\u0628\u0647"
    ],
    "name:ita_x_preferred":[
        "Cambambe"
    ],
    "name:por_x_preferred":[
        "Cambambe"
    ],
    "name:spa_x_preferred":[
        "Cambambe"
    ],
    "name:zho_x_preferred":[
        "\u574e\u73ed\u8c9d"
    ],
    "wof:name":"Cambambe",
    "wof:placetype":"locality"
},
  "geometry": {"coordinates":[17.10954,-8.85853],"type":"Point"}
}