{
  "type": "Feature",
  "properties": {
    "gn:admin1_code":"14.0",
    "gn:asciiname":"Marono",
    "gn:country_code":"AO",
    "gn:dem":1112,
    "gn:feature_class":"P",
    "gn:feature_code":"PPL",
    "gn:name":"Marono",
    "gn:population":0,
    "gn:timezone":"Africa/Luanda",
    "iso:country":"AO",
    "wof:name":"Marono",
    "wof:placetype":"locality"
},
  "geometry": {"coordinates":[20.85,-14.91667],"type":"Point"}
}