{
  "type": "Feature",
  "properties": {
    "gn:admin1_code":"16.0",
    "gn:asciiname":"Quintoto",
    "gn:country_code":"AO",
    "gn:dem":283,
    "gn:feature_class":"P",
    "gn:feature_code":"PPL",
    "gn:name":"Quint\u00f4to",
    "gn:population":0,
    "gn:timezone":"Africa/Luanda",
    "iso:country":"AO",
    "wof:name":"Quintoto",
    "wof:placetype":"locality"
},
  "geometry": {"coordinates":[14.06667,-5.98333],"type":"Point"}
}