{
  "type": "Feature",
  "properties": {
    "gn:admin1_code":"6.0",
    "gn:asciiname":"Caundo",
    "gn:country_code":"AO",
    "gn:dem":20,
    "gn:feature_class":"P",
    "gn:feature_code":"PPL",
    "gn:name":"Caundo",
    "gn:population":0,
    "gn:timezone":"Africa/Luanda",
    "iso:country":"AO",
    "wof:name":"Caundo",
    "wof:placetype":"locality"
},
  "geometry": {"coordinates":[13.95349,-10.43628],"type":"Point"}
}