{
  "type": "Feature",
  "properties": {
    "gn:admin1_code":"17.0",
    "gn:asciiname":"Nalamba",
    "gn:country_code":"AO",
    "gn:dem":836,
    "gn:feature_class":"P",
    "gn:feature_code":"PPL",
    "gn:name":"Nalamba",
    "gn:population":0,
    "gn:timezone":"Africa/Luanda",
    "iso:country":"AO",
    "name:und_x_variant":[
        "Coboi"
    ],
    "wof:name":"Nalamba",
    "wof:placetype":"locality"
},
  "geometry": {"coordinates":[20.55114,-8.50774],"type":"Point"}
}