{
  "type": "Feature",
  "properties": {
    "gn:admin1_code":"17.0",
    "gn:asciiname":"Sacabuata",
    "gn:country_code":"AO",
    "gn:dem":837,
    "gn:feature_class":"P",
    "gn:feature_code":"PPL",
    "gn:name":"Sacabuata",
    "gn:population":0,
    "gn:timezone":"Africa/Luanda",
    "iso:country":"AO",
    "wof:name":"Sacabuata",
    "wof:placetype":"locality"
},
  "geometry": {"coordinates":[21.01682000000001,-7.58145],"type":"Point"}
}