{
  "type": "Feature",
  "properties": {
    "gn:admin1_code":"1.0",
    "gn:asciiname":"Tchingolonga",
    "gn:country_code":"AO",
    "gn:dem":1477,
    "gn:feature_class":"P",
    "gn:feature_code":"PPL",
    "gn:name":"Tchingolonga",
    "gn:population":0,
    "gn:timezone":"Africa/Luanda",
    "iso:country":"AO",
    "wof:name":"Tchingolonga",
    "wof:placetype":"locality"
},
  "geometry": {"coordinates":[14.76667,-12.66667],"type":"Point"}
}