{
  "type": "Feature",
  "properties": {
    "gn:admin1_code":"0.0",
    "gn:asciiname":"Cuio",
    "gn:country_code":"AO",
    "gn:dem":6,
    "gn:feature_class":"P",
    "gn:feature_code":"PPL",
    "gn:name":"Cuio",
    "gn:population":0,
    "gn:timezone":"Africa/Luanda",
    "iso:country":"AO",
    "wof:name":"Cuio",
    "wof:placetype":"locality"
},
  "geometry": {"coordinates":[12.98028,-12.98222],"type":"Point"}
}