{
  "type": "Feature",
  "properties": {
    "gn:admin1_code":"6.0",
    "gn:asciiname":"Hanha",
    "gn:cc2":"AO",
    "gn:country_code":"AO",
    "gn:dem":1397,
    "gn:feature_class":"P",
    "gn:feature_code":"PPL",
    "gn:name":"Hanha",
    "gn:population":0,
    "gn:timezone":"Africa/Luanda",
    "iso:country":"AO",
    "name:und_x_variant":[
        "Anha",
        "Hanha"
    ],
    "wof:name":"Hanha",
    "wof:placetype":"locality"
},
  "geometry": {"coordinates":[14.81667,-11.51667],"type":"Point"}
}