{
  "type": "Feature",
  "properties": {
    "gn:admin1_code":"4.0",
    "gn:asciiname":"Chicote",
    "gn:cc2":"AO",
    "gn:country_code":"AO",
    "gn:dem":1165,
    "gn:feature_class":"P",
    "gn:feature_code":"PPL",
    "gn:name":"Chicote",
    "gn:population":0,
    "gn:timezone":"Africa/Luanda",
    "iso:country":"AO",
    "name:und_x_variant":[
        "Chicate",
        "Chicote"
    ],
    "wof:name":"Chicote",
    "wof:placetype":"locality"
},
  "geometry": {"coordinates":[18.78333,-17.23333],"type":"Point"}
}