{
  "type": "Feature",
  "properties": {
    "gn:admin1_code":"12.0",
    "gn:asciiname":"Quicundo",
    "gn:country_code":"AO",
    "gn:dem":779,
    "gn:feature_class":"P",
    "gn:feature_code":"PPL",
    "gn:name":"Quicundo",
    "gn:population":0,
    "gn:timezone":"Africa/Luanda",
    "iso:country":"AO",
    "wof:name":"Quicundo",
    "wof:placetype":"locality"
},
  "geometry": {"coordinates":[17.20936,-9.46632],"type":"Point"}
}