{
  "type": "Feature",
  "properties": {
    "gn:admin1_code":"15.0",
    "gn:asciiname":"Ianga",
    "gn:country_code":"AO",
    "gn:dem":883,
    "gn:feature_class":"P",
    "gn:feature_code":"PPL",
    "gn:name":"Ianga",
    "gn:population":0,
    "gn:timezone":"Africa/Luanda",
    "iso:country":"AO",
    "wof:name":"Ianga",
    "wof:placetype":"locality"
},
  "geometry": {"coordinates":[15.15026,-5.99427],"type":"Point"}
}