{
  "type": "Feature",
  "properties": {
    "gn:admin1_code":"5.0",
    "gn:asciiname":"Sa Leitao",
    "gn:country_code":"AO",
    "gn:dem":556,
    "gn:feature_class":"P",
    "gn:feature_code":"PPL",
    "gn:name":"S\u00e1 Leit\u00e3o",
    "gn:population":0,
    "gn:timezone":"Africa/Luanda",
    "iso:country":"AO",
    "wof:name":"Sa Leitao",
    "wof:placetype":"locality"
},
  "geometry": {"coordinates":[14.61667,-9.28333],"type":"Point"}
}