{
  "type": "Feature",
  "properties": {
    "gn:admin1_code":"12.0",
    "gn:asciiname":"Quilundo",
    "gn:country_code":"AO",
    "gn:dem":925,
    "gn:feature_class":"P",
    "gn:feature_code":"PPL",
    "gn:name":"Quilundo",
    "gn:population":0,
    "gn:timezone":"Africa/Luanda",
    "iso:country":"AO",
    "wof:name":"Quilundo",
    "wof:placetype":"locality"
},
  "geometry": {"coordinates":[15.63745,-9.16279],"type":"Point"}
}