{
  "type": "Feature",
  "properties": {
    "gn:admin1_code":"12.0",
    "gn:asciiname":"Caboloca",
    "gn:country_code":"AO",
    "gn:dem":1072,
    "gn:feature_class":"P",
    "gn:feature_code":"PPL",
    "gn:name":"Caboloca",
    "gn:population":0,
    "gn:timezone":"Africa/Luanda",
    "iso:country":"AO",
    "wof:name":"Caboloca",
    "wof:placetype":"locality"
},
  "geometry": {"coordinates":[16.99136,-10.22349],"type":"Point"}
}