{
  "type": "Feature",
  "properties": {
    "gn:admin1_code":"9.0",
    "gn:asciiname":"Mucua",
    "gn:country_code":"AO",
    "gn:dem":1256,
    "gn:feature_class":"P",
    "gn:feature_code":"PPL",
    "gn:name":"M\u00facua",
    "gn:population":0,
    "gn:timezone":"Africa/Luanda",
    "iso:country":"AO",
    "wof:name":"Mucua",
    "wof:placetype":"locality"
},
  "geometry": {"coordinates":[14.82421,-14.60518],"type":"Point"}
}