{
  "type": "Feature",
  "properties": {
    "gn:admin1_code":"2.0",
    "gn:asciiname":"Tchicala",
    "gn:country_code":"AO",
    "gn:dem":1742,
    "gn:feature_class":"P",
    "gn:feature_code":"PPL",
    "gn:name":"Tchicala",
    "gn:population":0,
    "gn:timezone":"Africa/Luanda",
    "iso:country":"AO",
    "wof:name":"Tchicala",
    "wof:placetype":"locality"
},
  "geometry": {"coordinates":[16.23437,-11.29567],"type":"Point"}
}