{
  "type": "Feature",
  "properties": {
    "gn:admin1_code":"15.0",
    "gn:asciiname":"Quimuinga",
    "gn:country_code":"AO",
    "gn:dem":1215,
    "gn:feature_class":"P",
    "gn:feature_code":"PPL",
    "gn:name":"Quimuinga",
    "gn:population":0,
    "gn:timezone":"Africa/Luanda",
    "iso:country":"AO",
    "wof:name":"Quimuinga",
    "wof:placetype":"locality"
},
  "geometry": {"coordinates":[15.63618,-7.88445],"type":"Point"}
}