{
  "type": "Feature",
  "properties": {
    "gn:admin1_code":"13.0",
    "gn:asciiname":"Sao Joao do Giraul",
    "gn:cc2":"AO",
    "gn:country_code":"AO",
    "gn:dem":-9999,
    "gn:feature_class":"P",
    "gn:feature_code":"PPL",
    "gn:name":"S\u00e3o J\u00f5ao do Giraul",
    "gn:population":0,
    "gn:timezone":"Africa/Luanda",
    "iso:country":"AO",
    "name:und_x_variant":[
        "Salinas",
        "S\u00e3o J\u00f5ao do Giraul"
    ],
    "wof:name":"Sao Joao do Giraul",
    "wof:placetype":"locality"
},
  "geometry": {"coordinates":[12.11667,-15.08333],"type":"Point"}
}