{
  "type": "Feature",
  "properties": {
    "gn:admin1_code":"15.0",
    "gn:asciiname":"Quimbunga",
    "gn:country_code":"AO",
    "gn:dem":1029,
    "gn:feature_class":"P",
    "gn:feature_code":"PPL",
    "gn:name":"Quimbunga",
    "gn:population":0,
    "gn:timezone":"Africa/Luanda",
    "iso:country":"AO",
    "wof:name":"Quimbunga",
    "wof:placetype":"locality"
},
  "geometry": {"coordinates":[15.31054,-6.92131],"type":"Point"}
}