{
  "type": "Feature",
  "properties": {
    "gn:admin1_code":"2.0",
    "gn:asciiname":"Tchimbuio",
    "gn:country_code":"AO",
    "gn:dem":1748,
    "gn:feature_class":"P",
    "gn:feature_code":"PPL",
    "gn:name":"Tchimbuio",
    "gn:population":0,
    "gn:timezone":"Africa/Luanda",
    "iso:country":"AO",
    "name:und_x_variant":[
        "Chimbuio"
    ],
    "wof:name":"Tchimbuio",
    "wof:placetype":"locality"
},
  "geometry": {"coordinates":[17.03505,-11.67512],"type":"Point"}
}