{
  "type": "Feature",
  "properties": {
    "gn:admin1_code":"14.0",
    "gn:asciiname":"Chitohola",
    "gn:country_code":"AO",
    "gn:dem":1169,
    "gn:feature_class":"P",
    "gn:feature_code":"PPL",
    "gn:name":"Chitohola",
    "gn:population":0,
    "gn:timezone":"Africa/Luanda",
    "iso:country":"AO",
    "wof:name":"Chitohola",
    "wof:placetype":"locality"
},
  "geometry": {"coordinates":[22.93333,-12.83333],"type":"Point"}
}