{
  "type": "Feature",
  "properties": {
    "gn:admin1_code":"17.0",
    "gn:asciiname":"Xamassanza",
    "gn:country_code":"AO",
    "gn:dem":934,
    "gn:feature_class":"P",
    "gn:feature_code":"PPL",
    "gn:name":"Xamassanza",
    "gn:population":0,
    "gn:timezone":"Africa/Luanda",
    "iso:country":"AO",
    "wof:name":"Xamassanza",
    "wof:placetype":"locality"
},
  "geometry": {"coordinates":[18.29009,-8.81446],"type":"Point"}
}