{
  "type": "Feature",
  "properties": {
    "gn:admin1_code":"12.0",
    "gn:asciiname":"Ndala Canhangue",
    "gn:country_code":"AO",
    "gn:dem":1125,
    "gn:feature_class":"P",
    "gn:feature_code":"PPL",
    "gn:name":"Ndala Canhangue",
    "gn:population":0,
    "gn:timezone":"Africa/Luanda",
    "iso:country":"AO",
    "name:und_x_variant":[
        "Dalacanhanga",
        "Dala Canhango",
        "Ndala Canhangue"
    ],
    "wof:name":"Ndala Canhangue",
    "wof:placetype":"locality"
},
  "geometry": {"coordinates":[15.8238,-9.03553],"type":"Point"}
}