{
  "type": "Feature",
  "properties": {
    "gn:admin1_code":"5.0",
    "gn:asciiname":"Quiringo",
    "gn:country_code":"AO",
    "gn:dem":249,
    "gn:feature_class":"P",
    "gn:feature_code":"PPL",
    "gn:name":"Quiringo",
    "gn:population":0,
    "gn:timezone":"Africa/Luanda",
    "iso:country":"AO",
    "name:und_x_variant":[
        "Quiringa",
        "Quiringo"
    ],
    "wof:name":"Quiringo",
    "wof:placetype":"locality"
},
  "geometry": {"coordinates":[14.58056,-9.58746],"type":"Point"}
}