{
  "type": "Feature",
  "properties": {
    "gn:admin1_code":"8.0",
    "gn:asciiname":"Maiaia",
    "gn:cc2":"AO",
    "gn:country_code":"AO",
    "gn:dem":1504,
    "gn:feature_class":"P",
    "gn:feature_code":"PPL",
    "gn:name":"Maiaia",
    "gn:population":0,
    "gn:timezone":"Africa/Luanda",
    "iso:country":"AO",
    "name:und_x_variant":[
        "Messias",
        "Maiaia"
    ],
    "wof:name":"Maiaia",
    "wof:placetype":"locality"
},
  "geometry": {"coordinates":[15.68333,-12.55],"type":"Point"}
}