{
  "type": "Feature",
  "properties": {
    "gn:admin1_code":"9.0",
    "gn:asciiname":"Quilengues",
    "gn:cc2":"AO",
    "gn:country_code":"AO",
    "gn:dem":843,
    "gn:feature_class":"P",
    "gn:feature_code":"PPL",
    "gn:name":"Quilengues",
    "gn:population":0,
    "gn:timezone":"Africa/Luanda",
    "iso:country":"AO",
    "name:azb_x_preferred":[
        "\u06a9\u0648\u06cc\u0644\u0646\u0642\u0648\u0633"
    ],
    "name:cat_x_preferred":[
        "Quilengues"
    ],
    "name:deu_x_preferred":[
        "Quilengues"
    ],
    "name:fas_x_preferred":[
        "\u06a9\u0648\u06cc\u0644\u0646\u06af\u0648\u0633"
    ],
    "name:fra_x_preferred":[
        "Quilengues"
    ],
    "name:ita_x_preferred":[
        "Quilengues"
    ],
    "name:msa_x_preferred":[
        "Quilengues"
    ],
    "name:por_x_preferred":[
        "Quilengues"
    ],
    "name:rus_x_preferred":[
        "\u041a\u0438\u043b\u0435\u043d\u0433\u0435\u0448"
    ],
    "name:spa_x_preferred":[
        "Quilengues"
    ],
    "name:und_x_variant":[
        "Killenges",
        "Quilenges"
    ],
    "name:zho_x_preferred":[
        "\u57fa\u502b\u5409\u4ec0"
    ],
    "wof:name":"Quilengues",
    "wof:placetype":"locality"
},
  "geometry": {"coordinates":[14.08333,-14.06667],"type":"Point"}
}