{
  "type": "Feature",
  "properties": {
    "gn:admin1_code":"9.0",
    "gn:asciiname":"Quilengues",
    "gn:cc2":"AO",
    "gn:country_code":"AO",
    "gn:dem":843,
    "gn:feature_class":"P",
    "gn:feature_code":"PPL",
    "gn:name":"Quilengues",
    "gn:population":0,
    "gn:timezone":"Africa/Luanda",
    "iso:country":"AO",
    "name:rus_x_preferred":[
        "\u041a\u0438\u043b\u0435\u043d\u0433\u0435\u0448"
    ],
    "name:und_x_variant":[
        "Killenges",
        "Quilenges",
        "Quilengues"
    ],
    "wof:name":"Quilengues",
    "wof:placetype":"locality"
},
  "geometry": {"coordinates":[14.08333,-14.06667],"type":"Point"}
}