{
  "type": "Feature",
  "properties": {
    "gn:admin1_code":"19.0",
    "gn:asciiname":"Cabocha",
    "gn:country_code":"AO",
    "gn:dem":25,
    "gn:feature_class":"P",
    "gn:feature_code":"PPL",
    "gn:name":"Cabocha",
    "gn:population":0,
    "gn:timezone":"Africa/Luanda",
    "iso:country":"AO",
    "wof:name":"Cabocha",
    "wof:placetype":"locality"
},
  "geometry": {"coordinates":[13.67306,-8.58361],"type":"Point"}
}