{
  "type": "Feature",
  "properties": {
    "gn:admin1_code":"17.0",
    "gn:asciiname":"Camaxilo",
    "gn:country_code":"AO",
    "gn:dem":1097,
    "gn:feature_class":"P",
    "gn:feature_code":"PPL",
    "gn:name":"Camaxilo",
    "gn:population":0,
    "gn:timezone":"Africa/Luanda",
    "iso:country":"AO",
    "name:rus_x_preferred":[
        "\u041a\u0430\u043c\u0430\u043a\u0441\u0438\u043b\u0443"
    ],
    "name:und_x_variant":[
        "Kamashilu",
        "Camaxil",
        "Camaxilo"
    ],
    "wof:name":"Camaxilo",
    "wof:placetype":"locality"
},
  "geometry": {"coordinates":[18.91055,-8.3383],"type":"Point"}
}