{
  "type": "Feature",
  "properties": {
    "gn:admin1_code":"1.0",
    "gn:asciiname":"Cateque Saieiro",
    "gn:cc2":"AO",
    "gn:country_code":"AO",
    "gn:dem":861,
    "gn:feature_class":"P",
    "gn:feature_code":"PPL",
    "gn:name":"Cateque Saieiro",
    "gn:population":0,
    "gn:timezone":"Africa/Luanda",
    "iso:country":"AO",
    "name:und_x_variant":[
        "Cateque",
        "Cateque Saieiro"
    ],
    "wof:name":"Cateque Saieiro",
    "wof:placetype":"locality"
},
  "geometry": {"coordinates":[14.03333,-12.46667],"type":"Point"}
}