{
  "type": "Feature",
  "properties": {
    "gn:admin1_code":"5.0",
    "gn:asciiname":"Fazenda Santo Antonio",
    "gn:country_code":"AO",
    "gn:dem":732,
    "gn:feature_class":"P",
    "gn:feature_code":"PPL",
    "gn:name":"Fazenda Santo Ant\u00f3nio",
    "gn:population":0,
    "gn:timezone":"Africa/Luanda",
    "iso:country":"AO",
    "wof:name":"Fazenda Santo Antonio",
    "wof:placetype":"locality"
},
  "geometry": {"coordinates":[14.63333,-9.06667],"type":"Point"}
}