{
  "type": "Feature",
  "properties": {
    "gn:admin1_code":"1.0",
    "gn:asciiname":"Bambi",
    "gn:country_code":"AO",
    "gn:dem":1013,
    "gn:feature_class":"P",
    "gn:feature_code":"PPL",
    "gn:name":"Bambi",
    "gn:population":0,
    "gn:timezone":"Africa/Luanda",
    "iso:country":"AO",
    "wof:name":"Bambi",
    "wof:placetype":"locality"
},
  "geometry": {"coordinates":[14.03333,-12.56667],"type":"Point"}
}