{
  "type": "Feature",
  "properties": {
    "gn:admin1_code":"2.0",
    "gn:asciiname":"Epandi",
    "gn:country_code":"AO",
    "gn:dem":1718,
    "gn:feature_class":"P",
    "gn:feature_code":"PPL",
    "gn:name":"Epandi",
    "gn:population":0,
    "gn:timezone":"Africa/Luanda",
    "iso:country":"AO",
    "wof:name":"Epandi",
    "wof:placetype":"locality"
},
  "geometry": {"coordinates":[16.7775,-11.56107],"type":"Point"}
}