{
  "type": "Feature",
  "properties": {
    "gn:admin1_code":"6.0",
    "gn:asciiname":"Quipuco",
    "gn:country_code":"AO",
    "gn:dem":1286,
    "gn:feature_class":"P",
    "gn:feature_code":"PPL",
    "gn:name":"Quipuco",
    "gn:population":0,
    "gn:timezone":"Africa/Luanda",
    "iso:country":"AO",
    "wof:name":"Quipuco",
    "wof:placetype":"locality"
},
  "geometry": {"coordinates":[15.155,-11.10122],"type":"Point"}
}