{
  "type": "Feature",
  "properties": {
    "gn:admin1_code":"18.0",
    "gn:asciiname":"Muhesse",
    "gn:country_code":"AO",
    "gn:dem":1364,
    "gn:feature_class":"P",
    "gn:feature_code":"PPL",
    "gn:name":"Muhesse",
    "gn:population":0,
    "gn:timezone":"Africa/Luanda",
    "iso:country":"AO",
    "wof:name":"Muhesse",
    "wof:placetype":"locality"
},
  "geometry": {"coordinates":[19.34631,-10.38382],"type":"Point"}
}