{
  "type": "Feature",
  "properties": {
    "gn:admin1_code":"8.0",
    "gn:asciiname":"Calilongai",
    "gn:country_code":"AO",
    "gn:dem":1434,
    "gn:feature_class":"P",
    "gn:feature_code":"PPL",
    "gn:name":"Calilongai",
    "gn:population":0,
    "gn:timezone":"Africa/Luanda",
    "iso:country":"AO",
    "wof:name":"Calilongai",
    "wof:placetype":"locality"
},
  "geometry": {"coordinates":[15.48333,-11.96667],"type":"Point"}
}