{
  "type": "Feature",
  "properties": {
    "gn:admin1_code":"17.0",
    "gn:asciiname":"Cambacache",
    "gn:country_code":"AO",
    "gn:dem":1135,
    "gn:feature_class":"P",
    "gn:feature_code":"PPL",
    "gn:name":"Cambacache",
    "gn:population":0,
    "gn:timezone":"Africa/Luanda",
    "iso:country":"AO",
    "wof:name":"Cambacache",
    "wof:placetype":"locality"
},
  "geometry": {"coordinates":[19.21667,-9.45],"type":"Point"}
}