{
  "type": "Feature",
  "properties": {
    "gn:admin1_code":"1.0",
    "gn:asciiname":"Chamume",
    "gn:cc2":"AO",
    "gn:country_code":"AO",
    "gn:dem":-9999,
    "gn:feature_class":"P",
    "gn:feature_code":"PPL",
    "gn:name":"Chamume",
    "gn:population":0,
    "gn:timezone":"Africa/Luanda",
    "iso:country":"AO",
    "name:und_x_variant":[
        "Chamune",
        "Chamume"
    ],
    "wof:name":"Chamume",
    "wof:placetype":"locality"
},
  "geometry": {"coordinates":[13.09278,-12.70694],"type":"Point"}
}