{
  "type": "Feature",
  "properties": {
    "gn:admin1_code":"7.0",
    "gn:asciiname":"Bambaemo",
    "gn:country_code":"AO",
    "gn:dem":1043,
    "gn:feature_class":"P",
    "gn:feature_code":"PPL",
    "gn:name":"Bambaemo",
    "gn:population":0,
    "gn:timezone":"Africa/Luanda",
    "iso:country":"AO",
    "wof:name":"Bambaemo",
    "wof:placetype":"locality"
},
  "geometry": {"coordinates":[13.98333,-17.15],"type":"Point"}
}