{
  "type": "Feature",
  "properties": {
    "gn:admin1_code":"6.0",
    "gn:asciiname":"Vila Graca de Utende",
    "gn:country_code":"AO",
    "gn:dem":1245,
    "gn:feature_class":"P",
    "gn:feature_code":"PPL",
    "gn:name":"Vila Gra\u00e7a de Utende",
    "gn:population":0,
    "gn:timezone":"Africa/Luanda",
    "iso:country":"AO",
    "wof:name":"Vila Graca de Utende",
    "wof:placetype":"locality"
},
  "geometry": {"coordinates":[15.19217,-10.94475],"type":"Point"}
}