{
  "type": "Feature",
  "properties": {
    "gn:admin1_code":"19.0",
    "gn:asciiname":"Quinvela",
    "gn:country_code":"AO",
    "gn:dem":853,
    "gn:feature_class":"P",
    "gn:feature_code":"PPL",
    "gn:name":"Quinvela",
    "gn:population":0,
    "gn:timezone":"Africa/Luanda",
    "iso:country":"AO",
    "wof:name":"Quinvela",
    "wof:placetype":"locality"
},
  "geometry": {"coordinates":[14.78333,-8.66667],"type":"Point"}
}