{
  "type": "Feature",
  "properties": {
    "gn:admin1_code":"12.0",
    "gn:asciiname":"Ngumba",
    "gn:country_code":"AO",
    "gn:dem":1135,
    "gn:feature_class":"P",
    "gn:feature_code":"PPL",
    "gn:name":"Ngumba",
    "gn:population":0,
    "gn:timezone":"Africa/Luanda",
    "iso:country":"AO",
    "name:ceb_x_preferred":[
        "Ngumba"
    ],
    "name:deu_x_preferred":[
        "Ngumba"
    ],
    "name:swe_x_preferred":[
        "Ngumba"
    ],
    "wof:name":"Ngumba",
    "wof:placetype":"locality"
},
  "geometry": {"coordinates":[16.32969,-9.41034],"type":"Point"}
}