{
  "type": "Feature",
  "properties": {
    "gn:admin1_code":"17.0",
    "gn:asciiname":"Sambamba",
    "gn:country_code":"AO",
    "gn:dem":1142,
    "gn:feature_class":"P",
    "gn:feature_code":"PPL",
    "gn:name":"Sambamba",
    "gn:population":0,
    "gn:timezone":"Africa/Luanda",
    "iso:country":"AO",
    "wof:name":"Sambamba",
    "wof:placetype":"locality"
},
  "geometry": {"coordinates":[18.30297,-10.33635],"type":"Point"}
}