{
  "type": "Feature",
  "properties": {
    "gn:admin1_code":"2.0",
    "gn:asciiname":"Dandau",
    "gn:cc2":"AO",
    "gn:country_code":"AO",
    "gn:dem":1758,
    "gn:feature_class":"P",
    "gn:feature_code":"PPL",
    "gn:name":"Dandau",
    "gn:population":0,
    "gn:timezone":"Africa/Luanda",
    "iso:country":"AO",
    "name:und_x_variant":[
        "Dendau",
        "Dandau"
    ],
    "wof:name":"Dandau",
    "wof:placetype":"locality"
},
  "geometry": {"coordinates":[16.91667,-11.91667],"type":"Point"}
}