{
  "type": "Feature",
  "properties": {
    "gn:admin1_code":"17.0",
    "gn:asciiname":"Ngunza Cambolo",
    "gn:country_code":"AO",
    "gn:dem":992,
    "gn:feature_class":"P",
    "gn:feature_code":"PPL",
    "gn:name":"Ngunza Cambolo",
    "gn:population":0,
    "gn:timezone":"Africa/Luanda",
    "iso:country":"AO",
    "wof:name":"Ngunza Cambolo",
    "wof:placetype":"locality"
},
  "geometry": {"coordinates":[17.90087999999999,-9.63832],"type":"Point"}
}