{
  "type": "Feature",
  "properties": {
    "gn:admin1_code":"9.0",
    "gn:asciiname":"Bunjei",
    "gn:cc2":"AO",
    "gn:country_code":"AO",
    "gn:dem":1690,
    "gn:feature_class":"P",
    "gn:feature_code":"PPL",
    "gn:name":"Bunjei",
    "gn:population":0,
    "gn:timezone":"Africa/Luanda",
    "iso:country":"AO",
    "name:und_x_variant":[
        "Bungei",
        "Bundjei",
        "Bundja",
        "Bunjei"
    ],
    "wof:name":"Bunjei",
    "wof:placetype":"locality"
},
  "geometry": {"coordinates":[16.01667,-13.53333],"type":"Point"}
}