{
  "type": "Feature",
  "properties": {
    "gn:admin1_code":"15.0",
    "gn:asciiname":"Quiluanga",
    "gn:country_code":"AO",
    "gn:dem":866,
    "gn:feature_class":"P",
    "gn:feature_code":"PPL",
    "gn:name":"Quiluanga",
    "gn:population":0,
    "gn:timezone":"Africa/Luanda",
    "iso:country":"AO",
    "wof:name":"Quiluanga",
    "wof:placetype":"locality"
},
  "geometry": {"coordinates":[15.12744,-5.93503],"type":"Point"}
}