{
  "type": "Feature",
  "properties": {
    "gn:admin1_code":"18.0",
    "gn:asciiname":"Satechela",
    "gn:cc2":"AO",
    "gn:country_code":"AO",
    "gn:dem":1050,
    "gn:feature_class":"P",
    "gn:feature_code":"PPL",
    "gn:name":"Satechela",
    "gn:population":0,
    "gn:timezone":"Africa/Luanda",
    "iso:country":"AO",
    "name:und_x_variant":[
        "Sachicoca",
        "Satechela"
    ],
    "wof:name":"Satechela",
    "wof:placetype":"locality"
},
  "geometry": {"coordinates":[21.01667,-9.06667],"type":"Point"}
}