{
  "type": "Feature",
  "properties": {
    "gn:admin1_code":"6.0",
    "gn:asciiname":"Calongue",
    "gn:cc2":"AO",
    "gn:country_code":"AO",
    "gn:dem":465,
    "gn:feature_class":"P",
    "gn:feature_code":"PPL",
    "gn:name":"Calongue",
    "gn:population":0,
    "gn:timezone":"Africa/Luanda",
    "iso:country":"AO",
    "name:und_x_variant":[
        "Calonquela",
        "Calongue"
    ],
    "wof:name":"Calongue",
    "wof:placetype":"locality"
},
  "geometry": {"coordinates":[14.21667,-11.55],"type":"Point"}
}