{
  "type": "Feature",
  "properties": {
    "gn:admin1_code":"17.0",
    "gn:asciiname":"Muiamba",
    "gn:cc2":"AO",
    "gn:country_code":"AO",
    "gn:dem":1017,
    "gn:feature_class":"P",
    "gn:feature_code":"PPL",
    "gn:name":"Muiamba",
    "gn:population":0,
    "gn:timezone":"Africa/Luanda",
    "iso:country":"AO",
    "name:und_x_variant":[
        "Uamba",
        "Muiamba"
    ],
    "wof:name":"Muiamba",
    "wof:placetype":"locality"
},
  "geometry": {"coordinates":[18.48333,-8.65],"type":"Point"}
}