{
  "type": "Feature",
  "properties": {
    "gn:admin1_code":"15.0",
    "gn:asciiname":"Angola Nova",
    "gn:country_code":"AO",
    "gn:dem":1037,
    "gn:feature_class":"P",
    "gn:feature_code":"PPL",
    "gn:name":"Angola Nova",
    "gn:population":0,
    "gn:timezone":"Africa/Luanda",
    "iso:country":"AO",
    "wof:name":"Angola Nova",
    "wof:placetype":"locality"
},
  "geometry": {"coordinates":[15.04127,-6.64934],"type":"Point"}
}