{
  "type": "Feature",
  "properties": {
    "gn:admin1_code":"17.0",
    "gn:asciiname":"Cha",
    "gn:cc2":"AO",
    "gn:country_code":"AO",
    "gn:dem":1019,
    "gn:feature_class":"P",
    "gn:feature_code":"PPL",
    "gn:name":"Cha",
    "gn:population":0,
    "gn:timezone":"Africa/Luanda",
    "iso:country":"AO",
    "name:und_x_variant":[
        "Ch\u00e1 Malembe",
        "Cha"
    ],
    "wof:name":"Cha",
    "wof:placetype":"locality"
},
  "geometry": {"coordinates":[19.95,-8.51667],"type":"Point"}
}