{
  "type": "Feature",
  "properties": {
    "gn:admin1_code":"15.0",
    "gn:asciiname":"Quitoana",
    "gn:country_code":"AO",
    "gn:dem":771,
    "gn:feature_class":"P",
    "gn:feature_code":"PPL",
    "gn:name":"Quitoana",
    "gn:population":0,
    "gn:timezone":"Africa/Luanda",
    "iso:country":"AO",
    "wof:name":"Quitoana",
    "wof:placetype":"locality"
},
  "geometry": {"coordinates":[15.61667,-6.06667],"type":"Point"}
}