{
  "type": "Feature",
  "properties": {
    "gn:admin1_code":"12.0",
    "gn:asciiname":"Quitubico Primeiro",
    "gn:country_code":"AO",
    "gn:dem":732,
    "gn:feature_class":"P",
    "gn:feature_code":"PPL",
    "gn:name":"Quitubico Primeiro",
    "gn:population":0,
    "gn:timezone":"Africa/Luanda",
    "iso:country":"AO",
    "wof:name":"Quitubico Primeiro",
    "wof:placetype":"locality"
},
  "geometry": {"coordinates":[17.24065,-9.1058],"type":"Point"}
}