{
  "type": "Feature",
  "properties": {
    "gn:admin1_code":"2.0",
    "gn:asciiname":"Saluhuma",
    "gn:country_code":"AO",
    "gn:dem":1396,
    "gn:feature_class":"P",
    "gn:feature_code":"PPL",
    "gn:name":"Saluhuma",
    "gn:population":0,
    "gn:timezone":"Africa/Luanda",
    "iso:country":"AO",
    "wof:name":"Saluhuma",
    "wof:placetype":"locality"
},
  "geometry": {"coordinates":[17.39906,-11.85852],"type":"Point"}
}