{
  "type": "Feature",
  "properties": {
    "gn:admin1_code":"19.0",
    "gn:asciiname":"Nzemba",
    "gn:country_code":"AO",
    "gn:dem":484,
    "gn:feature_class":"P",
    "gn:feature_code":"PPL",
    "gn:name":"Nzemba",
    "gn:population":0,
    "gn:timezone":"Africa/Luanda",
    "iso:country":"AO",
    "wof:name":"Nzemba",
    "wof:placetype":"locality"
},
  "geometry": {"coordinates":[14.40378,-10.22191],"type":"Point"}
}