{
  "type": "Feature",
  "properties": {
    "gn:admin1_code":"16.0",
    "gn:asciiname":"Undze",
    "gn:country_code":"AO",
    "gn:dem":613,
    "gn:feature_class":"P",
    "gn:feature_code":"PPL",
    "gn:name":"Undze",
    "gn:population":0,
    "gn:timezone":"Africa/Luanda",
    "iso:country":"AO",
    "name:und_x_variant":[
        "Unza",
        "Unze",
        "Undze"
    ],
    "wof:name":"Undze",
    "wof:placetype":"locality"
},
  "geometry": {"coordinates":[14.45155,-6.09918],"type":"Point"}
}