{
  "type": "Feature",
  "properties": {
    "gn:admin1_code":"6.0",
    "gn:asciiname":"Dumbo",
    "gn:country_code":"AO",
    "gn:dem":1426,
    "gn:feature_class":"P",
    "gn:feature_code":"PPL",
    "gn:name":"Dumbo",
    "gn:population":0,
    "gn:timezone":"Africa/Luanda",
    "iso:country":"AO",
    "wof:name":"Dumbo",
    "wof:placetype":"locality"
},
  "geometry": {"coordinates":[15.46667,-11.38333],"type":"Point"}
}