{
  "type": "Feature",
  "properties": {
    "iso:country":"AO",
    "ne:ADM0CAP":0.0,
    "ne:ADM0NAME":"Angola",
    "ne:ADM0_A3":"AGO",
    "ne:ADM1NAME":"HuOla",
    "ne:ADMIN1_COD":0,
    "ne:CAPALT":0,
    "ne:CHANGED":0,
    "ne:CHECKME":0,
    "ne:COMPARE":0,
    "ne:DIFFASCII":0,
    "ne:ELEVATION":0.0,
    "ne:FEATURECLA":"Populated place",
    "ne:GEONAMEID":-1,
    "ne:GEONAMESNO":"No GeoNames match due to small population, not in GeoNames, or poor NEV placement.",
    "ne:GN_POP":0,
    "ne:GTOPO30":0.0,
    "ne:ISO_A2":"AO",
    "ne:LABELRANK":6,
    "ne:LATITUDE":-15.749596,
    "ne:LONGITUDE":14.080009,
    "ne:LS_MATCH":1,
    "ne:LS_NAME":"Chibemba",
    "ne:MAX_AREAKM":2.0,
    "ne:MAX_AREAMI":1.0,
    "ne:MAX_BBXMAX":14.091667,
    "ne:MAX_BBXMIN":14.075,
    "ne:MAX_BBYMAX":-15.741667,
    "ne:MAX_BBYMIN":-15.758333,
    "ne:MAX_NATSCA":20.0,
    "ne:MAX_PERKM":7.0,
    "ne:MAX_PERMI":5.0,
    "ne:MAX_POP10":1502,
    "ne:MAX_POP20":1502,
    "ne:MAX_POP300":0,
    "ne:MAX_POP310":0,
    "ne:MAX_POP50":0,
    "ne:MEAN_BBXC":14.084722,
    "ne:MEAN_BBYC":-15.751389,
    "ne:MEGACITY":0,
    "ne:MIN_AREAKM":2.0,
    "ne:MIN_AREAMI":1.0,
    "ne:MIN_BBXMAX":14.091667,
    "ne:MIN_BBXMIN":14.075,
    "ne:MIN_BBYMAX":-15.741667,
    "ne:MIN_BBYMIN":-15.758333,
    "ne:MIN_PERKM":7.0,
    "ne:MIN_PERMI":5.0,
    "ne:NAME":"Chibemba",
    "ne:NAMEASCII":"Chibemba",
    "ne:NAMEDIFF":0,
    "ne:NATSCALE":20,
    "ne:POP1950":0,
    "ne:POP1955":0,
    "ne:POP1960":0,
    "ne:POP1965":0,
    "ne:POP1970":0,
    "ne:POP1975":0,
    "ne:POP1980":0,
    "ne:POP1985":0,
    "ne:POP1990":0,
    "ne:POP1995":0,
    "ne:POP2000":0,
    "ne:POP2005":0,
    "ne:POP2010":0,
    "ne:POP2015":0,
    "ne:POP2020":0,
    "ne:POP2025":0,
    "ne:POP2050":0,
    "ne:POP_MAX":1502,
    "ne:POP_MIN":1502,
    "ne:POP_OTHER":0,
    "ne:RANK_MAX":3,
    "ne:RANK_MIN":3,
    "ne:SCALERANK":7,
    "ne:SOV0NAME":"Angola",
    "ne:SOV_A3":"AGO",
    "ne:UN_FID":0,
    "ne:UN_LAT":0.0,
    "ne:UN_LONG":0.0,
    "ne:WORLDCITY":0,
    "ne:min_zoom":6.7,
    "wof:name":"Chibemba",
    "wof:placetype":"locality"
},
  "geometry": {"coordinates":[14.08000850287357,-15.74959552120549],"type":"Point"}
}