{
  "type": "Feature",
  "properties": {
    "gn:admin1_code":"5.0",
    "gn:asciiname":"Bungo",
    "gn:country_code":"AO",
    "gn:dem":295,
    "gn:feature_class":"P",
    "gn:feature_code":"PPL",
    "gn:name":"Bungo",
    "gn:population":0,
    "gn:timezone":"Africa/Luanda",
    "iso:country":"AO",
    "name:ceb_x_preferred":[
        "Bungo"
    ],
    "name:deu_x_preferred":[
        "Bungo"
    ],
    "name:fra_x_preferred":[
        "Bungo"
    ],
    "name:ind_x_preferred":[
        "Bungo"
    ],
    "name:lit_x_preferred":[
        "Bungo"
    ],
    "name:nld_x_preferred":[
        "Bungo"
    ],
    "name:pol_x_preferred":[
        "Bungo"
    ],
    "name:por_x_preferred":[
        "Bungo"
    ],
    "name:rus_x_preferred":[
        "\u0411\u0443\u043d\u0433\u043e"
    ],
    "name:slk_x_preferred":[
        "Bungo"
    ],
    "name:swe_x_preferred":[
        "Bungo"
    ],
    "wof:name":"Bungo",
    "wof:placetype":"locality"
},
  "geometry": {"coordinates":[14.66786,-9.6923],"type":"Point"}
}