{
  "type": "Feature",
  "properties": {
    "gn:admin1_code":"5.0",
    "gn:asciiname":"Bungo",
    "gn:country_code":"AO",
    "gn:dem":295,
    "gn:feature_class":"P",
    "gn:feature_code":"PPL",
    "gn:name":"Bungo",
    "gn:population":0,
    "gn:timezone":"Africa/Luanda",
    "iso:country":"AO",
    "wof:name":"Bungo",
    "wof:placetype":"locality"
},
  "geometry": {"coordinates":[14.66786,-9.6923],"type":"Point"}
}