{
  "type": "Feature",
  "properties": {
    "gn:admin1_code":"6.0",
    "gn:asciiname":"Cassuba",
    "gn:country_code":"AO",
    "gn:dem":1217,
    "gn:feature_class":"P",
    "gn:feature_code":"PPL",
    "gn:name":"Cassuba",
    "gn:population":0,
    "gn:timezone":"Africa/Luanda",
    "iso:country":"AO",
    "name:und_x_variant":[
        "Cassemba",
        "Cassuba"
    ],
    "wof:name":"Cassuba",
    "wof:placetype":"locality"
},
  "geometry": {"coordinates":[15.01863,-11.02441],"type":"Point"}
}