{
  "type": "Feature",
  "properties": {
    "gn:admin1_code":"19.0",
    "gn:asciiname":"Camaritare",
    "gn:country_code":"AO",
    "gn:dem":726,
    "gn:feature_class":"P",
    "gn:feature_code":"PPL",
    "gn:name":"Camaritare",
    "gn:population":0,
    "gn:timezone":"Africa/Luanda",
    "iso:country":"AO",
    "name:und_x_variant":[
        "Cambuta",
        "Camaritare"
    ],
    "wof:name":"Camaritare",
    "wof:placetype":"locality"
},
  "geometry": {"coordinates":[14.88333,-8.56667],"type":"Point"}
}