{
  "type": "Feature",
  "properties": {
    "gn:admin1_code":"5.0",
    "gn:asciiname":"Mbondo Caluache",
    "gn:country_code":"AO",
    "gn:dem":942,
    "gn:feature_class":"P",
    "gn:feature_code":"PPL",
    "gn:name":"Mbondo Caluache",
    "gn:population":0,
    "gn:timezone":"Africa/Luanda",
    "iso:country":"AO",
    "name:und_x_variant":[
        "Bondo"
    ],
    "wof:name":"Mbondo Caluache",
    "wof:placetype":"locality"
},
  "geometry": {"coordinates":[15.20339,-8.85312],"type":"Point"}
}