{
  "type": "Feature",
  "properties": {
    "gn:admin1_code":"8.0",
    "gn:asciiname":"Canjangue",
    "gn:cc2":"AO",
    "gn:country_code":"AO",
    "gn:dem":1707,
    "gn:feature_class":"P",
    "gn:feature_code":"PPL",
    "gn:name":"Canjangue",
    "gn:population":0,
    "gn:timezone":"Africa/Luanda",
    "iso:country":"AO",
    "name:und_x_variant":[
        "Candange",
        "Canjangue"
    ],
    "wof:name":"Canjangue",
    "wof:placetype":"locality"
},
  "geometry": {"coordinates":[15.23333,-12.63333],"type":"Point"}
}