{
  "type": "Feature",
  "properties": {
    "gn:admin1_code":"17.0",
    "gn:asciiname":"Mamuxito",
    "gn:cc2":"AO",
    "gn:country_code":"AO",
    "gn:dem":725,
    "gn:feature_class":"P",
    "gn:feature_code":"PPL",
    "gn:name":"Mamuxito",
    "gn:population":0,
    "gn:timezone":"Africa/Luanda",
    "iso:country":"AO",
    "name:und_x_variant":[
        "Mamachita",
        "Mamuxito"
    ],
    "wof:name":"Mamuxito",
    "wof:placetype":"locality"
},
  "geometry": {"coordinates":[21.35,-7.73333],"type":"Point"}
}