{
  "type": "Feature",
  "properties": {
    "gn:admin1_code":"12.0",
    "gn:asciiname":"Quiquende",
    "gn:country_code":"AO",
    "gn:dem":1071,
    "gn:feature_class":"P",
    "gn:feature_code":"PPL",
    "gn:name":"Quiquende",
    "gn:population":0,
    "gn:timezone":"Africa/Luanda",
    "iso:country":"AO",
    "wof:name":"Quiquende",
    "wof:placetype":"locality"
},
  "geometry": {"coordinates":[16.02806,-9.38013],"type":"Point"}
}