{
  "type": "Feature",
  "properties": {
    "gn:admin1_code":"6.0",
    "gn:asciiname":"Mungue",
    "gn:country_code":"AO",
    "gn:dem":977,
    "gn:feature_class":"P",
    "gn:feature_code":"PPL",
    "gn:name":"Mungue",
    "gn:population":0,
    "gn:timezone":"Africa/Luanda",
    "iso:country":"AO",
    "wof:name":"Mungue",
    "wof:placetype":"locality"
},
  "geometry": {"coordinates":[14.48559,-10.65009],"type":"Point"}
}