{
  "type": "Feature",
  "properties": {
    "gn:admin1_code":"15.0",
    "gn:asciiname":"Catambi Primeiro",
    "gn:country_code":"AO",
    "gn:dem":984,
    "gn:feature_class":"P",
    "gn:feature_code":"PPL",
    "gn:name":"Catambi Primeiro",
    "gn:population":0,
    "gn:timezone":"Africa/Luanda",
    "iso:country":"AO",
    "wof:name":"Catambi Primeiro",
    "wof:placetype":"locality"
},
  "geometry": {"coordinates":[15.14375,-7.54163],"type":"Point"}
}