{
  "type": "Feature",
  "properties": {
    "gn:admin1_code":"6.0",
    "gn:asciiname":"Candele",
    "gn:country_code":"AO",
    "gn:dem":1408,
    "gn:feature_class":"P",
    "gn:feature_code":"PPL",
    "gn:name":"Candele",
    "gn:population":0,
    "gn:timezone":"Africa/Luanda",
    "iso:country":"AO",
    "wof:name":"Candele",
    "wof:placetype":"locality"
},
  "geometry": {"coordinates":[14.44855,-10.91046],"type":"Point"}
}