{
  "type": "Feature",
  "properties": {
    "gn:admin1_code":"6.0",
    "gn:asciiname":"Mbanza Quicucuto",
    "gn:country_code":"AO",
    "gn:dem":1259,
    "gn:feature_class":"P",
    "gn:feature_code":"PPL",
    "gn:name":"Mbanza Quicucuto",
    "gn:population":0,
    "gn:timezone":"Africa/Luanda",
    "iso:country":"AO",
    "name:und_x_variant":[
        "Tchicucuto",
        "Banza Quicocuto",
        "Mbanza Quicucuto"
    ],
    "wof:name":"Mbanza Quicucuto",
    "wof:placetype":"locality"
},
  "geometry": {"coordinates":[15.17788,-11.20969],"type":"Point"}
}