{
  "type": "Feature",
  "properties": {
    "gn:admin1_code":"6.0",
    "gn:asciiname":"Capingana",
    "gn:country_code":"AO",
    "gn:dem":1684,
    "gn:feature_class":"P",
    "gn:feature_code":"PPL",
    "gn:name":"Capingana",
    "gn:population":0,
    "gn:timezone":"Africa/Luanda",
    "iso:country":"AO",
    "wof:name":"Capingana",
    "wof:placetype":"locality"
},
  "geometry": {"coordinates":[14.78333,-11.81667],"type":"Point"}
}