{
  "type": "Feature",
  "properties": {
    "gn:admin1_code":"5.0",
    "gn:asciiname":"Bango Azongo",
    "gn:cc2":"AO",
    "gn:country_code":"AO",
    "gn:dem":379,
    "gn:feature_class":"P",
    "gn:feature_code":"PPL",
    "gn:name":"Bango Azongo",
    "gn:population":0,
    "gn:timezone":"Africa/Luanda",
    "iso:country":"AO",
    "name:und_x_variant":[
        "Fazenda Bancoazongo",
        "Bango Azongo"
    ],
    "wof:name":"Bango Azongo",
    "wof:placetype":"locality"
},
  "geometry": {"coordinates":[14.53333,-9.05],"type":"Point"}
}