{
  "type": "Feature",
  "properties": {
    "gn:admin1_code":"12.0",
    "gn:asciiname":"Fazenda Teixeira",
    "gn:cc2":"AO",
    "gn:country_code":"AO",
    "gn:dem":1053,
    "gn:feature_class":"P",
    "gn:feature_code":"PPL",
    "gn:name":"Fazenda Teixeira",
    "gn:population":0,
    "gn:timezone":"Africa/Luanda",
    "iso:country":"AO",
    "name:und_x_variant":[
        "Fazenda Aurora",
        "Fazenda Teixeira"
    ],
    "wof:name":"Fazenda Teixeira",
    "wof:placetype":"locality"
},
  "geometry": {"coordinates":[15.83333,-9.41667],"type":"Point"}
}