{
  "type": "Feature",
  "properties": {
    "gn:admin1_code":"9.0",
    "gn:asciiname":"Muhindi",
    "gn:country_code":"AO",
    "gn:dem":1345,
    "gn:feature_class":"P",
    "gn:feature_code":"PPL",
    "gn:name":"Muhindi",
    "gn:population":0,
    "gn:timezone":"Africa/Luanda",
    "iso:country":"AO",
    "wof:name":"Muhindi",
    "wof:placetype":"locality"
},
  "geometry": {"coordinates":[14.35191,-14.63451],"type":"Point"}
}