{
  "type": "Feature",
  "properties": {
    "gn:admin1_code":"6.0",
    "gn:asciiname":"Quilulo",
    "gn:country_code":"AO",
    "gn:dem":1489,
    "gn:feature_class":"P",
    "gn:feature_code":"PPLL",
    "gn:name":"Quilulo",
    "gn:population":0,
    "gn:timezone":"Africa/Luanda",
    "iso:country":"AO",
    "wof:name":"Quilulo",
    "wof:placetype":"locality"
},
  "geometry": {"coordinates":[14.64665,-11.01316],"type":"Point"}
}