{
  "type": "Feature",
  "properties": {
    "gn:admin1_code":"15.0",
    "gn:asciiname":"Quibenga Suca",
    "gn:country_code":"AO",
    "gn:dem":966,
    "gn:feature_class":"P",
    "gn:feature_code":"PPL",
    "gn:name":"Quibenga Suca",
    "gn:population":0,
    "gn:timezone":"Africa/Luanda",
    "iso:country":"AO",
    "wof:name":"Quibenga Suca",
    "wof:placetype":"locality"
},
  "geometry": {"coordinates":[15.85537,-6.7076],"type":"Point"}
}