{
  "type": "Feature",
  "properties": {
    "gn:admin1_code":"6.0",
    "gn:asciiname":"Cauaca",
    "gn:country_code":"AO",
    "gn:dem":1355,
    "gn:feature_class":"P",
    "gn:feature_code":"PPL",
    "gn:name":"Cauaca",
    "gn:population":0,
    "gn:timezone":"Africa/Luanda",
    "iso:country":"AO",
    "wof:name":"Cauaca",
    "wof:placetype":"locality"
},
  "geometry": {"coordinates":[15.06742,-11.38607],"type":"Point"}
}