{
  "type": "Feature",
  "properties": {
    "gn:admin1_code":"15.0",
    "gn:asciiname":"Quilumbo",
    "gn:country_code":"AO",
    "gn:dem":837,
    "gn:feature_class":"P",
    "gn:feature_code":"PPL",
    "gn:name":"Quilumbo",
    "gn:population":0,
    "gn:timezone":"Africa/Luanda",
    "iso:country":"AO",
    "name:und_x_variant":[
        "Quibumbo",
        "Quilumbo"
    ],
    "wof:name":"Quilumbo",
    "wof:placetype":"locality"
},
  "geometry": {"coordinates":[15.39923,-6.14395],"type":"Point"}
}