{
  "type": "Feature",
  "properties": {
    "gn:admin1_code":"18.0",
    "gn:asciiname":"Cupuepua",
    "gn:country_code":"AO",
    "gn:dem":1093,
    "gn:feature_class":"P",
    "gn:feature_code":"PPL",
    "gn:name":"Cupu\u00e9pua",
    "gn:population":0,
    "gn:timezone":"Africa/Luanda",
    "iso:country":"AO",
    "wof:name":"Cupuepua",
    "wof:placetype":"locality"
},
  "geometry": {"coordinates":[20.5332,-9.85286],"type":"Point"}
}