{
  "type": "Feature",
  "properties": {
    "gn:admin1_code":"6.0",
    "gn:asciiname":"Genga",
    "gn:country_code":"AO",
    "gn:dem":1072,
    "gn:feature_class":"P",
    "gn:feature_code":"PPL",
    "gn:name":"Genga",
    "gn:population":0,
    "gn:timezone":"Africa/Luanda",
    "iso:country":"AO",
    "name:ceb_x_preferred":[
        "Genga"
    ],
    "name:deu_x_preferred":[
        "Genga"
    ],
    "name:fra_x_preferred":[
        "Genga"
    ],
    "name:swe_x_preferred":[
        "Genga"
    ],
    "wof:name":"Genga",
    "wof:placetype":"locality"
},
  "geometry": {"coordinates":[14.59124,-11.14571],"type":"Point"}
}