{
  "type": "Feature",
  "properties": {
    "gn:admin1_code":"6.0",
    "gn:asciiname":"Santo",
    "gn:country_code":"AO",
    "gn:dem":1653,
    "gn:feature_class":"P",
    "gn:feature_code":"PPL",
    "gn:name":"Santo",
    "gn:population":0,
    "gn:timezone":"Africa/Luanda",
    "iso:country":"AO",
    "name:ceb_x_preferred":[
        "Santo"
    ],
    "name:deu_x_preferred":[
        "Santo"
    ],
    "name:epo_x_preferred":[
        "Santo"
    ],
    "name:fra_x_preferred":[
        "Santo"
    ],
    "name:ita_x_preferred":[
        "Santo"
    ],
    "name:nld_x_preferred":[
        "Santo"
    ],
    "name:por_x_preferred":[
        "Santo"
    ],
    "name:spa_x_preferred":[
        "Santo"
    ],
    "name:srp_x_preferred":[
        "Santo"
    ],
    "name:swe_x_preferred":[
        "Santo"
    ],
    "wof:name":"Santo",
    "wof:placetype":"locality"
},
  "geometry": {"coordinates":[15.03333,-12.05],"type":"Point"}
}