{
  "type": "Feature",
  "properties": {
    "gn:admin1_code":"5.0",
    "gn:asciiname":"Fazenda Boa Esperanca",
    "gn:cc2":"AO",
    "gn:country_code":"AO",
    "gn:dem":27,
    "gn:feature_class":"P",
    "gn:feature_code":"PPL",
    "gn:name":"Fazenda Boa Esperan\u00e7a",
    "gn:population":0,
    "gn:timezone":"Africa/Luanda",
    "iso:country":"AO",
    "name:und_x_variant":[
        "Fazenda Esperan\u00e7a",
        "Fazenda Boa Esperan\u00e7a"
    ],
    "wof:name":"Fazenda Boa Esperanca",
    "wof:placetype":"locality"
},
  "geometry": {"coordinates":[14.33333,-9.53333],"type":"Point"}
}