{
  "type": "Feature",
  "properties": {
    "gn:admin1_code":"8.0",
    "gn:asciiname":"Sacaiamba",
    "gn:country_code":"AO",
    "gn:dem":1670,
    "gn:feature_class":"P",
    "gn:feature_code":"PPL",
    "gn:name":"Sacaiamba",
    "gn:population":0,
    "gn:timezone":"Africa/Luanda",
    "iso:country":"AO",
    "wof:name":"Sacaiamba",
    "wof:placetype":"locality"
},
  "geometry": {"coordinates":[15.60722,-13.24222],"type":"Point"}
}