{
  "type": "Feature",
  "properties": {
    "gn:admin1_code":"6.0",
    "gn:asciiname":"Quissacra",
    "gn:country_code":"AO",
    "gn:dem":993,
    "gn:feature_class":"P",
    "gn:feature_code":"PPL",
    "gn:name":"Quissacra",
    "gn:population":0,
    "gn:timezone":"Africa/Luanda",
    "iso:country":"AO",
    "wof:name":"Quissacra",
    "wof:placetype":"locality"
},
  "geometry": {"coordinates":[14.3572,-10.81044],"type":"Point"}
}