{
  "type": "Feature",
  "properties": {
    "gn:admin1_code":"4.0",
    "gn:asciiname":"Mahunizi",
    "gn:cc2":"AO",
    "gn:country_code":"AO",
    "gn:dem":997,
    "gn:feature_class":"P",
    "gn:feature_code":"PPL",
    "gn:name":"Mahunizi",
    "gn:population":0,
    "gn:timezone":"Africa/Luanda",
    "iso:country":"AO",
    "name:und_x_variant":[
        "Mahuntsi",
        "Mahunizi"
    ],
    "wof:name":"Mahunizi",
    "wof:placetype":"locality"
},
  "geometry": {"coordinates":[22.78333,-17.25],"type":"Point"}
}