{
  "type": "Feature",
  "properties": {
    "gn:admin1_code":"5.0",
    "gn:asciiname":"Quixingango",
    "gn:country_code":"AO",
    "gn:dem":22,
    "gn:feature_class":"P",
    "gn:feature_code":"PPL",
    "gn:name":"Quixingango",
    "gn:population":0,
    "gn:timezone":"Africa/Luanda",
    "iso:country":"AO",
    "name:und_x_variant":[
        "Quicingango",
        "Quixingango",
        "Caxingango"
    ],
    "wof:name":"Quixingango",
    "wof:placetype":"locality"
},
  "geometry": {"coordinates":[14.28804,-9.67594],"type":"Point"}
}