{
  "type": "Feature",
  "properties": {
    "gn:admin1_code":"15.0",
    "gn:asciiname":"Zonge",
    "gn:country_code":"AO",
    "gn:dem":605,
    "gn:feature_class":"P",
    "gn:feature_code":"PPL",
    "gn:name":"Zonge",
    "gn:population":0,
    "gn:timezone":"Africa/Luanda",
    "iso:country":"AO",
    "wof:name":"Zonge",
    "wof:placetype":"locality"
},
  "geometry": {"coordinates":[15.92535,-6.00572],"type":"Point"}
}