{
  "type": "Feature",
  "properties": {
    "gn:admin1_code":"5.0",
    "gn:asciiname":"Terra Nova",
    "gn:country_code":"AO",
    "gn:dem":1030,
    "gn:feature_class":"P",
    "gn:feature_code":"PPL",
    "gn:name":"Terra Nova",
    "gn:population":0,
    "gn:timezone":"Africa/Luanda",
    "iso:country":"AO",
    "wof:name":"Terra Nova",
    "wof:placetype":"locality"
},
  "geometry": {"coordinates":[15.52716,-9.05208],"type":"Point"}
}