{
  "type": "Feature",
  "properties": {
    "gn:admin1_code":"5.0",
    "gn:asciiname":"Terra Nova",
    "gn:country_code":"AO",
    "gn:dem":1030,
    "gn:feature_class":"P",
    "gn:feature_code":"PPL",
    "gn:name":"Terra Nova",
    "gn:population":0,
    "gn:timezone":"Africa/Luanda",
    "iso:country":"AO",
    "name:bul_x_preferred":[
        "\u0422\u0435\u0440\u0430 \u041d\u043e\u0432\u0430"
    ],
    "name:ceb_x_preferred":[
        "Terra Nova"
    ],
    "name:ces_x_preferred":[
        "Terra Nova"
    ],
    "name:deu_x_preferred":[
        "Terra Nova"
    ],
    "name:fin_x_preferred":[
        "Terra Nova"
    ],
    "name:fra_x_preferred":[
        "Terra Nova"
    ],
    "name:heb_x_preferred":[
        "\u05d8\u05e8\u05d4 \u05e0\u05d5\u05d1\u05d4"
    ],
    "name:hun_x_preferred":[
        "Terra Nova"
    ],
    "name:jpn_x_preferred":[
        "\u30c6\u30e9\u30fb\u30ce\u30f4\u30a1"
    ],
    "name:kat_x_preferred":[
        "\u10e2\u10d4\u10e0\u10d0-\u10dc\u10dd\u10d5\u10d0"
    ],
    "name:kor_x_preferred":[
        "\ud14c\ub77c \ub178\ubc14"
    ],
    "name:lat_x_preferred":[
        "Terra Nova"
    ],
    "name:lit_x_preferred":[
        "Terra Nova"
    ],
    "name:nld_x_preferred":[
        "Terra Nova"
    ],
    "name:nor_x_preferred":[
        "Terra Nova"
    ],
    "name:pol_x_preferred":[
        "Terra Nova"
    ],
    "name:por_x_preferred":[
        "Terra Nova"
    ],
    "name:ron_x_preferred":[
        "Terra Nova"
    ],
    "name:rus_x_preferred":[
        "\u0422\u0435\u0440\u0440\u0430 \u041d\u043e\u0432\u0430"
    ],
    "name:slk_x_preferred":[
        "Terra Nova"
    ],
    "name:srp_x_preferred":[
        "\u0422\u0435\u0440\u0430 \u043d\u043e\u0432\u0430"
    ],
    "name:swe_x_preferred":[
        "Terra Nova"
    ],
    "name:ukr_x_preferred":[
        "\u0422\u0435\u0440\u0440\u0430 \u041d\u043e\u0432\u0430"
    ],
    "name:vol_x_preferred":[
        "Terra Nova"
    ],
    "wof:name":"Terra Nova",
    "wof:placetype":"locality"
},
  "geometry": {"coordinates":[15.52716,-9.05208],"type":"Point"}
}