{
  "type": "Feature",
  "properties": {
    "gn:admin1_code":"7.0",
    "gn:asciiname":"Mulamba",
    "gn:country_code":"AO",
    "gn:dem":1122,
    "gn:feature_class":"P",
    "gn:feature_code":"PPL",
    "gn:name":"Mulamba",
    "gn:population":0,
    "gn:timezone":"Africa/Luanda",
    "iso:country":"AO",
    "wof:name":"Mulamba",
    "wof:placetype":"locality"
},
  "geometry": {"coordinates":[14.65,-17.08333],"type":"Point"}
}