{
  "type": "Feature",
  "properties": {
    "gn:admin1_code":"15.0",
    "gn:asciiname":"Quivala",
    "gn:country_code":"AO",
    "gn:dem":920,
    "gn:feature_class":"P",
    "gn:feature_code":"PPL",
    "gn:name":"Quivala",
    "gn:population":0,
    "gn:timezone":"Africa/Luanda",
    "iso:country":"AO",
    "wof:name":"Quivala",
    "wof:placetype":"locality"
},
  "geometry": {"coordinates":[15.15039,-6.01892],"type":"Point"}
}