{
  "type": "Feature",
  "properties": {
    "gn:admin1_code":"15.0",
    "gn:asciiname":"Quisseque",
    "gn:cc2":"AO",
    "gn:country_code":"AO",
    "gn:dem":1189,
    "gn:feature_class":"P",
    "gn:feature_code":"PPL",
    "gn:name":"Quisseque",
    "gn:population":0,
    "gn:timezone":"Africa/Luanda",
    "iso:country":"AO",
    "name:und_x_variant":[
        "Dende",
        "Quisseque"
    ],
    "wof:name":"Quisseque",
    "wof:placetype":"locality"
},
  "geometry": {"coordinates":[15.21667,-7.88333],"type":"Point"}
}