{
  "type": "Feature",
  "properties": {
    "gn:admin1_code":"18.0",
    "gn:asciiname":"Samaca",
    "gn:country_code":"AO",
    "gn:dem":1029,
    "gn:feature_class":"P",
    "gn:feature_code":"PPL",
    "gn:name":"Samaca",
    "gn:population":0,
    "gn:timezone":"Africa/Luanda",
    "iso:country":"AO",
    "wof:name":"Samaca",
    "wof:placetype":"locality"
},
  "geometry": {"coordinates":[20.85,-9.16667],"type":"Point"}
}