{
  "type": "Feature",
  "properties": {
    "gn:admin1_code":"8.0",
    "gn:asciiname":"Cahenda",
    "gn:cc2":"AO",
    "gn:country_code":"AO",
    "gn:dem":1575,
    "gn:feature_class":"P",
    "gn:feature_code":"PPL",
    "gn:name":"Cahenda",
    "gn:population":0,
    "gn:timezone":"Africa/Luanda",
    "iso:country":"AO",
    "name:und_x_variant":[
        "Caenda",
        "Caonda",
        "Cahenda"
    ],
    "wof:name":"Cahenda",
    "wof:placetype":"locality"
},
  "geometry": {"coordinates":[15.57639,-12.57278],"type":"Point"}
}