{
  "type": "Feature",
  "properties": {
    "gn:admin1_code":"15.0",
    "gn:asciiname":"Quimbeia",
    "gn:country_code":"AO",
    "gn:dem":1233,
    "gn:feature_class":"P",
    "gn:feature_code":"PPL",
    "gn:name":"Quimbeia",
    "gn:population":0,
    "gn:timezone":"Africa/Luanda",
    "iso:country":"AO",
    "wof:name":"Quimbeia",
    "wof:placetype":"locality"
},
  "geometry": {"coordinates":[15.66578,-7.89375],"type":"Point"}
}