{
  "type": "Feature",
  "properties": {
    "gn:admin1_code":"15.0",
    "gn:asciiname":"Condo",
    "gn:country_code":"AO",
    "gn:dem":1212,
    "gn:feature_class":"P",
    "gn:feature_code":"PPL",
    "gn:name":"Condo",
    "gn:population":0,
    "gn:timezone":"Africa/Luanda",
    "iso:country":"AO",
    "wof:name":"Condo",
    "wof:placetype":"locality"
},
  "geometry": {"coordinates":[15.16667,-7.18333],"type":"Point"}
}