{
  "type": "Feature",
  "properties": {
    "gn:admin1_code":"4.0",
    "gn:asciiname":"Macobita",
    "gn:cc2":"AO",
    "gn:country_code":"AO",
    "gn:dem":1411,
    "gn:feature_class":"P",
    "gn:feature_code":"PPL",
    "gn:name":"Macobita",
    "gn:population":0,
    "gn:timezone":"Africa/Luanda",
    "iso:country":"AO",
    "name:und_x_variant":[
        "Mocoboto",
        "Macobita"
    ],
    "wof:name":"Macobita",
    "wof:placetype":"locality"
},
  "geometry": {"coordinates":[17.95,-14.98333],"type":"Point"}
}