{
  "type": "Feature",
  "properties": {
    "gn:admin1_code":"19.0",
    "gn:asciiname":"Tereza Afonso",
    "gn:country_code":"AO",
    "gn:dem":291,
    "gn:feature_class":"P",
    "gn:feature_code":"PPL",
    "gn:name":"Tereza Afonso",
    "gn:population":0,
    "gn:timezone":"Africa/Luanda",
    "iso:country":"AO",
    "wof:name":"Tereza Afonso",
    "wof:placetype":"locality"
},
  "geometry": {"coordinates":[14.22043,-8.62109],"type":"Point"}
}