{
  "type": "Feature",
  "properties": {
    "gn:admin1_code":"6.0",
    "gn:asciiname":"Gando",
    "gn:country_code":"AO",
    "gn:dem":1382,
    "gn:feature_class":"P",
    "gn:feature_code":"PPL",
    "gn:name":"Gando",
    "gn:population":0,
    "gn:timezone":"Africa/Luanda",
    "iso:country":"AO",
    "name:ceb_x_preferred":[
        "Gando"
    ],
    "name:deu_x_preferred":[
        "Gando"
    ],
    "name:fra_x_preferred":[
        "Gando"
    ],
    "name:srp_x_preferred":[
        "\u0413\u0430\u043d\u0434\u043e"
    ],
    "name:swe_x_preferred":[
        "Gando"
    ],
    "wof:name":"Gando",
    "wof:placetype":"locality"
},
  "geometry": {"coordinates":[15.26667,-11.46667],"type":"Point"}
}