{
  "type": "Feature",
  "properties": {
    "gn:admin1_code":"15.0",
    "gn:asciiname":"Culo",
    "gn:country_code":"AO",
    "gn:dem":1254,
    "gn:feature_class":"P",
    "gn:feature_code":"PPL",
    "gn:name":"Culo",
    "gn:population":0,
    "gn:timezone":"Africa/Luanda",
    "iso:country":"AO",
    "name:ceb_x_preferred":[
        "Culo"
    ],
    "name:fas_x_preferred":[
        "\u06a9\u0648\u0644\u0648"
    ],
    "name:spa_x_preferred":[
        "Culo"
    ],
    "name:swe_x_preferred":[
        "Culo"
    ],
    "wof:name":"Culo",
    "wof:placetype":"locality"
},
  "geometry": {"coordinates":[15.2187,-7.69523],"type":"Point"}
}