{
  "type": "Feature",
  "properties": {
    "gn:admin1_code":"9.0",
    "gn:asciiname":"Tchipito",
    "gn:country_code":"AO",
    "gn:dem":1268,
    "gn:feature_class":"P",
    "gn:feature_code":"PPL",
    "gn:name":"Tchipito",
    "gn:population":0,
    "gn:timezone":"Africa/Luanda",
    "iso:country":"AO",
    "wof:name":"Tchipito",
    "wof:placetype":"locality"
},
  "geometry": {"coordinates":[15.5927,-14.89511],"type":"Point"}
}