{
  "type": "Feature",
  "properties": {
    "gn:admin1_code":"12.0",
    "gn:asciiname":"Munheba",
    "gn:country_code":"AO",
    "gn:dem":1120,
    "gn:feature_class":"P",
    "gn:feature_code":"PPL",
    "gn:name":"Munheba",
    "gn:population":0,
    "gn:timezone":"Africa/Luanda",
    "iso:country":"AO",
    "wof:name":"Munheba",
    "wof:placetype":"locality"
},
  "geometry": {"coordinates":[17.58063,-10.14258],"type":"Point"}
}