{
  "type": "Feature",
  "properties": {
    "gn:admin1_code":"6.0",
    "gn:asciiname":"Maria Augusta",
    "gn:country_code":"AO",
    "gn:dem":849,
    "gn:feature_class":"P",
    "gn:feature_code":"PPL",
    "gn:name":"Maria Augusta",
    "gn:population":0,
    "gn:timezone":"Africa/Luanda",
    "iso:country":"AO",
    "wof:name":"Maria Augusta",
    "wof:placetype":"locality"
},
  "geometry": {"coordinates":[14.34927,-10.92524],"type":"Point"}
}