{
  "type": "Feature",
  "properties": {
    "gn:admin1_code":"18.0",
    "gn:asciiname":"Luege",
    "gn:country_code":"AO",
    "gn:dem":1246,
    "gn:feature_class":"P",
    "gn:feature_code":"PPL",
    "gn:name":"Luege",
    "gn:population":0,
    "gn:timezone":"Africa/Luanda",
    "iso:country":"AO",
    "wof:name":"Luege",
    "wof:placetype":"locality"
},
  "geometry": {"coordinates":[20.15975,-10.99583],"type":"Point"}
}