{
  "type": "Feature",
  "properties": {
    "gn:admin1_code":"17.0",
    "gn:asciiname":"Canguindo",
    "gn:country_code":"AO",
    "gn:dem":1117,
    "gn:feature_class":"P",
    "gn:feature_code":"PPL",
    "gn:name":"Canguindo",
    "gn:population":0,
    "gn:timezone":"Africa/Luanda",
    "iso:country":"AO",
    "wof:name":"Canguindo",
    "wof:placetype":"locality"
},
  "geometry": {"coordinates":[19.43333,-8.66667],"type":"Point"}
}