{
  "type": "Feature",
  "properties": {
    "gn:admin1_code":"16.0",
    "gn:asciiname":"Quincandiua",
    "gn:country_code":"AO",
    "gn:dem":43,
    "gn:feature_class":"P",
    "gn:feature_code":"PPL",
    "gn:name":"Quincandiua",
    "gn:population":0,
    "gn:timezone":"Africa/Luanda",
    "iso:country":"AO",
    "wof:name":"Quincandiua",
    "wof:placetype":"locality"
},
  "geometry": {"coordinates":[12.78485,-6.89391],"type":"Point"}
}