{
  "type": "Feature",
  "properties": {
    "gn:admin1_code":"0.0",
    "gn:asciiname":"Eua",
    "gn:country_code":"AO",
    "gn:dem":37,
    "gn:feature_class":"P",
    "gn:feature_code":"PPL",
    "gn:name":"Eua",
    "gn:population":0,
    "gn:timezone":"Africa/Luanda",
    "iso:country":"AO",
    "wof:name":"Eua",
    "wof:placetype":"locality"
},
  "geometry": {"coordinates":[13.09194,-12.91389],"type":"Point"}
}