{
  "type": "Feature",
  "properties": {
    "gn:admin1_code":"14.0",
    "gn:asciiname":"Caluto",
    "gn:country_code":"AO",
    "gn:dem":1106,
    "gn:feature_class":"P",
    "gn:feature_code":"PPL",
    "gn:name":"Caluto",
    "gn:population":0,
    "gn:timezone":"Africa/Luanda",
    "iso:country":"AO",
    "wof:name":"Caluto",
    "wof:placetype":"locality"
},
  "geometry": {"coordinates":[22.95,-12.25],"type":"Point"}
}