{
  "type": "Feature",
  "properties": {
    "gn:admin1_code":"6.0",
    "gn:asciiname":"Meme",
    "gn:country_code":"AO",
    "gn:dem":1045,
    "gn:feature_class":"P",
    "gn:feature_code":"PPL",
    "gn:name":"Meme",
    "gn:population":0,
    "gn:timezone":"Africa/Luanda",
    "iso:country":"AO",
    "wof:name":"Meme",
    "wof:placetype":"locality"
},
  "geometry": {"coordinates":[14.39786,-11.3087],"type":"Point"}
}