{
  "type": "Feature",
  "properties": {
    "gn:admin1_code":"18.0",
    "gn:asciiname":"Sangongo",
    "gn:country_code":"AO",
    "gn:dem":1103,
    "gn:feature_class":"P",
    "gn:feature_code":"PPL",
    "gn:name":"Sangongo",
    "gn:population":0,
    "gn:timezone":"Africa/Luanda",
    "iso:country":"AO",
    "name:und_x_variant":[
        "Saluano"
    ],
    "wof:name":"Sangongo",
    "wof:placetype":"locality"
},
  "geometry": {"coordinates":[20.49646,-9.97892],"type":"Point"}
}