{
  "type": "Feature",
  "properties": {
    "gn:admin1_code":"2.0",
    "gn:asciiname":"Tchimbuelengue",
    "gn:country_code":"AO",
    "gn:dem":1762,
    "gn:feature_class":"P",
    "gn:feature_code":"PPL",
    "gn:name":"Tchimbuelengue",
    "gn:population":0,
    "gn:timezone":"Africa/Luanda",
    "iso:country":"AO",
    "wof:name":"Tchimbuelengue",
    "wof:placetype":"locality"
},
  "geometry": {"coordinates":[16.49301,-12.45777],"type":"Point"}
}