{
  "type": "Feature",
  "properties": {
    "gn:admin1_code":"2.0",
    "gn:asciiname":"Iaonga",
    "gn:cc2":"AO",
    "gn:country_code":"AO",
    "gn:dem":1475,
    "gn:feature_class":"P",
    "gn:feature_code":"PPL",
    "gn:name":"Iaonga",
    "gn:population":0,
    "gn:timezone":"Africa/Luanda",
    "iso:country":"AO",
    "name:und_x_variant":[
        "Mixa",
        "Iaonga"
    ],
    "wof:name":"Iaonga",
    "wof:placetype":"locality"
},
  "geometry": {"coordinates":[17.45,-14.03333],"type":"Point"}
}