{
  "type": "Feature",
  "properties": {
    "gn:admin1_code":"15.0",
    "gn:asciiname":"Lemba",
    "gn:country_code":"AO",
    "gn:dem":926,
    "gn:feature_class":"P",
    "gn:feature_code":"PPL",
    "gn:name":"Lemba",
    "gn:population":0,
    "gn:timezone":"Africa/Luanda",
    "iso:country":"AO",
    "wof:name":"Lemba",
    "wof:placetype":"locality"
},
  "geometry": {"coordinates":[15.27411,-6.46503],"type":"Point"}
}