{
  "type": "Feature",
  "properties": {
    "gn:admin1_code":"14.0",
    "gn:asciiname":"Tambo",
    "gn:country_code":"AO",
    "gn:dem":1234,
    "gn:feature_class":"P",
    "gn:feature_code":"PPL",
    "gn:name":"Tambo",
    "gn:population":0,
    "gn:timezone":"Africa/Luanda",
    "iso:country":"AO",
    "wof:name":"Tambo",
    "wof:placetype":"locality"
},
  "geometry": {"coordinates":[23.53472,-11.03007],"type":"Point"}
}