{
  "type": "Feature",
  "properties": {
    "gn:admin1_code":"14.0",
    "gn:asciiname":"Tambo",
    "gn:country_code":"AO",
    "gn:dem":1234,
    "gn:feature_class":"P",
    "gn:feature_code":"PPL",
    "gn:name":"Tambo",
    "gn:population":0,
    "gn:timezone":"Africa/Luanda",
    "iso:country":"AO",
    "name:ceb_x_preferred":[
        "Tambo"
    ],
    "name:deu_x_preferred":[
        "Tambo"
    ],
    "name:fra_x_preferred":[
        "Tambo"
    ],
    "name:hrv_x_preferred":[
        "Tambo"
    ],
    "name:nor_x_preferred":[
        "Tambo"
    ],
    "name:por_x_preferred":[
        "Tambo"
    ],
    "name:rus_x_preferred":[
        "\u0422\u0430\u043c\u0431\u043e"
    ],
    "name:spa_x_preferred":[
        "Tambo"
    ],
    "name:swe_x_preferred":[
        "Tambo"
    ],
    "wof:name":"Tambo",
    "wof:placetype":"locality"
},
  "geometry": {"coordinates":[23.53472,-11.03007],"type":"Point"}
}