{
  "type": "Feature",
  "properties": {
    "gn:admin1_code":"6.0",
    "gn:asciiname":"Gambula",
    "gn:country_code":"AO",
    "gn:dem":1158,
    "gn:feature_class":"P",
    "gn:feature_code":"PPL",
    "gn:name":"Gambula",
    "gn:population":0,
    "gn:timezone":"Africa/Luanda",
    "iso:country":"AO",
    "name:und_x_variant":[
        "Cambula"
    ],
    "wof:name":"Gambula",
    "wof:placetype":"locality"
},
  "geometry": {"coordinates":[14.75462,-10.7926],"type":"Point"}
}