{
  "type": "Feature",
  "properties": {
    "gn:admin1_code":"19.0",
    "gn:asciiname":"Cabianda",
    "gn:country_code":"AO",
    "gn:dem":22,
    "gn:feature_class":"P",
    "gn:feature_code":"PPL",
    "gn:name":"Cabianda",
    "gn:population":0,
    "gn:timezone":"Africa/Luanda",
    "iso:country":"AO",
    "name:und_x_variant":[
        "Cabiando",
        "Cabianda"
    ],
    "wof:name":"Cabianda",
    "wof:placetype":"locality"
},
  "geometry": {"coordinates":[13.62423,-10.23522],"type":"Point"}
}