{
  "type": "Feature",
  "properties": {
    "gn:admin1_code":"15.0",
    "gn:asciiname":"Hanga",
    "gn:country_code":"AO",
    "gn:dem":1262,
    "gn:feature_class":"P",
    "gn:feature_code":"PPL",
    "gn:name":"Hanga",
    "gn:population":0,
    "gn:timezone":"Africa/Luanda",
    "iso:country":"AO",
    "wof:name":"Hanga",
    "wof:placetype":"locality"
},
  "geometry": {"coordinates":[15.83843,-8.15136],"type":"Point"}
}