{
  "type": "Feature",
  "properties": {
    "gn:admin1_code":"15.0",
    "gn:asciiname":"Quifutila Sanza",
    "gn:country_code":"AO",
    "gn:dem":934,
    "gn:feature_class":"P",
    "gn:feature_code":"PPL",
    "gn:name":"Quifutila Sanza",
    "gn:population":0,
    "gn:timezone":"Africa/Luanda",
    "iso:country":"AO",
    "wof:name":"Quifutila Sanza",
    "wof:placetype":"locality"
},
  "geometry": {"coordinates":[16.01749,-7.29471],"type":"Point"}
}