{
  "type": "Feature",
  "properties": {
    "gn:admin1_code":"6.0",
    "gn:asciiname":"Zundo-Uba",
    "gn:country_code":"AO",
    "gn:dem":1328,
    "gn:feature_class":"P",
    "gn:feature_code":"PPL",
    "gn:name":"Zundo-Uba",
    "gn:population":0,
    "gn:timezone":"Africa/Luanda",
    "iso:country":"AO",
    "wof:name":"Zundo-Uba",
    "wof:placetype":"locality"
},
  "geometry": {"coordinates":[14.82369,-11.10497],"type":"Point"}
}