{
  "type": "Feature",
  "properties": {
    "gn:admin1_code":"12.0",
    "gn:asciiname":"Mjango",
    "gn:country_code":"AO",
    "gn:dem":739,
    "gn:feature_class":"P",
    "gn:feature_code":"PPL",
    "gn:name":"Mjango",
    "gn:population":0,
    "gn:timezone":"Africa/Luanda",
    "iso:country":"AO",
    "wof:name":"Mjango",
    "wof:placetype":"locality"
},
  "geometry": {"coordinates":[16.59682999999999,-8.38798],"type":"Point"}
}