{
  "type": "Feature",
  "properties": {
    "gn:admin1_code":"15.0",
    "gn:asciiname":"Quissosso",
    "gn:country_code":"AO",
    "gn:dem":1310,
    "gn:feature_class":"P",
    "gn:feature_code":"PPL",
    "gn:name":"Quissosso",
    "gn:population":0,
    "gn:timezone":"Africa/Luanda",
    "iso:country":"AO",
    "wof:name":"Quissosso",
    "wof:placetype":"locality"
},
  "geometry": {"coordinates":[15.10364,-7.3383],"type":"Point"}
}