{
  "type": "Feature",
  "properties": {
    "gn:admin1_code":"4.0",
    "gn:asciiname":"Chissanda",
    "gn:country_code":"AO",
    "gn:dem":1201,
    "gn:feature_class":"P",
    "gn:feature_code":"PPL",
    "gn:name":"Chissanda",
    "gn:population":0,
    "gn:timezone":"Africa/Luanda",
    "iso:country":"AO",
    "wof:name":"Chissanda",
    "wof:placetype":"locality"
},
  "geometry": {"coordinates":[19.26667,-15.05],"type":"Point"}
}