{
  "type": "Feature",
  "properties": {
    "gn:admin1_code":"12.0",
    "gn:asciiname":"Catuca",
    "gn:country_code":"AO",
    "gn:dem":1218,
    "gn:feature_class":"P",
    "gn:feature_code":"PPL",
    "gn:name":"Catuca",
    "gn:population":0,
    "gn:timezone":"Africa/Luanda",
    "iso:country":"AO",
    "wof:name":"Catuca",
    "wof:placetype":"locality"
},
  "geometry": {"coordinates":[16.21884,-8.42231],"type":"Point"}
}