{
  "type": "Feature",
  "properties": {
    "gn:admin1_code":"6.0",
    "gn:asciiname":"Quilometro Quarenta",
    "gn:country_code":"AO",
    "gn:dem":137,
    "gn:feature_class":"P",
    "gn:feature_code":"PPL",
    "gn:name":"Quil\u00f4metro Quarenta",
    "gn:population":0,
    "gn:timezone":"Africa/Luanda",
    "iso:country":"AO",
    "wof:name":"Quilometro Quarenta",
    "wof:placetype":"locality"
},
  "geometry": {"coordinates":[14.07651,-10.69399],"type":"Point"}
}