{
  "type": "Feature",
  "properties": {
    "gn:admin1_code":"8.0",
    "gn:asciiname":"Cassoco",
    "gn:country_code":"AO",
    "gn:dem":1818,
    "gn:feature_class":"P",
    "gn:feature_code":"PPL",
    "gn:name":"Cassoco",
    "gn:population":0,
    "gn:timezone":"Africa/Luanda",
    "iso:country":"AO",
    "wof:name":"Cassoco",
    "wof:placetype":"locality"
},
  "geometry": {"coordinates":[15.52361,-12.88167],"type":"Point"}
}