{
  "type": "Feature",
  "properties": {
    "gn:admin1_code":"8.0",
    "gn:asciiname":"Chimano",
    "gn:cc2":"AO",
    "gn:country_code":"AO",
    "gn:dem":1504,
    "gn:feature_class":"P",
    "gn:feature_code":"PPL",
    "gn:name":"Chimano",
    "gn:population":0,
    "gn:timezone":"Africa/Luanda",
    "iso:country":"AO",
    "name:und_x_variant":[
        "Tchimano",
        "Chimano"
    ],
    "wof:name":"Chimano",
    "wof:placetype":"locality"
},
  "geometry": {"coordinates":[15.96667,-12.35],"type":"Point"}
}