{
  "type": "Feature",
  "properties": {
    "gn:admin1_code":"12.0",
    "gn:asciiname":"Carima",
    "gn:country_code":"AO",
    "gn:dem":1099,
    "gn:feature_class":"P",
    "gn:feature_code":"PPL",
    "gn:name":"Carima",
    "gn:population":0,
    "gn:timezone":"Africa/Luanda",
    "iso:country":"AO",
    "wof:name":"Carima",
    "wof:placetype":"locality"
},
  "geometry": {"coordinates":[15.67713,-9.58531],"type":"Point"}
}