{
  "type": "Feature",
  "properties": {
    "gn:admin1_code":"17.0",
    "gn:asciiname":"Sanjimi",
    "gn:country_code":"AO",
    "gn:dem":840,
    "gn:feature_class":"P",
    "gn:feature_code":"PPL",
    "gn:name":"Sanjimi",
    "gn:population":0,
    "gn:timezone":"Africa/Luanda",
    "iso:country":"AO",
    "wof:name":"Sanjimi",
    "wof:placetype":"locality"
},
  "geometry": {"coordinates":[20.97404,-7.76763],"type":"Point"}
}