{
  "type": "Feature",
  "properties": {
    "gn:admin1_code":"17.0",
    "gn:asciiname":"Maludi",
    "gn:country_code":"AO",
    "gn:dem":812,
    "gn:feature_class":"P",
    "gn:feature_code":"PPL",
    "gn:name":"Maludi",
    "gn:population":0,
    "gn:timezone":"Africa/Luanda",
    "iso:country":"AO",
    "wof:name":"Maludi",
    "wof:placetype":"locality"
},
  "geometry": {"coordinates":[21.29846,-8.02561],"type":"Point"}
}