{
  "type": "Feature",
  "properties": {
    "gn:admin1_code":"8.0",
    "gn:asciiname":"Linha",
    "gn:cc2":"AO",
    "gn:country_code":"AO",
    "gn:dem":1530,
    "gn:feature_class":"P",
    "gn:feature_code":"PPL",
    "gn:name":"Linha",
    "gn:population":0,
    "gn:timezone":"Africa/Luanda",
    "iso:country":"AO",
    "name:und_x_variant":[
        "Pelinha",
        "Linha"
    ],
    "wof:name":"Linha",
    "wof:placetype":"locality"
},
  "geometry": {"coordinates":[15.21667,-12.06667],"type":"Point"}
}