{
  "type": "Feature",
  "properties": {
    "gn:admin1_code":"5.0",
    "gn:asciiname":"Quichina Mbamba",
    "gn:country_code":"AO",
    "gn:dem":1291,
    "gn:feature_class":"P",
    "gn:feature_code":"PPL",
    "gn:name":"Quichina Mbamba",
    "gn:population":0,
    "gn:timezone":"Africa/Luanda",
    "iso:country":"AO",
    "name:und_x_variant":[
        "Quixina",
        "Quichina Bamba",
        "Quichina Mbamba"
    ],
    "wof:name":"Quichina Mbamba",
    "wof:placetype":"locality"
},
  "geometry": {"coordinates":[15.65293,-8.74747],"type":"Point"}
}