{
  "type": "Feature",
  "properties": {
    "gn:admin1_code":"12.0",
    "gn:asciiname":"Quilanda",
    "gn:country_code":"AO",
    "gn:dem":1028,
    "gn:feature_class":"P",
    "gn:feature_code":"PPL",
    "gn:name":"Quilanda",
    "gn:population":0,
    "gn:timezone":"Africa/Luanda",
    "iso:country":"AO",
    "wof:name":"Quilanda",
    "wof:placetype":"locality"
},
  "geometry": {"coordinates":[15.89182,-9.5181],"type":"Point"}
}