{
  "type": "Feature",
  "properties": {
    "gn:admin1_code":"1.0",
    "gn:asciiname":"Luongo",
    "gn:country_code":"AO",
    "gn:dem":14,
    "gn:feature_class":"P",
    "gn:feature_code":"PPL",
    "gn:name":"Luongo",
    "gn:population":0,
    "gn:timezone":"Africa/Luanda",
    "iso:country":"AO",
    "name:und_x_variant":[
        "Luhongo"
    ],
    "wof:name":"Luongo",
    "wof:placetype":"locality"
},
  "geometry": {"coordinates":[13.5275,-12.45472],"type":"Point"}
}