{
  "type": "Feature",
  "properties": {
    "gn:admin1_code":"1.0",
    "gn:asciiname":"Sacana",
    "gn:country_code":"AO",
    "gn:dem":1397,
    "gn:feature_class":"P",
    "gn:feature_code":"PPL",
    "gn:name":"Sacana",
    "gn:population":0,
    "gn:timezone":"Africa/Luanda",
    "iso:country":"AO",
    "wof:name":"Sacana",
    "wof:placetype":"locality"
},
  "geometry": {"coordinates":[15.06667,-12.46667],"type":"Point"}
}