{
  "type": "Feature",
  "properties": {
    "gn:admin1_code":"12.0",
    "gn:asciiname":"Socola Segundo",
    "gn:country_code":"AO",
    "gn:dem":1156,
    "gn:feature_class":"P",
    "gn:feature_code":"PPL",
    "gn:name":"Socola Segundo",
    "gn:population":0,
    "gn:timezone":"Africa/Luanda",
    "iso:country":"AO",
    "wof:name":"Socola Segundo",
    "wof:placetype":"locality"
},
  "geometry": {"coordinates":[17.1027,-9.22413],"type":"Point"}
}