{
  "type": "Feature",
  "properties": {
    "gn:admin1_code":"19.0",
    "gn:asciiname":"Quiombe",
    "gn:country_code":"AO",
    "gn:dem":43,
    "gn:feature_class":"P",
    "gn:feature_code":"PPL",
    "gn:name":"Quiombe",
    "gn:population":0,
    "gn:timezone":"Africa/Luanda",
    "iso:country":"AO",
    "wof:name":"Quiombe",
    "wof:placetype":"locality"
},
  "geometry": {"coordinates":[13.21654,-8.04109],"type":"Point"}
}