{
  "type": "Feature",
  "properties": {
    "gn:admin1_code":"1.0",
    "gn:asciiname":"Moma",
    "gn:country_code":"AO",
    "gn:dem":1295,
    "gn:feature_class":"P",
    "gn:feature_code":"PPL",
    "gn:name":"Moma",
    "gn:population":0,
    "gn:timezone":"Africa/Luanda",
    "iso:country":"AO",
    "wof:name":"Moma",
    "wof:placetype":"locality"
},
  "geometry": {"coordinates":[14.79854,-12.1868],"type":"Point"}
}