{
  "type": "Feature",
  "properties": {
    "gn:admin1_code":"12.0",
    "gn:asciiname":"Cambumba",
    "gn:country_code":"AO",
    "gn:dem":1206,
    "gn:feature_class":"P",
    "gn:feature_code":"PPL",
    "gn:name":"Cambumba",
    "gn:population":0,
    "gn:timezone":"Africa/Luanda",
    "iso:country":"AO",
    "wof:name":"Cambumba",
    "wof:placetype":"locality"
},
  "geometry": {"coordinates":[17.99381,-10.98619],"type":"Point"}
}