{
  "type": "Feature",
  "properties": {
    "gn:admin1_code":"8.0",
    "gn:asciiname":"Tchinila",
    "gn:country_code":"AO",
    "gn:dem":1577,
    "gn:feature_class":"P",
    "gn:feature_code":"PPL",
    "gn:name":"Tchinila",
    "gn:population":0,
    "gn:timezone":"Africa/Luanda",
    "iso:country":"AO",
    "wof:name":"Tchinila",
    "wof:placetype":"locality"
},
  "geometry": {"coordinates":[15.38778,-12.88417],"type":"Point"}
}