{
  "type": "Feature",
  "properties": {
    "gn:admin1_code":"6.0",
    "gn:asciiname":"Capunga",
    "gn:country_code":"AO",
    "gn:dem":97,
    "gn:feature_class":"P",
    "gn:feature_code":"PPL",
    "gn:name":"Capunga",
    "gn:population":0,
    "gn:timezone":"Africa/Luanda",
    "iso:country":"AO",
    "wof:name":"Capunga",
    "wof:placetype":"locality"
},
  "geometry": {"coordinates":[13.91635,-11.003],"type":"Point"}
}