{
  "type": "Feature",
  "properties": {
    "gn:admin1_code":"12.0",
    "gn:asciiname":"Mundunde",
    "gn:country_code":"AO",
    "gn:dem":1120,
    "gn:feature_class":"P",
    "gn:feature_code":"PPL",
    "gn:name":"Mundunde",
    "gn:population":0,
    "gn:timezone":"Africa/Luanda",
    "iso:country":"AO",
    "wof:name":"Mundunde",
    "wof:placetype":"locality"
},
  "geometry": {"coordinates":[17.7482,-10.64801],"type":"Point"}
}