{
  "type": "Feature",
  "properties": {
    "gn:admin1_code":"15.0",
    "gn:asciiname":"Cangundo",
    "gn:country_code":"AO",
    "gn:dem":1093,
    "gn:feature_class":"P",
    "gn:feature_code":"PPL",
    "gn:name":"Cangundo",
    "gn:population":0,
    "gn:timezone":"Africa/Luanda",
    "iso:country":"AO",
    "name:und_x_variant":[
        "Cancundo",
        "Cangundo"
    ],
    "wof:name":"Cangundo",
    "wof:placetype":"locality"
},
  "geometry": {"coordinates":[15.22447,-7.77386],"type":"Point"}
}