{
  "type": "Feature",
  "properties": {
    "gn:admin1_code":"5.0",
    "gn:asciiname":"Quinguenga",
    "gn:country_code":"AO",
    "gn:dem":982,
    "gn:feature_class":"P",
    "gn:feature_code":"PPL",
    "gn:name":"Quinguenga",
    "gn:population":0,
    "gn:timezone":"Africa/Luanda",
    "iso:country":"AO",
    "wof:name":"Quinguenga",
    "wof:placetype":"locality"
},
  "geometry": {"coordinates":[15.35951,-8.95367],"type":"Point"}
}