{
  "type": "Feature",
  "properties": {
    "gn:admin1_code":"6.0",
    "gn:asciiname":"Catamba de Xariaia",
    "gn:country_code":"AO",
    "gn:dem":1095,
    "gn:feature_class":"P",
    "gn:feature_code":"PPL",
    "gn:name":"Catamba de Xariaia",
    "gn:population":0,
    "gn:timezone":"Africa/Luanda",
    "iso:country":"AO",
    "wof:name":"Catamba de Xariaia",
    "wof:placetype":"locality"
},
  "geometry": {"coordinates":[14.51358,-10.72427],"type":"Point"}
}