{
  "type": "Feature",
  "properties": {
    "gn:admin1_code":"9.0",
    "gn:asciiname":"Samucolo",
    "gn:country_code":"AO",
    "gn:dem":1470,
    "gn:feature_class":"P",
    "gn:feature_code":"PPL",
    "gn:name":"Samucolo",
    "gn:population":0,
    "gn:timezone":"Africa/Luanda",
    "iso:country":"AO",
    "wof:name":"Samucolo",
    "wof:placetype":"locality"
},
  "geometry": {"coordinates":[15.84901,-14.69014],"type":"Point"}
}