{
  "type": "Feature",
  "properties": {
    "gn:admin1_code":"12.0",
    "gn:asciiname":"Monzo",
    "gn:country_code":"AO",
    "gn:dem":1056,
    "gn:feature_class":"P",
    "gn:feature_code":"PPL",
    "gn:name":"Monzo",
    "gn:population":0,
    "gn:timezone":"Africa/Luanda",
    "iso:country":"AO",
    "wof:name":"Monzo",
    "wof:placetype":"locality"
},
  "geometry": {"coordinates":[15.9837,-9.3776],"type":"Point"}
}