{
  "type": "Feature",
  "properties": {
    "gn:admin1_code":"15.0",
    "gn:asciiname":"Paza",
    "gn:country_code":"AO",
    "gn:dem":499,
    "gn:feature_class":"P",
    "gn:feature_code":"PPL",
    "gn:name":"Paza",
    "gn:population":0,
    "gn:timezone":"Africa/Luanda",
    "iso:country":"AO",
    "wof:name":"Paza",
    "wof:placetype":"locality"
},
  "geometry": {"coordinates":[14.71667,-6.65],"type":"Point"}
}