{
  "type": "Feature",
  "properties": {
    "gn:admin1_code":"16.0",
    "gn:asciiname":"Ncossa Segundo",
    "gn:country_code":"AO",
    "gn:dem":279,
    "gn:feature_class":"P",
    "gn:feature_code":"PPL",
    "gn:name":"Ncossa Segundo",
    "gn:population":0,
    "gn:timezone":"Africa/Luanda",
    "iso:country":"AO",
    "wof:name":"Ncossa Segundo",
    "wof:placetype":"locality"
},
  "geometry": {"coordinates":[13.48492,-5.91479],"type":"Point"}
}