{
  "type": "Feature",
  "properties": {
    "gn:admin1_code":"6.0",
    "gn:asciiname":"Londa",
    "gn:country_code":"AO",
    "gn:dem":1648,
    "gn:feature_class":"P",
    "gn:feature_code":"PPLL",
    "gn:name":"Londa",
    "gn:population":0,
    "gn:timezone":"Africa/Luanda",
    "iso:country":"AO",
    "name:ceb_x_preferred":[
        "Londa"
    ],
    "name:deu_x_preferred":[
        "Londa"
    ],
    "name:nld_x_preferred":[
        "Londa"
    ],
    "name:swe_x_preferred":[
        "Londa"
    ],
    "wof:name":"Londa",
    "wof:placetype":"locality"
},
  "geometry": {"coordinates":[14.58243,-11.00841],"type":"Point"}
}