{
  "type": "Feature",
  "properties": {
    "gn:admin1_code":"17.0",
    "gn:asciiname":"Nascimento",
    "gn:country_code":"AO",
    "gn:dem":958,
    "gn:feature_class":"P",
    "gn:feature_code":"PPL",
    "gn:name":"Nascimento",
    "gn:population":0,
    "gn:timezone":"Africa/Luanda",
    "iso:country":"AO",
    "wof:name":"Nascimento",
    "wof:placetype":"locality"
},
  "geometry": {"coordinates":[20.56904,-8.46113],"type":"Point"}
}