{
  "type": "Feature",
  "properties": {
    "gn:admin1_code":"14.0",
    "gn:asciiname":"Samungole",
    "gn:cc2":"AO",
    "gn:country_code":"AO",
    "gn:dem":1066,
    "gn:feature_class":"P",
    "gn:feature_code":"PPL",
    "gn:name":"Samungole",
    "gn:population":0,
    "gn:timezone":"Africa/Luanda",
    "iso:country":"AO",
    "name:und_x_variant":[
        "Luangwli",
        "Luangole",
        "Samungole"
    ],
    "wof:name":"Samungole",
    "wof:placetype":"locality"
},
  "geometry": {"coordinates":[22.43333,-12.43333],"type":"Point"}
}