{
  "type": "Feature",
  "properties": {
    "gn:admin1_code":"8.0",
    "gn:asciiname":"Benfica",
    "gn:cc2":"AO",
    "gn:country_code":"AO",
    "gn:dem":1685,
    "gn:feature_class":"P",
    "gn:feature_code":"PPL",
    "gn:name":"Benfica",
    "gn:population":0,
    "gn:timezone":"Africa/Luanda",
    "iso:country":"AO",
    "name:und_x_variant":[
        "Bemfica",
        "Benfica"
    ],
    "wof:name":"Benfica",
    "wof:placetype":"locality"
},
  "geometry": {"coordinates":[15.81667,-12.88333],"type":"Point"}
}