{
  "type": "Feature",
  "properties": {
    "gn:admin1_code":"6.0",
    "gn:asciiname":"Viegas",
    "gn:country_code":"AO",
    "gn:dem":1299,
    "gn:feature_class":"P",
    "gn:feature_code":"PPL",
    "gn:name":"Viegas",
    "gn:population":0,
    "gn:timezone":"Africa/Luanda",
    "iso:country":"AO",
    "name:fra_x_preferred":[
        "Viegas"
    ],
    "wof:name":"Viegas",
    "wof:placetype":"locality"
},
  "geometry": {"coordinates":[14.86667,-11.13333],"type":"Point"}
}