{
  "type": "Feature",
  "properties": {
    "gn:admin1_code":"15.0",
    "gn:asciiname":"Aldeia",
    "gn:country_code":"AO",
    "gn:dem":1250,
    "gn:feature_class":"P",
    "gn:feature_code":"PPL",
    "gn:name":"Aldeia",
    "gn:population":0,
    "gn:timezone":"Africa/Luanda",
    "iso:country":"AO",
    "wof:name":"Aldeia",
    "wof:placetype":"locality"
},
  "geometry": {"coordinates":[15.27408,-7.77291],"type":"Point"}
}