{
  "type": "Feature",
  "properties": {
    "gn:admin1_code":"19.0",
    "gn:asciiname":"Quibua",
    "gn:country_code":"AO",
    "gn:dem":261,
    "gn:feature_class":"P",
    "gn:feature_code":"PPL",
    "gn:name":"Quibua",
    "gn:population":0,
    "gn:timezone":"Africa/Luanda",
    "iso:country":"AO",
    "wof:name":"Quibua",
    "wof:placetype":"locality"
},
  "geometry": {"coordinates":[14.18333,-8.66667],"type":"Point"}
}