{
  "type": "Feature",
  "properties": {
    "gn:admin1_code":"6.0",
    "gn:asciiname":"Mucongo",
    "gn:country_code":"AO",
    "gn:dem":100,
    "gn:feature_class":"P",
    "gn:feature_code":"PPL",
    "gn:name":"Mu\u00e7ongo",
    "gn:population":0,
    "gn:timezone":"Africa/Luanda",
    "iso:country":"AO",
    "wof:name":"Mucongo",
    "wof:placetype":"locality"
},
  "geometry": {"coordinates":[13.81051,-10.78296],"type":"Point"}
}