{
  "type": "Feature",
  "properties": {
    "gn:admin1_code":"15.0",
    "gn:asciiname":"Quinsenga",
    "gn:country_code":"AO",
    "gn:dem":604,
    "gn:feature_class":"P",
    "gn:feature_code":"PPL",
    "gn:name":"Quinsenga",
    "gn:population":0,
    "gn:timezone":"Africa/Luanda",
    "iso:country":"AO",
    "wof:name":"Quinsenga",
    "wof:placetype":"locality"
},
  "geometry": {"coordinates":[16.07689,-5.95029],"type":"Point"}
}