{
  "type": "Feature",
  "properties": {
    "gn:admin1_code":"12.0",
    "gn:asciiname":"Combo",
    "gn:cc2":"AO",
    "gn:country_code":"AO",
    "gn:dem":652,
    "gn:feature_class":"P",
    "gn:feature_code":"PPL",
    "gn:name":"Combo",
    "gn:population":0,
    "gn:timezone":"Africa/Luanda",
    "iso:country":"AO",
    "name:und_x_variant":[
        "Caingo",
        "Combo"
    ],
    "wof:name":"Combo",
    "wof:placetype":"locality"
},
  "geometry": {"coordinates":[17.11667000000001,-7.71667],"type":"Point"}
}