{
  "type": "Feature",
  "properties": {
    "gn:admin1_code":"15.0",
    "gn:asciiname":"Agostinho Neto",
    "gn:country_code":"AO",
    "gn:dem":1177,
    "gn:feature_class":"P",
    "gn:feature_code":"PPL",
    "gn:name":"Agostinho Neto",
    "gn:population":0,
    "gn:timezone":"Africa/Luanda",
    "iso:country":"AO",
    "wof:name":"Agostinho Neto",
    "wof:placetype":"locality"
},
  "geometry": {"coordinates":[15.36785,-7.31707],"type":"Point"}
}