{
  "type": "Feature",
  "properties": {
    "gn:admin1_code":"19.0",
    "gn:asciiname":"Gombe",
    "gn:country_code":"AO",
    "gn:dem":538,
    "gn:feature_class":"P",
    "gn:feature_code":"PPL",
    "gn:name":"Gombe",
    "gn:population":0,
    "gn:timezone":"Africa/Luanda",
    "iso:country":"AO",
    "wof:name":"Gombe",
    "wof:placetype":"locality"
},
  "geometry": {"coordinates":[14.20318,-8.0143],"type":"Point"}
}