{
  "type": "Feature",
  "properties": {
    "gn:admin1_code":"8.0",
    "gn:asciiname":"Catanda Primeiro",
    "gn:country_code":"AO",
    "gn:dem":1717,
    "gn:feature_class":"P",
    "gn:feature_code":"PPL",
    "gn:name":"Catanda Primeiro",
    "gn:population":0,
    "gn:timezone":"Africa/Luanda",
    "iso:country":"AO",
    "wof:name":"Catanda Primeiro",
    "wof:placetype":"locality"
},
  "geometry": {"coordinates":[15.40916,-12.27145],"type":"Point"}
}