{
  "type": "Feature",
  "properties": {
    "gn:admin1_code":"2.0",
    "gn:asciiname":"Mbanda",
    "gn:country_code":"AO",
    "gn:dem":1286,
    "gn:feature_class":"P",
    "gn:feature_code":"PPL",
    "gn:name":"Mbanda",
    "gn:population":0,
    "gn:timezone":"Africa/Luanda",
    "iso:country":"AO",
    "wof:name":"Mbanda",
    "wof:placetype":"locality"
},
  "geometry": {"coordinates":[17.45921,-11.59692],"type":"Point"}
}