{
  "type": "Feature",
  "properties": {
    "gn:admin1_code":"15.0",
    "gn:asciiname":"Quimbianda Primeiro",
    "gn:country_code":"AO",
    "gn:dem":1006,
    "gn:feature_class":"P",
    "gn:feature_code":"PPL",
    "gn:name":"Quimbianda Primeiro",
    "gn:population":0,
    "gn:timezone":"Africa/Luanda",
    "iso:country":"AO",
    "wof:name":"Quimbianda Primeiro",
    "wof:placetype":"locality"
},
  "geometry": {"coordinates":[15.87512,-6.75119],"type":"Point"}
}