{
  "type": "Feature",
  "properties": {
    "gn:admin1_code":"17.0",
    "gn:asciiname":"Camba Cassai",
    "gn:country_code":"AO",
    "gn:dem":1148,
    "gn:feature_class":"P",
    "gn:feature_code":"PPL",
    "gn:name":"Camba Cassai",
    "gn:population":0,
    "gn:timezone":"Africa/Luanda",
    "iso:country":"AO",
    "wof:name":"Camba Cassai",
    "wof:placetype":"locality"
},
  "geometry": {"coordinates":[19.15,-9.78333],"type":"Point"}
}