{
  "type": "Feature",
  "properties": {
    "gn:admin1_code":"17.0",
    "gn:asciiname":"Caquele",
    "gn:country_code":"AO",
    "gn:dem":1013,
    "gn:feature_class":"P",
    "gn:feature_code":"PPL",
    "gn:name":"Caquele",
    "gn:population":0,
    "gn:timezone":"Africa/Luanda",
    "iso:country":"AO",
    "name:und_x_variant":[
        "Salicuca"
    ],
    "wof:name":"Caquele",
    "wof:placetype":"locality"
},
  "geometry": {"coordinates":[20.58352,-8.94333],"type":"Point"}
}