{
  "type": "Feature",
  "properties": {
    "gn:admin1_code":"19.0",
    "gn:asciiname":"Calunga-Samba",
    "gn:cc2":"AO",
    "gn:country_code":"AO",
    "gn:dem":637,
    "gn:feature_class":"P",
    "gn:feature_code":"PPL",
    "gn:name":"Calunga-Samba",
    "gn:population":0,
    "gn:timezone":"Africa/Luanda",
    "iso:country":"AO",
    "name:und_x_variant":[
        "Golungo Samba",
        "Calunga-Samba"
    ],
    "wof:name":"Calunga-Samba",
    "wof:placetype":"locality"
},
  "geometry": {"coordinates":[14.53333,-8.08333],"type":"Point"}
}