{
  "type": "Feature",
  "properties": {
    "gn:admin1_code":"2.0",
    "gn:asciiname":"Quibanda",
    "gn:cc2":"AO",
    "gn:country_code":"AO",
    "gn:dem":1753,
    "gn:feature_class":"P",
    "gn:feature_code":"PPL",
    "gn:name":"Quibanda",
    "gn:population":0,
    "gn:timezone":"Africa/Luanda",
    "iso:country":"AO",
    "name:und_x_variant":[
        "Chibanda",
        "Quibanda"
    ],
    "wof:name":"Quibanda",
    "wof:placetype":"locality"
},
  "geometry": {"coordinates":[16.75,-12.15],"type":"Point"}
}