{
  "type": "Feature",
  "properties": {
    "gn:admin1_code":"2.0",
    "gn:asciiname":"Munhango",
    "gn:cc2":"AO",
    "gn:country_code":"AO",
    "gn:dem":1419,
    "gn:feature_class":"P",
    "gn:feature_code":"PPL",
    "gn:name":"Munhango",
    "gn:population":0,
    "gn:timezone":"Africa/Luanda",
    "iso:country":"AO",
    "name:deu_x_preferred":[
        "Munhango"
    ],
    "name:por_x_preferred":[
        "Munhango"
    ],
    "name:ron_x_preferred":[
        "Munhango"
    ],
    "name:rus_x_preferred":[
        "\u041c\u0443\u043d\u0430\u043d\u0433\u043e"
    ],
    "name:rus_x_variant":[
        "\u041c\u0443\u043d\u044c\u044f\u043d\u0433\u043e"
    ],
    "name:und_x_variant":[
        "Mualango",
        "Munjango",
        "Munhongo",
        "Munyango"
    ],
    "wof:name":"Munhango",
    "wof:placetype":"locality"
},
  "geometry": {"coordinates":[18.55,-12.16667],"type":"Point"}
}