{
  "type": "Feature",
  "properties": {
    "gn:admin1_code":"17.0",
    "gn:asciiname":"Cow-Boy",
    "gn:country_code":"AO",
    "gn:dem":989,
    "gn:feature_class":"P",
    "gn:feature_code":"PPL",
    "gn:name":"Cow-Boy",
    "gn:population":0,
    "gn:timezone":"Africa/Luanda",
    "iso:country":"AO",
    "wof:name":"Cow-Boy",
    "wof:placetype":"locality"
},
  "geometry": {"coordinates":[17.82251,-9.51472],"type":"Point"}
}