{
  "type": "Feature",
  "properties": {
    "gn:admin1_code":"7.0",
    "gn:asciiname":"Melunga",
    "gn:cc2":"AO",
    "gn:country_code":"AO",
    "gn:dem":1128,
    "gn:feature_class":"P",
    "gn:feature_code":"PPL",
    "gn:name":"Melunga",
    "gn:population":0,
    "gn:timezone":"Africa/Luanda",
    "iso:country":"AO",
    "name:und_x_variant":[
        "Melunda",
        "Melunga"
    ],
    "wof:name":"Melunga",
    "wof:placetype":"locality"
},
  "geometry": {"coordinates":[16.43333,-17.28333],"type":"Point"}
}