{
  "type": "Feature",
  "properties": {
    "gn:admin1_code":"8.0",
    "gn:asciiname":"Casseque",
    "gn:cc2":"AO",
    "gn:country_code":"AO",
    "gn:dem":1430,
    "gn:feature_class":"P",
    "gn:feature_code":"PPL",
    "gn:name":"Casseque",
    "gn:population":0,
    "gn:timezone":"Africa/Luanda",
    "iso:country":"AO",
    "name:und_x_variant":[
        "Gasseque",
        "Casseque"
    ],
    "wof:name":"Casseque",
    "wof:placetype":"locality"
},
  "geometry": {"coordinates":[14.91667,-12.66667],"type":"Point"}
}