{
  "type": "Feature",
  "properties": {
    "gn:admin1_code":"2.0",
    "gn:asciiname":"Muceque",
    "gn:country_code":"AO",
    "gn:dem":1169,
    "gn:feature_class":"P",
    "gn:feature_code":"PPL",
    "gn:name":"Muceque",
    "gn:population":0,
    "gn:timezone":"Africa/Luanda",
    "iso:country":"AO",
    "wof:name":"Muceque",
    "wof:placetype":"locality"
},
  "geometry": {"coordinates":[16.75,-11.05],"type":"Point"}
}