{
  "type": "Feature",
  "properties": {
    "gn:admin1_code":"8.0",
    "gn:asciiname":"Ussombo",
    "gn:country_code":"AO",
    "gn:dem":1661,
    "gn:feature_class":"P",
    "gn:feature_code":"PPL",
    "gn:name":"Ussombo",
    "gn:population":0,
    "gn:timezone":"Africa/Luanda",
    "iso:country":"AO",
    "wof:name":"Ussombo",
    "wof:placetype":"locality"
},
  "geometry": {"coordinates":[15.54694,-12.77444],"type":"Point"}
}