{
  "type": "Feature",
  "properties": {
    "gn:admin1_code":"18.0",
    "gn:asciiname":"Calemba",
    "gn:country_code":"AO",
    "gn:dem":1110,
    "gn:feature_class":"P",
    "gn:feature_code":"PPL",
    "gn:name":"Calemba",
    "gn:population":0,
    "gn:timezone":"Africa/Luanda",
    "iso:country":"AO",
    "wof:name":"Calemba",
    "wof:placetype":"locality"
},
  "geometry": {"coordinates":[21.1773,-10.4295],"type":"Point"}
}