{
  "type": "Feature",
  "properties": {
    "gn:admin1_code":"15.0",
    "gn:asciiname":"Bengo",
    "gn:country_code":"AO",
    "gn:dem":1242,
    "gn:feature_class":"P",
    "gn:feature_code":"PPL",
    "gn:name":"Bengo",
    "gn:population":0,
    "gn:timezone":"Africa/Luanda",
    "iso:country":"AO",
    "name:ceb_x_preferred":[
        "Bengo"
    ],
    "name:deu_x_preferred":[
        "Bengo"
    ],
    "name:ita_x_preferred":[
        "Bengo"
    ],
    "name:swe_x_preferred":[
        "Bengo"
    ],
    "wof:name":"Bengo",
    "wof:placetype":"locality"
},
  "geometry": {"coordinates":[15.59879,-7.85216],"type":"Point"}
}