{
  "type": "Feature",
  "properties": {
    "gn:admin1_code":"1.0",
    "gn:asciiname":"Caxiva",
    "gn:country_code":"AO",
    "gn:dem":7,
    "gn:feature_class":"P",
    "gn:feature_code":"PPL",
    "gn:name":"Caxiva",
    "gn:population":0,
    "gn:timezone":"Africa/Luanda",
    "iso:country":"AO",
    "wof:name":"Caxiva",
    "wof:placetype":"locality"
},
  "geometry": {"coordinates":[13.53715,-12.45271],"type":"Point"}
}