{
  "type": "Feature",
  "properties": {
    "gn:admin1_code":"15.0",
    "gn:asciiname":"Quipambo",
    "gn:country_code":"AO",
    "gn:dem":909,
    "gn:feature_class":"P",
    "gn:feature_code":"PPL",
    "gn:name":"Quipambo",
    "gn:population":0,
    "gn:timezone":"Africa/Luanda",
    "iso:country":"AO",
    "name:und_x_variant":[
        "Quipamba",
        "Quipambo"
    ],
    "wof:name":"Quipambo",
    "wof:placetype":"locality"
},
  "geometry": {"coordinates":[15.27971,-6.37143],"type":"Point"}
}