{
  "type": "Feature",
  "properties": {
    "gn:admin1_code":"15.0",
    "gn:asciiname":"Ndongo",
    "gn:country_code":"AO",
    "gn:dem":1024,
    "gn:feature_class":"P",
    "gn:feature_code":"PPL",
    "gn:name":"Ndongo",
    "gn:population":0,
    "gn:timezone":"Africa/Luanda",
    "iso:country":"AO",
    "name:rus_x_preferred":[
        "\u0414\u043e\u043d\u0433\u043e"
    ],
    "name:und_x_variant":[
        "Quindona",
        "Dongo",
        "Ndongo"
    ],
    "wof:name":"Ndongo",
    "wof:placetype":"locality"
},
  "geometry": {"coordinates":[15.10837,-6.80617],"type":"Point"}
}