{
  "type": "Feature",
  "properties": {
    "gn:admin1_code":"15.0",
    "gn:asciiname":"Luzuanda",
    "gn:country_code":"AO",
    "gn:dem":1114,
    "gn:feature_class":"P",
    "gn:feature_code":"PPL",
    "gn:name":"Luzuanda",
    "gn:population":0,
    "gn:timezone":"Africa/Luanda",
    "iso:country":"AO",
    "name:und_x_variant":[
        "Luzuando",
        "Lusuanda",
        "Luzunda"
    ],
    "wof:name":"Luzuanda",
    "wof:placetype":"locality"
},
  "geometry": {"coordinates":[15.17584,-6.68215],"type":"Point"}
}