{
  "type": "Feature",
  "properties": {
    "gn:admin1_code":"1.0",
    "gn:asciiname":"Cambolo",
    "gn:country_code":"AO",
    "gn:dem":8,
    "gn:feature_class":"P",
    "gn:feature_code":"PPL",
    "gn:name":"Cambolo",
    "gn:population":0,
    "gn:timezone":"Africa/Luanda",
    "iso:country":"AO",
    "wof:name":"Cambolo",
    "wof:placetype":"locality"
},
  "geometry": {"coordinates":[13.28472,-12.58889],"type":"Point"}
}