{
  "type": "Feature",
  "properties": {
    "gn:admin1_code":"15.0",
    "gn:asciiname":"Lambo",
    "gn:cc2":"AO",
    "gn:country_code":"AO",
    "gn:dem":452,
    "gn:feature_class":"P",
    "gn:feature_code":"PPL",
    "gn:name":"Lambo",
    "gn:population":0,
    "gn:timezone":"Africa/Luanda",
    "iso:country":"AO",
    "name:ceb_x_preferred":[
        "Lambo"
    ],
    "name:rus_x_preferred":[
        "\u041b\u0430\u043c\u0431\u043e"
    ],
    "name:spa_x_preferred":[
        "Lambo"
    ],
    "name:swe_x_preferred":[
        "Lambo"
    ],
    "name:und_x_variant":[
        "Ambuila"
    ],
    "wof:name":"Lambo",
    "wof:placetype":"locality"
},
  "geometry": {"coordinates":[14.26667,-7.48333],"type":"Point"}
}