{
  "type": "Feature",
  "properties": {
    "gn:admin1_code":"12.0",
    "gn:asciiname":"Quinguelegi",
    "gn:country_code":"AO",
    "gn:dem":1101,
    "gn:feature_class":"P",
    "gn:feature_code":"PPL",
    "gn:name":"Quinguelegi",
    "gn:population":0,
    "gn:timezone":"Africa/Luanda",
    "iso:country":"AO",
    "wof:name":"Quinguelegi",
    "wof:placetype":"locality"
},
  "geometry": {"coordinates":[16.32941,-9.24703],"type":"Point"}
}