{
  "type": "Feature",
  "properties": {
    "gn:admin1_code":"12.0",
    "gn:asciiname":"Zenga",
    "gn:country_code":"AO",
    "gn:dem":589,
    "gn:feature_class":"P",
    "gn:feature_code":"PPL",
    "gn:name":"Zenga",
    "gn:population":0,
    "gn:timezone":"Africa/Luanda",
    "iso:country":"AO",
    "name:fin_x_preferred":[
        "Zenga"
    ],
    "name:pol_x_preferred":[
        "Zenga"
    ],
    "name:rus_x_preferred":[
        "\u0414\u0437\u044d\u043d\u0433\u0430"
    ],
    "name:ukr_x_preferred":[
        "\u0414\u0437\u0435\u043d\u0433\u0430"
    ],
    "wof:name":"Zenga",
    "wof:placetype":"locality"
},
  "geometry": {"coordinates":[17.19018,-7.59142],"type":"Point"}
}