{
  "type": "Feature",
  "properties": {
    "gn:admin1_code":"8.0",
    "gn:asciiname":"Tchicoti",
    "gn:country_code":"AO",
    "gn:dem":1454,
    "gn:feature_class":"P",
    "gn:feature_code":"PPL",
    "gn:name":"Tchicoti",
    "gn:population":0,
    "gn:timezone":"Africa/Luanda",
    "iso:country":"AO",
    "wof:name":"Tchicoti",
    "wof:placetype":"locality"
},
  "geometry": {"coordinates":[15.34806,-12.91806],"type":"Point"}
}