{
  "type": "Feature",
  "properties": {
    "gn:admin1_code":"12.0",
    "gn:asciiname":"Quimbila",
    "gn:country_code":"AO",
    "gn:dem":1119,
    "gn:feature_class":"P",
    "gn:feature_code":"PPL",
    "gn:name":"Quimbila",
    "gn:population":0,
    "gn:timezone":"Africa/Luanda",
    "iso:country":"AO",
    "wof:name":"Quimbila",
    "wof:placetype":"locality"
},
  "geometry": {"coordinates":[17.03481,-9.70154],"type":"Point"}
}