{
  "type": "Feature",
  "properties": {
    "gn:admin1_code":"16.0",
    "gn:asciiname":"Quimi",
    "gn:country_code":"AO",
    "gn:dem":374,
    "gn:feature_class":"P",
    "gn:feature_code":"PPL",
    "gn:name":"Quimi",
    "gn:population":0,
    "gn:timezone":"Africa/Luanda",
    "iso:country":"AO",
    "wof:name":"Quimi",
    "wof:placetype":"locality"
},
  "geometry": {"coordinates":[13.85,-7.06667],"type":"Point"}
}