{
  "type": "Feature",
  "properties": {
    "gn:admin1_code":"6.0",
    "gn:asciiname":"Libata do Onze",
    "gn:country_code":"AO",
    "gn:dem":132,
    "gn:feature_class":"P",
    "gn:feature_code":"PPL",
    "gn:name":"Libata do Onze",
    "gn:population":0,
    "gn:timezone":"Africa/Luanda",
    "iso:country":"AO",
    "wof:name":"Libata do Onze",
    "wof:placetype":"locality"
},
  "geometry": {"coordinates":[13.83776,-10.73198],"type":"Point"}
}