{
  "type": "Feature",
  "properties": {
    "gn:admin1_code":"6.0",
    "gn:asciiname":"Ngonga Centro",
    "gn:country_code":"AO",
    "gn:dem":1153,
    "gn:feature_class":"P",
    "gn:feature_code":"PPL",
    "gn:name":"Ngonga Centro",
    "gn:population":0,
    "gn:timezone":"Africa/Luanda",
    "iso:country":"AO",
    "wof:name":"Ngonga Centro",
    "wof:placetype":"locality"
},
  "geometry": {"coordinates":[14.52556,-11.03047],"type":"Point"}
}