{
  "type": "Feature",
  "properties": {
    "gn:admin1_code":"1.0",
    "gn:asciiname":"Chipende",
    "gn:country_code":"AO",
    "gn:dem":1662,
    "gn:feature_class":"P",
    "gn:feature_code":"PPLL",
    "gn:name":"Chipende",
    "gn:population":0,
    "gn:timezone":"Africa/Luanda",
    "iso:country":"AO",
    "wof:name":"Chipende",
    "wof:placetype":"locality"
},
  "geometry": {"coordinates":[14.53236,-12.46705],"type":"Point"}
}