{
  "type": "Feature",
  "properties": {
    "gn:admin1_code":"8.0",
    "gn:admin2_code":"3345909.0",
    "gn:asciiname":"Tchindjendje",
    "gn:country_code":"AO",
    "gn:dem":1375,
    "gn:feature_class":"P",
    "gn:feature_code":"PPL",
    "gn:name":"Tchindjendje",
    "gn:population":0,
    "gn:timezone":"Africa/Luanda",
    "iso:country":"AO",
    "name:azb_x_preferred":[
        "\u062a\u0634\u06cc\u0646\u062f\u0698\u0646\u0698\u0647"
    ],
    "name:cat_x_preferred":[
        "Tchinjenje"
    ],
    "name:deu_x_preferred":[
        "Chinjenje"
    ],
    "name:fas_x_preferred":[
        "\u062a\u0634\u06cc\u0646\u062f\u0698\u0646\u0698\u0647"
    ],
    "name:ita_x_preferred":[
        "Tchindjendje"
    ],
    "name:por_x_preferred":[
        "Tchindjenje"
    ],
    "name:rus_x_preferred":[
        "\u0422\u0448\u0438\u043d\u0434\u0436\u0435\u043d\u0436\u0435"
    ],
    "name:spa_x_preferred":[
        "Tchinjenje"
    ],
    "name:und_x_variant":[
        "Kinjenje",
        "Quingenge"
    ],
    "name:zho_x_preferred":[
        "\u6b3d\u4efb\u6d85"
    ],
    "wof:name":"Tchindjendje",
    "wof:placetype":"locality"
},
  "geometry": {"coordinates":[14.92823,-12.82494],"type":"Point"}
}