{
  "type": "Feature",
  "properties": {
    "gn:admin1_code":"6.0",
    "gn:asciiname":"Quiemba",
    "gn:country_code":"AO",
    "gn:dem":1088,
    "gn:feature_class":"P",
    "gn:feature_code":"PPL",
    "gn:name":"Quiemba",
    "gn:population":0,
    "gn:timezone":"Africa/Luanda",
    "iso:country":"AO",
    "wof:name":"Quiemba",
    "wof:placetype":"locality"
},
  "geometry": {"coordinates":[14.42883,-10.79184],"type":"Point"}
}