{
  "type": "Feature",
  "properties": {
    "gn:admin1_code":"18.0",
    "gn:asciiname":"Samungi",
    "gn:country_code":"AO",
    "gn:dem":1304,
    "gn:feature_class":"P",
    "gn:feature_code":"PPL",
    "gn:name":"Samungi",
    "gn:population":0,
    "gn:timezone":"Africa/Luanda",
    "iso:country":"AO",
    "name:und_x_variant":[
        "Samunge"
    ],
    "wof:name":"Samungi",
    "wof:placetype":"locality"
},
  "geometry": {"coordinates":[19.08635,-10.93075],"type":"Point"}
}