{
  "type": "Feature",
  "properties": {
    "gn:admin1_code":"12.0",
    "gn:asciiname":"Laonda",
    "gn:country_code":"AO",
    "gn:dem":1066,
    "gn:feature_class":"P",
    "gn:feature_code":"PPL",
    "gn:name":"Laonda",
    "gn:population":0,
    "gn:timezone":"Africa/Luanda",
    "iso:country":"AO",
    "wof:name":"Laonda",
    "wof:placetype":"locality"
},
  "geometry": {"coordinates":[15.93333,-9.25],"type":"Point"}
}