{
  "type": "Feature",
  "properties": {
    "gn:admin1_code":"15.0",
    "gn:asciiname":"Bungo",
    "gn:country_code":"AO",
    "gn:dem":1228,
    "gn:feature_class":"P",
    "gn:feature_code":"PPL",
    "gn:name":"Bungo",
    "gn:population":0,
    "gn:timezone":"Africa/Luanda",
    "iso:country":"AO",
    "wof:name":"Bungo",
    "wof:placetype":"locality"
},
  "geometry": {"coordinates":[15.38524,-7.43956],"type":"Point"}
}