{
  "type": "Feature",
  "properties": {
    "gn:admin1_code":"12.0",
    "gn:asciiname":"Menha",
    "gn:country_code":"AO",
    "gn:dem":980,
    "gn:feature_class":"P",
    "gn:feature_code":"PPL",
    "gn:name":"Menha",
    "gn:population":0,
    "gn:timezone":"Africa/Luanda",
    "iso:country":"AO",
    "wof:name":"Menha",
    "wof:placetype":"locality"
},
  "geometry": {"coordinates":[16.05106,-9.12052],"type":"Point"}
}