{
  "type": "Feature",
  "properties": {
    "gn:admin1_code":"15.0",
    "gn:asciiname":"Gingolosaco",
    "gn:cc2":"AO",
    "gn:country_code":"AO",
    "gn:dem":962,
    "gn:feature_class":"P",
    "gn:feature_code":"PPL",
    "gn:name":"Gingolosaco",
    "gn:population":0,
    "gn:timezone":"Africa/Luanda",
    "iso:country":"AO",
    "name:und_x_variant":[
        "Quibenguibata",
        "Gingolosaco"
    ],
    "wof:name":"Gingolosaco",
    "wof:placetype":"locality"
},
  "geometry": {"coordinates":[15.33333,-6.91667],"type":"Point"}
}