{
  "type": "Feature",
  "properties": {
    "gn:admin1_code":"14.0",
    "gn:asciiname":"Caiongo",
    "gn:country_code":"AO",
    "gn:dem":1092,
    "gn:feature_class":"P",
    "gn:feature_code":"PPL",
    "gn:name":"Caiongo",
    "gn:population":0,
    "gn:timezone":"Africa/Luanda",
    "iso:country":"AO",
    "wof:name":"Caiongo",
    "wof:placetype":"locality"
},
  "geometry": {"coordinates":[21.81751,-11.27994],"type":"Point"}
}