{
  "type": "Feature",
  "properties": {
    "gn:admin1_code":"8.0",
    "gn:asciiname":"Loquengo",
    "gn:cc2":"AO",
    "gn:country_code":"AO",
    "gn:dem":1726,
    "gn:feature_class":"P",
    "gn:feature_code":"PPL",
    "gn:name":"Loquengo",
    "gn:population":0,
    "gn:timezone":"Africa/Luanda",
    "iso:country":"AO",
    "name:und_x_variant":[
        "Coquendo",
        "Coquengo",
        "Loquengo"
    ],
    "wof:name":"Loquengo",
    "wof:placetype":"locality"
},
  "geometry": {"coordinates":[15.64333,-13.04139],"type":"Point"}
}