{
  "type": "Feature",
  "properties": {
    "gn:admin1_code":"12.0",
    "gn:asciiname":"Luquembo",
    "gn:country_code":"AO",
    "gn:dem":1125,
    "gn:feature_class":"P",
    "gn:feature_code":"PPL",
    "gn:name":"Luquembo",
    "gn:population":0,
    "gn:timezone":"Africa/Luanda",
    "iso:country":"AO",
    "name:cat_x_preferred":[
        "Luquembo"
    ],
    "name:deu_x_preferred":[
        "Luquembo"
    ],
    "name:ita_x_preferred":[
        "Luquembo"
    ],
    "name:msa_x_preferred":[
        "Luquembo"
    ],
    "name:por_x_preferred":[
        "Luquembo"
    ],
    "name:spa_x_preferred":[
        "Luquembo"
    ],
    "name:zho_x_preferred":[
        "\u76e7\u80af\u535a"
    ],
    "wof:name":"Luquembo",
    "wof:placetype":"locality"
},
  "geometry": {"coordinates":[17.71766000000001,-10.73912],"type":"Point"}
}