{
  "type": "Feature",
  "properties": {
    "gn:admin1_code":"12.0",
    "gn:asciiname":"Diama",
    "gn:country_code":"AO",
    "gn:dem":1145,
    "gn:feature_class":"P",
    "gn:feature_code":"PPL",
    "gn:name":"Diama",
    "gn:population":0,
    "gn:timezone":"Africa/Luanda",
    "iso:country":"AO",
    "wof:name":"Diama",
    "wof:placetype":"locality"
},
  "geometry": {"coordinates":[17.29159,-9.86722],"type":"Point"}
}