{
  "type": "Feature",
  "properties": {
    "gn:admin1_code":"6.0",
    "gn:asciiname":"Lundo",
    "gn:country_code":"AO",
    "gn:dem":1240,
    "gn:feature_class":"P",
    "gn:feature_code":"PPL",
    "gn:name":"Lundo",
    "gn:population":0,
    "gn:timezone":"Africa/Luanda",
    "iso:country":"AO",
    "wof:name":"Lundo",
    "wof:placetype":"locality"
},
  "geometry": {"coordinates":[14.46667,-10.61667],"type":"Point"}
}