{
  "type": "Feature",
  "properties": {
    "gn:admin1_code":"6.0",
    "gn:asciiname":"Nhongono",
    "gn:country_code":"AO",
    "gn:dem":1183,
    "gn:feature_class":"P",
    "gn:feature_code":"PPL",
    "gn:name":"Nhongono",
    "gn:population":0,
    "gn:timezone":"Africa/Luanda",
    "iso:country":"AO",
    "wof:name":"Nhongono",
    "wof:placetype":"locality"
},
  "geometry": {"coordinates":[14.57178,-10.71707],"type":"Point"}
}