{
  "type": "Feature",
  "properties": {
    "gn:admin1_code":"2.0",
    "gn:asciiname":"Tchimbalandongo",
    "gn:country_code":"AO",
    "gn:dem":1692,
    "gn:feature_class":"P",
    "gn:feature_code":"PPL",
    "gn:name":"Tchimbalandongo",
    "gn:population":0,
    "gn:timezone":"Africa/Luanda",
    "iso:country":"AO",
    "wof:name":"Tchimbalandongo",
    "wof:placetype":"locality"
},
  "geometry": {"coordinates":[16.4108,-12.28619],"type":"Point"}
}