{
  "type": "Feature",
  "properties": {
    "gn:admin1_code":"12.0",
    "gn:asciiname":"Singombi",
    "gn:country_code":"AO",
    "gn:dem":1092,
    "gn:feature_class":"P",
    "gn:feature_code":"PPL",
    "gn:name":"Singombi",
    "gn:population":0,
    "gn:timezone":"Africa/Luanda",
    "iso:country":"AO",
    "wof:name":"Singombi",
    "wof:placetype":"locality"
},
  "geometry": {"coordinates":[17.40312999999999,-10.47974],"type":"Point"}
}