{
  "type": "Feature",
  "properties": {
    "gn:admin1_code":"15.0",
    "gn:asciiname":"Quindacumbua",
    "gn:country_code":"AO",
    "gn:dem":788,
    "gn:feature_class":"P",
    "gn:feature_code":"PPL",
    "gn:name":"Quindacumbua",
    "gn:population":0,
    "gn:timezone":"Africa/Luanda",
    "iso:country":"AO",
    "wof:name":"Quindacumbua",
    "wof:placetype":"locality"
},
  "geometry": {"coordinates":[16.36013,-6.38514],"type":"Point"}
}