{
  "type": "Feature",
  "properties": {
    "gn:admin1_code":"15.0",
    "gn:asciiname":"Mbanza-Ngungo",
    "gn:country_code":"AO",
    "gn:dem":975,
    "gn:feature_class":"P",
    "gn:feature_code":"PPL",
    "gn:name":"Mbanza-Ngungo",
    "gn:population":0,
    "gn:timezone":"Africa/Luanda",
    "iso:country":"AO",
    "wof:name":"Mbanza-Ngungo",
    "wof:placetype":"locality"
},
  "geometry": {"coordinates":[16.03243,-7.19659],"type":"Point"}
}