{
  "type": "Feature",
  "properties": {
    "gn:admin1_code":"9.0",
    "gn:asciiname":"Tchiquelo",
    "gn:country_code":"AO",
    "gn:dem":1250,
    "gn:feature_class":"P",
    "gn:feature_code":"PPL",
    "gn:name":"Tchiquelo",
    "gn:population":0,
    "gn:timezone":"Africa/Luanda",
    "iso:country":"AO",
    "name:und_x_variant":[
        "Q\u00fbe",
        "Chiquelo",
        "Chiqueto",
        "Tchiquelo"
    ],
    "wof:name":"Tchiquelo",
    "wof:placetype":"locality"
},
  "geometry": {"coordinates":[14.88773,-14.64801],"type":"Point"}
}