{
  "type": "Feature",
  "properties": {
    "gn:admin1_code":"12.0",
    "gn:asciiname":"Cachandila",
    "gn:country_code":"AO",
    "gn:dem":983,
    "gn:feature_class":"P",
    "gn:feature_code":"PPL",
    "gn:name":"Cachandila",
    "gn:population":0,
    "gn:timezone":"Africa/Luanda",
    "iso:country":"AO",
    "name:und_x_variant":[
        "Cachadila",
        "Cach\u00e1rila",
        "Cachandila"
    ],
    "wof:name":"Cachandila",
    "wof:placetype":"locality"
},
  "geometry": {"coordinates":[15.6199,-9.73327],"type":"Point"}
}