{
  "type": "Feature",
  "properties": {
    "gn:admin1_code":"1.0",
    "gn:asciiname":"Chiquela",
    "gn:cc2":"AO",
    "gn:country_code":"AO",
    "gn:dem":1204,
    "gn:feature_class":"P",
    "gn:feature_code":"PPL",
    "gn:name":"Chiquela",
    "gn:population":0,
    "gn:timezone":"Africa/Luanda",
    "iso:country":"AO",
    "name:und_x_variant":[
        "Chiquele",
        "Chiquela"
    ],
    "wof:name":"Chiquela",
    "wof:placetype":"locality"
},
  "geometry": {"coordinates":[14.56667,-12.31667],"type":"Point"}
}