{
  "type": "Feature",
  "properties": {
    "gn:admin1_code":"4.0",
    "gn:asciiname":"Jambe",
    "gn:cc2":"AO",
    "gn:country_code":"AO",
    "gn:dem":1498,
    "gn:feature_class":"P",
    "gn:feature_code":"PPL",
    "gn:name":"Jambe",
    "gn:population":0,
    "gn:timezone":"Africa/Luanda",
    "iso:country":"AO",
    "name:und_x_variant":[
        "Muene Jambi",
        "Muene Jombi",
        "Jambe"
    ],
    "name:urd_x_preferred":[
        "\u062c\u0645\u0628\u06d2"
    ],
    "wof:name":"Jambe",
    "wof:placetype":"locality"
},
  "geometry": {"coordinates":[16.81667,-14.31667],"type":"Point"}
}