{
  "type": "Feature",
  "properties": {
    "gn:admin1_code":"6.0",
    "gn:asciiname":"Capiane",
    "gn:country_code":"AO",
    "gn:dem":863,
    "gn:feature_class":"P",
    "gn:feature_code":"PPL",
    "gn:name":"Capiane",
    "gn:population":0,
    "gn:timezone":"Africa/Luanda",
    "iso:country":"AO",
    "wof:name":"Capiane",
    "wof:placetype":"locality"
},
  "geometry": {"coordinates":[14.36949,-10.54343],"type":"Point"}
}