{
  "type": "Feature",
  "properties": {
    "gn:admin1_code":"8.0",
    "gn:asciiname":"Sanga",
    "gn:country_code":"AO",
    "gn:dem":1549,
    "gn:feature_class":"P",
    "gn:feature_code":"PPL",
    "gn:name":"Sanga",
    "gn:population":0,
    "gn:timezone":"Africa/Luanda",
    "iso:country":"AO",
    "wof:name":"Sanga",
    "wof:placetype":"locality"
},
  "geometry": {"coordinates":[15.61917,-12.61889],"type":"Point"}
}