{
  "type": "Feature",
  "properties": {
    "gn:admin1_code":"15.0",
    "gn:asciiname":"Quivenguete",
    "gn:country_code":"AO",
    "gn:dem":827,
    "gn:feature_class":"P",
    "gn:feature_code":"PPL",
    "gn:name":"Quivenguete",
    "gn:population":0,
    "gn:timezone":"Africa/Luanda",
    "iso:country":"AO",
    "wof:name":"Quivenguete",
    "wof:placetype":"locality"
},
  "geometry": {"coordinates":[15.7877,-6.4718],"type":"Point"}
}