{
  "type": "Feature",
  "properties": {
    "gn:admin1_code":"6.0",
    "gn:asciiname":"Cassuba",
    "gn:country_code":"AO",
    "gn:dem":1125,
    "gn:feature_class":"P",
    "gn:feature_code":"PPL",
    "gn:name":"Cassuba",
    "gn:population":0,
    "gn:timezone":"Africa/Luanda",
    "iso:country":"AO",
    "wof:name":"Cassuba",
    "wof:placetype":"locality"
},
  "geometry": {"coordinates":[15.16765,-10.12165],"type":"Point"}
}