{
  "type": "Feature",
  "properties": {
    "gn:admin1_code":"15.0",
    "gn:asciiname":"Quibanji",
    "gn:country_code":"AO",
    "gn:dem":528,
    "gn:feature_class":"P",
    "gn:feature_code":"PPL",
    "gn:name":"Quibanji",
    "gn:population":0,
    "gn:timezone":"Africa/Luanda",
    "iso:country":"AO",
    "wof:name":"Quibanji",
    "wof:placetype":"locality"
},
  "geometry": {"coordinates":[16.22754,-5.94698],"type":"Point"}
}