{
  "type": "Feature",
  "properties": {
    "gn:admin1_code":"12.0",
    "gn:asciiname":"Macungo",
    "gn:country_code":"AO",
    "gn:dem":699,
    "gn:feature_class":"P",
    "gn:feature_code":"PPL",
    "gn:name":"Macungo",
    "gn:population":0,
    "gn:timezone":"Africa/Luanda",
    "iso:country":"AO",
    "wof:name":"Macungo",
    "wof:placetype":"locality"
},
  "geometry": {"coordinates":[17.25816,-8.58802],"type":"Point"}
}