{
  "type": "Feature",
  "properties": {
    "gn:admin1_code":"5.0",
    "gn:asciiname":"Sala Hato",
    "gn:country_code":"AO",
    "gn:dem":1032,
    "gn:feature_class":"P",
    "gn:feature_code":"PPL",
    "gn:name":"Sala Hato",
    "gn:population":0,
    "gn:timezone":"Africa/Luanda",
    "iso:country":"AO",
    "wof:name":"Sala Hato",
    "wof:placetype":"locality"
},
  "geometry": {"coordinates":[15.23082,-8.68225],"type":"Point"}
}