{
  "type": "Feature",
  "properties": {
    "gn:admin1_code":"12.0",
    "gn:asciiname":"Pacheco",
    "gn:country_code":"AO",
    "gn:dem":1074,
    "gn:feature_class":"P",
    "gn:feature_code":"PPL",
    "gn:name":"Pacheco",
    "gn:population":0,
    "gn:timezone":"Africa/Luanda",
    "iso:country":"AO",
    "name:kor_x_preferred":[
        "\ud30c\uccb4\ucf54"
    ],
    "wof:name":"Pacheco",
    "wof:placetype":"locality"
},
  "geometry": {"coordinates":[16.13102,-9.21099],"type":"Point"}
}