{
  "type": "Feature",
  "properties": {
    "gn:admin1_code":"3.0",
    "gn:asciiname":"N'To",
    "gn:country_code":"AO",
    "gn:dem":118,
    "gn:feature_class":"P",
    "gn:feature_code":"PPL",
    "gn:name":"N\u2019T\u00f3",
    "gn:population":0,
    "gn:timezone":"Africa/Luanda",
    "iso:country":"AO",
    "name:und_x_variant":[
        "M\u2019T\u00f3",
        "N\u2019T\u00f3"
    ],
    "wof:name":"N'To",
    "wof:placetype":"locality"
},
  "geometry": {"coordinates":[12.25,-5.68333],"type":"Point"}
}