{
  "type": "Feature",
  "properties": {
    "gn:admin1_code":"2.0",
    "gn:asciiname":"Salvador",
    "gn:country_code":"AO",
    "gn:dem":1701,
    "gn:feature_class":"P",
    "gn:feature_code":"PPL",
    "gn:name":"Salvador",
    "gn:population":0,
    "gn:timezone":"Africa/Luanda",
    "iso:country":"AO",
    "wof:name":"Salvador",
    "wof:placetype":"locality"
},
  "geometry": {"coordinates":[15.79265,-11.39578],"type":"Point"}
}