{
  "type": "Feature",
  "properties": {
    "gn:admin1_code":"2.0",
    "gn:asciiname":"Jundo",
    "gn:country_code":"AO",
    "gn:dem":1661,
    "gn:feature_class":"P",
    "gn:feature_code":"PPL",
    "gn:name":"Jund\u00f3",
    "gn:population":0,
    "gn:timezone":"Africa/Luanda",
    "iso:country":"AO",
    "wof:name":"Jundo",
    "wof:placetype":"locality"
},
  "geometry": {"coordinates":[17.03424,-11.4304],"type":"Point"}
}