{
  "type": "Feature",
  "properties": {
    "gn:admin1_code":"1.0",
    "gn:asciiname":"Etalelua",
    "gn:country_code":"AO",
    "gn:dem":795,
    "gn:feature_class":"P",
    "gn:feature_code":"PPL",
    "gn:name":"Etalelua",
    "gn:population":0,
    "gn:timezone":"Africa/Luanda",
    "iso:country":"AO",
    "wof:name":"Etalelua",
    "wof:placetype":"locality"
},
  "geometry": {"coordinates":[14.13333,-12.98333],"type":"Point"}
}