{
  "type": "Feature",
  "properties": {
    "gn:admin1_code":"12.0",
    "gn:asciiname":"Hele Pezo",
    "gn:country_code":"AO",
    "gn:dem":1119,
    "gn:feature_class":"P",
    "gn:feature_code":"PPL",
    "gn:name":"Hele Pezo",
    "gn:population":0,
    "gn:timezone":"Africa/Luanda",
    "iso:country":"AO",
    "wof:name":"Hele Pezo",
    "wof:placetype":"locality"
},
  "geometry": {"coordinates":[16.16817,-9.21043],"type":"Point"}
}