{
  "type": "Feature",
  "properties": {
    "gn:admin1_code":"17.0",
    "gn:asciiname":"Samalambo",
    "gn:cc2":"AO",
    "gn:country_code":"AO",
    "gn:dem":859,
    "gn:feature_class":"P",
    "gn:feature_code":"PPL",
    "gn:name":"Samalambo",
    "gn:population":0,
    "gn:timezone":"Africa/Luanda",
    "iso:country":"AO",
    "name:und_x_variant":[
        "Sambalanga",
        "Samalambo"
    ],
    "wof:name":"Samalambo",
    "wof:placetype":"locality"
},
  "geometry": {"coordinates":[21.25,-7.65],"type":"Point"}
}