{
  "type": "Feature",
  "properties": {
    "gn:admin1_code":"9.0",
    "gn:asciiname":"Ndongue ia Handa",
    "gn:country_code":"AO",
    "gn:dem":1320,
    "gn:feature_class":"P",
    "gn:feature_code":"PPLL",
    "gn:name":"Ndongue i\u00e1 Handa",
    "gn:population":0,
    "gn:timezone":"Africa/Luanda",
    "iso:country":"AO",
    "wof:name":"Ndongue ia Handa",
    "wof:placetype":"locality"
},
  "geometry": {"coordinates":[14.62527,-14.56391],"type":"Point"}
}