{
  "type": "Feature",
  "properties": {
    "gn:admin1_code":"8.0",
    "gn:asciiname":"Manda",
    "gn:country_code":"AO",
    "gn:dem":1765,
    "gn:feature_class":"P",
    "gn:feature_code":"PPL",
    "gn:name":"Manda",
    "gn:population":0,
    "gn:timezone":"Africa/Luanda",
    "iso:country":"AO",
    "name:ceb_x_preferred":[
        "Manda"
    ],
    "name:deu_x_preferred":[
        "Manda"
    ],
    "name:fin_x_preferred":[
        "Manda"
    ],
    "name:fra_x_preferred":[
        "Manda"
    ],
    "name:hun_x_preferred":[
        "Manda"
    ],
    "name:ind_x_preferred":[
        "Manda"
    ],
    "name:ita_x_preferred":[
        "Manda"
    ],
    "name:kat_x_preferred":[
        "\u10db\u10d0\u10dc\u10d3\u10d0"
    ],
    "name:msa_x_preferred":[
        "Manda"
    ],
    "name:por_x_preferred":[
        "Manda"
    ],
    "name:rus_x_preferred":[
        "\u041c\u0430\u043d\u0434\u0430"
    ],
    "name:spa_x_preferred":[
        "Manda"
    ],
    "name:swa_x_preferred":[
        "Manda"
    ],
    "name:swe_x_preferred":[
        "Manda"
    ],
    "name:tur_x_preferred":[
        "Manda"
    ],
    "wof:name":"Manda",
    "wof:placetype":"locality"
},
  "geometry": {"coordinates":[15.46222,-13.07917],"type":"Point"}
}