{
  "type": "Feature",
  "properties": {
    "gn:admin1_code":"2.0",
    "gn:asciiname":"Ngango",
    "gn:country_code":"AO",
    "gn:dem":1638,
    "gn:feature_class":"P",
    "gn:feature_code":"PPL",
    "gn:name":"Ngango",
    "gn:population":0,
    "gn:timezone":"Africa/Luanda",
    "iso:country":"AO",
    "name:und_x_variant":[
        "Chiengue",
        "Gango",
        "Ngango"
    ],
    "wof:name":"Ngango",
    "wof:placetype":"locality"
},
  "geometry": {"coordinates":[16.01433,-11.17507],"type":"Point"}
}