{
  "type": "Feature",
  "properties": {
    "gn:admin1_code":"5.0",
    "gn:asciiname":"Cabanga",
    "gn:country_code":"AO",
    "gn:dem":870,
    "gn:feature_class":"P",
    "gn:feature_code":"PPL",
    "gn:name":"Cabanga",
    "gn:population":0,
    "gn:timezone":"Africa/Luanda",
    "iso:country":"AO",
    "wof:name":"Cabanga",
    "wof:placetype":"locality"
},
  "geometry": {"coordinates":[15.14844,-8.71944],"type":"Point"}
}