{
  "type": "Feature",
  "properties": {
    "gn:admin1_code":"6.0",
    "gn:asciiname":"Clemente",
    "gn:country_code":"AO",
    "gn:dem":393,
    "gn:feature_class":"P",
    "gn:feature_code":"PPL",
    "gn:name":"Clemente",
    "gn:population":0,
    "gn:timezone":"Africa/Luanda",
    "iso:country":"AO",
    "name:ita_x_preferred":[
        "Clemente"
    ],
    "name:spa_x_preferred":[
        "Clemente"
    ],
    "wof:name":"Clemente",
    "wof:placetype":"locality"
},
  "geometry": {"coordinates":[14.76667,-9.81667],"type":"Point"}
}