{
  "type": "Feature",
  "properties": {
    "gn:admin1_code":"17.0",
    "gn:asciiname":"Tchitato",
    "gn:country_code":"AO",
    "gn:dem":724,
    "gn:feature_class":"P",
    "gn:feature_code":"PPL",
    "gn:name":"Tchitato",
    "gn:population":0,
    "gn:timezone":"Africa/Luanda",
    "iso:country":"AO",
    "name:cat_x_preferred":[
        "Chitato"
    ],
    "name:deu_x_preferred":[
        "Chitato"
    ],
    "name:ita_x_preferred":[
        "Chitato"
    ],
    "name:por_x_preferred":[
        "Chitato"
    ],
    "name:spa_x_preferred":[
        "Chitato"
    ],
    "name:und_x_variant":[
        "Portug\u00e1lia",
        "Luachimo",
        "Dundo",
        "Chitato",
        "Tchitato"
    ],
    "name:zho_x_preferred":[
        "\u5e0c\u5854\u6258"
    ],
    "wof:name":"Tchitato",
    "wof:placetype":"locality"
},
  "geometry": {"coordinates":[20.82008,-7.34469],"type":"Point"}
}