{
  "type": "Feature",
  "properties": {
    "gn:admin1_code":"2.0",
    "gn:asciiname":"Navio",
    "gn:country_code":"AO",
    "gn:dem":1474,
    "gn:feature_class":"P",
    "gn:feature_code":"PPL",
    "gn:name":"Navio",
    "gn:population":0,
    "gn:timezone":"Africa/Luanda",
    "iso:country":"AO",
    "wof:name":"Navio",
    "wof:placetype":"locality"
},
  "geometry": {"coordinates":[16.85269,-11.40901],"type":"Point"}
}