{
  "type": "Feature",
  "properties": {
    "gn:admin1_code":"8.0",
    "gn:asciiname":"Nguia",
    "gn:country_code":"AO",
    "gn:dem":1707,
    "gn:feature_class":"P",
    "gn:feature_code":"PPL",
    "gn:name":"Nguia",
    "gn:population":0,
    "gn:timezone":"Africa/Luanda",
    "iso:country":"AO",
    "wof:name":"Nguia",
    "wof:placetype":"locality"
},
  "geometry": {"coordinates":[15.55611,-12.88306],"type":"Point"}
}