{
  "type": "Feature",
  "properties": {
    "gn:admin1_code":"5.0",
    "gn:asciiname":"Mucala",
    "gn:country_code":"AO",
    "gn:dem":778,
    "gn:feature_class":"P",
    "gn:feature_code":"PPL",
    "gn:name":"Mucala",
    "gn:population":0,
    "gn:timezone":"Africa/Luanda",
    "iso:country":"AO",
    "wof:name":"Mucala",
    "wof:placetype":"locality"
},
  "geometry": {"coordinates":[14.721,-9.07598],"type":"Point"}
}