{
  "type": "Feature",
  "properties": {
    "gn:admin1_code":"17.0",
    "gn:asciiname":"Muhuri",
    "gn:country_code":"AO",
    "gn:dem":1396,
    "gn:feature_class":"P",
    "gn:feature_code":"PPL",
    "gn:name":"Muh\u00fari",
    "gn:population":0,
    "gn:timezone":"Africa/Luanda",
    "iso:country":"AO",
    "wof:name":"Muhuri",
    "wof:placetype":"locality"
},
  "geometry": {"coordinates":[18.05697,-10.23195],"type":"Point"}
}