{
  "type": "Feature",
  "properties": {
    "gn:admin1_code":"15.0",
    "gn:asciiname":"Nsosso",
    "gn:country_code":"AO",
    "gn:dem":998,
    "gn:feature_class":"P",
    "gn:feature_code":"PPL",
    "gn:name":"Nsosso",
    "gn:population":0,
    "gn:timezone":"Africa/Luanda",
    "iso:country":"AO",
    "name:und_x_variant":[
        "31 de Janeiro",
        "Quinzala",
        "Trinta-e-um de Janeiro",
        "Nsosso"
    ],
    "wof:name":"Nsosso",
    "wof:placetype":"locality"
},
  "geometry": {"coordinates":[15.32401,-6.89809],"type":"Point"}
}