{
  "type": "Feature",
  "properties": {
    "gn:admin1_code":"8.0",
    "gn:asciiname":"Bento",
    "gn:country_code":"AO",
    "gn:dem":1420,
    "gn:feature_class":"P",
    "gn:feature_code":"PPL",
    "gn:name":"Bento",
    "gn:population":0,
    "gn:timezone":"Africa/Luanda",
    "iso:country":"AO",
    "wof:name":"Bento",
    "wof:placetype":"locality"
},
  "geometry": {"coordinates":[15.46667,-11.85],"type":"Point"}
}