{
  "type": "Feature",
  "properties": {
    "gn:admin1_code":"12.0",
    "gn:asciiname":"Cacui",
    "gn:country_code":"AO",
    "gn:dem":1082,
    "gn:feature_class":"P",
    "gn:feature_code":"PPL",
    "gn:name":"Cacui",
    "gn:population":0,
    "gn:timezone":"Africa/Luanda",
    "iso:country":"AO",
    "wof:name":"Cacui",
    "wof:placetype":"locality"
},
  "geometry": {"coordinates":[17.01214,-10.75316],"type":"Point"}
}