{
  "type": "Feature",
  "properties": {
    "gn:admin1_code":"18.0",
    "gn:asciiname":"Americo Boavida",
    "gn:country_code":"AO",
    "gn:dem":1301,
    "gn:feature_class":"P",
    "gn:feature_code":"PPL",
    "gn:name":"Am\u00e9rico Boavida",
    "gn:population":0,
    "gn:timezone":"Africa/Luanda",
    "iso:country":"AO",
    "wof:name":"Americo Boavida",
    "wof:placetype":"locality"
},
  "geometry": {"coordinates":[19.3536,-10.11752],"type":"Point"}
}