{
  "type": "Feature",
  "properties": {
    "gn:admin1_code":"12.0",
    "gn:asciiname":"Nganangombe",
    "gn:country_code":"AO",
    "gn:dem":1096,
    "gn:feature_class":"P",
    "gn:feature_code":"PPL",
    "gn:name":"Nganangombe",
    "gn:population":0,
    "gn:timezone":"Africa/Luanda",
    "iso:country":"AO",
    "wof:name":"Nganangombe",
    "wof:placetype":"locality"
},
  "geometry": {"coordinates":[16.96837,-10.09757],"type":"Point"}
}