{
  "type": "Feature",
  "properties": {
    "gn:admin1_code":"5.0",
    "gn:asciiname":"Quindangi",
    "gn:country_code":"AO",
    "gn:dem":1021,
    "gn:feature_class":"P",
    "gn:feature_code":"PPL",
    "gn:name":"Quindangi",
    "gn:population":0,
    "gn:timezone":"Africa/Luanda",
    "iso:country":"AO",
    "wof:name":"Quindangi",
    "wof:placetype":"locality"
},
  "geometry": {"coordinates":[15.30741,-8.71764],"type":"Point"}
}