{
  "type": "Feature",
  "properties": {
    "gn:admin1_code":"16.0",
    "gn:asciiname":"Safo",
    "gn:cc2":"AO",
    "gn:country_code":"AO",
    "gn:dem":639,
    "gn:feature_class":"P",
    "gn:feature_code":"PPL",
    "gn:name":"Safo",
    "gn:population":0,
    "gn:timezone":"Africa/Luanda",
    "iso:country":"AO",
    "name:und_x_variant":[
        "Safu",
        "Safo"
    ],
    "wof:name":"Safo",
    "wof:placetype":"locality"
},
  "geometry": {"coordinates":[14.36667,-6.58333],"type":"Point"}
}