{
  "type": "Feature",
  "properties": {
    "gn:admin1_code":"18.0",
    "gn:asciiname":"Cassongo",
    "gn:cc2":"AO",
    "gn:country_code":"AO",
    "gn:dem":916,
    "gn:feature_class":"P",
    "gn:feature_code":"PPL",
    "gn:name":"Cassongo",
    "gn:population":0,
    "gn:timezone":"Africa/Luanda",
    "iso:country":"AO",
    "name:und_x_variant":[
        "Casanga",
        "Cassongo"
    ],
    "wof:name":"Cassongo",
    "wof:placetype":"locality"
},
  "geometry": {"coordinates":[21.06667,-9.06667],"type":"Point"}
}