{
  "type": "Feature",
  "properties": {
    "gn:admin1_code":"9.0",
    "gn:asciiname":"Cangalongue",
    "gn:country_code":"AO",
    "gn:dem":1612,
    "gn:feature_class":"P",
    "gn:feature_code":"PPL",
    "gn:name":"Cangalongue",
    "gn:population":0,
    "gn:timezone":"Africa/Luanda",
    "iso:country":"AO",
    "wof:name":"Cangalongue",
    "wof:placetype":"locality"
},
  "geometry": {"coordinates":[13.46667,-15.26667],"type":"Point"}
}