{
  "type": "Feature",
  "properties": {
    "gn:admin1_code":"6.0",
    "gn:asciiname":"Cambuiu",
    "gn:country_code":"AO",
    "gn:dem":969,
    "gn:feature_class":"P",
    "gn:feature_code":"PPL",
    "gn:name":"Cambuiu",
    "gn:population":0,
    "gn:timezone":"Africa/Luanda",
    "iso:country":"AO",
    "wof:name":"Cambuiu",
    "wof:placetype":"locality"
},
  "geometry": {"coordinates":[14.27643,-11.09322],"type":"Point"}
}