{
  "type": "Feature",
  "properties": {
    "gn:admin1_code":"17.0",
    "gn:asciiname":"Mucundo ua Samba",
    "gn:country_code":"AO",
    "gn:dem":700,
    "gn:feature_class":"P",
    "gn:feature_code":"PPL",
    "gn:name":"Mucundo u\u00e1 Samba",
    "gn:population":0,
    "gn:timezone":"Africa/Luanda",
    "iso:country":"AO",
    "wof:name":"Mucundo ua Samba",
    "wof:placetype":"locality"
},
  "geometry": {"coordinates":[17.90178,-8.70946],"type":"Point"}
}