{
  "type": "Feature",
  "properties": {
    "gn:admin1_code":"6.0",
    "gn:asciiname":"Izidro",
    "gn:country_code":"AO",
    "gn:dem":1083,
    "gn:feature_class":"P",
    "gn:feature_code":"PPL",
    "gn:name":"Izidro",
    "gn:population":0,
    "gn:timezone":"Africa/Luanda",
    "iso:country":"AO",
    "wof:name":"Izidro",
    "wof:placetype":"locality"
},
  "geometry": {"coordinates":[14.41044,-10.85325],"type":"Point"}
}