{
  "type": "Feature",
  "properties": {
    "gn:admin1_code":"2.0",
    "gn:asciiname":"Salale",
    "gn:country_code":"AO",
    "gn:dem":1749,
    "gn:feature_class":"P",
    "gn:feature_code":"PPL",
    "gn:name":"Salale",
    "gn:population":0,
    "gn:timezone":"Africa/Luanda",
    "iso:country":"AO",
    "wof:name":"Salale",
    "wof:placetype":"locality"
},
  "geometry": {"coordinates":[17.03655,-11.53214],"type":"Point"}
}