{
  "type": "Feature",
  "properties": {
    "gn:admin1_code":"15.0",
    "gn:asciiname":"Lengue",
    "gn:country_code":"AO",
    "gn:dem":1017,
    "gn:feature_class":"P",
    "gn:feature_code":"PPL",
    "gn:name":"Lengue",
    "gn:population":0,
    "gn:timezone":"Africa/Luanda",
    "iso:country":"AO",
    "wof:name":"Lengue",
    "wof:placetype":"locality"
},
  "geometry": {"coordinates":[14.8664,-6.57338],"type":"Point"}
}