{
  "type": "Feature",
  "properties": {
    "gn:admin1_code":"14.0",
    "gn:asciiname":"Caiengue",
    "gn:country_code":"AO",
    "gn:dem":1159,
    "gn:feature_class":"P",
    "gn:feature_code":"PPL",
    "gn:name":"Caiengue",
    "gn:population":0,
    "gn:timezone":"Africa/Luanda",
    "iso:country":"AO",
    "wof:name":"Caiengue",
    "wof:placetype":"locality"
},
  "geometry": {"coordinates":[20.86667000000001,-12.61667],"type":"Point"}
}