{
  "type": "Feature",
  "properties": {
    "gn:admin1_code":"17.0",
    "gn:asciiname":"Catunga",
    "gn:country_code":"AO",
    "gn:dem":1180,
    "gn:feature_class":"P",
    "gn:feature_code":"PPL",
    "gn:name":"Catunga",
    "gn:population":0,
    "gn:timezone":"Africa/Luanda",
    "iso:country":"AO",
    "wof:name":"Catunga",
    "wof:placetype":"locality"
},
  "geometry": {"coordinates":[19.56359,-9.50552],"type":"Point"}
}