{
  "type": "Feature",
  "properties": {
    "gn:admin1_code":"6.0",
    "gn:asciiname":"Saca",
    "gn:country_code":"AO",
    "gn:dem":215,
    "gn:feature_class":"P",
    "gn:feature_code":"PPL",
    "gn:name":"Saca",
    "gn:population":0,
    "gn:timezone":"Africa/Luanda",
    "iso:country":"AO",
    "name:ceb_x_preferred":[
        "Saca"
    ],
    "name:deu_x_preferred":[
        "Saca"
    ],
    "name:ita_x_preferred":[
        "Saca"
    ],
    "name:nld_x_preferred":[
        "Saca"
    ],
    "name:ron_x_preferred":[
        "Saca"
    ],
    "name:swe_x_preferred":[
        "Saca"
    ],
    "wof:name":"Saca",
    "wof:placetype":"locality"
},
  "geometry": {"coordinates":[14.10816,-11.05359],"type":"Point"}
}