{
  "type": "Feature",
  "properties": {
    "gn:admin1_code":"19.0",
    "gn:asciiname":"Quibomba",
    "gn:country_code":"AO",
    "gn:dem":580,
    "gn:feature_class":"P",
    "gn:feature_code":"PPL",
    "gn:name":"Quibomba",
    "gn:population":0,
    "gn:timezone":"Africa/Luanda",
    "iso:country":"AO",
    "wof:name":"Quibomba",
    "wof:placetype":"locality"
},
  "geometry": {"coordinates":[14.43982,-8.71666],"type":"Point"}
}