{
  "type": "Feature",
  "properties": {
    "gn:admin1_code":"12.0",
    "gn:asciiname":"Cassongo",
    "gn:country_code":"AO",
    "gn:dem":697,
    "gn:feature_class":"P",
    "gn:feature_code":"PPL",
    "gn:name":"Cassongo",
    "gn:population":0,
    "gn:timezone":"Africa/Luanda",
    "iso:country":"AO",
    "name:und_x_variant":[
        "Cassocasoca",
        "Cassocosoco",
        "Cassongo"
    ],
    "wof:name":"Cassongo",
    "wof:placetype":"locality"
},
  "geometry": {"coordinates":[16.62711,-8.16604],"type":"Point"}
}