{
  "type": "Feature",
  "properties": {
    "gn:admin1_code":"15.0",
    "gn:asciiname":"Quimbiandangumba",
    "gn:cc2":"AO",
    "gn:country_code":"AO",
    "gn:dem":1017,
    "gn:feature_class":"P",
    "gn:feature_code":"PPL",
    "gn:name":"Quimbiandangumba",
    "gn:population":0,
    "gn:timezone":"Africa/Luanda",
    "iso:country":"AO",
    "name:und_x_variant":[
        "Quimbinguila",
        "Quimbiandangumba"
    ],
    "wof:name":"Quimbiandangumba",
    "wof:placetype":"locality"
},
  "geometry": {"coordinates":[15.86667,-6.95],"type":"Point"}
}