{
  "type": "Feature",
  "properties": {
    "gn:admin1_code":"14.0",
    "gn:asciiname":"Chameia",
    "gn:cc2":"AO",
    "gn:country_code":"AO",
    "gn:dem":1139,
    "gn:feature_class":"P",
    "gn:feature_code":"PPL",
    "gn:name":"Chameia",
    "gn:population":0,
    "gn:timezone":"Africa/Luanda",
    "iso:country":"AO",
    "name:und_x_variant":[
        "Chabae",
        "Shabai",
        "Chameia"
    ],
    "wof:name":"Chameia",
    "wof:placetype":"locality"
},
  "geometry": {"coordinates":[20.55,-14.03333],"type":"Point"}
}