{
  "type": "Feature",
  "properties": {
    "gn:admin1_code":"15.0",
    "gn:asciiname":"Bala",
    "gn:country_code":"AO",
    "gn:dem":570,
    "gn:feature_class":"P",
    "gn:feature_code":"PPL",
    "gn:name":"Bala",
    "gn:population":0,
    "gn:timezone":"Africa/Luanda",
    "iso:country":"AO",
    "wof:name":"Bala",
    "wof:placetype":"locality"
},
  "geometry": {"coordinates":[14.91667,-7.28333],"type":"Point"}
}