{
  "type": "Feature",
  "properties": {
    "gn:admin1_code":"12.0",
    "gn:asciiname":"Quianeco",
    "gn:country_code":"AO",
    "gn:dem":1144,
    "gn:feature_class":"P",
    "gn:feature_code":"PPL",
    "gn:name":"Quianeco",
    "gn:population":0,
    "gn:timezone":"Africa/Luanda",
    "iso:country":"AO",
    "wof:name":"Quianeco",
    "wof:placetype":"locality"
},
  "geometry": {"coordinates":[16.16771,-8.92064],"type":"Point"}
}