{
  "type": "Feature",
  "properties": {
    "gn:admin1_code":"5.0",
    "gn:asciiname":"Cambanze",
    "gn:country_code":"AO",
    "gn:dem":484,
    "gn:feature_class":"P",
    "gn:feature_code":"PPL",
    "gn:name":"Cambanze",
    "gn:population":0,
    "gn:timezone":"Africa/Luanda",
    "iso:country":"AO",
    "wof:name":"Cambanze",
    "wof:placetype":"locality"
},
  "geometry": {"coordinates":[14.74921,-9.63862],"type":"Point"}
}