{
  "type": "Feature",
  "properties": {
    "gn:admin1_code":"1.0",
    "gn:asciiname":"Polovero",
    "gn:country_code":"AO",
    "gn:dem":1142,
    "gn:feature_class":"P",
    "gn:feature_code":"PPL",
    "gn:name":"Polovero",
    "gn:population":0,
    "gn:timezone":"Africa/Luanda",
    "iso:country":"AO",
    "wof:name":"Polovero",
    "wof:placetype":"locality"
},
  "geometry": {"coordinates":[14.18333,-12.35],"type":"Point"}
}