{
  "type": "Feature",
  "properties": {
    "gn:admin1_code":"15.0",
    "gn:asciiname":"Quisola",
    "gn:cc2":"AO",
    "gn:country_code":"AO",
    "gn:dem":1032,
    "gn:feature_class":"P",
    "gn:feature_code":"PPL",
    "gn:name":"Quisola",
    "gn:population":0,
    "gn:timezone":"Africa/Luanda",
    "iso:country":"AO",
    "name:und_x_variant":[
        "Quizola",
        "Quisola"
    ],
    "wof:name":"Quisola",
    "wof:placetype":"locality"
},
  "geometry": {"coordinates":[14.96667,-6.45],"type":"Point"}
}