{
  "type": "Feature",
  "properties": {
    "gn:admin1_code":"12.0",
    "gn:asciiname":"Sibolobolo",
    "gn:country_code":"AO",
    "gn:dem":1120,
    "gn:feature_class":"P",
    "gn:feature_code":"PPL",
    "gn:name":"Sibolobolo",
    "gn:population":0,
    "gn:timezone":"Africa/Luanda",
    "iso:country":"AO",
    "name:und_x_variant":[
        "Nzomba"
    ],
    "wof:name":"Sibolobolo",
    "wof:placetype":"locality"
},
  "geometry": {"coordinates":[17.27282,-10.39653],"type":"Point"}
}