{
  "type": "Feature",
  "properties": {
    "gn:admin1_code":"15.0",
    "gn:asciiname":"Quibaba",
    "gn:country_code":"AO",
    "gn:dem":1133,
    "gn:feature_class":"P",
    "gn:feature_code":"PPL",
    "gn:name":"Quibaba",
    "gn:population":0,
    "gn:timezone":"Africa/Luanda",
    "iso:country":"AO",
    "wof:name":"Quibaba",
    "wof:placetype":"locality"
},
  "geometry": {"coordinates":[15.70637,-7.62275],"type":"Point"}
}