{
  "type": "Feature",
  "properties": {
    "gn:admin1_code":"17.0",
    "gn:asciiname":"Mona Quesse",
    "gn:country_code":"AO",
    "gn:dem":1075,
    "gn:feature_class":"P",
    "gn:feature_code":"PPL",
    "gn:name":"Mona Quesse",
    "gn:population":0,
    "gn:timezone":"Africa/Luanda",
    "iso:country":"AO",
    "wof:name":"Mona Quesse",
    "wof:placetype":"locality"
},
  "geometry": {"coordinates":[18.51965,-8.59988],"type":"Point"}
}