{
  "type": "Feature",
  "properties": {
    "gn:admin1_code":"12.0",
    "gn:asciiname":"Cavambo",
    "gn:country_code":"AO",
    "gn:dem":1149,
    "gn:feature_class":"P",
    "gn:feature_code":"PPL",
    "gn:name":"Cavambo",
    "gn:population":0,
    "gn:timezone":"Africa/Luanda",
    "iso:country":"AO",
    "wof:name":"Cavambo",
    "wof:placetype":"locality"
},
  "geometry": {"coordinates":[17.57435,-10.35896],"type":"Point"}
}