{
  "type": "Feature",
  "properties": {
    "gn:admin1_code":"2.0",
    "gn:asciiname":"Cauango",
    "gn:country_code":"AO",
    "gn:dem":1720,
    "gn:feature_class":"P",
    "gn:feature_code":"PPL",
    "gn:name":"Cauango",
    "gn:population":0,
    "gn:timezone":"Africa/Luanda",
    "iso:country":"AO",
    "wof:name":"Cauango",
    "wof:placetype":"locality"
},
  "geometry": {"coordinates":[16.80368,-11.88742],"type":"Point"}
}