{
  "type": "Feature",
  "properties": {
    "gn:admin1_code":"17.0",
    "gn:asciiname":"Munguanha Primeiro",
    "gn:country_code":"AO",
    "gn:dem":748,
    "gn:feature_class":"P",
    "gn:feature_code":"PPL",
    "gn:name":"Munguanha Primeiro",
    "gn:population":0,
    "gn:timezone":"Africa/Luanda",
    "iso:country":"AO",
    "wof:name":"Munguanha Primeiro",
    "wof:placetype":"locality"
},
  "geometry": {"coordinates":[21.23184,-7.4521],"type":"Point"}
}