{
  "type": "Feature",
  "properties": {
    "gn:admin1_code":"15.0",
    "gn:asciiname":"Tangi",
    "gn:country_code":"AO",
    "gn:dem":865,
    "gn:feature_class":"P",
    "gn:feature_code":"PPL",
    "gn:name":"Tangi",
    "gn:population":0,
    "gn:timezone":"Africa/Luanda",
    "iso:country":"AO",
    "name:bre_x_preferred":[
        "Tangi"
    ],
    "name:ceb_x_preferred":[
        "Tangi"
    ],
    "name:fra_x_preferred":[
        "Tangi"
    ],
    "name:ita_x_preferred":[
        "Tangi"
    ],
    "name:swe_x_preferred":[
        "Tangi"
    ],
    "name:tgl_x_preferred":[
        "Tangi"
    ],
    "name:und_x_variant":[
        "Banza",
        "Banza Tange"
    ],
    "wof:name":"Tangi",
    "wof:placetype":"locality"
},
  "geometry": {"coordinates":[15.06915,-7.63371],"type":"Point"}
}