{
  "type": "Feature",
  "properties": {
    "gn:admin1_code":"6.0",
    "gn:asciiname":"Capango",
    "gn:country_code":"AO",
    "gn:dem":1102,
    "gn:feature_class":"P",
    "gn:feature_code":"PPL",
    "gn:name":"Capango",
    "gn:population":0,
    "gn:timezone":"Africa/Luanda",
    "iso:country":"AO",
    "wof:name":"Capango",
    "wof:placetype":"locality"
},
  "geometry": {"coordinates":[14.42885,-10.82486],"type":"Point"}
}