{
  "type": "Feature",
  "properties": {
    "gn:admin1_code":"8.0",
    "gn:asciiname":"M. Mendes",
    "gn:cc2":"AO",
    "gn:country_code":"AO",
    "gn:dem":1490,
    "gn:feature_class":"P",
    "gn:feature_code":"PPL",
    "gn:name":"M. Mendes",
    "gn:population":0,
    "gn:timezone":"Africa/Luanda",
    "iso:country":"AO",
    "name:und_x_variant":[
        "Mendes",
        "M. Tunda",
        "M. Mendes"
    ],
    "wof:name":"M. Mendes",
    "wof:placetype":"locality"
},
  "geometry": {"coordinates":[15.91667,-12.38333],"type":"Point"}
}