{
  "type": "Feature",
  "properties": {
    "gn:admin1_code":"12.0",
    "gn:asciiname":"Coca",
    "gn:country_code":"AO",
    "gn:dem":1239,
    "gn:feature_class":"P",
    "gn:feature_code":"PPL",
    "gn:name":"Coca",
    "gn:population":0,
    "gn:timezone":"Africa/Luanda",
    "iso:country":"AO",
    "name:heb_x_preferred":[
        "\u05e7\u05d5\u05e7\u05d4"
    ],
    "name:ind_x_preferred":[
        "Koka"
    ],
    "name:vie_x_preferred":[
        "C\u00f4ca"
    ],
    "wof:name":"Coca",
    "wof:placetype":"locality"
},
  "geometry": {"coordinates":[15.88333,-8.28333],"type":"Point"}
}