{
  "type": "Feature",
  "properties": {
    "gn:admin1_code":"17.0",
    "gn:asciiname":"Nachir",
    "gn:cc2":"AO",
    "gn:country_code":"AO",
    "gn:dem":749,
    "gn:feature_class":"P",
    "gn:feature_code":"PPL",
    "gn:name":"Nachir",
    "gn:population":0,
    "gn:timezone":"Africa/Luanda",
    "iso:country":"AO",
    "name:und_x_variant":[
        "Sachir",
        "Nachir"
    ],
    "wof:name":"Nachir",
    "wof:placetype":"locality"
},
  "geometry": {"coordinates":[20.78333,-7.35],"type":"Point"}
}