{
  "type": "Feature",
  "properties": {
    "gn:admin1_code":"16.0",
    "gn:asciiname":"Mongo Soio",
    "gn:country_code":"AO",
    "gn:dem":38,
    "gn:feature_class":"P",
    "gn:feature_code":"PPL",
    "gn:name":"Mongo Soio",
    "gn:population":0,
    "gn:timezone":"Africa/Luanda",
    "iso:country":"AO",
    "wof:name":"Mongo Soio",
    "wof:placetype":"locality"
},
  "geometry": {"coordinates":[12.37884,-6.20613],"type":"Point"}
}