{
  "type": "Feature",
  "properties": {
    "gn:admin1_code":"15.0",
    "gn:asciiname":"Demba",
    "gn:country_code":"AO",
    "gn:dem":998,
    "gn:feature_class":"P",
    "gn:feature_code":"PPL",
    "gn:name":"Demba",
    "gn:population":0,
    "gn:timezone":"Africa/Luanda",
    "iso:country":"AO",
    "name:ceb_x_preferred":[
        "Demba"
    ],
    "name:deu_x_preferred":[
        "Demba"
    ],
    "name:ron_x_preferred":[
        "Demba"
    ],
    "name:swe_x_preferred":[
        "Demba"
    ],
    "wof:name":"Demba",
    "wof:placetype":"locality"
},
  "geometry": {"coordinates":[15.43333,-6.83333],"type":"Point"}
}