{
  "type": "Feature",
  "properties": {
    "gn:admin1_code":"5.0",
    "gn:asciiname":"Tabi Segundo",
    "gn:country_code":"AO",
    "gn:dem":1151,
    "gn:feature_class":"P",
    "gn:feature_code":"PPL",
    "gn:name":"Tabi Segundo",
    "gn:population":0,
    "gn:timezone":"Africa/Luanda",
    "iso:country":"AO",
    "wof:name":"Tabi Segundo",
    "wof:placetype":"locality"
},
  "geometry": {"coordinates":[15.42395,-8.62068],"type":"Point"}
}