{
  "type": "Feature",
  "properties": {
    "gn:admin1_code":"14.0",
    "gn:asciiname":"Chipuica",
    "gn:cc2":"AO",
    "gn:country_code":"AO",
    "gn:dem":1100,
    "gn:feature_class":"P",
    "gn:feature_code":"PPL",
    "gn:name":"Chipuica",
    "gn:population":0,
    "gn:timezone":"Africa/Luanda",
    "iso:country":"AO",
    "name:und_x_variant":[
        "Xipuica",
        "Chupuica",
        "Chipuica"
    ],
    "wof:name":"Chipuica",
    "wof:placetype":"locality"
},
  "geometry": {"coordinates":[22.16667,-10.73333],"type":"Point"}
}