{
  "type": "Feature",
  "properties": {
    "gn:admin1_code":"12.0",
    "gn:asciiname":"Muati",
    "gn:country_code":"AO",
    "gn:dem":1264,
    "gn:feature_class":"P",
    "gn:feature_code":"PPL",
    "gn:name":"Mu\u00e1ti",
    "gn:population":0,
    "gn:timezone":"Africa/Luanda",
    "iso:country":"AO",
    "wof:name":"Muati",
    "wof:placetype":"locality"
},
  "geometry": {"coordinates":[17.66536,-10.08159],"type":"Point"}
}