{
  "type": "Feature",
  "properties": {
    "gn:admin1_code":"9.0",
    "gn:asciiname":"Catchihondo",
    "gn:country_code":"AO",
    "gn:dem":1437,
    "gn:feature_class":"P",
    "gn:feature_code":"PPL",
    "gn:name":"Catchihondo",
    "gn:population":0,
    "gn:timezone":"Africa/Luanda",
    "iso:country":"AO",
    "wof:name":"Catchihondo",
    "wof:placetype":"locality"
},
  "geometry": {"coordinates":[15.98183,-14.61056],"type":"Point"}
}