{
  "type": "Feature",
  "properties": {
    "gn:admin1_code":"15.0",
    "gn:asciiname":"Tucu Maza",
    "gn:country_code":"AO",
    "gn:dem":905,
    "gn:feature_class":"P",
    "gn:feature_code":"PPL",
    "gn:name":"Tucu Maza",
    "gn:population":0,
    "gn:timezone":"Africa/Luanda",
    "iso:country":"AO",
    "name:und_x_variant":[
        "Tuco"
    ],
    "wof:name":"Tucu Maza",
    "wof:placetype":"locality"
},
  "geometry": {"coordinates":[15.09243,-6.08953],"type":"Point"}
}