{
  "type": "Feature",
  "properties": {
    "gn:admin1_code":"6.0",
    "gn:asciiname":"Ebo",
    "gn:country_code":"AO",
    "gn:dem":1359,
    "gn:feature_class":"P",
    "gn:feature_code":"PPL",
    "gn:name":"Ebo",
    "gn:population":0,
    "gn:timezone":"Africa/Luanda",
    "iso:country":"AO",
    "name:ceb_x_preferred":[
        "Ebo"
    ],
    "name:por_x_preferred":[
        "Ebo"
    ],
    "name:swe_x_preferred":[
        "Ebo"
    ],
    "wof:name":"Ebo",
    "wof:placetype":"locality"
},
  "geometry": {"coordinates":[14.71667,-11.05],"type":"Point"}
}