{
  "type": "Feature",
  "properties": {
    "gn:admin1_code":"6.0",
    "gn:asciiname":"Ndalambiri",
    "gn:country_code":"AO",
    "gn:dem":1276,
    "gn:feature_class":"P",
    "gn:feature_code":"PPL",
    "gn:name":"Ndalambiri",
    "gn:population":0,
    "gn:timezone":"Africa/Luanda",
    "iso:country":"AO",
    "wof:name":"Ndalambiri",
    "wof:placetype":"locality"
},
  "geometry": {"coordinates":[14.68109,-10.96703],"type":"Point"}
}