{
  "type": "Feature",
  "properties": {
    "gn:admin1_code":"15.0",
    "gn:asciiname":"Quiendissa",
    "gn:country_code":"AO",
    "gn:dem":938,
    "gn:feature_class":"P",
    "gn:feature_code":"PPL",
    "gn:name":"Quiendissa",
    "gn:population":0,
    "gn:timezone":"Africa/Luanda",
    "iso:country":"AO",
    "wof:name":"Quiendissa",
    "wof:placetype":"locality"
},
  "geometry": {"coordinates":[16.13184,-6.97906],"type":"Point"}
}