{
  "type": "Feature",
  "properties": {
    "gn:admin1_code":"15.0",
    "gn:asciiname":"Quissengue",
    "gn:country_code":"AO",
    "gn:dem":650,
    "gn:feature_class":"P",
    "gn:feature_code":"PPL",
    "gn:name":"Quissengue",
    "gn:population":0,
    "gn:timezone":"Africa/Luanda",
    "iso:country":"AO",
    "wof:name":"Quissengue",
    "wof:placetype":"locality"
},
  "geometry": {"coordinates":[14.85,-7.75],"type":"Point"}
}