{
  "type": "Feature",
  "properties": {
    "gn:admin1_code":"1.0",
    "gn:asciiname":"Fazenda Cupo",
    "gn:cc2":"AO",
    "gn:country_code":"AO",
    "gn:dem":1199,
    "gn:feature_class":"P",
    "gn:feature_code":"PPL",
    "gn:name":"Fazenda Cupo",
    "gn:population":0,
    "gn:timezone":"Africa/Luanda",
    "iso:country":"AO",
    "name:und_x_variant":[
        "Cupo",
        "Fazenda Cupo"
    ],
    "wof:name":"Fazenda Cupo",
    "wof:placetype":"locality"
},
  "geometry": {"coordinates":[14.56667,-12.25],"type":"Point"}
}