{
  "type": "Feature",
  "properties": {
    "gn:admin1_code":"12.0",
    "gn:asciiname":"Ndala Medile",
    "gn:country_code":"AO",
    "gn:dem":673,
    "gn:feature_class":"P",
    "gn:feature_code":"PPL",
    "gn:name":"Ndala Medile",
    "gn:population":0,
    "gn:timezone":"Africa/Luanda",
    "iso:country":"AO",
    "wof:name":"Ndala Medile",
    "wof:placetype":"locality"
},
  "geometry": {"coordinates":[16.71502000000001,-8.65467],"type":"Point"}
}