{
  "type": "Feature",
  "properties": {
    "gn:admin1_code":"9.0",
    "gn:asciiname":"Micossi",
    "gn:country_code":"AO",
    "gn:dem":1257,
    "gn:feature_class":"P",
    "gn:feature_code":"PPL",
    "gn:name":"Micossi",
    "gn:population":0,
    "gn:timezone":"Africa/Luanda",
    "iso:country":"AO",
    "name:und_x_variant":[
        "Micosse"
    ],
    "wof:name":"Micossi",
    "wof:placetype":"locality"
},
  "geometry": {"coordinates":[15.26188,-14.76721],"type":"Point"}
}