{
  "type": "Feature",
  "properties": {
    "gn:admin1_code":"15.0",
    "gn:asciiname":"Bula",
    "gn:country_code":"AO",
    "gn:dem":1047,
    "gn:feature_class":"P",
    "gn:feature_code":"PPL",
    "gn:name":"Bula",
    "gn:population":0,
    "gn:timezone":"Africa/Luanda",
    "iso:country":"AO",
    "wof:name":"Bula",
    "wof:placetype":"locality"
},
  "geometry": {"coordinates":[16.01687,-7.71171],"type":"Point"}
}