{
  "type": "Feature",
  "properties": {
    "gn:admin1_code":"17.0",
    "gn:asciiname":"Sauianga",
    "gn:country_code":"AO",
    "gn:dem":1198,
    "gn:feature_class":"P",
    "gn:feature_code":"PPL",
    "gn:name":"Sauianga",
    "gn:population":0,
    "gn:timezone":"Africa/Luanda",
    "iso:country":"AO",
    "wof:name":"Sauianga",
    "wof:placetype":"locality"
},
  "geometry": {"coordinates":[18.97765,-8.5559],"type":"Point"}
}