{
  "type": "Feature",
  "properties": {
    "gn:admin1_code":"4.0",
    "gn:asciiname":"Mucuio",
    "gn:country_code":"AO",
    "gn:dem":1152,
    "gn:feature_class":"P",
    "gn:feature_code":"PPL",
    "gn:name":"Mucuio",
    "gn:population":0,
    "gn:timezone":"Africa/Luanda",
    "iso:country":"AO",
    "wof:name":"Mucuio",
    "wof:placetype":"locality"
},
  "geometry": {"coordinates":[18.05,-16.88332999999999],"type":"Point"}
}