{
  "type": "Feature",
  "properties": {
    "gn:admin1_code":"17.0",
    "gn:asciiname":"Cabinza",
    "gn:country_code":"AO",
    "gn:dem":731,
    "gn:feature_class":"P",
    "gn:feature_code":"PPL",
    "gn:name":"Cabinza",
    "gn:population":0,
    "gn:timezone":"Africa/Luanda",
    "iso:country":"AO",
    "wof:name":"Cabinza",
    "wof:placetype":"locality"
},
  "geometry": {"coordinates":[21.15449,-7.37516],"type":"Point"}
}