{
  "type": "Feature",
  "properties": {
    "gn:admin1_code":"6.0",
    "gn:asciiname":"Quitila",
    "gn:country_code":"AO",
    "gn:dem":1143,
    "gn:feature_class":"P",
    "gn:feature_code":"PPL",
    "gn:name":"Quitila",
    "gn:population":0,
    "gn:timezone":"Africa/Luanda",
    "iso:country":"AO",
    "wof:name":"Quitila",
    "wof:placetype":"locality"
},
  "geometry": {"coordinates":[14.93016,-10.14723],"type":"Point"}
}