{
  "type": "Feature",
  "properties": {
    "gn:admin1_code":"17.0",
    "gn:asciiname":"Calanga",
    "gn:country_code":"AO",
    "gn:dem":790,
    "gn:feature_class":"P",
    "gn:feature_code":"PPL",
    "gn:name":"Calanga",
    "gn:population":0,
    "gn:timezone":"Africa/Luanda",
    "iso:country":"AO",
    "wof:name":"Calanga",
    "wof:placetype":"locality"
},
  "geometry": {"coordinates":[17.83333,-8.75],"type":"Point"}
}