{
  "type": "Feature",
  "properties": {
    "gn:admin1_code":"19.0",
    "gn:asciiname":"Casseno Primeiro",
    "gn:country_code":"AO",
    "gn:dem":815,
    "gn:feature_class":"P",
    "gn:feature_code":"PPL",
    "gn:name":"Casseno Primeiro",
    "gn:population":0,
    "gn:timezone":"Africa/Luanda",
    "iso:country":"AO",
    "wof:name":"Casseno Primeiro",
    "wof:placetype":"locality"
},
  "geometry": {"coordinates":[14.80377,-8.72849],"type":"Point"}
}