{
  "type": "Feature",
  "properties": {
    "gn:admin1_code":"6.0",
    "gn:asciiname":"Massango",
    "gn:country_code":"AO",
    "gn:dem":391,
    "gn:feature_class":"P",
    "gn:feature_code":"PPL",
    "gn:name":"Massango",
    "gn:population":0,
    "gn:timezone":"Africa/Luanda",
    "iso:country":"AO",
    "wof:name":"Massango",
    "wof:placetype":"locality"
},
  "geometry": {"coordinates":[14.29761,-10.55449],"type":"Point"}
}