{
  "type": "Feature",
  "properties": {
    "gn:admin1_code":"9.0",
    "gn:asciiname":"Quenha",
    "gn:country_code":"AO",
    "gn:dem":1283,
    "gn:feature_class":"P",
    "gn:feature_code":"PPLL",
    "gn:name":"Quenha",
    "gn:population":0,
    "gn:timezone":"Africa/Luanda",
    "iso:country":"AO",
    "wof:name":"Quenha",
    "wof:placetype":"locality"
},
  "geometry": {"coordinates":[15.46906,-14.88747],"type":"Point"}
}