{
  "type": "Feature",
  "properties": {
    "gn:admin1_code":"8.0",
    "gn:asciiname":"Cossito I",
    "gn:cc2":"AO",
    "gn:country_code":"AO",
    "gn:dem":1774,
    "gn:feature_class":"P",
    "gn:feature_code":"PPL",
    "gn:name":"Cossito I",
    "gn:population":0,
    "gn:timezone":"Africa/Luanda",
    "iso:country":"AO",
    "name:und_x_variant":[
        "Cocito",
        "Cassito",
        "Cossilo",
        "Cossito I"
    ],
    "wof:name":"Cossito I",
    "wof:placetype":"locality"
},
  "geometry": {"coordinates":[15.48694,-12.9025],"type":"Point"}
}