{
  "type": "Feature",
  "properties": {
    "gn:admin1_code":"12.0",
    "gn:asciiname":"Mangangi",
    "gn:country_code":"AO",
    "gn:dem":1089,
    "gn:feature_class":"P",
    "gn:feature_code":"PPL",
    "gn:name":"Mangangi",
    "gn:population":0,
    "gn:timezone":"Africa/Luanda",
    "iso:country":"AO",
    "wof:name":"Mangangi",
    "wof:placetype":"locality"
},
  "geometry": {"coordinates":[16.06905,-9.38387],"type":"Point"}
}