{
  "type": "Feature",
  "properties": {
    "gn:admin1_code":"7.0",
    "gn:asciiname":"Muhoto",
    "gn:country_code":"AO",
    "gn:dem":1039,
    "gn:feature_class":"P",
    "gn:feature_code":"PPL",
    "gn:name":"Muhoto",
    "gn:population":0,
    "gn:timezone":"Africa/Luanda",
    "iso:country":"AO",
    "wof:name":"Muhoto",
    "wof:placetype":"locality"
},
  "geometry": {"coordinates":[14.28333,-17.25],"type":"Point"}
}