{
  "type": "Feature",
  "properties": {
    "gn:admin1_code":"18.0",
    "gn:asciiname":"Camagicua",
    "gn:country_code":"AO",
    "gn:dem":945,
    "gn:feature_class":"P",
    "gn:feature_code":"PPL",
    "gn:name":"Camagicua",
    "gn:population":0,
    "gn:timezone":"Africa/Luanda",
    "iso:country":"AO",
    "wof:name":"Camagicua",
    "wof:placetype":"locality"
},
  "geometry": {"coordinates":[20.45583,-9.0131],"type":"Point"}
}