{
  "type": "Feature",
  "properties": {
    "gn:admin1_code":"15.0",
    "gn:asciiname":"Quimbila",
    "gn:country_code":"AO",
    "gn:dem":917,
    "gn:feature_class":"P",
    "gn:feature_code":"PPL",
    "gn:name":"Quimbila",
    "gn:population":0,
    "gn:timezone":"Africa/Luanda",
    "iso:country":"AO",
    "wof:name":"Quimbila",
    "wof:placetype":"locality"
},
  "geometry": {"coordinates":[15.26682,-6.39062],"type":"Point"}
}