{
  "type": "Feature",
  "properties": {
    "gn:admin1_code":"18.0",
    "gn:asciiname":"Sacatechongo",
    "gn:country_code":"AO",
    "gn:dem":1218,
    "gn:feature_class":"P",
    "gn:feature_code":"PPL",
    "gn:name":"Sacatechongo",
    "gn:population":0,
    "gn:timezone":"Africa/Luanda",
    "iso:country":"AO",
    "wof:name":"Sacatechongo",
    "wof:placetype":"locality"
},
  "geometry": {"coordinates":[20.45111,-10.91611],"type":"Point"}
}