{
  "type": "Feature",
  "properties": {
    "gn:admin1_code":"15.0",
    "gn:asciiname":"Cuissa-Salco",
    "gn:country_code":"AO",
    "gn:dem":965,
    "gn:feature_class":"P",
    "gn:feature_code":"PPL",
    "gn:name":"Cuissa-Sal\u00e7o",
    "gn:population":0,
    "gn:timezone":"Africa/Luanda",
    "iso:country":"AO",
    "wof:name":"Cuissa-Salco",
    "wof:placetype":"locality"
},
  "geometry": {"coordinates":[15.81827,-6.68563],"type":"Point"}
}