{
  "type": "Feature",
  "properties": {
    "gn:admin1_code":"18.0",
    "gn:asciiname":"Muacuango",
    "gn:country_code":"AO",
    "gn:dem":1324,
    "gn:feature_class":"P",
    "gn:feature_code":"PPL",
    "gn:name":"Muacuango",
    "gn:population":0,
    "gn:timezone":"Africa/Luanda",
    "iso:country":"AO",
    "wof:name":"Muacuango",
    "wof:placetype":"locality"
},
  "geometry": {"coordinates":[19.13656,-10.82478],"type":"Point"}
}