{
  "type": "Feature",
  "properties": {
    "gn:admin1_code":"6.0",
    "gn:asciiname":"Paca",
    "gn:country_code":"AO",
    "gn:dem":1131,
    "gn:feature_class":"P",
    "gn:feature_code":"PPL",
    "gn:name":"Paca",
    "gn:population":0,
    "gn:timezone":"Africa/Luanda",
    "iso:country":"AO",
    "wof:name":"Paca",
    "wof:placetype":"locality"
},
  "geometry": {"coordinates":[15.06461,-10.10948],"type":"Point"}
}