{
  "type": "Feature",
  "properties": {
    "gn:admin1_code":"15.0",
    "gn:asciiname":"Quinzola",
    "gn:country_code":"AO",
    "gn:dem":849,
    "gn:feature_class":"P",
    "gn:feature_code":"PPL",
    "gn:name":"Quinzola",
    "gn:population":0,
    "gn:timezone":"Africa/Luanda",
    "iso:country":"AO",
    "wof:name":"Quinzola",
    "wof:placetype":"locality"
},
  "geometry": {"coordinates":[15.12549,-5.88947],"type":"Point"}
}