{
  "type": "Feature",
  "properties": {
    "gn:admin1_code":"14.0",
    "gn:asciiname":"Chiember",
    "gn:cc2":"AO",
    "gn:country_code":"AO",
    "gn:dem":1084,
    "gn:feature_class":"P",
    "gn:feature_code":"PPL",
    "gn:name":"Chiember",
    "gn:population":0,
    "gn:timezone":"Africa/Luanda",
    "iso:country":"AO",
    "name:und_x_variant":[
        "Chienga",
        "Chiember"
    ],
    "wof:name":"Chiember",
    "wof:placetype":"locality"
},
  "geometry": {"coordinates":[21.63333,-13.81667],"type":"Point"}
}