{
  "type": "Feature",
  "properties": {
    "gn:admin1_code":"16.0",
    "gn:asciiname":"Luvovambo",
    "gn:country_code":"AO",
    "gn:dem":543,
    "gn:feature_class":"P",
    "gn:feature_code":"PPL",
    "gn:name":"Luvovambo",
    "gn:population":0,
    "gn:timezone":"Africa/Luanda",
    "iso:country":"AO",
    "wof:name":"Luvovambo",
    "wof:placetype":"locality"
},
  "geometry": {"coordinates":[14.48333,-6.16667],"type":"Point"}
}