{
  "type": "Feature",
  "properties": {
    "gn:admin1_code":"6.0",
    "gn:asciiname":"Cassoco Grande",
    "gn:country_code":"AO",
    "gn:dem":1410,
    "gn:feature_class":"P",
    "gn:feature_code":"PPL",
    "gn:name":"Casso\u00e7o Grande",
    "gn:population":0,
    "gn:timezone":"Africa/Luanda",
    "iso:country":"AO",
    "wof:name":"Cassoco Grande",
    "wof:placetype":"locality"
},
  "geometry": {"coordinates":[15.2858,-11.33431],"type":"Point"}
}