{
  "type": "Feature",
  "properties": {
    "gn:admin1_code":"12.0",
    "gn:asciiname":"Quinjango",
    "gn:country_code":"AO",
    "gn:dem":1221,
    "gn:feature_class":"P",
    "gn:feature_code":"PPL",
    "gn:name":"Quinjango",
    "gn:population":0,
    "gn:timezone":"Africa/Luanda",
    "iso:country":"AO",
    "wof:name":"Quinjango",
    "wof:placetype":"locality"
},
  "geometry": {"coordinates":[16.37501,-8.81128],"type":"Point"}
}