{
  "type": "Feature",
  "properties": {
    "gn:admin1_code":"18.0",
    "gn:asciiname":"Samuimba",
    "gn:cc2":"AO",
    "gn:country_code":"AO",
    "gn:dem":1182,
    "gn:feature_class":"P",
    "gn:feature_code":"PPL",
    "gn:name":"Samuimba",
    "gn:population":0,
    "gn:timezone":"Africa/Luanda",
    "iso:country":"AO",
    "name:und_x_variant":[
        "Chalumba",
        "Samuimba"
    ],
    "wof:name":"Samuimba",
    "wof:placetype":"locality"
},
  "geometry": {"coordinates":[20.11667000000001,-10.35],"type":"Point"}
}