{
  "type": "Feature",
  "properties": {
    "gn:admin1_code":"9.0",
    "gn:asciiname":"Cutenda",
    "gn:country_code":"AO",
    "gn:dem":1300,
    "gn:feature_class":"P",
    "gn:feature_code":"PPL",
    "gn:name":"Cutenda",
    "gn:population":0,
    "gn:timezone":"Africa/Luanda",
    "iso:country":"AO",
    "name:msa_x_preferred":[
        "Kutenda"
    ],
    "name:por_x_preferred":[
        "Kutenda"
    ],
    "wof:name":"Cutenda",
    "wof:placetype":"locality"
},
  "geometry": {"coordinates":[15.08333,-14.36667],"type":"Point"}
}