{
  "type": "Feature",
  "properties": {
    "gn:admin1_code":"19.0",
    "gn:asciiname":"Piri",
    "gn:country_code":"AO",
    "gn:dem":695,
    "gn:feature_class":"P",
    "gn:feature_code":"PPL",
    "gn:name":"Piri",
    "gn:population":0,
    "gn:timezone":"Africa/Luanda",
    "iso:country":"AO",
    "name:cat_x_preferred":[
        "Piri"
    ],
    "name:msa_x_preferred":[
        "Piri"
    ],
    "name:por_x_preferred":[
        "Piri"
    ],
    "wof:name":"Piri",
    "wof:placetype":"locality"
},
  "geometry": {"coordinates":[14.43555,-8.53412],"type":"Point"}
}