{
  "type": "Feature",
  "properties": {
    "gn:admin1_code":"8.0",
    "gn:asciiname":"Kasenje",
    "gn:country_code":"AO",
    "gn:dem":1562,
    "gn:feature_class":"P",
    "gn:feature_code":"PPL",
    "gn:name":"Kasenje",
    "gn:population":0,
    "gn:timezone":"Africa/Luanda",
    "iso:country":"AO",
    "wof:name":"Kasenje",
    "wof:placetype":"locality"
},
  "geometry": {"coordinates":[15.48333,-12.45],"type":"Point"}
}