{
  "type": "Feature",
  "properties": {
    "gn:admin1_code":"15.0",
    "gn:asciiname":"Quivingue",
    "gn:country_code":"AO",
    "gn:dem":1027,
    "gn:feature_class":"P",
    "gn:feature_code":"PPL",
    "gn:name":"Quivingue",
    "gn:population":0,
    "gn:timezone":"Africa/Luanda",
    "iso:country":"AO",
    "wof:name":"Quivingue",
    "wof:placetype":"locality"
},
  "geometry": {"coordinates":[15.18333,-6.66667],"type":"Point"}
}