{
  "type": "Feature",
  "properties": {
    "gn:admin1_code":"12.0",
    "gn:asciiname":"Utende",
    "gn:country_code":"AO",
    "gn:dem":1067,
    "gn:feature_class":"P",
    "gn:feature_code":"PPL",
    "gn:name":"Utende",
    "gn:population":0,
    "gn:timezone":"Africa/Luanda",
    "iso:country":"AO",
    "wof:name":"Utende",
    "wof:placetype":"locality"
},
  "geometry": {"coordinates":[16.41861,-9.69972],"type":"Point"}
}