{
  "type": "Feature",
  "properties": {
    "gn:admin1_code":"8.0",
    "gn:asciiname":"Sambemba",
    "gn:country_code":"AO",
    "gn:dem":1807,
    "gn:feature_class":"P",
    "gn:feature_code":"PPL",
    "gn:name":"Sambemba",
    "gn:population":0,
    "gn:timezone":"Africa/Luanda",
    "iso:country":"AO",
    "wof:name":"Sambemba",
    "wof:placetype":"locality"
},
  "geometry": {"coordinates":[15.4375,-12.60528],"type":"Point"}
}