{
  "type": "Feature",
  "properties": {
    "gn:admin1_code":"18.0",
    "gn:asciiname":"Cavuma",
    "gn:country_code":"AO",
    "gn:dem":1184,
    "gn:feature_class":"P",
    "gn:feature_code":"PPL",
    "gn:name":"Cavuma",
    "gn:population":0,
    "gn:timezone":"Africa/Luanda",
    "iso:country":"AO",
    "wof:name":"Cavuma",
    "wof:placetype":"locality"
},
  "geometry": {"coordinates":[20.64087,-11.0254],"type":"Point"}
}