{
  "type": "Feature",
  "properties": {
    "gn:admin1_code":"14.0",
    "gn:asciiname":"Caripande",
    "gn:cc2":"AO",
    "gn:country_code":"AO",
    "gn:dem":1087,
    "gn:feature_class":"P",
    "gn:feature_code":"PPL",
    "gn:name":"Caripande",
    "gn:population":0,
    "gn:timezone":"Africa/Luanda",
    "iso:country":"AO",
    "name:und_x_variant":[
        "Chepena",
        "Caripande"
    ],
    "wof:name":"Caripande",
    "wof:placetype":"locality"
},
  "geometry": {"coordinates":[22.73333,-12.98333],"type":"Point"}
}