{
  "type": "Feature",
  "properties": {
    "gn:admin1_code":"17.0",
    "gn:asciiname":"Cabana",
    "gn:country_code":"AO",
    "gn:dem":897,
    "gn:feature_class":"P",
    "gn:feature_code":"PPL",
    "gn:name":"Cabana",
    "gn:population":0,
    "gn:timezone":"Africa/Luanda",
    "iso:country":"AO",
    "wof:name":"Cabana",
    "wof:placetype":"locality"
},
  "geometry": {"coordinates":[18.21667,-9.46667],"type":"Point"}
}