{
  "type": "Feature",
  "properties": {
    "gn:admin1_code":"12.0",
    "gn:asciiname":"Mangumbo",
    "gn:country_code":"AO",
    "gn:dem":951,
    "gn:feature_class":"P",
    "gn:feature_code":"PPL",
    "gn:name":"Mangumbo",
    "gn:population":0,
    "gn:timezone":"Africa/Luanda",
    "iso:country":"AO",
    "wof:name":"Mangumbo",
    "wof:placetype":"locality"
},
  "geometry": {"coordinates":[16.50416,-7.92004],"type":"Point"}
}