{
  "type": "Feature",
  "properties": {
    "gn:admin1_code":"12.0",
    "gn:asciiname":"Quiocundo",
    "gn:country_code":"AO",
    "gn:dem":928,
    "gn:feature_class":"P",
    "gn:feature_code":"PPL",
    "gn:name":"Quiocundo",
    "gn:population":0,
    "gn:timezone":"Africa/Luanda",
    "iso:country":"AO",
    "wof:name":"Quiocundo",
    "wof:placetype":"locality"
},
  "geometry": {"coordinates":[15.5536,-9.18042],"type":"Point"}
}