{
  "type": "Feature",
  "properties": {
    "gn:admin1_code":"15.0",
    "gn:asciiname":"Quiteca",
    "gn:country_code":"AO",
    "gn:dem":1094,
    "gn:feature_class":"P",
    "gn:feature_code":"PPL",
    "gn:name":"Quiteca",
    "gn:population":0,
    "gn:timezone":"Africa/Luanda",
    "iso:country":"AO",
    "wof:name":"Quiteca",
    "wof:placetype":"locality"
},
  "geometry": {"coordinates":[15.22239,-6.91646],"type":"Point"}
}