{
  "type": "Feature",
  "properties": {
    "gn:admin1_code":"9.0",
    "gn:asciiname":"Sosinho",
    "gn:country_code":"AO",
    "gn:dem":1436,
    "gn:feature_class":"P",
    "gn:feature_code":"PPL",
    "gn:name":"S\u00f3sinho",
    "gn:population":0,
    "gn:timezone":"Africa/Luanda",
    "iso:country":"AO",
    "wof:name":"Sosinho",
    "wof:placetype":"locality"
},
  "geometry": {"coordinates":[15.70483,-14.62052],"type":"Point"}
}