{
  "type": "Feature",
  "properties": {
    "gn:admin1_code":"16.0",
    "gn:asciiname":"Quindegi",
    "gn:country_code":"AO",
    "gn:dem":581,
    "gn:feature_class":"P",
    "gn:feature_code":"PPL",
    "gn:name":"Quindegi",
    "gn:population":0,
    "gn:timezone":"Africa/Luanda",
    "iso:country":"AO",
    "name:und_x_variant":[
        "Quindege",
        "Beca Monteira",
        "Quinoeje",
        "Bessa Monteiro",
        "Quindeje",
        "Be\u00e7a Monteiro",
        "Besa Monteiro",
        "Kindeje",
        "Quindegi"
    ],
    "wof:name":"Quindegi",
    "wof:placetype":"locality"
},
  "geometry": {"coordinates":[13.63689,-7.15648],"type":"Point"}
}