{
  "type": "Feature",
  "properties": {
    "gn:admin1_code":"16.0",
    "gn:asciiname":"Quicumbi",
    "gn:country_code":"AO",
    "gn:dem":89,
    "gn:feature_class":"P",
    "gn:feature_code":"PPL",
    "gn:name":"Quicumbi",
    "gn:population":0,
    "gn:timezone":"Africa/Luanda",
    "iso:country":"AO",
    "wof:name":"Quicumbi",
    "wof:placetype":"locality"
},
  "geometry": {"coordinates":[13.03333,-6.61667],"type":"Point"}
}