{
  "type": "Feature",
  "properties": {
    "gn:admin1_code":"16.0",
    "gn:asciiname":"Quivola",
    "gn:country_code":"AO",
    "gn:dem":325,
    "gn:feature_class":"P",
    "gn:feature_code":"PPL",
    "gn:name":"Quivola",
    "gn:population":0,
    "gn:timezone":"Africa/Luanda",
    "iso:country":"AO",
    "wof:name":"Quivola",
    "wof:placetype":"locality"
},
  "geometry": {"coordinates":[13.57861,-6.0153],"type":"Point"}
}