{
  "type": "Feature",
  "properties": {
    "gn:admin1_code":"15.0",
    "gn:asciiname":"Quijoao",
    "gn:country_code":"AO",
    "gn:dem":730,
    "gn:feature_class":"P",
    "gn:feature_code":"PPL",
    "gn:name":"Quijo\u00e3o",
    "gn:population":0,
    "gn:timezone":"Africa/Luanda",
    "iso:country":"AO",
    "name:por_x_preferred":[
        "Quijo\u00e3o"
    ],
    "name:und_x_variant":[
        "Quimojungo",
        "Quijo\u00e3o"
    ],
    "wof:name":"Quijoao",
    "wof:placetype":"locality"
},
  "geometry": {"coordinates":[16.44418,-6.31136],"type":"Point"}
}