{
  "type": "Feature",
  "properties": {
    "gn:admin1_code":"6.0",
    "gn:asciiname":"Quitambi",
    "gn:country_code":"AO",
    "gn:dem":1120,
    "gn:feature_class":"P",
    "gn:feature_code":"PPL",
    "gn:name":"Quitambi",
    "gn:population":0,
    "gn:timezone":"Africa/Luanda",
    "iso:country":"AO",
    "wof:name":"Quitambi",
    "wof:placetype":"locality"
},
  "geometry": {"coordinates":[14.74603,-10.69298],"type":"Point"}
}