{
  "type": "Feature",
  "properties": {
    "gn:admin1_code":"4.0",
    "gn:asciiname":"Lilondo",
    "gn:cc2":"AO",
    "gn:country_code":"AO",
    "gn:dem":1116,
    "gn:feature_class":"P",
    "gn:feature_code":"PPL",
    "gn:name":"Lilondo",
    "gn:population":0,
    "gn:timezone":"Africa/Luanda",
    "iso:country":"AO",
    "name:und_x_variant":[
        "Rilondo",
        "Lilondo"
    ],
    "wof:name":"Lilondo",
    "wof:placetype":"locality"
},
  "geometry": {"coordinates":[19.28333,-16.88332999999999],"type":"Point"}
}