{
  "type": "Feature",
  "properties": {
    "gn:admin1_code":"14.0",
    "gn:asciiname":"Cauina",
    "gn:cc2":"AO",
    "gn:country_code":"AO",
    "gn:dem":1081,
    "gn:feature_class":"P",
    "gn:feature_code":"PPL",
    "gn:name":"Cauina",
    "gn:population":0,
    "gn:timezone":"Africa/Luanda",
    "iso:country":"AO",
    "name:und_x_variant":[
        "Canhima",
        "Cauina"
    ],
    "wof:name":"Cauina",
    "wof:placetype":"locality"
},
  "geometry": {"coordinates":[22.56667,-11.68333],"type":"Point"}
}