{
  "type": "Feature",
  "properties": {
    "gn:admin1_code":"5.0",
    "gn:asciiname":"Mucoso",
    "gn:country_code":"AO",
    "gn:dem":283,
    "gn:feature_class":"P",
    "gn:feature_code":"PPL",
    "gn:name":"Mucoso",
    "gn:population":0,
    "gn:timezone":"Africa/Luanda",
    "iso:country":"AO",
    "name:und_x_variant":[
        "Mucozo",
        "Mucoso"
    ],
    "wof:name":"Mucoso",
    "wof:placetype":"locality"
},
  "geometry": {"coordinates":[14.65594,-9.53658],"type":"Point"}
}