{
  "type": "Feature",
  "properties": {
    "gn:admin1_code":"14.0",
    "gn:asciiname":"Luvuei",
    "gn:country_code":"AO",
    "gn:dem":1136,
    "gn:feature_class":"P",
    "gn:feature_code":"PPL",
    "gn:name":"Luvuei",
    "gn:population":0,
    "gn:timezone":"Africa/Luanda",
    "iso:country":"AO",
    "wof:name":"Luvuei",
    "wof:placetype":"locality"
},
  "geometry": {"coordinates":[21.16667,-13.06667],"type":"Point"}
}