{
  "type": "Feature",
  "properties": {
    "gn:admin1_code":"8.0",
    "gn:asciiname":"Thela",
    "gn:country_code":"AO",
    "gn:dem":1471,
    "gn:feature_class":"P",
    "gn:feature_code":"PPL",
    "gn:name":"Thela",
    "gn:population":0,
    "gn:timezone":"Africa/Luanda",
    "iso:country":"AO",
    "wof:name":"Thela",
    "wof:placetype":"locality"
},
  "geometry": {"coordinates":[15.30282,-12.0619],"type":"Point"}
}