{
  "type": "Feature",
  "properties": {
    "gn:admin1_code":"15.0",
    "gn:asciiname":"Vuma",
    "gn:cc2":"AO",
    "gn:country_code":"AO",
    "gn:dem":680,
    "gn:feature_class":"P",
    "gn:feature_code":"PPL",
    "gn:name":"Vuma",
    "gn:population":0,
    "gn:timezone":"Africa/Luanda",
    "iso:country":"AO",
    "name:und_x_variant":[
        "Quivemba",
        "Vuma"
    ],
    "wof:name":"Vuma",
    "wof:placetype":"locality"
},
  "geometry": {"coordinates":[14.91667,-5.86667],"type":"Point"}
}