{
  "type": "Feature",
  "properties": {
    "gn:admin1_code":"12.0",
    "gn:asciiname":"Cabadi",
    "gn:country_code":"AO",
    "gn:dem":1264,
    "gn:feature_class":"P",
    "gn:feature_code":"PPL",
    "gn:name":"Cabadi",
    "gn:population":0,
    "gn:timezone":"Africa/Luanda",
    "iso:country":"AO",
    "wof:name":"Cabadi",
    "wof:placetype":"locality"
},
  "geometry": {"coordinates":[16.06087999999999,-8.36885],"type":"Point"}
}