{
  "type": "Feature",
  "properties": {
    "gn:admin1_code":"18.0",
    "gn:asciiname":"Calombuegi",
    "gn:country_code":"AO",
    "gn:dem":1183,
    "gn:feature_class":"P",
    "gn:feature_code":"PPL",
    "gn:name":"Calombuegi",
    "gn:population":0,
    "gn:timezone":"Africa/Luanda",
    "iso:country":"AO",
    "wof:name":"Calombuegi",
    "wof:placetype":"locality"
},
  "geometry": {"coordinates":[19.93891,-9.94226],"type":"Point"}
}