{
  "type": "Feature",
  "properties": {
    "gn:admin1_code":"0.0",
    "gn:asciiname":"Nutaca",
    "gn:country_code":"AO",
    "gn:dem":26,
    "gn:feature_class":"P",
    "gn:feature_code":"PPL",
    "gn:name":"Nutaca",
    "gn:population":0,
    "gn:timezone":"Africa/Luanda",
    "iso:country":"AO",
    "wof:name":"Nutaca",
    "wof:placetype":"locality"
},
  "geometry": {"coordinates":[13.55667,-12.39194],"type":"Point"}
}