{
  "type": "Feature",
  "properties": {
    "gn:admin1_code":"5.0",
    "gn:asciiname":"Luege",
    "gn:country_code":"AO",
    "gn:dem":1303,
    "gn:feature_class":"P",
    "gn:feature_code":"PPL",
    "gn:name":"Lu\u00e9ge",
    "gn:population":0,
    "gn:timezone":"Africa/Luanda",
    "iso:country":"AO",
    "wof:name":"Luege",
    "wof:placetype":"locality"
},
  "geometry": {"coordinates":[15.56667,-8.85],"type":"Point"}
}