{
  "type": "Feature",
  "properties": {
    "gn:admin1_code":"2.0",
    "gn:asciiname":"Bembe",
    "gn:country_code":"AO",
    "gn:dem":1497,
    "gn:feature_class":"P",
    "gn:feature_code":"PPL",
    "gn:name":"Bembe",
    "gn:population":0,
    "gn:timezone":"Africa/Luanda",
    "iso:country":"AO",
    "name:ast_x_preferred":[
        "Bembe"
    ],
    "name:cat_x_preferred":[
        "Bembe"
    ],
    "name:deu_x_preferred":[
        "Bembe"
    ],
    "name:ita_x_preferred":[
        "Bembe"
    ],
    "name:msa_x_preferred":[
        "Bembe"
    ],
    "name:por_x_preferred":[
        "Bembe"
    ],
    "name:spa_x_preferred":[
        "Bembe"
    ],
    "name:zho_x_preferred":[
        "\u672c\u8c9d"
    ],
    "wof:name":"Bembe",
    "wof:placetype":"locality"
},
  "geometry": {"coordinates":[17.18333,-13.96667],"type":"Point"}
}