{
  "type": "Feature",
  "properties": {
    "gn:admin1_code":"17.0",
    "gn:asciiname":"Tchamufuca",
    "gn:country_code":"AO",
    "gn:dem":869,
    "gn:feature_class":"P",
    "gn:feature_code":"PPL",
    "gn:name":"Tchamufuca",
    "gn:population":0,
    "gn:timezone":"Africa/Luanda",
    "iso:country":"AO",
    "name:und_x_variant":[
        "Mafuca",
        "Samufuca",
        "Tchamufuca"
    ],
    "wof:name":"Tchamufuca",
    "wof:placetype":"locality"
},
  "geometry": {"coordinates":[21.0617,-8.26741],"type":"Point"}
}