{
  "type": "Feature",
  "properties": {
    "gn:admin1_code":"18.0",
    "gn:asciiname":"Sacambunge",
    "gn:country_code":"AO",
    "gn:dem":998,
    "gn:feature_class":"P",
    "gn:feature_code":"PPL",
    "gn:name":"Sacambunge",
    "gn:population":0,
    "gn:timezone":"Africa/Luanda",
    "iso:country":"AO",
    "name:und_x_variant":[
        "Sakambundji",
        "Sacambunge"
    ],
    "wof:name":"Sacambunge",
    "wof:placetype":"locality"
},
  "geometry": {"coordinates":[22.2291,-10.41355],"type":"Point"}
}