{
  "type": "Feature",
  "properties": {
    "gn:admin1_code":"17.0",
    "gn:asciiname":"Muamugina",
    "gn:country_code":"AO",
    "gn:dem":1174,
    "gn:feature_class":"P",
    "gn:feature_code":"PPL",
    "gn:name":"Muamugina",
    "gn:population":0,
    "gn:timezone":"Africa/Luanda",
    "iso:country":"AO",
    "wof:name":"Muamugina",
    "wof:placetype":"locality"
},
  "geometry": {"coordinates":[18.3688,-10.06959],"type":"Point"}
}