{
  "type": "Feature",
  "properties": {
    "gn:admin1_code":"0.0",
    "gn:asciiname":"Uche",
    "gn:country_code":"AO",
    "gn:dem":60,
    "gn:feature_class":"P",
    "gn:feature_code":"PPL",
    "gn:name":"Uche",
    "gn:population":0,
    "gn:timezone":"Africa/Luanda",
    "iso:country":"AO",
    "name:ceb_x_preferred":[
        "Uche"
    ],
    "name:deu_x_preferred":[
        "Uche"
    ],
    "name:nds_x_preferred":[
        "Uche"
    ],
    "name:spa_x_preferred":[
        "Uche"
    ],
    "name:swe_x_preferred":[
        "Uche"
    ],
    "wof:name":"Uche",
    "wof:placetype":"locality"
},
  "geometry": {"coordinates":[13.3725,-12.6625],"type":"Point"}
}