{
  "type": "Feature",
  "properties": {
    "gn:admin1_code":"9.0",
    "gn:asciiname":"Cachicala",
    "gn:cc2":"AO",
    "gn:country_code":"AO",
    "gn:dem":1439,
    "gn:feature_class":"P",
    "gn:feature_code":"PPL",
    "gn:name":"Cachicala",
    "gn:population":0,
    "gn:timezone":"Africa/Luanda",
    "iso:country":"AO",
    "name:und_x_variant":[
        "Cherequera",
        "Cachicala"
    ],
    "wof:name":"Cachicala",
    "wof:placetype":"locality"
},
  "geometry": {"coordinates":[15.35,-14.03333],"type":"Point"}
}