{
  "type": "Feature",
  "properties": {
    "gn:admin1_code":"12.0",
    "gn:asciiname":"Zaila Ngola",
    "gn:country_code":"AO",
    "gn:dem":1144,
    "gn:feature_class":"P",
    "gn:feature_code":"PPL",
    "gn:name":"Za\u00edla Ngola",
    "gn:population":0,
    "gn:timezone":"Africa/Luanda",
    "iso:country":"AO",
    "wof:name":"Zaila Ngola",
    "wof:placetype":"locality"
},
  "geometry": {"coordinates":[15.90316,-8.94621],"type":"Point"}
}