{
  "type": "Feature",
  "properties": {
    "gn:admin1_code":"17.0",
    "gn:asciiname":"Sucumuna",
    "gn:country_code":"AO",
    "gn:dem":1227,
    "gn:feature_class":"P",
    "gn:feature_code":"PPL",
    "gn:name":"Sucumuna",
    "gn:population":0,
    "gn:timezone":"Africa/Luanda",
    "iso:country":"AO",
    "name:und_x_variant":[
        "Sukumuna",
        "Sucumuna"
    ],
    "wof:name":"Sucumuna",
    "wof:placetype":"locality"
},
  "geometry": {"coordinates":[19.28062000000001,-9.39082],"type":"Point"}
}