{
  "type": "Feature",
  "properties": {
    "gn:admin1_code":"0.0",
    "gn:asciiname":"Chimuco",
    "gn:country_code":"AO",
    "gn:dem":260,
    "gn:feature_class":"P",
    "gn:feature_code":"PPL",
    "gn:name":"Chimuco",
    "gn:population":0,
    "gn:timezone":"Africa/Luanda",
    "iso:country":"AO",
    "wof:name":"Chimuco",
    "wof:placetype":"locality"
},
  "geometry": {"coordinates":[13.52472,-12.55194],"type":"Point"}
}